{
  "type": "Feature",
  "properties": {
    "gn:admin1_code":"21.0",
    "gn:admin2_code":"381.0",
    "gn:asciiname":"Berg",
    "gn:country_code":"SE",
    "gn:dem":31,
    "gn:feature_class":"P",
    "gn:feature_code":"PPL",
    "gn:name":"Berg",
    "gn:population":0,
    "gn:timezone":"Europe/Stockholm",
    "iso:country":"SE",
    "wof:name":"Berg",
    "wof:placetype":"locality"
},
  "geometry": {"coordinates":[17.15,59.55],"type":"Point"}
}