{
  "type": "Feature",
  "properties": {
    "iso:country":"SE",
    "name:swe_x_preferred":[
        "H\u00f6gsbotorp"
    ],
    "wof:name":"Hogsbotorp",
    "wof:placetype":"neighbourhood"
},
  "geometry": {"coordinates":[11.92985979986782,57.67154719750685],"type":"Point"}
}