{
  "type": "Feature",
  "properties": {
    "gn:admin1_code":"16.0",
    "gn:admin2_code":"583.0",
    "gn:asciiname":"Hycklinge",
    "gn:country_code":"SE",
    "gn:dem":94,
    "gn:feature_class":"P",
    "gn:feature_code":"PPL",
    "gn:name":"Hycklinge",
    "gn:population":0,
    "gn:timezone":"Europe/Stockholm",
    "iso:country":"SE",
    "wof:name":"Hycklinge",
    "wof:placetype":"locality"
},
  "geometry": {"coordinates":[15.21667,58.48333],"type":"Point"}
}