{
  "type": "Feature",
  "properties": {
    "gn:admin1_code":"22.0",
    "gn:admin2_code":"1785.0",
    "gn:asciiname":"Rolfsbol",
    "gn:country_code":"SE",
    "gn:dem":102,
    "gn:feature_class":"P",
    "gn:feature_code":"PPL",
    "gn:name":"Rolfsbol",
    "gn:population":0,
    "gn:timezone":"Europe/Stockholm",
    "iso:country":"SE",
    "wof:name":"Rolfsbol",
    "wof:placetype":"locality"
},
  "geometry": {"coordinates":[12.75,59.28333000000001],"type":"Point"}
}