{
  "type": "Feature",
  "properties": {
    "gn:gn_country":"SE",
    "gn:gn_fcode":"PPL",
    "gn:gn_pop":0,
    "iso:country":"SE",
    "name:dan_x_preferred":[
        "Garnan\u00e4s"
    ],
    "name:deu_x_preferred":[
        "Garnan\u00e4s"
    ],
    "name:eng_x_preferred":[
        "Garnan\u00e4s"
    ],
    "name:fra_x_preferred":[
        "Garnan\u00e4s"
    ],
    "name:nds_x_preferred":[
        "Garnan\u00e4s"
    ],
    "name:nld_x_preferred":[
        "Garnan\u00e4s"
    ],
    "name:nno_x_preferred":[
        "Garnan\u00e4s"
    ],
    "name:nob_x_preferred":[
        "Garnan\u00e4s"
    ],
    "name:swe_x_preferred":[
        "Garnan\u00e4s"
    ],
    "qs_pg:aaroncc":"SE",
    "qs_pg:gn_country":"SE",
    "qs_pg:gn_fcode":"PPL",
    "qs_pg:gn_pop":0,
    "qs_pg:name":"Garnan\u00e4s",
    "qs_pg:name_adm0":"Sverige",
    "qs_pg:name_adm1":"Blekinge L\u00e4n",
    "qs_pg:photos":1042,
    "qs_pg:photos_1k":211,
    "qs_pg:photos_9k":5,
    "qs_pg:photos_9r":7,
    "qs_pg:photos_all":1042,
    "qs_pg:photos_sr":11,
    "qs_pg:pop_sr":0,
    "qs_pg:qs_pg_placetype":"locality",
    "qs_pg:qs_pg_placetype_gp":"Town",
    "qs_pg:woe_adm0":23424954,
    "woe:adm0_id":23424954,
    "woe:name_adm0":"Sverige",
    "woe:name_adm1":"Blekinge L\u00e4n",
    "woe:placetype":"Town",
    "wof:name":"Garnan\u00e4s",
    "wof:placetype":"locality"
},
  "geometry": {"coordinates":[15.08333,56.15833],"type":"Point"}
}