{
  "type": "Feature",
  "properties": {
    "gn:admin1_code":"23.0",
    "gn:admin2_code":"2401.0",
    "gn:asciiname":"Tobole",
    "gn:country_code":"SE",
    "gn:dem":49,
    "gn:feature_class":"P",
    "gn:feature_code":"PPL",
    "gn:name":"Tob\u00f6le",
    "gn:population":0,
    "gn:timezone":"Europe/Stockholm",
    "iso:country":"SE",
    "name:nor_x_preferred":[
        "Tob\u00f6le"
    ],
    "name:nor_x_variant":[
        "Tob\u00f8le"
    ],
    "wof:name":"Tobole",
    "wof:placetype":"locality"
},
  "geometry": {"coordinates":[19.26667,63.63333000000001],"type":"Point"}
}