{
  "type": "Feature",
  "properties": {
    "gn:admin1_code":"22.0",
    "gn:admin2_code":"1761.0",
    "gn:asciiname":"Ostra Hovlanda",
    "gn:country_code":"SE",
    "gn:dem":56,
    "gn:feature_class":"P",
    "gn:feature_code":"PPL",
    "gn:name":"\u00d6stra Hovlanda",
    "gn:population":0,
    "gn:timezone":"Europe/Stockholm",
    "iso:country":"SE",
    "name:nor_x_preferred":[
        "\u00d6stra Hovlanda"
    ],
    "name:nor_x_variant":[
        "\u00d8stra Hovlanda"
    ],
    "name:und_x_variant":[
        "\u00d6stra Hovlanda"
    ],
    "wof:name":"Ostra Hovlanda",
    "wof:placetype":"locality"
},
  "geometry": {"coordinates":[13.53333,59.31667],"type":"Point"}
}