{
  "type": "Feature",
  "properties": {
    "gn:admin1_code":"22.0",
    "gn:admin2_code":"1785.0",
    "gn:asciiname":"Esbjorbyn",
    "gn:cc2":"SE",
    "gn:country_code":"SE",
    "gn:dem":202,
    "gn:feature_class":"P",
    "gn:feature_code":"PPL",
    "gn:name":"Esbj\u00f6rbyn",
    "gn:population":0,
    "gn:timezone":"Europe/Stockholm",
    "iso:country":"SE",
    "name:nor_x_preferred":[
        "Esbj\u00f6rbyn"
    ],
    "name:nor_x_variant":[
        "Esbj\u00f8rbyn"
    ],
    "name:und_x_variant":[
        "Essbj\u00f6rbyn",
        "Esbj\u00e4rbyn"
    ],
    "wof:name":"Esbjorbyn",
    "wof:placetype":"locality"
},
  "geometry": {"coordinates":[12.55,59.26667],"type":"Point"}
}