{
  "type": "Feature",
  "properties": {
    "gn:admin1_code":"23.0",
    "gn:admin2_code":"2482.0",
    "gn:asciiname":"Storbrannan",
    "gn:cc2":"SE",
    "gn:country_code":"SE",
    "gn:dem":164,
    "gn:feature_class":"P",
    "gn:feature_code":"PPL",
    "gn:name":"Storbr\u00e4nnan",
    "gn:population":0,
    "gn:timezone":"Europe/Stockholm",
    "iso:country":"SE",
    "name:und_x_variant":[
        "Storbr\u00e4nna",
        "Storbr\u00e4nnan"
    ],
    "wof:name":"Storbrannan",
    "wof:placetype":"locality"
},
  "geometry": {"coordinates":[20.76667,65.06667],"type":"Point"}
}