{
  "type": "Feature",
  "properties": {
    "gn:admin1_code":"3.0",
    "gn:asciiname":"Maludden",
    "gn:country_code":"SE",
    "gn:dem":5,
    "gn:feature_class":"P",
    "gn:feature_code":"PPL",
    "gn:name":"Maludden",
    "gn:population":0,
    "gn:timezone":"Europe/Stockholm",
    "iso:country":"SE",
    "wof:name":"Maludden",
    "wof:placetype":"locality"
},
  "geometry": {"coordinates":[17.18333,61.71666999999999],"type":"Point"}
}