{
  "type": "Feature",
  "properties": {
    "gn:admin1_code":"8.0",
    "gn:admin2_code":"685.0",
    "gn:asciiname":"Rosas",
    "gn:country_code":"SE",
    "gn:dem":249,
    "gn:feature_class":"P",
    "gn:feature_code":"PPL",
    "gn:name":"R\u00f6s\u00e5s",
    "gn:population":0,
    "gn:timezone":"Europe/Stockholm",
    "iso:country":"SE",
    "name:nor_x_preferred":[
        "R\u00f6s\u00e5s"
    ],
    "name:nor_x_variant":[
        "R\u00f8s\u00e5s"
    ],
    "name:und_x_variant":[
        "R\u00f6s\u00e5s"
    ],
    "wof:name":"Rosas",
    "wof:placetype":"locality"
},
  "geometry": {"coordinates":[14.95,57.26667],"type":"Point"}
}