{
  "type": "Feature",
  "properties": {
    "gn:admin1_code":"23.0",
    "gn:admin2_code":"2482.0",
    "gn:asciiname":"Brattjarn",
    "gn:country_code":"SE",
    "gn:dem":80,
    "gn:feature_class":"P",
    "gn:feature_code":"PPL",
    "gn:name":"Brattj\u00e4rn",
    "gn:population":0,
    "gn:timezone":"Europe/Stockholm",
    "iso:country":"SE",
    "wof:name":"Brattjarn",
    "wof:placetype":"locality"
},
  "geometry": {"coordinates":[21.16667,64.51666999999999],"type":"Point"}
}