{
  "type": "Feature",
  "properties": {
    "gn:admin1_code":"7.0",
    "gn:admin2_code":"2326.0",
    "gn:asciiname":"Stabergsvallen",
    "gn:country_code":"SE",
    "gn:dem":455,
    "gn:feature_class":"P",
    "gn:feature_code":"PPL",
    "gn:name":"Stabergsvallen",
    "gn:population":0,
    "gn:timezone":"Europe/Stockholm",
    "iso:country":"SE",
    "wof:name":"Stabergsvallen",
    "wof:placetype":"locality"
},
  "geometry": {"coordinates":[14.28333,62.48333],"type":"Point"}
}