{
  "type": "Feature",
  "properties": {
    "gn:admin1_code":"14.0",
    "gn:admin2_code":"2580.0",
    "gn:asciiname":"Bjuranas",
    "gn:country_code":"SE",
    "gn:dem":54,
    "gn:feature_class":"P",
    "gn:feature_code":"PPL",
    "gn:name":"Bjur\u00e5n\u00e4s",
    "gn:population":0,
    "gn:timezone":"Europe/Stockholm",
    "iso:country":"SE",
    "wof:name":"Bjuranas",
    "wof:placetype":"locality"
},
  "geometry": {"coordinates":[22.16667,66.05],"type":"Point"}
}