{
  "type": "Feature",
  "properties": {
    "gn:admin1_code":"28.0",
    "gn:admin2_code":"1490.0",
    "gn:asciiname":"Hena",
    "gn:country_code":"SE",
    "gn:dem":121,
    "gn:feature_class":"P",
    "gn:feature_code":"PPL",
    "gn:name":"Hen\u00e5",
    "gn:population":0,
    "gn:timezone":"Europe/Stockholm",
    "iso:country":"SE",
    "name:deu_x_preferred":[
        "Hena"
    ],
    "wof:name":"Hena",
    "wof:placetype":"locality"
},
  "geometry": {"coordinates":[12.61667,57.75],"type":"Point"}
}