{
  "type": "Feature",
  "properties": {
    "gn:admin1_code":"15.0",
    "gn:admin2_code":"1863.0",
    "gn:asciiname":"Jonshyttan",
    "gn:country_code":"SE",
    "gn:dem":238,
    "gn:feature_class":"P",
    "gn:feature_code":"PPL",
    "gn:name":"J\u00f6nshyttan",
    "gn:population":0,
    "gn:timezone":"Europe/Stockholm",
    "iso:country":"SE",
    "name:nor_x_preferred":[
        "J\u00f6nshyttan"
    ],
    "name:nor_x_variant":[
        "J\u00f8nshyttan"
    ],
    "wof:name":"Jonshyttan",
    "wof:placetype":"locality"
},
  "geometry": {"coordinates":[14.66667,59.81667],"type":"Point"}
}