{
  "type": "Feature",
  "properties": {
    "gn:admin1_code":"9.0",
    "gn:admin2_code":"882.0",
    "gn:asciiname":"Asjogle",
    "gn:cc2":"SE",
    "gn:country_code":"SE",
    "gn:dem":116,
    "gn:feature_class":"P",
    "gn:feature_code":"PPL",
    "gn:name":"\u00c5sj\u00f6gle",
    "gn:population":0,
    "gn:timezone":"Europe/Stockholm",
    "iso:country":"SE",
    "name:nor_x_preferred":[
        "\u00c5sj\u00f6gle"
    ],
    "name:nor_x_variant":[
        "\u00c5sj\u00f8gle"
    ],
    "name:und_x_variant":[
        "\u00c5sk\u00f6gle"
    ],
    "wof:name":"Asjogle",
    "wof:placetype":"locality"
},
  "geometry": {"coordinates":[16.03333,57.41667],"type":"Point"}
}