{
  "type": "Feature",
  "properties": {
    "gn:admin1_code":"28.0",
    "gn:admin2_code":"1486.0",
    "gn:asciiname":"Skar",
    "gn:country_code":"SE",
    "gn:dem":4,
    "gn:feature_class":"P",
    "gn:feature_code":"PPL",
    "gn:name":"Sk\u00e4r",
    "gn:population":0,
    "gn:timezone":"Europe/Stockholm",
    "iso:country":"SE",
    "name:nor_x_preferred":[
        "Skar"
    ],
    "wof:name":"Skar",
    "wof:placetype":"locality"
},
  "geometry": {"coordinates":[11.21667,58.88889],"type":"Point"}
}