{
  "type": "Feature",
  "properties": {
    "gn:gn_country":"SE",
    "gn:gn_fcode":"PPL",
    "gn:gn_pop":0,
    "iso:country":"SE",
    "name:dan_x_preferred":[
        "Dalkarlsberg"
    ],
    "name:dut_x_preferred":[
        "Dalkarlsberg"
    ],
    "name:eng_x_preferred":[
        "Dalkarlsberg"
    ],
    "name:fre_x_preferred":[
        "Dalkarlsberg"
    ],
    "name:ger_x_preferred":[
        "Dalkarlsberg"
    ],
    "name:nds_x_preferred":[
        "Dalkarlsberg"
    ],
    "name:nno_x_preferred":[
        "Dalkarlsberg"
    ],
    "name:nob_x_preferred":[
        "Dalkarlsberg"
    ],
    "name:swe_x_preferred":[
        "Dalkarlsberg"
    ],
    "qs_pg:aaroncc":"SE",
    "qs_pg:gn_country":"SE",
    "qs_pg:gn_fcode":"PPL",
    "qs_pg:gn_pop":0,
    "qs_pg:name":"Dalkarlsberg",
    "qs_pg:name_adm0":"Sverige",
    "qs_pg:name_adm1":"\u00d6rebro L\u00e4n",
    "qs_pg:photos":22,
    "qs_pg:photos_1k":4,
    "qs_pg:photos_9k":1,
    "qs_pg:photos_9r":1,
    "qs_pg:photos_all":22,
    "qs_pg:photos_sr":1,
    "qs_pg:pop_sr":0,
    "qs_pg:qs_pg_placetype":"locality",
    "qs_pg:qs_pg_placetype_gp":"Town",
    "qs_pg:woe_adm0":23424954,
    "woe:adm0_id":23424954,
    "woe:name_adm0":"Sverige",
    "woe:name_adm1":"\u00d6rebro L\u00e4n",
    "woe:placetype":"Town",
    "wof:name":"Dalkarlsberg",
    "wof:placetype":"locality"
},
  "geometry": {"coordinates":[14.85,59.43333],"type":"Point"}
}