{
  "type": "Feature",
  "properties": {
    "gn:admin1_code":"27.0",
    "gn:admin2_code":"1290.0",
    "gn:asciiname":"Hovby",
    "gn:country_code":"SE",
    "gn:dem":4,
    "gn:feature_class":"P",
    "gn:feature_code":"PPL",
    "gn:name":"Hovby",
    "gn:population":0,
    "gn:timezone":"Europe/Stockholm",
    "iso:country":"SE",
    "wof:name":"Hovby",
    "wof:placetype":"locality"
},
  "geometry": {"coordinates":[14.18333,55.96666999999999],"type":"Point"}
}