{
  "type": "Feature",
  "properties": {
    "gn:admin1_code":"22.0",
    "gn:admin2_code":"1785.0",
    "gn:asciiname":"Sodra Torp",
    "gn:country_code":"SE",
    "gn:dem":58,
    "gn:feature_class":"P",
    "gn:feature_code":"PPL",
    "gn:name":"S\u00f6dra Torp",
    "gn:population":0,
    "gn:timezone":"Europe/Stockholm",
    "iso:country":"SE",
    "name:nor_x_preferred":[
        "S\u00f6dra Torp"
    ],
    "name:nor_x_variant":[
        "S\u00f8dra Torp"
    ],
    "name:und_x_variant":[
        "S\u00f6dra Torp"
    ],
    "wof:name":"Sodra Torp",
    "wof:placetype":"locality"
},
  "geometry": {"coordinates":[13.06667,59.05],"type":"Point"}
}