{
  "type": "Feature",
  "properties": {
    "gn:admin1_code":"28.0",
    "gn:admin2_code":"1444.0",
    "gn:asciiname":"Tengenestorp",
    "gn:cc2":"SE",
    "gn:country_code":"SE",
    "gn:dem":58,
    "gn:feature_class":"P",
    "gn:feature_code":"PPL",
    "gn:name":"Tengenestorp",
    "gn:population":0,
    "gn:timezone":"Europe/Stockholm",
    "iso:country":"SE",
    "name:und_x_variant":[
        "Tengenedstorp",
        "Tengenestorp"
    ],
    "wof:name":"Tengenestorp",
    "wof:placetype":"locality"
},
  "geometry": {"coordinates":[12.65,58.31667],"type":"Point"}
}