{
  "type": "Feature",
  "properties": {
    "gn:admin1_code":"6.0",
    "gn:admin2_code":"1382.0",
    "gn:asciiname":"Haljared",
    "gn:country_code":"SE",
    "gn:dem":156,
    "gn:feature_class":"P",
    "gn:feature_code":"PPL",
    "gn:name":"H\u00e4ljared",
    "gn:population":0,
    "gn:timezone":"Europe/Stockholm",
    "iso:country":"SE",
    "wof:name":"Haljared",
    "wof:placetype":"locality"
},
  "geometry": {"coordinates":[12.86667,57.13333000000001],"type":"Point"}
}