{
  "type": "Feature",
  "properties": {
    "gn:admin1_code":"22.0",
    "gn:admin2_code":"1766.0",
    "gn:asciiname":"Norra Nas",
    "gn:country_code":"SE",
    "gn:dem":151,
    "gn:feature_class":"P",
    "gn:feature_code":"PPL",
    "gn:name":"Norra N\u00e4s",
    "gn:population":0,
    "gn:timezone":"Europe/Stockholm",
    "iso:country":"SE",
    "wof:name":"Norra Nas",
    "wof:placetype":"locality"
},
  "geometry": {"coordinates":[13.11667,59.93333000000001],"type":"Point"}
}