{
  "type": "Feature",
  "properties": {
    "gn:country":"SE",
    "gn:fcode":"PPL",
    "gn:population":892,
    "iso:country":"SE",
    "name:fra_x_preferred":[
        "Sj\u00f6vik"
    ],
    "name:ita_x_preferred":[
        "Sj\u00f6vik"
    ],
    "name:nld_x_preferred":[
        "Sj\u00f6vik"
    ],
    "name:nno_x_preferred":[
        "Sj\u00f6vik"
    ],
    "name:nor_x_preferred":[
        "Sj\u00f8vik"
    ],
    "name:nor_x_variant":[
        "Sj\u00f6vik"
    ],
    "name:sco_x_preferred":[
        "Sj\u00f6vik"
    ],
    "name:swe_x_preferred":[
        "Sj\u00f6vik"
    ],
    "qs_pg:aaroncc":"SE",
    "qs_pg:gn_country":"SE",
    "qs_pg:gn_fcode":"PPL",
    "qs_pg:gn_pop":892,
    "qs_pg:name":"Sj\u00f6vik",
    "qs_pg:name_adm0":"Sverige",
    "qs_pg:name_adm1":"Dalarnas L\u00e4n",
    "qs_pg:photos_9r":0,
    "qs_pg:photos_sr":0,
    "qs_pg:pop_sr":2,
    "qs_pg:qs_pg_placetype":"locality",
    "qs_pg:qs_pg_placetype_gp":"Town",
    "qs_pg:woe_adm0":23424954,
    "woe:adm0_id":23424954,
    "woe:name_adm0":"Sverige",
    "woe:name_adm1":"Dalarnas L\u00e4n",
    "woe:placetype":"Town",
    "wof:name":"Sj\u00f6vik",
    "wof:placetype":"locality",
    "wof:population":892
},
  "geometry": {"coordinates":[16.31667,60.15],"type":"Point"}
}