{
  "type": "Feature",
  "properties": {
    "gn:admin1_code":"10.0",
    "gn:admin2_code":"2023.0",
    "gn:asciiname":"Famtberget",
    "gn:country_code":"SE",
    "gn:dem":460,
    "gn:feature_class":"P",
    "gn:feature_code":"PPL",
    "gn:name":"F\u00e4mtberget",
    "gn:population":0,
    "gn:timezone":"Europe/Stockholm",
    "iso:country":"SE",
    "wof:name":"Famtberget",
    "wof:placetype":"locality"
},
  "geometry": {"coordinates":[13.23306,60.78306],"type":"Point"}
}