{
  "type": "Feature",
  "properties": {
    "gn:gn_country":"SE",
    "gn:gn_fcode":"PPL",
    "gn:gn_pop":492,
    "gn:population":435,
    "iso:country":"SE",
    "name:ceb_x_preferred":[
        "K\u00e4larne"
    ],
    "name:eng_x_preferred":[
        "K\u00e4larne"
    ],
    "name:ita_x_preferred":[
        "K\u00e4larne"
    ],
    "name:nan_x_preferred":[
        "K\u00e4larne"
    ],
    "name:nld_x_preferred":[
        "K\u00e4larne"
    ],
    "name:nno_x_preferred":[
        "K\u00e4larne"
    ],
    "name:nob_x_preferred":[
        "K\u00e4larne"
    ],
    "name:swe_x_preferred":[
        "K\u00e4larne"
    ],
    "qs_pg:aaroncc":"SE",
    "qs_pg:gn_country":"SE",
    "qs_pg:gn_fcode":"PPL",
    "qs_pg:gn_pop":492,
    "qs_pg:name":"K\u00e4larne",
    "qs_pg:name_adm0":"Sverige",
    "qs_pg:name_adm1":"J\u00e4mtlands L\u00e4n",
    "qs_pg:photos_9k":1,
    "qs_pg:photos_9r":1,
    "qs_pg:photos_all":1,
    "qs_pg:photos_sr":0,
    "qs_pg:pop_sr":2,
    "qs_pg:qs_pg_placetype":"locality",
    "qs_pg:qs_pg_placetype_gp":"Town",
    "qs_pg:woe_adm0":23424954,
    "woe:adm0_id":23424954,
    "woe:name_adm0":"Sverige",
    "woe:name_adm1":"J\u00e4mtlands L\u00e4n",
    "woe:placetype":"Town",
    "wof:name":"K\u00e4larne",
    "wof:placetype":"locality",
    "wof:population":435
},
  "geometry": {"coordinates":[16.08333,62.98333],"type":"Point"}
}