{
  "type": "Feature",
  "properties": {
    "gn:admin1_code":"27.0",
    "gn:asciiname":"Koarp",
    "gn:country_code":"SE",
    "gn:dem":185,
    "gn:feature_class":"P",
    "gn:feature_code":"PPL",
    "gn:name":"Koarp",
    "gn:population":0,
    "gn:timezone":"Europe/Stockholm",
    "iso:country":"SE",
    "wof:name":"Koarp",
    "wof:placetype":"locality"
},
  "geometry": {"coordinates":[13.11667,56.35],"type":"Point"}
}