{
  "type": "Feature",
  "properties": {
    "gn:admin1_code":"16.0",
    "gn:admin2_code":"582.0",
    "gn:asciiname":"Yttergarda",
    "gn:country_code":"SE",
    "gn:dem":10,
    "gn:feature_class":"P",
    "gn:feature_code":"PPL",
    "gn:name":"Ytterg\u00e5rda",
    "gn:population":0,
    "gn:timezone":"Europe/Stockholm",
    "iso:country":"SE",
    "wof:name":"Yttergarda",
    "wof:placetype":"locality"
},
  "geometry": {"coordinates":[16.75832999999999,58.35],"type":"Point"}
}