{
  "type": "Feature",
  "properties": {
    "gn:admin1_code":"27.0",
    "gn:admin2_code":"1282.0",
    "gn:asciiname":"Lilla Horstad",
    "gn:country_code":"SE",
    "gn:dem":12,
    "gn:feature_class":"P",
    "gn:feature_code":"PPL",
    "gn:name":"Lilla H\u00f6rstad",
    "gn:population":0,
    "gn:timezone":"Europe/Stockholm",
    "iso:country":"SE",
    "name:nor_x_preferred":[
        "Lilla H\u00f6rstad"
    ],
    "name:nor_x_variant":[
        "Lilla H\u00f8rstad"
    ],
    "name:und_x_variant":[
        "Lilla H\u00f6rstad"
    ],
    "wof:name":"Lilla Horstad",
    "wof:placetype":"locality"
},
  "geometry": {"coordinates":[12.95,55.86666999999999],"type":"Point"}
}