{
  "type": "Feature",
  "properties": {
    "gn:admin1_code":"23.0",
    "gn:admin2_code":"2480.0",
    "gn:asciiname":"Osterbacka",
    "gn:country_code":"SE",
    "gn:dem":162,
    "gn:feature_class":"P",
    "gn:feature_code":"PPL",
    "gn:name":"\u00d6sterbacka",
    "gn:population":0,
    "gn:timezone":"Europe/Stockholm",
    "iso:country":"SE",
    "name:nor_x_preferred":[
        "\u00d6sterbacka"
    ],
    "name:nor_x_variant":[
        "\u00d8sterbacka"
    ],
    "name:und_x_variant":[
        "\u00d6sterbacka"
    ],
    "wof:name":"Osterbacka",
    "wof:placetype":"locality"
},
  "geometry": {"coordinates":[20.08333,64.08333],"type":"Point"}
}