{
  "type": "Feature",
  "properties": {
    "gn:admin1_code":"18.0",
    "gn:admin2_code":"428.0",
    "gn:asciiname":"Baggetorp",
    "gn:country_code":"SE",
    "gn:dem":44,
    "gn:feature_class":"P",
    "gn:feature_code":"PPL",
    "gn:name":"Baggetorp",
    "gn:population":490,
    "gn:timezone":"Europe/Stockholm",
    "iso:country":"SE",
    "wof:name":"Baggetorp",
    "wof:placetype":"locality",
    "wof:population":490
},
  "geometry": {"coordinates":[16.0697,59.00899],"type":"Point"}
}