{
  "type": "Feature",
  "properties": {
    "gn:admin1_code":"10.0",
    "gn:admin2_code":"2080.0",
    "gn:admin3_code":"208011.0",
    "gn:admin4_code":"2342.0",
    "gn:asciiname":"Soerskog",
    "gn:country_code":"SE",
    "gn:dem":401,
    "gn:elevation":"401.0",
    "gn:feature_class":"P",
    "gn:feature_code":"PPL",
    "gn:name":"S\u00f6rskog",
    "gn:population":30,
    "gn:timezone":"Europe/Stockholm",
    "iso:country":"SE",
    "name:eng_x_preferred":[
        "Sorskog"
    ],
    "name:swe_x_historical":[
        "S\u00f6derskog"
    ],
    "name:swe_x_preferred":[
        "S\u00f6rskog"
    ],
    "name:swe_x_variant":[
        "S\u00f6derskog"
    ],
    "wof:name":"Soerskog",
    "wof:placetype":"locality",
    "wof:population":30
},
  "geometry": {"coordinates":[15.37657,60.81805],"type":"Point"}
}