{
  "type": "Feature",
  "properties": {
    "gn:admin1_code":"22.0",
    "gn:admin2_code":"1715.0",
    "gn:asciiname":"Torestad",
    "gn:country_code":"SE",
    "gn:dem":170,
    "gn:feature_class":"P",
    "gn:feature_code":"PPL",
    "gn:name":"Torestad",
    "gn:population":0,
    "gn:timezone":"Europe/Stockholm",
    "iso:country":"SE",
    "wof:name":"Torestad",
    "wof:placetype":"locality"
},
  "geometry": {"coordinates":[13.13333,59.65],"type":"Point"}
}