{
  "type": "Feature",
  "properties": {
    "gn:admin1_code":"15.0",
    "gn:admin2_code":"1862.0",
    "gn:asciiname":"Grasmossen",
    "gn:country_code":"SE",
    "gn:dem":123,
    "gn:feature_class":"P",
    "gn:feature_code":"PPL",
    "gn:name":"Gr\u00e4smossen",
    "gn:population":0,
    "gn:timezone":"Europe/Stockholm",
    "iso:country":"SE",
    "wof:name":"Grasmossen",
    "wof:placetype":"locality"
},
  "geometry": {"coordinates":[14.36667,59.26667],"type":"Point"}
}