{
  "type": "Feature",
  "properties": {
    "gn:admin1_code":"16.0",
    "gn:admin2_code":"580.0",
    "gn:asciiname":"Tobo",
    "gn:country_code":"SE",
    "gn:dem":131,
    "gn:feature_class":"P",
    "gn:feature_code":"PPL",
    "gn:name":"Tobo",
    "gn:population":0,
    "gn:timezone":"Europe/Stockholm",
    "iso:country":"SE",
    "name:ceb_x_preferred":[
        "Tobo"
    ],
    "name:epo_x_preferred":[
        "Tobo"
    ],
    "name:ita_x_preferred":[
        "Tobo"
    ],
    "name:nld_x_preferred":[
        "Tobo"
    ],
    "name:nno_x_preferred":[
        "Tobo"
    ],
    "name:nor_x_preferred":[
        "Tobo"
    ],
    "name:swe_x_preferred":[
        "Tobo"
    ],
    "wof:name":"Tobo",
    "wof:placetype":"locality"
},
  "geometry": {"coordinates":[15.55,58.25],"type":"Point"}
}