{
  "type": "Feature",
  "properties": {
    "gn:admin1_code":"10.0",
    "gn:admin2_code":"2029.0",
    "gn:asciiname":"Sagen",
    "gn:country_code":"SE",
    "gn:dem":172,
    "gn:feature_class":"P",
    "gn:feature_code":"PPL",
    "gn:name":"S\u00e5gen",
    "gn:population":0,
    "gn:timezone":"Europe/Stockholm",
    "iso:country":"SE",
    "wof:name":"Sagen",
    "wof:placetype":"locality"
},
  "geometry": {"coordinates":[15.26667,60.71666999999999],"type":"Point"}
}