{
  "type": "Feature",
  "properties": {
    "gn:admin1_code":"14.0",
    "gn:admin2_code":"2582.0",
    "gn:asciiname":"Vibbyn",
    "gn:cc2":"SE",
    "gn:country_code":"SE",
    "gn:dem":6,
    "gn:feature_class":"P",
    "gn:feature_code":"PPL",
    "gn:name":"Vibbyn",
    "gn:population":0,
    "gn:timezone":"Europe/Stockholm",
    "iso:country":"SE",
    "name:und_x_variant":[
        "Vibyn",
        "Vibbyn"
    ],
    "wof:name":"Vibbyn",
    "wof:placetype":"locality"
},
  "geometry": {"coordinates":[21.93333,65.83333],"type":"Point"}
}