{
  "type": "Feature",
  "properties": {
    "gn:admin1_code":"7.0",
    "gn:admin2_code":"2380.0",
    "gn:asciiname":"Ytterasen",
    "gn:cc2":"SE",
    "gn:country_code":"SE",
    "gn:dem":319,
    "gn:feature_class":"P",
    "gn:feature_code":"PPL",
    "gn:name":"Ytter\u00e5sen",
    "gn:population":0,
    "gn:timezone":"Europe/Stockholm",
    "iso:country":"SE",
    "name:und_x_variant":[
        "\u00c5sen",
        "Ytter\u00e5sen"
    ],
    "wof:name":"Ytterasen",
    "wof:placetype":"locality"
},
  "geometry": {"coordinates":[14.95,63.26667],"type":"Point"}
}