{
  "type": "Feature",
  "properties": {
    "gn:gn_country":"SE",
    "gn:gn_fcode":"PPL",
    "gn:gn_pop":917,
    "gn:population":917,
    "iso:country":"SE",
    "name:bul_x_preferred":[
        "\u042e\u043d\u0433\u0430\u0432\u0435\u0440\u043a"
    ],
    "name:dan_x_preferred":[
        "Ljungaverk"
    ],
    "name:deu_x_preferred":[
        "Ljungaverk"
    ],
    "name:eng_x_preferred":[
        "Ljungaverk"
    ],
    "name:fao_x_preferred":[
        "Ljungaverk"
    ],
    "name:fra_x_preferred":[
        "Ljungaverk"
    ],
    "name:isl_x_preferred":[
        "Ljungaverk"
    ],
    "name:nan_x_preferred":[
        "Ljungaverk"
    ],
    "name:nld_x_preferred":[
        "Ljungaverk"
    ],
    "name:nno_x_preferred":[
        "Ljungaverk"
    ],
    "name:nob_x_preferred":[
        "Ljungaverk"
    ],
    "name:pol_x_preferred":[
        "Ljungaverk"
    ],
    "name:swe_x_preferred":[
        "Ljungaverk"
    ],
    "qs_pg:aaroncc":"SE",
    "qs_pg:gn_country":"SE",
    "qs_pg:gn_fcode":"PPL",
    "qs_pg:gn_pop":917,
    "qs_pg:name":"Ljungaverk",
    "qs_pg:name_adm0":"Sverige",
    "qs_pg:name_adm1":"V\u00e4sternorrlands L\u00e4n",
    "qs_pg:photos":601,
    "qs_pg:photos_1k":122,
    "qs_pg:photos_9k":3,
    "qs_pg:photos_9r":5,
    "qs_pg:photos_all":601,
    "qs_pg:photos_sr":8,
    "qs_pg:pop_sr":2,
    "qs_pg:qs_pg_placetype":"locality",
    "qs_pg:qs_pg_placetype_gp":"Town",
    "qs_pg:woe_adm0":23424954,
    "woe:adm0_id":23424954,
    "woe:name_adm0":"Sverige",
    "woe:name_adm1":"V\u00e4sternorrlands L\u00e4n",
    "woe:placetype":"Town",
    "wof:name":"Ljungaverk",
    "wof:placetype":"locality",
    "wof:population":917
},
  "geometry": {"coordinates":[16.01667,62.48333],"type":"Point"}
}