{
  "type": "Feature",
  "properties": {
    "gn:admin1_code":"7.0",
    "gn:admin2_code":"2380.0",
    "gn:asciiname":"Fagerland",
    "gn:cc2":"SE",
    "gn:country_code":"SE",
    "gn:dem":426,
    "gn:feature_class":"P",
    "gn:feature_code":"PPL",
    "gn:name":"Fagerland",
    "gn:population":0,
    "gn:timezone":"Europe/Stockholm",
    "iso:country":"SE",
    "name:und_x_variant":[
        "Fagerlandsvallen",
        "Fagerland"
    ],
    "wof:name":"Fagerland",
    "wof:placetype":"locality"
},
  "geometry": {"coordinates":[15.18333,63.41667],"type":"Point"}
}