{
  "type": "Feature",
  "properties": {
    "gn:admin1_code":"10.0",
    "gn:admin2_code":"2080.0",
    "gn:asciiname":"Risholn",
    "gn:country_code":"SE",
    "gn:dem":148,
    "gn:feature_class":"P",
    "gn:feature_code":"PPL",
    "gn:name":"Risholn",
    "gn:population":0,
    "gn:timezone":"Europe/Stockholm",
    "iso:country":"SE",
    "wof:name":"Risholn",
    "wof:placetype":"locality"
},
  "geometry": {"coordinates":[15.75,60.61666999999999],"type":"Point"}
}