{
  "type": "Feature",
  "properties": {
    "gn:admin1_code":"14.0",
    "gn:admin2_code":"2523.0",
    "gn:asciiname":"Avvakko",
    "gn:cc2":"SE",
    "gn:country_code":"SE",
    "gn:dem":473,
    "gn:feature_class":"P",
    "gn:feature_code":"PPL",
    "gn:name":"Avvakko",
    "gn:population":0,
    "gn:timezone":"Europe/Stockholm",
    "iso:country":"SE",
    "name:und_x_variant":[
        "Auvakko",
        "Avvakko"
    ],
    "wof:name":"Avvakko",
    "wof:placetype":"locality"
},
  "geometry": {"coordinates":[20.96667,67.33333],"type":"Point"}
}