{
  "type": "Feature",
  "properties": {
    "gn:admin1_code":"14.0",
    "gn:admin2_code":"2514.0",
    "gn:asciiname":"Bjorkfors",
    "gn:country_code":"SE",
    "gn:dem":21,
    "gn:feature_class":"P",
    "gn:feature_code":"PPL",
    "gn:name":"Bj\u00f6rkfors",
    "gn:population":0,
    "gn:timezone":"Europe/Stockholm",
    "iso:country":"SE",
    "name:nor_x_preferred":[
        "Bj\u00f6rkfors"
    ],
    "name:nor_x_variant":[
        "Bj\u00f8rkfors"
    ],
    "wof:name":"Bjorkfors",
    "wof:placetype":"locality"
},
  "geometry": {"coordinates":[23.45,65.91667],"type":"Point"}
}