{
  "type": "Feature",
  "properties": {
    "gn:admin1_code":"22.0",
    "gn:admin2_code":"1766.0",
    "gn:asciiname":"Langjohanstorp",
    "gn:country_code":"SE",
    "gn:dem":356,
    "gn:feature_class":"P",
    "gn:feature_code":"PPL",
    "gn:name":"L\u00e5ngjohanstorp",
    "gn:population":0,
    "gn:timezone":"Europe/Stockholm",
    "iso:country":"SE",
    "wof:name":"Langjohanstorp",
    "wof:placetype":"locality"
},
  "geometry": {"coordinates":[12.85,59.83333],"type":"Point"}
}