{
  "type": "Feature",
  "properties": {
    "gn:admin1_code":"28.0",
    "gn:admin2_code":"1463.0",
    "gn:asciiname":"Gunnared",
    "gn:country_code":"SE",
    "gn:dem":61,
    "gn:feature_class":"P",
    "gn:feature_code":"PPL",
    "gn:name":"Gunnared",
    "gn:population":0,
    "gn:timezone":"Europe/Stockholm",
    "iso:country":"SE",
    "name:por_x_preferred":[
        "Gunnared"
    ],
    "wof:name":"Gunnared",
    "wof:placetype":"locality"
},
  "geometry": {"coordinates":[12.55,57.53333000000001],"type":"Point"}
}