{
  "type": "Feature",
  "properties": {
    "gn:admin1_code":"22.0",
    "gn:admin2_code":"1784.0",
    "gn:asciiname":"Braten",
    "gn:country_code":"SE",
    "gn:dem":111,
    "gn:feature_class":"P",
    "gn:feature_code":"PPL",
    "gn:name":"Br\u00e5ten",
    "gn:population":0,
    "gn:timezone":"Europe/Stockholm",
    "iso:country":"SE",
    "wof:name":"Braten",
    "wof:placetype":"locality"
},
  "geometry": {"coordinates":[12.95,59.68333000000001],"type":"Point"}
}