{
  "type": "Feature",
  "properties": {
    "gn:admin1_code":"26.0",
    "gn:admin2_code":"120.0",
    "gn:asciiname":"Baldersnaes",
    "gn:country_code":"SE",
    "gn:dem":26,
    "gn:feature_class":"P",
    "gn:feature_code":"PPL",
    "gn:name":"Baldersn\u00e4s",
    "gn:population":265,
    "gn:timezone":"Europe/Stockholm",
    "iso:country":"SE",
    "wof:name":"Baldersnaes",
    "wof:placetype":"locality",
    "wof:population":265
},
  "geometry": {"coordinates":[18.47917,59.22917],"type":"Point"}
}