{
  "type": "Feature",
  "properties": {
    "gn:admin1_code":"15.0",
    "gn:admin2_code":"1885.0",
    "gn:asciiname":"Kallernas",
    "gn:country_code":"SE",
    "gn:dem":84,
    "gn:feature_class":"P",
    "gn:feature_code":"PPL",
    "gn:name":"Kallern\u00e4s",
    "gn:population":0,
    "gn:timezone":"Europe/Stockholm",
    "iso:country":"SE",
    "wof:name":"Kallernas",
    "wof:placetype":"locality"
},
  "geometry": {"coordinates":[15.16667,59.68333000000001],"type":"Point"}
}