{
  "type": "Feature",
  "properties": {
    "gn:gn_country":"SE",
    "gn:gn_fcode":"PPL",
    "gn:gn_pop":335,
    "gn:population":291,
    "iso:country":"SE",
    "name:als_x_preferred":[
        "Berg"
    ],
    "name:cat_x_preferred":[
        "Berg"
    ],
    "name:ceb_x_preferred":[
        "Berg"
    ],
    "name:ces_x_preferred":[
        "Berg"
    ],
    "name:deu_x_preferred":[
        "Berg"
    ],
    "name:epo_x_preferred":[
        "Berg"
    ],
    "name:eus_x_preferred":[
        "Berg"
    ],
    "name:fin_x_preferred":[
        "Berg"
    ],
    "name:fra_x_preferred":[
        "Berg"
    ],
    "name:hun_x_preferred":[
        "Berg"
    ],
    "name:hye_x_preferred":[
        "\u0532\u0565\u0580\u0563"
    ],
    "name:ita_x_preferred":[
        "Berg"
    ],
    "name:jpn_x_preferred":[
        "\u30d9\u30eb\u30af"
    ],
    "name:kat_x_preferred":[
        "\u10d1\u10d4\u10e0\u10d2\u10d8"
    ],
    "name:kor_x_preferred":[
        "\ubca0\ub974\ud06c"
    ],
    "name:lim_x_preferred":[
        "Berg"
    ],
    "name:lmo_x_preferred":[
        "Berg"
    ],
    "name:nds_x_preferred":[
        "Berg"
    ],
    "name:nld_x_preferred":[
        "Berg"
    ],
    "name:nno_x_preferred":[
        "Berg"
    ],
    "name:nor_x_preferred":[
        "Berg"
    ],
    "name:pms_x_preferred":[
        "Berg"
    ],
    "name:pol_x_preferred":[
        "Berg"
    ],
    "name:por_x_preferred":[
        "Berg"
    ],
    "name:ron_x_preferred":[
        "Berg"
    ],
    "name:rus_x_preferred":[
        "\u0411\u0435\u0440\u0433"
    ],
    "name:slk_x_preferred":[
        "Berg"
    ],
    "name:spa_x_preferred":[
        "Berg"
    ],
    "name:srp_x_preferred":[
        "\u0411\u0435\u0440\u0433"
    ],
    "name:swe_x_preferred":[
        "Berg"
    ],
    "name:ukr_x_preferred":[
        "\u0411\u0435\u0440\u0433"
    ],
    "name:vol_x_preferred":[
        "Berg"
    ],
    "qs_pg:aaroncc":"SE",
    "qs_pg:gn_country":"SE",
    "qs_pg:gn_fcode":"PPL",
    "qs_pg:gn_pop":335,
    "qs_pg:name":"Berg",
    "qs_pg:name_adm0":"Sverige",
    "qs_pg:name_adm1":"\u00d6sterg\u00f6tlands L\u00e4n",
    "qs_pg:photos":24,
    "qs_pg:photos_1k":5,
    "qs_pg:photos_9k":1,
    "qs_pg:photos_9r":1,
    "qs_pg:photos_all":24,
    "qs_pg:photos_sr":1,
    "qs_pg:pop_sr":2,
    "qs_pg:qs_pg_placetype":"locality",
    "qs_pg:qs_pg_placetype_gp":"Town",
    "qs_pg:woe_adm0":23424954,
    "woe:adm0_id":23424954,
    "woe:name_adm0":"Sverige",
    "woe:name_adm1":"\u00d6sterg\u00f6tlands L\u00e4n",
    "woe:placetype":"Town",
    "wof:name":"Berg",
    "wof:placetype":"locality",
    "wof:population":291
},
  "geometry": {"coordinates":[16.03333,58.21667],"type":"Point"}
}