{
  "type": "Feature",
  "properties": {
    "gn:admin1_code":"2.0",
    "gn:admin2_code":"1080.0",
    "gn:asciiname":"Harstorp",
    "gn:country_code":"SE",
    "gn:dem":77,
    "gn:feature_class":"P",
    "gn:feature_code":"PPL",
    "gn:name":"Harstorp",
    "gn:population":0,
    "gn:timezone":"Europe/Stockholm",
    "iso:country":"SE",
    "wof:name":"Harstorp",
    "wof:placetype":"locality"
},
  "geometry": {"coordinates":[15.55,56.25],"type":"Point"}
}