{
  "type": "Feature",
  "properties": {
    "gn:gn_country":"SE",
    "gn:gn_fcode":"PPL",
    "gn:gn_pop":710,
    "gn:population":716,
    "iso:country":"SE",
    "name:dut_x_preferred":[
        "Fliseryd"
    ],
    "name:eng_x_preferred":[
        "Fliseryd"
    ],
    "name:ita_x_preferred":[
        "Fliseryd"
    ],
    "name:nan_x_preferred":[
        "Fliseryd"
    ],
    "name:nno_x_preferred":[
        "Fliseryd"
    ],
    "name:nob_x_preferred":[
        "Fliseryd"
    ],
    "name:swe_x_preferred":[
        "Fliseryd"
    ],
    "qs_pg:aaroncc":"SE",
    "qs_pg:gn_country":"SE",
    "qs_pg:gn_fcode":"PPL",
    "qs_pg:gn_pop":710,
    "qs_pg:name":"Fliseryd",
    "qs_pg:name_adm0":"Sverige",
    "qs_pg:name_adm1":"Kalmar L\u00e4n",
    "qs_pg:photos_9k":1,
    "qs_pg:photos_9r":1,
    "qs_pg:photos_all":1,
    "qs_pg:photos_sr":0,
    "qs_pg:pop_sr":2,
    "qs_pg:qs_pg_placetype":"locality",
    "qs_pg:qs_pg_placetype_gp":"Town",
    "qs_pg:woe_adm0":23424954,
    "woe:adm0_id":23424954,
    "woe:name_adm0":"Sverige",
    "woe:name_adm1":"Kalmar L\u00e4n",
    "woe:placetype":"Town",
    "wof:name":"Fliseryd",
    "wof:placetype":"locality",
    "wof:population":716
},
  "geometry": {"coordinates":[16.26667,57.13333],"type":"Point"}
}