{
  "type": "Feature",
  "properties": {
    "gn:admin1_code":"28.0",
    "gn:admin2_code":"1440.0",
    "gn:asciiname":"Sandaker",
    "gn:country_code":"SE",
    "gn:dem":50,
    "gn:feature_class":"P",
    "gn:feature_code":"PPL",
    "gn:name":"Sand\u00e5ker",
    "gn:population":0,
    "gn:timezone":"Europe/Stockholm",
    "iso:country":"SE",
    "wof:name":"Sandaker",
    "wof:placetype":"locality"
},
  "geometry": {"coordinates":[12.26667,58.03333000000001],"type":"Point"}
}