{
  "type": "Feature",
  "properties": {
    "gn:admin1_code":"2.0",
    "gn:admin2_code":"1080.0",
    "gn:asciiname":"Mocklo",
    "gn:country_code":"SE",
    "gn:dem":7,
    "gn:feature_class":"P",
    "gn:feature_code":"PPL",
    "gn:name":"M\u00f6ckl\u00f6",
    "gn:population":0,
    "gn:timezone":"Europe/Stockholm",
    "iso:country":"SE",
    "name:nor_x_preferred":[
        "M\u00f6ckl\u00f6"
    ],
    "name:nor_x_variant":[
        "M\u00f8ckl\u00f8"
    ],
    "name:und_x_variant":[
        "M\u00f6ckl\u00f6"
    ],
    "wof:name":"Mocklo",
    "wof:placetype":"locality"
},
  "geometry": {"coordinates":[15.75,56.15],"type":"Point"}
}