{
  "type": "Feature",
  "properties": {
    "gn:admin1_code":"25.0",
    "gn:admin2_code":"1983.0",
    "gn:asciiname":"Ava",
    "gn:country_code":"SE",
    "gn:dem":58,
    "gn:feature_class":"P",
    "gn:feature_code":"PPL",
    "gn:name":"\u00c5va",
    "gn:population":0,
    "gn:timezone":"Europe/Stockholm",
    "iso:country":"SE",
    "wof:name":"Ava",
    "wof:placetype":"locality"
},
  "geometry": {"coordinates":[16.05,59.61666999999999],"type":"Point"}
}