{
  "type": "Feature",
  "properties": {
    "gn:admin1_code":"22.0",
    "gn:admin2_code":"1765.0",
    "gn:asciiname":"Tenvik",
    "gn:country_code":"SE",
    "gn:dem":174,
    "gn:feature_class":"P",
    "gn:feature_code":"PPL",
    "gn:name":"Tenvik",
    "gn:population":0,
    "gn:timezone":"Europe/Stockholm",
    "iso:country":"SE",
    "name:ceb_x_preferred":[
        "Tenvik"
    ],
    "name:msa_x_preferred":[
        "Tenvik"
    ],
    "name:nor_x_preferred":[
        "Tenvik"
    ],
    "wof:name":"Tenvik",
    "wof:placetype":"locality"
},
  "geometry": {"coordinates":[12.23333,59.38333000000001],"type":"Point"}
}