{
  "type": "Feature",
  "properties": {
    "gn:admin1_code":"26.0",
    "gn:asciiname":"Kapellskar",
    "gn:country_code":"SE",
    "gn:dem":9,
    "gn:feature_class":"P",
    "gn:feature_code":"PPL",
    "gn:name":"Kapellsk\u00e4r",
    "gn:population":0,
    "gn:timezone":"Europe/Stockholm",
    "iso:country":"SE",
    "name:deu_x_preferred":[
        "Kapellsk\u00e4r"
    ],
    "name:est_x_preferred":[
        "Kapellsk\u00e4ri sadam"
    ],
    "name:fin_x_preferred":[
        "Kapellsk\u00e4rin satama"
    ],
    "name:fra_x_preferred":[
        "Kapellsk\u00e4r"
    ],
    "name:jpn_x_preferred":[
        "\u30ab\u30da\u30eb\u30b7\u30e3\u30fc"
    ],
    "name:nld_x_preferred":[
        "Kapellsk\u00e4r"
    ],
    "name:nor_x_preferred":[
        "Kapellsk\u00e4r"
    ],
    "name:swe_x_preferred":[
        "Kapellsk\u00e4rs hamn"
    ],
    "name:und_x_variant":[
        "Kappelsk\u00e4r"
    ],
    "wof:name":"Kapellskar",
    "wof:placetype":"locality"
},
  "geometry": {"coordinates":[19.06667,59.71666999999999],"type":"Point"}
}