{
  "type": "Feature",
  "properties": {
    "gn:admin1_code":"24.0",
    "gn:admin2_code":"2283.0",
    "gn:asciiname":"Gammelmo",
    "gn:cc2":"SE",
    "gn:country_code":"SE",
    "gn:dem":188,
    "gn:feature_class":"P",
    "gn:feature_code":"PPL",
    "gn:name":"Gammelmo",
    "gn:population":0,
    "gn:timezone":"Europe/Stockholm",
    "iso:country":"SE",
    "name:und_x_variant":[
        "Mo",
        "Gammelmo"
    ],
    "wof:name":"Gammelmo",
    "wof:placetype":"locality"
},
  "geometry": {"coordinates":[16.53333,63.46666999999999],"type":"Point"}
}