{
  "type": "Feature",
  "properties": {
    "gn:admin1_code":"3.0",
    "gn:admin2_code":"2101.0",
    "gn:asciiname":"Ostervik",
    "gn:country_code":"SE",
    "gn:dem":102,
    "gn:feature_class":"P",
    "gn:feature_code":"PPL",
    "gn:name":"\u00d6stervik",
    "gn:population":0,
    "gn:timezone":"Europe/Stockholm",
    "iso:country":"SE",
    "name:nor_x_preferred":[
        "\u00d6stervik"
    ],
    "name:nor_x_variant":[
        "\u00d8stervik"
    ],
    "wof:name":"Ostervik",
    "wof:placetype":"locality"
},
  "geometry": {"coordinates":[16.75,61.03333000000001],"type":"Point"}
}