{
  "type": "Feature",
  "properties": {
    "gn:admin1_code":"7.0",
    "gn:admin2_code":"2321.0",
    "gn:asciiname":"Strand",
    "gn:country_code":"SE",
    "gn:dem":321,
    "gn:feature_class":"P",
    "gn:feature_code":"PPL",
    "gn:name":"Strand",
    "gn:population":0,
    "gn:timezone":"Europe/Stockholm",
    "iso:country":"SE",
    "name:ceb_x_preferred":[
        "Strand"
    ],
    "name:dan_x_preferred":[
        "Strand"
    ],
    "name:deu_x_preferred":[
        "Strand"
    ],
    "name:eus_x_preferred":[
        "Strand"
    ],
    "name:fin_x_preferred":[
        "Strand"
    ],
    "name:fra_x_preferred":[
        "Strand"
    ],
    "name:heb_x_preferred":[
        "\u05e1\u05d8\u05e8\u05e0\u05d3"
    ],
    "name:ita_x_preferred":[
        "Strand"
    ],
    "name:jpn_x_preferred":[
        "\u30b9\u30c8\u30e9\u30f3\u30c9"
    ],
    "name:kor_x_preferred":[
        "\uc2a4\ud2b8\ub79c\ub4dc"
    ],
    "name:nld_x_preferred":[
        "Strand"
    ],
    "name:nno_x_preferred":[
        "Strand"
    ],
    "name:nor_x_preferred":[
        "Strand"
    ],
    "name:pol_x_preferred":[
        "Strand"
    ],
    "name:por_x_preferred":[
        "Strand"
    ],
    "name:ron_x_preferred":[
        "Strand"
    ],
    "name:rus_x_preferred":[
        "\u0421\u0442\u0440\u044d\u043d\u0434"
    ],
    "name:spa_x_preferred":[
        "Strand"
    ],
    "name:swe_x_preferred":[
        "Strand"
    ],
    "wof:name":"Strand",
    "wof:placetype":"locality"
},
  "geometry": {"coordinates":[13.51667,63.33333],"type":"Point"}
}