{
  "type": "Feature",
  "properties": {
    "gn:admin1_code":"8.0",
    "gn:admin2_code":"665.0",
    "gn:asciiname":"Masseberg",
    "gn:country_code":"SE",
    "gn:dem":240,
    "gn:feature_class":"P",
    "gn:feature_code":"PPL",
    "gn:name":"M\u00e4sseberg",
    "gn:population":0,
    "gn:timezone":"Europe/Stockholm",
    "iso:country":"SE",
    "wof:name":"Masseberg",
    "wof:placetype":"locality"
},
  "geometry": {"coordinates":[13.93333,57.38333000000001],"type":"Point"}
}