{
  "type": "Feature",
  "properties": {
    "gn:admin1_code":"14.0",
    "gn:admin2_code":"2580.0",
    "gn:asciiname":"Porsoen",
    "gn:country_code":"SE",
    "gn:dem":17,
    "gn:feature_class":"P",
    "gn:feature_code":"PPL",
    "gn:name":"Pors\u00f6n",
    "gn:population":0,
    "gn:timezone":"Europe/Stockholm",
    "iso:country":"SE",
    "name:fas_x_preferred":[
        "\u067e\u0648\u0631\u0634\u0646"
    ],
    "name:swe_x_preferred":[
        "Pors\u00f6n"
    ],
    "wof:name":"Porsoen",
    "wof:placetype":"locality"
},
  "geometry": {"coordinates":[22.13788,65.61784],"type":"Point"}
}