{
  "type": "Feature",
  "properties": {
    "gn:admin1_code":"25.0",
    "gn:admin2_code":"1962.0",
    "gn:asciiname":"Kolningsberg",
    "gn:cc2":"SE",
    "gn:country_code":"SE",
    "gn:dem":182,
    "gn:feature_class":"P",
    "gn:feature_code":"PPL",
    "gn:name":"Kolningsberg",
    "gn:population":0,
    "gn:timezone":"Europe/Stockholm",
    "iso:country":"SE",
    "name:und_x_variant":[
        "Nya Kolningbergsf\u00e4ltet",
        "Kolningberg",
        "Kolningsberg"
    ],
    "wof:name":"Kolningsberg",
    "wof:placetype":"locality"
},
  "geometry": {"coordinates":[15.86667,60.06667],"type":"Point"}
}