{
  "type": "Feature",
  "properties": {
    "gn:admin1_code":"21.0",
    "gn:admin2_code":"382.0",
    "gn:asciiname":"Lunda",
    "gn:country_code":"SE",
    "gn:dem":20,
    "gn:feature_class":"P",
    "gn:feature_code":"PPL",
    "gn:name":"Lunda",
    "gn:population":0,
    "gn:timezone":"Europe/Stockholm",
    "iso:country":"SE",
    "name:bel_x_preferred":[
        "\u041b\u0443\u043d\u0434\u0430"
    ],
    "name:cat_x_preferred":[
        "Lunda"
    ],
    "name:ceb_x_preferred":[
        "Lunda"
    ],
    "name:deu_x_preferred":[
        "Lunda"
    ],
    "name:fra_x_preferred":[
        "Lunda"
    ],
    "name:lin_x_preferred":[
        "Lunda"
    ],
    "name:pol_x_preferred":[
        "Lunda"
    ],
    "name:por_x_preferred":[
        "Lunda"
    ],
    "name:rus_x_preferred":[
        "\u041b\u0443\u043d\u0434\u0430"
    ],
    "name:swe_x_preferred":[
        "Lunda"
    ],
    "wof:name":"Lunda",
    "wof:placetype":"locality"
},
  "geometry": {"coordinates":[18.06667,60.11666999999999],"type":"Point"}
}