{
  "type": "Feature",
  "properties": {
    "gn:admin1_code":"8.0",
    "gn:admin2_code":"617.0",
    "gn:asciiname":"Almas",
    "gn:country_code":"SE",
    "gn:dem":281,
    "gn:feature_class":"P",
    "gn:feature_code":"PPL",
    "gn:name":"\u00c4lm\u00e5s",
    "gn:population":0,
    "gn:timezone":"Europe/Stockholm",
    "iso:country":"SE",
    "wof:name":"Almas",
    "wof:placetype":"locality"
},
  "geometry": {"coordinates":[13.76667,57.28333000000001],"type":"Point"}
}