{
  "type": "Feature",
  "properties": {
    "gn:admin1_code":"8.0",
    "gn:admin2_code":"617.0",
    "gn:asciiname":"Almas",
    "gn:country_code":"SE",
    "gn:dem":281,
    "gn:feature_class":"P",
    "gn:feature_code":"PPL",
    "gn:name":"\u00c4lm\u00e5s",
    "gn:population":0,
    "gn:timezone":"Europe/Stockholm",
    "iso:country":"SE",
    "name:ceb_x_preferred":[
        "Almas"
    ],
    "name:deu_x_preferred":[
        "Almas"
    ],
    "name:epo_x_preferred":[
        "Almas"
    ],
    "name:ita_x_preferred":[
        "Almas"
    ],
    "name:kaz_x_preferred":[
        "\u0410\u043b\u043c\u0430\u0441"
    ],
    "name:nld_x_preferred":[
        "Almas"
    ],
    "name:por_x_preferred":[
        "Almas"
    ],
    "name:rus_x_preferred":[
        "\u0410\u043b\u043c\u0430\u0441"
    ],
    "name:spa_x_preferred":[
        "Almas"
    ],
    "name:swe_x_preferred":[
        "Almas"
    ],
    "name:tur_x_preferred":[
        "Almas"
    ],
    "name:vie_x_preferred":[
        "Almas"
    ],
    "wof:name":"Almas",
    "wof:placetype":"locality"
},
  "geometry": {"coordinates":[13.76667,57.28333000000001],"type":"Point"}
}