{
  "type": "Feature",
  "properties": {
    "gn:admin1_code":"6.0",
    "gn:admin2_code":"1382.0",
    "gn:asciiname":"Asige",
    "gn:country_code":"SE",
    "gn:dem":44,
    "gn:feature_class":"P",
    "gn:feature_code":"PPL",
    "gn:name":"Asige",
    "gn:population":0,
    "gn:timezone":"Europe/Stockholm",
    "iso:country":"SE",
    "wof:name":"Asige",
    "wof:placetype":"locality"
},
  "geometry": {"coordinates":[12.73333,56.86666999999999],"type":"Point"}
}