{
  "type": "Feature",
  "properties": {
    "gn:admin1_code":"3.0",
    "gn:asciiname":"Balson",
    "gn:cc2":"SE",
    "gn:country_code":"SE",
    "gn:dem":2,
    "gn:feature_class":"P",
    "gn:feature_code":"PPL",
    "gn:name":"B\u00e5ls\u00f6n",
    "gn:population":0,
    "gn:timezone":"Europe/Stockholm",
    "iso:country":"SE",
    "name:nor_x_preferred":[
        "B\u00e5ls\u00f6n"
    ],
    "name:nor_x_variant":[
        "B\u00e5ls\u00f8n"
    ],
    "name:und_x_variant":[
        "B\u00e5ls\u00f6",
        "B\u00e5ls\u00f6n"
    ],
    "wof:name":"Balson",
    "wof:placetype":"locality"
},
  "geometry": {"coordinates":[17.53333,61.71666999999999],"type":"Point"}
}