{
  "type": "Feature",
  "properties": {
    "gn:admin1_code":"10.0",
    "gn:admin2_code":"2062.0",
    "gn:asciiname":"Amberg",
    "gn:country_code":"SE",
    "gn:dem":333,
    "gn:feature_class":"P",
    "gn:feature_code":"PPL",
    "gn:name":"\u00c5mberg",
    "gn:population":0,
    "gn:timezone":"Europe/Stockholm",
    "iso:country":"SE",
    "wof:name":"Amberg",
    "wof:placetype":"locality"
},
  "geometry": {"coordinates":[14.35,60.91667],"type":"Point"}
}