{
  "type": "Feature",
  "properties": {
    "gn:admin1_code":"3.0",
    "gn:admin2_code":"2181.0",
    "gn:asciiname":"Vreta",
    "gn:country_code":"SE",
    "gn:dem":56,
    "gn:feature_class":"P",
    "gn:feature_code":"PPL",
    "gn:name":"Vreta",
    "gn:population":0,
    "gn:timezone":"Europe/Stockholm",
    "iso:country":"SE",
    "name:swe_x_preferred":[
        "Vreta"
    ],
    "wof:name":"Vreta",
    "wof:placetype":"locality"
},
  "geometry": {"coordinates":[16.78333,60.33333],"type":"Point"}
}