{
  "type": "Feature",
  "properties": {
    "gn:admin1_code":"27.0",
    "gn:admin2_code":"1293.0",
    "gn:asciiname":"Bjorkerod",
    "gn:country_code":"SE",
    "gn:dem":62,
    "gn:feature_class":"P",
    "gn:feature_code":"PPL",
    "gn:name":"Bj\u00f6rker\u00f6d",
    "gn:population":0,
    "gn:timezone":"Europe/Stockholm",
    "iso:country":"SE",
    "name:nor_x_preferred":[
        "Bj\u00f6rker\u00f6d"
    ],
    "name:nor_x_variant":[
        "Bj\u00f8rker\u00f8d"
    ],
    "wof:name":"Bjorkerod",
    "wof:placetype":"locality"
},
  "geometry": {"coordinates":[13.68333,56.21666999999999],"type":"Point"}
}