{
  "type": "Feature",
  "properties": {
    "gn:admin1_code":"14.0",
    "gn:admin2_code":"2518.0",
    "gn:asciiname":"Korva",
    "gn:country_code":"SE",
    "gn:dem":61,
    "gn:feature_class":"P",
    "gn:feature_code":"PPL",
    "gn:name":"Korva",
    "gn:population":0,
    "gn:timezone":"Europe/Stockholm",
    "iso:country":"SE",
    "name:und_x_variant":[
        "Torrakankorva",
        "Torakankorva"
    ],
    "wof:name":"Korva",
    "wof:placetype":"locality"
},
  "geometry": {"coordinates":[23.66748,66.46666],"type":"Point"}
}