{
  "type": "Feature",
  "properties": {
    "gn:admin1_code":"9.0",
    "gn:asciiname":"Sjolyckan",
    "gn:country_code":"SE",
    "gn:dem":-9999,
    "gn:feature_class":"P",
    "gn:feature_code":"PPL",
    "gn:name":"Sj\u00f6lyckan",
    "gn:population":0,
    "gn:timezone":"Europe/Stockholm",
    "iso:country":"SE",
    "name:nor_x_preferred":[
        "Sj\u00f6lyckan"
    ],
    "name:nor_x_variant":[
        "Sj\u00f8lyckan"
    ],
    "wof:name":"Sjolyckan",
    "wof:placetype":"locality"
},
  "geometry": {"coordinates":[16.33333,56.65],"type":"Point"}
}