{
  "type": "Feature",
  "properties": {
    "gn:admin1_code":"24",
    "gn:admin2_code":"2262.0",
    "gn:admin3_code":"226203.0",
    "gn:admin4_code":"2471.0",
    "gn:asciiname":"Rigsta",
    "gn:country_code":"SE",
    "gn:dem":102,
    "gn:feature_class":"P",
    "gn:feature_code":"PPL",
    "gn:name":"Rigsta",
    "gn:population":0,
    "gn:timezone":"Europe/Stockholm",
    "iso:country":"SE",
    "wof:name":"Rigsta",
    "wof:placetype":"locality"
},
  "geometry": {"coordinates":[17.50277,62.51313],"type":"Point"}
}