{
  "type": "Feature",
  "properties": {
    "gn:admin1_code":"24.0",
    "gn:admin2_code":"2282.0",
    "gn:asciiname":"Frok",
    "gn:country_code":"SE",
    "gn:dem":58,
    "gn:feature_class":"P",
    "gn:feature_code":"PPL",
    "gn:name":"Fr\u00f6k",
    "gn:population":0,
    "gn:timezone":"Europe/Stockholm",
    "iso:country":"SE",
    "name:nor_x_preferred":[
        "Fr\u00f6k"
    ],
    "name:nor_x_variant":[
        "Fr\u00f8k"
    ],
    "wof:name":"Frok",
    "wof:placetype":"locality"
},
  "geometry": {"coordinates":[17.78333,63.06667],"type":"Point"}
}