{
  "type": "Feature",
  "properties": {
    "gn:admin1_code":"25.0",
    "gn:admin2_code":"1980.0",
    "gn:asciiname":"Ostjadra",
    "gn:country_code":"SE",
    "gn:dem":38,
    "gn:feature_class":"P",
    "gn:feature_code":"PPL",
    "gn:name":"\u00d6stj\u00e4dra",
    "gn:population":0,
    "gn:timezone":"Europe/Stockholm",
    "iso:country":"SE",
    "wof:name":"Ostjadra",
    "wof:placetype":"locality"
},
  "geometry": {"coordinates":[16.38332999999999,59.58333],"type":"Point"}
}