{
  "type": "Feature",
  "properties": {
    "gn:admin1_code":"08",
    "gn:admin2_code":"643.0",
    "gn:admin3_code":"64301.0",
    "gn:admin4_code":"1918.0",
    "gn:asciiname":"Svedudden, NO Fagerhult VG",
    "gn:country_code":"SE",
    "gn:dem":93,
    "gn:feature_class":"P",
    "gn:feature_code":"PPL",
    "gn:name":"Svedudden, NO Fagerhult VG",
    "gn:population":0,
    "gn:timezone":"Europe/Stockholm",
    "iso:country":"SE",
    "wof:name":"Svedudden, NO Fagerhult VG",
    "wof:placetype":"locality"
},
  "geometry": {"coordinates":[14.17751,58.0161],"type":"Point"}
}