{
  "type": "Feature",
  "properties": {
    "gn:admin1_code":"28.0",
    "gn:admin2_code":"1435.0",
    "gn:asciiname":"Stabackehult",
    "gn:country_code":"SE",
    "gn:dem":75,
    "gn:feature_class":"P",
    "gn:feature_code":"PPL",
    "gn:name":"Stab\u00e4ckehult",
    "gn:population":0,
    "gn:timezone":"Europe/Stockholm",
    "iso:country":"SE",
    "wof:name":"Stabackehult",
    "wof:placetype":"locality"
},
  "geometry": {"coordinates":[11.56667,58.85],"type":"Point"}
}