{
  "type": "Feature",
  "properties": {
    "gn:admin1_code":"28.0",
    "gn:admin2_code":"1485.0",
    "gn:asciiname":"Kastet",
    "gn:country_code":"SE",
    "gn:dem":40,
    "gn:feature_class":"P",
    "gn:feature_code":"PPL",
    "gn:name":"Kastet",
    "gn:population":0,
    "gn:timezone":"Europe/Stockholm",
    "iso:country":"SE",
    "wof:name":"Kastet",
    "wof:placetype":"locality"
},
  "geometry": {"coordinates":[11.875,58.325],"type":"Point"}
}