{
  "type": "Feature",
  "properties": {
    "gn:admin1_code":"24.0",
    "gn:admin2_code":"2283.0",
    "gn:asciiname":"Ostertjarn",
    "gn:country_code":"SE",
    "gn:dem":221,
    "gn:feature_class":"P",
    "gn:feature_code":"PPL",
    "gn:name":"\u00d6stertj\u00e4rn",
    "gn:population":0,
    "gn:timezone":"Europe/Stockholm",
    "iso:country":"SE",
    "wof:name":"Ostertjarn",
    "wof:placetype":"locality"
},
  "geometry": {"coordinates":[16.96667,63.68333000000001],"type":"Point"}
}