{
  "type": "Feature",
  "properties": {
    "gn:admin1_code":"12.0",
    "gn:admin2_code":"764.0",
    "gn:asciiname":"Hjartanas",
    "gn:country_code":"SE",
    "gn:dem":150,
    "gn:feature_class":"P",
    "gn:feature_code":"PPL",
    "gn:name":"Hj\u00e4rtan\u00e4s",
    "gn:population":0,
    "gn:timezone":"Europe/Stockholm",
    "iso:country":"SE",
    "wof:name":"Hjartanas",
    "wof:placetype":"locality"
},
  "geometry": {"coordinates":[14.55,56.93333000000001],"type":"Point"}
}