{
  "type": "Feature",
  "properties": {
    "gn:admin1_code":"26.0",
    "gn:admin2_code":"188.0",
    "gn:asciiname":"Sundsro",
    "gn:country_code":"SE",
    "gn:dem":28,
    "gn:feature_class":"P",
    "gn:feature_code":"PPL",
    "gn:name":"Sundsro",
    "gn:population":0,
    "gn:timezone":"Europe/Stockholm",
    "iso:country":"SE",
    "wof:name":"Sundsro",
    "wof:placetype":"locality"
},
  "geometry": {"coordinates":[18.93333,59.91667],"type":"Point"}
}