{
  "type": "Feature",
  "properties": {
    "gn:admin1_code":"28.0",
    "gn:admin2_code":"1419.0",
    "gn:asciiname":"Kolerod",
    "gn:country_code":"SE",
    "gn:dem":21,
    "gn:feature_class":"P",
    "gn:feature_code":"PPL",
    "gn:name":"K\u00f6ler\u00f6d",
    "gn:population":0,
    "gn:timezone":"Europe/Stockholm",
    "iso:country":"SE",
    "name:nor_x_preferred":[
        "K\u00f6ler\u00f6d"
    ],
    "name:nor_x_variant":[
        "K\u00f8ler\u00f8d"
    ],
    "name:und_x_variant":[
        "K\u00f6ler\u00f6d"
    ],
    "wof:name":"Kolerod",
    "wof:placetype":"locality"
},
  "geometry": {"coordinates":[11.61667,58.05],"type":"Point"}
}