{
  "type": "Feature",
  "properties": {
    "gn:admin1_code":"8.0",
    "gn:admin2_code":"665.0",
    "gn:asciiname":"Ekhult",
    "gn:country_code":"SE",
    "gn:dem":211,
    "gn:feature_class":"P",
    "gn:feature_code":"PPL",
    "gn:name":"Ekhult",
    "gn:population":0,
    "gn:timezone":"Europe/Stockholm",
    "iso:country":"SE",
    "wof:name":"Ekhult",
    "wof:placetype":"locality"
},
  "geometry": {"coordinates":[14.18333,57.41667],"type":"Point"}
}