{
  "type": "Feature",
  "properties": {
    "gn:admin1_code":"25.0",
    "gn:admin2_code":"1904.0",
    "gn:asciiname":"Tomasbo",
    "gn:country_code":"SE",
    "gn:dem":106,
    "gn:feature_class":"P",
    "gn:feature_code":"PPL",
    "gn:name":"Tomasbo",
    "gn:population":0,
    "gn:timezone":"Europe/Stockholm",
    "iso:country":"SE",
    "wof:name":"Tomasbo",
    "wof:placetype":"locality"
},
  "geometry": {"coordinates":[15.66667,59.73333],"type":"Point"}
}