{
  "type": "Feature",
  "properties": {
    "gn:admin1_code":"25.0",
    "gn:admin2_code":"1981.0",
    "gn:asciiname":"Sorhorende",
    "gn:country_code":"SE",
    "gn:dem":83,
    "gn:feature_class":"P",
    "gn:feature_code":"PPL",
    "gn:name":"S\u00f6rh\u00f6rende",
    "gn:population":0,
    "gn:timezone":"Europe/Stockholm",
    "iso:country":"SE",
    "name:nor_x_preferred":[
        "S\u00f6rh\u00f6rende"
    ],
    "name:nor_x_variant":[
        "S\u00f8rh\u00f8rende"
    ],
    "name:und_x_variant":[
        "S\u00f6rh\u00f6rende"
    ],
    "wof:name":"Sorhorende",
    "wof:placetype":"locality"
},
  "geometry": {"coordinates":[16.16667,59.95],"type":"Point"}
}