{
  "type": "Feature",
  "properties": {
    "gn:admin1_code":"15.0",
    "gn:admin2_code":"1885.0",
    "gn:asciiname":"Vastersorby",
    "gn:cc2":"SE",
    "gn:country_code":"SE",
    "gn:dem":38,
    "gn:feature_class":"P",
    "gn:feature_code":"PPL",
    "gn:name":"V\u00e4sters\u00f6rby",
    "gn:population":0,
    "gn:timezone":"Europe/Stockholm",
    "iso:country":"SE",
    "name:und_x_variant":[
        "V\u00e4stra S\u00f6rby",
        "V\u00e4sters\u00f6rby"
    ],
    "wof:name":"Vastersorby",
    "wof:placetype":"locality"
},
  "geometry": {"coordinates":[15.66667,59.43333000000001],"type":"Point"}
}