{
  "type": "Feature",
  "properties": {
    "gn:admin1_code":"7.0",
    "gn:admin2_code":"2326.0",
    "gn:asciiname":"Mjovattnet",
    "gn:country_code":"SE",
    "gn:dem":400,
    "gn:feature_class":"P",
    "gn:feature_code":"PPL",
    "gn:name":"Mj\u00f6vattnet",
    "gn:population":0,
    "gn:timezone":"Europe/Stockholm",
    "iso:country":"SE",
    "name:nor_x_preferred":[
        "Mj\u00f6vattnet"
    ],
    "name:nor_x_variant":[
        "Mj\u00f8vattnet"
    ],
    "name:und_x_variant":[
        "Mj\u00f6vattnet"
    ],
    "wof:name":"Mjovattnet",
    "wof:placetype":"locality"
},
  "geometry": {"coordinates":[14.78333,62.71666999999999],"type":"Point"}
}