{
  "type": "Feature",
  "properties": {
    "gn:admin1_code":"28.0",
    "gn:admin2_code":"1496.0",
    "gn:asciiname":"Vallby",
    "gn:country_code":"SE",
    "gn:dem":72,
    "gn:feature_class":"P",
    "gn:feature_code":"PPL",
    "gn:name":"Vallby",
    "gn:population":0,
    "gn:timezone":"Europe/Stockholm",
    "iso:country":"SE",
    "wof:name":"Vallby",
    "wof:placetype":"locality"
},
  "geometry": {"coordinates":[13.98333,58.53333000000001],"type":"Point"}
}