{
  "type": "Feature",
  "properties": {
    "gn:admin1_code":"28.0",
    "gn:admin2_code":"1442.0",
    "gn:asciiname":"Ane",
    "gn:cc2":"SE",
    "gn:country_code":"SE",
    "gn:dem":131,
    "gn:feature_class":"P",
    "gn:feature_code":"PPL",
    "gn:name":"\u00c4ne",
    "gn:population":0,
    "gn:timezone":"Europe/Stockholm",
    "iso:country":"SE",
    "name:und_x_variant":[
        "\u00c4net",
        "\u00c4ne"
    ],
    "wof:name":"Ane",
    "wof:placetype":"locality"
},
  "geometry": {"coordinates":[12.91667,58.01667],"type":"Point"}
}