{
  "type": "Feature",
  "properties": {
    "iso:country":"SE",
    "qs_pg:aaroncc":"SE",
    "qs_pg:name":"Tveta Fritidsomr\u00e5de",
    "qs_pg:name_adm0":"Sverige",
    "qs_pg:name_adm1":"Kalmar L\u00e4n",
    "qs_pg:photos":38,
    "qs_pg:photos_1k":8,
    "qs_pg:photos_9k":1,
    "qs_pg:photos_9r":2,
    "qs_pg:photos_all":38,
    "qs_pg:photos_sr":2,
    "qs_pg:pop_sr":0,
    "qs_pg:qs_pg_placetype":"locality",
    "qs_pg:qs_pg_placetype_gp":"Town",
    "qs_pg:woe_adm0":23424954,
    "woe:adm0_id":23424954,
    "woe:name_adm0":"Sverige",
    "woe:name_adm1":"Kalmar L\u00e4n",
    "woe:placetype":"Town",
    "wof:name":"Tveta Fritidsomr\u00e5de",
    "wof:placetype":"locality"
},
  "geometry": {"coordinates":[16.6005525,56.66791],"type":"Point"}
}