{
  "type": "Feature",
  "properties": {
    "gn:admin1_code":"8.0",
    "gn:admin2_code":"680.0",
    "gn:admin3_code":"68008.0",
    "gn:admin4_code":"3010.0",
    "gn:asciiname":"Hovslatt",
    "gn:country_code":"SE",
    "gn:dem":116,
    "gn:feature_class":"P",
    "gn:feature_code":"PPL",
    "gn:name":"Hovsl\u00e4tt",
    "gn:population":0,
    "gn:timezone":"Europe/Stockholm",
    "iso:country":"SE",
    "wof:name":"Hovslatt",
    "wof:placetype":"locality"
},
  "geometry": {"coordinates":[14.11945,57.7297],"type":"Point"}
}