{
  "type": "Feature",
  "properties": {
    "gn:admin1_code":"7.0",
    "gn:admin2_code":"2303.0",
    "gn:admin3_code":"230302.0",
    "gn:admin4_code":"2526.0",
    "gn:asciiname":"Osterasen",
    "gn:country_code":"SE",
    "gn:dem":125,
    "gn:feature_class":"P",
    "gn:feature_code":"PPL",
    "gn:name":"\u00d6ster\u00e5sen",
    "gn:population":0,
    "gn:timezone":"Europe/Stockholm",
    "iso:country":"SE",
    "name:nor_x_preferred":[
        "\u00d6ster\u00e5sen"
    ],
    "name:nor_x_variant":[
        "\u00d8ster\u00e5sen"
    ],
    "name:und_x_variant":[
        "\u00d6ster\u00e5sen"
    ],
    "wof:name":"Osterasen",
    "wof:placetype":"locality"
},
  "geometry": {"coordinates":[16.64083,62.96839],"type":"Point"}
}