{
  "type": "Feature",
  "properties": {
    "gn:admin1_code":"18.0",
    "gn:admin2_code":"484.0",
    "gn:admin3_code":"48418.0",
    "gn:admin4_code":"334.0",
    "gn:asciiname":"Hallsta",
    "gn:country_code":"SE",
    "gn:dem":38,
    "gn:feature_class":"P",
    "gn:feature_code":"PPL",
    "gn:name":"H\u00e5llsta",
    "gn:population":917,
    "gn:timezone":"Europe/Stockholm",
    "iso:country":"SE",
    "name:ita_x_preferred":[
        "H\u00e5llsta"
    ],
    "name:nld_x_preferred":[
        "H\u00e5llsta"
    ],
    "name:pol_x_preferred":[
        "H\u00e5llsta"
    ],
    "name:swe_x_preferred":[
        "H\u00e5llsta"
    ],
    "wof:name":"Hallsta",
    "wof:placetype":"locality",
    "wof:population":917
},
  "geometry": {"coordinates":[16.45434,59.29491],"type":"Point"}
}