{
  "type": "Feature",
  "properties": {
    "gn:admin1_code":"27.0",
    "gn:admin2_code":"1293.0",
    "gn:asciiname":"Anglarp",
    "gn:country_code":"SE",
    "gn:dem":140,
    "gn:feature_class":"P",
    "gn:feature_code":"PPL",
    "gn:name":"\u00c4nglarp",
    "gn:population":0,
    "gn:timezone":"Europe/Stockholm",
    "iso:country":"SE",
    "wof:name":"Anglarp",
    "wof:placetype":"locality"
},
  "geometry": {"coordinates":[13.53333,56.28333000000001],"type":"Point"}
}