{
  "type": "Feature",
  "properties": {
    "gn:admin1_code":"6.0",
    "gn:admin2_code":"1315.0",
    "gn:asciiname":"Aker",
    "gn:country_code":"SE",
    "gn:dem":134,
    "gn:feature_class":"P",
    "gn:feature_code":"PPL",
    "gn:name":"\u00c5ker",
    "gn:population":0,
    "gn:timezone":"Europe/Stockholm",
    "iso:country":"SE",
    "wof:name":"Aker",
    "wof:placetype":"locality"
},
  "geometry": {"coordinates":[13.33333,56.98333],"type":"Point"}
}