{
  "type": "Feature",
  "properties": {
    "gn:admin1_code":"6.0",
    "gn:admin2_code":"1315.0",
    "gn:asciiname":"Aker",
    "gn:country_code":"SE",
    "gn:dem":134,
    "gn:feature_class":"P",
    "gn:feature_code":"PPL",
    "gn:name":"\u00c5ker",
    "gn:population":0,
    "gn:timezone":"Europe/Stockholm",
    "iso:country":"SE",
    "name:ceb_x_preferred":[
        "Aker"
    ],
    "name:deu_x_preferred":[
        "Aker"
    ],
    "name:eus_x_preferred":[
        "Aker"
    ],
    "name:fin_x_preferred":[
        "Aker"
    ],
    "name:fra_x_preferred":[
        "Aker"
    ],
    "name:nld_x_preferred":[
        "Aker"
    ],
    "name:nor_x_preferred":[
        "Aker"
    ],
    "name:rus_x_preferred":[
        "\u0410\u043a\u0435\u0440"
    ],
    "name:slk_x_preferred":[
        "Aker"
    ],
    "name:swe_x_preferred":[
        "Aker"
    ],
    "wof:name":"Aker",
    "wof:placetype":"locality"
},
  "geometry": {"coordinates":[13.33333,56.98333],"type":"Point"}
}