{
  "type": "Feature",
  "properties": {
    "gn:admin1_code":"10.0",
    "gn:admin2_code":"2084.0",
    "gn:asciiname":"Nickarvet",
    "gn:cc2":"SE",
    "gn:country_code":"SE",
    "gn:dem":106,
    "gn:feature_class":"P",
    "gn:feature_code":"PPL",
    "gn:name":"Nickarvet",
    "gn:population":0,
    "gn:timezone":"Europe/Stockholm",
    "iso:country":"SE",
    "name:und_x_variant":[
        "Nickarfvet",
        "Nickarvet"
    ],
    "wof:name":"Nickarvet",
    "wof:placetype":"locality"
},
  "geometry": {"coordinates":[16.26667,60.25],"type":"Point"}
}