{
  "type": "Feature",
  "properties": {
    "gn:admin1_code":"22.0",
    "gn:admin2_code":"1784.0",
    "gn:asciiname":"Gravas",
    "gn:cc2":"SE",
    "gn:country_code":"SE",
    "gn:dem":127,
    "gn:feature_class":"P",
    "gn:feature_code":"PPL",
    "gn:name":"Grav\u00e5s",
    "gn:population":0,
    "gn:timezone":"Europe/Stockholm",
    "iso:country":"SE",
    "name:und_x_variant":[
        "Graf\u00e5s",
        "Grav\u00e5s"
    ],
    "wof:name":"Gravas",
    "wof:placetype":"locality"
},
  "geometry": {"coordinates":[12.55,59.78333000000001],"type":"Point"}
}