{
  "type": "Feature",
  "properties": {
    "gn:admin1_code":"22.0",
    "gn:admin2_code":"1766.0",
    "gn:asciiname":"Svineberg",
    "gn:country_code":"SE",
    "gn:dem":82,
    "gn:feature_class":"P",
    "gn:feature_code":"PPL",
    "gn:name":"Svineberg",
    "gn:population":0,
    "gn:timezone":"Europe/Stockholm",
    "iso:country":"SE",
    "wof:name":"Svineberg",
    "wof:placetype":"locality"
},
  "geometry": {"coordinates":[13.18333,59.86666999999999],"type":"Point"}
}