{
  "type": "Feature",
  "properties": {
    "gn:admin1_code":"28.0",
    "gn:admin2_code":"1473.0",
    "gn:asciiname":"Ravsnas",
    "gn:country_code":"SE",
    "gn:dem":104,
    "gn:feature_class":"P",
    "gn:feature_code":"PPL",
    "gn:name":"R\u00e4vsn\u00e4s",
    "gn:population":0,
    "gn:timezone":"Europe/Stockholm",
    "iso:country":"SE",
    "wof:name":"Ravsnas",
    "wof:placetype":"locality"
},
  "geometry": {"coordinates":[14.05,58.76667],"type":"Point"}
}