{
  "type": "Feature",
  "properties": {
    "gn:admin1_code":"8.0",
    "gn:admin2_code":"685.0",
    "gn:asciiname":"Loaklev",
    "gn:country_code":"SE",
    "gn:dem":189,
    "gn:feature_class":"P",
    "gn:feature_code":"PPL",
    "gn:name":"Loaklev",
    "gn:population":0,
    "gn:timezone":"Europe/Stockholm",
    "iso:country":"SE",
    "wof:name":"Loaklev",
    "wof:placetype":"locality"
},
  "geometry": {"coordinates":[15.35,57.38333000000001],"type":"Point"}
}