{
  "type": "Feature",
  "properties": {
    "gn:admin1_code":"23.0",
    "gn:admin2_code":"2480.0",
    "gn:asciiname":"Morbyn",
    "gn:country_code":"SE",
    "gn:dem":92,
    "gn:feature_class":"P",
    "gn:feature_code":"PPL",
    "gn:name":"Morbyn",
    "gn:population":0,
    "gn:timezone":"Europe/Stockholm",
    "iso:country":"SE",
    "wof:name":"Morbyn",
    "wof:placetype":"locality"
},
  "geometry": {"coordinates":[20.51667,64.05],"type":"Point"}
}