{
  "type": "Feature",
  "properties": {
    "iso:country":"SE",
    "name:swe_x_preferred":[
        "Lillsved"
    ],
    "name:unk_x_variant":[
        "Lillsved"
    ],
    "qs:gn_adm0_cc":"SE",
    "qs:gn_local":2663540,
    "qs:gn_nam_loc":"Vaxholm, Vaxholm, Stockholms L\u00e4n, SE",
    "qs:gn_namadm1":"26",
    "qs:local_max":572,
    "qs:local_sum":1935,
    "qs:localhoods":11,
    "qs:name":"Lillsved",
    "qs:name_adm0":"Sverige",
    "qs:name_adm1":"Stockholms L\u00e4n",
    "qs:name_adm2":"V\u00e4rmd\u00f6",
    "qs:name_local":"Vaxholm",
    "qs:photo_max":36,
    "qs:photo_sum":157,
    "qs:placetype":"Suburb",
    "qs:quad_count":33,
    "qs:woe_adm0":23424954,
    "qs:woe_adm1":2347067,
    "qs:woe_adm2":12587485,
    "qs:woe_lau":0,
    "qs:woe_local":909710,
    "qs:woe_ver":"7.10.0",
    "wof:lang":[
        "swe"
    ],
    "wof:name":"Lillsved",
    "wof:placetype":"neighbourhood"
},
  "geometry": {"coordinates":[18.544266,59.413982],"type":"Point"}
}