{
  "type": "Feature",
  "properties": {
    "gn:admin1_code":"9.0",
    "gn:admin2_code":"880.0",
    "gn:asciiname":"Raby",
    "gn:country_code":"SE",
    "gn:dem":17,
    "gn:feature_class":"P",
    "gn:feature_code":"PPL",
    "gn:name":"R\u00e5by",
    "gn:population":0,
    "gn:timezone":"Europe/Stockholm",
    "iso:country":"SE",
    "name:ceb_x_preferred":[
        "Raby"
    ],
    "name:deu_x_preferred":[
        "Raby"
    ],
    "name:fas_x_preferred":[
        "\u0631\u0628\u06cc"
    ],
    "name:nld_x_preferred":[
        "Raby"
    ],
    "name:pol_x_preferred":[
        "Raby"
    ],
    "name:swe_x_preferred":[
        "Raby"
    ],
    "wof:name":"Raby",
    "wof:placetype":"locality"
},
  "geometry": {"coordinates":[16.18333,56.65],"type":"Point"}
}