{
  "type": "Feature",
  "properties": {
    "gn:admin1_code":"9.0",
    "gn:admin2_code":"861.0",
    "gn:asciiname":"Sodra Backebo",
    "gn:country_code":"SE",
    "gn:dem":14,
    "gn:feature_class":"P",
    "gn:feature_code":"PPL",
    "gn:name":"S\u00f6dra B\u00e4ckebo",
    "gn:population":0,
    "gn:timezone":"Europe/Stockholm",
    "iso:country":"SE",
    "wof:name":"Sodra Backebo",
    "wof:placetype":"locality"
},
  "geometry": {"coordinates":[16.38332999999999,56.91667],"type":"Point"}
}