{
  "type": "Feature",
  "properties": {
    "gn:admin1_code":"10.0",
    "gn:admin2_code":"2034.0",
    "gn:asciiname":"Enaberg",
    "gn:country_code":"SE",
    "gn:dem":352,
    "gn:feature_class":"P",
    "gn:feature_code":"PPL",
    "gn:name":"En\u00e5berg",
    "gn:population":0,
    "gn:timezone":"Europe/Stockholm",
    "iso:country":"SE",
    "wof:name":"Enaberg",
    "wof:placetype":"locality"
},
  "geometry": {"coordinates":[14.76667,61.13306],"type":"Point"}
}