{
  "type": "Feature",
  "properties": {
    "iso:country":"SE",
    "name:dut_x_preferred":[
        "Stensj\u00f6 och del av Stora Skip\u00e5s"
    ],
    "name:eng_x_preferred":[
        "Stensj\u00f6"
    ],
    "name:fin_x_preferred":[
        "Stensj\u00f6"
    ],
    "name:ger_x_preferred":[
        "Stensj\u00f6"
    ],
    "name:swe_x_preferred":[
        "Stensj\u00f6 och del av Stora Skip\u00e5s"
    ],
    "qs_pg:aaroncc":"SE",
    "qs_pg:name":"Stensj\u00f6",
    "qs_pg:name_adm0":"Sverige",
    "qs_pg:name_adm1":"Hallands L\u00e4n",
    "qs_pg:photos":170,
    "qs_pg:photos_1k":34,
    "qs_pg:photos_9k":1,
    "qs_pg:photos_9r":4,
    "qs_pg:photos_all":170,
    "qs_pg:photos_sr":4,
    "qs_pg:pop_sr":0,
    "qs_pg:qs_pg_placetype":"locality",
    "qs_pg:qs_pg_placetype_gp":"Town",
    "qs_pg:woe_adm0":23424954,
    "woe:adm0_id":23424954,
    "woe:name_adm0":"Sverige",
    "woe:name_adm1":"Hallands L\u00e4n",
    "woe:placetype":"Town",
    "wof:name":"Stensj\u00f6",
    "wof:placetype":"locality"
},
  "geometry": {"coordinates":[12.631069,56.797447],"type":"Point"}
}