{
  "type": "Feature",
  "properties": {
    "gn:admin1_code":"22.0",
    "gn:admin2_code":"1760.0",
    "gn:asciiname":"Sandsjotorp",
    "gn:country_code":"SE",
    "gn:dem":115,
    "gn:feature_class":"P",
    "gn:feature_code":"PPL",
    "gn:name":"Sandsj\u00f6torp",
    "gn:population":0,
    "gn:timezone":"Europe/Stockholm",
    "iso:country":"SE",
    "name:nor_x_preferred":[
        "Sandsj\u00f6torp"
    ],
    "name:nor_x_variant":[
        "Sandsj\u00f8torp"
    ],
    "name:und_x_variant":[
        "Sandsj\u00f6torp"
    ],
    "wof:name":"Sandsjotorp",
    "wof:placetype":"locality"
},
  "geometry": {"coordinates":[14.31667,59.48333],"type":"Point"}
}