{
  "type": "Feature",
  "properties": {
    "gn:admin1_code":"3.0",
    "gn:admin2_code":"2132.0",
    "gn:asciiname":"Langsbo",
    "gn:country_code":"SE",
    "gn:dem":111,
    "gn:feature_class":"P",
    "gn:feature_code":"PPL",
    "gn:name":"Langsbo",
    "gn:population":0,
    "gn:timezone":"Europe/Stockholm",
    "iso:country":"SE",
    "wof:name":"Langsbo",
    "wof:placetype":"locality"
},
  "geometry": {"coordinates":[16.76667,62.08333],"type":"Point"}
}