{
  "type": "Feature",
  "properties": {
    "gn:admin1_code":"14.0",
    "gn:admin2_code":"2581.0",
    "gn:asciiname":"Langtrask",
    "gn:country_code":"SE",
    "gn:dem":327,
    "gn:feature_class":"P",
    "gn:feature_code":"PPL",
    "gn:name":"L\u00e5ngtr\u00e4sk",
    "gn:population":0,
    "gn:timezone":"Europe/Stockholm",
    "iso:country":"SE",
    "wof:name":"Langtrask",
    "wof:placetype":"locality"
},
  "geometry": {"coordinates":[20.33333,65.38333],"type":"Point"}
}