{
  "type": "Feature",
  "properties": {
    "gn:admin1_code":"12.0",
    "gn:admin2_code":"763.0",
    "gn:asciiname":"Korpalycke",
    "gn:country_code":"SE",
    "gn:dem":138,
    "gn:feature_class":"P",
    "gn:feature_code":"PPL",
    "gn:name":"Korpalycke",
    "gn:population":0,
    "gn:timezone":"Europe/Stockholm",
    "iso:country":"SE",
    "wof:name":"Korpalycke",
    "wof:placetype":"locality"
},
  "geometry": {"coordinates":[14.98333,56.53333000000001],"type":"Point"}
}