{
  "type": "Feature",
  "properties": {
    "gn:country":"SE",
    "gn:fcode":"PPL",
    "gn:population":498,
    "iso:country":"SE",
    "name:ceb_x_preferred":[
        "Seittenkaari"
    ],
    "name:deu_x_preferred":[
        "Seskar\u00f6"
    ],
    "name:eng_x_preferred":[
        "Seskar\u00f6"
    ],
    "name:fin_x_preferred":[
        "Seittenkaari"
    ],
    "name:ita_x_preferred":[
        "Seskar\u00f6"
    ],
    "name:nan_x_preferred":[
        "Seskar\u00f6"
    ],
    "name:nld_x_preferred":[
        "Seskar\u00f6"
    ],
    "name:nno_x_preferred":[
        "Seskar\u00f6"
    ],
    "name:nob_x_preferred":[
        "Seskar\u00f6"
    ],
    "name:nor_x_preferred":[
        "Seskar\u00f8"
    ],
    "name:nor_x_variant":[
        "Seskar\u00f6"
    ],
    "name:spa_x_preferred":[
        "Seskar\u00f6"
    ],
    "name:swe_x_preferred":[
        "Seskar\u00f6"
    ],
    "qs_pg:aaroncc":"SE",
    "qs_pg:gn_country":"SE",
    "qs_pg:gn_fcode":"PPL",
    "qs_pg:gn_pop":498,
    "qs_pg:name":"Seskar\u00f6",
    "qs_pg:photos_9r":0,
    "qs_pg:photos_sr":0,
    "qs_pg:pop_sr":2,
    "qs_pg:qs_pg_placetype":"locality",
    "wof:name":"Seskar\u00f6",
    "wof:placetype":"locality",
    "wof:population":498
},
  "geometry": {"coordinates":[23.73333,65.75],"type":"Point"}
}