{
  "type": "Feature",
  "properties": {
    "gn:admin1_code":"27.0",
    "gn:admin2_code":"1264.0",
    "gn:asciiname":"Karlsborg",
    "gn:country_code":"SE",
    "gn:dem":46,
    "gn:feature_class":"P",
    "gn:feature_code":"PPL",
    "gn:name":"Karlsborg",
    "gn:population":0,
    "gn:timezone":"Europe/Stockholm",
    "iso:country":"SE",
    "wof:name":"Karlsborg",
    "wof:placetype":"locality"
},
  "geometry": {"coordinates":[13.63333,55.46666999999999],"type":"Point"}
}