{
  "type": "Feature",
  "properties": {
    "gn:admin1_code":"27.0",
    "gn:admin2_code":"1264.0",
    "gn:asciiname":"Karlsborg",
    "gn:country_code":"SE",
    "gn:dem":46,
    "gn:feature_class":"P",
    "gn:feature_code":"PPL",
    "gn:name":"Karlsborg",
    "gn:population":0,
    "gn:timezone":"Europe/Stockholm",
    "iso:country":"SE",
    "name:ara_x_preferred":[
        "\u0643\u0627\u0631\u0644\u0633\u0628\u0648\u0631\u064a"
    ],
    "name:bul_x_preferred":[
        "\u041a\u0430\u0440\u043b\u0441\u0431\u043e\u0440\u0438"
    ],
    "name:ceb_x_preferred":[
        "Karlsborg"
    ],
    "name:dan_x_preferred":[
        "Karlsborg"
    ],
    "name:deu_x_preferred":[
        "Karlsborg"
    ],
    "name:fao_x_preferred":[
        "Karlsborg"
    ],
    "name:fas_x_preferred":[
        "\u06a9\u0627\u0631\u0644\u0633\u0646\u0628\u0648\u0631\u06cc"
    ],
    "name:fin_x_preferred":[
        "Karlsborg"
    ],
    "name:isl_x_preferred":[
        "Karlsborg"
    ],
    "name:ita_x_preferred":[
        "Karlsborg"
    ],
    "name:nld_x_preferred":[
        "Karlsborg"
    ],
    "name:nno_x_preferred":[
        "Karlsborg"
    ],
    "name:nor_x_preferred":[
        "Karlsborg"
    ],
    "name:pol_x_preferred":[
        "Karlsborg"
    ],
    "name:por_x_preferred":[
        "Karlsborg"
    ],
    "name:ron_x_preferred":[
        "Karlsborg"
    ],
    "name:sco_x_preferred":[
        "Karlsborg"
    ],
    "name:swe_x_preferred":[
        "Karlsborg"
    ],
    "name:ukr_x_preferred":[
        "\u041a\u0430\u0440\u043b\u0441\u0431\u043e\u0440\u0433"
    ],
    "wof:name":"Karlsborg",
    "wof:placetype":"locality"
},
  "geometry": {"coordinates":[13.63333,55.46666999999999],"type":"Point"}
}