{
  "type": "Feature",
  "properties": {
    "gn:admin1_code":"9.0",
    "gn:admin2_code":"821.0",
    "gn:asciiname":"Ringhult",
    "gn:country_code":"SE",
    "gn:dem":170,
    "gn:feature_class":"P",
    "gn:feature_code":"PPL",
    "gn:name":"Ringhult",
    "gn:population":0,
    "gn:timezone":"Europe/Stockholm",
    "iso:country":"SE",
    "wof:name":"Ringhult",
    "wof:placetype":"locality"
},
  "geometry": {"coordinates":[15.71667,57.18333000000001],"type":"Point"}
}