{
  "type": "Feature",
  "properties": {
    "gn:admin1_code":"23.0",
    "gn:admin2_code":"2404.0",
    "gn:asciiname":"Halsingfors",
    "gn:country_code":"SE",
    "gn:dem":257,
    "gn:feature_class":"P",
    "gn:feature_code":"PPL",
    "gn:name":"H\u00e4lsingfors",
    "gn:population":0,
    "gn:timezone":"Europe/Stockholm",
    "iso:country":"SE",
    "wof:name":"Halsingfors",
    "wof:placetype":"locality"
},
  "geometry": {"coordinates":[19.55,64.13333],"type":"Point"}
}