{
  "type": "Feature",
  "properties": {
    "gn:admin1_code":"14.0",
    "gn:admin2_code":"2584.0",
    "gn:admin3_code":"258403.0",
    "gn:admin4_code":"176.0",
    "gn:asciiname":"Keinovuopio",
    "gn:country_code":"SE",
    "gn:dem":483,
    "gn:feature_class":"P",
    "gn:feature_code":"PPL",
    "gn:name":"Keinovuopio",
    "gn:population":6,
    "gn:timezone":"Europe/Stockholm",
    "iso:country":"SE",
    "wof:name":"Keinovuopio",
    "wof:placetype":"locality",
    "wof:population":6
},
  "geometry": {"coordinates":[21.04448,68.87496999999999],"type":"Point"}
}