{
  "type": "Feature",
  "properties": {
    "gn:admin1_code":"9.0",
    "gn:admin2_code":"883.0",
    "gn:asciiname":"Bredvassa",
    "gn:country_code":"SE",
    "gn:dem":15,
    "gn:feature_class":"P",
    "gn:feature_code":"PPL",
    "gn:name":"Bredvassa",
    "gn:population":0,
    "gn:timezone":"Europe/Stockholm",
    "iso:country":"SE",
    "wof:name":"Bredvassa",
    "wof:placetype":"locality"
},
  "geometry": {"coordinates":[16.71667,57.91667],"type":"Point"}
}