{
  "type": "Feature",
  "properties": {
    "iso:country":"SE",
    "name:swe_x_preferred":[
        "Norslund"
    ],
    "name:unk_x_variant":[
        "Norslund"
    ],
    "qs:gn_adm0_cc":"SE",
    "qs:gn_fcode":"PPLX",
    "qs:gn_local":2715459,
    "qs:gn_namadm1":"10",
    "qs:gn_name":"Norslund",
    "qs:local_max":1706,
    "qs:local_sum":1706,
    "qs:localhoods":1,
    "qs:name":"Norslund",
    "qs:name_adm0":"Sverige",
    "qs:name_adm1":"Dalarnas L\u00e4n",
    "qs:name_adm2":"Falun",
    "qs:name_local":"Falun",
    "qs:photo_max":139,
    "qs:photo_sum":1706,
    "qs:placetype":"Suburb",
    "qs:quad_count":142,
    "qs:woe_adm0":23424954,
    "qs:woe_adm1":2347053,
    "qs:woe_adm2":12587289,
    "qs:woe_lau":0,
    "qs:woe_local":889278,
    "qs:woe_ver":"7.10.0",
    "wof:lang":[
        "swe"
    ],
    "wof:name":"Norslund",
    "wof:placetype":"neighbourhood"
},
  "geometry": {"coordinates":[15.636159,60.604128],"type":"Point"}
}