{
  "type": "Feature",
  "properties": {
    "gn:admin1_code":"14.0",
    "gn:admin2_code":"2580.0",
    "gn:asciiname":"Prastholm",
    "gn:cc2":"SE",
    "gn:country_code":"SE",
    "gn:dem":24,
    "gn:feature_class":"P",
    "gn:feature_code":"PPL",
    "gn:name":"Pr\u00e4stholm",
    "gn:population":0,
    "gn:timezone":"Europe/Stockholm",
    "iso:country":"SE",
    "name:und_x_variant":[
        "Prestholm",
        "Pr\u00e4stholmen",
        "Pr\u00e4stholm"
    ],
    "wof:name":"Prastholm",
    "wof:placetype":"locality"
},
  "geometry": {"coordinates":[22.18333,65.90000000000001],"type":"Point"}
}