{
  "type": "Feature",
  "properties": {
    "gn:admin1_code":"6.0",
    "gn:admin2_code":"1384.0",
    "gn:asciiname":"Schweizerdalen",
    "gn:country_code":"SE",
    "gn:dem":43,
    "gn:feature_class":"P",
    "gn:feature_code":"PPL",
    "gn:name":"Schweizerdalen",
    "gn:population":0,
    "gn:timezone":"Europe/Stockholm",
    "iso:country":"SE",
    "wof:name":"Schweizerdalen",
    "wof:placetype":"locality"
},
  "geometry": {"coordinates":[12.20796,57.45986],"type":"Point"}
}