{
  "type": "Feature",
  "properties": {
    "gn:admin1_code":"28.0",
    "gn:admin2_code":"1452.0",
    "gn:asciiname":"Ommesala",
    "gn:country_code":"SE",
    "gn:dem":178,
    "gn:feature_class":"P",
    "gn:feature_code":"PPL",
    "gn:name":"\u00d6mmesala",
    "gn:population":0,
    "gn:timezone":"Europe/Stockholm",
    "iso:country":"SE",
    "name:nor_x_preferred":[
        "\u00d6mmesala"
    ],
    "name:nor_x_variant":[
        "\u00d8mmesala"
    ],
    "name:und_x_variant":[
        "\u00d6mmesala"
    ],
    "wof:name":"Ommesala",
    "wof:placetype":"locality"
},
  "geometry": {"coordinates":[13.25,57.63333000000001],"type":"Point"}
}