{
  "type": "Feature",
  "properties": {
    "gn:admin1_code":"8.0",
    "gn:admin2_code":"662.0",
    "gn:asciiname":"Slatteryd",
    "gn:country_code":"SE",
    "gn:dem":211,
    "gn:feature_class":"P",
    "gn:feature_code":"PPL",
    "gn:name":"Sl\u00e4tteryd",
    "gn:population":0,
    "gn:timezone":"Europe/Stockholm",
    "iso:country":"SE",
    "wof:name":"Slatteryd",
    "wof:placetype":"locality"
},
  "geometry": {"coordinates":[13.55,57.36666999999999],"type":"Point"}
}