{
  "type": "Feature",
  "properties": {
    "gn:admin1_code":"24.0",
    "gn:admin2_code":"2280.0",
    "gn:asciiname":"Lungon",
    "gn:cc2":"SE",
    "gn:country_code":"SE",
    "gn:dem":-9999,
    "gn:feature_class":"P",
    "gn:feature_code":"PPL",
    "gn:name":"Lung\u00f6n",
    "gn:population":0,
    "gn:timezone":"Europe/Stockholm",
    "iso:country":"SE",
    "name:nor_x_preferred":[
        "Lung\u00f6n"
    ],
    "name:nor_x_variant":[
        "Lung\u00f8n"
    ],
    "name:und_x_variant":[
        "Lung\u00f6"
    ],
    "wof:name":"Lungon",
    "wof:placetype":"locality"
},
  "geometry": {"coordinates":[18.06667,62.66667],"type":"Point"}
}