{
  "type": "Feature",
  "properties": {
    "gn:admin1_code":"18.0",
    "gn:admin2_code":"483.0",
    "gn:asciiname":"Braten",
    "gn:country_code":"SE",
    "gn:dem":64,
    "gn:feature_class":"P",
    "gn:feature_code":"PPL",
    "gn:name":"Br\u00e5ten",
    "gn:population":0,
    "gn:timezone":"Europe/Stockholm",
    "iso:country":"SE",
    "wof:name":"Braten",
    "wof:placetype":"locality"
},
  "geometry": {"coordinates":[16.21667,59.05],"type":"Point"}
}