{
  "type": "Feature",
  "properties": {
    "gn:admin1_code":"23.0",
    "gn:admin2_code":"2401.0",
    "gn:admin3_code":"240102.0",
    "gn:admin4_code":"146.0",
    "gn:asciiname":"Rodviken",
    "gn:country_code":"SE",
    "gn:dem":-9999,
    "gn:feature_class":"P",
    "gn:feature_code":"PPL",
    "gn:name":"R\u00f6dviken",
    "gn:population":0,
    "gn:timezone":"Europe/Stockholm",
    "iso:country":"SE",
    "name:nor_x_preferred":[
        "R\u00f6dviken"
    ],
    "name:nor_x_variant":[
        "R\u00f8dviken"
    ],
    "wof:name":"Rodviken",
    "wof:placetype":"locality"
},
  "geometry": {"coordinates":[19.46127000000001,63.57027],"type":"Point"}
}