{
  "type": "Feature",
  "properties": {
    "gn:admin1_code":"14.0",
    "gn:admin2_code":"2514.0",
    "gn:asciiname":"Bruksbacken",
    "gn:country_code":"SE",
    "gn:dem":30,
    "gn:feature_class":"P",
    "gn:feature_code":"PPL",
    "gn:name":"Bruksbacken",
    "gn:population":0,
    "gn:timezone":"Europe/Stockholm",
    "iso:country":"SE",
    "wof:name":"Bruksbacken",
    "wof:placetype":"locality"
},
  "geometry": {"coordinates":[22.63333,65.91667],"type":"Point"}
}