{
  "type": "Feature",
  "properties": {
    "gn:admin1_code":"23.0",
    "gn:admin2_code":"2401.0",
    "gn:asciiname":"Tannstrand",
    "gn:country_code":"SE",
    "gn:dem":-9999,
    "gn:feature_class":"P",
    "gn:feature_code":"PPL",
    "gn:name":"T\u00e4nnstrand",
    "gn:population":0,
    "gn:timezone":"Europe/Stockholm",
    "iso:country":"SE",
    "wof:name":"Tannstrand",
    "wof:placetype":"locality"
},
  "geometry": {"coordinates":[19.35833,63.49166999999999],"type":"Point"}
}