{
  "type": "Feature",
  "properties": {
    "gn:gn_country":"SE",
    "gn:gn_fcode":"PPL",
    "gn:gn_pop":633,
    "gn:population":669,
    "iso:country":"SE",
    "name:bul_x_preferred":[
        "\u041a\u043e\u043f\u043e\u043c"
    ],
    "name:ceb_x_preferred":[
        "Koppom"
    ],
    "name:eng_x_preferred":[
        "Koppom"
    ],
    "name:ita_x_preferred":[
        "Koppom"
    ],
    "name:nan_x_preferred":[
        "Koppom"
    ],
    "name:nld_x_preferred":[
        "Koppom"
    ],
    "name:nno_x_preferred":[
        "Koppom"
    ],
    "name:nob_x_preferred":[
        "Koppom"
    ],
    "name:swe_x_preferred":[
        "Koppom"
    ],
    "qs_pg:aaroncc":"SE",
    "qs_pg:gn_country":"SE",
    "qs_pg:gn_fcode":"PPL",
    "qs_pg:gn_pop":633,
    "qs_pg:name":"Koppom",
    "qs_pg:name_adm0":"Sverige",
    "qs_pg:name_adm1":"V\u00e4rmlands L\u00e4n",
    "qs_pg:photos":31,
    "qs_pg:photos_1k":6,
    "qs_pg:photos_9k":1,
    "qs_pg:photos_9r":2,
    "qs_pg:photos_all":31,
    "qs_pg:photos_sr":2,
    "qs_pg:pop_sr":2,
    "qs_pg:qs_pg_placetype":"locality",
    "qs_pg:qs_pg_placetype_gp":"Town",
    "qs_pg:woe_adm0":23424954,
    "woe:adm0_id":23424954,
    "woe:name_adm0":"Sverige",
    "woe:name_adm1":"V\u00e4rmlands L\u00e4n",
    "woe:placetype":"Town",
    "wof:name":"Koppom",
    "wof:placetype":"locality",
    "wof:population":669
},
  "geometry": {"coordinates":[12.15,59.71667],"type":"Point"}
}