{
  "type": "Feature",
  "properties": {
    "gn:gn_country":"SE",
    "iso:country":"SE",
    "name:deu_x_preferred":[
        "Hari"
    ],
    "name:ita_x_preferred":[
        "Hari"
    ],
    "name:kan_x_preferred":[
        "\u0cb9\u0cb0\u0cbf"
    ],
    "name:kaz_x_preferred":[
        "\u0425\u0430\u0440\u0438"
    ],
    "name:pol_x_preferred":[
        "Hari"
    ],
    "name:por_x_preferred":[
        "Hari"
    ],
    "name:rus_x_preferred":[
        "\u0425\u0430\u0440\u0438"
    ],
    "name:tam_x_preferred":[
        "\u0bb9\u0bb0\u0bbf"
    ],
    "name:tel_x_preferred":[
        "\u0c39\u0c30\u0c3f"
    ],
    "name:ukr_x_preferred":[
        "\u0425\u0430\u0440\u0456"
    ],
    "qs_pg:aaroncc":"SE",
    "qs_pg:gn_country":"SE",
    "qs_pg:name":"Hari",
    "qs_pg:name_adm0":"Sverige",
    "qs_pg:name_adm1":"G\u00e4vleborgs L\u00e4n",
    "qs_pg:photos":7,
    "qs_pg:photos_1k":1,
    "qs_pg:photos_9k":1,
    "qs_pg:photos_9r":1,
    "qs_pg:photos_all":7,
    "qs_pg:photos_sr":1,
    "qs_pg:pop_sr":0,
    "qs_pg:qs_pg_placetype":"locality",
    "qs_pg:qs_pg_placetype_gp":"Town",
    "qs_pg:woe_adm0":23424954,
    "woe:adm0_id":23424954,
    "woe:name_adm0":"Sverige",
    "woe:name_adm1":"G\u00e4vleborgs L\u00e4n",
    "woe:placetype":"Town",
    "wof:name":"Hari",
    "wof:placetype":"locality"
},
  "geometry": {"coordinates":[17.16751,60.986886],"type":"Point"}
}