{
  "type": "Feature",
  "properties": {
    "gn:admin1_code":"7.0",
    "gn:admin2_code":"2303.0",
    "gn:asciiname":"Ammer",
    "gn:country_code":"SE",
    "gn:dem":260,
    "gn:feature_class":"P",
    "gn:feature_code":"PPL",
    "gn:name":"Ammer",
    "gn:population":0,
    "gn:timezone":"Europe/Stockholm",
    "iso:country":"SE",
    "name:ceb_x_preferred":[
        "Ammer"
    ],
    "name:ces_x_preferred":[
        "Ammer"
    ],
    "name:deu_x_preferred":[
        "Ammer"
    ],
    "name:nds_x_preferred":[
        "Ammer"
    ],
    "name:pol_x_preferred":[
        "Ammer"
    ],
    "wof:name":"Ammer",
    "wof:placetype":"locality"
},
  "geometry": {"coordinates":[16.21667,63.16667],"type":"Point"}
}