{
  "type": "Feature",
  "properties": {
    "gn:admin1_code":"7.0",
    "gn:admin2_code":"2309.0",
    "gn:asciiname":"Valsjobyn",
    "gn:cc2":"SE",
    "gn:country_code":"SE",
    "gn:dem":353,
    "gn:feature_class":"P",
    "gn:feature_code":"PPL",
    "gn:name":"Valsj\u00f6byn",
    "gn:population":0,
    "gn:timezone":"Europe/Stockholm",
    "iso:country":"SE",
    "name:nor_x_preferred":[
        "Valsj\u00f6byn"
    ],
    "name:nor_x_variant":[
        "Valsj\u00f8byn"
    ],
    "name:und_x_variant":[
        "Valsj\u00f6",
        "Valsj\u00f6n"
    ],
    "wof:name":"Valsjobyn",
    "wof:placetype":"locality"
},
  "geometry": {"coordinates":[14.13333,64.06667],"type":"Point"}
}