{
  "type": "Feature",
  "properties": {
    "gn:admin1_code":"26.0",
    "gn:admin2_code":"120.0",
    "gn:asciiname":"Johannesberg",
    "gn:country_code":"SE",
    "gn:dem":25,
    "gn:feature_class":"P",
    "gn:feature_code":"PPL",
    "gn:name":"Johannesberg",
    "gn:population":0,
    "gn:timezone":"Europe/Stockholm",
    "iso:country":"SE",
    "wof:name":"Johannesberg",
    "wof:placetype":"locality"
},
  "geometry": {"coordinates":[18.56944,59.375],"type":"Point"}
}