{
  "type": "Feature",
  "properties": {
    "gn:country":"SE",
    "gn:fcode":"PPL",
    "gn:population":362,
    "iso:country":"SE",
    "name:ceb_x_preferred":[
        "\u00c5ryd"
    ],
    "name:fra_x_preferred":[
        "\u00c5ryd"
    ],
    "name:nld_x_preferred":[
        "\u00c5ryd"
    ],
    "name:swe_x_preferred":[
        "\u00c5ryd"
    ],
    "qs_pg:aaroncc":"SE",
    "qs_pg:gn_country":"SE",
    "qs_pg:gn_fcode":"PPL",
    "qs_pg:gn_pop":362,
    "qs_pg:name":"\u00c5ryd",
    "qs_pg:photos_9r":0,
    "qs_pg:photos_sr":0,
    "qs_pg:pop_sr":2,
    "qs_pg:qs_pg_placetype":"locality",
    "wof:name":"\u00c5ryd",
    "wof:placetype":"locality",
    "wof:population":362
},
  "geometry": {"coordinates":[13.65,57.95],"type":"Point"}
}