{
  "type": "Feature",
  "properties": {
    "gn:gn_country":"SE",
    "gn:gn_fcode":"PPL",
    "gn:gn_pop":0,
    "gn:population":548,
    "iso:country":"SE",
    "name:eng_x_preferred":[
        "Klagstorp"
    ],
    "name:ita_x_preferred":[
        "Klagstorp"
    ],
    "name:nan_x_preferred":[
        "Klagstorp"
    ],
    "name:nld_x_preferred":[
        "Klagstorp"
    ],
    "name:nno_x_preferred":[
        "Klagstorp"
    ],
    "name:nob_x_preferred":[
        "Klagstorp"
    ],
    "name:swe_x_preferred":[
        "Klagstorp"
    ],
    "qs_pg:aaroncc":"SE",
    "qs_pg:gn_country":"SE",
    "qs_pg:gn_fcode":"PPL",
    "qs_pg:gn_pop":0,
    "qs_pg:name":"Klagstorp",
    "qs_pg:name_adm0":"Sverige",
    "qs_pg:name_adm1":"Sk\u00e5ne L\u00e4n",
    "qs_pg:photos":160,
    "qs_pg:photos_1k":32,
    "qs_pg:photos_9k":1,
    "qs_pg:photos_9r":4,
    "qs_pg:photos_all":160,
    "qs_pg:photos_sr":4,
    "qs_pg:pop_sr":0,
    "qs_pg:qs_pg_placetype":"locality",
    "qs_pg:qs_pg_placetype_gp":"Town",
    "qs_pg:woe_adm0":23424954,
    "woe:adm0_id":23424954,
    "woe:name_adm0":"Sverige",
    "woe:name_adm1":"Sk\u00e5ne L\u00e4n",
    "woe:placetype":"Town",
    "wof:name":"Klagstorp",
    "wof:placetype":"locality",
    "wof:population":548
},
  "geometry": {"coordinates":[13.37465,55.39296],"type":"Point"}
}