{
  "type": "Feature",
  "properties": {
    "gn:admin1_code":"3.0",
    "gn:admin2_code":"2181.0",
    "gn:asciiname":"On",
    "gn:country_code":"SE",
    "gn:dem":30,
    "gn:feature_class":"P",
    "gn:feature_code":"PPL",
    "gn:name":"\u00d6n",
    "gn:population":0,
    "gn:timezone":"Europe/Stockholm",
    "iso:country":"SE",
    "name:heb_x_preferred":[
        "\u05d0\u05d5\u05df"
    ],
    "name:nor_x_preferred":[
        "\u00d6n"
    ],
    "name:nor_x_variant":[
        "\u00d8n"
    ],
    "name:ukr_x_preferred":[
        "\u041e\u043d"
    ],
    "wof:name":"On",
    "wof:placetype":"locality"
},
  "geometry": {"coordinates":[16.76667,60.23333],"type":"Point"}
}