{
  "type": "Feature",
  "properties": {
    "gn:admin1_code":"28.0",
    "gn:admin2_code":"1441.0",
    "gn:asciiname":"Gullringsbo",
    "gn:country_code":"SE",
    "gn:dem":70,
    "gn:feature_class":"P",
    "gn:feature_code":"PPL",
    "gn:name":"Gullringsbo",
    "gn:population":0,
    "gn:timezone":"Europe/Stockholm",
    "iso:country":"SE",
    "wof:name":"Gullringsbo",
    "wof:placetype":"locality"
},
  "geometry": {"coordinates":[12.21667,57.75],"type":"Point"}
}