{
  "type": "Feature",
  "properties": {
    "gn:admin1_code":"28.0",
    "gn:admin2_code":"1499.0",
    "gn:asciiname":"Skorstorp",
    "gn:country_code":"SE",
    "gn:dem":229,
    "gn:feature_class":"P",
    "gn:feature_code":"PPL",
    "gn:name":"Sk\u00f6rstorp",
    "gn:population":0,
    "gn:timezone":"Europe/Stockholm",
    "iso:country":"SE",
    "name:nor_x_preferred":[
        "Sk\u00f6rstorp"
    ],
    "name:nor_x_variant":[
        "Sk\u00f8rstorp"
    ],
    "wof:name":"Skorstorp",
    "wof:placetype":"locality"
},
  "geometry": {"coordinates":[13.73333,58.13333000000001],"type":"Point"}
}