{
  "type": "Feature",
  "properties": {
    "gn:admin1_code":"22.0",
    "gn:admin2_code":"1785.0",
    "gn:asciiname":"Torverud",
    "gn:cc2":"SE",
    "gn:country_code":"SE",
    "gn:dem":67,
    "gn:feature_class":"P",
    "gn:feature_code":"PPL",
    "gn:name":"Torverud",
    "gn:population":0,
    "gn:timezone":"Europe/Stockholm",
    "iso:country":"SE",
    "name:und_x_variant":[
        "Torfverud",
        "Torverud"
    ],
    "wof:name":"Torverud",
    "wof:placetype":"locality"
},
  "geometry": {"coordinates":[13.15,59.05],"type":"Point"}
}