{
  "type": "Feature",
  "properties": {
    "gn:admin1_code":"2.0",
    "gn:admin2_code":"1080.0",
    "gn:asciiname":"Lyckeaborg",
    "gn:cc2":"SE",
    "gn:country_code":"SE",
    "gn:dem":40,
    "gn:feature_class":"P",
    "gn:feature_code":"PPL",
    "gn:name":"Lycke\u00e5borg",
    "gn:population":0,
    "gn:timezone":"Europe/Stockholm",
    "iso:country":"SE",
    "name:nld_x_preferred":[
        "Lycke\u00e5borg"
    ],
    "name:swe_x_preferred":[
        "Lycke\u00e5borg"
    ],
    "name:und_x_variant":[
        "Lycke\u00e5borgs Bruk",
        "Lycke\u00e5borg"
    ],
    "wof:name":"Lyckeaborg",
    "wof:placetype":"locality"
},
  "geometry": {"coordinates":[15.68333,56.21666999999999],"type":"Point"}
}