{
  "type": "Feature",
  "properties": {
    "gn:admin1_code":"26.0",
    "gn:admin2_code":"188.0",
    "gn:asciiname":"Soderhenninge",
    "gn:cc2":"SE",
    "gn:country_code":"SE",
    "gn:dem":24,
    "gn:feature_class":"P",
    "gn:feature_code":"PPL",
    "gn:name":"S\u00f6derhenninge",
    "gn:population":0,
    "gn:timezone":"Europe/Stockholm",
    "iso:country":"SE",
    "name:nor_x_preferred":[
        "S\u00f6derhenninge"
    ],
    "name:nor_x_variant":[
        "S\u00f8derhenninge"
    ],
    "name:und_x_variant":[
        "S\u00f6derh\u00e4nninge",
        "S\u00f6derhenninge"
    ],
    "wof:name":"Soderhenninge",
    "wof:placetype":"locality"
},
  "geometry": {"coordinates":[18.55,59.93333000000001],"type":"Point"}
}