{
  "type": "Feature",
  "properties": {
    "gn:admin1_code":"23.0",
    "gn:admin2_code":"2403.0",
    "gn:asciiname":"Storarmsjo",
    "gn:country_code":"SE",
    "gn:dem":241,
    "gn:feature_class":"P",
    "gn:feature_code":"PPL",
    "gn:name":"Storarmsj\u00f6",
    "gn:population":0,
    "gn:timezone":"Europe/Stockholm",
    "iso:country":"SE",
    "name:nor_x_preferred":[
        "Storarmsj\u00f6"
    ],
    "name:nor_x_variant":[
        "Storarmsj\u00f8"
    ],
    "wof:name":"Storarmsjo",
    "wof:placetype":"locality"
},
  "geometry": {"coordinates":[19.25,64.03333000000001],"type":"Point"}
}