{
  "type": "Feature",
  "properties": {
    "gn:gn_country":"SE",
    "gn:gn_fcode":"PPL",
    "gn:gn_pop":0,
    "iso:country":"SE",
    "name:bul_x_preferred":[
        "\u0412\u0430\u043b\u0435\u0432\u0438\u043a\u0435\u043d"
    ],
    "name:ceb_x_preferred":[
        "Valleviken"
    ],
    "name:deu_x_preferred":[
        "Valleviken"
    ],
    "name:eng_x_preferred":[
        "Valleviken"
    ],
    "name:fin_x_preferred":[
        "Valleviken"
    ],
    "name:nld_x_preferred":[
        "Valleviken"
    ],
    "name:swe_x_preferred":[
        "Valleviken"
    ],
    "qs_pg:aaroncc":"SE",
    "qs_pg:gn_country":"SE",
    "qs_pg:gn_fcode":"PPL",
    "qs_pg:gn_pop":0,
    "qs_pg:name":"Valleviken",
    "qs_pg:name_adm0":"Sverige",
    "qs_pg:name_adm1":"Gotlands L\u00e4n",
    "qs_pg:photos":257,
    "qs_pg:photos_1k":52,
    "qs_pg:photos_9k":1,
    "qs_pg:photos_9r":4,
    "qs_pg:photos_all":257,
    "qs_pg:photos_sr":5,
    "qs_pg:pop_sr":0,
    "qs_pg:qs_pg_placetype":"locality",
    "qs_pg:qs_pg_placetype_gp":"Town",
    "qs_pg:woe_adm0":23424954,
    "woe:adm0_id":23424954,
    "woe:name_adm0":"Sverige",
    "woe:name_adm1":"Gotlands L\u00e4n",
    "woe:placetype":"Town",
    "wof:name":"Valleviken",
    "wof:placetype":"locality"
},
  "geometry": {"coordinates":[18.95,57.78333],"type":"Point"}
}