{
  "type": "Feature",
  "properties": {
    "gn:admin1_code":"8.0",
    "gn:admin2_code":"682.0",
    "gn:asciiname":"Bjorkelund",
    "gn:country_code":"SE",
    "gn:dem":333,
    "gn:feature_class":"P",
    "gn:feature_code":"PPL",
    "gn:name":"Bj\u00f6rkelund",
    "gn:population":0,
    "gn:timezone":"Europe/Stockholm",
    "iso:country":"SE",
    "name:nor_x_preferred":[
        "Bj\u00f6rkelund"
    ],
    "name:nor_x_variant":[
        "Bj\u00f8rkelund"
    ],
    "name:und_x_variant":[
        "Bj\u00f6rkelund"
    ],
    "wof:name":"Bjorkelund",
    "wof:placetype":"locality"
},
  "geometry": {"coordinates":[14.51667,57.63333000000001],"type":"Point"}
}