{
  "type": "Feature",
  "properties": {
    "gn:admin1_code":"22.0",
    "gn:admin2_code":"1737.0",
    "gn:asciiname":"Hjallstad",
    "gn:country_code":"SE",
    "gn:dem":242,
    "gn:feature_class":"P",
    "gn:feature_code":"PPL",
    "gn:name":"Hj\u00e4llstad",
    "gn:population":0,
    "gn:timezone":"Europe/Stockholm",
    "iso:country":"SE",
    "wof:name":"Hjallstad",
    "wof:placetype":"locality"
},
  "geometry": {"coordinates":[13.09972,60.53306],"type":"Point"}
}