{
  "type": "Feature",
  "properties": {
    "gn:admin1_code":"3.0",
    "gn:admin2_code":"2180.0",
    "gn:asciiname":"Storsand",
    "gn:country_code":"SE",
    "gn:dem":18,
    "gn:feature_class":"P",
    "gn:feature_code":"PPL",
    "gn:name":"Storsand",
    "gn:population":0,
    "gn:timezone":"Europe/Stockholm",
    "iso:country":"SE",
    "name:nor_x_preferred":[
        "Storsand"
    ],
    "name:ron_x_preferred":[
        "Storsand"
    ],
    "name:spa_x_preferred":[
        "Storsand"
    ],
    "wof:name":"Storsand",
    "wof:placetype":"locality"
},
  "geometry": {"coordinates":[17.25,60.71666999999999],"type":"Point"}
}