{
  "type": "Feature",
  "properties": {
    "gn:admin1_code":"24.0",
    "gn:admin2_code":"2262.0",
    "gn:admin3_code":"226204.0",
    "gn:admin4_code":"2506.0",
    "gn:asciiname":"Stora Akero",
    "gn:cc2":"SE",
    "gn:country_code":"SE",
    "gn:dem":1,
    "gn:feature_class":"P",
    "gn:feature_code":"PPL",
    "gn:name":"Stora \u00c5ker\u00f6",
    "gn:population":0,
    "gn:timezone":"Europe/Stockholm",
    "iso:country":"SE",
    "name:nor_x_preferred":[
        "Stora \u00c5ker\u00f6"
    ],
    "name:nor_x_variant":[
        "Stora \u00c5ker\u00f8"
    ],
    "name:und_x_variant":[
        "St\u00f6rre Aker\u00f6",
        "Stora \u00c5ker\u00f6"
    ],
    "wof:name":"Stora Akero",
    "wof:placetype":"locality"
},
  "geometry": {"coordinates":[17.7188,62.41433000000001],"type":"Point"}
}