{
  "type": "Feature",
  "properties": {
    "gn:admin1_code":"14.0",
    "gn:admin2_code":"2580.0",
    "gn:asciiname":"Langnas",
    "gn:country_code":"SE",
    "gn:dem":46,
    "gn:feature_class":"P",
    "gn:feature_code":"PPL",
    "gn:name":"L\u00e5ngn\u00e4s",
    "gn:population":0,
    "gn:timezone":"Europe/Stockholm",
    "iso:country":"SE",
    "wof:name":"Langnas",
    "wof:placetype":"locality"
},
  "geometry": {"coordinates":[21.76667,65.58333],"type":"Point"}
}