{
  "type": "Feature",
  "properties": {
    "gn:admin1_code":"9.0",
    "gn:admin2_code":"881.0",
    "gn:asciiname":"Lisabo",
    "gn:country_code":"SE",
    "gn:dem":90,
    "gn:feature_class":"P",
    "gn:feature_code":"PPL",
    "gn:name":"Lisabo",
    "gn:population":0,
    "gn:timezone":"Europe/Stockholm",
    "iso:country":"SE",
    "wof:name":"Lisabo",
    "wof:placetype":"locality"
},
  "geometry": {"coordinates":[15.95,56.68333000000001],"type":"Point"}
}