{
  "type": "Feature",
  "properties": {
    "gn:admin1_code":"26.0",
    "gn:asciiname":"Bjorko",
    "gn:country_code":"SE",
    "gn:dem":12,
    "gn:feature_class":"P",
    "gn:feature_code":"PPL",
    "gn:name":"Bj\u00f6rk\u00f6",
    "gn:population":0,
    "gn:timezone":"Europe/Stockholm",
    "iso:country":"SE",
    "name:dan_x_preferred":[
        "Bj\u00f6rk\u00f6"
    ],
    "name:deu_x_preferred":[
        "Bj\u00f6rk\u00f6"
    ],
    "name:fra_x_preferred":[
        "Bj\u00f6rk\u00f6"
    ],
    "name:lat_x_preferred":[
        "Birca"
    ],
    "name:nld_x_preferred":[
        "Bj\u00f6rk\u00f6"
    ],
    "name:nor_x_preferred":[
        "Bj\u00f6rk\u00f6"
    ],
    "name:nor_x_variant":[
        "Bj\u00f8rk\u00f8"
    ],
    "name:pol_x_preferred":[
        "Bj\u00f6rk\u00f6"
    ],
    "name:spa_x_preferred":[
        "Bj\u00f6rk\u00f6"
    ],
    "name:swe_x_preferred":[
        "Bj\u00f6rk\u00f6"
    ],
    "name:und_x_variant":[
        "Bj\u00f6rk\u00f6"
    ],
    "name:zho_x_preferred":[
        "\u6bd4\u7d04\u514b\u5cf6"
    ],
    "wof:name":"Bjorko",
    "wof:placetype":"locality"
},
  "geometry": {"coordinates":[17.55,59.33333],"type":"Point"}
}