{
  "type": "Feature",
  "properties": {
    "gn:admin1_code":"3.0",
    "gn:admin2_code":"2161.0",
    "gn:asciiname":"Malungshed",
    "gn:country_code":"SE",
    "gn:dem":258,
    "gn:feature_class":"P",
    "gn:feature_code":"PPL",
    "gn:name":"Malungshed",
    "gn:population":0,
    "gn:timezone":"Europe/Stockholm",
    "iso:country":"SE",
    "wof:name":"Malungshed",
    "wof:placetype":"locality"
},
  "geometry": {"coordinates":[15.11667,61.61666999999999],"type":"Point"}
}