{
  "type": "Feature",
  "properties": {
    "gn:admin1_code":"18.0",
    "gn:admin2_code":"484.0",
    "gn:asciiname":"Roxnas",
    "gn:country_code":"SE",
    "gn:dem":14,
    "gn:feature_class":"P",
    "gn:feature_code":"PPL",
    "gn:name":"Roxn\u00e4s",
    "gn:population":0,
    "gn:timezone":"Europe/Stockholm",
    "iso:country":"SE",
    "wof:name":"Roxnas",
    "wof:placetype":"locality"
},
  "geometry": {"coordinates":[16.45,59.43333000000001],"type":"Point"}
}