{
  "type": "Feature",
  "properties": {
    "gn:admin1_code":"8.0",
    "gn:admin2_code":"686.0",
    "gn:asciiname":"Eldskog",
    "gn:country_code":"SE",
    "gn:dem":222,
    "gn:feature_class":"P",
    "gn:feature_code":"PPL",
    "gn:name":"Eldskog",
    "gn:population":0,
    "gn:timezone":"Europe/Stockholm",
    "iso:country":"SE",
    "wof:name":"Eldskog",
    "wof:placetype":"locality"
},
  "geometry": {"coordinates":[15.06667,57.61666999999999],"type":"Point"}
}