{
  "type": "Feature",
  "properties": {
    "gn:admin1_code":"3.0",
    "gn:admin2_code":"2101.0",
    "gn:asciiname":"Bole",
    "gn:country_code":"SE",
    "gn:dem":74,
    "gn:feature_class":"P",
    "gn:feature_code":"PPL",
    "gn:name":"B\u00f6le",
    "gn:population":0,
    "gn:timezone":"Europe/Stockholm",
    "iso:country":"SE",
    "name:ceb_x_preferred":[
        "Bole"
    ],
    "name:deu_x_preferred":[
        "Bole"
    ],
    "name:fra_x_preferred":[
        "Bole"
    ],
    "name:ita_x_preferred":[
        "Bole"
    ],
    "name:nld_x_preferred":[
        "Bole"
    ],
    "name:nor_x_preferred":[
        "B\u00f6le"
    ],
    "name:nor_x_variant":[
        "B\u00f8le"
    ],
    "name:pol_x_preferred":[
        "Bole"
    ],
    "name:swe_x_preferred":[
        "Bole"
    ],
    "name:und_x_variant":[
        "B\u00f6le"
    ],
    "name:wln_x_preferred":[
        "Bole"
    ],
    "wof:name":"Bole",
    "wof:placetype":"locality"
},
  "geometry": {"coordinates":[16.68333,60.88333000000001],"type":"Point"}
}