{
  "type": "Feature",
  "properties": {
    "gn:admin1_code":"24.0",
    "gn:admin2_code":"2260.0",
    "gn:admin3_code":"226004.0",
    "gn:admin4_code":"2502.0",
    "gn:asciiname":"Sodra Gullgard",
    "gn:country_code":"SE",
    "gn:dem":129,
    "gn:feature_class":"P",
    "gn:feature_code":"PPL",
    "gn:name":"S\u00f6dra Gullg\u00e5rd",
    "gn:population":0,
    "gn:timezone":"Europe/Stockholm",
    "iso:country":"SE",
    "name:nor_x_preferred":[
        "S\u00f6dra Gullg\u00e5rd"
    ],
    "name:nor_x_variant":[
        "S\u00f8dra Gullg\u00e5rd"
    ],
    "wof:name":"Sodra Gullgard",
    "wof:placetype":"locality"
},
  "geometry": {"coordinates":[16.09883,62.48308000000001],"type":"Point"}
}