{
  "type": "Feature",
  "properties": {
    "gn:admin1_code":"28.0",
    "gn:admin2_code":"1465.0",
    "gn:asciiname":"Oja",
    "gn:country_code":"SE",
    "gn:dem":189,
    "gn:feature_class":"P",
    "gn:feature_code":"PPL",
    "gn:name":"\u00d6ja",
    "gn:population":0,
    "gn:timezone":"Europe/Stockholm",
    "iso:country":"SE",
    "name:ceb_x_preferred":[
        "Oja"
    ],
    "name:deu_x_preferred":[
        "Oja"
    ],
    "name:est_x_preferred":[
        "Oja"
    ],
    "name:fra_x_preferred":[
        "Oja"
    ],
    "name:lav_x_preferred":[
        "Oja"
    ],
    "name:nds_x_preferred":[
        "Oja"
    ],
    "name:nor_x_preferred":[
        "\u00d6ja"
    ],
    "name:nor_x_variant":[
        "\u00d8ja"
    ],
    "name:pol_x_preferred":[
        "Oja"
    ],
    "name:por_x_preferred":[
        "Oja"
    ],
    "name:swe_x_preferred":[
        "Oja"
    ],
    "wof:name":"Oja",
    "wof:placetype":"locality"
},
  "geometry": {"coordinates":[12.91667,57.48333],"type":"Point"}
}