{
  "type": "Feature",
  "properties": {
    "gn:gn_country":"SE",
    "gn:gn_fcode":"PPL",
    "gn:gn_pop":475,
    "gn:population":475,
    "iso:country":"SE",
    "name:dut_x_preferred":[
        "R\u00e5da"
    ],
    "name:eng_x_preferred":[
        "R\u00e5da"
    ],
    "name:jpn_x_preferred":[
        "\u30ed\u30fc\u30c0"
    ],
    "name:nan_x_preferred":[
        "R\u00e5da"
    ],
    "name:nno_x_preferred":[
        "R\u00e5da"
    ],
    "name:nob_x_preferred":[
        "R\u00e5da"
    ],
    "name:swe_x_preferred":[
        "R\u00e5da"
    ],
    "qs_pg:aaroncc":"SE",
    "qs_pg:gn_country":"SE",
    "qs_pg:gn_fcode":"PPL",
    "qs_pg:gn_pop":475,
    "qs_pg:name":"R\u00e5da",
    "qs_pg:photos_9r":0,
    "qs_pg:photos_sr":0,
    "qs_pg:pop_sr":2,
    "qs_pg:qs_pg_placetype":"locality",
    "wof:name":"R\u00e5da",
    "wof:placetype":"locality",
    "wof:population":475
},
  "geometry": {"coordinates":[13.41667,60.15],"type":"Point"}
}