{
  "type": "Feature",
  "properties": {
    "gn:admin1_code":"14.0",
    "gn:admin2_code":"2560.0",
    "gn:asciiname":"Laduberg",
    "gn:country_code":"SE",
    "gn:dem":103,
    "gn:feature_class":"P",
    "gn:feature_code":"PPL",
    "gn:name":"Laduberg",
    "gn:population":0,
    "gn:timezone":"Europe/Stockholm",
    "iso:country":"SE",
    "wof:name":"Laduberg",
    "wof:placetype":"locality"
},
  "geometry": {"coordinates":[21.08333,65.71666999999999],"type":"Point"}
}