{
  "type": "Feature",
  "properties": {
    "gn:admin1_code":"23.0",
    "gn:admin2_code":"2425.0",
    "gn:asciiname":"Sorfors",
    "gn:cc2":"SE",
    "gn:country_code":"SE",
    "gn:dem":385,
    "gn:feature_class":"P",
    "gn:feature_code":"PPL",
    "gn:name":"S\u00f6rfors",
    "gn:population":0,
    "gn:timezone":"Europe/Stockholm",
    "iso:country":"SE",
    "name:nor_x_preferred":[
        "S\u00f6rfors"
    ],
    "name:nor_x_variant":[
        "S\u00f8rfors"
    ],
    "name:und_x_variant":[
        "S\u00f6derfors",
        "S\u00f6rfors"
    ],
    "wof:name":"Sorfors",
    "wof:placetype":"locality"
},
  "geometry": {"coordinates":[15.46667,64.61667],"type":"Point"}
}