{
  "type": "Feature",
  "properties": {
    "gn:admin1_code":"24.0",
    "gn:admin2_code":"2283.0",
    "gn:admin3_code":"228303.0",
    "gn:admin4_code":"2462.0",
    "gn:asciiname":"Bullerbo",
    "gn:country_code":"SE",
    "gn:dem":192,
    "gn:feature_class":"P",
    "gn:feature_code":"PPL",
    "gn:name":"Bullerbo",
    "gn:population":0,
    "gn:timezone":"Europe/Stockholm",
    "iso:country":"SE",
    "wof:name":"Bullerbo",
    "wof:placetype":"locality"
},
  "geometry": {"coordinates":[17.0973,62.99316],"type":"Point"}
}