{
  "type": "Feature",
  "properties": {
    "gn:gn_country":"SE",
    "gn:gn_fcode":"PPL",
    "gn:gn_pop":453,
    "gn:population":453,
    "iso:country":"SE",
    "name:fao_x_preferred":[
        "Onslunda"
    ],
    "name:ita_x_preferred":[
        "Onslunda"
    ],
    "name:nld_x_preferred":[
        "Onslunda"
    ],
    "name:nno_x_preferred":[
        "Onslunda"
    ],
    "name:nor_x_preferred":[
        "Onslunda"
    ],
    "name:swe_x_preferred":[
        "Onslunda"
    ],
    "qs_pg:aaroncc":"SE",
    "qs_pg:gn_country":"SE",
    "qs_pg:gn_fcode":"PPL",
    "qs_pg:gn_pop":453,
    "qs_pg:name":"Onslunda",
    "qs_pg:name_adm0":"Sverige",
    "qs_pg:name_adm1":"Uppsala L\u00e4n",
    "qs_pg:photos_9r":0,
    "qs_pg:photos_sr":0,
    "qs_pg:pop_sr":2,
    "qs_pg:qs_pg_placetype":"locality",
    "qs_pg:qs_pg_placetype_gp":"Town",
    "qs_pg:woe_adm0":23424954,
    "woe:adm0_id":23424954,
    "woe:name_adm0":"Sverige",
    "woe:name_adm1":"Uppsala L\u00e4n",
    "woe:placetype":"Town",
    "wof:name":"Onslunda",
    "wof:placetype":"locality",
    "wof:population":453
},
  "geometry": {"coordinates":[17.63333,60.01667],"type":"Point"}
}