{
  "type": "Feature",
  "properties": {
    "gn:admin1_code":"27.0",
    "gn:admin2_code":"1256.0",
    "gn:asciiname":"Svinaberga",
    "gn:country_code":"SE",
    "gn:dem":69,
    "gn:feature_class":"P",
    "gn:feature_code":"PPL",
    "gn:name":"Svinaberga",
    "gn:population":0,
    "gn:timezone":"Europe/Stockholm",
    "iso:country":"SE",
    "wof:name":"Svinaberga",
    "wof:placetype":"locality"
},
  "geometry": {"coordinates":[14.11667,56.25],"type":"Point"}
}