{
  "type": "Feature",
  "properties": {
    "gn:admin1_code":"24.0",
    "gn:admin2_code":"2281.0",
    "gn:asciiname":"Allsta",
    "gn:country_code":"SE",
    "gn:dem":76,
    "gn:feature_class":"P",
    "gn:feature_code":"PPL",
    "gn:name":"Allsta",
    "gn:population":0,
    "gn:timezone":"Europe/Stockholm",
    "iso:country":"SE",
    "wof:name":"Allsta",
    "wof:placetype":"locality"
},
  "geometry": {"coordinates":[17.23333,62.31667],"type":"Point"}
}