{
  "type": "Feature",
  "properties": {
    "gn:admin1_code":"26.0",
    "gn:admin2_code":"188.0",
    "gn:asciiname":"Storangsbacken",
    "gn:country_code":"SE",
    "gn:dem":15,
    "gn:feature_class":"P",
    "gn:feature_code":"PPL",
    "gn:name":"Stor\u00e4ngsbacken",
    "gn:population":0,
    "gn:timezone":"Europe/Stockholm",
    "iso:country":"SE",
    "wof:name":"Storangsbacken",
    "wof:placetype":"locality"
},
  "geometry": {"coordinates":[19.01667,59.88333000000001],"type":"Point"}
}