{
  "type": "Feature",
  "properties": {
    "gn:country":"SE",
    "gn:fcode":"PPL",
    "gn:population":226,
    "iso:country":"SE",
    "name:bul_x_preferred":[
        "\u0413\u043e\u0442\u043d\u0435"
    ],
    "name:ceb_x_preferred":[
        "Gottne"
    ],
    "name:dan_x_preferred":[
        "Gottne"
    ],
    "name:deu_x_preferred":[
        "Gottne"
    ],
    "name:eng_x_preferred":[
        "Gottne"
    ],
    "name:fra_x_preferred":[
        "Gottne"
    ],
    "name:gle_x_preferred":[
        "Gottne"
    ],
    "name:ita_x_preferred":[
        "Gottne"
    ],
    "name:lld_x_preferred":[
        "Gottne"
    ],
    "name:nan_x_preferred":[
        "Gottne"
    ],
    "name:nld_x_preferred":[
        "Gottne"
    ],
    "name:nno_x_preferred":[
        "Gottne"
    ],
    "name:nob_x_preferred":[
        "Gottne"
    ],
    "name:pol_x_preferred":[
        "Gottne"
    ],
    "name:spa_x_preferred":[
        "Gottne"
    ],
    "name:swe_x_preferred":[
        "Gottne"
    ],
    "qs_pg:aaroncc":"SE",
    "qs_pg:gn_country":"SE",
    "qs_pg:gn_fcode":"PPL",
    "qs_pg:gn_pop":226,
    "qs_pg:name":"Gottne",
    "qs_pg:name_adm0":"Sverige",
    "qs_pg:name_adm1":"V\u00e4sternorrlands L\u00e4n",
    "qs_pg:photos_9k":1,
    "qs_pg:photos_9r":1,
    "qs_pg:photos_all":1,
    "qs_pg:photos_sr":0,
    "qs_pg:pop_sr":2,
    "qs_pg:qs_pg_placetype":"locality",
    "qs_pg:qs_pg_placetype_gp":"Town",
    "qs_pg:woe_adm0":23424954,
    "woe:adm0_id":23424954,
    "woe:name_adm0":"Sverige",
    "woe:name_adm1":"V\u00e4sternorrlands L\u00e4n",
    "woe:placetype":"Town",
    "wof:name":"Gottne",
    "wof:placetype":"locality",
    "wof:population":212
},
  "geometry": {"coordinates":[18.42991,63.43249],"type":"Point"}
}