{
  "type": "Feature",
  "properties": {
    "gn:admin1_code":"12.0",
    "gn:admin2_code":"781.0",
    "gn:asciiname":"Flahult",
    "gn:country_code":"SE",
    "gn:dem":193,
    "gn:feature_class":"P",
    "gn:feature_code":"PPL",
    "gn:name":"Flahult",
    "gn:population":0,
    "gn:timezone":"Europe/Stockholm",
    "iso:country":"SE",
    "wof:name":"Flahult",
    "wof:placetype":"locality"
},
  "geometry": {"coordinates":[13.81667,56.96666999999999],"type":"Point"}
}