{
  "type": "Feature",
  "properties": {
    "gn:admin1_code":"16.0",
    "gn:admin2_code":"582.0",
    "gn:asciiname":"Yxeltorp",
    "gn:country_code":"SE",
    "gn:dem":50,
    "gn:feature_class":"P",
    "gn:feature_code":"PPL",
    "gn:name":"Yxeltorp",
    "gn:population":0,
    "gn:timezone":"Europe/Stockholm",
    "iso:country":"SE",
    "wof:name":"Yxeltorp",
    "wof:placetype":"locality"
},
  "geometry": {"coordinates":[16.56667,58.41667],"type":"Point"}
}