{
  "type": "Feature",
  "properties": {
    "gn:admin1_code":"22.0",
    "gn:admin2_code":"1765.0",
    "gn:asciiname":"Backen",
    "gn:country_code":"SE",
    "gn:dem":172,
    "gn:feature_class":"P",
    "gn:feature_code":"PPL",
    "gn:name":"B\u00e4cken",
    "gn:population":0,
    "gn:timezone":"Europe/Stockholm",
    "iso:country":"SE",
    "name:fas_x_preferred":[
        "\u0628\u06a9\u06a9\u0646"
    ],
    "name:swe_x_preferred":[
        "Backen"
    ],
    "wof:name":"Backen",
    "wof:placetype":"locality"
},
  "geometry": {"coordinates":[12.31667,59.28333000000001],"type":"Point"}
}