{
  "type": "Feature",
  "properties": {
    "gn:admin1_code":"28.0",
    "gn:admin2_code":"1466.0",
    "gn:asciiname":"Attorp",
    "gn:country_code":"SE",
    "gn:dem":181,
    "gn:feature_class":"P",
    "gn:feature_code":"PPL",
    "gn:name":"Attorp",
    "gn:population":0,
    "gn:timezone":"Europe/Stockholm",
    "iso:country":"SE",
    "wof:name":"Attorp",
    "wof:placetype":"locality"
},
  "geometry": {"coordinates":[13.03333,57.95],"type":"Point"}
}