{
  "type": "Feature",
  "properties": {
    "iso:country":"SE",
    "qs_pg:aaroncc":"SE",
    "qs_pg:name":"Otteid",
    "qs_pg:name_adm0":"Norge",
    "qs_pg:name_adm1":"\u00d8stfold Fylke",
    "qs_pg:photos":627,
    "qs_pg:photos_1k":127,
    "qs_pg:photos_9k":3,
    "qs_pg:photos_9r":5,
    "qs_pg:photos_all":627,
    "qs_pg:photos_sr":8,
    "qs_pg:pop_sr":0,
    "qs_pg:qs_pg_placetype":"locality",
    "qs_pg:qs_pg_placetype_gp":"Town",
    "qs_pg:woe_adm0":23424910,
    "woe:adm0_id":23424910,
    "woe:name_adm0":"Norge",
    "woe:name_adm1":"\u00d8stfold Fylke",
    "woe:placetype":"Town",
    "wof:name":"Otteid",
    "wof:placetype":"locality"
},
  "geometry": {"coordinates":[11.839249,59.361742],"type":"Point"}
}