{
  "type": "Feature",
  "properties": {
    "gn:admin1_code":"2.0",
    "gn:admin2_code":"1060.0",
    "gn:asciiname":"Ronas",
    "gn:country_code":"SE",
    "gn:dem":129,
    "gn:feature_class":"P",
    "gn:feature_code":"PPL",
    "gn:name":"R\u00f6n\u00e5s",
    "gn:population":0,
    "gn:timezone":"Europe/Stockholm",
    "iso:country":"SE",
    "name:nor_x_preferred":[
        "R\u00f6n\u00e5s"
    ],
    "name:nor_x_variant":[
        "R\u00f8n\u00e5s"
    ],
    "wof:name":"Ronas",
    "wof:placetype":"locality"
},
  "geometry": {"coordinates":[14.56667,56.36666999999999],"type":"Point"}
}