{
  "type": "Feature",
  "properties": {
    "gn:admin1_code":"27.0",
    "gn:admin2_code":"1292.0",
    "gn:asciiname":"Kaglenas",
    "gn:country_code":"SE",
    "gn:dem":15,
    "gn:feature_class":"P",
    "gn:feature_code":"PPL",
    "gn:name":"K\u00e4glen\u00e4s",
    "gn:population":0,
    "gn:timezone":"Europe/Stockholm",
    "iso:country":"SE",
    "wof:name":"Kaglenas",
    "wof:placetype":"locality"
},
  "geometry": {"coordinates":[12.86667,56.29167],"type":"Point"}
}