{
  "type": "Feature",
  "properties": {
    "gn:admin1_code":"5.0",
    "gn:admin2_code":"980.0",
    "gn:admin3_code":"98073.0",
    "gn:admin4_code":"967.0",
    "gn:asciiname":"Tomtbod",
    "gn:country_code":"SE",
    "gn:dem":1,
    "gn:feature_class":"P",
    "gn:feature_code":"PPL",
    "gn:name":"Tomtbod",
    "gn:population":0,
    "gn:timezone":"Europe/Stockholm",
    "iso:country":"SE",
    "name:und_x_variant":[
        "Tomteboda",
        "Tomtbod"
    ],
    "wof:name":"Tomtbod",
    "wof:placetype":"locality"
},
  "geometry": {"coordinates":[18.53308,57.18725],"type":"Point"}
}