{
  "type": "Feature",
  "properties": {
    "gn:admin1_code":"10.0",
    "gn:admin2_code":"2081.0",
    "gn:asciiname":"Gylltagt",
    "gn:country_code":"SE",
    "gn:dem":143,
    "gn:feature_class":"P",
    "gn:feature_code":"PPL",
    "gn:name":"Gyllt\u00e4gt",
    "gn:population":0,
    "gn:timezone":"Europe/Stockholm",
    "iso:country":"SE",
    "wof:name":"Gylltagt",
    "wof:placetype":"locality"
},
  "geometry": {"coordinates":[15.38333,60.45],"type":"Point"}
}