{
  "type": "Feature",
  "properties": {
    "gn:gn_country":"SE",
    "gn:gn_fcode":"PPL",
    "gn:gn_pop":0,
    "iso:country":"SE",
    "name:dan_x_preferred":[
        "St\u00f6mne"
    ],
    "name:deu_x_preferred":[
        "St\u00f6mne"
    ],
    "name:eng_x_preferred":[
        "St\u00f6mne"
    ],
    "name:fra_x_preferred":[
        "St\u00f6mne"
    ],
    "name:nds_x_preferred":[
        "St\u00f6mne"
    ],
    "name:nld_x_preferred":[
        "St\u00f6mne"
    ],
    "name:nno_x_preferred":[
        "St\u00f6mne"
    ],
    "name:nob_x_preferred":[
        "St\u00f6mne"
    ],
    "name:nor_x_preferred":[
        "St\u00f8mne"
    ],
    "name:nor_x_variant":[
        "St\u00f6mne"
    ],
    "name:swe_x_preferred":[
        "St\u00f6mne"
    ],
    "qs_pg:aaroncc":"SE",
    "qs_pg:gn_country":"SE",
    "qs_pg:gn_fcode":"PPL",
    "qs_pg:gn_pop":0,
    "qs_pg:name":"St\u00f6mne",
    "qs_pg:name_adm0":"Sverige",
    "qs_pg:name_adm1":"V\u00e4rmlands L\u00e4n",
    "qs_pg:photos":109,
    "qs_pg:photos_1k":22,
    "qs_pg:photos_9k":1,
    "qs_pg:photos_9r":3,
    "qs_pg:photos_all":109,
    "qs_pg:photos_sr":3,
    "qs_pg:pop_sr":0,
    "qs_pg:qs_pg_placetype":"locality",
    "qs_pg:qs_pg_placetype_gp":"Town",
    "qs_pg:woe_adm0":23424954,
    "woe:adm0_id":23424954,
    "woe:name_adm0":"Sverige",
    "woe:name_adm1":"V\u00e4rmlands L\u00e4n",
    "woe:placetype":"Town",
    "wof:name":"St\u00f6mne",
    "wof:placetype":"locality"
},
  "geometry": {"coordinates":[12.76667,59.43333],"type":"Point"}
}