{
  "type": "Feature",
  "properties": {
    "gn:gn_country":"SE",
    "gn:gn_fcode":"PPL",
    "gn:gn_pop":301,
    "gn:population":301,
    "iso:country":"SE",
    "name:fra_x_preferred":[
        "\u00c4ng"
    ],
    "name:ita_x_preferred":[
        "\u00c4ng"
    ],
    "name:nld_x_preferred":[
        "\u00c4ng"
    ],
    "name:nno_x_preferred":[
        "\u00c4ng"
    ],
    "name:nor_x_preferred":[
        "\u00c4ng"
    ],
    "name:swe_x_preferred":[
        "\u00c4ng"
    ],
    "qs_pg:aaroncc":"SE",
    "qs_pg:gn_country":"SE",
    "qs_pg:gn_fcode":"PPL",
    "qs_pg:gn_pop":301,
    "qs_pg:name":"\u00c4ng",
    "qs_pg:photos_9r":0,
    "qs_pg:photos_sr":0,
    "qs_pg:pop_sr":2,
    "qs_pg:qs_pg_placetype":"locality",
    "wof:name":"\u00c4ng",
    "wof:placetype":"locality",
    "wof:population":301
},
  "geometry": {"coordinates":[11.96667,59.03333],"type":"Point"}
}