{
  "type": "Feature",
  "properties": {
    "gn:admin1_code":"21.0",
    "gn:admin2_code":"380.0",
    "gn:asciiname":"Nolmyra",
    "gn:country_code":"SE",
    "gn:dem":41,
    "gn:feature_class":"P",
    "gn:feature_code":"PPL",
    "gn:name":"Nolmyra",
    "gn:population":0,
    "gn:timezone":"Europe/Stockholm",
    "iso:country":"SE",
    "wof:name":"Nolmyra",
    "wof:placetype":"locality"
},
  "geometry": {"coordinates":[17.35,60.11666999999999],"type":"Point"}
}