{
  "type": "Feature",
  "properties": {
    "gn:admin1_code":"12.0",
    "gn:admin2_code":"760.0",
    "gn:asciiname":"Stora Blotskog",
    "gn:country_code":"SE",
    "gn:dem":244,
    "gn:feature_class":"P",
    "gn:feature_code":"PPL",
    "gn:name":"Stora Bl\u00f6tskog",
    "gn:population":0,
    "gn:timezone":"Europe/Stockholm",
    "iso:country":"SE",
    "name:nor_x_preferred":[
        "Stora Bl\u00f6tskog"
    ],
    "name:nor_x_variant":[
        "Stora Bl\u00f8tskog"
    ],
    "wof:name":"Stora Blotskog",
    "wof:placetype":"locality"
},
  "geometry": {"coordinates":[15.48333,57.03333000000001],"type":"Point"}
}