{
  "type": "Feature",
  "properties": {
    "iso:country":"SE",
    "name:swe_x_preferred":[
        "V\u00e4ssings\u00f6"
    ],
    "wof:name":"Vassingso",
    "wof:placetype":"neighbourhood"
},
  "geometry": {"coordinates":[11.84608900576526,57.66424838134776],"type":"Point"}
}