{
  "type": "Feature",
  "properties": {
    "gn:admin1_code":"9.0",
    "gn:admin2_code":"883.0",
    "gn:asciiname":"Lofta",
    "gn:country_code":"SE",
    "gn:dem":17,
    "gn:feature_class":"P",
    "gn:feature_code":"PPL",
    "gn:name":"Lofta",
    "gn:population":0,
    "gn:timezone":"Europe/Stockholm",
    "iso:country":"SE",
    "name:nld_x_preferred":[
        "Lofta"
    ],
    "name:swe_x_preferred":[
        "Lofta"
    ],
    "wof:name":"Lofta",
    "wof:placetype":"locality"
},
  "geometry": {"coordinates":[16.46667,57.93306],"type":"Point"}
}