{
  "type": "Feature",
  "properties": {
    "gn:admin1_code":"14.0",
    "gn:admin2_code":"2580.0",
    "gn:asciiname":"Brannan",
    "gn:country_code":"SE",
    "gn:dem":16,
    "gn:feature_class":"P",
    "gn:feature_code":"PPL",
    "gn:name":"Br\u00e4nnan",
    "gn:population":0,
    "gn:timezone":"Europe/Stockholm",
    "iso:country":"SE",
    "wof:name":"Brannan",
    "wof:placetype":"locality"
},
  "geometry": {"coordinates":[22.1081,65.679],"type":"Point"}
}