{
  "type": "Feature",
  "properties": {
    "gn:country":"SE",
    "gn:fcode":"ADM3",
    "gn:population":6750,
    "iso:country":"SE",
    "name:dan_x_preferred":[
        "Folk\u00e4rna"
    ],
    "name:deu_x_preferred":[
        "Folk\u00e4rna"
    ],
    "name:eng_x_preferred":[
        "Folk\u00e4rna"
    ],
    "name:fra_x_preferred":[
        "Folk\u00e4rna"
    ],
    "name:nds_x_preferred":[
        "Folk\u00e4rna"
    ],
    "name:nld_x_preferred":[
        "Folk\u00e4rna"
    ],
    "name:nno_x_preferred":[
        "Folk\u00e4rna"
    ],
    "name:nob_x_preferred":[
        "Folk\u00e4rna"
    ],
    "name:swe_x_preferred":[
        "Folk\u00e4rna"
    ],
    "qs_pg:aaroncc":"SE",
    "qs_pg:gn_country":"SE",
    "qs_pg:gn_fcode":"ADM3",
    "qs_pg:gn_pop":6750,
    "qs_pg:name":"Folkarna",
    "qs_pg:name_adm0":"Sverige",
    "qs_pg:name_adm1":"Dalarnas L\u00e4n",
    "qs_pg:photos_9k":1,
    "qs_pg:photos_9r":1,
    "qs_pg:photos_all":1,
    "qs_pg:photos_sr":0,
    "qs_pg:pop_sr":5,
    "qs_pg:qs_pg_placetype":"locality",
    "qs_pg:qs_pg_placetype_gp":"Town",
    "qs_pg:woe_adm0":23424954,
    "woe:adm0_id":23424954,
    "woe:name_adm0":"Sverige",
    "woe:name_adm1":"Dalarnas L\u00e4n",
    "woe:placetype":"Town",
    "wof:name":"Folkarna",
    "wof:placetype":"locality",
    "wof:population":6750
},
  "geometry": {"coordinates":[16.31667,60.15],"type":"Point"}
}