{
  "type": "Feature",
  "properties": {
    "gn:admin1_code":"8.0",
    "gn:admin2_code":"662.0",
    "gn:asciiname":"Fagerhult",
    "gn:country_code":"SE",
    "gn:dem":164,
    "gn:feature_class":"P",
    "gn:feature_code":"PPL",
    "gn:name":"F\u00e4gerhult",
    "gn:population":0,
    "gn:timezone":"Europe/Stockholm",
    "iso:country":"SE",
    "name:ceb_x_preferred":[
        "Fagerhult"
    ],
    "name:fin_x_preferred":[
        "Fagerhult"
    ],
    "name:fra_x_preferred":[
        "Fagerhult"
    ],
    "name:nld_x_preferred":[
        "Fagerhult"
    ],
    "name:swe_x_preferred":[
        "Fagerhult"
    ],
    "wof:name":"Fagerhult",
    "wof:placetype":"locality"
},
  "geometry": {"coordinates":[13.35,57.15],"type":"Point"}
}