{
  "type": "Feature",
  "properties": {
    "gn:admin1_code":"27.0",
    "gn:admin2_code":"1284.0",
    "gn:admin3_code":"128403.0",
    "gn:admin4_code":"1392.0",
    "gn:asciiname":"Viken",
    "gn:country_code":"SE",
    "gn:dem":7,
    "gn:feature_class":"P",
    "gn:feature_code":"PPL",
    "gn:name":"Viken",
    "gn:population":4489,
    "gn:timezone":"Europe/Stockholm",
    "iso:country":"SE",
    "name:ceb_x_preferred":[
        "Viken"
    ],
    "name:dan_x_preferred":[
        "Viken"
    ],
    "name:deu_x_preferred":[
        "Viken"
    ],
    "name:fin_x_preferred":[
        "Viken"
    ],
    "name:fra_x_preferred":[
        "Viken"
    ],
    "name:ita_x_preferred":[
        "Viken"
    ],
    "name:nld_x_preferred":[
        "Viken"
    ],
    "name:nor_x_preferred":[
        "Viken"
    ],
    "name:swe_x_preferred":[
        "Viken"
    ],
    "wof:name":"Viken",
    "wof:placetype":"locality",
    "wof:population":4489
},
  "geometry": {"coordinates":[12.57429,56.15063000000001],"type":"Point"}
}