{
  "type": "Feature",
  "properties": {
    "gn:admin1_code":"10.0",
    "gn:admin2_code":"2021.0",
    "gn:asciiname":"Overborg",
    "gn:cc2":"SE",
    "gn:country_code":"SE",
    "gn:dem":238,
    "gn:feature_class":"P",
    "gn:feature_code":"PPL",
    "gn:name":"\u00d6verborg",
    "gn:population":0,
    "gn:timezone":"Europe/Stockholm",
    "iso:country":"SE",
    "name:nor_x_preferred":[
        "\u00d6verborg"
    ],
    "name:nor_x_variant":[
        "\u00d8verborg"
    ],
    "name:und_x_variant":[
        "\u00d6fverborg",
        "\u00d6verborg"
    ],
    "wof:name":"Overborg",
    "wof:placetype":"locality"
},
  "geometry": {"coordinates":[14.48333,60.48333],"type":"Point"}
}