{
  "type": "Feature",
  "properties": {
    "gn:admin1_code":"15.0",
    "gn:admin2_code":"1863.0",
    "gn:asciiname":"Norralgen",
    "gn:cc2":"SE",
    "gn:country_code":"SE",
    "gn:dem":192,
    "gn:feature_class":"P",
    "gn:feature_code":"PPL",
    "gn:name":"Norr\u00e4lgen",
    "gn:population":0,
    "gn:timezone":"Europe/Stockholm",
    "iso:country":"SE",
    "name:und_x_variant":[
        "Norrelgen",
        "Norr\u00e4lgen"
    ],
    "wof:name":"Norralgen",
    "wof:placetype":"locality"
},
  "geometry": {"coordinates":[14.58333,59.81667],"type":"Point"}
}