{
  "type": "Feature",
  "properties": {
    "gn:admin1_code":"3.0",
    "gn:admin2_code":"2101.0",
    "gn:asciiname":"Norrbo",
    "gn:country_code":"SE",
    "gn:dem":75,
    "gn:feature_class":"P",
    "gn:feature_code":"PPL",
    "gn:name":"Norrbo",
    "gn:population":0,
    "gn:timezone":"Europe/Stockholm",
    "iso:country":"SE",
    "wof:name":"Norrbo",
    "wof:placetype":"locality"
},
  "geometry": {"coordinates":[16.61667000000001,60.95],"type":"Point"}
}