{
  "type": "Feature",
  "properties": {
    "gn:admin1_code":"23.0",
    "gn:admin2_code":"2422.0",
    "gn:asciiname":"Giltjaur",
    "gn:cc2":"SE",
    "gn:country_code":"SE",
    "gn:dem":437,
    "gn:feature_class":"P",
    "gn:feature_code":"PPL",
    "gn:name":"Giltjaur",
    "gn:population":0,
    "gn:timezone":"Europe/Stockholm",
    "iso:country":"SE",
    "name:und_x_variant":[
        "Jiltjaur",
        "Giltjaur"
    ],
    "wof:name":"Giltjaur",
    "wof:placetype":"locality"
},
  "geometry": {"coordinates":[16.96667,65.53333000000001],"type":"Point"}
}