{
  "type": "Feature",
  "properties": {
    "gn:admin1_code":"10.0",
    "gn:admin2_code":"2084.0",
    "gn:asciiname":"Basinge",
    "gn:country_code":"SE",
    "gn:dem":83,
    "gn:feature_class":"P",
    "gn:feature_code":"PPL",
    "gn:name":"B\u00e4singe",
    "gn:population":0,
    "gn:timezone":"Europe/Stockholm",
    "iso:country":"SE",
    "wof:name":"Basinge",
    "wof:placetype":"locality"
},
  "geometry": {"coordinates":[16.36667000000001,60.13333000000001],"type":"Point"}
}