{
  "type": "Feature",
  "properties": {
    "gn:admin1_code":"8.0",
    "gn:admin2_code":"685.0",
    "gn:asciiname":"Skinnberga",
    "gn:cc2":"SE",
    "gn:country_code":"SE",
    "gn:dem":173,
    "gn:feature_class":"P",
    "gn:feature_code":"PPL",
    "gn:name":"Skinnberga",
    "gn:population":0,
    "gn:timezone":"Europe/Stockholm",
    "iso:country":"SE",
    "name:und_x_variant":[
        "Skinberga",
        "Skinnberga"
    ],
    "wof:name":"Skinnberga",
    "wof:placetype":"locality"
},
  "geometry": {"coordinates":[15.16667,57.48333],"type":"Point"}
}