{
  "type": "Feature",
  "properties": {
    "gn:admin1_code":"7.0",
    "gn:admin2_code":"2380.0",
    "gn:asciiname":"Hornsjobole",
    "gn:country_code":"SE",
    "gn:dem":366,
    "gn:feature_class":"P",
    "gn:feature_code":"PPL",
    "gn:name":"Hornsj\u00f6b\u00f6le",
    "gn:population":0,
    "gn:timezone":"Europe/Stockholm",
    "iso:country":"SE",
    "name:nor_x_preferred":[
        "Hornsj\u00f6b\u00f6le"
    ],
    "name:nor_x_variant":[
        "Hornsj\u00f8b\u00f8le"
    ],
    "name:und_x_variant":[
        "Hornsj\u00f6b\u00f6le"
    ],
    "wof:name":"Hornsjobole",
    "wof:placetype":"locality"
},
  "geometry": {"coordinates":[14.95,63.05],"type":"Point"}
}