{
  "type": "Feature",
  "properties": {
    "gn:admin1_code":"14.0",
    "gn:admin2_code":"2583.0",
    "gn:asciiname":"Sipola",
    "gn:country_code":"SE",
    "gn:dem":45,
    "gn:feature_class":"P",
    "gn:feature_code":"PPL",
    "gn:name":"Sipola",
    "gn:population":0,
    "gn:timezone":"Europe/Stockholm",
    "iso:country":"SE",
    "name:fit_x_preferred":[
        "Sipola"
    ],
    "name:swe_x_preferred":[
        "Skogsk\u00e4rr"
    ],
    "wof:name":"Sipola",
    "wof:placetype":"locality"
},
  "geometry": {"coordinates":[23.90036,66.1438],"type":"Point"}
}