{
  "type": "Feature",
  "properties": {
    "gn:admin1_code":"24",
    "gn:admin2_code":"2281.0",
    "gn:admin3_code":"228105.0",
    "gn:admin4_code":"2500.0",
    "gn:asciiname":"Norasjoe",
    "gn:country_code":"SE",
    "gn:dem":161,
    "gn:feature_class":"P",
    "gn:feature_code":"PPL",
    "gn:name":"Norasj\u00f6",
    "gn:population":0,
    "gn:timezone":"Europe/Stockholm",
    "iso:country":"SE",
    "wof:name":"Norasjoe",
    "wof:placetype":"locality"
},
  "geometry": {"coordinates":[16.95036,62.49462],"type":"Point"}
}