{
  "type": "Feature",
  "properties": {
    "gn:admin1_code":"8.0",
    "gn:admin2_code":"683.0",
    "gn:asciiname":"Almhult",
    "gn:country_code":"SE",
    "gn:dem":195,
    "gn:feature_class":"P",
    "gn:feature_code":"PPL",
    "gn:name":"\u00c4lmhult",
    "gn:population":0,
    "gn:timezone":"Europe/Stockholm",
    "iso:country":"SE",
    "wof:name":"Almhult",
    "wof:placetype":"locality"
},
  "geometry": {"coordinates":[14.28333,57.23333],"type":"Point"}
}