{
  "type": "Feature",
  "properties": {
    "gn:admin1_code":"9.0",
    "gn:admin2_code":"880.0",
    "gn:asciiname":"Ugglerum",
    "gn:country_code":"SE",
    "gn:dem":32,
    "gn:feature_class":"P",
    "gn:feature_code":"PPL",
    "gn:name":"Ugglerum",
    "gn:population":0,
    "gn:timezone":"Europe/Stockholm",
    "iso:country":"SE",
    "wof:name":"Ugglerum",
    "wof:placetype":"locality"
},
  "geometry": {"coordinates":[16.21667,56.76667],"type":"Point"}
}