{
  "type": "Feature",
  "properties": {
    "gn:admin1_code":"15.0",
    "gn:admin2_code":"1880.0",
    "gn:asciiname":"Halglot",
    "gn:country_code":"SE",
    "gn:dem":51,
    "gn:feature_class":"P",
    "gn:feature_code":"PPL",
    "gn:name":"H\u00e4lgl\u00f6t",
    "gn:population":0,
    "gn:timezone":"Europe/Stockholm",
    "iso:country":"SE",
    "wof:name":"Halglot",
    "wof:placetype":"locality"
},
  "geometry": {"coordinates":[15.56667,59.35],"type":"Point"}
}