{
  "type": "Feature",
  "properties": {
    "gn:admin1_code":"7.0",
    "gn:admin2_code":"2361.0",
    "gn:asciiname":"Valmasen",
    "gn:country_code":"SE",
    "gn:dem":567,
    "gn:feature_class":"P",
    "gn:feature_code":"PPL",
    "gn:name":"Valm\u00e5sen",
    "gn:population":0,
    "gn:timezone":"Europe/Stockholm",
    "iso:country":"SE",
    "wof:name":"Valmasen",
    "wof:placetype":"locality"
},
  "geometry": {"coordinates":[12.76667,62.45],"type":"Point"}
}