{
  "type": "Feature",
  "properties": {
    "gn:admin1_code":"27.0",
    "gn:admin2_code":"1292.0",
    "gn:admin3_code":"129209.0",
    "gn:admin4_code":"1024.0",
    "gn:asciiname":"Barkakra",
    "gn:country_code":"SE",
    "gn:dem":33,
    "gn:feature_class":"P",
    "gn:feature_code":"PPL",
    "gn:name":"Bark\u00e5kra",
    "gn:population":0,
    "gn:timezone":"Europe/Stockholm",
    "iso:country":"SE",
    "wof:name":"Barkakra",
    "wof:placetype":"locality"
},
  "geometry": {"coordinates":[12.83581,56.29494],"type":"Point"}
}