{
  "type": "Feature",
  "properties": {
    "gn:admin1_code":"24.0",
    "gn:admin2_code":"2280.0",
    "gn:asciiname":"Froland",
    "gn:country_code":"SE",
    "gn:dem":103,
    "gn:feature_class":"P",
    "gn:feature_code":"PPL",
    "gn:name":"Fr\u00f6land",
    "gn:population":0,
    "gn:timezone":"Europe/Stockholm",
    "iso:country":"SE",
    "name:bar_x_preferred":[
        "Froland"
    ],
    "name:bpy_x_preferred":[
        "\u09ab\u09cd\u09b0\u09cb\u09b2\u09c7\u09a8\u09cd\u09a1"
    ],
    "name:cat_x_preferred":[
        "Froland"
    ],
    "name:ceb_x_preferred":[
        "Froland"
    ],
    "name:dan_x_preferred":[
        "Froland"
    ],
    "name:deu_x_preferred":[
        "Froland"
    ],
    "name:epo_x_preferred":[
        "Froland"
    ],
    "name:est_x_preferred":[
        "Frolandi vald"
    ],
    "name:eus_x_preferred":[
        "Froland"
    ],
    "name:fin_x_preferred":[
        "Froland"
    ],
    "name:fra_x_preferred":[
        "Froland"
    ],
    "name:hun_x_preferred":[
        "Froland"
    ],
    "name:ita_x_preferred":[
        "Froland"
    ],
    "name:jav_x_preferred":[
        "Froland"
    ],
    "name:lat_x_preferred":[
        "Froland"
    ],
    "name:lim_x_preferred":[
        "Froland"
    ],
    "name:msa_x_preferred":[
        "Froland"
    ],
    "name:nds_x_preferred":[
        "Kommun Froland"
    ],
    "name:nld_x_preferred":[
        "Froland"
    ],
    "name:nno_x_preferred":[
        "Froland kommune"
    ],
    "name:nor_x_preferred":[
        "Fr\u00f6land"
    ],
    "name:nor_x_variant":[
        "Fr\u00f8land",
        "Froland"
    ],
    "name:pol_x_preferred":[
        "Froland"
    ],
    "name:por_x_preferred":[
        "Froland"
    ],
    "name:ron_x_preferred":[
        "Froland"
    ],
    "name:rus_x_preferred":[
        "\u0424\u0440\u043e\u043b\u0430\u043d\u043d"
    ],
    "name:slv_x_preferred":[
        "Froland"
    ],
    "name:sme_x_preferred":[
        "Froland"
    ],
    "name:spa_x_preferred":[
        "Froland"
    ],
    "name:sqi_x_preferred":[
        "Froland"
    ],
    "name:swe_x_preferred":[
        "Frolands kommun"
    ],
    "name:und_x_variant":[
        "Fr\u00f6land"
    ],
    "name:vie_x_preferred":[
        "Froland"
    ],
    "name:war_x_preferred":[
        "Froland"
    ],
    "name:zho_x_preferred":[
        "\u5f17\u7f85\u862d"
    ],
    "wof:name":"Froland",
    "wof:placetype":"locality"
},
  "geometry": {"coordinates":[17.88332999999999,62.61666999999999],"type":"Point"}
}