{
  "type": "Feature",
  "properties": {
    "gn:admin1_code":"24.0",
    "gn:admin2_code":"2280.0",
    "gn:asciiname":"Froland",
    "gn:country_code":"SE",
    "gn:dem":103,
    "gn:feature_class":"P",
    "gn:feature_code":"PPL",
    "gn:name":"Fr\u00f6land",
    "gn:population":0,
    "gn:timezone":"Europe/Stockholm",
    "iso:country":"SE",
    "name:nor_x_preferred":[
        "Fr\u00f6land"
    ],
    "name:nor_x_variant":[
        "Fr\u00f8land"
    ],
    "name:und_x_variant":[
        "Fr\u00f6land"
    ],
    "wof:name":"Froland",
    "wof:placetype":"locality"
},
  "geometry": {"coordinates":[17.88332999999999,62.61666999999999],"type":"Point"}
}