{
  "type": "Feature",
  "properties": {
    "gn:admin1_code":"9.0",
    "gn:admin2_code":"882.0",
    "gn:asciiname":"Blomsterhult",
    "gn:country_code":"SE",
    "gn:dem":36,
    "gn:feature_class":"P",
    "gn:feature_code":"PPL",
    "gn:name":"Blomsterhult",
    "gn:population":0,
    "gn:timezone":"Europe/Stockholm",
    "iso:country":"SE",
    "wof:name":"Blomsterhult",
    "wof:placetype":"locality"
},
  "geometry": {"coordinates":[16.41667,57.45],"type":"Point"}
}