{
  "type": "Feature",
  "properties": {
    "gn:admin1_code":"8.0",
    "gn:admin2_code":"685.0",
    "gn:asciiname":"Hokhult",
    "gn:country_code":"SE",
    "gn:dem":245,
    "gn:feature_class":"P",
    "gn:feature_code":"PPL",
    "gn:name":"H\u00f6khult",
    "gn:population":0,
    "gn:timezone":"Europe/Stockholm",
    "iso:country":"SE",
    "name:nor_x_preferred":[
        "H\u00f6khult"
    ],
    "name:nor_x_variant":[
        "H\u00f8khult"
    ],
    "name:und_x_variant":[
        "H\u00f6khult"
    ],
    "wof:name":"Hokhult",
    "wof:placetype":"locality"
},
  "geometry": {"coordinates":[14.86667,57.28333000000001],"type":"Point"}
}