{
  "type": "Feature",
  "properties": {
    "gn:admin1_code":"14.0",
    "gn:admin2_code":"2505.0",
    "gn:asciiname":"Renviken",
    "gn:country_code":"SE",
    "gn:dem":414,
    "gn:feature_class":"P",
    "gn:feature_code":"PPL",
    "gn:name":"Renviken",
    "gn:population":0,
    "gn:timezone":"Europe/Stockholm",
    "iso:country":"SE",
    "name:sju_x_preferred":[
        "Sarvade"
    ],
    "name:swe_x_preferred":[
        "Renviken"
    ],
    "wof:name":"Renviken",
    "wof:placetype":"locality"
},
  "geometry": {"coordinates":[18.53584,65.65205999999999],"type":"Point"}
}