{
  "type": "Feature",
  "properties": {
    "gn:admin1_code":"6.0",
    "gn:admin2_code":"1381.0",
    "gn:asciiname":"Sodra Mellby",
    "gn:country_code":"SE",
    "gn:dem":13,
    "gn:feature_class":"P",
    "gn:feature_code":"PPL",
    "gn:name":"S\u00f6dra Mellby",
    "gn:population":0,
    "gn:timezone":"Europe/Stockholm",
    "iso:country":"SE",
    "name:nor_x_preferred":[
        "S\u00f6dra Mellby"
    ],
    "name:nor_x_variant":[
        "S\u00f8dra Mellby"
    ],
    "name:und_x_variant":[
        "S\u00f6dra Mellby"
    ],
    "wof:name":"Sodra Mellby",
    "wof:placetype":"locality"
},
  "geometry": {"coordinates":[12.95,56.48333],"type":"Point"}
}