{
  "type": "Feature",
  "properties": {
    "gn:admin1_code":"24.0",
    "gn:admin2_code":"2281.0",
    "gn:admin3_code":"228111.0",
    "gn:admin4_code":"2473.0",
    "gn:asciiname":"Kavsta",
    "gn:country_code":"SE",
    "gn:dem":123,
    "gn:feature_class":"P",
    "gn:feature_code":"PPL",
    "gn:name":"K\u00e4vsta",
    "gn:population":0,
    "gn:timezone":"Europe/Stockholm",
    "iso:country":"SE",
    "wof:name":"Kavsta",
    "wof:placetype":"locality"
},
  "geometry": {"coordinates":[17.12442,62.56815],"type":"Point"}
}