{
  "type": "Feature",
  "properties": {
    "gn:admin1_code":"14.0",
    "gn:admin2_code":"2580.0",
    "gn:asciiname":"Borjelslandet",
    "gn:country_code":"SE",
    "gn:dem":16,
    "gn:feature_class":"P",
    "gn:feature_code":"PPL",
    "gn:name":"B\u00f6rjelslandet",
    "gn:population":0,
    "gn:timezone":"Europe/Stockholm",
    "iso:country":"SE",
    "name:nor_x_preferred":[
        "B\u00f6rjelslandet"
    ],
    "name:nor_x_variant":[
        "B\u00f8rjelslandet"
    ],
    "wof:name":"Borjelslandet",
    "wof:placetype":"locality"
},
  "geometry": {"coordinates":[22.15,65.78333000000001],"type":"Point"}
}