{
  "type": "Feature",
  "properties": {
    "gn:admin1_code":"12.0",
    "gn:admin2_code":"760.0",
    "gn:asciiname":"Mada",
    "gn:country_code":"SE",
    "gn:dem":209,
    "gn:feature_class":"P",
    "gn:feature_code":"PPL",
    "gn:name":"Mada",
    "gn:population":0,
    "gn:timezone":"Europe/Stockholm",
    "iso:country":"SE",
    "name:fra_x_preferred":[
        "Mada"
    ],
    "wof:name":"Mada",
    "wof:placetype":"locality"
},
  "geometry": {"coordinates":[15.46667,57.13333000000001],"type":"Point"}
}