{
  "type": "Feature",
  "properties": {
    "gn:admin1_code":"3.0",
    "gn:admin2_code":"2184.0",
    "gn:asciiname":"Baggalve",
    "gn:cc2":"SE",
    "gn:country_code":"SE",
    "gn:dem":205,
    "gn:feature_class":"P",
    "gn:feature_code":"PPL",
    "gn:name":"Bagg\u00e4lve",
    "gn:population":0,
    "gn:timezone":"Europe/Stockholm",
    "iso:country":"SE",
    "name:und_x_variant":[
        "Bagg\u00e4lfve",
        "Bagg\u00e4lve"
    ],
    "wof:name":"Baggalve",
    "wof:placetype":"locality"
},
  "geometry": {"coordinates":[16.38332999999999,61.86666999999999],"type":"Point"}
}