{
  "type": "Feature",
  "properties": {
    "gn:admin1_code":"7.0",
    "gn:admin2_code":"2361.0",
    "gn:asciiname":"Osterhallan",
    "gn:country_code":"SE",
    "gn:dem":475,
    "gn:feature_class":"P",
    "gn:feature_code":"PPL",
    "gn:name":"\u00d6sterh\u00e5llan",
    "gn:population":0,
    "gn:timezone":"Europe/Stockholm",
    "iso:country":"SE",
    "name:nor_x_preferred":[
        "\u00d6sterh\u00e5llan"
    ],
    "name:nor_x_variant":[
        "\u00d8sterh\u00e5llan"
    ],
    "wof:name":"Osterhallan",
    "wof:placetype":"locality"
},
  "geometry": {"coordinates":[14.43306,62.18306],"type":"Point"}
}