{
  "type": "Feature",
  "properties": {
    "gn:admin1_code":"8.0",
    "gn:admin2_code":"680.0",
    "gn:asciiname":"Klackarp",
    "gn:country_code":"SE",
    "gn:dem":269,
    "gn:feature_class":"P",
    "gn:feature_code":"PPL",
    "gn:name":"Klackarp",
    "gn:population":0,
    "gn:timezone":"Europe/Stockholm",
    "iso:country":"SE",
    "wof:name":"Klackarp",
    "wof:placetype":"locality"
},
  "geometry": {"coordinates":[14.43333,57.73333],"type":"Point"}
}