{
  "type": "Feature",
  "properties": {
    "gn:admin1_code":"22.0",
    "gn:admin2_code":"1780.0",
    "gn:asciiname":"Sodra Radom",
    "gn:cc2":"SE",
    "gn:country_code":"SE",
    "gn:dem":138,
    "gn:feature_class":"P",
    "gn:feature_code":"PPL",
    "gn:name":"S\u00f6dra R\u00e5dom",
    "gn:population":0,
    "gn:timezone":"Europe/Stockholm",
    "iso:country":"SE",
    "name:nor_x_preferred":[
        "S\u00f6dra R\u00e5dom"
    ],
    "name:nor_x_variant":[
        "S\u00f8dra R\u00e5dom"
    ],
    "name:und_x_variant":[
        "S\u00f6dra R\u00e5um"
    ],
    "wof:name":"Sodra Radom",
    "wof:placetype":"locality"
},
  "geometry": {"coordinates":[13.65,59.61666999999999],"type":"Point"}
}