{
  "type": "Feature",
  "properties": {
    "gn:admin1_code":"25.0",
    "gn:admin2_code":"1962.0",
    "gn:asciiname":"Tuntorpet",
    "gn:country_code":"SE",
    "gn:dem":142,
    "gn:feature_class":"P",
    "gn:feature_code":"PPL",
    "gn:name":"Tuntorpet",
    "gn:population":0,
    "gn:timezone":"Europe/Stockholm",
    "iso:country":"SE",
    "wof:name":"Tuntorpet",
    "wof:placetype":"locality"
},
  "geometry": {"coordinates":[15.98333,60.08333],"type":"Point"}
}