{
  "type": "Feature",
  "properties": {
    "gn:admin1_code":"28.0",
    "gn:admin2_code":"1493.0",
    "gn:asciiname":"Frolunda",
    "gn:country_code":"SE",
    "gn:dem":68,
    "gn:feature_class":"P",
    "gn:feature_code":"PPL",
    "gn:name":"Fr\u00f6lunda",
    "gn:population":0,
    "gn:timezone":"Europe/Stockholm",
    "iso:country":"SE",
    "name:nor_x_preferred":[
        "Fr\u00f6lunda"
    ],
    "name:nor_x_variant":[
        "Fr\u00f8lunda"
    ],
    "name:und_x_variant":[
        "Fr\u00f6lunda"
    ],
    "wof:name":"Frolunda",
    "wof:placetype":"locality"
},
  "geometry": {"coordinates":[13.86667,58.58333],"type":"Point"}
}