{
  "type": "Feature",
  "properties": {
    "gn:admin1_code":"23.0",
    "gn:admin2_code":"2425.0",
    "gn:asciiname":"Lavsjo",
    "gn:cc2":"SE",
    "gn:country_code":"SE",
    "gn:dem":334,
    "gn:feature_class":"P",
    "gn:feature_code":"PPL",
    "gn:name":"Lavsj\u00f6",
    "gn:population":0,
    "gn:timezone":"Europe/Stockholm",
    "iso:country":"SE",
    "name:nor_x_preferred":[
        "Lavsj\u00f6"
    ],
    "name:nor_x_variant":[
        "Lavsj\u00f8"
    ],
    "name:und_x_variant":[
        "Lafsj\u00f6",
        "Lavsj\u00f6n"
    ],
    "wof:name":"Lavsjo",
    "wof:placetype":"locality"
},
  "geometry": {"coordinates":[16.65,64.18333],"type":"Point"}
}