{
  "type": "Feature",
  "properties": {
    "gn:admin1_code":"10.0",
    "gn:admin2_code":"2082.0",
    "gn:admin3_code":"208201.0",
    "gn:admin4_code":"2384.0",
    "gn:asciiname":"Aspnas",
    "gn:country_code":"SE",
    "gn:dem":221,
    "gn:feature_class":"P",
    "gn:feature_code":"PPL",
    "gn:name":"Aspn\u00e4s",
    "gn:population":0,
    "gn:timezone":"Europe/Stockholm",
    "iso:country":"SE",
    "wof:name":"Aspnas",
    "wof:placetype":"locality"
},
  "geometry": {"coordinates":[15.65543,60.33234],"type":"Point"}
}