{
  "type": "Feature",
  "properties": {
    "gn:admin1_code":"23.0",
    "gn:asciiname":"Gallejaur",
    "gn:country_code":"SE",
    "gn:dem":422,
    "gn:feature_class":"P",
    "gn:feature_code":"PPL",
    "gn:name":"Gallejaur",
    "gn:population":0,
    "gn:timezone":"Europe/Stockholm",
    "iso:country":"SE",
    "wof:name":"Gallejaur",
    "wof:placetype":"locality"
},
  "geometry": {"coordinates":[19.43333,65.16667],"type":"Point"}
}