{
  "type": "Feature",
  "properties": {
    "gn:admin1_code":"9.0",
    "gn:admin2_code":"860.0",
    "gn:asciiname":"Trandenas",
    "gn:country_code":"SE",
    "gn:dem":133,
    "gn:feature_class":"P",
    "gn:feature_code":"PPL",
    "gn:name":"Tr\u00e4nden\u00e4s",
    "gn:population":0,
    "gn:timezone":"Europe/Stockholm",
    "iso:country":"SE",
    "wof:name":"Trandenas",
    "wof:placetype":"locality"
},
  "geometry": {"coordinates":[15.76667,57.21666999999999],"type":"Point"}
}