{
  "type": "Feature",
  "properties": {
    "gn:admin1_code":"14.0",
    "gn:admin2_code":"2518.0",
    "gn:asciiname":"Mukkajarvi",
    "gn:country_code":"SE",
    "gn:dem":148,
    "gn:feature_class":"P",
    "gn:feature_code":"PPL",
    "gn:name":"Mukkaj\u00e4rvi",
    "gn:population":0,
    "gn:timezone":"Europe/Stockholm",
    "iso:country":"SE",
    "wof:name":"Mukkajarvi",
    "wof:placetype":"locality"
},
  "geometry": {"coordinates":[23.15,66.61667],"type":"Point"}
}