{
  "type": "Feature",
  "properties": {
    "gn:admin1_code":"10.0",
    "gn:admin2_code":"2083.0",
    "gn:asciiname":"Nordanby",
    "gn:country_code":"SE",
    "gn:dem":117,
    "gn:feature_class":"P",
    "gn:feature_code":"PPL",
    "gn:name":"Nordanby",
    "gn:population":0,
    "gn:timezone":"Europe/Stockholm",
    "iso:country":"SE",
    "wof:name":"Nordanby",
    "wof:placetype":"locality"
},
  "geometry": {"coordinates":[15.86667,60.31667],"type":"Point"}
}