{
  "type": "Feature",
  "properties": {
    "gn:admin1_code":"9.0",
    "gn:admin2_code":"861.0",
    "gn:asciiname":"Gelebo",
    "gn:country_code":"SE",
    "gn:dem":14,
    "gn:feature_class":"P",
    "gn:feature_code":"PPL",
    "gn:name":"Gelebo",
    "gn:population":0,
    "gn:timezone":"Europe/Stockholm",
    "iso:country":"SE",
    "wof:name":"Gelebo",
    "wof:placetype":"locality"
},
  "geometry": {"coordinates":[16.41667,57.08333],"type":"Point"}
}