{
  "type": "Feature",
  "properties": {
    "gn:admin1_code":"6.0",
    "gn:admin2_code":"1381.0",
    "gn:asciiname":"Bastena",
    "gn:country_code":"SE",
    "gn:dem":78,
    "gn:feature_class":"P",
    "gn:feature_code":"PPL",
    "gn:name":"Bastena",
    "gn:population":0,
    "gn:timezone":"Europe/Stockholm",
    "iso:country":"SE",
    "wof:name":"Bastena",
    "wof:placetype":"locality"
},
  "geometry": {"coordinates":[13.23333,56.38333000000001],"type":"Point"}
}