{
  "type": "Feature",
  "properties": {
    "gn:admin1_code":"15.0",
    "gn:admin2_code":"1882.0",
    "gn:asciiname":"Sodra Svaldre",
    "gn:country_code":"SE",
    "gn:dem":144,
    "gn:feature_class":"P",
    "gn:feature_code":"PPL",
    "gn:name":"S\u00f6dra Svaldre",
    "gn:population":0,
    "gn:timezone":"Europe/Stockholm",
    "iso:country":"SE",
    "name:nor_x_preferred":[
        "S\u00f6dra Svaldre"
    ],
    "name:nor_x_variant":[
        "S\u00f8dra Svaldre"
    ],
    "name:und_x_variant":[
        "S\u00f6dra Svaldre"
    ],
    "wof:name":"Sodra Svaldre",
    "wof:placetype":"locality"
},
  "geometry": {"coordinates":[15.15,58.93333000000001],"type":"Point"}
}