{
  "type": "Feature",
  "properties": {
    "gn:admin1_code":"14.0",
    "gn:admin2_code":"2583.0",
    "gn:asciiname":"Sandviken",
    "gn:cc2":"SE",
    "gn:country_code":"SE",
    "gn:dem":6,
    "gn:feature_class":"P",
    "gn:feature_code":"PPL",
    "gn:name":"Sandviken",
    "gn:population":0,
    "gn:timezone":"Europe/Stockholm",
    "iso:country":"SE",
    "name:rus_x_preferred":[
        "\u0421\u0430\u043d\u0434\u0432\u0438\u043a\u0435\u043d"
    ],
    "name:und_x_variant":[
        "Sandvik",
        "Sandviken"
    ],
    "wof:name":"Sandviken",
    "wof:placetype":"locality"
},
  "geometry": {"coordinates":[23.76667,65.73333000000001],"type":"Point"}
}