{
  "type": "Feature",
  "properties": {
    "gn:admin1_code":"10.0",
    "gn:admin2_code":"2084.0",
    "gn:asciiname":"Ostra Strandmora",
    "gn:country_code":"SE",
    "gn:dem":50,
    "gn:feature_class":"P",
    "gn:feature_code":"PPL",
    "gn:name":"\u00d6stra Strandmora",
    "gn:population":0,
    "gn:timezone":"Europe/Stockholm",
    "iso:country":"SE",
    "name:nor_x_preferred":[
        "\u00d6stra Strandmora"
    ],
    "name:nor_x_variant":[
        "\u00d8stra Strandmora"
    ],
    "name:und_x_variant":[
        "\u00d6stra Strandmora"
    ],
    "wof:name":"Ostra Strandmora",
    "wof:placetype":"locality"
},
  "geometry": {"coordinates":[16.41667,60.16667],"type":"Point"}
}