{
  "type": "Feature",
  "properties": {
    "gn:admin1_code":"3.0",
    "gn:admin2_code":"2161.0",
    "gn:asciiname":"Vallsberget",
    "gn:country_code":"SE",
    "gn:dem":441,
    "gn:feature_class":"P",
    "gn:feature_code":"PPL",
    "gn:name":"Vallsberget",
    "gn:population":0,
    "gn:timezone":"Europe/Stockholm",
    "iso:country":"SE",
    "wof:name":"Vallsberget",
    "wof:placetype":"locality"
},
  "geometry": {"coordinates":[15.31667,61.88333000000001],"type":"Point"}
}