{
  "type": "Feature",
  "properties": {
    "gn:admin1_code":"24.0",
    "gn:admin2_code":"2283.0",
    "gn:asciiname":"Ottsjo",
    "gn:country_code":"SE",
    "gn:dem":231,
    "gn:feature_class":"P",
    "gn:feature_code":"PPL",
    "gn:name":"Ottsj\u00f6",
    "gn:population":0,
    "gn:timezone":"Europe/Stockholm",
    "iso:country":"SE",
    "name:nor_x_preferred":[
        "Ottsj\u00f6"
    ],
    "name:nor_x_variant":[
        "Ottsj\u00f8"
    ],
    "name:und_x_variant":[
        "Ottsj\u00f6"
    ],
    "wof:name":"Ottsjo",
    "wof:placetype":"locality"
},
  "geometry": {"coordinates":[17.03333,63.55],"type":"Point"}
}