{
  "type": "Feature",
  "properties": {
    "gn:admin1_code":"21.0",
    "gn:admin2_code":"380.0",
    "gn:asciiname":"Kumla",
    "gn:country_code":"SE",
    "gn:dem":42,
    "gn:feature_class":"P",
    "gn:feature_code":"PPL",
    "gn:name":"Kumla",
    "gn:population":0,
    "gn:timezone":"Europe/Stockholm",
    "iso:country":"SE",
    "name:ara_x_preferred":[
        "\u0643\u0648\u0645\u0644\u0627"
    ],
    "name:bul_x_preferred":[
        "\u041a\u0443\u043c\u043b\u0430"
    ],
    "name:ceb_x_preferred":[
        "Kumla"
    ],
    "name:dan_x_preferred":[
        "Kumla"
    ],
    "name:deu_x_preferred":[
        "Kumla"
    ],
    "name:est_x_preferred":[
        "Kumla"
    ],
    "name:fao_x_preferred":[
        "Kumla"
    ],
    "name:fas_x_preferred":[
        "\u06a9\u0648\u0645\u0644\u0647"
    ],
    "name:fin_x_preferred":[
        "Kumla"
    ],
    "name:fra_x_preferred":[
        "Kumla"
    ],
    "name:hrv_x_preferred":[
        "Kumla"
    ],
    "name:hun_x_preferred":[
        "Kumla"
    ],
    "name:ind_x_preferred":[
        "Kumla"
    ],
    "name:isl_x_preferred":[
        "Kumla"
    ],
    "name:ita_x_preferred":[
        "Kumla"
    ],
    "name:kor_x_preferred":[
        "\ucff0\ub77c"
    ],
    "name:lit_x_preferred":[
        "Kumla"
    ],
    "name:nld_x_preferred":[
        "Kumla"
    ],
    "name:nno_x_preferred":[
        "Kumla"
    ],
    "name:nor_x_preferred":[
        "Kumla"
    ],
    "name:pol_x_preferred":[
        "Kumla"
    ],
    "name:por_x_preferred":[
        "Kumla"
    ],
    "name:ron_x_preferred":[
        "Kumla"
    ],
    "name:rus_x_preferred":[
        "\u041a\u0443\u043c\u043b\u0430"
    ],
    "name:sqi_x_preferred":[
        "Kumla"
    ],
    "name:srp_x_preferred":[
        "\u041a\u0443\u043c\u043b\u0430"
    ],
    "name:swe_x_preferred":[
        "Kumla"
    ],
    "name:tur_x_preferred":[
        "Kumla"
    ],
    "name:ukr_x_preferred":[
        "\u041a\u0443\u043c\u043b\u0430"
    ],
    "name:zho_x_preferred":[
        "\u5eab\u59c6\u62c9"
    ],
    "wof:name":"Kumla",
    "wof:placetype":"locality"
},
  "geometry": {"coordinates":[17.45,59.76667],"type":"Point"}
}