{
  "type": "Feature",
  "properties": {
    "gn:admin1_code":"25.0",
    "gn:admin2_code":"1982.0",
    "gn:asciiname":"Ennora",
    "gn:country_code":"SE",
    "gn:dem":130,
    "gn:feature_class":"P",
    "gn:feature_code":"PPL",
    "gn:name":"Ennora",
    "gn:population":0,
    "gn:timezone":"Europe/Stockholm",
    "iso:country":"SE",
    "wof:name":"Ennora",
    "wof:placetype":"locality"
},
  "geometry": {"coordinates":[15.95,59.96666999999999],"type":"Point"}
}