{
  "type": "Feature",
  "properties": {
    "gn:admin1_code":"14.0",
    "gn:admin2_code":"2518.0",
    "gn:asciiname":"Aapua",
    "gn:country_code":"SE",
    "gn:dem":187,
    "gn:feature_class":"P",
    "gn:feature_code":"PPL",
    "gn:name":"Aapua",
    "gn:population":0,
    "gn:timezone":"Europe/Stockholm",
    "iso:country":"SE",
    "name:est_x_preferred":[
        "Aapua"
    ],
    "name:ita_x_preferred":[
        "Aapua"
    ],
    "name:nld_x_preferred":[
        "Aapua"
    ],
    "name:swe_x_preferred":[
        "Aapua"
    ],
    "wof:name":"Aapua",
    "wof:placetype":"locality"
},
  "geometry": {"coordinates":[23.52938,66.85819000000001],"type":"Point"}
}