{
  "type": "Feature",
  "properties": {
    "gn:admin1_code":"10.0",
    "gn:admin2_code":"2039.0",
    "gn:asciiname":"Ringnas",
    "gn:country_code":"SE",
    "gn:dem":458,
    "gn:feature_class":"P",
    "gn:feature_code":"PPL",
    "gn:name":"Ringn\u00e4s",
    "gn:population":0,
    "gn:timezone":"Europe/Stockholm",
    "iso:country":"SE",
    "wof:name":"Ringnas",
    "wof:placetype":"locality"
},
  "geometry": {"coordinates":[13.36667,61.26667],"type":"Point"}
}