{
  "type": "Feature",
  "properties": {
    "gn:admin1_code":"7.0",
    "gn:admin2_code":"2313.0",
    "gn:asciiname":"Havsnas",
    "gn:cc2":"SE",
    "gn:country_code":"SE",
    "gn:dem":288,
    "gn:feature_class":"P",
    "gn:feature_code":"PPL",
    "gn:name":"Havsn\u00e4s",
    "gn:population":0,
    "gn:timezone":"Europe/Stockholm",
    "iso:country":"SE",
    "name:und_x_variant":[
        "Hafsn\u00e4set",
        "Havsn\u00e4s"
    ],
    "wof:name":"Havsnas",
    "wof:placetype":"locality"
},
  "geometry": {"coordinates":[15.81667,64.08333],"type":"Point"}
}