{
  "type": "Feature",
  "properties": {
    "gn:admin1_code":"24.0",
    "gn:admin2_code":"2262.0",
    "gn:asciiname":"Lillroten",
    "gn:country_code":"SE",
    "gn:dem":203,
    "gn:feature_class":"P",
    "gn:feature_code":"PPL",
    "gn:name":"Lillroten",
    "gn:population":0,
    "gn:timezone":"Europe/Stockholm",
    "iso:country":"SE",
    "wof:name":"Lillroten",
    "wof:placetype":"locality"
},
  "geometry": {"coordinates":[17.53333,62.63333000000001],"type":"Point"}
}