{
  "type": "Feature",
  "properties": {
    "gn:admin1_code":"7.0",
    "gn:admin2_code":"2313.0",
    "gn:asciiname":"Rolandstorp",
    "gn:country_code":"SE",
    "gn:dem":347,
    "gn:feature_class":"P",
    "gn:feature_code":"PPL",
    "gn:name":"Rolandstorp",
    "gn:population":0,
    "gn:timezone":"Europe/Stockholm",
    "iso:country":"SE",
    "wof:name":"Rolandstorp",
    "wof:placetype":"locality"
},
  "geometry": {"coordinates":[14.13333,64.65000000000001],"type":"Point"}
}