{
  "type": "Feature",
  "properties": {
    "gn:admin1_code":"15.0",
    "gn:admin2_code":"1881.0",
    "gn:asciiname":"Orsta",
    "gn:country_code":"SE",
    "gn:dem":42,
    "gn:feature_class":"P",
    "gn:feature_code":"PPL",
    "gn:name":"\u00d6rsta",
    "gn:population":0,
    "gn:timezone":"Europe/Stockholm",
    "iso:country":"SE",
    "name:nor_x_preferred":[
        "\u00d6rsta"
    ],
    "name:nor_x_variant":[
        "\u00d8rsta"
    ],
    "name:und_x_variant":[
        "\u00d6rsta"
    ],
    "wof:name":"Orsta",
    "wof:placetype":"locality"
},
  "geometry": {"coordinates":[15.16667,59.11666999999999],"type":"Point"}
}