{
  "type": "Feature",
  "properties": {
    "gn:admin1_code":"8.0",
    "gn:admin2_code":"604.0",
    "gn:asciiname":"Lommaryd",
    "gn:country_code":"SE",
    "gn:dem":237,
    "gn:feature_class":"P",
    "gn:feature_code":"PPL",
    "gn:name":"Lommaryd",
    "gn:population":0,
    "gn:timezone":"Europe/Stockholm",
    "iso:country":"SE",
    "wof:name":"Lommaryd",
    "wof:placetype":"locality"
},
  "geometry": {"coordinates":[14.75,57.88333000000001],"type":"Point"}
}