{
  "type": "Feature",
  "properties": {
    "gn:admin1_code":"28.0",
    "gn:admin2_code":"1470.0",
    "gn:asciiname":"Rytteras",
    "gn:country_code":"SE",
    "gn:dem":76,
    "gn:feature_class":"P",
    "gn:feature_code":"PPL",
    "gn:name":"Rytter\u00e5s",
    "gn:population":0,
    "gn:timezone":"Europe/Stockholm",
    "iso:country":"SE",
    "wof:name":"Rytteras",
    "wof:placetype":"locality"
},
  "geometry": {"coordinates":[12.95,58.31667],"type":"Point"}
}