{
  "type": "Feature",
  "properties": {
    "gn:admin1_code":"10.0",
    "gn:admin2_code":"2085.0",
    "gn:asciiname":"Dagkarlsbo",
    "gn:country_code":"SE",
    "gn:dem":156,
    "gn:feature_class":"P",
    "gn:feature_code":"PPL",
    "gn:name":"Dagkarlsbo",
    "gn:population":0,
    "gn:timezone":"Europe/Stockholm",
    "iso:country":"SE",
    "wof:name":"Dagkarlsbo",
    "wof:placetype":"locality"
},
  "geometry": {"coordinates":[15.18333,60.11666999999999],"type":"Point"}
}