{
  "type": "Feature",
  "properties": {
    "gn:admin1_code":"23.0",
    "gn:admin2_code":"2417.0",
    "gn:asciiname":"Hogberg",
    "gn:country_code":"SE",
    "gn:dem":285,
    "gn:feature_class":"P",
    "gn:feature_code":"PPL",
    "gn:name":"H\u00f6gberg",
    "gn:population":0,
    "gn:timezone":"Europe/Stockholm",
    "iso:country":"SE",
    "name:nor_x_preferred":[
        "H\u00f6gberg"
    ],
    "name:nor_x_variant":[
        "H\u00f8gberg"
    ],
    "name:und_x_variant":[
        "H\u00f6gberg"
    ],
    "wof:name":"Hogberg",
    "wof:placetype":"locality"
},
  "geometry": {"coordinates":[19.51667,65.13333],"type":"Point"}
}