{
  "type": "Feature",
  "properties": {
    "gn:admin1_code":"22.0",
    "gn:admin2_code":"1760.0",
    "gn:asciiname":"Mogsjon",
    "gn:country_code":"SE",
    "gn:dem":157,
    "gn:feature_class":"P",
    "gn:feature_code":"PPL",
    "gn:name":"M\u00f6gsj\u00f6n",
    "gn:population":0,
    "gn:timezone":"Europe/Stockholm",
    "iso:country":"SE",
    "name:nor_x_preferred":[
        "M\u00f6gsj\u00f6n"
    ],
    "name:nor_x_variant":[
        "M\u00f8gsj\u00f8n"
    ],
    "wof:name":"Mogsjon",
    "wof:placetype":"locality"
},
  "geometry": {"coordinates":[14.26667,59.56667],"type":"Point"}
}