{
  "type": "Feature",
  "properties": {
    "gn:admin1_code":"21.0",
    "gn:admin2_code":"331.0",
    "gn:asciiname":"Arnebo",
    "gn:country_code":"SE",
    "gn:dem":62,
    "gn:feature_class":"P",
    "gn:feature_code":"PPL",
    "gn:name":"Arnebo",
    "gn:population":0,
    "gn:timezone":"Europe/Stockholm",
    "iso:country":"SE",
    "wof:name":"Arnebo",
    "wof:placetype":"locality"
},
  "geometry": {"coordinates":[16.81667,59.96666999999999],"type":"Point"}
}