{
  "type": "Feature",
  "properties": {
    "gn:admin1_code":"9.0",
    "gn:admin2_code":"834.0",
    "gn:asciiname":"Ad",
    "gn:country_code":"SE",
    "gn:dem":-9999,
    "gn:feature_class":"P",
    "gn:feature_code":"PPL",
    "gn:name":"\u00c5d",
    "gn:population":0,
    "gn:timezone":"Europe/Stockholm",
    "iso:country":"SE",
    "wof:name":"Ad",
    "wof:placetype":"locality"
},
  "geometry": {"coordinates":[16.11667000000001,56.43333000000001],"type":"Point"}
}