{
  "type": "Feature",
  "properties": {
    "gn:admin1_code":"21.0",
    "gn:admin2_code":"360.0",
    "gn:asciiname":"Hallen",
    "gn:country_code":"SE",
    "gn:dem":13,
    "gn:feature_class":"P",
    "gn:feature_code":"PPL",
    "gn:name":"H\u00e5llen",
    "gn:population":0,
    "gn:timezone":"Europe/Stockholm",
    "iso:country":"SE",
    "name:ceb_x_preferred":[
        "Hallen"
    ],
    "name:deu_x_preferred":[
        "Hallen"
    ],
    "name:nld_x_preferred":[
        "Hallen"
    ],
    "name:swe_x_preferred":[
        "Hallen"
    ],
    "wof:name":"Hallen",
    "wof:placetype":"locality"
},
  "geometry": {"coordinates":[17.95,60.58333],"type":"Point"}
}