{
  "type": "Feature",
  "properties": {
    "gn:admin1_code":"15.0",
    "gn:admin2_code":"1880.0",
    "gn:asciiname":"Saby",
    "gn:country_code":"SE",
    "gn:dem":56,
    "gn:feature_class":"P",
    "gn:feature_code":"PPL",
    "gn:name":"S\u00e4by",
    "gn:population":0,
    "gn:timezone":"Europe/Stockholm",
    "iso:country":"SE",
    "wof:name":"Saby",
    "wof:placetype":"locality"
},
  "geometry": {"coordinates":[14.96667,59.25],"type":"Point"}
}