{
  "type": "Feature",
  "properties": {
    "gn:admin1_code":"8.0",
    "gn:admin2_code":"686.0",
    "gn:asciiname":"Kulla",
    "gn:country_code":"SE",
    "gn:dem":316,
    "gn:feature_class":"P",
    "gn:feature_code":"PPL",
    "gn:name":"Kulla",
    "gn:population":0,
    "gn:timezone":"Europe/Stockholm",
    "iso:country":"SE",
    "wof:name":"Kulla",
    "wof:placetype":"locality"
},
  "geometry": {"coordinates":[14.83333,57.61666999999999],"type":"Point"}
}