{
  "type": "Feature",
  "properties": {
    "gn:admin1_code":"10.0",
    "gn:admin2_code":"2021.0",
    "gn:asciiname":"Utsalje",
    "gn:country_code":"SE",
    "gn:dem":243,
    "gn:feature_class":"P",
    "gn:feature_code":"PPL",
    "gn:name":"Uts\u00e4lje",
    "gn:population":0,
    "gn:timezone":"Europe/Stockholm",
    "iso:country":"SE",
    "wof:name":"Utsalje",
    "wof:placetype":"locality"
},
  "geometry": {"coordinates":[14.35,60.53333000000001],"type":"Point"}
}