{
  "type": "Feature",
  "properties": {
    "gn:admin1_code":"8.0",
    "gn:admin2_code":"686.0",
    "gn:asciiname":"Sandvik",
    "gn:country_code":"SE",
    "gn:dem":259,
    "gn:feature_class":"P",
    "gn:feature_code":"PPL",
    "gn:name":"Sandvik",
    "gn:population":0,
    "gn:timezone":"Europe/Stockholm",
    "iso:country":"SE",
    "wof:name":"Sandvik",
    "wof:placetype":"locality"
},
  "geometry": {"coordinates":[15.55,57.56667],"type":"Point"}
}