{
  "type": "Feature",
  "properties": {
    "gn:admin1_code":"8.0",
    "gn:admin2_code":"686.0",
    "gn:asciiname":"Sandvik",
    "gn:country_code":"SE",
    "gn:dem":259,
    "gn:feature_class":"P",
    "gn:feature_code":"PPL",
    "gn:name":"Sandvik",
    "gn:population":0,
    "gn:timezone":"Europe/Stockholm",
    "iso:country":"SE",
    "name:dan_x_preferred":[
        "Sandvik"
    ],
    "name:deu_x_preferred":[
        "Sandvik"
    ],
    "name:fas_x_preferred":[
        "\u0633\u0646\u062f\u0648\u06cc\u06a9"
    ],
    "name:fin_x_preferred":[
        "Sandvik"
    ],
    "name:fra_x_preferred":[
        "Sandvik"
    ],
    "name:isl_x_preferred":[
        "Sandvik"
    ],
    "name:ita_x_preferred":[
        "Sandvik"
    ],
    "name:jpn_x_preferred":[
        "\u30b5\u30f3\u30c9\u30d3\u30c3\u30af"
    ],
    "name:por_x_preferred":[
        "Sandvik"
    ],
    "name:rus_x_preferred":[
        "Sandvik"
    ],
    "name:slv_x_preferred":[
        "Sandvik"
    ],
    "name:spa_x_preferred":[
        "Sandvik"
    ],
    "name:swe_x_preferred":[
        "Sandvik"
    ],
    "name:zho_x_preferred":[
        "\u5c71\u7279\u7ef4\u514b"
    ],
    "wof:name":"Sandvik",
    "wof:placetype":"locality"
},
  "geometry": {"coordinates":[15.55,57.56667],"type":"Point"}
}