{
  "type": "Feature",
  "properties": {
    "gn:admin1_code":"3.0",
    "gn:admin2_code":"2161.0",
    "gn:asciiname":"Sjovesta",
    "gn:country_code":"SE",
    "gn:dem":156,
    "gn:feature_class":"P",
    "gn:feature_code":"PPL",
    "gn:name":"Sj\u00f6vesta",
    "gn:population":0,
    "gn:timezone":"Europe/Stockholm",
    "iso:country":"SE",
    "name:nor_x_preferred":[
        "Sj\u00f6vesta"
    ],
    "name:nor_x_variant":[
        "Sj\u00f8vesta"
    ],
    "name:und_x_variant":[
        "Sj\u00f6vesta"
    ],
    "wof:name":"Sjovesta",
    "wof:placetype":"locality"
},
  "geometry": {"coordinates":[16.05,61.78333000000001],"type":"Point"}
}