{
  "type": "Feature",
  "properties": {
    "gn:admin1_code":"23.0",
    "gn:admin2_code":"2481.0",
    "gn:asciiname":"Odelasbacken",
    "gn:cc2":"SE",
    "gn:country_code":"SE",
    "gn:dem":283,
    "gn:feature_class":"P",
    "gn:feature_code":"PPL",
    "gn:name":"Odel\u00e5sbacken",
    "gn:population":0,
    "gn:timezone":"Europe/Stockholm",
    "iso:country":"SE",
    "name:und_x_variant":[
        "Odel\u00e5s",
        "Odel\u00e5sbacken"
    ],
    "wof:name":"Odelasbacken",
    "wof:placetype":"locality"
},
  "geometry": {"coordinates":[17.98333,64.83333],"type":"Point"}
}