{
  "type": "Feature",
  "properties": {
    "gn:country":"SE",
    "gn:fcode":"PPL",
    "gn:population":299,
    "iso:country":"SE",
    "name:ceb_x_preferred":[
        "Moskosel"
    ],
    "name:dan_x_preferred":[
        "Moskosel"
    ],
    "name:deu_x_preferred":[
        "Moskosel"
    ],
    "name:eng_x_preferred":[
        "Moskosel"
    ],
    "name:fra_x_preferred":[
        "Moskosel"
    ],
    "name:nan_x_preferred":[
        "Moskosel"
    ],
    "name:nds_x_preferred":[
        "Moskosel"
    ],
    "name:nld_x_preferred":[
        "Moskosel"
    ],
    "name:nno_x_preferred":[
        "Moskosel"
    ],
    "name:nob_x_preferred":[
        "Moskosel"
    ],
    "name:swe_x_preferred":[
        "Moskosel"
    ],
    "name:und_x_variant":[
        "Muskossel"
    ],
    "qs_pg:aaroncc":"SE",
    "qs_pg:gn_country":"SE",
    "qs_pg:gn_fcode":"PPL",
    "qs_pg:gn_pop":299,
    "qs_pg:name":"Moskosel",
    "qs_pg:name_adm0":"Sverige",
    "qs_pg:name_adm1":"Norrbottens L\u00e4n",
    "qs_pg:photos_9k":1,
    "qs_pg:photos_9r":1,
    "qs_pg:photos_all":11,
    "qs_pg:photos_sr":0,
    "qs_pg:pop_sr":2,
    "qs_pg:qs_pg_placetype":"locality",
    "qs_pg:qs_pg_placetype_gp":"Town",
    "qs_pg:woe_adm0":23424954,
    "woe:adm0_id":23424954,
    "woe:name_adm0":"Sverige",
    "woe:name_adm1":"Norrbottens L\u00e4n",
    "woe:placetype":"Town",
    "wof:name":"Moskosel",
    "wof:placetype":"locality",
    "wof:population":299
},
  "geometry": {"coordinates":[19.41667,65.86667],"type":"Point"}
}