{
  "type": "Feature",
  "properties": {
    "gn:admin1_code":"3.0",
    "gn:admin2_code":"2183.0",
    "gn:asciiname":"Rimsbo",
    "gn:country_code":"SE",
    "gn:dem":303,
    "gn:feature_class":"P",
    "gn:feature_code":"PPL",
    "gn:name":"Rimsbo",
    "gn:population":0,
    "gn:timezone":"Europe/Stockholm",
    "iso:country":"SE",
    "wof:name":"Rimsbo",
    "wof:placetype":"locality"
},
  "geometry": {"coordinates":[16.17256,61.13031],"type":"Point"}
}