{
  "type": "Feature",
  "properties": {
    "gn:admin1_code":"6.0",
    "gn:admin2_code":"1382.0",
    "gn:asciiname":"Stenstorp",
    "gn:country_code":"SE",
    "gn:dem":71,
    "gn:feature_class":"P",
    "gn:feature_code":"PPL",
    "gn:name":"Stenstorp",
    "gn:population":0,
    "gn:timezone":"Europe/Stockholm",
    "iso:country":"SE",
    "name:deu_x_preferred":[
        "Stenstorp"
    ],
    "name:fas_x_preferred":[
        "\u0627\u0633\u062a\u06cc\u0646\u0633 \u062a\u0648\u0631"
    ],
    "name:fra_x_preferred":[
        "Stenstorp"
    ],
    "name:ita_x_preferred":[
        "Stenstorp"
    ],
    "name:nld_x_preferred":[
        "Stenstorp"
    ],
    "name:nno_x_preferred":[
        "Stenstorp"
    ],
    "name:nor_x_preferred":[
        "Stenstorp"
    ],
    "name:por_x_preferred":[
        "Stenstorp"
    ],
    "name:swe_x_preferred":[
        "Stenstorp"
    ],
    "wof:name":"Stenstorp",
    "wof:placetype":"locality"
},
  "geometry": {"coordinates":[12.68333,56.83333],"type":"Point"}
}