{
  "type": "Feature",
  "properties": {
    "gn:admin1_code":"24.0",
    "gn:admin2_code":"2281.0",
    "gn:admin3_code":"228106.0",
    "gn:admin4_code":"2487.0",
    "gn:asciiname":"Osterro",
    "gn:country_code":"SE",
    "gn:dem":45,
    "gn:feature_class":"P",
    "gn:feature_code":"PPL",
    "gn:name":"\u00d6sterro",
    "gn:population":0,
    "gn:timezone":"Europe/Stockholm",
    "iso:country":"SE",
    "name:nor_x_preferred":[
        "\u00d6sterro"
    ],
    "name:nor_x_variant":[
        "\u00d8sterro"
    ],
    "wof:name":"Osterro",
    "wof:placetype":"locality"
},
  "geometry": {"coordinates":[17.22304,62.42319000000001],"type":"Point"}
}