{
  "type": "Feature",
  "properties": {
    "gn:admin1_code":"21.0",
    "gn:admin2_code":"381.0",
    "gn:asciiname":"Alsta",
    "gn:country_code":"SE",
    "gn:dem":23,
    "gn:feature_class":"P",
    "gn:feature_code":"PPL",
    "gn:name":"Alsta",
    "gn:population":0,
    "gn:timezone":"Europe/Stockholm",
    "iso:country":"SE",
    "name:aze_x_preferred":[
        "Alsta adas\u0131"
    ],
    "name:cat_x_preferred":[
        "Alsten"
    ],
    "name:ceb_x_preferred":[
        "Alsten"
    ],
    "name:dan_x_preferred":[
        "Alsten"
    ],
    "name:fin_x_preferred":[
        "Alsten"
    ],
    "name:fra_x_preferred":[
        "Alsten"
    ],
    "name:glg_x_preferred":[
        "Alsten"
    ],
    "name:nld_x_preferred":[
        "Alsten"
    ],
    "name:nno_x_preferred":[
        "Alsta"
    ],
    "name:nor_x_preferred":[
        "Alsta"
    ],
    "name:rus_x_preferred":[
        "\u0410\u043b\u0441\u0442\u0435\u043d"
    ],
    "name:spa_x_preferred":[
        "Alsten"
    ],
    "name:swe_x_preferred":[
        "Alsten"
    ],
    "name:ukr_x_preferred":[
        "\u0410\u043b\u044c\u0441\u0442\u0435\u043d"
    ],
    "name:zho_x_preferred":[
        "\u963f\u723e\u65af\u9a30\u5cf6"
    ],
    "wof:name":"Alsta",
    "wof:placetype":"locality"
},
  "geometry": {"coordinates":[17.25,59.75],"type":"Point"}
}