{
  "type": "Feature",
  "properties": {
    "gn:admin1_code":"14.0",
    "gn:admin2_code":"2505.0",
    "gn:asciiname":"Holmen",
    "gn:country_code":"SE",
    "gn:dem":405,
    "gn:feature_class":"P",
    "gn:feature_code":"PPL",
    "gn:name":"Holmen",
    "gn:population":0,
    "gn:timezone":"Europe/Stockholm",
    "iso:country":"SE",
    "name:ceb_x_preferred":[
        "Holmen"
    ],
    "name:dan_x_preferred":[
        "Holmen"
    ],
    "name:deu_x_preferred":[
        "Holmen"
    ],
    "name:est_x_preferred":[
        "Holmen"
    ],
    "name:fra_x_preferred":[
        "Holmen"
    ],
    "name:nld_x_preferred":[
        "Holmen"
    ],
    "name:nor_x_preferred":[
        "Holmen"
    ],
    "name:swe_x_preferred":[
        "Holmen"
    ],
    "wof:name":"Holmen",
    "wof:placetype":"locality"
},
  "geometry": {"coordinates":[18.87998,65.55656999999999],"type":"Point"}
}