{
  "type": "Feature",
  "properties": {
    "gn:admin1_code":"28.0",
    "gn:asciiname":"Ekenas",
    "gn:country_code":"SE",
    "gn:dem":3,
    "gn:feature_class":"P",
    "gn:feature_code":"PPL",
    "gn:name":"Eken\u00e4s",
    "gn:population":0,
    "gn:timezone":"Europe/Stockholm",
    "iso:country":"SE",
    "wof:name":"Ekenas",
    "wof:placetype":"locality"
},
  "geometry": {"coordinates":[11.04813,58.89316],"type":"Point"}
}