{
  "type": "Feature",
  "properties": {
    "gn:admin1_code":"16.0",
    "gn:admin2_code":"586.0",
    "gn:asciiname":"Luntan",
    "gn:cc2":"SE",
    "gn:country_code":"SE",
    "gn:dem":87,
    "gn:feature_class":"P",
    "gn:feature_code":"PPL",
    "gn:name":"Luntan",
    "gn:population":0,
    "gn:timezone":"Europe/Stockholm",
    "iso:country":"SE",
    "name:und_x_variant":[
        "Lunta",
        "Luntan"
    ],
    "wof:name":"Luntan",
    "wof:placetype":"locality"
},
  "geometry": {"coordinates":[15.33333,58.38333000000001],"type":"Point"}
}