{
  "type": "Feature",
  "properties": {
    "gn:admin1_code":"23.0",
    "gn:admin2_code":"2482.0",
    "gn:admin3_code":"248205.0",
    "gn:admin4_code":"141.0",
    "gn:asciiname":"Ulriksberg",
    "gn:country_code":"SE",
    "gn:dem":360,
    "gn:feature_class":"P",
    "gn:feature_code":"PPL",
    "gn:name":"Ulriksberg",
    "gn:population":0,
    "gn:timezone":"Europe/Stockholm",
    "iso:country":"SE",
    "wof:name":"Ulriksberg",
    "wof:placetype":"locality"
},
  "geometry": {"coordinates":[20.08826,65.34531],"type":"Point"}
}