{
  "type": "Feature",
  "properties": {
    "gn:admin1_code":"10.0",
    "gn:admin2_code":"2081.0",
    "gn:asciiname":"Vastanang",
    "gn:cc2":"SE",
    "gn:country_code":"SE",
    "gn:dem":153,
    "gn:feature_class":"P",
    "gn:feature_code":"PPL",
    "gn:name":"V\u00e4stan\u00e4ng",
    "gn:population":0,
    "gn:timezone":"Europe/Stockholm",
    "iso:country":"SE",
    "name:und_x_variant":[
        "Vestan\u00e4ng",
        "V\u00e4stan\u00e4ng"
    ],
    "wof:name":"Vastanang",
    "wof:placetype":"locality"
},
  "geometry": {"coordinates":[15.38333,60.46666999999999],"type":"Point"}
}