{
  "type": "Feature",
  "properties": {
    "gn:admin1_code":"9.0",
    "gn:admin2_code":"834.0",
    "gn:asciiname":"Bidalite",
    "gn:country_code":"SE",
    "gn:dem":65,
    "gn:feature_class":"P",
    "gn:feature_code":"PPL",
    "gn:name":"Bidalite",
    "gn:population":0,
    "gn:timezone":"Europe/Stockholm",
    "iso:country":"SE",
    "wof:name":"Bidalite",
    "wof:placetype":"locality"
},
  "geometry": {"coordinates":[15.86667,56.41667],"type":"Point"}
}