{
  "type": "Feature",
  "properties": {
    "gn:admin1_code":"14.0",
    "gn:admin2_code":"2584.0",
    "gn:asciiname":"Lannavaara",
    "gn:country_code":"SE",
    "gn:dem":350,
    "gn:feature_class":"P",
    "gn:feature_code":"PPL",
    "gn:name":"Lannavaara",
    "gn:population":0,
    "gn:timezone":"Europe/Stockholm",
    "iso:country":"SE",
    "name:fit_x_preferred":[
        "Lannavaara"
    ],
    "name:sme_x_preferred":[
        "L\u00e1ttev\u00e1rri"
    ],
    "wof:name":"Lannavaara",
    "wof:placetype":"locality"
},
  "geometry": {"coordinates":[21.97416,68.04746999999999],"type":"Point"}
}