{
  "type": "Feature",
  "properties": {
    "gn:admin1_code":"9.0",
    "gn:admin2_code":"840.0",
    "gn:asciiname":"Ronnerum",
    "gn:country_code":"SE",
    "gn:dem":42,
    "gn:feature_class":"P",
    "gn:feature_code":"PPL",
    "gn:name":"R\u00f6nnerum",
    "gn:population":0,
    "gn:timezone":"Europe/Stockholm",
    "iso:country":"SE",
    "name:nor_x_preferred":[
        "R\u00f6nnerum"
    ],
    "name:nor_x_variant":[
        "R\u00f8nnerum"
    ],
    "wof:name":"Ronnerum",
    "wof:placetype":"locality"
},
  "geometry": {"coordinates":[16.56667,56.75],"type":"Point"}
}