{
  "type": "Feature",
  "properties": {
    "gn:admin1_code":"7.0",
    "gn:admin2_code":"2313.0",
    "gn:asciiname":"Risede",
    "gn:country_code":"SE",
    "gn:dem":375,
    "gn:feature_class":"P",
    "gn:feature_code":"PPL",
    "gn:name":"Risede",
    "gn:population":0,
    "gn:timezone":"Europe/Stockholm",
    "iso:country":"SE",
    "wof:name":"Risede",
    "wof:placetype":"locality"
},
  "geometry": {"coordinates":[15.11667,64.40000000000001],"type":"Point"}
}