{
  "type": "Feature",
  "properties": {
    "gn:admin1_code":"15.0",
    "gn:admin2_code":"1864.0",
    "gn:asciiname":"Basttjarn",
    "gn:country_code":"SE",
    "gn:dem":325,
    "gn:feature_class":"P",
    "gn:feature_code":"PPL",
    "gn:name":"Basttj\u00e4rn",
    "gn:population":0,
    "gn:timezone":"Europe/Stockholm",
    "iso:country":"SE",
    "wof:name":"Basttjarn",
    "wof:placetype":"locality"
},
  "geometry": {"coordinates":[14.98333,60.01667],"type":"Point"}
}