{
  "type": "Feature",
  "properties": {
    "gn:admin1_code":"26.0",
    "gn:admin2_code":"136.0",
    "gn:asciiname":"Smahamra",
    "gn:country_code":"SE",
    "gn:dem":34,
    "gn:feature_class":"P",
    "gn:feature_code":"PPL",
    "gn:name":"Sm\u00e5hamra",
    "gn:population":0,
    "gn:timezone":"Europe/Stockholm",
    "iso:country":"SE",
    "wof:name":"Smahamra",
    "wof:placetype":"locality"
},
  "geometry": {"coordinates":[18.25,59.14972],"type":"Point"}
}