{
  "type": "Feature",
  "properties": {
    "gn:admin1_code":"28.0",
    "gn:admin2_code":"1491.0",
    "gn:asciiname":"Lena",
    "gn:country_code":"SE",
    "gn:dem":183,
    "gn:feature_class":"P",
    "gn:feature_code":"PPL",
    "gn:name":"Lena",
    "gn:population":0,
    "gn:timezone":"Europe/Stockholm",
    "iso:country":"SE",
    "wof:name":"Lena",
    "wof:placetype":"locality"
},
  "geometry": {"coordinates":[13.42667,57.86229],"type":"Point"}
}