{
  "type": "Feature",
  "properties": {
    "gn:admin1_code":"14.0",
    "gn:admin2_code":"2560.0",
    "gn:asciiname":"Grantrask",
    "gn:country_code":"SE",
    "gn:dem":124,
    "gn:feature_class":"P",
    "gn:feature_code":"PPL",
    "gn:name":"Grantr\u00e4sk",
    "gn:population":0,
    "gn:timezone":"Europe/Stockholm",
    "iso:country":"SE",
    "wof:name":"Grantrask",
    "wof:placetype":"locality"
},
  "geometry": {"coordinates":[20.95,65.53333000000001],"type":"Point"}
}