{
  "type": "Feature",
  "properties": {
    "iso:country":"SE",
    "name:swe_x_preferred":[
        "Hj\u00e4llbo"
    ],
    "wof:name":"Hjallbo",
    "wof:placetype":"neighbourhood"
},
  "geometry": {"coordinates":[12.02035400128395,57.76875495533191],"type":"Point"}
}