{
  "type": "Feature",
  "properties": {
    "gn:admin1_code":"9.0",
    "gn:admin2_code":"881.0",
    "gn:asciiname":"Kopparfly",
    "gn:country_code":"SE",
    "gn:dem":160,
    "gn:feature_class":"P",
    "gn:feature_code":"PPL",
    "gn:name":"Kopparfly",
    "gn:population":0,
    "gn:timezone":"Europe/Stockholm",
    "iso:country":"SE",
    "wof:name":"Kopparfly",
    "wof:placetype":"locality"
},
  "geometry": {"coordinates":[15.68333,56.71666999999999],"type":"Point"}
}