{
  "type": "Feature",
  "properties": {
    "gn:admin1_code":"7.0",
    "gn:admin2_code":"2313.0",
    "gn:asciiname":"Kyrkbolandet",
    "gn:cc2":"SE",
    "gn:country_code":"SE",
    "gn:dem":393,
    "gn:feature_class":"P",
    "gn:feature_code":"PPL",
    "gn:name":"Kyrkbolandet",
    "gn:population":0,
    "gn:timezone":"Europe/Stockholm",
    "iso:country":"SE",
    "name:und_x_variant":[
        "Kyrkbolet",
        "Kyrkbollandet",
        "Kyrkbolandet"
    ],
    "wof:name":"Kyrkbolandet",
    "wof:placetype":"locality"
},
  "geometry": {"coordinates":[13.93333,64.61667],"type":"Point"}
}