{
  "type": "Feature",
  "properties": {
    "gn:admin1_code":"2.0",
    "gn:admin2_code":"1060.0",
    "gn:asciiname":"Hakantorp",
    "gn:country_code":"SE",
    "gn:dem":41,
    "gn:feature_class":"P",
    "gn:feature_code":"PPL",
    "gn:name":"H\u00e5kantorp",
    "gn:population":0,
    "gn:timezone":"Europe/Stockholm",
    "iso:country":"SE",
    "wof:name":"Hakantorp",
    "wof:placetype":"locality"
},
  "geometry": {"coordinates":[14.63333,56.23333],"type":"Point"}
}