{
  "type": "Feature",
  "properties": {
    "gn:admin1_code":"8.0",
    "gn:admin2_code":"684.0",
    "gn:asciiname":"Uggleryd",
    "gn:country_code":"SE",
    "gn:dem":223,
    "gn:feature_class":"P",
    "gn:feature_code":"PPL",
    "gn:name":"Uggleryd",
    "gn:population":0,
    "gn:timezone":"Europe/Stockholm",
    "iso:country":"SE",
    "wof:name":"Uggleryd",
    "wof:placetype":"locality"
},
  "geometry": {"coordinates":[14.51667,57.18333000000001],"type":"Point"}
}