{
  "type": "Feature",
  "properties": {
    "gn:admin1_code":"23.0",
    "gn:admin2_code":"2417.0",
    "gn:asciiname":"Lidbranna",
    "gn:country_code":"SE",
    "gn:dem":397,
    "gn:feature_class":"P",
    "gn:feature_code":"PPL",
    "gn:name":"Lidbr\u00e4nna",
    "gn:population":0,
    "gn:timezone":"Europe/Stockholm",
    "iso:country":"SE",
    "wof:name":"Lidbranna",
    "wof:placetype":"locality"
},
  "geometry": {"coordinates":[19.31667,64.98333000000001],"type":"Point"}
}