{
  "type": "Feature",
  "properties": {
    "gn:admin1_code":"23.0",
    "gn:admin2_code":"2482.0",
    "gn:asciiname":"Vikmyren",
    "gn:cc2":"SE",
    "gn:country_code":"SE",
    "gn:dem":40,
    "gn:feature_class":"P",
    "gn:feature_code":"PPL",
    "gn:name":"Vikmyren",
    "gn:population":0,
    "gn:timezone":"Europe/Stockholm",
    "iso:country":"SE",
    "name:und_x_variant":[
        "Vikmyran",
        "Vikmyren"
    ],
    "wof:name":"Vikmyren",
    "wof:placetype":"locality"
},
  "geometry": {"coordinates":[21.06667,64.63333],"type":"Point"}
}