{
  "type": "Feature",
  "properties": {
    "gn:admin1_code":"5.0",
    "gn:admin2_code":"980.0",
    "gn:asciiname":"Lillakre",
    "gn:country_code":"SE",
    "gn:dem":33,
    "gn:feature_class":"P",
    "gn:feature_code":"PPL",
    "gn:name":"Lill\u00e5kre",
    "gn:population":0,
    "gn:timezone":"Europe/Stockholm",
    "iso:country":"SE",
    "wof:name":"Lillakre",
    "wof:placetype":"locality"
},
  "geometry": {"coordinates":[18.46978,57.56883000000001],"type":"Point"}
}