{
  "type": "Feature",
  "properties": {
    "gn:admin1_code":"24.0",
    "gn:asciiname":"Abord",
    "gn:country_code":"SE",
    "gn:dem":32,
    "gn:feature_class":"P",
    "gn:feature_code":"PPL",
    "gn:name":"\u00c5bord",
    "gn:population":0,
    "gn:timezone":"Europe/Stockholm",
    "iso:country":"SE",
    "wof:name":"Abord",
    "wof:placetype":"locality"
},
  "geometry": {"coordinates":[17.96667,62.78333000000001],"type":"Point"}
}