{
  "type": "Feature",
  "properties": {
    "gn:admin1_code":"8.0",
    "gn:admin2_code":"684.0",
    "gn:asciiname":"Boeryd",
    "gn:country_code":"SE",
    "gn:dem":280,
    "gn:feature_class":"P",
    "gn:feature_code":"PPL",
    "gn:name":"Boeryd",
    "gn:population":0,
    "gn:timezone":"Europe/Stockholm",
    "iso:country":"SE",
    "wof:name":"Boeryd",
    "wof:placetype":"locality"
},
  "geometry": {"coordinates":[14.75,57.23333],"type":"Point"}
}