{
  "type": "Feature",
  "properties": {
    "gn:admin1_code":"26.0",
    "gn:admin2_code":"188.0",
    "gn:asciiname":"Torvsjo",
    "gn:country_code":"SE",
    "gn:dem":11,
    "gn:feature_class":"P",
    "gn:feature_code":"PPL",
    "gn:name":"Torvsj\u00f6",
    "gn:population":0,
    "gn:timezone":"Europe/Stockholm",
    "iso:country":"SE",
    "name:nor_x_preferred":[
        "Torvsj\u00f6"
    ],
    "name:nor_x_variant":[
        "Torvsj\u00f8"
    ],
    "wof:name":"Torvsjo",
    "wof:placetype":"locality"
},
  "geometry": {"coordinates":[19.075,59.75],"type":"Point"}
}