{
  "type": "Feature",
  "properties": {
    "gn:admin1_code":"15.0",
    "gn:admin2_code":"1882.0",
    "gn:asciiname":"Gronlid",
    "gn:country_code":"SE",
    "gn:dem":159,
    "gn:feature_class":"P",
    "gn:feature_code":"PPL",
    "gn:name":"Gr\u00f6nlid",
    "gn:population":0,
    "gn:timezone":"Europe/Stockholm",
    "iso:country":"SE",
    "name:nor_x_preferred":[
        "Gr\u00f6nlid"
    ],
    "name:nor_x_variant":[
        "Gr\u00f8nlid"
    ],
    "wof:name":"Gronlid",
    "wof:placetype":"locality"
},
  "geometry": {"coordinates":[14.88333,58.85],"type":"Point"}
}