{
  "type": "Feature",
  "properties": {
    "gn:gn_country":"SE",
    "gn:gn_fcode":"PPL",
    "gn:gn_pop":646,
    "gn:population":646,
    "iso:country":"SE",
    "name:chi_x_preferred":[
        "\u798f\u4ec0\u6bd4"
    ],
    "name:dut_x_preferred":[
        "Forsby"
    ],
    "name:eng_x_preferred":[
        "Forsby"
    ],
    "name:nan_x_preferred":[
        "Forsby"
    ],
    "name:nno_x_preferred":[
        "Forsby i G\u00e4strikland"
    ],
    "name:nob_x_preferred":[
        "Forsby"
    ],
    "name:swe_x_preferred":[
        "Forsby"
    ],
    "qs_pg:aaroncc":"SE",
    "qs_pg:gn_country":"SE",
    "qs_pg:gn_fcode":"PPL",
    "qs_pg:gn_pop":646,
    "qs_pg:name":"Forsby",
    "qs_pg:name_adm0":"Sverige",
    "qs_pg:name_adm1":"G\u00e4vleborgs L\u00e4n",
    "qs_pg:photos_9r":0,
    "qs_pg:photos_sr":0,
    "qs_pg:pop_sr":2,
    "qs_pg:qs_pg_placetype":"locality",
    "qs_pg:qs_pg_placetype_gp":"Town",
    "qs_pg:woe_adm0":23424954,
    "woe:adm0_id":23424954,
    "woe:name_adm0":"Sverige",
    "woe:name_adm1":"G\u00e4vleborgs L\u00e4n",
    "woe:placetype":"Town",
    "wof:name":"Forsby",
    "wof:placetype":"locality",
    "wof:population":646
},
  "geometry": {"coordinates":[17.13333,60.71667],"type":"Point"}
}