{
  "type": "Feature",
  "properties": {
    "gn:admin1_code":"8.0",
    "gn:admin2_code":"686.0",
    "gn:asciiname":"Ebbarp",
    "gn:country_code":"SE",
    "gn:dem":238,
    "gn:feature_class":"P",
    "gn:feature_code":"PPL",
    "gn:name":"Ebbarp",
    "gn:population":0,
    "gn:timezone":"Europe/Stockholm",
    "iso:country":"SE",
    "wof:name":"Ebbarp",
    "wof:placetype":"locality"
},
  "geometry": {"coordinates":[15.16667,57.63333000000001],"type":"Point"}
}