{
  "type": "Feature",
  "properties": {
    "gn:admin1_code":"7.0",
    "gn:admin2_code":"2361.0",
    "gn:asciiname":"Olingdal",
    "gn:country_code":"SE",
    "gn:dem":492,
    "gn:feature_class":"P",
    "gn:feature_code":"PPL",
    "gn:name":"Olingdal",
    "gn:population":0,
    "gn:timezone":"Europe/Stockholm",
    "iso:country":"SE",
    "wof:name":"Olingdal",
    "wof:placetype":"locality"
},
  "geometry": {"coordinates":[14.26667,61.86666999999999],"type":"Point"}
}