{
  "type": "Feature",
  "properties": {
    "gn:admin1_code":"28.0",
    "gn:admin2_code":"1486.0",
    "gn:asciiname":"Ylserod",
    "gn:country_code":"SE",
    "gn:dem":23,
    "gn:feature_class":"P",
    "gn:feature_code":"PPL",
    "gn:name":"Ylser\u00f6d",
    "gn:population":0,
    "gn:timezone":"Europe/Stockholm",
    "iso:country":"SE",
    "name:nor_x_preferred":[
        "Ylser\u00f6d"
    ],
    "name:nor_x_variant":[
        "Ylser\u00f8d"
    ],
    "name:und_x_variant":[
        "Ylser\u00f6d"
    ],
    "wof:name":"Ylserod",
    "wof:placetype":"locality"
},
  "geometry": {"coordinates":[11.225,58.99444],"type":"Point"}
}