{
  "type": "Feature",
  "properties": {
    "gn:admin1_code":"23.0",
    "gn:admin2_code":"2482.0",
    "gn:asciiname":"Sodra Hedensbyn",
    "gn:country_code":"SE",
    "gn:dem":17,
    "gn:feature_class":"P",
    "gn:feature_code":"PPL",
    "gn:name":"S\u00f6dra Hedensbyn",
    "gn:population":0,
    "gn:timezone":"Europe/Stockholm",
    "iso:country":"SE",
    "name:nor_x_preferred":[
        "S\u00f6dra Hedensbyn"
    ],
    "name:nor_x_variant":[
        "S\u00f8dra Hedensbyn"
    ],
    "wof:name":"Sodra Hedensbyn",
    "wof:placetype":"locality"
},
  "geometry": {"coordinates":[21.02234,64.73891],"type":"Point"}
}