{
  "type": "Feature",
  "properties": {
    "gn:admin1_code":"12.0",
    "gn:admin2_code":"781.0",
    "gn:asciiname":"Bjarnaryd",
    "gn:country_code":"SE",
    "gn:dem":167,
    "gn:feature_class":"P",
    "gn:feature_code":"PPL",
    "gn:name":"Bj\u00e4rnaryd",
    "gn:population":0,
    "gn:timezone":"Europe/Stockholm",
    "iso:country":"SE",
    "wof:name":"Bjarnaryd",
    "wof:placetype":"locality"
},
  "geometry": {"coordinates":[13.83333,56.86666999999999],"type":"Point"}
}