{
  "type": "Feature",
  "properties": {
    "gn:country":"SE",
    "gn:fcode":"PPL",
    "gn:population":399,
    "iso:country":"SE",
    "name:ceb_x_preferred":[
        "Backaryd"
    ],
    "name:eng_x_preferred":[
        "Backaryd"
    ],
    "name:fra_x_preferred":[
        "Backaryd"
    ],
    "name:ita_x_preferred":[
        "Backaryd"
    ],
    "name:nan_x_preferred":[
        "Backaryd"
    ],
    "name:nld_x_preferred":[
        "Backaryd"
    ],
    "name:nno_x_preferred":[
        "Backaryd"
    ],
    "name:nob_x_preferred":[
        "Backaryd"
    ],
    "name:swe_x_preferred":[
        "Backaryd"
    ],
    "qs_pg:aaroncc":"SE",
    "qs_pg:gn_country":"SE",
    "qs_pg:gn_fcode":"PPL",
    "qs_pg:gn_pop":399,
    "qs_pg:name":"Backaryd",
    "qs_pg:name_adm0":"Sverige",
    "qs_pg:name_adm1":"Blekinge L\u00e4n",
    "qs_pg:photos":24,
    "qs_pg:photos_1k":5,
    "qs_pg:photos_9k":1,
    "qs_pg:photos_9r":1,
    "qs_pg:photos_all":24,
    "qs_pg:photos_sr":1,
    "qs_pg:pop_sr":2,
    "qs_pg:qs_pg_placetype":"locality",
    "qs_pg:qs_pg_placetype_gp":"Town",
    "qs_pg:woe_adm0":23424954,
    "woe:adm0_id":23424954,
    "woe:name_adm0":"Sverige",
    "woe:name_adm1":"Blekinge L\u00e4n",
    "woe:placetype":"Town",
    "wof:name":"Backaryd",
    "wof:placetype":"locality",
    "wof:population":386
},
  "geometry": {"coordinates":[15.18333,56.33333],"type":"Point"}
}