{
  "type": "Feature",
  "properties": {
    "gn:admin1_code":"28.0",
    "gn:asciiname":"Apelskift",
    "gn:cc2":"SE",
    "gn:country_code":"SE",
    "gn:dem":237,
    "gn:feature_class":"P",
    "gn:feature_code":"PPL",
    "gn:name":"Apelskift",
    "gn:population":0,
    "gn:timezone":"Europe/Stockholm",
    "iso:country":"SE",
    "name:und_x_variant":[
        "Appelskift",
        "Apelskift"
    ],
    "wof:name":"Apelskift",
    "wof:placetype":"locality"
},
  "geometry": {"coordinates":[13.96667,57.85],"type":"Point"}
}