{
  "type": "Feature",
  "properties": {
    "gn:gn_country":"SE",
    "gn:gn_fcode":"PPL",
    "gn:gn_pop":452,
    "gn:population":463,
    "iso:country":"SE",
    "name:bul_x_preferred":[
        "\u0410\u043f\u043b\u0430\u0440\u0435\u0434"
    ],
    "name:cat_x_preferred":[
        "Aplared"
    ],
    "name:deu_x_preferred":[
        "Aplared"
    ],
    "name:eng_x_preferred":[
        "Aplared"
    ],
    "name:fra_x_preferred":[
        "Aplared"
    ],
    "name:ita_x_preferred":[
        "Aplared"
    ],
    "name:nan_x_preferred":[
        "Aplared"
    ],
    "name:nld_x_preferred":[
        "Aplared"
    ],
    "name:nno_x_preferred":[
        "Aplared"
    ],
    "name:nob_x_preferred":[
        "Aplared"
    ],
    "name:oci_x_preferred":[
        "Aplared"
    ],
    "name:sco_x_preferred":[
        "Aplared"
    ],
    "name:spa_x_preferred":[
        "Aplared"
    ],
    "name:swe_x_preferred":[
        "Aplared"
    ],
    "qs_pg:aaroncc":"SE",
    "qs_pg:gn_country":"SE",
    "qs_pg:gn_fcode":"PPL",
    "qs_pg:gn_pop":452,
    "qs_pg:name":"Aplared",
    "qs_pg:name_adm0":"Sverige",
    "qs_pg:name_adm1":"V\u00e4stra G\u00f6talands L\u00e4n",
    "qs_pg:photos_9k":1,
    "qs_pg:photos_9r":1,
    "qs_pg:photos_all":1,
    "qs_pg:photos_sr":0,
    "qs_pg:pop_sr":2,
    "qs_pg:qs_pg_placetype":"locality",
    "qs_pg:qs_pg_placetype_gp":"Town",
    "qs_pg:woe_adm0":23424954,
    "woe:adm0_id":23424954,
    "woe:name_adm0":"Sverige",
    "woe:name_adm1":"V\u00e4stra G\u00f6talands L\u00e4n",
    "woe:placetype":"Town",
    "wof:name":"Aplared",
    "wof:placetype":"locality",
    "wof:population":463
},
  "geometry": {"coordinates":[13.06667,57.65],"type":"Point"}
}