{
  "type": "Feature",
  "properties": {
    "gn:gn_country":"SE",
    "gn:gn_fcode":"PPL",
    "gn:gn_pop":52,
    "gn:population":52,
    "iso:country":"SE",
    "name:dan_x_preferred":[
        "T\u00e4nndalen"
    ],
    "name:dut_x_preferred":[
        "T\u00e4nndalen"
    ],
    "name:eng_x_preferred":[
        "T\u00e4nndalen"
    ],
    "name:fao_x_preferred":[
        "T\u00e4nndalen"
    ],
    "name:fin_x_preferred":[
        "T\u00e4nndalen"
    ],
    "name:fit_x_preferred":[
        "T\u00e4nndalen"
    ],
    "name:fre_x_preferred":[
        "T\u00e4nndalen"
    ],
    "name:ger_x_preferred":[
        "T\u00e4nndalen"
    ],
    "name:ice_x_preferred":[
        "T\u00e4nndalen"
    ],
    "name:nds_x_preferred":[
        "T\u00e4nndalen"
    ],
    "name:nno_x_preferred":[
        "T\u00e4nndalen"
    ],
    "name:nob_x_preferred":[
        "T\u00e4nndalen"
    ],
    "name:rus_x_preferred":[
        "\u0422\u044d\u043d\u043d\u0434\u0430\u043b\u0435\u043d"
    ],
    "name:swe_x_preferred":[
        "T\u00e4nndalen"
    ],
    "qs_pg:aaroncc":"SE",
    "qs_pg:gn_country":"SE",
    "qs_pg:gn_fcode":"PPL",
    "qs_pg:gn_pop":52,
    "qs_pg:name":"T\u00e4nndalen",
    "qs_pg:photos_9r":0,
    "qs_pg:photos_sr":0,
    "qs_pg:pop_sr":1,
    "qs_pg:qs_pg_placetype":"locality",
    "wof:name":"T\u00e4nndalen",
    "wof:placetype":"locality",
    "wof:population":52
},
  "geometry": {"coordinates":[12.33266,62.54372],"type":"Point"}
}