{
  "type": "Feature",
  "properties": {
    "gn:admin1_code":"12.0",
    "gn:admin2_code":"763.0",
    "gn:asciiname":"Rammsjo",
    "gn:cc2":"SE",
    "gn:country_code":"SE",
    "gn:dem":138,
    "gn:feature_class":"P",
    "gn:feature_code":"PPL",
    "gn:name":"Rammsj\u00f6",
    "gn:population":0,
    "gn:timezone":"Europe/Stockholm",
    "iso:country":"SE",
    "name:nor_x_preferred":[
        "Rammsj\u00f6"
    ],
    "name:nor_x_variant":[
        "Rammsj\u00f8"
    ],
    "name:und_x_variant":[
        "Ramsj\u00f6"
    ],
    "wof:name":"Rammsjo",
    "wof:placetype":"locality"
},
  "geometry": {"coordinates":[15.36667,56.51667],"type":"Point"}
}