{
  "type": "Feature",
  "properties": {
    "gn:admin1_code":"25.0",
    "gn:admin2_code":"1983.0",
    "gn:asciiname":"Sorsylta",
    "gn:country_code":"SE",
    "gn:dem":17,
    "gn:feature_class":"P",
    "gn:feature_code":"PPL",
    "gn:name":"S\u00f6rsylta",
    "gn:population":0,
    "gn:timezone":"Europe/Stockholm",
    "iso:country":"SE",
    "name:nor_x_preferred":[
        "S\u00f6rsylta"
    ],
    "name:nor_x_variant":[
        "S\u00f8rsylta"
    ],
    "wof:name":"Sorsylta",
    "wof:placetype":"locality"
},
  "geometry": {"coordinates":[16.18333,59.51667],"type":"Point"}
}