{
  "type": "Feature",
  "properties": {
    "gn:admin1_code":"15.0",
    "gn:admin2_code":"1885.0",
    "gn:admin3_code":"188504.0",
    "gn:admin4_code":"2246.0",
    "gn:asciiname":"Lia",
    "gn:country_code":"SE",
    "gn:dem":40,
    "gn:feature_class":"P",
    "gn:feature_code":"PPL",
    "gn:name":"Lia",
    "gn:population":0,
    "gn:timezone":"Europe/Stockholm",
    "iso:country":"SE",
    "wof:name":"Lia",
    "wof:placetype":"locality"
},
  "geometry": {"coordinates":[15.33026,59.45701],"type":"Point"}
}