{
  "type": "Feature",
  "properties": {
    "gn:admin1_code":"16.0",
    "gn:admin2_code":"562.0",
    "gn:asciiname":"Ljusfall",
    "gn:country_code":"SE",
    "gn:dem":84,
    "gn:feature_class":"P",
    "gn:feature_code":"PPL",
    "gn:name":"Ljusfall",
    "gn:population":0,
    "gn:timezone":"Europe/Stockholm",
    "iso:country":"SE",
    "wof:name":"Ljusfall",
    "wof:placetype":"locality"
},
  "geometry": {"coordinates":[15.46667,58.78333000000001],"type":"Point"}
}