{
  "type": "Feature",
  "properties": {
    "gn:admin1_code":"24.0",
    "gn:admin2_code":"2284.0",
    "gn:asciiname":"Mosjo",
    "gn:country_code":"SE",
    "gn:dem":163,
    "gn:feature_class":"P",
    "gn:feature_code":"PPL",
    "gn:name":"Mosj\u00f6",
    "gn:population":0,
    "gn:timezone":"Europe/Stockholm",
    "iso:country":"SE",
    "name:nor_x_preferred":[
        "Mosj\u00f6"
    ],
    "name:nor_x_variant":[
        "Mosj\u00f8"
    ],
    "wof:name":"Mosjo",
    "wof:placetype":"locality"
},
  "geometry": {"coordinates":[17.91667,63.38333000000001],"type":"Point"}
}