{
  "type": "Feature",
  "properties": {
    "gn:admin1_code":"12.0",
    "gn:admin2_code":"781.0",
    "gn:asciiname":"Ossjohult",
    "gn:country_code":"SE",
    "gn:dem":183,
    "gn:feature_class":"P",
    "gn:feature_code":"PPL",
    "gn:name":"\u00d6ssj\u00f6hult",
    "gn:population":0,
    "gn:timezone":"Europe/Stockholm",
    "iso:country":"SE",
    "name:nor_x_preferred":[
        "\u00d6ssj\u00f6hult"
    ],
    "name:nor_x_variant":[
        "\u00d8ssj\u00f8hult"
    ],
    "name:und_x_variant":[
        "\u00d6ssj\u00f6hult"
    ],
    "wof:name":"Ossjohult",
    "wof:placetype":"locality"
},
  "geometry": {"coordinates":[13.41667,56.63333000000001],"type":"Point"}
}