{
  "type": "Feature",
  "properties": {
    "gn:admin1_code":"10.0",
    "gn:admin2_code":"2083.0",
    "gn:asciiname":"Persbo",
    "gn:country_code":"SE",
    "gn:dem":167,
    "gn:feature_class":"P",
    "gn:feature_code":"PPL",
    "gn:name":"Persbo",
    "gn:population":0,
    "gn:timezone":"Europe/Stockholm",
    "iso:country":"SE",
    "name:ita_x_preferred":[
        "Persbo"
    ],
    "name:nld_x_preferred":[
        "Persbo"
    ],
    "name:nno_x_preferred":[
        "Persbo"
    ],
    "name:nor_x_preferred":[
        "Persbo"
    ],
    "wof:name":"Persbo",
    "wof:placetype":"locality"
},
  "geometry": {"coordinates":[16.21667,60.26667],"type":"Point"}
}