{
  "type": "Feature",
  "properties": {
    "gn:gn_country":"SE",
    "iso:country":"SE",
    "name:bel_x_preferred":[
        "\u0421\u043a\u0430\u043d\u0441\u0435\u043d"
    ],
    "name:bul_x_preferred":[
        "\u0421\u043a\u0430\u043d\u0441\u0435\u043d"
    ],
    "name:ces_x_preferred":[
        "Skansen"
    ],
    "name:ckb_x_preferred":[
        "\u0633\u06a9\u0627\u0646\u0633\u06ce\u0646"
    ],
    "name:dan_x_preferred":[
        "Skansen"
    ],
    "name:deu_x_preferred":[
        "Skansen"
    ],
    "name:ell_x_preferred":[
        "\u03a3\u03ba\u03ac\u03bd\u03c3\u03b5\u03bd"
    ],
    "name:epo_x_preferred":[
        "Skanseno"
    ],
    "name:est_x_preferred":[
        "Skansen"
    ],
    "name:eus_x_preferred":[
        "Skansen"
    ],
    "name:fas_x_preferred":[
        "\u0627\u0633\u06a9\u0627\u0646\u0633\u0646"
    ],
    "name:fin_x_preferred":[
        "Skansen"
    ],
    "name:fra_x_preferred":[
        "Skansen"
    ],
    "name:heb_x_preferred":[
        "\u05e1\u05e7\u05d0\u05e0\u05e1\u05df"
    ],
    "name:hun_x_preferred":[
        "Skansen"
    ],
    "name:ita_x_preferred":[
        "Skansen"
    ],
    "name:jpn_x_preferred":[
        "\u30b9\u30ab\u30f3\u30bb\u30f3"
    ],
    "name:kor_x_preferred":[
        "\uc2a4\uce78\uc13c"
    ],
    "name:lav_x_preferred":[
        "Skansens"
    ],
    "name:nld_x_preferred":[
        "Skansen"
    ],
    "name:nor_x_preferred":[
        "Skansen"
    ],
    "name:olo_x_preferred":[
        "Skansen"
    ],
    "name:por_x_preferred":[
        "Skansen"
    ],
    "name:rus_x_preferred":[
        "\u0421\u043a\u0430\u043d\u0441\u0435\u043d"
    ],
    "name:spa_x_preferred":[
        "Skansen"
    ],
    "name:swe_x_preferred":[
        "Skansen"
    ],
    "name:ukr_x_preferred":[
        "\u0421\u043a\u0430\u043d\u0441\u0435\u043d"
    ],
    "name:zho_x_preferred":[
        "\u65af\u582a\u68ee\u535a\u7269\u9928"
    ],
    "qs_pg:aaroncc":"SE",
    "qs_pg:gn_country":"SE",
    "qs_pg:name":"Skansen",
    "qs_pg:name_adm0":"Sverige",
    "qs_pg:name_adm1":"Stockholms L\u00e4n",
    "qs_pg:photos":143,
    "qs_pg:photos_1k":29,
    "qs_pg:photos_9k":1,
    "qs_pg:photos_9r":3,
    "qs_pg:photos_all":143,
    "qs_pg:photos_sr":3,
    "qs_pg:pop_sr":0,
    "qs_pg:qs_pg_placetype":"locality",
    "qs_pg:qs_pg_placetype_gp":"Town",
    "qs_pg:woe_adm0":23424954,
    "woe:adm0_id":23424954,
    "woe:name_adm0":"Sverige",
    "woe:name_adm1":"Stockholms L\u00e4n",
    "woe:placetype":"Town",
    "wof:name":"Skansen",
    "wof:placetype":"locality"
},
  "geometry": {"coordinates":[17.74955,59.042938],"type":"Point"}
}