{
  "type": "Feature",
  "properties": {
    "gn:admin1_code":"8.0",
    "gn:admin2_code":"680.0",
    "gn:asciiname":"Avlosa",
    "gn:country_code":"SE",
    "gn:dem":105,
    "gn:feature_class":"P",
    "gn:feature_code":"PPL",
    "gn:name":"Avl\u00f6sa",
    "gn:population":0,
    "gn:timezone":"Europe/Stockholm",
    "iso:country":"SE",
    "name:nor_x_preferred":[
        "Avl\u00f6sa"
    ],
    "name:nor_x_variant":[
        "Avl\u00f8sa"
    ],
    "name:und_x_variant":[
        "Avl\u00f6sa"
    ],
    "wof:name":"Avlosa",
    "wof:placetype":"locality"
},
  "geometry": {"coordinates":[14.35,58.06667],"type":"Point"}
}