{
  "type": "Feature",
  "properties": {
    "gn:admin1_code":"2.0",
    "gn:admin2_code":"1060.0",
    "gn:asciiname":"Hasslehult",
    "gn:country_code":"SE",
    "gn:dem":70,
    "gn:feature_class":"P",
    "gn:feature_code":"PPL",
    "gn:name":"H\u00e4sslehult",
    "gn:population":0,
    "gn:timezone":"Europe/Stockholm",
    "iso:country":"SE",
    "wof:name":"Hasslehult",
    "wof:placetype":"locality"
},
  "geometry": {"coordinates":[14.56667,56.25],"type":"Point"}
}