{
  "type": "Feature",
  "properties": {
    "gn:admin1_code":"3.0",
    "gn:admin2_code":"2184.0",
    "gn:asciiname":"Krako Hamn",
    "gn:country_code":"SE",
    "gn:dem":-9999,
    "gn:feature_class":"P",
    "gn:feature_code":"PPL",
    "gn:name":"Kr\u00e5k\u00f6 Hamn",
    "gn:population":0,
    "gn:timezone":"Europe/Stockholm",
    "iso:country":"SE",
    "name:nor_x_preferred":[
        "Kr\u00e5k\u00f6 Hamn"
    ],
    "name:nor_x_variant":[
        "Kr\u00e5k\u00f8 Hamn"
    ],
    "name:und_x_variant":[
        "Kr\u00e5k\u00f6 Hamn"
    ],
    "wof:name":"Krako Hamn",
    "wof:placetype":"locality"
},
  "geometry": {"coordinates":[17.32361,61.56583000000001],"type":"Point"}
}