{
  "type": "Feature",
  "properties": {
    "gn:admin1_code":"10.0",
    "gn:admin2_code":"2082.0",
    "gn:asciiname":"Murmastarbo",
    "gn:country_code":"SE",
    "gn:dem":106,
    "gn:feature_class":"P",
    "gn:feature_code":"PPL",
    "gn:name":"Murm\u00e4starbo",
    "gn:population":0,
    "gn:timezone":"Europe/Stockholm",
    "iso:country":"SE",
    "wof:name":"Murmastarbo",
    "wof:placetype":"locality"
},
  "geometry": {"coordinates":[15.78333,60.43333000000001],"type":"Point"}
}