{
  "type": "Feature",
  "properties": {
    "gn:admin1_code":"6.0",
    "gn:admin2_code":"1383.0",
    "gn:asciiname":"Gudmundared",
    "gn:country_code":"SE",
    "gn:dem":177,
    "gn:feature_class":"P",
    "gn:feature_code":"PPL",
    "gn:name":"Gudmundared",
    "gn:population":0,
    "gn:timezone":"Europe/Stockholm",
    "iso:country":"SE",
    "wof:name":"Gudmundared",
    "wof:placetype":"locality"
},
  "geometry": {"coordinates":[12.66667,57.28333000000001],"type":"Point"}
}