{
  "type": "Feature",
  "properties": {
    "gn:admin1_code":"15.0",
    "gn:admin2_code":"1880.0",
    "gn:asciiname":"Okna",
    "gn:country_code":"SE",
    "gn:dem":63,
    "gn:feature_class":"P",
    "gn:feature_code":"PPL",
    "gn:name":"\u00d6kna",
    "gn:population":0,
    "gn:timezone":"Europe/Stockholm",
    "iso:country":"SE",
    "name:ceb_x_preferred":[
        "Okna"
    ],
    "name:ces_x_preferred":[
        "Okna"
    ],
    "name:deu_x_preferred":[
        "Okna"
    ],
    "name:nor_x_preferred":[
        "\u00d6kna"
    ],
    "name:nor_x_variant":[
        "\u00d8kna"
    ],
    "name:pol_x_preferred":[
        "Okna"
    ],
    "name:rus_x_preferred":[
        "\u041e\u043a\u043d\u0430"
    ],
    "name:slk_x_preferred":[
        "Okna"
    ],
    "name:swe_x_preferred":[
        "Okna"
    ],
    "wof:name":"Okna",
    "wof:placetype":"locality"
},
  "geometry": {"coordinates":[14.83333,59.16667],"type":"Point"}
}