{
  "type": "Feature",
  "properties": {
    "gn:admin1_code":"24.0",
    "gn:admin2_code":"2280.0",
    "gn:admin3_code":"228002.0",
    "gn:admin4_code":"2472.0",
    "gn:asciiname":"Storsela",
    "gn:country_code":"SE",
    "gn:dem":247,
    "gn:feature_class":"P",
    "gn:feature_code":"PPL",
    "gn:name":"Storsela",
    "gn:population":0,
    "gn:timezone":"Europe/Stockholm",
    "iso:country":"SE",
    "wof:name":"Storsela",
    "wof:placetype":"locality"
},
  "geometry": {"coordinates":[17.61667000000001,62.81667],"type":"Point"}
}