{
  "type": "Feature",
  "properties": {
    "gn:admin1_code":"6.0",
    "gn:admin2_code":"1383.0",
    "gn:asciiname":"Arnaes",
    "gn:country_code":"SE",
    "gn:dem":14,
    "gn:feature_class":"P",
    "gn:feature_code":"PPL",
    "gn:name":"\u00c5rn\u00e4s",
    "gn:population":679,
    "gn:timezone":"Europe/Stockholm",
    "iso:country":"SE",
    "name:swe_x_preferred":[
        "\u00c5rn\u00e4s"
    ],
    "name:und_x_variant":[
        "\u00c5rn\u00e4s"
    ],
    "wof:name":"Arnaes",
    "wof:placetype":"locality",
    "wof:population":679
},
  "geometry": {"coordinates":[12.21293,57.20627],"type":"Point"}
}