{
  "type": "Feature",
  "properties": {
    "gn:admin1_code":"25.0",
    "gn:admin2_code":"1981.0",
    "gn:asciiname":"Grallsta",
    "gn:country_code":"SE",
    "gn:dem":61,
    "gn:feature_class":"P",
    "gn:feature_code":"PPL",
    "gn:name":"Gr\u00e4llsta",
    "gn:population":0,
    "gn:timezone":"Europe/Stockholm",
    "iso:country":"SE",
    "wof:name":"Grallsta",
    "wof:placetype":"locality"
},
  "geometry": {"coordinates":[16.54301,59.85536999999999],"type":"Point"}
}