{
  "type": "Feature",
  "properties": {
    "gn:admin1_code":"24.0",
    "gn:admin2_code":"2282.0",
    "gn:admin3_code":"228207.0",
    "gn:admin4_code":"2452.0",
    "gn:asciiname":"Norrland",
    "gn:country_code":"SE",
    "gn:dem":-9999,
    "gn:feature_class":"P",
    "gn:feature_code":"PPL",
    "gn:name":"Norrland",
    "gn:population":0,
    "gn:timezone":"Europe/Stockholm",
    "iso:country":"SE",
    "wof:name":"Norrland",
    "wof:placetype":"locality"
},
  "geometry": {"coordinates":[17.88332999999999,62.91667],"type":"Point"}
}