{
  "type": "Feature",
  "properties": {
    "gn:admin1_code":"24.0",
    "gn:admin2_code":"2282.0",
    "gn:admin3_code":"228207.0",
    "gn:admin4_code":"2452.0",
    "gn:asciiname":"Norrland",
    "gn:country_code":"SE",
    "gn:dem":-9999,
    "gn:feature_class":"P",
    "gn:feature_code":"PPL",
    "gn:name":"Norrland",
    "gn:population":0,
    "gn:timezone":"Europe/Stockholm",
    "iso:country":"SE",
    "name:ara_x_preferred":[
        "\u0646\u0648\u0631\u0644\u0646\u062f"
    ],
    "name:bel_x_preferred":[
        "\u041d\u043e\u0440\u043b\u0430\u043d\u0434"
    ],
    "name:bre_x_preferred":[
        "Norrland"
    ],
    "name:cat_x_preferred":[
        "Norrland"
    ],
    "name:ces_x_preferred":[
        "Norrland"
    ],
    "name:dan_x_preferred":[
        "Norrland"
    ],
    "name:deu_x_preferred":[
        "Norrland"
    ],
    "name:epo_x_preferred":[
        "Norrland"
    ],
    "name:est_x_preferred":[
        "Norrland"
    ],
    "name:eus_x_preferred":[
        "Norrland"
    ],
    "name:fas_x_preferred":[
        "\u0646\u0648\u0631\u0644\u0627\u0646\u062f"
    ],
    "name:fin_x_preferred":[
        "Norlanti"
    ],
    "name:fra_x_preferred":[
        "Norrland"
    ],
    "name:fry_x_preferred":[
        "Norrland"
    ],
    "name:heb_x_preferred":[
        "\u05e0\u05d5\u05e8\u05dc\u05e0\u05d3"
    ],
    "name:hrv_x_preferred":[
        "Norrland"
    ],
    "name:hun_x_preferred":[
        "Norrland"
    ],
    "name:ind_x_preferred":[
        "Norrland"
    ],
    "name:isl_x_preferred":[
        "Nor\u00f0urland"
    ],
    "name:ita_x_preferred":[
        "Norrland"
    ],
    "name:jpn_x_preferred":[
        "\u30ce\u30fc\u30eb\u30e9\u30f3\u30c9"
    ],
    "name:kor_x_preferred":[
        "\ub178\ub97c\ub780\ub4dc"
    ],
    "name:lav_x_preferred":[
        "Norlande"
    ],
    "name:lit_x_preferred":[
        "Norlandas"
    ],
    "name:nld_x_preferred":[
        "Norrland"
    ],
    "name:nno_x_preferred":[
        "Norrland"
    ],
    "name:nor_x_preferred":[
        "Norrland"
    ],
    "name:pol_x_preferred":[
        "Norrland"
    ],
    "name:por_x_preferred":[
        "Norl\u00e2ndia"
    ],
    "name:ron_x_preferred":[
        "Norrland"
    ],
    "name:rus_x_preferred":[
        "\u041d\u043e\u0440\u0440\u043b\u0430\u043d\u0434"
    ],
    "name:sco_x_preferred":[
        "Norrland"
    ],
    "name:sna_x_preferred":[
        "Norrland"
    ],
    "name:spa_x_preferred":[
        "Norrland"
    ],
    "name:srp_x_preferred":[
        "\u041d\u043e\u0440\u043b\u0430\u043d\u0434"
    ],
    "name:swe_x_preferred":[
        "Norrland"
    ],
    "name:ukr_x_preferred":[
        "\u041d\u043e\u0440\u0440\u043b\u0430\u043d\u0434"
    ],
    "name:uzb_x_preferred":[
        "Norland"
    ],
    "name:vie_x_preferred":[
        "Norrland"
    ],
    "name:vol_x_preferred":[
        "Norl\u00e4ni\u00e4n"
    ],
    "name:xmf_x_preferred":[
        "\u10dc\u10dd\u10e0\u10da\u10d0\u10dc\u10d3\u10d8"
    ],
    "name:zho_x_preferred":[
        "\u8afe\u723e\u862d"
    ],
    "wof:name":"Norrland",
    "wof:placetype":"locality"
},
  "geometry": {"coordinates":[17.88332999999999,62.91667],"type":"Point"}
}