{
  "type": "Feature",
  "properties": {
    "gn:admin1_code":"10.0",
    "gn:admin2_code":"2029.0",
    "gn:asciiname":"Ovre Heden",
    "gn:cc2":"SE",
    "gn:country_code":"SE",
    "gn:dem":186,
    "gn:feature_class":"P",
    "gn:feature_code":"PPL",
    "gn:name":"\u00d6vre Heden",
    "gn:population":0,
    "gn:timezone":"Europe/Stockholm",
    "iso:country":"SE",
    "name:nor_x_preferred":[
        "\u00d6vre Heden"
    ],
    "name:nor_x_variant":[
        "\u00d8vre Heden"
    ],
    "name:und_x_variant":[
        "Ofvre Heden",
        "\u00d6vre Heden"
    ],
    "wof:name":"Ovre Heden",
    "wof:placetype":"locality"
},
  "geometry": {"coordinates":[15.08333,60.66667],"type":"Point"}
}