{
  "type": "Feature",
  "properties": {
    "gn:admin1_code":"12.0",
    "gn:admin2_code":"781.0",
    "gn:asciiname":"Viggasa",
    "gn:country_code":"SE",
    "gn:dem":175,
    "gn:feature_class":"P",
    "gn:feature_code":"PPL",
    "gn:name":"Vigg\u00e5sa",
    "gn:population":0,
    "gn:timezone":"Europe/Stockholm",
    "iso:country":"SE",
    "wof:name":"Viggasa",
    "wof:placetype":"locality"
},
  "geometry": {"coordinates":[13.56667,56.76667],"type":"Point"}
}