{
  "type": "Feature",
  "properties": {
    "gn:admin1_code":"8.0",
    "gn:admin2_code":"682.0",
    "gn:asciiname":"Kull",
    "gn:country_code":"SE",
    "gn:dem":265,
    "gn:feature_class":"P",
    "gn:feature_code":"PPL",
    "gn:name":"Kull",
    "gn:population":0,
    "gn:timezone":"Europe/Stockholm",
    "iso:country":"SE",
    "name:ita_x_preferred":[
        "Kull"
    ],
    "name:swe_x_preferred":[
        "Kull"
    ],
    "name:ukr_x_preferred":[
        "\u041a\u0443\u043b\u043b"
    ],
    "wof:name":"Kull",
    "wof:placetype":"locality"
},
  "geometry": {"coordinates":[14.71667,57.48333],"type":"Point"}
}