{
  "type": "Feature",
  "properties": {
    "gn:admin1_code":"5.0",
    "gn:admin2_code":"980.0",
    "gn:asciiname":"Eke",
    "gn:country_code":"SE",
    "gn:dem":23,
    "gn:feature_class":"P",
    "gn:feature_code":"PPL",
    "gn:name":"Eke",
    "gn:population":0,
    "gn:timezone":"Europe/Stockholm",
    "iso:country":"SE",
    "name:bre_x_preferred":[
        "Eke"
    ],
    "name:ceb_x_preferred":[
        "Eke"
    ],
    "name:deu_x_preferred":[
        "Eke"
    ],
    "name:est_x_preferred":[
        "EKE"
    ],
    "name:nld_x_preferred":[
        "Eke"
    ],
    "name:swe_x_preferred":[
        "Eke"
    ],
    "name:vls_x_preferred":[
        "Eke"
    ],
    "wof:name":"Eke",
    "wof:placetype":"locality"
},
  "geometry": {"coordinates":[18.38439,57.16792],"type":"Point"}
}