{
  "type": "Feature",
  "properties": {
    "gn:admin1_code":"3.0",
    "gn:admin2_code":"2183.0",
    "gn:asciiname":"Bjortomta",
    "gn:country_code":"SE",
    "gn:dem":103,
    "gn:feature_class":"P",
    "gn:feature_code":"PPL",
    "gn:name":"Bj\u00f6rtomta",
    "gn:population":0,
    "gn:timezone":"Europe/Stockholm",
    "iso:country":"SE",
    "name:nor_x_preferred":[
        "Bj\u00f6rtomta"
    ],
    "name:nor_x_variant":[
        "Bj\u00f8rtomta"
    ],
    "wof:name":"Bjortomta",
    "wof:placetype":"locality"
},
  "geometry": {"coordinates":[16.63332999999999,61.35],"type":"Point"}
}