{
  "type": "Feature",
  "properties": {
    "gn:admin1_code":"18.0",
    "gn:admin2_code":"428.0",
    "gn:asciiname":"Attersta",
    "gn:country_code":"SE",
    "gn:dem":41,
    "gn:feature_class":"P",
    "gn:feature_code":"PPL",
    "gn:name":"\u00c4ttersta",
    "gn:population":0,
    "gn:timezone":"Europe/Stockholm",
    "iso:country":"SE",
    "wof:name":"Attersta",
    "wof:placetype":"locality"
},
  "geometry": {"coordinates":[15.96667,59.13333000000001],"type":"Point"}
}