{
  "type": "Feature",
  "properties": {
    "gn:admin1_code":"6.0",
    "gn:admin2_code":"1380.0",
    "gn:asciiname":"Fammarp",
    "gn:country_code":"SE",
    "gn:dem":23,
    "gn:feature_class":"P",
    "gn:feature_code":"PPL",
    "gn:name":"Fammarp",
    "gn:population":0,
    "gn:timezone":"Europe/Stockholm",
    "iso:country":"SE",
    "wof:name":"Fammarp",
    "wof:placetype":"locality"
},
  "geometry": {"coordinates":[12.76667,56.68333000000001],"type":"Point"}
}