{
  "type": "Feature",
  "properties": {
    "gn:admin1_code":"14.0",
    "gn:admin2_code":"2518.0",
    "gn:asciiname":"Vyoni",
    "gn:country_code":"SE",
    "gn:dem":146,
    "gn:feature_class":"P",
    "gn:feature_code":"PPL",
    "gn:name":"Vy\u00f6ni",
    "gn:population":0,
    "gn:timezone":"Europe/Stockholm",
    "iso:country":"SE",
    "name:nor_x_preferred":[
        "Vy\u00f6ni"
    ],
    "name:nor_x_variant":[
        "Vy\u00f8ni"
    ],
    "name:und_x_variant":[
        "Vy\u00f6ni"
    ],
    "wof:name":"Vyoni",
    "wof:placetype":"locality"
},
  "geometry": {"coordinates":[23.696,66.58459000000001],"type":"Point"}
}