{
  "type": "Feature",
  "properties": {
    "gn:admin1_code":"3.0",
    "gn:admin2_code":"2181.0",
    "gn:asciiname":"Osterbo",
    "gn:country_code":"SE",
    "gn:dem":79,
    "gn:feature_class":"P",
    "gn:feature_code":"PPL",
    "gn:name":"\u00d6sterbo",
    "gn:population":0,
    "gn:timezone":"Europe/Stockholm",
    "iso:country":"SE",
    "name:nor_x_preferred":[
        "\u00d6sterbo"
    ],
    "name:nor_x_variant":[
        "\u00d8sterbo"
    ],
    "name:und_x_variant":[
        "\u00d6sterbo"
    ],
    "wof:name":"Osterbo",
    "wof:placetype":"locality"
},
  "geometry": {"coordinates":[16.71667,60.45],"type":"Point"}
}