{
  "type": "Feature",
  "properties": {
    "iso:country":"SE",
    "name:swe_x_preferred":[
        "Neglingeon"
    ],
    "qs:gn_adm0_cc":"SE",
    "qs:gn_local":2680460,
    "qs:gn_nam_loc":"Saltsj\u00f6baden, Nacka, Stockholms L\u00e4n, SE",
    "qs:gn_namadm1":"26",
    "qs:local_max":694,
    "qs:local_sum":1275,
    "qs:localhoods":7,
    "qs:name":"Neglingeon",
    "qs:name_adm0":"Sverige",
    "qs:name_adm1":"Stockholms L\u00e4n",
    "qs:name_adm2":"Nacka",
    "qs:name_local":"Saltsj\u00f6baden",
    "qs:photo_max":149,
    "qs:photo_sum":694,
    "qs:placetype":"Suburb",
    "qs:quad_count":42,
    "qs:woe_adm0":23424954,
    "qs:woe_adm1":2347067,
    "qs:woe_adm2":12587469,
    "qs:woe_lau":0,
    "qs:woe_local":903260,
    "qs:woe_ver":"7.10.0",
    "wof:name":"Neglingeon",
    "wof:placetype":"neighbourhood"
},
  "geometry": {"coordinates":[18.306056,59.288073],"type":"Point"}
}