{
  "type": "Feature",
  "properties": {
    "gn:admin1_code":"6.0",
    "gn:admin2_code":"1380.0",
    "gn:asciiname":"Fjallgime",
    "gn:country_code":"SE",
    "gn:dem":57,
    "gn:feature_class":"P",
    "gn:feature_code":"PPL",
    "gn:name":"Fj\u00e4llgime",
    "gn:population":0,
    "gn:timezone":"Europe/Stockholm",
    "iso:country":"SE",
    "wof:name":"Fjallgime",
    "wof:placetype":"locality"
},
  "geometry": {"coordinates":[12.95,56.76667],"type":"Point"}
}