{
  "type": "Feature",
  "properties": {
    "gn:admin1_code":"16.0",
    "gn:admin2_code":"583.0",
    "gn:asciiname":"Hyttefallet",
    "gn:country_code":"SE",
    "gn:dem":85,
    "gn:feature_class":"P",
    "gn:feature_code":"PPL",
    "gn:name":"Hyttefallet",
    "gn:population":0,
    "gn:timezone":"Europe/Stockholm",
    "iso:country":"SE",
    "wof:name":"Hyttefallet",
    "wof:placetype":"locality"
},
  "geometry": {"coordinates":[15.41667,58.66667],"type":"Point"}
}