{
  "type": "Feature",
  "properties": {
    "gn:admin1_code":"9.0",
    "gn:admin2_code":"880.0",
    "gn:asciiname":"Snacko Hamn",
    "gn:country_code":"SE",
    "gn:dem":5,
    "gn:feature_class":"P",
    "gn:feature_code":"PPL",
    "gn:name":"Sn\u00e4ck\u00f6 Hamn",
    "gn:population":0,
    "gn:timezone":"Europe/Stockholm",
    "iso:country":"SE",
    "wof:name":"Snacko Hamn",
    "wof:placetype":"locality"
},
  "geometry": {"coordinates":[16.43333,56.85833],"type":"Point"}
}