{
  "type": "Feature",
  "properties": {
    "gn:admin1_code":"15.0",
    "gn:admin2_code":"1881.0",
    "gn:asciiname":"Sodra Via",
    "gn:country_code":"SE",
    "gn:dem":50,
    "gn:feature_class":"P",
    "gn:feature_code":"PPL",
    "gn:name":"S\u00f6dra Via",
    "gn:population":0,
    "gn:timezone":"Europe/Stockholm",
    "iso:country":"SE",
    "name:nor_x_preferred":[
        "S\u00f6dra Via"
    ],
    "name:nor_x_variant":[
        "S\u00f8dra Via"
    ],
    "wof:name":"Sodra Via",
    "wof:placetype":"locality"
},
  "geometry": {"coordinates":[15.13333,59.11666999999999],"type":"Point"}
}