{
  "type": "Feature",
  "properties": {
    "gn:admin1_code":"28.0",
    "gn:admin2_code":"1440.0",
    "gn:asciiname":"Grunne",
    "gn:country_code":"SE",
    "gn:dem":25,
    "gn:feature_class":"P",
    "gn:feature_code":"PPL",
    "gn:name":"Grunne",
    "gn:population":0,
    "gn:timezone":"Europe/Stockholm",
    "iso:country":"SE",
    "wof:name":"Grunne",
    "wof:placetype":"locality"
},
  "geometry": {"coordinates":[12.13333,57.93333000000001],"type":"Point"}
}