{
  "type": "Feature",
  "properties": {
    "gn:admin1_code":"22.0",
    "gn:admin2_code":"1737.0",
    "gn:asciiname":"Boseberg",
    "gn:country_code":"SE",
    "gn:dem":296,
    "gn:feature_class":"P",
    "gn:feature_code":"PPL",
    "gn:name":"Boseberg",
    "gn:population":0,
    "gn:timezone":"Europe/Stockholm",
    "iso:country":"SE",
    "wof:name":"Boseberg",
    "wof:placetype":"locality"
},
  "geometry": {"coordinates":[12.75,60.23333],"type":"Point"}
}