{
  "type": "Feature",
  "properties": {
    "gn:admin1_code":"28.0",
    "gn:admin2_code":"1446.0",
    "gn:asciiname":"Rodesund",
    "gn:country_code":"SE",
    "gn:dem":92,
    "gn:feature_class":"P",
    "gn:feature_code":"PPL",
    "gn:name":"R\u00f6desund",
    "gn:population":0,
    "gn:timezone":"Europe/Stockholm",
    "iso:country":"SE",
    "name:nor_x_preferred":[
        "R\u00f6desund"
    ],
    "name:nor_x_variant":[
        "R\u00f8desund"
    ],
    "name:und_x_variant":[
        "R\u00f6desund"
    ],
    "wof:name":"Rodesund",
    "wof:placetype":"locality"
},
  "geometry": {"coordinates":[14.50556,58.53955],"type":"Point"}
}