{
  "type": "Feature",
  "properties": {
    "gn:admin1_code":"8.0",
    "gn:admin2_code":"685.0",
    "gn:asciiname":"Stora Fagraryd",
    "gn:country_code":"SE",
    "gn:dem":217,
    "gn:feature_class":"P",
    "gn:feature_code":"PPL",
    "gn:name":"Stora Fagraryd",
    "gn:population":0,
    "gn:timezone":"Europe/Stockholm",
    "iso:country":"SE",
    "wof:name":"Stora Fagraryd",
    "wof:placetype":"locality"
},
  "geometry": {"coordinates":[15.11667,57.35],"type":"Point"}
}