{
  "type": "Feature",
  "properties": {
    "gn:admin1_code":"24.0",
    "gn:admin2_code":"2280.0",
    "gn:admin3_code":"228003.0",
    "gn:admin4_code":"2469.0",
    "gn:asciiname":"Hogsnas",
    "gn:country_code":"SE",
    "gn:dem":113,
    "gn:feature_class":"P",
    "gn:feature_code":"PPL",
    "gn:name":"H\u00f6gsn\u00e4s",
    "gn:population":0,
    "gn:timezone":"Europe/Stockholm",
    "iso:country":"SE",
    "wof:name":"Hogsnas",
    "wof:placetype":"locality"
},
  "geometry": {"coordinates":[17.71751,62.55619],"type":"Point"}
}