{
  "type": "Feature",
  "properties": {
    "gn:admin1_code":"28.0",
    "gn:admin2_code":"1499.0",
    "gn:asciiname":"Ostra Tunhem",
    "gn:cc2":"SE",
    "gn:country_code":"SE",
    "gn:dem":226,
    "gn:feature_class":"P",
    "gn:feature_code":"PPL",
    "gn:name":"\u00d6stra Tunhem",
    "gn:population":0,
    "gn:timezone":"Europe/Stockholm",
    "iso:country":"SE",
    "name:nor_x_preferred":[
        "\u00d6stra Tunhem"
    ],
    "name:nor_x_variant":[
        "\u00d8stra Tunhem"
    ],
    "name:und_x_variant":[
        "Tunhem",
        "\u00d6stra Tunhem"
    ],
    "wof:name":"Ostra Tunhem",
    "wof:placetype":"locality"
},
  "geometry": {"coordinates":[13.53306,58.21666999999999],"type":"Point"}
}