{
  "type": "Feature",
  "properties": {
    "gn:admin1_code":"21.0",
    "gn:admin2_code":"382.0",
    "gn:asciiname":"Kilby",
    "gn:country_code":"SE",
    "gn:dem":20,
    "gn:feature_class":"P",
    "gn:feature_code":"PPL",
    "gn:name":"Kilby",
    "gn:population":0,
    "gn:timezone":"Europe/Stockholm",
    "iso:country":"SE",
    "name:ceb_x_preferred":[
        "Kilby"
    ],
    "name:cym_x_preferred":[
        "Kilby"
    ],
    "name:pol_x_preferred":[
        "Kilby"
    ],
    "name:swe_x_preferred":[
        "Kilby"
    ],
    "wof:name":"Kilby",
    "wof:placetype":"locality"
},
  "geometry": {"coordinates":[18.06667,60.11666999999999],"type":"Point"}
}