{
  "type": "Feature",
  "properties": {
    "gn:admin1_code":"3.0",
    "gn:admin2_code":"2161.0",
    "gn:asciiname":"Vattuvalla",
    "gn:country_code":"SE",
    "gn:dem":194,
    "gn:feature_class":"P",
    "gn:feature_code":"PPL",
    "gn:name":"Vattuvalla",
    "gn:population":0,
    "gn:timezone":"Europe/Stockholm",
    "iso:country":"SE",
    "wof:name":"Vattuvalla",
    "wof:placetype":"locality"
},
  "geometry": {"coordinates":[15.91667,61.98333],"type":"Point"}
}