{
  "type": "Feature",
  "properties": {
    "gn:country":"SE",
    "gn:fcode":"PPL",
    "gn:population":251,
    "iso:country":"SE",
    "name:bul_x_preferred":[
        "\u041a\u0439\u0440\u043a\u0445\u0435\u0434\u0438\u043d\u0433\u0435"
    ],
    "name:ceb_x_preferred":[
        "Kyrkheddinge"
    ],
    "name:dan_x_preferred":[
        "Kyrkheddinge"
    ],
    "name:deu_x_preferred":[
        "Kyrkheddinge"
    ],
    "name:eng_x_preferred":[
        "Kyrkheddinge"
    ],
    "name:fra_x_preferred":[
        "Kyrkheddinge"
    ],
    "name:gle_x_preferred":[
        "Kyrkheddinge"
    ],
    "name:ita_x_preferred":[
        "Kyrkheddinge"
    ],
    "name:lld_x_preferred":[
        "Kyrkheddinge"
    ],
    "name:nan_x_preferred":[
        "Kyrkheddinge"
    ],
    "name:nld_x_preferred":[
        "Kyrkheddinge"
    ],
    "name:nno_x_preferred":[
        "Kyrkheddinge"
    ],
    "name:nob_x_preferred":[
        "Kyrkheddinge"
    ],
    "name:pol_x_preferred":[
        "Kyrkheddinge"
    ],
    "name:swe_x_preferred":[
        "Kyrkheddinge"
    ],
    "qs_pg:aaroncc":"SE",
    "qs_pg:gn_country":"SE",
    "qs_pg:gn_fcode":"PPL",
    "qs_pg:gn_pop":251,
    "qs_pg:name":"Kyrkheddinge",
    "qs_pg:name_adm0":"Sverige",
    "qs_pg:name_adm1":"Sk\u00e5ne L\u00e4n",
    "qs_pg:photos_9k":1,
    "qs_pg:photos_9r":1,
    "qs_pg:photos_all":1,
    "qs_pg:photos_sr":0,
    "qs_pg:pop_sr":2,
    "qs_pg:qs_pg_placetype":"locality",
    "qs_pg:qs_pg_placetype_gp":"Town",
    "qs_pg:woe_adm0":23424954,
    "woe:adm0_id":23424954,
    "woe:name_adm0":"Sverige",
    "woe:name_adm1":"Sk\u00e5ne L\u00e4n",
    "woe:placetype":"Town",
    "wof:name":"Kyrkheddinge",
    "wof:placetype":"locality",
    "wof:population":259
},
  "geometry": {"coordinates":[13.26667,55.65],"type":"Point"}
}