{
  "type": "Feature",
  "properties": {
    "gn:admin1_code":"7.0",
    "gn:admin2_code":"2326.0",
    "gn:asciiname":"Marntallsasen",
    "gn:cc2":"SE",
    "gn:country_code":"SE",
    "gn:dem":635,
    "gn:feature_class":"P",
    "gn:feature_code":"PPL",
    "gn:name":"Marntalls\u00e5sen",
    "gn:population":0,
    "gn:timezone":"Europe/Stockholm",
    "iso:country":"SE",
    "name:und_x_variant":[
        "Martalls\u00e5sen",
        "Marntalls\u00e5sen"
    ],
    "wof:name":"Marntallsasen",
    "wof:placetype":"locality"
},
  "geometry": {"coordinates":[14.03333,62.91667],"type":"Point"}
}