{
  "type": "Feature",
  "properties": {
    "gn:admin1_code":"28.0",
    "gn:admin2_code":"1494.0",
    "gn:asciiname":"Larstorp",
    "gn:country_code":"SE",
    "gn:dem":47,
    "gn:feature_class":"P",
    "gn:feature_code":"PPL",
    "gn:name":"Larstorp",
    "gn:population":0,
    "gn:timezone":"Europe/Stockholm",
    "iso:country":"SE",
    "wof:name":"Larstorp",
    "wof:placetype":"locality"
},
  "geometry": {"coordinates":[12.96667,58.54971999999999],"type":"Point"}
}