{
  "type": "Feature",
  "properties": {
    "gn:admin1_code":"8.0",
    "gn:admin2_code":"604.0",
    "gn:asciiname":"Skoldseryd",
    "gn:cc2":"SE",
    "gn:country_code":"SE",
    "gn:dem":291,
    "gn:feature_class":"P",
    "gn:feature_code":"PPL",
    "gn:name":"Sk\u00f6ldseryd",
    "gn:population":0,
    "gn:timezone":"Europe/Stockholm",
    "iso:country":"SE",
    "name:nor_x_preferred":[
        "Sk\u00f6ldseryd"
    ],
    "name:nor_x_variant":[
        "Sk\u00f8ldseryd"
    ],
    "name:und_x_variant":[
        "Sk\u00f6lseryd",
        "Sk\u00f6ldseryd"
    ],
    "wof:name":"Skoldseryd",
    "wof:placetype":"locality"
},
  "geometry": {"coordinates":[14.68333,57.86666999999999],"type":"Point"}
}