{
  "type": "Feature",
  "properties": {
    "gn:admin1_code":"25.0",
    "gn:admin2_code":"1981.0",
    "gn:asciiname":"Osby",
    "gn:country_code":"SE",
    "gn:dem":74,
    "gn:feature_class":"P",
    "gn:feature_code":"PPL",
    "gn:name":"\u00d6sby",
    "gn:population":0,
    "gn:timezone":"Europe/Stockholm",
    "iso:country":"SE",
    "name:nor_x_preferred":[
        "\u00d6sby"
    ],
    "name:nor_x_variant":[
        "\u00d8sby"
    ],
    "name:und_x_variant":[
        "\u00d6sby"
    ],
    "wof:name":"Osby",
    "wof:placetype":"locality"
},
  "geometry": {"coordinates":[16.28333,59.96666999999999],"type":"Point"}
}