{
  "type": "Feature",
  "properties": {
    "gn:admin1_code":"25.0",
    "gn:admin2_code":"1981.0",
    "gn:asciiname":"Osby",
    "gn:country_code":"SE",
    "gn:dem":74,
    "gn:feature_class":"P",
    "gn:feature_code":"PPL",
    "gn:name":"\u00d6sby",
    "gn:population":0,
    "gn:timezone":"Europe/Stockholm",
    "iso:country":"SE",
    "name:bul_x_preferred":[
        "\u041e\u0441\u0431\u044e"
    ],
    "name:ceb_x_preferred":[
        "Osby"
    ],
    "name:dan_x_preferred":[
        "Osby"
    ],
    "name:deu_x_preferred":[
        "Osby"
    ],
    "name:fao_x_preferred":[
        "Osby"
    ],
    "name:fas_x_preferred":[
        "\u0627\u0648\u0633\u0628\u06cc"
    ],
    "name:fin_x_preferred":[
        "Osby"
    ],
    "name:isl_x_preferred":[
        "Osby"
    ],
    "name:ita_x_preferred":[
        "Osby"
    ],
    "name:nld_x_preferred":[
        "Osby"
    ],
    "name:nno_x_preferred":[
        "Osby"
    ],
    "name:nor_x_preferred":[
        "\u00d6sby"
    ],
    "name:nor_x_variant":[
        "\u00d8sby",
        "Osby"
    ],
    "name:pol_x_preferred":[
        "Osby"
    ],
    "name:ron_x_preferred":[
        "Osby"
    ],
    "name:swe_x_preferred":[
        "Osby"
    ],
    "name:tur_x_preferred":[
        "Osby"
    ],
    "wof:name":"Osby",
    "wof:placetype":"locality"
},
  "geometry": {"coordinates":[16.28333,59.96666999999999],"type":"Point"}
}