{
  "type": "Feature",
  "properties": {
    "gn:admin1_code":"26.0",
    "gn:admin2_code":"127.0",
    "gn:asciiname":"Klippsta",
    "gn:country_code":"SE",
    "gn:dem":39,
    "gn:feature_class":"P",
    "gn:feature_code":"PPL",
    "gn:name":"Klippsta",
    "gn:population":0,
    "gn:timezone":"Europe/Stockholm",
    "iso:country":"SE",
    "wof:name":"Klippsta",
    "wof:placetype":"locality"
},
  "geometry": {"coordinates":[17.75,59.13333000000001],"type":"Point"}
}