{
  "type": "Feature",
  "properties": {
    "gn:admin1_code":"23.0",
    "gn:admin2_code":"2401.0",
    "gn:asciiname":"Haknas Backen",
    "gn:cc2":"SE",
    "gn:country_code":"SE",
    "gn:dem":50,
    "gn:feature_class":"P",
    "gn:feature_code":"PPL",
    "gn:name":"H\u00e5kn\u00e4s Backen",
    "gn:population":0,
    "gn:timezone":"Europe/Stockholm",
    "iso:country":"SE",
    "name:und_x_variant":[
        "H\u00e5ken\u00e4s",
        "H\u00e5kn\u00e4s",
        "H\u00e5kn\u00e4s Backen"
    ],
    "wof:name":"Haknas Backen",
    "wof:placetype":"locality"
},
  "geometry": {"coordinates":[19.66667,63.58333],"type":"Point"}
}