{
  "type": "Feature",
  "properties": {
    "gn:admin1_code":"28.0",
    "gn:admin2_code":"1481.0",
    "gn:asciiname":"Sparrod",
    "gn:cc2":"SE",
    "gn:country_code":"SE",
    "gn:dem":53,
    "gn:feature_class":"P",
    "gn:feature_code":"PPL",
    "gn:name":"Sp\u00e5rr\u00f6d",
    "gn:population":0,
    "gn:timezone":"Europe/Stockholm",
    "iso:country":"SE",
    "name:nor_x_preferred":[
        "Sp\u00e5rr\u00f6d"
    ],
    "name:nor_x_variant":[
        "Sp\u00e5rr\u00f8d"
    ],
    "name:und_x_variant":[
        "Sp\u00e5rred",
        "Sp\u00e5rr\u00f6d"
    ],
    "wof:name":"Sparrod",
    "wof:placetype":"locality"
},
  "geometry": {"coordinates":[12.08333,57.61666999999999],"type":"Point"}
}