{
  "type": "Feature",
  "properties": {
    "gn:gn_country":"SE",
    "gn:gn_fcode":"PPL",
    "gn:gn_pop":220,
    "gn:population":220,
    "iso:country":"SE",
    "name:dan_x_preferred":[
        "\u00d6vre Soppero"
    ],
    "name:deu_x_preferred":[
        "\u00d6vre Soppero"
    ],
    "name:eng_x_preferred":[
        "\u00d6vre Soppero"
    ],
    "name:fra_x_preferred":[
        "\u00d6vre Soppero"
    ],
    "name:nan_x_preferred":[
        "\u00d6vre Soppero"
    ],
    "name:nds_x_preferred":[
        "\u00d6vre Soppero"
    ],
    "name:nld_x_preferred":[
        "\u00d6vre Soppero"
    ],
    "name:nno_x_preferred":[
        "\u00d6vre Soppero"
    ],
    "name:nob_x_preferred":[
        "\u00d6vre Soppero"
    ],
    "name:nor_x_preferred":[
        "\u00d8vre Soppero"
    ],
    "name:nor_x_variant":[
        "\u00d6vre Soppero"
    ],
    "name:pol_x_preferred":[
        "\u00d6vre Soppero"
    ],
    "name:rus_x_preferred":[
        "\u042d\u0432\u0440\u0435-\u0421\u043e\u043f\u043f\u0435\u0440\u0443"
    ],
    "name:swe_x_preferred":[
        "\u00d6vre Soppero"
    ],
    "name:unk_x_variant":[
        "Soppero"
    ],
    "qs_pg:aaroncc":"SE",
    "qs_pg:gn_country":"SE",
    "qs_pg:gn_fcode":"PPL",
    "qs_pg:gn_pop":220,
    "qs_pg:name":"\u00d6vre Soppero",
    "qs_pg:name_adm0":"Sverige",
    "qs_pg:name_adm1":"Norrbottens L\u00e4n",
    "qs_pg:photos_9k":1,
    "qs_pg:photos_9r":1,
    "qs_pg:photos_all":3,
    "qs_pg:photos_sr":0,
    "qs_pg:pop_sr":2,
    "qs_pg:qs_pg_placetype":"locality",
    "qs_pg:qs_pg_placetype_gp":"Town",
    "qs_pg:woe_adm0":23424954,
    "woe:adm0_id":23424954,
    "woe:name_adm0":"Sverige",
    "woe:name_adm1":"Norrbottens L\u00e4n",
    "woe:placetype":"Town",
    "wof:name":"\u00d6vre Soppero",
    "wof:placetype":"locality",
    "wof:population":220
},
  "geometry": {"coordinates":[21.68333,68.08333],"type":"Point"}
}