{
  "type": "Feature",
  "properties": {
    "gn:admin1_code":"28.0",
    "gn:admin2_code":"1485.0",
    "gn:asciiname":"Bjorkebacken",
    "gn:country_code":"SE",
    "gn:dem":84,
    "gn:feature_class":"P",
    "gn:feature_code":"PPL",
    "gn:name":"Bj\u00f6rkebacken",
    "gn:population":0,
    "gn:timezone":"Europe/Stockholm",
    "iso:country":"SE",
    "name:nor_x_preferred":[
        "Bj\u00f6rkebacken"
    ],
    "name:nor_x_variant":[
        "Bj\u00f8rkebacken"
    ],
    "wof:name":"Bjorkebacken",
    "wof:placetype":"locality"
},
  "geometry": {"coordinates":[12.01667,58.25],"type":"Point"}
}