{
  "type": "Feature",
  "properties": {
    "gn:admin1_code":"21.0",
    "gn:admin2_code":"380.0",
    "gn:asciiname":"Lot",
    "gn:country_code":"SE",
    "gn:dem":48,
    "gn:feature_class":"P",
    "gn:feature_code":"PPL",
    "gn:name":"L\u00f6t",
    "gn:population":0,
    "gn:timezone":"Europe/Stockholm",
    "iso:country":"SE",
    "name:nor_x_preferred":[
        "L\u00f6t"
    ],
    "name:nor_x_variant":[
        "L\u00f8t"
    ],
    "name:und_x_variant":[
        "L\u00f6t"
    ],
    "wof:name":"Lot",
    "wof:placetype":"locality"
},
  "geometry": {"coordinates":[17.93332999999999,59.86666999999999],"type":"Point"}
}