{
  "type": "Feature",
  "properties": {
    "gn:country":"SE",
    "gn:fcode":"PPL",
    "gn:population":657,
    "iso:country":"SE",
    "name:ceb_x_preferred":[
        "P\u00e5ryd"
    ],
    "name:eng_x_preferred":[
        "P\u00e5ryd"
    ],
    "name:ita_x_preferred":[
        "P\u00e5ryd"
    ],
    "name:nan_x_preferred":[
        "P\u00e5ryd"
    ],
    "name:nld_x_preferred":[
        "P\u00e5ryd"
    ],
    "name:nno_x_preferred":[
        "P\u00e5ryd"
    ],
    "name:nob_x_preferred":[
        "P\u00e5ryd"
    ],
    "name:swe_x_preferred":[
        "P\u00e5ryd"
    ],
    "qs_pg:aaroncc":"SE",
    "qs_pg:gn_country":"SE",
    "qs_pg:gn_fcode":"PPL",
    "qs_pg:gn_pop":657,
    "qs_pg:name":"P\u00e5ryd",
    "qs_pg:name_adm0":"Sverige",
    "qs_pg:name_adm1":"Kalmar L\u00e4n",
    "qs_pg:photos_9k":1,
    "qs_pg:photos_9r":1,
    "qs_pg:photos_all":3,
    "qs_pg:photos_sr":0,
    "qs_pg:pop_sr":2,
    "qs_pg:qs_pg_placetype":"locality",
    "qs_pg:qs_pg_placetype_gp":"Town",
    "qs_pg:woe_adm0":23424954,
    "woe:adm0_id":23424954,
    "woe:name_adm0":"Sverige",
    "woe:name_adm1":"Kalmar L\u00e4n",
    "woe:placetype":"Town",
    "wof:name":"P\u00e5ryd",
    "wof:placetype":"locality",
    "wof:population":663
},
  "geometry": {"coordinates":[15.91667,56.56667],"type":"Point"}
}