{
  "type": "Feature",
  "properties": {
    "gn:admin1_code":"26.0",
    "gn:admin2_code":"117.0",
    "gn:asciiname":"Vallersvik",
    "gn:country_code":"SE",
    "gn:dem":12,
    "gn:feature_class":"P",
    "gn:feature_code":"PPL",
    "gn:name":"Vallersvik",
    "gn:population":0,
    "gn:timezone":"Europe/Stockholm",
    "iso:country":"SE",
    "wof:name":"Vallersvik",
    "wof:placetype":"locality"
},
  "geometry": {"coordinates":[18.45333,59.50167],"type":"Point"}
}