{
  "type": "Feature",
  "properties": {
    "gn:admin1_code":"28.0",
    "gn:admin2_code":"1492.0",
    "gn:asciiname":"Ostra Byn",
    "gn:cc2":"SE",
    "gn:country_code":"SE",
    "gn:dem":84,
    "gn:feature_class":"P",
    "gn:feature_code":"PPL",
    "gn:name":"\u00d6stra Byn",
    "gn:population":0,
    "gn:timezone":"Europe/Stockholm",
    "iso:country":"SE",
    "name:nor_x_preferred":[
        "\u00d6stra Byn"
    ],
    "name:nor_x_variant":[
        "\u00d8stra Byn"
    ],
    "name:und_x_variant":[
        "Byn",
        "\u00d6stra Byn"
    ],
    "wof:name":"Ostra Byn",
    "wof:placetype":"locality"
},
  "geometry": {"coordinates":[12.63333,59.11666999999999],"type":"Point"}
}