{
  "type": "Feature",
  "properties": {
    "gn:gn_country":"SE",
    "iso:country":"SE",
    "qs_pg:aaroncc":"SE",
    "qs_pg:gn_country":"SE",
    "qs_pg:name":"Viggs\u00f6",
    "qs_pg:name_adm0":"Sverige",
    "qs_pg:name_adm1":"Stockholms L\u00e4n",
    "qs_pg:photos":415,
    "qs_pg:photos_1k":84,
    "qs_pg:photos_9k":2,
    "qs_pg:photos_9r":5,
    "qs_pg:photos_all":415,
    "qs_pg:photos_sr":6,
    "qs_pg:pop_sr":0,
    "qs_pg:qs_pg_placetype":"locality",
    "qs_pg:qs_pg_placetype_gp":"Town",
    "qs_pg:woe_adm0":23424954,
    "woe:adm0_id":23424954,
    "woe:name_adm0":"Sverige",
    "woe:name_adm1":"Stockholms L\u00e4n",
    "woe:placetype":"Town",
    "wof:name":"Viggs\u00f6",
    "wof:placetype":"locality"
},
  "geometry": {"coordinates":[18.564147,59.407477],"type":"Point"}
}