{
  "type": "Feature",
  "properties": {
    "gn:admin1_code":"27.0",
    "gn:admin2_code":"1285.0",
    "gn:asciiname":"Slogstorp",
    "gn:country_code":"SE",
    "gn:dem":91,
    "gn:feature_class":"P",
    "gn:feature_code":"PPL",
    "gn:name":"Slogstorp",
    "gn:population":0,
    "gn:timezone":"Europe/Stockholm",
    "iso:country":"SE",
    "wof:name":"Slogstorp",
    "wof:placetype":"locality"
},
  "geometry": {"coordinates":[13.45,55.75],"type":"Point"}
}