{
  "type": "Feature",
  "properties": {
    "gn:admin1_code":"10.0",
    "gn:admin2_code":"2021.0",
    "gn:asciiname":"Havberget",
    "gn:cc2":"SE",
    "gn:country_code":"SE",
    "gn:dem":372,
    "gn:feature_class":"P",
    "gn:feature_code":"PPL",
    "gn:name":"H\u00e5vberget",
    "gn:population":0,
    "gn:timezone":"Europe/Stockholm",
    "iso:country":"SE",
    "name:und_x_variant":[
        "H\u00e5fberget",
        "H\u00e5vberget"
    ],
    "wof:name":"Havberget",
    "wof:placetype":"locality"
},
  "geometry": {"coordinates":[14.61667,60.28333000000001],"type":"Point"}
}