{
  "type": "Feature",
  "properties": {
    "gn:admin1_code":"28.0",
    "gn:admin2_code":"1473.0",
    "gn:asciiname":"Habelsbolet",
    "gn:cc2":"SE",
    "gn:country_code":"SE",
    "gn:dem":128,
    "gn:feature_class":"P",
    "gn:feature_code":"PPL",
    "gn:name":"Habelsbolet",
    "gn:population":0,
    "gn:timezone":"Europe/Stockholm",
    "iso:country":"SE",
    "name:und_x_variant":[
        "Habbelsbolet",
        "Habelsbolet"
    ],
    "wof:name":"Habelsbolet",
    "wof:placetype":"locality"
},
  "geometry": {"coordinates":[14.31667,58.75],"type":"Point"}
}