{
  "type": "Feature",
  "properties": {
    "gn:admin1_code":"27.0",
    "gn:admin2_code":"1293.0",
    "gn:asciiname":"Havraljunga",
    "gn:country_code":"SE",
    "gn:dem":111,
    "gn:feature_class":"P",
    "gn:feature_code":"PPL",
    "gn:name":"Havraljunga",
    "gn:population":0,
    "gn:timezone":"Europe/Stockholm",
    "iso:country":"SE",
    "wof:name":"Havraljunga",
    "wof:placetype":"locality"
},
  "geometry": {"coordinates":[13.65,56.36666999999999],"type":"Point"}
}