{
  "type": "Feature",
  "properties": {
    "gn:admin1_code":"23.0",
    "gn:admin2_code":"2422.0",
    "gn:asciiname":"Staggtrask",
    "gn:country_code":"SE",
    "gn:dem":317,
    "gn:feature_class":"P",
    "gn:feature_code":"PPL",
    "gn:name":"Staggtr\u00e4sk",
    "gn:population":0,
    "gn:timezone":"Europe/Stockholm",
    "iso:country":"SE",
    "name:sju_x_preferred":[
        "St\u00e1gg\u00e1vrrie"
    ],
    "name:swe_x_preferred":[
        "Staggtr\u00e4sk"
    ],
    "wof:name":"Staggtrask",
    "wof:placetype":"locality"
},
  "geometry": {"coordinates":[17.83338,65.37468],"type":"Point"}
}