{
  "type": "Feature",
  "properties": {
    "gn:admin1_code":"8.0",
    "gn:admin2_code":"682.0",
    "gn:asciiname":"Stora Malen",
    "gn:country_code":"SE",
    "gn:dem":322,
    "gn:feature_class":"P",
    "gn:feature_code":"PPL",
    "gn:name":"Stora M\u00e5len",
    "gn:population":0,
    "gn:timezone":"Europe/Stockholm",
    "iso:country":"SE",
    "wof:name":"Stora Malen",
    "wof:placetype":"locality"
},
  "geometry": {"coordinates":[14.73333,57.61666999999999],"type":"Point"}
}