{
  "type": "Feature",
  "properties": {
    "gn:admin1_code":"3.0",
    "gn:admin2_code":"2161.0",
    "gn:asciiname":"Holanna",
    "gn:country_code":"SE",
    "gn:dem":166,
    "gn:feature_class":"P",
    "gn:feature_code":"PPL",
    "gn:name":"Hol\u00e4nna",
    "gn:population":0,
    "gn:timezone":"Europe/Stockholm",
    "iso:country":"SE",
    "wof:name":"Holanna",
    "wof:placetype":"locality"
},
  "geometry": {"coordinates":[16.25,61.86666999999999],"type":"Point"}
}