{
  "type": "Feature",
  "properties": {
    "gn:admin1_code":"28.0",
    "gn:admin2_code":"1466.0",
    "gn:asciiname":"Sibbarp",
    "gn:country_code":"SE",
    "gn:dem":160,
    "gn:feature_class":"P",
    "gn:feature_code":"PPL",
    "gn:name":"Sibbarp",
    "gn:population":0,
    "gn:timezone":"Europe/Stockholm",
    "iso:country":"SE",
    "wof:name":"Sibbarp",
    "wof:placetype":"locality"
},
  "geometry": {"coordinates":[13.18333,58.05],"type":"Point"}
}