{
  "type": "Feature",
  "properties": {
    "gn:admin1_code":"6.0",
    "gn:admin2_code":"1383.0",
    "gn:asciiname":"Pribetsgarden",
    "gn:country_code":"SE",
    "gn:dem":13,
    "gn:feature_class":"P",
    "gn:feature_code":"PPL",
    "gn:name":"Pribetsg\u00e5rden",
    "gn:population":0,
    "gn:timezone":"Europe/Stockholm",
    "iso:country":"SE",
    "wof:name":"Pribetsgarden",
    "wof:placetype":"locality"
},
  "geometry": {"coordinates":[12.15,57.225],"type":"Point"}
}