{
  "type": "Feature",
  "properties": {
    "gn:admin1_code":"12.0",
    "gn:admin2_code":"763.0",
    "gn:asciiname":"Alshult",
    "gn:country_code":"SE",
    "gn:dem":154,
    "gn:feature_class":"P",
    "gn:feature_code":"PPL",
    "gn:name":"\u00c5lshult",
    "gn:population":0,
    "gn:timezone":"Europe/Stockholm",
    "iso:country":"SE",
    "wof:name":"Alshult",
    "wof:placetype":"locality"
},
  "geometry": {"coordinates":[14.66667,56.51667],"type":"Point"}
}