{
  "type": "Feature",
  "properties": {
    "gn:admin1_code":"28.0",
    "gn:admin2_code":"1421.0",
    "gn:asciiname":"Bot",
    "gn:country_code":"SE",
    "gn:dem":-9999,
    "gn:feature_class":"P",
    "gn:feature_code":"PPL",
    "gn:name":"Bot",
    "gn:population":0,
    "gn:timezone":"Europe/Stockholm",
    "iso:country":"SE",
    "name:aze_x_preferred":[
        "Bot"
    ],
    "name:bel_x_preferred":[
        "\u0411\u043e\u0442"
    ],
    "name:ben_x_preferred":[
        "\u09ac\u099f"
    ],
    "name:cat_x_preferred":[
        "Bot"
    ],
    "name:ceb_x_preferred":[
        "Bot"
    ],
    "name:ces_x_preferred":[
        "Bot"
    ],
    "name:eus_x_preferred":[
        "Bot"
    ],
    "name:fin_x_preferred":[
        "Bot"
    ],
    "name:fra_x_preferred":[
        "Bot"
    ],
    "name:fry_x_preferred":[
        "Bot"
    ],
    "name:glg_x_preferred":[
        "Bot"
    ],
    "name:heb_x_preferred":[
        "\u05d1\u05d5\u05d8"
    ],
    "name:hun_x_preferred":[
        "Bot"
    ],
    "name:jpn_x_preferred":[
        "Bot"
    ],
    "name:msa_x_preferred":[
        "Bot"
    ],
    "name:nld_x_preferred":[
        "Bot"
    ],
    "name:nor_x_preferred":[
        "Bot"
    ],
    "name:pol_x_preferred":[
        "Bot"
    ],
    "name:por_x_preferred":[
        "Bot"
    ],
    "name:ron_x_preferred":[
        "Bot"
    ],
    "name:rus_x_preferred":[
        "\u0411\u043e\u0442"
    ],
    "name:slk_x_preferred":[
        "Bot"
    ],
    "name:spa_x_preferred":[
        "Bot"
    ],
    "name:swe_x_preferred":[
        "Bot"
    ],
    "name:tur_x_preferred":[
        "Bot"
    ],
    "name:ukr_x_preferred":[
        "\u0411\u043e\u0442"
    ],
    "wof:name":"Bot",
    "wof:placetype":"locality"
},
  "geometry": {"coordinates":[11.55,58.08333],"type":"Point"}
}