{
  "type": "Feature",
  "properties": {
    "gn:admin1_code":"8.0",
    "gn:admin2_code":"683.0",
    "gn:asciiname":"Mossle",
    "gn:country_code":"SE",
    "gn:dem":173,
    "gn:feature_class":"P",
    "gn:feature_code":"PPL",
    "gn:name":"Mossle",
    "gn:population":0,
    "gn:timezone":"Europe/Stockholm",
    "iso:country":"SE",
    "wof:name":"Mossle",
    "wof:placetype":"locality"
},
  "geometry": {"coordinates":[14.03333,57.16667],"type":"Point"}
}