{
  "type": "Feature",
  "properties": {
    "gn:admin1_code":"6.0",
    "gn:admin2_code":"1315.0",
    "gn:asciiname":"Lahult",
    "gn:country_code":"SE",
    "gn:dem":99,
    "gn:feature_class":"P",
    "gn:feature_code":"PPL",
    "gn:name":"Lahult",
    "gn:population":0,
    "gn:timezone":"Europe/Stockholm",
    "iso:country":"SE",
    "wof:name":"Lahult",
    "wof:placetype":"locality"
},
  "geometry": {"coordinates":[13.16667,56.96666999999999],"type":"Point"}
}