{
  "type": "Feature",
  "properties": {
    "gn:admin1_code":"26.0",
    "gn:asciiname":"Farjstaden",
    "gn:cc2":"SE",
    "gn:country_code":"SE",
    "gn:dem":19,
    "gn:feature_class":"P",
    "gn:feature_code":"PPL",
    "gn:name":"F\u00e4rjstaden",
    "gn:population":0,
    "gn:timezone":"Europe/Stockholm",
    "iso:country":"SE",
    "name:und_x_variant":[
        "F\u00e4rjestaden"
    ],
    "wof:name":"Farjstaden",
    "wof:placetype":"locality"
},
  "geometry": {"coordinates":[17.76661,59.37432],"type":"Point"}
}