{
  "type": "Feature",
  "properties": {
    "gn:admin1_code":"23.0",
    "gn:admin2_code":"2463.0",
    "gn:asciiname":"Osternoret",
    "gn:country_code":"SE",
    "gn:dem":308,
    "gn:feature_class":"P",
    "gn:feature_code":"PPL",
    "gn:name":"\u00d6sternoret",
    "gn:population":0,
    "gn:timezone":"Europe/Stockholm",
    "iso:country":"SE",
    "name:nor_x_preferred":[
        "\u00d6sternoret"
    ],
    "name:nor_x_variant":[
        "\u00d8sternoret"
    ],
    "wof:name":"Osternoret",
    "wof:placetype":"locality"
},
  "geometry": {"coordinates":[17.33333,64.09999999999999],"type":"Point"}
}