{
  "type": "Feature",
  "properties": {
    "gn:admin1_code":"25.0",
    "gn:admin2_code":"1984.0",
    "gn:asciiname":"Holmsatter",
    "gn:country_code":"SE",
    "gn:dem":45,
    "gn:feature_class":"P",
    "gn:feature_code":"PPL",
    "gn:name":"Holms\u00e4tter",
    "gn:population":0,
    "gn:timezone":"Europe/Stockholm",
    "iso:country":"SE",
    "wof:name":"Holmsatter",
    "wof:placetype":"locality"
},
  "geometry": {"coordinates":[15.66667,59.35],"type":"Point"}
}