{
  "type": "Feature",
  "properties": {
    "gn:admin1_code":"22.0",
    "gn:admin2_code":"1781.0",
    "gn:asciiname":"Norra Ugglebol",
    "gn:country_code":"SE",
    "gn:dem":88,
    "gn:feature_class":"P",
    "gn:feature_code":"PPL",
    "gn:name":"Norra Ugglebol",
    "gn:population":0,
    "gn:timezone":"Europe/Stockholm",
    "iso:country":"SE",
    "wof:name":"Norra Ugglebol",
    "wof:placetype":"locality"
},
  "geometry": {"coordinates":[14.23333,59.06667],"type":"Point"}
}