{
  "type": "Feature",
  "properties": {
    "gn:admin1_code":"7.0",
    "gn:admin2_code":"2313.0",
    "gn:asciiname":"Sjulsasen",
    "gn:country_code":"SE",
    "gn:dem":295,
    "gn:feature_class":"P",
    "gn:feature_code":"PPL",
    "gn:name":"Sjuls\u00e5sen",
    "gn:population":0,
    "gn:timezone":"Europe/Stockholm",
    "iso:country":"SE",
    "wof:name":"Sjulsasen",
    "wof:placetype":"locality"
},
  "geometry": {"coordinates":[14.78333,64.34999999999999],"type":"Point"}
}