{
  "type": "Feature",
  "properties": {
    "gn:admin1_code":"23.0",
    "gn:admin2_code":"2460.0",
    "gn:asciiname":"Ostra Starkesmark",
    "gn:country_code":"SE",
    "gn:dem":179,
    "gn:feature_class":"P",
    "gn:feature_code":"PPL",
    "gn:name":"\u00d6stra St\u00e4rkesmark",
    "gn:population":0,
    "gn:timezone":"Europe/Stockholm",
    "iso:country":"SE",
    "wof:name":"Ostra Starkesmark",
    "wof:placetype":"locality"
},
  "geometry": {"coordinates":[19.75,64.03333000000001],"type":"Point"}
}