{
  "type": "Feature",
  "properties": {
    "gn:admin1_code":"23.0",
    "gn:admin2_code":"2463.0",
    "gn:asciiname":"Storlogda",
    "gn:country_code":"SE",
    "gn:dem":315,
    "gn:feature_class":"P",
    "gn:feature_code":"PPL",
    "gn:name":"Storl\u00f6gda",
    "gn:population":0,
    "gn:timezone":"Europe/Stockholm",
    "iso:country":"SE",
    "name:nor_x_preferred":[
        "Storl\u00f6gda"
    ],
    "name:nor_x_variant":[
        "Storl\u00f8gda"
    ],
    "name:und_x_variant":[
        "Storl\u00f6gda"
    ],
    "wof:name":"Storlogda",
    "wof:placetype":"locality"
},
  "geometry": {"coordinates":[18.33333,64.13333],"type":"Point"}
}