{
  "type": "Feature",
  "properties": {
    "gn:admin1_code":"7.0",
    "gn:admin2_code":"2313.0",
    "gn:asciiname":"Ankarvattnet",
    "gn:cc2":"SE",
    "gn:country_code":"SE",
    "gn:dem":448,
    "gn:feature_class":"P",
    "gn:feature_code":"PPL",
    "gn:name":"Ankarvattnet",
    "gn:population":0,
    "gn:timezone":"Europe/Stockholm",
    "iso:country":"SE",
    "name:ceb_x_preferred":[
        "Ankarvattnet"
    ],
    "name:epo_x_preferred":[
        "Ankarvattnet"
    ],
    "name:nno_x_preferred":[
        "Ankarvattnet"
    ],
    "name:nor_x_preferred":[
        "Ankarvattnet"
    ],
    "name:swe_x_preferred":[
        "Ankarvattnet"
    ],
    "name:und_x_variant":[
        "Ankarsvattnet"
    ],
    "wof:name":"Ankarvattnet",
    "wof:placetype":"locality"
},
  "geometry": {"coordinates":[14.21667,64.86667],"type":"Point"}
}