{
  "type": "Feature",
  "properties": {
    "gn:admin1_code":"22.0",
    "gn:admin2_code":"1766.0",
    "gn:asciiname":"Kolsgard",
    "gn:cc2":"SE",
    "gn:country_code":"SE",
    "gn:dem":118,
    "gn:feature_class":"P",
    "gn:feature_code":"PPL",
    "gn:name":"Kolsg\u00e5rd",
    "gn:population":0,
    "gn:timezone":"Europe/Stockholm",
    "iso:country":"SE",
    "name:und_x_variant":[
        "K\u00e5lsg\u00e5rden",
        "K\u00e5lsg\u00e5rd",
        "Kolsg\u00e5rd"
    ],
    "wof:name":"Kolsgard",
    "wof:placetype":"locality"
},
  "geometry": {"coordinates":[13.13333,59.73333],"type":"Point"}
}