{
  "type": "Feature",
  "properties": {
    "gn:admin1_code":"8.0",
    "gn:admin2_code":"684.0",
    "gn:asciiname":"Hyltan",
    "gn:country_code":"SE",
    "gn:dem":231,
    "gn:feature_class":"P",
    "gn:feature_code":"PPL",
    "gn:name":"Hyltan",
    "gn:population":0,
    "gn:timezone":"Europe/Stockholm",
    "iso:country":"SE",
    "wof:name":"Hyltan",
    "wof:placetype":"locality"
},
  "geometry": {"coordinates":[14.71667,57.33333],"type":"Point"}
}