{
  "type": "Feature",
  "properties": {
    "gn:admin1_code":"24.0",
    "gn:admin2_code":"2281.0",
    "gn:asciiname":"Sodalen",
    "gn:country_code":"SE",
    "gn:dem":230,
    "gn:feature_class":"P",
    "gn:feature_code":"PPL",
    "gn:name":"Sodalen",
    "gn:population":0,
    "gn:timezone":"Europe/Stockholm",
    "iso:country":"SE",
    "wof:name":"Sodalen",
    "wof:placetype":"locality"
},
  "geometry": {"coordinates":[16.85,62.58333],"type":"Point"}
}