{
  "type": "Feature",
  "properties": {
    "gn:admin1_code":"23.0",
    "gn:admin2_code":"2425.0",
    "gn:asciiname":"Mardsjo",
    "gn:country_code":"SE",
    "gn:dem":325,
    "gn:feature_class":"P",
    "gn:feature_code":"PPL",
    "gn:name":"M\u00e5rdsj\u00f6",
    "gn:population":0,
    "gn:timezone":"Europe/Stockholm",
    "iso:country":"SE",
    "name:nor_x_preferred":[
        "M\u00e5rdsj\u00f6"
    ],
    "name:nor_x_variant":[
        "M\u00e5rdsj\u00f8"
    ],
    "name:und_x_variant":[
        "M\u00e5rdsj\u00f6"
    ],
    "wof:name":"Mardsjo",
    "wof:placetype":"locality"
},
  "geometry": {"coordinates":[16.53333,64.28333000000001],"type":"Point"}
}