{
  "type": "Feature",
  "properties": {
    "gn:admin1_code":"28.0",
    "gn:admin2_code":"1447.0",
    "gn:asciiname":"Tattertorp",
    "gn:country_code":"SE",
    "gn:dem":111,
    "gn:feature_class":"P",
    "gn:feature_code":"PPL",
    "gn:name":"Tattertorp",
    "gn:population":0,
    "gn:timezone":"Europe/Stockholm",
    "iso:country":"SE",
    "wof:name":"Tattertorp",
    "wof:placetype":"locality"
},
  "geometry": {"coordinates":[14.11667,58.89972],"type":"Point"}
}