{
  "type": "Feature",
  "properties": {
    "gn:admin1_code":"6.0",
    "gn:admin2_code":"1381.0",
    "gn:asciiname":"Lagaholm",
    "gn:country_code":"SE",
    "gn:dem":8,
    "gn:feature_class":"P",
    "gn:feature_code":"PPL",
    "gn:name":"Lagaholm",
    "gn:population":0,
    "gn:timezone":"Europe/Stockholm",
    "iso:country":"SE",
    "wof:name":"Lagaholm",
    "wof:placetype":"locality"
},
  "geometry": {"coordinates":[13.05,56.51667],"type":"Point"}
}