{
  "type": "Feature",
  "properties": {
    "gn:admin1_code":"23.0",
    "gn:admin2_code":"2421.0",
    "gn:asciiname":"Bygget",
    "gn:country_code":"SE",
    "gn:dem":468,
    "gn:feature_class":"P",
    "gn:feature_code":"PPL",
    "gn:name":"Bygget",
    "gn:population":0,
    "gn:timezone":"Europe/Stockholm",
    "iso:country":"SE",
    "wof:name":"Bygget",
    "wof:placetype":"locality"
},
  "geometry": {"coordinates":[15.0662,65.73421999999999],"type":"Point"}
}