{
  "type": "Feature",
  "properties": {
    "gn:admin1_code":"8.0",
    "gn:asciiname":"Mjohult",
    "gn:country_code":"SE",
    "gn:dem":174,
    "gn:feature_class":"P",
    "gn:feature_code":"PPL",
    "gn:name":"Mj\u00f6hult",
    "gn:population":0,
    "gn:timezone":"Europe/Stockholm",
    "iso:country":"SE",
    "name:nor_x_preferred":[
        "Mj\u00f6hult"
    ],
    "name:nor_x_variant":[
        "Mj\u00f8hult"
    ],
    "wof:name":"Mjohult",
    "wof:placetype":"locality"
},
  "geometry": {"coordinates":[14.33098,56.82005],"type":"Point"}
}