{
  "type": "Feature",
  "properties": {
    "gn:admin1_code":"23.0",
    "gn:admin2_code":"2481.0",
    "gn:asciiname":"Overbo",
    "gn:country_code":"SE",
    "gn:dem":277,
    "gn:feature_class":"P",
    "gn:feature_code":"PPL",
    "gn:name":"\u00d6verbo",
    "gn:population":0,
    "gn:timezone":"Europe/Stockholm",
    "iso:country":"SE",
    "name:nor_x_preferred":[
        "\u00d6verbo"
    ],
    "name:nor_x_variant":[
        "\u00d8verbo"
    ],
    "wof:name":"Overbo",
    "wof:placetype":"locality"
},
  "geometry": {"coordinates":[18.86667000000001,64.51666999999999],"type":"Point"}
}