{
  "type": "Feature",
  "properties": {
    "gn:admin1_code":"3.0",
    "gn:admin2_code":"2184.0",
    "gn:asciiname":"Aspe",
    "gn:country_code":"SE",
    "gn:dem":25,
    "gn:feature_class":"P",
    "gn:feature_code":"PPL",
    "gn:name":"Aspe",
    "gn:population":0,
    "gn:timezone":"Europe/Stockholm",
    "iso:country":"SE",
    "name:ara_x_preferred":[
        "\u0623\u0633\u0628\u064a"
    ],
    "name:arg_x_preferred":[
        "Asp"
    ],
    "name:ast_x_preferred":[
        "Aspe"
    ],
    "name:azb_x_preferred":[
        "\u0622\u0633\u067e\u0647"
    ],
    "name:aze_x_preferred":[
        "Aspe"
    ],
    "name:cat_x_preferred":[
        "Asp"
    ],
    "name:ceb_x_preferred":[
        "Aspe"
    ],
    "name:eus_x_preferred":[
        "Aspe"
    ],
    "name:fas_x_preferred":[
        "\u0622\u0633\u067e\u0647"
    ],
    "name:fra_x_preferred":[
        "Aspe"
    ],
    "name:hun_x_preferred":[
        "Aspe"
    ],
    "name:ita_x_preferred":[
        "Aspe"
    ],
    "name:kaz_x_preferred":[
        "\u0410\u0441\u043f\u0435"
    ],
    "name:msa_x_preferred":[
        "Aspe"
    ],
    "name:nld_x_preferred":[
        "Aspe"
    ],
    "name:oci_x_preferred":[
        "Aspe"
    ],
    "name:pol_x_preferred":[
        "Aspe"
    ],
    "name:por_x_preferred":[
        "Aspe"
    ],
    "name:rus_x_preferred":[
        "\u0410\u0441\u043f\u0435"
    ],
    "name:spa_x_preferred":[
        "Aspe"
    ],
    "name:srp_x_preferred":[
        "\u0410\u0441\u043f\u0435"
    ],
    "name:swe_x_preferred":[
        "Aspe"
    ],
    "name:ukr_x_preferred":[
        "\u0410\u0441\u043f\u0435"
    ],
    "name:uzb_x_preferred":[
        "Aspe"
    ],
    "name:war_x_preferred":[
        "Aspe"
    ],
    "name:zho_x_preferred":[
        "\u963f\u65af\u4f69"
    ],
    "wof:name":"Aspe",
    "wof:placetype":"locality"
},
  "geometry": {"coordinates":[17.24278,61.84056],"type":"Point"}
}