{
  "type": "Feature",
  "properties": {
    "gn:admin1_code":"8.0",
    "gn:admin2_code":"680.0",
    "gn:asciiname":"Tovrida",
    "gn:cc2":"SE",
    "gn:country_code":"SE",
    "gn:dem":214,
    "gn:feature_class":"P",
    "gn:feature_code":"PPL",
    "gn:name":"Tovrida",
    "gn:population":0,
    "gn:timezone":"Europe/Stockholm",
    "iso:country":"SE",
    "name:und_x_variant":[
        "Tofrida",
        "Tovrida"
    ],
    "wof:name":"Tovrida",
    "wof:placetype":"locality"
},
  "geometry": {"coordinates":[14.38333,57.76667],"type":"Point"}
}