{
  "type": "Feature",
  "properties": {
    "gn:admin1_code":"15.0",
    "gn:admin2_code":"1880.0",
    "gn:asciiname":"Sodra Navesta",
    "gn:country_code":"SE",
    "gn:dem":69,
    "gn:feature_class":"P",
    "gn:feature_code":"PPL",
    "gn:name":"S\u00f6dra N\u00e4vesta",
    "gn:population":0,
    "gn:timezone":"Europe/Stockholm",
    "iso:country":"SE",
    "wof:name":"Sodra Navesta",
    "wof:placetype":"locality"
},
  "geometry": {"coordinates":[15.16667,59.36666999999999],"type":"Point"}
}