{
  "type": "Feature",
  "properties": {
    "gn:admin1_code":"23.0",
    "gn:admin2_code":"2422.0",
    "gn:asciiname":"Duvvieksuvvane",
    "gn:country_code":"SE",
    "gn:dem":338,
    "gn:feature_class":"P",
    "gn:feature_code":"PPL",
    "gn:name":"Duvvieksuvvane",
    "gn:population":0,
    "gn:timezone":"Europe/Stockholm",
    "iso:country":"SE",
    "name:sju_x_preferred":[
        "Duvvieksuvvane"
    ],
    "name:swe_x_preferred":[
        "Lomselen\u00e4s"
    ],
    "name:und_x_variant":[
        "Lomsele",
        "Lamsele"
    ],
    "wof:name":"Duvvieksuvvane",
    "wof:placetype":"locality"
},
  "geometry": {"coordinates":[17.64172,65.21236],"type":"Point"}
}