{
  "type": "Feature",
  "properties": {
    "gn:admin1_code":"12.0",
    "gn:asciiname":"Kophult",
    "gn:country_code":"SE",
    "gn:dem":116,
    "gn:feature_class":"P",
    "gn:feature_code":"PPL",
    "gn:name":"K\u00f6phult",
    "gn:population":0,
    "gn:timezone":"Europe/Stockholm",
    "iso:country":"SE",
    "name:nor_x_preferred":[
        "K\u00f6phult"
    ],
    "name:nor_x_variant":[
        "K\u00f8phult"
    ],
    "wof:name":"Kophult",
    "wof:placetype":"locality"
},
  "geometry": {"coordinates":[13.53333,56.41667],"type":"Point"}
}