{
  "type": "Feature",
  "properties": {
    "gn:admin1_code":"2.0",
    "gn:admin2_code":"1060.0",
    "gn:asciiname":"Morkamala",
    "gn:country_code":"SE",
    "gn:dem":146,
    "gn:feature_class":"P",
    "gn:feature_code":"PPL",
    "gn:name":"M\u00f6rkam\u00e5la",
    "gn:population":0,
    "gn:timezone":"Europe/Stockholm",
    "iso:country":"SE",
    "name:nor_x_preferred":[
        "M\u00f6rkam\u00e5la"
    ],
    "name:nor_x_variant":[
        "M\u00f8rkam\u00e5la"
    ],
    "name:und_x_variant":[
        "M\u00f6rkam\u00e5la"
    ],
    "wof:name":"Morkamala",
    "wof:placetype":"locality"
},
  "geometry": {"coordinates":[14.63333,56.33333],"type":"Point"}
}