{
  "type": "Feature",
  "properties": {
    "gn:gn_country":"SE",
    "gn:gn_fcode":"PPL",
    "gn:gn_pop":371,
    "gn:population":326,
    "iso:country":"SE",
    "name:dut_x_preferred":[
        "\u00c4sk\u00f6ping"
    ],
    "name:eng_x_preferred":[
        "\u00c4sk\u00f6ping"
    ],
    "name:ita_x_preferred":[
        "\u00c4sk\u00f6ping"
    ],
    "name:mac_x_preferred":[
        "\u0415\u0441\u0448\u0435\u043f\u0438\u043d\u0433"
    ],
    "name:nan_x_preferred":[
        "\u00c4sk\u00f6ping"
    ],
    "name:nno_x_preferred":[
        "\u00c4sk\u00f6ping"
    ],
    "name:nob_x_preferred":[
        "\u00c4sk\u00f6ping"
    ],
    "name:pol_x_preferred":[
        "\u00c4sk\u00f6ping"
    ],
    "name:swe_x_preferred":[
        "\u00c4sk\u00f6ping"
    ],
    "qs_pg:aaroncc":"SE",
    "qs_pg:gn_country":"SE",
    "qs_pg:gn_fcode":"PPL",
    "qs_pg:gn_pop":371,
    "qs_pg:name":"\u00c4sk\u00f6ping",
    "qs_pg:photos_9r":0,
    "qs_pg:photos_sr":0,
    "qs_pg:pop_sr":2,
    "qs_pg:qs_pg_placetype":"locality",
    "wof:name":"\u00c4sk\u00f6ping",
    "wof:placetype":"locality",
    "wof:population":326
},
  "geometry": {"coordinates":[16.06667,59.15],"type":"Point"}
}