{
  "type": "Feature",
  "properties": {
    "gn:admin1_code":"9.0",
    "gn:admin2_code":"882.0",
    "gn:asciiname":"Veningehult",
    "gn:country_code":"SE",
    "gn:dem":63,
    "gn:feature_class":"P",
    "gn:feature_code":"PPL",
    "gn:name":"Veningehult",
    "gn:population":0,
    "gn:timezone":"Europe/Stockholm",
    "iso:country":"SE",
    "wof:name":"Veningehult",
    "wof:placetype":"locality"
},
  "geometry": {"coordinates":[16.25,57.28333000000001],"type":"Point"}
}