{
  "type": "Feature",
  "properties": {
    "iso:country":"SE",
    "name:swe_x_preferred":[
        "Lindalen"
    ],
    "name:unk_x_variant":[
        "Lindal",
        "Lindalen"
    ],
    "qs:gn_adm0_cc":"SE",
    "qs:gn_fcode":"PPL",
    "qs:gn_local":2666779,
    "qs:gn_nam_loc":"Tyres\u00f6, Tyres\u00f6, Stockholms L\u00e4n, SE",
    "qs:gn_namadm1":"26",
    "qs:gn_name":"Lindalen",
    "qs:local_max":305,
    "qs:local_sum":994,
    "qs:localhoods":4,
    "qs:name":"Lindalen",
    "qs:name_adm0":"Sverige",
    "qs:name_adm1":"Stockholms L\u00e4n",
    "qs:name_adm2":"Tyres\u00f6",
    "qs:name_local":"Tyres\u00f6",
    "qs:photo_max":175,
    "qs:photo_sum":262,
    "qs:placetype":"Suburb",
    "qs:quad_count":17,
    "qs:woe_adm0":23424954,
    "qs:woe_adm1":2347067,
    "qs:woe_adm2":12587481,
    "qs:woe_lau":0,
    "qs:woe_local":908326,
    "qs:woe_ver":"7.10.0",
    "wof:lang":[
        "swe"
    ],
    "wof:name":"Lindalen",
    "wof:placetype":"neighbourhood"
},
  "geometry": {"coordinates":[18.208252,59.245682],"type":"Point"}
}