{
  "type": "Feature",
  "properties": {
    "gn:admin1_code":"12.0",
    "gn:admin2_code":"763.0",
    "gn:asciiname":"Sodra Veramala",
    "gn:country_code":"SE",
    "gn:dem":164,
    "gn:feature_class":"P",
    "gn:feature_code":"PPL",
    "gn:name":"S\u00f6dra Veram\u00e5la",
    "gn:population":0,
    "gn:timezone":"Europe/Stockholm",
    "iso:country":"SE",
    "name:nor_x_preferred":[
        "S\u00f6dra Veram\u00e5la"
    ],
    "name:nor_x_variant":[
        "S\u00f8dra Veram\u00e5la"
    ],
    "name:und_x_variant":[
        "S\u00f6dra Veram\u00e5la"
    ],
    "wof:name":"Sodra Veramala",
    "wof:placetype":"locality"
},
  "geometry": {"coordinates":[15.03333,56.51667],"type":"Point"}
}