{
  "type": "Feature",
  "properties": {
    "gn:admin1_code":"24",
    "gn:admin2_code":"2281.0",
    "gn:admin3_code":"228108.0",
    "gn:admin4_code":"2505.0",
    "gn:asciiname":"Svanaeng",
    "gn:country_code":"SE",
    "gn:dem":48,
    "gn:feature_class":"P",
    "gn:feature_code":"PPL",
    "gn:name":"Svan\u00e4ng",
    "gn:population":0,
    "gn:timezone":"Europe/Stockholm",
    "iso:country":"SE",
    "wof:name":"Svanaeng",
    "wof:placetype":"locality"
},
  "geometry": {"coordinates":[17.18116,62.32273000000001],"type":"Point"}
}