{
  "type": "Feature",
  "properties": {
    "gn:admin1_code":"7.0",
    "gn:admin2_code":"2309.0",
    "gn:asciiname":"Sorbyn",
    "gn:country_code":"SE",
    "gn:dem":364,
    "gn:feature_class":"P",
    "gn:feature_code":"PPL",
    "gn:name":"S\u00f6rbyn",
    "gn:population":0,
    "gn:timezone":"Europe/Stockholm",
    "iso:country":"SE",
    "name:nor_x_preferred":[
        "S\u00f6rbyn"
    ],
    "name:nor_x_variant":[
        "S\u00f8rbyn"
    ],
    "wof:name":"Sorbyn",
    "wof:placetype":"locality"
},
  "geometry": {"coordinates":[14.58333,63.25],"type":"Point"}
}