{
  "type": "Feature",
  "properties": {
    "gn:admin1_code":"23.0",
    "gn:admin2_code":"2482.0",
    "gn:asciiname":"Lidbacken",
    "gn:country_code":"SE",
    "gn:dem":264,
    "gn:feature_class":"P",
    "gn:feature_code":"PPL",
    "gn:name":"Lidbacken",
    "gn:population":0,
    "gn:timezone":"Europe/Stockholm",
    "iso:country":"SE",
    "wof:name":"Lidbacken",
    "wof:placetype":"locality"
},
  "geometry": {"coordinates":[20.61667000000001,65.01666999999999],"type":"Point"}
}