{
  "type": "Feature",
  "properties": {
    "gn:admin1_code":"14.0",
    "gn:admin2_code":"2506.0",
    "gn:asciiname":"Nurrholm",
    "gn:country_code":"SE",
    "gn:dem":412,
    "gn:feature_class":"P",
    "gn:feature_code":"PPL",
    "gn:name":"Nurrholm",
    "gn:population":0,
    "gn:timezone":"Europe/Stockholm",
    "iso:country":"SE",
    "name:swe_x_preferred":[
        "Nurrholm"
    ],
    "wof:name":"Nurrholm",
    "wof:placetype":"locality"
},
  "geometry": {"coordinates":[17.76584,65.93786],"type":"Point"}
}