{
  "type": "Feature",
  "properties": {
    "gn:admin1_code":"3.0",
    "gn:admin2_code":"2180.0",
    "gn:asciiname":"Nordansjo",
    "gn:country_code":"SE",
    "gn:dem":39,
    "gn:feature_class":"P",
    "gn:feature_code":"PPL",
    "gn:name":"Nordansj\u00f6",
    "gn:population":0,
    "gn:timezone":"Europe/Stockholm",
    "iso:country":"SE",
    "name:nor_x_preferred":[
        "Nordansj\u00f6"
    ],
    "name:nor_x_variant":[
        "Nordansj\u00f8"
    ],
    "wof:name":"Nordansjo",
    "wof:placetype":"locality"
},
  "geometry": {"coordinates":[17.25,60.46666999999999],"type":"Point"}
}