{
  "type": "Feature",
  "properties": {
    "gn:admin1_code":"28.0",
    "gn:admin2_code":"1494.0",
    "gn:asciiname":"Ostby",
    "gn:country_code":"SE",
    "gn:dem":59,
    "gn:feature_class":"P",
    "gn:feature_code":"PPL",
    "gn:name":"\u00d6stby",
    "gn:population":0,
    "gn:timezone":"Europe/Stockholm",
    "iso:country":"SE",
    "name:nor_x_preferred":[
        "\u00d6stby"
    ],
    "name:nor_x_variant":[
        "\u00d8stby"
    ],
    "name:und_x_variant":[
        "\u00d6stby"
    ],
    "wof:name":"Ostby",
    "wof:placetype":"locality"
},
  "geometry": {"coordinates":[13.15,58.46666999999999],"type":"Point"}
}