{
  "type": "Feature",
  "properties": {
    "gn:admin1_code":"25.0",
    "gn:admin2_code":"1960.0",
    "gn:asciiname":"Holma",
    "gn:country_code":"SE",
    "gn:dem":9,
    "gn:feature_class":"P",
    "gn:feature_code":"PPL",
    "gn:name":"Holma",
    "gn:population":0,
    "gn:timezone":"Europe/Stockholm",
    "iso:country":"SE",
    "name:ita_x_preferred":[
        "Holma"
    ],
    "name:nld_x_preferred":[
        "Holma"
    ],
    "name:vie_x_preferred":[
        "Holma"
    ],
    "wof:name":"Holma",
    "wof:placetype":"locality"
},
  "geometry": {"coordinates":[15.93333,59.41667],"type":"Point"}
}