{
  "type": "Feature",
  "properties": {
    "gn:admin1_code":"10.0",
    "gn:admin2_code":"2081.0",
    "gn:asciiname":"Angarna",
    "gn:country_code":"SE",
    "gn:dem":135,
    "gn:feature_class":"P",
    "gn:feature_code":"PPL",
    "gn:name":"\u00c4ngarna",
    "gn:population":0,
    "gn:timezone":"Europe/Stockholm",
    "iso:country":"SE",
    "wof:name":"Angarna",
    "wof:placetype":"locality"
},
  "geometry": {"coordinates":[15.41667,60.41667],"type":"Point"}
}