{
  "type": "Feature",
  "properties": {
    "gn:gn_country":"SE",
    "gn:gn_fcode":"PPL",
    "gn:gn_pop":509,
    "gn:population":689,
    "iso:country":"SE",
    "name:ceb_x_preferred":[
        "Barseb\u00e4ck"
    ],
    "name:dan_x_preferred":[
        "Barseb\u00e4ck"
    ],
    "name:deu_x_preferred":[
        "Barseb\u00e4ck"
    ],
    "name:eng_x_preferred":[
        "Barseb\u00e4ck"
    ],
    "name:est_x_preferred":[
        "Barseb\u00e4ck"
    ],
    "name:fin_x_preferred":[
        "Barseb\u00e4ck"
    ],
    "name:fra_x_preferred":[
        "Barseb\u00e4ck"
    ],
    "name:ita_x_preferred":[
        "Barseb\u00e4ck"
    ],
    "name:nan_x_preferred":[
        "Barseb\u00e4ck"
    ],
    "name:nld_x_preferred":[
        "Barseb\u00e4ck"
    ],
    "name:nno_x_preferred":[
        "Barseb\u00e4ck"
    ],
    "name:nob_x_preferred":[
        "Barseb\u00e4ck"
    ],
    "name:por_x_preferred":[
        "Barseb\u00e4ck"
    ],
    "name:swe_x_preferred":[
        "Barseb\u00e4ck"
    ],
    "name:unk_x_variant":[
        "Barseb\u00e4ck"
    ],
    "qs_pg:aaroncc":"SE",
    "qs_pg:gn_country":"SE",
    "qs_pg:gn_fcode":"PPL",
    "qs_pg:gn_pop":509,
    "qs_pg:name":"Barseback",
    "qs_pg:name_adm0":"Sverige",
    "qs_pg:name_adm1":"Sk\u00e5ne L\u00e4n",
    "qs_pg:photos":223,
    "qs_pg:photos_1k":45,
    "qs_pg:photos_9k":1,
    "qs_pg:photos_9r":4,
    "qs_pg:photos_all":223,
    "qs_pg:photos_sr":4,
    "qs_pg:pop_sr":2,
    "qs_pg:qs_pg_placetype":"locality",
    "qs_pg:qs_pg_placetype_gp":"Town",
    "qs_pg:woe_adm0":23424954,
    "woe:adm0_id":23424954,
    "woe:name_adm0":"Sverige",
    "woe:name_adm1":"Sk\u00e5ne L\u00e4n",
    "woe:placetype":"Town",
    "wof:name":"Barseback",
    "wof:placetype":"locality",
    "wof:population":689
},
  "geometry": {"coordinates":[12.95,55.76667],"type":"Point"}
}