{
  "type": "Feature",
  "properties": {
    "gn:admin1_code":"22.0",
    "gn:admin2_code":"1764.0",
    "gn:asciiname":"Vegerbol",
    "gn:country_code":"SE",
    "gn:dem":105,
    "gn:feature_class":"P",
    "gn:feature_code":"PPL",
    "gn:name":"Vegerbol",
    "gn:population":0,
    "gn:timezone":"Europe/Stockholm",
    "iso:country":"SE",
    "wof:name":"Vegerbol",
    "wof:placetype":"locality"
},
  "geometry": {"coordinates":[12.88333,59.46666999999999],"type":"Point"}
}