{
  "type": "Feature",
  "properties": {
    "gn:admin1_code":"28.0",
    "gn:admin2_code":"1473.0",
    "gn:admin3_code":"147313.0",
    "gn:admin4_code":"2105.0",
    "gn:asciiname":"AElgaras",
    "gn:country_code":"SE",
    "gn:dem":124,
    "gn:feature_class":"P",
    "gn:feature_code":"PPL",
    "gn:name":"\u00c4lgar\u00e5s",
    "gn:population":373,
    "gn:timezone":"Europe/Stockholm",
    "iso:country":"SE",
    "wof:name":"AElgaras",
    "wof:placetype":"locality",
    "wof:population":373
},
  "geometry": {"coordinates":[14.25552,58.81036999999999],"type":"Point"}
}