{
  "type": "Feature",
  "properties": {
    "gn:admin1_code":"27.0",
    "gn:admin2_code":"1230.0",
    "gn:asciiname":"Mossheddinge",
    "gn:country_code":"SE",
    "gn:dem":5,
    "gn:feature_class":"P",
    "gn:feature_code":"PPL",
    "gn:name":"Mossheddinge",
    "gn:population":0,
    "gn:timezone":"Europe/Stockholm",
    "iso:country":"SE",
    "wof:name":"Mossheddinge",
    "wof:placetype":"locality"
},
  "geometry": {"coordinates":[13.26667,55.61666999999999],"type":"Point"}
}