{
  "type": "Feature",
  "properties": {
    "gn:admin1_code":"9.0",
    "gn:admin2_code":"860.0",
    "gn:asciiname":"Venskogle",
    "gn:cc2":"SE",
    "gn:country_code":"SE",
    "gn:dem":99,
    "gn:feature_class":"P",
    "gn:feature_code":"PPL",
    "gn:name":"Vensk\u00f6gle",
    "gn:population":0,
    "gn:timezone":"Europe/Stockholm",
    "iso:country":"SE",
    "name:nor_x_preferred":[
        "Vensk\u00f6gle"
    ],
    "name:nor_x_variant":[
        "Vensk\u00f8gle"
    ],
    "name:und_x_variant":[
        "Vensj\u00f6gle"
    ],
    "wof:name":"Venskogle",
    "wof:placetype":"locality"
},
  "geometry": {"coordinates":[15.61667,57.35],"type":"Point"}
}