{
  "type": "Feature",
  "properties": {
    "gn:admin1_code":"10.0",
    "gn:admin2_code":"2080.0",
    "gn:asciiname":"Attjarnbo",
    "gn:country_code":"SE",
    "gn:dem":284,
    "gn:feature_class":"P",
    "gn:feature_code":"PPL",
    "gn:name":"Attj\u00e4rnbo",
    "gn:population":0,
    "gn:timezone":"Europe/Stockholm",
    "iso:country":"SE",
    "wof:name":"Attjarnbo",
    "wof:placetype":"locality"
},
  "geometry": {"coordinates":[15.48333,60.78333000000001],"type":"Point"}
}