{
  "type": "Feature",
  "properties": {
    "gn:admin1_code":"12.0",
    "gn:admin2_code":"761.0",
    "gn:asciiname":"Gummekulla",
    "gn:cc2":"SE",
    "gn:country_code":"SE",
    "gn:dem":177,
    "gn:feature_class":"P",
    "gn:feature_code":"PPL",
    "gn:name":"Gummekulla",
    "gn:population":0,
    "gn:timezone":"Europe/Stockholm",
    "iso:country":"SE",
    "name:und_x_variant":[
        "Gummikulla",
        "Gummekulla"
    ],
    "wof:name":"Gummekulla",
    "wof:placetype":"locality"
},
  "geometry": {"coordinates":[15.36667,56.61666999999999],"type":"Point"}
}