{
  "type": "Feature",
  "properties": {
    "gn:admin1_code":"28.0",
    "gn:admin2_code":"1497.0",
    "gn:asciiname":"Gate",
    "gn:country_code":"SE",
    "gn:dem":169,
    "gn:feature_class":"P",
    "gn:feature_code":"PPL",
    "gn:name":"Gate",
    "gn:population":0,
    "gn:timezone":"Europe/Stockholm",
    "iso:country":"SE",
    "name:als_x_preferred":[
        "Tor"
    ],
    "name:ara_x_preferred":[
        "\u0628\u0648\u0627\u0628\u0629"
    ],
    "name:arc_x_preferred":[
        "\u0712\u0712\u0710"
    ],
    "name:azb_x_preferred":[
        "\u0642\u0627\u067e\u0627\u0686\u06cc\u0642"
    ],
    "name:aze_x_preferred":[
        "Darvaza"
    ],
    "name:bel_x_preferred":[
        "\u0411\u0440\u0430\u043c\u0430"
    ],
    "name:bul_x_preferred":[
        "\u041f\u043e\u0440\u0442\u0430"
    ],
    "name:ces_x_preferred":[
        "Br\u00e1na"
    ],
    "name:che_x_preferred":[
        "\u041a\u043e\u0432"
    ],
    "name:chv_x_preferred":[
        "\u0425\u0430\u043f\u0445\u0430"
    ],
    "name:deu_x_preferred":[
        "Tor"
    ],
    "name:epo_x_preferred":[
        "Pordego"
    ],
    "name:est_x_preferred":[
        "V\u00e4rav"
    ],
    "name:eus_x_preferred":[
        "Langa"
    ],
    "name:fas_x_preferred":[
        "\u062f\u0631\u0648\u0627\u0632\u0647"
    ],
    "name:fin_x_preferred":[
        "Portti"
    ],
    "name:gle_x_preferred":[
        "Geata"
    ],
    "name:heb_x_preferred":[
        "\u05e9\u05e2\u05e8"
    ],
    "name:hun_x_preferred":[
        "Kapu"
    ],
    "name:ind_x_preferred":[
        "Gerbang"
    ],
    "name:ita_x_preferred":[
        "Cancello"
    ],
    "name:kat_x_preferred":[
        "\u10d9\u10d0\u10e0\u10d8\u10d1\u10ed\u10d4"
    ],
    "name:kaz_x_preferred":[
        "\u049a\u0430\u049b\u043f\u0430"
    ],
    "name:kor_x_preferred":[
        "\ubb38"
    ],
    "name:lit_x_preferred":[
        "Vartai"
    ],
    "name:mal_x_preferred":[
        "\u0d2a\u0d1f\u0d3f\u0d35\u0d3e\u0d24\u0d3f\u0d7d"
    ],
    "name:new_x_preferred":[
        "\u0927\u094d\u0935\u0916\u093e"
    ],
    "name:nld_x_preferred":[
        "Poort"
    ],
    "name:nor_x_preferred":[
        "Port"
    ],
    "name:nrm_x_preferred":[
        "Barryire"
    ],
    "name:pnb_x_preferred":[
        "\u067e\u06be\u0627\u0679\u06a9"
    ],
    "name:pol_x_preferred":[
        "Brama"
    ],
    "name:por_x_preferred":[
        "Port\u00e3o"
    ],
    "name:ron_x_preferred":[
        "Poart\u0103"
    ],
    "name:rus_x_preferred":[
        "\u0412\u043e\u0440\u043e\u0442\u0430"
    ],
    "name:sco_x_preferred":[
        "Yett"
    ],
    "name:slk_x_preferred":[
        "Br\u00e1na"
    ],
    "name:spa_x_preferred":[
        "Verja"
    ],
    "name:srp_x_preferred":[
        "\u041a\u0430\u043f\u0438\u0458\u0430"
    ],
    "name:swe_x_preferred":[
        "Grind"
    ],
    "name:tgk_x_preferred":[
        "\u0414\u0430\u0440\u0432\u043e\u0437\u0430"
    ],
    "name:ukr_x_preferred":[
        "\u0412\u043e\u0440\u043e\u0442\u0430"
    ],
    "name:uzb_x_preferred":[
        "Darvoza"
    ],
    "name:vie_x_preferred":[
        "C\u1ed5ng"
    ],
    "name:zho_x_preferred":[
        "\u9580"
    ],
    "wof:name":"Gate",
    "wof:placetype":"locality"
},
  "geometry": {"coordinates":[14.18333,58.16667],"type":"Point"}
}