{
  "type": "Feature",
  "properties": {
    "gn:admin1_code":"22.0",
    "gn:admin2_code":"1784.0",
    "gn:asciiname":"Lilla Tenhojden",
    "gn:country_code":"SE",
    "gn:dem":281,
    "gn:feature_class":"P",
    "gn:feature_code":"PPL",
    "gn:name":"Lilla Tenh\u00f6jden",
    "gn:population":0,
    "gn:timezone":"Europe/Stockholm",
    "iso:country":"SE",
    "name:nor_x_preferred":[
        "Lilla Tenh\u00f6jden"
    ],
    "name:nor_x_variant":[
        "Lilla Tenh\u00f8jden"
    ],
    "name:und_x_variant":[
        "Lilla Tenh\u00f6jden"
    ],
    "wof:name":"Lilla Tenhojden",
    "wof:placetype":"locality"
},
  "geometry": {"coordinates":[12.68333,59.96666999999999],"type":"Point"}
}