{
  "type": "Feature",
  "properties": {
    "iso:country":"SE",
    "name:ceb_x_preferred":[
        "Nolvik"
    ],
    "name:fra_x_preferred":[
        "Nolvik"
    ],
    "name:ita_x_preferred":[
        "Nolvik"
    ],
    "name:nld_x_preferred":[
        "Nolvik"
    ],
    "name:nno_x_preferred":[
        "Nolvik"
    ],
    "name:nor_x_preferred":[
        "Nolvik"
    ],
    "name:sco_x_preferred":[
        "Nolvik"
    ],
    "name:swe_x_preferred":[
        "Nolvik"
    ],
    "wof:name":"Nolvik",
    "wof:placetype":"neighbourhood"
},
  "geometry": {"coordinates":[11.83334191478778,57.77611063835262],"type":"Point"}
}