{
  "type": "Feature",
  "properties": {
    "gn:admin1_code":"26.0",
    "gn:admin2_code":"125.0",
    "gn:asciiname":"Bergalund",
    "gn:country_code":"SE",
    "gn:dem":29,
    "gn:feature_class":"P",
    "gn:feature_code":"PPL",
    "gn:name":"Bergalund",
    "gn:population":0,
    "gn:timezone":"Europe/Stockholm",
    "iso:country":"SE",
    "wof:name":"Bergalund",
    "wof:placetype":"locality"
},
  "geometry": {"coordinates":[17.76667,59.31667],"type":"Point"}
}