{
  "type": "Feature",
  "properties": {
    "gn:admin1_code":"24.0",
    "gn:admin2_code":"2260.0",
    "gn:admin3_code":"226002.0",
    "gn:admin4_code":"2455.0",
    "gn:asciiname":"Nedergardarna",
    "gn:country_code":"SE",
    "gn:dem":411,
    "gn:feature_class":"P",
    "gn:feature_code":"PPL",
    "gn:name":"Nederg\u00e5rdarna",
    "gn:population":0,
    "gn:timezone":"Europe/Stockholm",
    "iso:country":"SE",
    "wof:name":"Nedergardarna",
    "wof:placetype":"locality"
},
  "geometry": {"coordinates":[15.83333,62.43333000000001],"type":"Point"}
}