{
  "type": "Feature",
  "properties": {
    "gn:admin1_code":"23.0",
    "gn:admin2_code":"2463.0",
    "gn:asciiname":"Sodra Insjo",
    "gn:country_code":"SE",
    "gn:dem":367,
    "gn:feature_class":"P",
    "gn:feature_code":"PPL",
    "gn:name":"S\u00f6dra Insj\u00f6",
    "gn:population":0,
    "gn:timezone":"Europe/Stockholm",
    "iso:country":"SE",
    "name:nor_x_preferred":[
        "S\u00f6dra Insj\u00f6"
    ],
    "name:nor_x_variant":[
        "S\u00f8dra Insj\u00f8"
    ],
    "name:und_x_variant":[
        "S\u00f6dra Insj\u00f6"
    ],
    "wof:name":"Sodra Insjo",
    "wof:placetype":"locality"
},
  "geometry": {"coordinates":[17.48333,64.38333],"type":"Point"}
}