{
  "type": "Feature",
  "properties": {
    "gn:admin1_code":"18.0",
    "gn:admin2_code":"488.0",
    "gn:asciiname":"Litselby",
    "gn:cc2":"SE",
    "gn:country_code":"SE",
    "gn:dem":7,
    "gn:feature_class":"P",
    "gn:feature_code":"PPL",
    "gn:name":"Litselby",
    "gn:population":0,
    "gn:timezone":"Europe/Stockholm",
    "iso:country":"SE",
    "name:und_x_variant":[
        "Litsleby",
        "Litselby"
    ],
    "wof:name":"Litselby",
    "wof:placetype":"locality"
},
  "geometry": {"coordinates":[17.38306,58.83306],"type":"Point"}
}