{
  "type": "Feature",
  "properties": {
    "gn:admin1_code":"10.0",
    "gn:admin2_code":"2021.0",
    "gn:asciiname":"Gruvan",
    "gn:cc2":"SE",
    "gn:country_code":"SE",
    "gn:dem":242,
    "gn:feature_class":"P",
    "gn:feature_code":"PPL",
    "gn:name":"Gruvan",
    "gn:population":0,
    "gn:timezone":"Europe/Stockholm",
    "iso:country":"SE",
    "name:und_x_variant":[
        "Grufvan",
        "Gruvan"
    ],
    "wof:name":"Gruvan",
    "wof:placetype":"locality"
},
  "geometry": {"coordinates":[14.31667,60.53333000000001],"type":"Point"}
}