{
  "type": "Feature",
  "properties": {
    "gn:admin1_code":"24.0",
    "gn:admin2_code":"2281.0",
    "gn:admin3_code":"228112.0",
    "gn:admin4_code":"2468.0",
    "gn:asciiname":"Vastbyn",
    "gn:country_code":"SE",
    "gn:dem":259,
    "gn:feature_class":"P",
    "gn:feature_code":"PPL",
    "gn:name":"V\u00e4stbyn",
    "gn:population":0,
    "gn:timezone":"Europe/Stockholm",
    "iso:country":"SE",
    "wof:name":"Vastbyn",
    "wof:placetype":"locality"
},
  "geometry": {"coordinates":[16.61667000000001,62.66667],"type":"Point"}
}