{
  "type": "Feature",
  "properties": {
    "gn:admin1_code":"10.0",
    "gn:admin2_code":"2083.0",
    "gn:asciiname":"Backnilsbo",
    "gn:country_code":"SE",
    "gn:dem":91,
    "gn:feature_class":"P",
    "gn:feature_code":"PPL",
    "gn:name":"Backnilsbo",
    "gn:population":0,
    "gn:timezone":"Europe/Stockholm",
    "iso:country":"SE",
    "wof:name":"Backnilsbo",
    "wof:placetype":"locality"
},
  "geometry": {"coordinates":[15.95,60.25],"type":"Point"}
}