{
  "type": "Feature",
  "properties": {
    "gn:admin1_code":"28.0",
    "gn:admin2_code":"1491.0",
    "gn:asciiname":"Bone",
    "gn:country_code":"SE",
    "gn:dem":248,
    "gn:feature_class":"P",
    "gn:feature_code":"PPL",
    "gn:name":"B\u00f6ne",
    "gn:population":0,
    "gn:timezone":"Europe/Stockholm",
    "iso:country":"SE",
    "name:nor_x_preferred":[
        "B\u00f6ne"
    ],
    "name:nor_x_variant":[
        "B\u00f8ne"
    ],
    "name:und_x_variant":[
        "B\u00f6ne"
    ],
    "wof:name":"Bone",
    "wof:placetype":"locality"
},
  "geometry": {"coordinates":[13.51667,57.88333000000001],"type":"Point"}
}