{
  "type": "Feature",
  "properties": {
    "gn:admin1_code":"3.0",
    "gn:admin2_code":"2184.0",
    "gn:asciiname":"Gasfjard",
    "gn:country_code":"SE",
    "gn:dem":33,
    "gn:feature_class":"P",
    "gn:feature_code":"PPL",
    "gn:name":"G\u00e5sfj\u00e4rd",
    "gn:population":0,
    "gn:timezone":"Europe/Stockholm",
    "iso:country":"SE",
    "wof:name":"Gasfjard",
    "wof:placetype":"locality"
},
  "geometry": {"coordinates":[17.08333,61.61666999999999],"type":"Point"}
}