{
  "type": "Feature",
  "properties": {
    "gn:admin1_code":"27.0",
    "gn:admin2_code":"1270.0",
    "gn:asciiname":"Myrestad",
    "gn:country_code":"SE",
    "gn:dem":105,
    "gn:feature_class":"P",
    "gn:feature_code":"PPL",
    "gn:name":"Myrestad",
    "gn:population":0,
    "gn:timezone":"Europe/Stockholm",
    "iso:country":"SE",
    "wof:name":"Myrestad",
    "wof:placetype":"locality"
},
  "geometry": {"coordinates":[14.08333,55.76667],"type":"Point"}
}