{
  "type": "Feature",
  "properties": {
    "gn:country":"SE",
    "gn:fcode":"PPL",
    "gn:population":802,
    "iso:country":"SE",
    "name:bul_x_preferred":[
        "\u0424\u0438\u0433\u0435\u0445\u043e\u043b\u043c"
    ],
    "name:ceb_x_preferred":[
        "Figeholm"
    ],
    "name:deu_x_preferred":[
        "Figeholm"
    ],
    "name:eng_x_preferred":[
        "Figeholm"
    ],
    "name:fin_x_preferred":[
        "Figeholm"
    ],
    "name:fra_x_preferred":[
        "Figeholm"
    ],
    "name:ita_x_preferred":[
        "Figeholm"
    ],
    "name:nan_x_preferred":[
        "Figeholm"
    ],
    "name:nld_x_preferred":[
        "Figeholm"
    ],
    "name:nno_x_preferred":[
        "Figeholm"
    ],
    "name:nob_x_preferred":[
        "Figeholm"
    ],
    "name:swe_x_preferred":[
        "Figeholm"
    ],
    "qs_pg:aaroncc":"SE",
    "qs_pg:gn_country":"SE",
    "qs_pg:gn_fcode":"PPL",
    "qs_pg:gn_pop":802,
    "qs_pg:name":"Figeholm",
    "qs_pg:name_adm0":"Sverige",
    "qs_pg:name_adm1":"Kalmar L\u00e4n",
    "qs_pg:photos":86,
    "qs_pg:photos_1k":17,
    "qs_pg:photos_9k":1,
    "qs_pg:photos_9r":3,
    "qs_pg:photos_all":86,
    "qs_pg:photos_sr":3,
    "qs_pg:pop_sr":2,
    "qs_pg:qs_pg_placetype":"locality",
    "qs_pg:qs_pg_placetype_gp":"Town",
    "qs_pg:woe_adm0":23424954,
    "woe:adm0_id":23424954,
    "woe:name_adm0":"Sverige",
    "woe:name_adm1":"Kalmar L\u00e4n",
    "woe:placetype":"Town",
    "wof:name":"Figeholm",
    "wof:placetype":"locality",
    "wof:population":730
},
  "geometry": {"coordinates":[16.55,57.36667],"type":"Point"}
}