{
  "type": "Feature",
  "properties": {
    "gn:admin1_code":"18.0",
    "gn:admin2_code":"483.0",
    "gn:asciiname":"Hagby",
    "gn:country_code":"SE",
    "gn:dem":42,
    "gn:feature_class":"P",
    "gn:feature_code":"PPL",
    "gn:name":"Hagby",
    "gn:population":0,
    "gn:timezone":"Europe/Stockholm",
    "iso:country":"SE",
    "wof:name":"Hagby",
    "wof:placetype":"locality"
},
  "geometry": {"coordinates":[16.15,59.16667],"type":"Point"}
}