{
  "type": "Feature",
  "properties": {
    "gn:admin1_code":"28.0",
    "gn:admin2_code":"1430.0",
    "gn:asciiname":"Valbo-Ryr",
    "gn:country_code":"SE",
    "gn:dem":68,
    "gn:feature_class":"P",
    "gn:feature_code":"PPL",
    "gn:name":"Valbo-Ryr",
    "gn:population":0,
    "gn:timezone":"Europe/Stockholm",
    "iso:country":"SE",
    "wof:name":"Valbo-Ryr",
    "wof:placetype":"locality"
},
  "geometry": {"coordinates":[11.81667,58.48306],"type":"Point"}
}