{
  "type": "Feature",
  "properties": {
    "gn:admin1_code":"16.0",
    "gn:admin2_code":"580.0",
    "gn:asciiname":"Kogenas",
    "gn:country_code":"SE",
    "gn:dem":105,
    "gn:feature_class":"P",
    "gn:feature_code":"PPL",
    "gn:name":"K\u00f6gen\u00e4s",
    "gn:population":0,
    "gn:timezone":"Europe/Stockholm",
    "iso:country":"SE",
    "wof:name":"Kogenas",
    "wof:placetype":"locality"
},
  "geometry": {"coordinates":[15.68333,58.26667],"type":"Point"}
}