{
  "type": "Feature",
  "properties": {
    "gn:admin1_code":"21.0",
    "gn:admin2_code":"382.0",
    "gn:asciiname":"Losholmen",
    "gn:country_code":"SE",
    "gn:dem":12,
    "gn:feature_class":"P",
    "gn:feature_code":"PPL",
    "gn:name":"L\u00f6sholmen",
    "gn:population":0,
    "gn:timezone":"Europe/Stockholm",
    "iso:country":"SE",
    "name:nor_x_preferred":[
        "L\u00f6sholmen"
    ],
    "name:nor_x_variant":[
        "L\u00f8sholmen"
    ],
    "name:und_x_variant":[
        "L\u00f6sholmen"
    ],
    "wof:name":"Losholmen",
    "wof:placetype":"locality"
},
  "geometry": {"coordinates":[18.48333,60.275],"type":"Point"}
}