{
  "type": "Feature",
  "properties": {
    "gn:admin1_code":"10.0",
    "gn:admin2_code":"2083.0",
    "gn:asciiname":"Grado Nybyn",
    "gn:country_code":"SE",
    "gn:dem":129,
    "gn:feature_class":"P",
    "gn:feature_code":"PPL",
    "gn:name":"Gr\u00e5d\u00f6 Nybyn",
    "gn:population":0,
    "gn:timezone":"Europe/Stockholm",
    "iso:country":"SE",
    "name:nor_x_preferred":[
        "Gr\u00e5d\u00f6 Nybyn"
    ],
    "name:nor_x_variant":[
        "Gr\u00e5d\u00f8 Nybyn"
    ],
    "wof:name":"Grado Nybyn",
    "wof:placetype":"locality"
},
  "geometry": {"coordinates":[16.05,60.23333],"type":"Point"}
}