{
  "type": "Feature",
  "properties": {
    "gn:admin1_code":"10.0",
    "gn:admin2_code":"2039.0",
    "gn:asciiname":"Lissavallen",
    "gn:country_code":"SE",
    "gn:dem":507,
    "gn:feature_class":"P",
    "gn:feature_code":"PPL",
    "gn:name":"Liss\u00e5vallen",
    "gn:population":0,
    "gn:timezone":"Europe/Stockholm",
    "iso:country":"SE",
    "wof:name":"Lissavallen",
    "wof:placetype":"locality"
},
  "geometry": {"coordinates":[12.96667,61.56667],"type":"Point"}
}