{
  "type": "Feature",
  "properties": {
    "gn:admin1_code":"16.0",
    "gn:admin2_code":"581.0",
    "gn:asciiname":"Rada",
    "gn:country_code":"SE",
    "gn:dem":13,
    "gn:feature_class":"P",
    "gn:feature_code":"PPL",
    "gn:name":"R\u00e5da",
    "gn:population":0,
    "gn:timezone":"Europe/Stockholm",
    "iso:country":"SE",
    "name:fin_x_preferred":[
        "Rada"
    ],
    "name:ita_x_preferred":[
        "Rada"
    ],
    "name:jpn_x_preferred":[
        "\u30e9\u30fc\u30c0"
    ],
    "name:pol_x_preferred":[
        "Rada"
    ],
    "name:rus_x_preferred":[
        "\u0420\u0430\u0434\u0430"
    ],
    "name:ukr_x_preferred":[
        "\u0420\u0430\u0434\u0430"
    ],
    "wof:name":"Rada",
    "wof:placetype":"locality"
},
  "geometry": {"coordinates":[16.43306,58.56667],"type":"Point"}
}