{
  "type": "Feature",
  "properties": {
    "gn:admin1_code":"14.0",
    "gn:admin2_code":"2521.0",
    "gn:asciiname":"Virkamaa",
    "gn:country_code":"SE",
    "gn:dem":258,
    "gn:feature_class":"P",
    "gn:feature_code":"PPL",
    "gn:name":"Virkamaa",
    "gn:population":0,
    "gn:timezone":"Europe/Stockholm",
    "iso:country":"SE",
    "wof:name":"Virkamaa",
    "wof:placetype":"locality"
},
  "geometry": {"coordinates":[23.23333,66.86667],"type":"Point"}
}