{
  "type": "Feature",
  "properties": {
    "gn:admin1_code":"9.0",
    "gn:admin2_code":"840.0",
    "gn:admin3_code":"84008.0",
    "gn:admin4_code":"869.0",
    "gn:asciiname":"Perstorp",
    "gn:country_code":"SE",
    "gn:dem":35,
    "gn:feature_class":"P",
    "gn:feature_code":"PPL",
    "gn:name":"Perstorp",
    "gn:population":0,
    "gn:timezone":"Europe/Stockholm",
    "iso:country":"SE",
    "name:bul_x_preferred":[
        "\u041f\u0435\u0440\u0449\u043e\u0440\u043f"
    ],
    "name:ceb_x_preferred":[
        "Perstorp"
    ],
    "name:dan_x_preferred":[
        "Perstorp"
    ],
    "name:deu_x_preferred":[
        "Perstorp"
    ],
    "name:fao_x_preferred":[
        "Perstorp"
    ],
    "name:fas_x_preferred":[
        "\u067e\u0631\u0633\u062a\u0648\u0631\u067e"
    ],
    "name:fin_x_preferred":[
        "Perstorp"
    ],
    "name:isl_x_preferred":[
        "Perstorp"
    ],
    "name:ita_x_preferred":[
        "Perstorp"
    ],
    "name:nld_x_preferred":[
        "Perstorp"
    ],
    "name:nno_x_preferred":[
        "Perstorp"
    ],
    "name:nor_x_preferred":[
        "Perstorp"
    ],
    "name:pol_x_preferred":[
        "Perstorp"
    ],
    "name:ron_x_preferred":[
        "Perstorp"
    ],
    "name:swe_x_preferred":[
        "Perstorp"
    ],
    "wof:name":"Perstorp",
    "wof:placetype":"locality"
},
  "geometry": {"coordinates":[16.42691,56.37081],"type":"Point"}
}