{
  "type": "Feature",
  "properties": {
    "gn:admin1_code":"27.0",
    "gn:admin2_code":"1284.0",
    "gn:asciiname":"Stensnas",
    "gn:country_code":"SE",
    "gn:dem":43,
    "gn:feature_class":"P",
    "gn:feature_code":"PPL",
    "gn:name":"Stensn\u00e4s",
    "gn:population":0,
    "gn:timezone":"Europe/Stockholm",
    "iso:country":"SE",
    "wof:name":"Stensnas",
    "wof:placetype":"locality"
},
  "geometry": {"coordinates":[12.58333,56.26667],"type":"Point"}
}