{
  "type": "Feature",
  "properties": {
    "gn:admin1_code":"27.0",
    "gn:admin2_code":"1276.0",
    "gn:admin3_code":"127601.0",
    "gn:admin4_code":"1138.0",
    "gn:asciiname":"Hyllstofta",
    "gn:country_code":"SE",
    "gn:dem":56,
    "gn:feature_class":"P",
    "gn:feature_code":"PPL",
    "gn:name":"Hyllstofta",
    "gn:population":0,
    "gn:timezone":"Europe/Stockholm",
    "iso:country":"SE",
    "wof:name":"Hyllstofta",
    "wof:placetype":"locality"
},
  "geometry": {"coordinates":[13.28907,56.13376],"type":"Point"}
}