{
  "type": "Feature",
  "properties": {
    "gn:gn_country":"SE",
    "gn:gn_fcode":"PPL",
    "gn:gn_pop":0,
    "gn:population":1094,
    "iso:country":"SE",
    "name:deu_x_preferred":[
        "G\u00e4rsn\u00e4s"
    ],
    "name:eng_x_preferred":[
        "G\u00e4rsn\u00e4s"
    ],
    "name:fao_x_preferred":[
        "G\u00e4rsn\u00e4s"
    ],
    "name:fra_x_preferred":[
        "G\u00e4rsn\u00e4s"
    ],
    "name:ita_x_preferred":[
        "G\u00e4rsn\u00e4s"
    ],
    "name:nan_x_preferred":[
        "G\u00e4rsn\u00e4s"
    ],
    "name:nld_x_preferred":[
        "G\u00e4rsn\u00e4s"
    ],
    "name:nno_x_preferred":[
        "G\u00e4rsn\u00e4s"
    ],
    "name:nob_x_preferred":[
        "G\u00e4rsn\u00e4s"
    ],
    "name:por_x_preferred":[
        "G\u00e4rsn\u00e4s"
    ],
    "name:swe_x_preferred":[
        "G\u00e4rsn\u00e4s"
    ],
    "qs_pg:aaroncc":"SE",
    "qs_pg:gn_country":"SE",
    "qs_pg:gn_fcode":"PPL",
    "qs_pg:gn_pop":0,
    "qs_pg:name":"G\u00e4rsn\u00e4s",
    "qs_pg:name_adm0":"Sverige",
    "qs_pg:name_adm1":"Sk\u00e5ne L\u00e4n",
    "qs_pg:photos":36,
    "qs_pg:photos_1k":7,
    "qs_pg:photos_9k":1,
    "qs_pg:photos_9r":2,
    "qs_pg:photos_all":36,
    "qs_pg:photos_sr":2,
    "qs_pg:pop_sr":0,
    "qs_pg:qs_pg_placetype":"locality",
    "qs_pg:qs_pg_placetype_gp":"Town",
    "qs_pg:woe_adm0":23424954,
    "woe:adm0_id":23424954,
    "woe:name_adm0":"Sverige",
    "woe:name_adm1":"Sk\u00e5ne L\u00e4n",
    "woe:placetype":"Town",
    "wof:name":"G\u00e4rsn\u00e4s",
    "wof:placetype":"locality",
    "wof:population":1094
},
  "geometry": {"coordinates":[14.18333,55.55],"type":"Point"}
}