{
  "type": "Feature",
  "properties": {
    "gn:admin1_code":"14.0",
    "gn:admin2_code":"2584.0",
    "gn:admin3_code":"258401.0",
    "gn:admin4_code":"172.0",
    "gn:asciiname":"Rautas",
    "gn:country_code":"SE",
    "gn:dem":458,
    "gn:feature_class":"P",
    "gn:feature_code":"PPL",
    "gn:name":"Rautas",
    "gn:population":0,
    "gn:timezone":"Europe/Stockholm",
    "iso:country":"SE",
    "name:nld_x_preferred":[
        "Rautas"
    ],
    "name:swe_x_preferred":[
        "Rautas"
    ],
    "wof:name":"Rautas",
    "wof:placetype":"locality"
},
  "geometry": {"coordinates":[19.90448,67.99175],"type":"Point"}
}