{
  "type": "Feature",
  "properties": {
    "gn:admin1_code":"10.0",
    "gn:admin2_code":"2084.0",
    "gn:asciiname":"Bergshyttan",
    "gn:country_code":"SE",
    "gn:dem":78,
    "gn:feature_class":"P",
    "gn:feature_code":"PPL",
    "gn:name":"Bergshyttan",
    "gn:population":0,
    "gn:timezone":"Europe/Stockholm",
    "iso:country":"SE",
    "wof:name":"Bergshyttan",
    "wof:placetype":"locality"
},
  "geometry": {"coordinates":[16.36667000000001,60.11666999999999],"type":"Point"}
}