{
  "type": "Feature",
  "properties": {
    "gn:admin1_code":"5.0",
    "gn:admin2_code":"980.0",
    "gn:asciiname":"Nygards",
    "gn:country_code":"SE",
    "gn:dem":42,
    "gn:feature_class":"P",
    "gn:feature_code":"PPL",
    "gn:name":"Nyg\u00e5rds",
    "gn:population":0,
    "gn:timezone":"Europe/Stockholm",
    "iso:country":"SE",
    "wof:name":"Nygards",
    "wof:placetype":"locality"
},
  "geometry": {"coordinates":[18.51667,57.35],"type":"Point"}
}