{
  "type": "Feature",
  "properties": {
    "gn:admin1_code":"16.0",
    "gn:admin2_code":"513.0",
    "gn:asciiname":"Killingevid",
    "gn:country_code":"SE",
    "gn:dem":148,
    "gn:feature_class":"P",
    "gn:feature_code":"PPL",
    "gn:name":"Killingevid",
    "gn:population":0,
    "gn:timezone":"Europe/Stockholm",
    "iso:country":"SE",
    "wof:name":"Killingevid",
    "wof:placetype":"locality"
},
  "geometry": {"coordinates":[15.76667,57.98333],"type":"Point"}
}