{
  "type": "Feature",
  "properties": {
    "gn:admin1_code":"23.0",
    "gn:admin2_code":"2403.0",
    "gn:asciiname":"Nordas",
    "gn:country_code":"SE",
    "gn:dem":186,
    "gn:feature_class":"P",
    "gn:feature_code":"PPL",
    "gn:name":"Nord\u00e5s",
    "gn:population":0,
    "gn:timezone":"Europe/Stockholm",
    "iso:country":"SE",
    "wof:name":"Nordas",
    "wof:placetype":"locality"
},
  "geometry": {"coordinates":[18.81667,63.85],"type":"Point"}
}