{
  "type": "Feature",
  "properties": {
    "gn:admin1_code":"9.0",
    "gn:admin2_code":"834.0",
    "gn:asciiname":"Slatafly",
    "gn:country_code":"SE",
    "gn:dem":71,
    "gn:feature_class":"P",
    "gn:feature_code":"PPL",
    "gn:name":"Sl\u00e4tafly",
    "gn:population":0,
    "gn:timezone":"Europe/Stockholm",
    "iso:country":"SE",
    "wof:name":"Slatafly",
    "wof:placetype":"locality"
},
  "geometry": {"coordinates":[15.86667,56.35],"type":"Point"}
}