{
  "type": "Feature",
  "properties": {
    "gn:admin1_code":"21.0",
    "gn:admin2_code":"381.0",
    "gn:asciiname":"Bjornome",
    "gn:country_code":"SE",
    "gn:dem":44,
    "gn:feature_class":"P",
    "gn:feature_code":"PPL",
    "gn:name":"Bj\u00f6rnome",
    "gn:population":0,
    "gn:timezone":"Europe/Stockholm",
    "iso:country":"SE",
    "name:nor_x_preferred":[
        "Bj\u00f6rnome"
    ],
    "name:nor_x_variant":[
        "Bj\u00f8rnome"
    ],
    "name:und_x_variant":[
        "Bj\u00f6rnome"
    ],
    "wof:name":"Bjornome",
    "wof:placetype":"locality"
},
  "geometry": {"coordinates":[17.33333,59.78333000000001],"type":"Point"}
}