{
  "type": "Feature",
  "properties": {
    "gn:gn_country":"SE",
    "gn:gn_fcode":"PPL",
    "gn:gn_pop":0,
    "iso:country":"SE",
    "name:dan_x_preferred":[
        "Bonnarp"
    ],
    "name:dut_x_preferred":[
        "Bonnarp"
    ],
    "name:eng_x_preferred":[
        "Bonnarp"
    ],
    "name:fre_x_preferred":[
        "Bonnarp"
    ],
    "name:ger_x_preferred":[
        "Bonnarp"
    ],
    "name:nds_x_preferred":[
        "Bonnarp"
    ],
    "name:nno_x_preferred":[
        "Bonnarp"
    ],
    "name:nob_x_preferred":[
        "Bonnarp"
    ],
    "name:swe_x_preferred":[
        "Bonnarp"
    ],
    "name:unk_x_variant":[
        "Bonarp"
    ],
    "qs_pg:aaroncc":"SE",
    "qs_pg:gn_country":"SE",
    "qs_pg:gn_fcode":"PPL",
    "qs_pg:gn_pop":0,
    "qs_pg:name":"Bonnarp",
    "qs_pg:name_adm0":"Sverige",
    "qs_pg:name_adm1":"Sk\u00e5ne L\u00e4n",
    "qs_pg:photos":79,
    "qs_pg:photos_1k":16,
    "qs_pg:photos_9k":1,
    "qs_pg:photos_9r":3,
    "qs_pg:photos_all":79,
    "qs_pg:photos_sr":3,
    "qs_pg:pop_sr":0,
    "qs_pg:qs_pg_placetype":"locality",
    "qs_pg:qs_pg_placetype_gp":"Town",
    "qs_pg:woe_adm0":23424954,
    "woe:adm0_id":23424954,
    "woe:name_adm0":"Sverige",
    "woe:name_adm1":"Sk\u00e5ne L\u00e4n",
    "woe:placetype":"Town",
    "wof:name":"Bonnarp",
    "wof:placetype":"locality"
},
  "geometry": {"coordinates":[13.18333,56.06667],"type":"Point"}
}