{
  "type": "Feature",
  "properties": {
    "iso:country":"SE",
    "name:swe_x_preferred":[
        "H\u00e4llsvik"
    ],
    "wof:name":"Hallsvik",
    "wof:placetype":"neighbourhood"
},
  "geometry": {"coordinates":[11.74053028361678,57.70721078535296],"type":"Point"}
}