{
  "type": "Feature",
  "properties": {
    "gn:gn_country":"SE",
    "gn:gn_fcode":"PPL",
    "gn:gn_pop":578,
    "gn:population":552,
    "iso:country":"SE",
    "name:dut_x_preferred":[
        "S\u00e5gmyra"
    ],
    "name:eng_x_preferred":[
        "S\u00e5gmyra"
    ],
    "name:fre_x_preferred":[
        "S\u00e5gmyra"
    ],
    "name:ger_x_preferred":[
        "S\u00e5gmyra"
    ],
    "name:nan_x_preferred":[
        "S\u00e5gmyra"
    ],
    "name:nno_x_preferred":[
        "S\u00e5gmyra"
    ],
    "name:nob_x_preferred":[
        "S\u00e5gmyra"
    ],
    "name:swe_x_preferred":[
        "S\u00e5gmyra"
    ],
    "name:urd_x_preferred":[
        "\u0633\u06af\u0645\u06cc\u0631\u0627"
    ],
    "qs_pg:aaroncc":"SE",
    "qs_pg:gn_country":"SE",
    "qs_pg:gn_fcode":"PPL",
    "qs_pg:gn_pop":578,
    "qs_pg:name":"S\u00e5gmyra",
    "qs_pg:name_adm0":"Sverige",
    "qs_pg:name_adm1":"Dalarnas L\u00e4n",
    "qs_pg:photos":50,
    "qs_pg:photos_1k":10,
    "qs_pg:photos_9k":1,
    "qs_pg:photos_9r":2,
    "qs_pg:photos_all":50,
    "qs_pg:photos_sr":2,
    "qs_pg:pop_sr":2,
    "qs_pg:qs_pg_placetype":"locality",
    "qs_pg:qs_pg_placetype_gp":"Town",
    "qs_pg:woe_adm0":23424954,
    "woe:adm0_id":23424954,
    "woe:name_adm0":"Sverige",
    "woe:name_adm1":"Dalarnas L\u00e4n",
    "woe:placetype":"Town",
    "wof:name":"S\u00e5gmyra",
    "wof:placetype":"locality",
    "wof:population":552
},
  "geometry": {"coordinates":[15.28333,60.71667],"type":"Point"}
}