{
  "type": "Feature",
  "properties": {
    "iso:country":"SE",
    "name:swe_x_preferred":[
        "Norra Bergsj\u00f6n"
    ],
    "wof:name":"Norra Bergsjon",
    "wof:placetype":"neighbourhood"
},
  "geometry": {"coordinates":[12.06452821784622,57.76106364088525],"type":"Point"}
}