{
  "type": "Feature",
  "properties": {
    "gn:admin1_code":"28.0",
    "gn:admin2_code":"1442.0",
    "gn:asciiname":"Arred",
    "gn:country_code":"SE",
    "gn:dem":218,
    "gn:feature_class":"P",
    "gn:feature_code":"PPL",
    "gn:name":"\u00c5rred",
    "gn:population":0,
    "gn:timezone":"Europe/Stockholm",
    "iso:country":"SE",
    "wof:name":"Arred",
    "wof:placetype":"locality"
},
  "geometry": {"coordinates":[12.83333,57.91667],"type":"Point"}
}