{
  "type": "Feature",
  "properties": {
    "gn:admin1_code":"7.0",
    "gn:admin2_code":"2309.0",
    "gn:asciiname":"Landon",
    "gn:country_code":"SE",
    "gn:dem":346,
    "gn:feature_class":"P",
    "gn:feature_code":"PPL",
    "gn:name":"Land\u00f6n",
    "gn:population":0,
    "gn:timezone":"Europe/Stockholm",
    "iso:country":"SE",
    "name:nor_x_preferred":[
        "Land\u00f6n"
    ],
    "name:nor_x_variant":[
        "Land\u00f8n"
    ],
    "wof:name":"Landon",
    "wof:placetype":"locality"
},
  "geometry": {"coordinates":[14.26667,63.56667],"type":"Point"}
}