{
  "type": "Feature",
  "properties": {
    "gn:admin1_code":"24.0",
    "gn:asciiname":"Dravle",
    "gn:country_code":"SE",
    "gn:dem":62,
    "gn:feature_class":"P",
    "gn:feature_code":"PPL",
    "gn:name":"Dravle",
    "gn:population":0,
    "gn:timezone":"Europe/Stockholm",
    "iso:country":"SE",
    "wof:name":"Dravle",
    "wof:placetype":"locality"
},
  "geometry": {"coordinates":[18.01667,62.68333000000001],"type":"Point"}
}