{
  "type": "Feature",
  "properties": {
    "gn:admin1_code":"28.0",
    "gn:admin2_code":"1419.0",
    "gn:asciiname":"Almosund",
    "gn:country_code":"SE",
    "gn:dem":23,
    "gn:feature_class":"P",
    "gn:feature_code":"PPL",
    "gn:name":"Alm\u00f6sund",
    "gn:population":0,
    "gn:timezone":"Europe/Stockholm",
    "iso:country":"SE",
    "name:nor_x_preferred":[
        "Alm\u00f6sund"
    ],
    "name:nor_x_variant":[
        "Alm\u00f8sund"
    ],
    "name:und_x_variant":[
        "Alm\u00f6sund"
    ],
    "wof:name":"Almosund",
    "wof:placetype":"locality"
},
  "geometry": {"coordinates":[11.75,58.06667],"type":"Point"}
}