{
  "type": "Feature",
  "properties": {
    "gn:gn_country":"SE",
    "gn:gn_fcode":"PPL",
    "gn:gn_pop":100,
    "gn:population":100,
    "iso:country":"SE",
    "name:dan_x_preferred":[
        "B\u00f6da"
    ],
    "name:dut_x_preferred":[
        "B\u00f6da"
    ],
    "name:eng_x_preferred":[
        "B\u00f6da"
    ],
    "name:fre_x_preferred":[
        "B\u00f6da"
    ],
    "name:ger_x_preferred":[
        "B\u00f6da"
    ],
    "name:ita_x_preferred":[
        "B\u00f6da"
    ],
    "name:nds_x_preferred":[
        "B\u00f6da"
    ],
    "name:nno_x_preferred":[
        "B\u00f6da"
    ],
    "name:nob_x_preferred":[
        "B\u00f6da"
    ],
    "name:nor_x_preferred":[
        "B\u00f8da"
    ],
    "name:nor_x_variant":[
        "B\u00f6da"
    ],
    "name:swe_x_preferred":[
        "B\u00f6da"
    ],
    "qs_pg:aaroncc":"SE",
    "qs_pg:gn_country":"SE",
    "qs_pg:gn_fcode":"PPL",
    "qs_pg:gn_pop":100,
    "qs_pg:name":"Boda",
    "qs_pg:name_adm0":"Sverige",
    "qs_pg:name_adm1":"Kalmar L\u00e4n",
    "qs_pg:photos":73,
    "qs_pg:photos_1k":15,
    "qs_pg:photos_9k":1,
    "qs_pg:photos_9r":2,
    "qs_pg:photos_all":73,
    "qs_pg:photos_sr":2,
    "qs_pg:pop_sr":1,
    "qs_pg:qs_pg_placetype":"locality",
    "qs_pg:qs_pg_placetype_gp":"Town",
    "qs_pg:woe_adm0":23424954,
    "woe:adm0_id":23424954,
    "woe:name_adm0":"Sverige",
    "woe:name_adm1":"Kalmar L\u00e4n",
    "woe:placetype":"Town",
    "wof:name":"Boda",
    "wof:placetype":"locality",
    "wof:population":100
},
  "geometry": {"coordinates":[17.05,57.25],"type":"Point"}
}