{
  "type": "Feature",
  "properties": {
    "gn:admin1_code":"22.0",
    "gn:admin2_code":"1730.0",
    "gn:asciiname":"Myre",
    "gn:country_code":"SE",
    "gn:dem":162,
    "gn:feature_class":"P",
    "gn:feature_code":"PPL",
    "gn:name":"Myre",
    "gn:population":0,
    "gn:timezone":"Europe/Stockholm",
    "iso:country":"SE",
    "name:ceb_x_preferred":[
        "Myre"
    ],
    "name:fra_x_preferred":[
        "Myre"
    ],
    "name:nld_x_preferred":[
        "Myre"
    ],
    "name:spa_x_preferred":[
        "Myre"
    ],
    "wof:name":"Myre",
    "wof:placetype":"locality"
},
  "geometry": {"coordinates":[12.41667,59.78333000000001],"type":"Point"}
}