{
  "type": "Feature",
  "properties": {
    "gn:admin1_code":"24.0",
    "gn:admin2_code":"2262.0",
    "gn:admin3_code":"226204.0",
    "gn:admin4_code":"2506.0",
    "gn:asciiname":"Myckelang",
    "gn:cc2":"SE",
    "gn:country_code":"SE",
    "gn:dem":-9999,
    "gn:feature_class":"P",
    "gn:feature_code":"PPL",
    "gn:name":"Myckel\u00e4ng",
    "gn:population":0,
    "gn:timezone":"Europe/Stockholm",
    "iso:country":"SE",
    "name:und_x_variant":[
        "Myckling",
        "Myckel\u00e4ng"
    ],
    "wof:name":"Myckelang",
    "wof:placetype":"locality"
},
  "geometry": {"coordinates":[17.53298,62.46234000000001],"type":"Point"}
}