{
  "type": "Feature",
  "properties": {
    "gn:admin1_code":"28.0",
    "gn:admin2_code":"1465.0",
    "gn:asciiname":"Martenstorp",
    "gn:country_code":"SE",
    "gn:dem":152,
    "gn:feature_class":"P",
    "gn:feature_code":"PPL",
    "gn:name":"M\u00e5rtenstorp",
    "gn:population":0,
    "gn:timezone":"Europe/Stockholm",
    "iso:country":"SE",
    "wof:name":"Martenstorp",
    "wof:placetype":"locality"
},
  "geometry": {"coordinates":[13.08333,57.53333000000001],"type":"Point"}
}