{
  "type": "Feature",
  "properties": {
    "gn:admin1_code":"16.0",
    "gn:admin2_code":"513.0",
    "gn:asciiname":"Brot",
    "gn:country_code":"SE",
    "gn:dem":112,
    "gn:feature_class":"P",
    "gn:feature_code":"PPL",
    "gn:name":"Br\u00f6t",
    "gn:population":0,
    "gn:timezone":"Europe/Stockholm",
    "iso:country":"SE",
    "name:nor_x_preferred":[
        "Br\u00f6t"
    ],
    "name:nor_x_variant":[
        "Br\u00f8t"
    ],
    "name:und_x_variant":[
        "Br\u00f6t"
    ],
    "wof:name":"Brot",
    "wof:placetype":"locality"
},
  "geometry": {"coordinates":[15.73333,58.05],"type":"Point"}
}