{
  "type": "Feature",
  "properties": {
    "gn:admin1_code":"5.0",
    "gn:admin2_code":"980.0",
    "gn:asciiname":"Gurfiles",
    "gn:country_code":"SE",
    "gn:dem":35,
    "gn:feature_class":"P",
    "gn:feature_code":"PPL",
    "gn:name":"Gurfiles",
    "gn:population":0,
    "gn:timezone":"Europe/Stockholm",
    "iso:country":"SE",
    "wof:name":"Gurfiles",
    "wof:placetype":"locality"
},
  "geometry": {"coordinates":[18.61101,57.43666],"type":"Point"}
}