{
  "type": "Feature",
  "properties": {
    "gn:gn_country":"SE",
    "gn:gn_fcode":"PPL",
    "gn:gn_pop":227,
    "gn:population":227,
    "iso:country":"SE",
    "name:cat_x_preferred":[
        "Ovan\u00e5ker"
    ],
    "name:ceb_x_preferred":[
        "Ovan\u00e5ker"
    ],
    "name:dan_x_preferred":[
        "Ovan\u00e5ker"
    ],
    "name:deu_x_preferred":[
        "Ovan\u00e5ker"
    ],
    "name:eng_x_preferred":[
        "Ovan\u00e5ker"
    ],
    "name:fao_x_preferred":[
        "Ovan\u00e5ker"
    ],
    "name:fas_x_preferred":[
        "\u0627\u0648\u0648\u0627\u0646\u0648\u06a9\u0631"
    ],
    "name:fra_x_preferred":[
        "Ovan\u00e5ker"
    ],
    "name:isl_x_preferred":[
        "Ovan\u00e5ker"
    ],
    "name:jpn_x_preferred":[
        "\u30aa\u30f4\u30a1\u30ce\u30fc\u30b1\u30eb"
    ],
    "name:nan_x_preferred":[
        "Ovan\u00e5ker"
    ],
    "name:nds_x_preferred":[
        "Ovan\u00e5ker"
    ],
    "name:nld_x_preferred":[
        "Ovan\u00e5ker"
    ],
    "name:nno_x_preferred":[
        "Ovan\u00e5ker"
    ],
    "name:nob_x_preferred":[
        "Ovan\u00e5ker"
    ],
    "name:ron_x_preferred":[
        "Ovan\u00e5ker"
    ],
    "name:swe_x_preferred":[
        "Ovan\u00e5ker"
    ],
    "name:swe_x_variant":[
        "Ryd\u00f6bruk"
    ],
    "name:unk_x_variant":[
        "Ofvanakers"
    ],
    "qs_pg:aaroncc":"SE",
    "qs_pg:gn_country":"SE",
    "qs_pg:gn_fcode":"PPL",
    "qs_pg:gn_pop":227,
    "qs_pg:name":"Ovan\u00e5ker",
    "qs_pg:name_adm0":"Sverige",
    "qs_pg:name_adm1":"G\u00e4vleborgs L\u00e4n",
    "qs_pg:photos_9k":1,
    "qs_pg:photos_9r":1,
    "qs_pg:photos_all":4,
    "qs_pg:photos_sr":0,
    "qs_pg:pop_sr":2,
    "qs_pg:qs_pg_placetype":"locality",
    "qs_pg:qs_pg_placetype_gp":"Town",
    "qs_pg:woe_adm0":23424954,
    "woe:adm0_id":23424954,
    "woe:name_adm0":"Sverige",
    "woe:name_adm1":"G\u00e4vleborgs L\u00e4n",
    "woe:placetype":"Town",
    "wof:name":"Ovan\u00e5ker",
    "wof:placetype":"locality",
    "wof:population":227
},
  "geometry": {"coordinates":[15.89271,61.3625],"type":"Point"}
}