{
  "type": "Feature",
  "properties": {
    "gn:gn_country":"SE",
    "gn:gn_fcode":"PPL",
    "gn:gn_pop":0,
    "gn:population":324,
    "iso:country":"SE",
    "name:dut_x_preferred":[
        "Marma"
    ],
    "name:eng_x_preferred":[
        "Marma"
    ],
    "name:ita_x_preferred":[
        "Marma"
    ],
    "name:nan_x_preferred":[
        "Marma"
    ],
    "name:nno_x_preferred":[
        "Marma"
    ],
    "name:nob_x_preferred":[
        "Marma"
    ],
    "name:swe_x_preferred":[
        "Marma"
    ],
    "qs_pg:aaroncc":"SE",
    "qs_pg:gn_country":"SE",
    "qs_pg:gn_fcode":"PPL",
    "qs_pg:gn_pop":0,
    "qs_pg:name":"Marma",
    "qs_pg:name_adm0":"Sverige",
    "qs_pg:name_adm1":"Uppsala L\u00e4n",
    "qs_pg:photos":19,
    "qs_pg:photos_1k":4,
    "qs_pg:photos_9k":1,
    "qs_pg:photos_9r":1,
    "qs_pg:photos_all":19,
    "qs_pg:photos_sr":1,
    "qs_pg:pop_sr":9,
    "qs_pg:qs_pg_placetype":"locality",
    "qs_pg:qs_pg_placetype_gp":"Town",
    "qs_pg:woe_adm0":23424954,
    "woe:adm0_id":23424954,
    "woe:name_adm0":"Sverige",
    "woe:name_adm1":"Uppsala L\u00e4n",
    "woe:placetype":"Town",
    "wof:name":"Marma",
    "wof:placetype":"locality",
    "wof:population":324
},
  "geometry": {"coordinates":[17.41667,60.48333],"type":"Point"}
}