{
  "type": "Feature",
  "properties": {
    "gn:admin1_code":"23.0",
    "gn:admin2_code":"2409.0",
    "gn:asciiname":"Kalaboda",
    "gn:country_code":"SE",
    "gn:dem":68,
    "gn:feature_class":"P",
    "gn:feature_code":"PPL",
    "gn:name":"K\u00e5laboda",
    "gn:population":0,
    "gn:timezone":"Europe/Stockholm",
    "iso:country":"SE",
    "wof:name":"Kalaboda",
    "wof:placetype":"locality"
},
  "geometry": {"coordinates":[20.91667,64.38333],"type":"Point"}
}