{
  "type": "Feature",
  "properties": {
    "gn:admin1_code":"22.0",
    "gn:admin2_code":"1730.0",
    "gn:asciiname":"Mellbyn",
    "gn:cc2":"SE",
    "gn:country_code":"SE",
    "gn:dem":111,
    "gn:feature_class":"P",
    "gn:feature_code":"PPL",
    "gn:name":"Mellbyn",
    "gn:population":0,
    "gn:timezone":"Europe/Stockholm",
    "iso:country":"SE",
    "name:und_x_variant":[
        "Mellby",
        "Mellbyn"
    ],
    "wof:name":"Mellbyn",
    "wof:placetype":"locality"
},
  "geometry": {"coordinates":[12.31667,59.83333],"type":"Point"}
}