{
  "type": "Feature",
  "properties": {
    "gn:admin1_code":"28.0",
    "gn:admin2_code":"1421.0",
    "gn:asciiname":"Bjonne",
    "gn:country_code":"SE",
    "gn:dem":13,
    "gn:feature_class":"P",
    "gn:feature_code":"PPL",
    "gn:name":"Bj\u00f6nne",
    "gn:population":0,
    "gn:timezone":"Europe/Stockholm",
    "iso:country":"SE",
    "name:nor_x_preferred":[
        "Bj\u00f6nne"
    ],
    "name:nor_x_variant":[
        "Bj\u00f8nne"
    ],
    "wof:name":"Bjonne",
    "wof:placetype":"locality"
},
  "geometry": {"coordinates":[11.45,58.17083],"type":"Point"}
}