{
  "type": "Feature",
  "properties": {
    "gn:admin1_code":"10.0",
    "gn:admin2_code":"2031.0",
    "gn:asciiname":"Nittsjo",
    "gn:country_code":"SE",
    "gn:dem":234,
    "gn:feature_class":"P",
    "gn:feature_code":"PPL",
    "gn:name":"Nittsj\u00f6",
    "gn:population":0,
    "gn:timezone":"Europe/Stockholm",
    "iso:country":"SE",
    "name:nor_x_preferred":[
        "Nittsj\u00f6"
    ],
    "name:nor_x_variant":[
        "Nittsj\u00f8"
    ],
    "wof:name":"Nittsjo",
    "wof:placetype":"locality"
},
  "geometry": {"coordinates":[15.06667,60.91667],"type":"Point"}
}