{
  "type": "Feature",
  "properties": {
    "gn:admin1_code":"21.0",
    "gn:admin2_code":"382.0",
    "gn:asciiname":"Koxut",
    "gn:country_code":"SE",
    "gn:dem":-9999,
    "gn:feature_class":"P",
    "gn:feature_code":"PPL",
    "gn:name":"Koxut",
    "gn:population":0,
    "gn:timezone":"Europe/Stockholm",
    "iso:country":"SE",
    "wof:name":"Koxut",
    "wof:placetype":"locality"
},
  "geometry": {"coordinates":[18.41667,60.24166999999999],"type":"Point"}
}