{
  "type": "Feature",
  "properties": {
    "iso:country":"SE",
    "wof:name":"Tomtebacken",
    "wof:placetype":"neighbourhood"
},
  "geometry": {"coordinates":[11.91562497620819,57.84335658577669],"type":"Point"}
}