{
  "type": "Feature",
  "properties": {
    "gn:admin1_code":"28.0",
    "gn:admin2_code":"1480.0",
    "gn:asciiname":"Vastergard",
    "gn:country_code":"SE",
    "gn:dem":8,
    "gn:feature_class":"P",
    "gn:feature_code":"PPL",
    "gn:name":"V\u00e4sterg\u00e5rd",
    "gn:population":0,
    "gn:timezone":"Europe/Stockholm",
    "iso:country":"SE",
    "wof:name":"Vastergard",
    "wof:placetype":"locality"
},
  "geometry": {"coordinates":[11.90028,57.62444],"type":"Point"}
}