{
  "type": "Feature",
  "properties": {
    "gn:admin1_code":"22.0",
    "gn:admin2_code":"1766.0",
    "gn:asciiname":"Orback",
    "gn:cc2":"SE",
    "gn:country_code":"SE",
    "gn:dem":85,
    "gn:feature_class":"P",
    "gn:feature_code":"PPL",
    "gn:name":"\u00d6rb\u00e4ck",
    "gn:population":0,
    "gn:timezone":"Europe/Stockholm",
    "iso:country":"SE",
    "name:und_x_variant":[
        "\u00d6rb\u00e4cken",
        "\u00d6rb\u00e4ck"
    ],
    "wof:name":"Orback",
    "wof:placetype":"locality"
},
  "geometry": {"coordinates":[13.16667,59.78333000000001],"type":"Point"}
}