{
  "type": "Feature",
  "properties": {
    "gn:admin1_code":"28.0",
    "gn:admin2_code":"1481.0",
    "gn:asciiname":"Greggered",
    "gn:cc2":"SE",
    "gn:country_code":"SE",
    "gn:dem":52,
    "gn:feature_class":"P",
    "gn:feature_code":"PPL",
    "gn:name":"Greggered",
    "gn:population":0,
    "gn:timezone":"Europe/Stockholm",
    "iso:country":"SE",
    "name:und_x_variant":[
        "Gr\u00e4ggered"
    ],
    "wof:name":"Greggered",
    "wof:placetype":"locality"
},
  "geometry": {"coordinates":[12.15294,57.609],"type":"Point"}
}