{
  "type": "Feature",
  "properties": {
    "gn:country":"SE",
    "gn:fcode":"PPL",
    "gn:population":364,
    "iso:country":"SE",
    "name:bul_x_preferred":[
        "\u041a\u0443\u0442\u0430\u0438\u043d\u0435\u043d"
    ],
    "name:ceb_x_preferred":[
        "Kuttainen"
    ],
    "name:dan_x_preferred":[
        "Kuttainen"
    ],
    "name:deu_x_preferred":[
        "Kuttainen"
    ],
    "name:eng_x_preferred":[
        "Kuttainen"
    ],
    "name:eus_x_preferred":[
        "Kuttainen"
    ],
    "name:fin_x_preferred":[
        "Kuttainen"
    ],
    "name:fra_x_preferred":[
        "Kuttainen"
    ],
    "name:gle_x_preferred":[
        "Kuttainen"
    ],
    "name:ita_x_preferred":[
        "Kuttainen"
    ],
    "name:lld_x_preferred":[
        "Kuttainen"
    ],
    "name:nan_x_preferred":[
        "Kuttainen"
    ],
    "name:nld_x_preferred":[
        "Kuttainen"
    ],
    "name:nno_x_preferred":[
        "Kuttainen"
    ],
    "name:nob_x_preferred":[
        "Kuttainen"
    ],
    "name:pol_x_preferred":[
        "Kuttainen"
    ],
    "name:rus_x_preferred":[
        "\u041a\u0443\u0442\u0442\u0430\u0439\u043d\u0435\u043d"
    ],
    "name:sme_x_preferred":[
        "Guhtt\u00e1s"
    ],
    "name:swe_x_preferred":[
        "Kuttainen"
    ],
    "name:und_x_variant":[
        "Kuttanen"
    ],
    "qs_pg:aaroncc":"SE",
    "qs_pg:gn_country":"SE",
    "qs_pg:gn_fcode":"PPL",
    "qs_pg:gn_pop":364,
    "qs_pg:name":"Kuttainen",
    "qs_pg:photos_9r":0,
    "qs_pg:photos_sr":0,
    "qs_pg:pop_sr":2,
    "qs_pg:qs_pg_placetype":"locality",
    "wof:name":"Kuttainen",
    "wof:placetype":"locality",
    "wof:population":218
},
  "geometry": {"coordinates":[22.81667,68.38333],"type":"Point"}
}