{
  "type": "Feature",
  "properties": {
    "gn:admin1_code":"27.0",
    "gn:admin2_code":"1265.0",
    "gn:asciiname":"Klamby",
    "gn:country_code":"SE",
    "gn:dem":81,
    "gn:feature_class":"P",
    "gn:feature_code":"PPL",
    "gn:name":"Klamby",
    "gn:population":0,
    "gn:timezone":"Europe/Stockholm",
    "iso:country":"SE",
    "wof:name":"Klamby",
    "wof:placetype":"locality"
},
  "geometry": {"coordinates":[13.73333,55.66667],"type":"Point"}
}