{
  "type": "Feature",
  "properties": {
    "gn:admin1_code":"10.0",
    "gn:admin2_code":"2023.0",
    "gn:asciiname":"Bygardet",
    "gn:country_code":"SE",
    "gn:dem":454,
    "gn:feature_class":"P",
    "gn:feature_code":"PPL",
    "gn:name":"Byg\u00e4rdet",
    "gn:population":0,
    "gn:timezone":"Europe/Stockholm",
    "iso:country":"SE",
    "wof:name":"Bygardet",
    "wof:placetype":"locality"
},
  "geometry": {"coordinates":[13.36667,60.93333000000001],"type":"Point"}
}