{
  "type": "Feature",
  "properties": {
    "gn:admin1_code":"18.0",
    "gn:admin2_code":"461.0",
    "gn:asciiname":"Dillnas",
    "gn:cc2":"SE",
    "gn:country_code":"SE",
    "gn:dem":26,
    "gn:feature_class":"P",
    "gn:feature_code":"PPL",
    "gn:name":"Dilln\u00e4s",
    "gn:population":0,
    "gn:timezone":"Europe/Stockholm",
    "iso:country":"SE",
    "name:und_x_variant":[
        "Dilln\u00e4sby",
        "Dilln\u00e4s"
    ],
    "wof:name":"Dillnas",
    "wof:placetype":"locality"
},
  "geometry": {"coordinates":[17.26667,59.11666999999999],"type":"Point"}
}