{
  "type": "Feature",
  "properties": {
    "gn:admin1_code":"21.0",
    "gn:admin2_code":"382.0",
    "gn:asciiname":"Vettsta",
    "gn:cc2":"SE",
    "gn:country_code":"SE",
    "gn:dem":17,
    "gn:feature_class":"P",
    "gn:feature_code":"PPL",
    "gn:name":"Vettsta",
    "gn:population":0,
    "gn:timezone":"Europe/Stockholm",
    "iso:country":"SE",
    "name:und_x_variant":[
        "V\u00e4ttsta",
        "Vettsta"
    ],
    "wof:name":"Vettsta",
    "wof:placetype":"locality"
},
  "geometry": {"coordinates":[18.15,60.11666999999999],"type":"Point"}
}