{
  "type": "Feature",
  "properties": {
    "gn:gn_country":"SE",
    "gn:gn_fcode":"PPL",
    "gn:gn_pop":0,
    "gn:population":502,
    "iso:country":"SE",
    "name:dan_x_preferred":[
        "K\u00e5rsta"
    ],
    "name:deu_x_preferred":[
        "K\u00e5rsta"
    ],
    "name:eng_x_preferred":[
        "K\u00e5rsta"
    ],
    "name:fra_x_preferred":[
        "K\u00e5rsta"
    ],
    "name:ita_x_preferred":[
        "K\u00e5rsta"
    ],
    "name:nan_x_preferred":[
        "K\u00e5rsta"
    ],
    "name:nds_x_preferred":[
        "K\u00e5rsta"
    ],
    "name:nld_x_preferred":[
        "K\u00e5rsta"
    ],
    "name:nno_x_preferred":[
        "K\u00e5rsta"
    ],
    "name:nob_x_preferred":[
        "K\u00e5rsta"
    ],
    "name:swe_x_preferred":[
        "K\u00e5rsta"
    ],
    "qs_pg:aaroncc":"SE",
    "qs_pg:gn_country":"SE",
    "qs_pg:gn_fcode":"PPL",
    "qs_pg:gn_pop":0,
    "qs_pg:name":"K\u00e5rsta",
    "qs_pg:name_adm0":"Sverige",
    "qs_pg:name_adm1":"Stockholms L\u00e4n",
    "qs_pg:photos":49,
    "qs_pg:photos_1k":10,
    "qs_pg:photos_9k":1,
    "qs_pg:photos_9r":2,
    "qs_pg:photos_all":49,
    "qs_pg:photos_sr":2,
    "qs_pg:pop_sr":0,
    "qs_pg:qs_pg_placetype":"locality",
    "qs_pg:qs_pg_placetype_gp":"Town",
    "qs_pg:woe_adm0":23424954,
    "woe:adm0_id":23424954,
    "woe:name_adm0":"Sverige",
    "woe:name_adm1":"Stockholms L\u00e4n",
    "woe:placetype":"Town",
    "wof:name":"K\u00e5rsta",
    "wof:placetype":"locality",
    "wof:population":502
},
  "geometry": {"coordinates":[18.26667,59.65],"type":"Point"}
}