{
  "type": "Feature",
  "properties": {
    "gn:admin1_code":"25.0",
    "gn:admin2_code":"1983.0",
    "gn:asciiname":"Halle",
    "gn:country_code":"SE",
    "gn:dem":35,
    "gn:feature_class":"P",
    "gn:feature_code":"PPL",
    "gn:name":"H\u00e4lle",
    "gn:population":0,
    "gn:timezone":"Europe/Stockholm",
    "iso:country":"SE",
    "wof:name":"Halle",
    "wof:placetype":"locality"
},
  "geometry": {"coordinates":[15.91667,59.48333],"type":"Point"}
}