{
  "type": "Feature",
  "properties": {
    "gn:admin1_code":"27.0",
    "gn:admin2_code":"1283.0",
    "gn:asciiname":"Broda",
    "gn:country_code":"SE",
    "gn:dem":34,
    "gn:feature_class":"P",
    "gn:feature_code":"PPL",
    "gn:name":"Br\u00f6da",
    "gn:population":0,
    "gn:timezone":"Europe/Stockholm",
    "iso:country":"SE",
    "name:ces_x_preferred":[
        "Broda"
    ],
    "name:deu_x_preferred":[
        "Broda"
    ],
    "name:fra_x_preferred":[
        "Broda"
    ],
    "name:heb_x_preferred":[
        "\u05d1\u05e8\u05d5\u05d9\u05d3\u05d0"
    ],
    "name:nor_x_preferred":[
        "Br\u00f6da"
    ],
    "name:nor_x_variant":[
        "Br\u00f8da"
    ],
    "name:pol_x_preferred":[
        "Broda"
    ],
    "name:rus_x_preferred":[
        "\u0411\u0440\u043e\u0434\u0430"
    ],
    "wof:name":"Broda",
    "wof:placetype":"locality"
},
  "geometry": {"coordinates":[12.68333,56.11666999999999],"type":"Point"}
}