{
  "type": "Feature",
  "properties": {
    "gn:admin1_code":"7.0",
    "gn:admin2_code":"2321.0",
    "gn:asciiname":"Tvarastugan",
    "gn:country_code":"SE",
    "gn:dem":800,
    "gn:feature_class":"P",
    "gn:feature_code":"PPL",
    "gn:name":"Tv\u00e4r\u00e5stugan",
    "gn:population":0,
    "gn:timezone":"Europe/Stockholm",
    "iso:country":"SE",
    "wof:name":"Tvarastugan",
    "wof:placetype":"locality"
},
  "geometry": {"coordinates":[13.01667,63.43333000000001],"type":"Point"}
}