{
  "type": "Feature",
  "properties": {
    "gn:admin1_code":"22.0",
    "gn:admin2_code":"1781.0",
    "gn:asciiname":"Persbol",
    "gn:cc2":"SE",
    "gn:country_code":"SE",
    "gn:dem":81,
    "gn:feature_class":"P",
    "gn:feature_code":"PPL",
    "gn:name":"Persbol",
    "gn:population":0,
    "gn:timezone":"Europe/Stockholm",
    "iso:country":"SE",
    "name:und_x_variant":[
        "P\u00e4rsbol",
        "Persbol"
    ],
    "wof:name":"Persbol",
    "wof:placetype":"locality"
},
  "geometry": {"coordinates":[14.28333,59.06667],"type":"Point"}
}