{
  "type": "Feature",
  "properties": {
    "gn:admin1_code":"9.0",
    "gn:admin2_code":"881.0",
    "gn:asciiname":"Sodra Bjornahult",
    "gn:cc2":"SE",
    "gn:country_code":"SE",
    "gn:dem":149,
    "gn:feature_class":"P",
    "gn:feature_code":"PPL",
    "gn:name":"S\u00f6dra Bj\u00f6rnahult",
    "gn:population":0,
    "gn:timezone":"Europe/Stockholm",
    "iso:country":"SE",
    "name:nor_x_preferred":[
        "S\u00f6dra Bj\u00f6rnahult"
    ],
    "name:nor_x_variant":[
        "S\u00f8dra Bj\u00f8rnahult"
    ],
    "name:und_x_variant":[
        "Bj\u00f6rnahult",
        "S\u00f6dra Bj\u00f6rnahult"
    ],
    "wof:name":"Sodra Bjornahult",
    "wof:placetype":"locality"
},
  "geometry": {"coordinates":[15.73333,56.75],"type":"Point"}
}