{
  "type": "Feature",
  "properties": {
    "gn:admin1_code":"28.0",
    "gn:admin2_code":"1482.0",
    "gn:asciiname":"Skara",
    "gn:country_code":"SE",
    "gn:dem":0,
    "gn:feature_class":"P",
    "gn:feature_code":"PPL",
    "gn:name":"Sk\u00e5ra",
    "gn:population":0,
    "gn:timezone":"Europe/Stockholm",
    "iso:country":"SE",
    "wof:name":"Skara",
    "wof:placetype":"locality"
},
  "geometry": {"coordinates":[11.78333,57.90556],"type":"Point"}
}