{
  "type": "Feature",
  "properties": {
    "gn:admin1_code":"6.0",
    "gn:admin2_code":"1382.0",
    "gn:asciiname":"Silvergarde",
    "gn:country_code":"SE",
    "gn:dem":147,
    "gn:feature_class":"P",
    "gn:feature_code":"PPL",
    "gn:name":"Silverg\u00e4rde",
    "gn:population":0,
    "gn:timezone":"Europe/Stockholm",
    "iso:country":"SE",
    "wof:name":"Silvergarde",
    "wof:placetype":"locality"
},
  "geometry": {"coordinates":[12.88333,57.11666999999999],"type":"Point"}
}