{
  "type": "Feature",
  "properties": {
    "gn:admin1_code":"28.0",
    "gn:admin2_code":"1435.0",
    "gn:asciiname":"Aleviken",
    "gn:country_code":"SE",
    "gn:dem":17,
    "gn:feature_class":"P",
    "gn:feature_code":"PPL",
    "gn:name":"Aleviken",
    "gn:population":0,
    "gn:timezone":"Europe/Stockholm",
    "iso:country":"SE",
    "wof:name":"Aleviken",
    "wof:placetype":"locality"
},
  "geometry": {"coordinates":[11.21667,58.73611],"type":"Point"}
}