{
  "type": "Feature",
  "properties": {
    "gn:gn_country":"SE",
    "gn:gn_fcode":"PPL",
    "gn:gn_pop":0,
    "iso:country":"SE",
    "name:bul_x_preferred":[
        "\u0420\u043e\u043d\u0435\u0445\u0430\u043c\u043d"
    ],
    "name:deu_x_preferred":[
        "Ronehamn"
    ],
    "name:eng_x_preferred":[
        "Ronehamn"
    ],
    "name:fin_x_preferred":[
        "Ronehamn"
    ],
    "name:fra_x_preferred":[
        "Ronehamn"
    ],
    "name:nld_x_preferred":[
        "Ronehamn"
    ],
    "name:swe_x_preferred":[
        "Ronehamn"
    ],
    "name:unk_x_variant":[
        "Ronehamn"
    ],
    "qs_pg:aaroncc":"SE",
    "qs_pg:gn_country":"SE",
    "qs_pg:gn_fcode":"PPL",
    "qs_pg:gn_pop":0,
    "qs_pg:name":"Ronehamm",
    "qs_pg:name_adm0":"Sverige",
    "qs_pg:name_adm1":"Gotlands L\u00e4n",
    "qs_pg:photos":199,
    "qs_pg:photos_1k":40,
    "qs_pg:photos_9k":1,
    "qs_pg:photos_9r":4,
    "qs_pg:photos_all":199,
    "qs_pg:photos_sr":4,
    "qs_pg:pop_sr":0,
    "qs_pg:qs_pg_placetype":"locality",
    "qs_pg:qs_pg_placetype_gp":"Town",
    "qs_pg:woe_adm0":23424954,
    "woe:adm0_id":23424954,
    "woe:name_adm0":"Sverige",
    "woe:name_adm1":"Gotlands L\u00e4n",
    "woe:placetype":"Town",
    "wof:name":"Ronehamm",
    "wof:placetype":"locality"
},
  "geometry": {"coordinates":[18.48333,57.16667],"type":"Point"}
}