{
  "type": "Feature",
  "properties": {
    "iso:country":"SE",
    "name:ceb_x_preferred":[
        "Salt\u00f6"
    ],
    "name:eng_x_preferred":[
        "Salt\u00f6"
    ],
    "name:ita_x_preferred":[
        "Salt\u00f6"
    ],
    "name:nld_x_preferred":[
        "Salt\u00f6"
    ],
    "name:nor_x_preferred":[
        "Salt\u00f8"
    ],
    "name:nor_x_variant":[
        "Salt\u00f6"
    ],
    "name:swe_x_colloquial":[
        "Salto",
        "Saltoe"
    ],
    "name:swe_x_preferred":[
        "Salt\u00f6"
    ],
    "qs:gn_adm0_cc":"SE",
    "qs:gn_fcode":"PPLX",
    "qs:gn_local":2701713,
    "qs:gn_nam_loc":"Karlskrona, Karlskrona, Blekinge L\u00e4n, SE",
    "qs:gn_namadm1":"02",
    "qs:gn_name":"Salt\u00f6",
    "qs:local_max":3772,
    "qs:local_sum":4547,
    "qs:localhoods":2,
    "qs:name":"Salt\u00f6",
    "qs:name_adm0":"Sverige",
    "qs:name_adm1":"Blekinge L\u00e4n",
    "qs:name_adm2":"Karlskrona",
    "qs:name_local":"Karlskrona",
    "qs:photo_max":448,
    "qs:photo_sum":3772,
    "qs:placetype":"Suburb",
    "qs:quad_count":102,
    "qs:woe_adm0":23424954,
    "qs:woe_adm1":2347045,
    "qs:woe_adm2":12587219,
    "qs:woe_lau":0,
    "qs:woe_local":894952,
    "qs:woe_ver":"7.10.0",
    "wd:wordcount":83,
    "wof:name":"Salt\u00f6",
    "wof:placetype":"neighbourhood"
},
  "geometry": {"coordinates":[15.585791,56.162705],"type":"Point"}
}