{
  "type": "Feature",
  "properties": {
    "gn:country":"SE",
    "gn:fcode":"PPL",
    "gn:population":260,
    "iso:country":"SE",
    "name:ceb_x_preferred":[
        "B\u00e4lgviken"
    ],
    "name:dan_x_preferred":[
        "B\u00e4lgviken"
    ],
    "name:deu_x_preferred":[
        "B\u00e4lgviken"
    ],
    "name:eng_x_preferred":[
        "B\u00e4lgviken"
    ],
    "name:fra_x_preferred":[
        "B\u00e4lgviken"
    ],
    "name:gle_x_preferred":[
        "B\u00e4lgviken"
    ],
    "name:ita_x_preferred":[
        "B\u00e4lgviken"
    ],
    "name:lld_x_preferred":[
        "B\u00e4lgviken"
    ],
    "name:nan_x_preferred":[
        "B\u00e4lgviken"
    ],
    "name:nld_x_preferred":[
        "B\u00e4lgviken"
    ],
    "name:nno_x_preferred":[
        "B\u00e4lgviken"
    ],
    "name:nob_x_preferred":[
        "B\u00e4lgviken"
    ],
    "name:pol_x_preferred":[
        "B\u00e4lgviken"
    ],
    "name:swe_x_preferred":[
        "B\u00e4lgviken"
    ],
    "qs_pg:aaroncc":"SE",
    "qs_pg:gn_country":"SE",
    "qs_pg:gn_fcode":"PPL",
    "qs_pg:gn_pop":260,
    "qs_pg:name":"B\u00e4lgviken",
    "qs_pg:name_adm0":"Sverige",
    "qs_pg:name_adm1":"S\u00f6dermanlands L\u00e4n",
    "qs_pg:photos_9r":0,
    "qs_pg:photos_sr":0,
    "qs_pg:pop_sr":2,
    "qs_pg:qs_pg_placetype":"locality",
    "qs_pg:qs_pg_placetype_gp":"Town",
    "qs_pg:woe_adm0":23424954,
    "woe:adm0_id":23424954,
    "woe:name_adm0":"Sverige",
    "woe:name_adm1":"S\u00f6dermanlands L\u00e4n",
    "woe:placetype":"Town",
    "wof:name":"B\u00e4lgviken",
    "wof:placetype":"locality",
    "wof:population":226
},
  "geometry": {"coordinates":[16.45,59.25],"type":"Point"}
}