{
  "type": "Feature",
  "properties": {
    "gn:admin1_code":"28.0",
    "gn:asciiname":"Bratton",
    "gn:country_code":"SE",
    "gn:dem":4,
    "gn:feature_class":"P",
    "gn:feature_code":"PPL",
    "gn:name":"Bratt\u00f6n",
    "gn:population":0,
    "gn:timezone":"Europe/Stockholm",
    "iso:country":"SE",
    "name:ceb_x_preferred":[
        "Bratton"
    ],
    "name:deu_x_preferred":[
        "Bratton"
    ],
    "name:fra_x_preferred":[
        "Bratton"
    ],
    "name:nld_x_preferred":[
        "Bratton"
    ],
    "name:nor_x_preferred":[
        "Bratt\u00f6n"
    ],
    "name:nor_x_variant":[
        "Bratt\u00f8n"
    ],
    "name:pol_x_preferred":[
        "Bratton"
    ],
    "name:swe_x_preferred":[
        "Bratton"
    ],
    "name:und_x_variant":[
        "Bratt\u00f6n"
    ],
    "wof:name":"Bratton",
    "wof:placetype":"locality"
},
  "geometry": {"coordinates":[11.73333,57.91667],"type":"Point"}
}