{
  "type": "Feature",
  "properties": {
    "gn:admin1_code":"21.0",
    "gn:admin2_code":"380.0",
    "gn:asciiname":"Skeberga",
    "gn:country_code":"SE",
    "gn:dem":22,
    "gn:feature_class":"P",
    "gn:feature_code":"PPL",
    "gn:name":"Skeberga",
    "gn:population":0,
    "gn:timezone":"Europe/Stockholm",
    "iso:country":"SE",
    "wof:name":"Skeberga",
    "wof:placetype":"locality"
},
  "geometry": {"coordinates":[17.98333,60.03333000000001],"type":"Point"}
}