{
  "type": "Feature",
  "properties": {
    "gn:admin1_code":"18.0",
    "gn:admin2_code":"483.0",
    "gn:asciiname":"Kalsta",
    "gn:country_code":"SE",
    "gn:dem":32,
    "gn:feature_class":"P",
    "gn:feature_code":"PPL",
    "gn:name":"Kalsta",
    "gn:population":0,
    "gn:timezone":"Europe/Stockholm",
    "iso:country":"SE",
    "wof:name":"Kalsta",
    "wof:placetype":"locality"
},
  "geometry": {"coordinates":[16.33333,59.06667],"type":"Point"}
}