{
  "type": "Feature",
  "properties": {
    "gn:admin1_code":"9.0",
    "gn:admin2_code":"840.0",
    "gn:asciiname":"Brostorp",
    "gn:country_code":"SE",
    "gn:dem":42,
    "gn:feature_class":"P",
    "gn:feature_code":"PPL",
    "gn:name":"Brostorp",
    "gn:population":0,
    "gn:timezone":"Europe/Stockholm",
    "iso:country":"SE",
    "wof:name":"Brostorp",
    "wof:placetype":"locality"
},
  "geometry": {"coordinates":[16.55,56.71666999999999],"type":"Point"}
}