{
  "type": "Feature",
  "properties": {
    "gn:admin1_code":"26.0",
    "gn:asciiname":"Eldgarnso",
    "gn:cc2":"SE",
    "gn:country_code":"SE",
    "gn:dem":21,
    "gn:feature_class":"P",
    "gn:feature_code":"PPL",
    "gn:name":"Eldgarns\u00f6",
    "gn:population":0,
    "gn:timezone":"Europe/Stockholm",
    "iso:country":"SE",
    "name:nor_x_preferred":[
        "Eldgarns\u00f6"
    ],
    "name:nor_x_variant":[
        "Eldgarns\u00f8"
    ],
    "name:und_x_variant":[
        "Eldgarn",
        "Eldgarns\u00f6"
    ],
    "wof:name":"Eldgarnso",
    "wof:placetype":"locality"
},
  "geometry": {"coordinates":[17.65,59.43333000000001],"type":"Point"}
}