{
  "type": "Feature",
  "properties": {
    "gn:admin1_code":"28.0",
    "gn:admin2_code":"1486.0",
    "gn:asciiname":"Kollekind",
    "gn:country_code":"SE",
    "gn:dem":42,
    "gn:feature_class":"P",
    "gn:feature_code":"PPL",
    "gn:name":"Kollekind",
    "gn:population":0,
    "gn:timezone":"Europe/Stockholm",
    "iso:country":"SE",
    "wof:name":"Kollekind",
    "wof:placetype":"locality"
},
  "geometry": {"coordinates":[11.25,58.925],"type":"Point"}
}