{
  "type": "Feature",
  "properties": {
    "gn:admin1_code":"28.0",
    "gn:admin2_code":"1487.0",
    "gn:asciiname":"Binas",
    "gn:cc2":"SE",
    "gn:country_code":"SE",
    "gn:dem":73,
    "gn:feature_class":"P",
    "gn:feature_code":"PPL",
    "gn:name":"Bin\u00e4s",
    "gn:population":0,
    "gn:timezone":"Europe/Stockholm",
    "iso:country":"SE",
    "name:cat_x_preferred":[
        "Binas"
    ],
    "name:ceb_x_preferred":[
        "Binas"
    ],
    "name:deu_x_preferred":[
        "Binas"
    ],
    "name:eus_x_preferred":[
        "Binas"
    ],
    "name:fra_x_preferred":[
        "Binas"
    ],
    "name:hun_x_preferred":[
        "Binas"
    ],
    "name:ita_x_preferred":[
        "Binas"
    ],
    "name:lat_x_preferred":[
        "Binas"
    ],
    "name:msa_x_preferred":[
        "Binas"
    ],
    "name:nld_x_preferred":[
        "Binas"
    ],
    "name:oci_x_preferred":[
        "Binas"
    ],
    "name:pms_x_preferred":[
        "Binas"
    ],
    "name:pol_x_preferred":[
        "Binas"
    ],
    "name:por_x_preferred":[
        "Binas"
    ],
    "name:ron_x_preferred":[
        "Binas"
    ],
    "name:slk_x_preferred":[
        "Binas"
    ],
    "name:spa_x_preferred":[
        "Binas"
    ],
    "name:srp_x_preferred":[
        "\u0411\u0438\u043d\u0430"
    ],
    "name:swe_x_preferred":[
        "Binas"
    ],
    "name:ukr_x_preferred":[
        "\u0411\u0456\u043d\u0430"
    ],
    "name:und_x_variant":[
        "S\u00f6dra Bin\u00e4s",
        "Bin\u00e4s"
    ],
    "name:uzb_x_preferred":[
        "Binas"
    ],
    "name:vie_x_preferred":[
        "Binas"
    ],
    "name:vol_x_preferred":[
        "Binas"
    ],
    "name:war_x_preferred":[
        "Binas"
    ],
    "wof:name":"Binas",
    "wof:placetype":"locality"
},
  "geometry": {"coordinates":[12.13306,58.45],"type":"Point"}
}