{
  "type": "Feature",
  "properties": {
    "gn:admin1_code":"28.0",
    "gn:admin2_code":"1487.0",
    "gn:asciiname":"Binas",
    "gn:cc2":"SE",
    "gn:country_code":"SE",
    "gn:dem":73,
    "gn:feature_class":"P",
    "gn:feature_code":"PPL",
    "gn:name":"Bin\u00e4s",
    "gn:population":0,
    "gn:timezone":"Europe/Stockholm",
    "iso:country":"SE",
    "name:und_x_variant":[
        "S\u00f6dra Bin\u00e4s",
        "Bin\u00e4s"
    ],
    "wof:name":"Binas",
    "wof:placetype":"locality"
},
  "geometry": {"coordinates":[12.13306,58.45],"type":"Point"}
}