{
  "type": "Feature",
  "properties": {
    "gn:admin1_code":"23.0",
    "gn:admin2_code":"2409.0",
    "gn:asciiname":"Ratu",
    "gn:country_code":"SE",
    "gn:dem":19,
    "gn:feature_class":"P",
    "gn:feature_code":"PPL",
    "gn:name":"Ratu",
    "gn:population":0,
    "gn:timezone":"Europe/Stockholm",
    "iso:country":"SE",
    "name:fra_x_preferred":[
        "Ratu"
    ],
    "name:hin_x_preferred":[
        "\u0930\u093e\u0924\u0942"
    ],
    "name:ita_x_preferred":[
        "Ratu"
    ],
    "name:new_x_preferred":[
        "\u0930\u0924\u0941"
    ],
    "name:nor_x_preferred":[
        "Ratu"
    ],
    "name:pol_x_preferred":[
        "Ratu"
    ],
    "name:rus_x_preferred":[
        "\u0420\u0430\u0442\u0443"
    ],
    "name:swe_x_preferred":[
        "Ratu"
    ],
    "name:tur_x_preferred":[
        "Ratu"
    ],
    "name:zho_x_preferred":[
        "\u62c9\u56fe"
    ],
    "wof:name":"Ratu",
    "wof:placetype":"locality"
},
  "geometry": {"coordinates":[20.81667,63.96666999999999],"type":"Point"}
}