{
  "type": "Feature",
  "properties": {
    "gn:admin1_code":"25.0",
    "gn:admin2_code":"1962.0",
    "gn:asciiname":"Broarna",
    "gn:country_code":"SE",
    "gn:dem":83,
    "gn:feature_class":"P",
    "gn:feature_code":"PPL",
    "gn:name":"Broarna",
    "gn:population":0,
    "gn:timezone":"Europe/Stockholm",
    "iso:country":"SE",
    "wof:name":"Broarna",
    "wof:placetype":"locality"
},
  "geometry": {"coordinates":[16.03333,60.01667],"type":"Point"}
}