{
  "type": "Feature",
  "properties": {
    "gn:admin1_code":"27.0",
    "gn:admin2_code":"1278.0",
    "gn:asciiname":"Ljungby",
    "gn:cc2":"SE",
    "gn:country_code":"SE",
    "gn:dem":25,
    "gn:feature_class":"P",
    "gn:feature_code":"PPL",
    "gn:name":"Ljungby",
    "gn:population":0,
    "gn:timezone":"Europe/Stockholm",
    "iso:country":"SE",
    "name:und_x_variant":[
        "V\u00e4stra Ljungby",
        "Ljungby"
    ],
    "wof:name":"Ljungby",
    "wof:placetype":"locality"
},
  "geometry": {"coordinates":[12.78333,56.33333],"type":"Point"}
}