{
  "type": "Feature",
  "properties": {
    "gn:admin1_code":"27.0",
    "gn:admin2_code":"1278.0",
    "gn:asciiname":"Ljungby",
    "gn:cc2":"SE",
    "gn:country_code":"SE",
    "gn:dem":25,
    "gn:feature_class":"P",
    "gn:feature_code":"PPL",
    "gn:name":"Ljungby",
    "gn:population":0,
    "gn:timezone":"Europe/Stockholm",
    "iso:country":"SE",
    "name:bul_x_preferred":[
        "\u042e\u043d\u0433\u0431\u044e"
    ],
    "name:ceb_x_preferred":[
        "Ljungby"
    ],
    "name:dan_x_preferred":[
        "Ljungby"
    ],
    "name:deu_x_preferred":[
        "Ljungby"
    ],
    "name:fao_x_preferred":[
        "Ljungby"
    ],
    "name:fas_x_preferred":[
        "\u0644\u0626\u0648\u0646\u0628\u0647"
    ],
    "name:fin_x_preferred":[
        "Ljungby"
    ],
    "name:fra_x_preferred":[
        "Ljungby"
    ],
    "name:hrv_x_preferred":[
        "Ljungby"
    ],
    "name:ind_x_preferred":[
        "Ljungby"
    ],
    "name:isl_x_preferred":[
        "Ljungby"
    ],
    "name:ita_x_preferred":[
        "Ljungby"
    ],
    "name:lit_x_preferred":[
        "Jungbis"
    ],
    "name:nld_x_preferred":[
        "Ljungby"
    ],
    "name:nno_x_preferred":[
        "Ljungby"
    ],
    "name:nor_x_preferred":[
        "Ljungby"
    ],
    "name:pol_x_preferred":[
        "Ljungby"
    ],
    "name:por_x_preferred":[
        "Ljungby"
    ],
    "name:ron_x_preferred":[
        "Ljungby"
    ],
    "name:sme_x_preferred":[
        "Ljungby"
    ],
    "name:srp_x_preferred":[
        "\u0408\u0443\u043d\u0433\u0431\u0438"
    ],
    "name:swa_x_preferred":[
        "Ljungby"
    ],
    "name:swe_x_preferred":[
        "Ljungby"
    ],
    "name:tur_x_preferred":[
        "Ljungby"
    ],
    "name:ukr_x_preferred":[
        "\u042e\u043d\u0433\u0431\u044e"
    ],
    "name:und_x_variant":[
        "V\u00e4stra Ljungby"
    ],
    "name:vol_x_preferred":[
        "Ljungby"
    ],
    "wof:name":"Ljungby",
    "wof:placetype":"locality"
},
  "geometry": {"coordinates":[12.78333,56.33333],"type":"Point"}
}