{
  "type": "Feature",
  "properties": {
    "gn:country":"SE",
    "gn:fcode":"PPL",
    "gn:population":100,
    "iso:country":"SE",
    "name:dan_x_preferred":[
        "H\u00e4lles\u00e5s"
    ],
    "name:deu_x_preferred":[
        "H\u00e4lles\u00e5s"
    ],
    "name:eng_x_preferred":[
        "H\u00e4lles\u00e5s"
    ],
    "name:fra_x_preferred":[
        "H\u00e4lles\u00e5s"
    ],
    "name:nds_x_preferred":[
        "H\u00e4lles\u00e5s"
    ],
    "name:nld_x_preferred":[
        "H\u00e4lles\u00e5s"
    ],
    "name:nno_x_preferred":[
        "H\u00e4lles\u00e5s"
    ],
    "name:nob_x_preferred":[
        "H\u00e4lles\u00e5s"
    ],
    "name:swe_x_preferred":[
        "H\u00e4lles\u00e5s"
    ],
    "qs_pg:aaroncc":"SE",
    "qs_pg:gn_country":"SE",
    "qs_pg:gn_fcode":"PPL",
    "qs_pg:gn_pop":100,
    "qs_pg:name":"H\u00e4lles\u00e5s",
    "qs_pg:photos_9r":0,
    "qs_pg:photos_sr":0,
    "qs_pg:pop_sr":1,
    "qs_pg:qs_pg_placetype":"locality",
    "wof:name":"H\u00e4lles\u00e5s",
    "wof:placetype":"locality",
    "wof:population":100
},
  "geometry": {"coordinates":[11.9993,57.56143],"type":"Point"}
}