{
  "type": "Feature",
  "properties": {
    "gn:admin1_code":"27.0",
    "gn:admin2_code":"1292.0",
    "gn:asciiname":"OEssjoe",
    "gn:country_code":"SE",
    "gn:dem":45,
    "gn:feature_class":"P",
    "gn:feature_code":"PPL",
    "gn:name":"\u00d6ssj\u00f6",
    "gn:population":223,
    "gn:timezone":"Europe/Stockholm",
    "iso:country":"SE",
    "name:deu_x_preferred":[
        "\u00d6ssj\u00f6"
    ],
    "name:gla_x_preferred":[
        "\u00d6ssj\u00f6"
    ],
    "name:nor_x_preferred":[
        "\u00d6ssj\u00f6"
    ],
    "name:nor_x_variant":[
        "\u00d8ssj\u00f8"
    ],
    "name:pol_x_preferred":[
        "\u00d6ssj\u00f6"
    ],
    "name:por_x_preferred":[
        "\u00d6ssj\u00f6"
    ],
    "name:swe_x_preferred":[
        "\u00d6ssj\u00f6"
    ],
    "wof:name":"OEssjoe",
    "wof:placetype":"locality",
    "wof:population":223
},
  "geometry": {"coordinates":[13.03322,56.22849],"type":"Point"}
}