{
  "type": "Feature",
  "properties": {
    "gn:admin1_code":"28.0",
    "gn:admin2_code":"1473.0",
    "gn:asciiname":"Sodra Tallasen",
    "gn:cc2":"SE",
    "gn:country_code":"SE",
    "gn:dem":106,
    "gn:feature_class":"P",
    "gn:feature_code":"PPL",
    "gn:name":"S\u00f6dra T\u00e4ll\u00e5sen",
    "gn:population":0,
    "gn:timezone":"Europe/Stockholm",
    "iso:country":"SE",
    "name:und_x_variant":[
        "S\u00f6dra Tell\u00e5sen",
        "S\u00f6dra T\u00e4ll\u00e5sen"
    ],
    "wof:name":"Sodra Tallasen",
    "wof:placetype":"locality"
},
  "geometry": {"coordinates":[14.15,58.68333000000001],"type":"Point"}
}