{
  "type": "Feature",
  "properties": {
    "gn:admin1_code":"24.0",
    "gn:admin2_code":"2284.0",
    "gn:asciiname":"Norum",
    "gn:country_code":"SE",
    "gn:dem":50,
    "gn:feature_class":"P",
    "gn:feature_code":"PPL",
    "gn:name":"Norum",
    "gn:population":0,
    "gn:timezone":"Europe/Stockholm",
    "iso:country":"SE",
    "name:rus_x_preferred":[
        "\u041d\u043e\u0440\u0443\u043c"
    ],
    "wof:name":"Norum",
    "wof:placetype":"locality"
},
  "geometry": {"coordinates":[18.43333,63.18333000000001],"type":"Point"}
}