{
  "type": "Feature",
  "properties": {
    "gn:admin1_code":"7.0",
    "gn:admin2_code":"2303.0",
    "gn:asciiname":"Oravattnet",
    "gn:country_code":"SE",
    "gn:dem":411,
    "gn:feature_class":"P",
    "gn:feature_code":"PPL",
    "gn:name":"\u00d6ravattnet",
    "gn:population":0,
    "gn:timezone":"Europe/Stockholm",
    "iso:country":"SE",
    "name:nor_x_preferred":[
        "\u00d6ravattnet"
    ],
    "name:nor_x_variant":[
        "\u00d8ravattnet"
    ],
    "name:und_x_variant":[
        "\u00d6ravattnet"
    ],
    "wof:name":"Oravattnet",
    "wof:placetype":"locality"
},
  "geometry": {"coordinates":[15.58333,63.35],"type":"Point"}
}