{
  "type": "Feature",
  "properties": {
    "gn:admin1_code":"23.0",
    "gn:admin2_code":"2482.0",
    "gn:asciiname":"Martensboda",
    "gn:country_code":"SE",
    "gn:dem":70,
    "gn:feature_class":"P",
    "gn:feature_code":"PPL",
    "gn:name":"M\u00e5rtensboda",
    "gn:population":0,
    "gn:timezone":"Europe/Stockholm",
    "iso:country":"SE",
    "wof:name":"Martensboda",
    "wof:placetype":"locality"
},
  "geometry": {"coordinates":[20.95,64.45],"type":"Point"}
}