{
  "type": "Feature",
  "properties": {
    "gn:admin1_code":"26.0",
    "gn:admin2_code":"120.0",
    "gn:asciiname":"Grisslinge",
    "gn:cc2":"SE",
    "gn:country_code":"SE",
    "gn:dem":36,
    "gn:feature_class":"P",
    "gn:feature_code":"PPL",
    "gn:name":"Grisslinge",
    "gn:population":0,
    "gn:timezone":"Europe/Stockholm",
    "iso:country":"SE",
    "name:und_x_variant":[
        "Grisslingebaden",
        "Grisslinge"
    ],
    "wof:name":"Grisslinge",
    "wof:placetype":"locality"
},
  "geometry": {"coordinates":[18.46667,59.31667],"type":"Point"}
}