{
  "type": "Feature",
  "properties": {
    "gn:admin1_code":"3.0",
    "gn:admin2_code":"2104.0",
    "gn:asciiname":"Stridsborg",
    "gn:country_code":"SE",
    "gn:dem":127,
    "gn:feature_class":"P",
    "gn:feature_code":"PPL",
    "gn:name":"Stridsborg",
    "gn:population":0,
    "gn:timezone":"Europe/Stockholm",
    "iso:country":"SE",
    "wof:name":"Stridsborg",
    "wof:placetype":"locality"
},
  "geometry": {"coordinates":[16.46667,60.45],"type":"Point"}
}