{
  "type": "Feature",
  "properties": {
    "gn:admin1_code":"26.0",
    "gn:admin2_code":"160.0",
    "gn:asciiname":"Viggbyholm",
    "gn:country_code":"SE",
    "gn:dem":14,
    "gn:feature_class":"P",
    "gn:feature_code":"PPL",
    "gn:name":"Viggbyholm",
    "gn:population":0,
    "gn:timezone":"Europe/Stockholm",
    "iso:country":"SE",
    "wof:name":"Viggbyholm",
    "wof:placetype":"locality"
},
  "geometry": {"coordinates":[18.10401,59.43888000000001],"type":"Point"}
}