{
  "type": "Feature",
  "properties": {
    "gn:admin1_code":"23.0",
    "gn:admin2_code":"2482.0",
    "gn:asciiname":"Granbergstrask",
    "gn:country_code":"SE",
    "gn:dem":289,
    "gn:feature_class":"P",
    "gn:feature_code":"PPL",
    "gn:name":"Granbergstr\u00e4sk",
    "gn:population":0,
    "gn:timezone":"Europe/Stockholm",
    "iso:country":"SE",
    "wof:name":"Granbergstrask",
    "wof:placetype":"locality"
},
  "geometry": {"coordinates":[19.85,65.09999999999999],"type":"Point"}
}