{
  "type": "Feature",
  "properties": {
    "gn:admin1_code":"21.0",
    "gn:asciiname":"Korbo",
    "gn:country_code":"SE",
    "gn:dem":34,
    "gn:feature_class":"P",
    "gn:feature_code":"PPL",
    "gn:name":"Korbo",
    "gn:population":0,
    "gn:timezone":"Europe/Stockholm",
    "iso:country":"SE",
    "wof:name":"Korbo",
    "wof:placetype":"locality"
},
  "geometry": {"coordinates":[17.25,60.18333000000001],"type":"Point"}
}