{
  "type": "Feature",
  "properties": {
    "gn:admin1_code":"7.0",
    "gn:admin2_code":"2303.0",
    "gn:asciiname":"Osterede",
    "gn:country_code":"SE",
    "gn:dem":113,
    "gn:feature_class":"P",
    "gn:feature_code":"PPL",
    "gn:name":"\u00d6sterede",
    "gn:population":0,
    "gn:timezone":"Europe/Stockholm",
    "iso:country":"SE",
    "name:nor_x_preferred":[
        "\u00d6sterede"
    ],
    "name:nor_x_variant":[
        "\u00d8sterede"
    ],
    "wof:name":"Osterede",
    "wof:placetype":"locality"
},
  "geometry": {"coordinates":[16.56667,63.03333000000001],"type":"Point"}
}