{
  "type": "Feature",
  "properties": {
    "gn:admin1_code":"28.0",
    "gn:admin2_code":"1499.0",
    "gn:asciiname":"Hog",
    "gn:country_code":"SE",
    "gn:dem":212,
    "gn:feature_class":"P",
    "gn:feature_code":"PPL",
    "gn:name":"H\u00f6g",
    "gn:population":0,
    "gn:timezone":"Europe/Stockholm",
    "iso:country":"SE",
    "name:nor_x_preferred":[
        "H\u00f6g"
    ],
    "name:nor_x_variant":[
        "H\u00f8g"
    ],
    "name:und_x_variant":[
        "H\u00f6g"
    ],
    "wof:name":"Hog",
    "wof:placetype":"locality"
},
  "geometry": {"coordinates":[13.55,58.05],"type":"Point"}
}