{
  "type": "Feature",
  "properties": {
    "gn:admin1_code":"14.0",
    "gn:admin2_code":"2581.0",
    "gn:asciiname":"Hogsbole",
    "gn:country_code":"SE",
    "gn:dem":3,
    "gn:feature_class":"P",
    "gn:feature_code":"PPL",
    "gn:name":"H\u00f6gsb\u00f6le",
    "gn:population":0,
    "gn:timezone":"Europe/Stockholm",
    "iso:country":"SE",
    "name:nor_x_preferred":[
        "H\u00f6gsb\u00f6le"
    ],
    "name:nor_x_variant":[
        "H\u00f8gsb\u00f8le"
    ],
    "name:und_x_variant":[
        "H\u00f6gsb\u00f6le"
    ],
    "wof:name":"Hogsbole",
    "wof:placetype":"locality"
},
  "geometry": {"coordinates":[21.51667,65.21666999999999],"type":"Point"}
}