{
  "type": "Feature",
  "properties": {
    "gn:admin1_code":"22.0",
    "gn:admin2_code":"1763.0",
    "gn:asciiname":"Dejeforsbruk",
    "gn:cc2":"SE",
    "gn:country_code":"SE",
    "gn:dem":75,
    "gn:feature_class":"P",
    "gn:feature_code":"PPL",
    "gn:name":"Dejeforsbruk",
    "gn:population":0,
    "gn:timezone":"Europe/Stockholm",
    "iso:country":"SE",
    "name:und_x_variant":[
        "Dejefors",
        "Dejeforsbruk"
    ],
    "wof:name":"Dejeforsbruk",
    "wof:placetype":"locality"
},
  "geometry": {"coordinates":[13.46667,59.61666999999999],"type":"Point"}
}