{
  "type": "Feature",
  "properties": {
    "gn:admin1_code":"10.0",
    "gn:admin2_code":"2085.0",
    "gn:asciiname":"Ostanbjorka",
    "gn:country_code":"SE",
    "gn:dem":157,
    "gn:feature_class":"P",
    "gn:feature_code":"PPL",
    "gn:name":"\u00d6stanbj\u00f6rka",
    "gn:population":0,
    "gn:timezone":"Europe/Stockholm",
    "iso:country":"SE",
    "name:nor_x_preferred":[
        "\u00d6stanbj\u00f6rka"
    ],
    "name:nor_x_variant":[
        "\u00d8stanbj\u00f8rka"
    ],
    "wof:name":"Ostanbjorka",
    "wof:placetype":"locality"
},
  "geometry": {"coordinates":[15.01667,60.26667],"type":"Point"}
}