{
  "type": "Feature",
  "properties": {
    "gn:admin1_code":"26.0",
    "gn:admin2_code":"188.0",
    "gn:asciiname":"Almvik",
    "gn:country_code":"SE",
    "gn:dem":15,
    "gn:feature_class":"P",
    "gn:feature_code":"PPL",
    "gn:name":"Almvik",
    "gn:population":0,
    "gn:timezone":"Europe/Stockholm",
    "iso:country":"SE",
    "name:ceb_x_preferred":[
        "Almvik"
    ],
    "name:fas_x_preferred":[
        "\u0627\u0644\u0645\u0648\u06cc\u06a9"
    ],
    "name:ita_x_preferred":[
        "Almvik"
    ],
    "name:nld_x_preferred":[
        "Almvik"
    ],
    "name:nno_x_preferred":[
        "Almvik"
    ],
    "name:nor_x_preferred":[
        "Almvik"
    ],
    "name:swe_x_preferred":[
        "Almvik"
    ],
    "wof:name":"Almvik",
    "wof:placetype":"locality"
},
  "geometry": {"coordinates":[18.89444,59.61833000000001],"type":"Point"}
}