{
  "type": "Feature",
  "properties": {
    "gn:admin1_code":"26.0",
    "gn:admin2_code":"120.0",
    "gn:asciiname":"Sodersunda",
    "gn:country_code":"SE",
    "gn:dem":-9999,
    "gn:feature_class":"P",
    "gn:feature_code":"PPL",
    "gn:name":"S\u00f6dersunda",
    "gn:population":0,
    "gn:timezone":"Europe/Stockholm",
    "iso:country":"SE",
    "name:nor_x_preferred":[
        "S\u00f6dersunda"
    ],
    "name:nor_x_variant":[
        "S\u00f8dersunda"
    ],
    "wof:name":"Sodersunda",
    "wof:placetype":"locality"
},
  "geometry": {"coordinates":[18.73333,59.26667],"type":"Point"}
}