{
  "type": "Feature",
  "properties": {
    "gn:admin1_code":"18.0",
    "gn:admin2_code":"480.0",
    "gn:asciiname":"Enstorp",
    "gn:country_code":"SE",
    "gn:dem":33,
    "gn:feature_class":"P",
    "gn:feature_code":"PPL",
    "gn:name":"Enstorp",
    "gn:population":0,
    "gn:timezone":"Europe/Stockholm",
    "iso:country":"SE",
    "wof:name":"Enstorp",
    "wof:placetype":"locality"
},
  "geometry": {"coordinates":[16.75,58.75],"type":"Point"}
}