{
  "type": "Feature",
  "properties": {
    "gn:admin1_code":"22.0",
    "gn:admin2_code":"1781.0",
    "gn:asciiname":"Linnevalstorp",
    "gn:country_code":"SE",
    "gn:dem":98,
    "gn:feature_class":"P",
    "gn:feature_code":"PPL",
    "gn:name":"Linnevalstorp",
    "gn:population":0,
    "gn:timezone":"Europe/Stockholm",
    "iso:country":"SE",
    "wof:name":"Linnevalstorp",
    "wof:placetype":"locality"
},
  "geometry": {"coordinates":[14.23333,59.08333],"type":"Point"}
}