{
  "type": "Feature",
  "properties": {
    "gn:country":"SE",
    "gn:fcode":"PPLL",
    "gn:population":75,
    "iso:country":"SE",
    "name:dan_x_preferred":[
        "Ensta"
    ],
    "name:deu_x_preferred":[
        "Ensta"
    ],
    "name:eng_x_preferred":[
        "Ensta"
    ],
    "name:fra_x_preferred":[
        "Ensta"
    ],
    "name:nds_x_preferred":[
        "Ensta"
    ],
    "name:nld_x_preferred":[
        "Norrbyvret"
    ],
    "name:nno_x_preferred":[
        "Ensta"
    ],
    "name:nob_x_preferred":[
        "Ensta"
    ],
    "name:swe_x_preferred":[
        "Ensta"
    ],
    "qs_pg:aaroncc":"SE",
    "qs_pg:gn_country":"SE",
    "qs_pg:gn_fcode":"PPLL",
    "qs_pg:gn_pop":75,
    "qs_pg:name":"Norrbyvret",
    "qs_pg:photos_9r":0,
    "qs_pg:photos_sr":0,
    "qs_pg:pop_sr":1,
    "qs_pg:qs_pg_placetype":"locality",
    "wof:name":"Norrbyvret",
    "wof:placetype":"locality",
    "wof:population":75
},
  "geometry": {"coordinates":[17.77944,59.18722],"type":"Point"}
}