{
  "type": "Feature",
  "properties": {
    "gn:admin1_code":"24.0",
    "gn:admin2_code":"2284.0",
    "gn:asciiname":"Solberg",
    "gn:country_code":"SE",
    "gn:dem":368,
    "gn:feature_class":"P",
    "gn:feature_code":"PPL",
    "gn:name":"Solberg",
    "gn:population":0,
    "gn:timezone":"Europe/Stockholm",
    "iso:country":"SE",
    "wof:name":"Solberg",
    "wof:placetype":"locality"
},
  "geometry": {"coordinates":[17.63332999999999,63.78333000000001],"type":"Point"}
}