{
  "type": "Feature",
  "properties": {
    "gn:admin1_code":"28.0",
    "gn:admin2_code":"1480.0",
    "gn:asciiname":"Lunnegarden",
    "gn:country_code":"SE",
    "gn:dem":28,
    "gn:feature_class":"P",
    "gn:feature_code":"PPL",
    "gn:name":"Lunneg\u00e5rden",
    "gn:population":0,
    "gn:timezone":"Europe/Stockholm",
    "iso:country":"SE",
    "wof:name":"Lunnegarden",
    "wof:placetype":"locality"
},
  "geometry": {"coordinates":[11.81667,57.76667],"type":"Point"}
}