{
  "type": "Feature",
  "properties": {
    "gn:admin1_code":"23.0",
    "gn:admin2_code":"2460.0",
    "gn:asciiname":"Hallfors",
    "gn:country_code":"SE",
    "gn:dem":99,
    "gn:feature_class":"P",
    "gn:feature_code":"PPL",
    "gn:name":"H\u00e4llfors",
    "gn:population":0,
    "gn:timezone":"Europe/Stockholm",
    "iso:country":"SE",
    "wof:name":"Hallfors",
    "wof:placetype":"locality"
},
  "geometry": {"coordinates":[19.66667,63.95],"type":"Point"}
}