{
  "type": "Feature",
  "properties": {
    "gn:admin1_code":"28.0",
    "gn:admin2_code":"1485.0",
    "gn:asciiname":"Strandhagen",
    "gn:country_code":"SE",
    "gn:dem":68,
    "gn:feature_class":"P",
    "gn:feature_code":"PPL",
    "gn:name":"Strandhagen",
    "gn:population":0,
    "gn:timezone":"Europe/Stockholm",
    "iso:country":"SE",
    "wof:name":"Strandhagen",
    "wof:placetype":"locality"
},
  "geometry": {"coordinates":[11.65,58.2875],"type":"Point"}
}