{
  "type": "Feature",
  "properties": {
    "gn:admin1_code":"28.0",
    "gn:admin2_code":"1439.0",
    "gn:asciiname":"Hare",
    "gn:cc2":"SE",
    "gn:country_code":"SE",
    "gn:dem":134,
    "gn:feature_class":"P",
    "gn:feature_code":"PPL",
    "gn:name":"H\u00e4re",
    "gn:population":0,
    "gn:timezone":"Europe/Stockholm",
    "iso:country":"SE",
    "name:und_x_variant":[
        "H\u00e4r\u00f6",
        "H\u00e4reholm",
        "H\u00e4re"
    ],
    "wof:name":"Hare",
    "wof:placetype":"locality"
},
  "geometry": {"coordinates":[11.96667,58.65],"type":"Point"}
}