{
  "type": "Feature",
  "properties": {
    "gn:admin1_code":"21.0",
    "gn:admin2_code":"360.0",
    "gn:asciiname":"Gryttby",
    "gn:country_code":"SE",
    "gn:dem":31,
    "gn:feature_class":"P",
    "gn:feature_code":"PPL",
    "gn:name":"Gryttby",
    "gn:population":0,
    "gn:timezone":"Europe/Stockholm",
    "iso:country":"SE",
    "wof:name":"Gryttby",
    "wof:placetype":"locality"
},
  "geometry": {"coordinates":[17.56667,60.13333000000001],"type":"Point"}
}