{
  "type": "Feature",
  "properties": {
    "gn:admin1_code":"12.0",
    "gn:admin2_code":"765.0",
    "gn:asciiname":"Ljunggardskop",
    "gn:country_code":"SE",
    "gn:dem":127,
    "gn:feature_class":"P",
    "gn:feature_code":"PPL",
    "gn:name":"Ljungg\u00e5rdsk\u00f6p",
    "gn:population":0,
    "gn:timezone":"Europe/Stockholm",
    "iso:country":"SE",
    "name:nor_x_preferred":[
        "Ljungg\u00e5rdsk\u00f6p"
    ],
    "name:nor_x_variant":[
        "Ljungg\u00e5rdsk\u00f8p"
    ],
    "wof:name":"Ljunggardskop",
    "wof:placetype":"locality"
},
  "geometry": {"coordinates":[13.88333,56.56667],"type":"Point"}
}