{
  "type": "Feature",
  "properties": {
    "iso:country":"SE",
    "qs_pg:aaroncc":"SE",
    "qs_pg:name":"G\u00f6rvik",
    "qs_pg:name_adm0":"Sverige",
    "qs_pg:name_adm1":"Hallands L\u00e4n",
    "qs_pg:photos":341,
    "qs_pg:photos_1k":69,
    "qs_pg:photos_9k":2,
    "qs_pg:photos_9r":5,
    "qs_pg:photos_all":341,
    "qs_pg:photos_sr":5,
    "qs_pg:pop_sr":0,
    "qs_pg:qs_pg_placetype":"locality",
    "qs_pg:qs_pg_placetype_gp":"Town",
    "qs_pg:woe_adm0":23424954,
    "woe:adm0_id":23424954,
    "woe:name_adm0":"Sverige",
    "woe:name_adm1":"Hallands L\u00e4n",
    "woe:placetype":"Town",
    "wof:name":"G\u00f6rvik",
    "wof:placetype":"locality"
},
  "geometry": {"coordinates":[12.749633,56.647002],"type":"Point"}
}