{
  "type": "Feature",
  "properties": {
    "gn:admin1_code":"14.0",
    "gn:asciiname":"Haparanda Hamn",
    "gn:country_code":"SE",
    "gn:dem":15,
    "gn:feature_class":"P",
    "gn:feature_code":"PPL",
    "gn:name":"Haparanda Hamn",
    "gn:population":0,
    "gn:timezone":"Europe/Stockholm",
    "iso:country":"SE",
    "name:fin_x_preferred":[
        "Hamina"
    ],
    "name:und_x_variant":[
        "Haparandshamn",
        "Karl Johans Stad",
        "Karl Johans Stads",
        "Haparanda Hamn"
    ],
    "wof:name":"Haparanda Hamn",
    "wof:placetype":"locality"
},
  "geometry": {"coordinates":[23.89961,65.77979000000001],"type":"Point"}
}