{
  "type": "Feature",
  "properties": {
    "gn:admin1_code":"22.0",
    "gn:admin2_code":"1780.0",
    "gn:asciiname":"Fosked",
    "gn:cc2":"SE",
    "gn:country_code":"SE",
    "gn:dem":131,
    "gn:feature_class":"P",
    "gn:feature_code":"PPL",
    "gn:name":"F\u00f6sked",
    "gn:population":0,
    "gn:timezone":"Europe/Stockholm",
    "iso:country":"SE",
    "name:nor_x_preferred":[
        "F\u00f6sked"
    ],
    "name:nor_x_variant":[
        "F\u00f8sked"
    ],
    "name:und_x_variant":[
        "F\u00f6ske",
        "F\u00f6sked"
    ],
    "wof:name":"Fosked",
    "wof:placetype":"locality"
},
  "geometry": {"coordinates":[13.66667,59.65],"type":"Point"}
}