{
  "type": "Feature",
  "properties": {
    "gn:admin1_code":"27.0",
    "gn:admin2_code":"1270.0",
    "gn:asciiname":"Sallshog",
    "gn:country_code":"SE",
    "gn:dem":76,
    "gn:feature_class":"P",
    "gn:feature_code":"PPL",
    "gn:name":"S\u00e4llsh\u00f6g",
    "gn:population":0,
    "gn:timezone":"Europe/Stockholm",
    "iso:country":"SE",
    "wof:name":"Sallshog",
    "wof:placetype":"locality"
},
  "geometry": {"coordinates":[13.96667,55.56667],"type":"Point"}
}