{
  "type": "Feature",
  "properties": {
    "gn:admin1_code":"27.0",
    "gn:admin2_code":"1292.0",
    "gn:asciiname":"Vejbyslatt",
    "gn:country_code":"SE",
    "gn:dem":21,
    "gn:feature_class":"P",
    "gn:feature_code":"PPL",
    "gn:name":"Vejbysl\u00e4tt",
    "gn:population":0,
    "gn:timezone":"Europe/Stockholm",
    "iso:country":"SE",
    "wof:name":"Vejbyslatt",
    "wof:placetype":"locality"
},
  "geometry": {"coordinates":[12.81667,56.31667],"type":"Point"}
}