{
  "type": "Feature",
  "properties": {
    "gn:admin1_code":"14.0",
    "gn:admin2_code":"2582.0",
    "gn:asciiname":"Risappi",
    "gn:cc2":"SE",
    "gn:country_code":"SE",
    "gn:dem":249,
    "gn:feature_class":"P",
    "gn:feature_code":"PPL",
    "gn:name":"Risappi",
    "gn:population":0,
    "gn:timezone":"Europe/Stockholm",
    "iso:country":"SE",
    "name:und_x_variant":[
        "Risape",
        "Risappi"
    ],
    "wof:name":"Risappi",
    "wof:placetype":"locality"
},
  "geometry": {"coordinates":[21.56667,66.31667],"type":"Point"}
}