{
  "type": "Feature",
  "properties": {
    "gn:admin1_code":"12.0",
    "gn:admin2_code":"780.0",
    "gn:asciiname":"Horda",
    "gn:country_code":"SE",
    "gn:dem":175,
    "gn:feature_class":"P",
    "gn:feature_code":"PPL",
    "gn:name":"H\u00f6rda",
    "gn:population":0,
    "gn:timezone":"Europe/Stockholm",
    "iso:country":"SE",
    "name:nor_x_preferred":[
        "H\u00f6rda"
    ],
    "name:nor_x_variant":[
        "H\u00f8rda"
    ],
    "name:und_x_variant":[
        "H\u00f6rda"
    ],
    "wof:name":"Horda",
    "wof:placetype":"locality"
},
  "geometry": {"coordinates":[14.71667,57.01667],"type":"Point"}
}