{
  "type": "Feature",
  "properties": {
    "gn:admin1_code":"15.0",
    "gn:admin2_code":"1862.0",
    "gn:asciiname":"Backetorp",
    "gn:cc2":"SE",
    "gn:country_code":"SE",
    "gn:dem":95,
    "gn:feature_class":"P",
    "gn:feature_code":"PPL",
    "gn:name":"B\u00e4cketorp",
    "gn:population":0,
    "gn:timezone":"Europe/Stockholm",
    "iso:country":"SE",
    "name:und_x_variant":[
        "B\u00e4cktorp",
        "B\u00e4cketorp"
    ],
    "wof:name":"Backetorp",
    "wof:placetype":"locality"
},
  "geometry": {"coordinates":[14.38333,59.11666999999999],"type":"Point"}
}