{
  "type": "Feature",
  "properties": {
    "gn:admin1_code":"22.0",
    "gn:admin2_code":"1780.0",
    "gn:asciiname":"Jonsbyn",
    "gn:country_code":"SE",
    "gn:dem":135,
    "gn:feature_class":"P",
    "gn:feature_code":"PPL",
    "gn:name":"Jonsbyn",
    "gn:population":0,
    "gn:timezone":"Europe/Stockholm",
    "iso:country":"SE",
    "wof:name":"Jonsbyn",
    "wof:placetype":"locality"
},
  "geometry": {"coordinates":[13.75,59.65],"type":"Point"}
}