{
  "type": "Feature",
  "properties": {
    "gn:admin1_code":"12.0",
    "gn:admin2_code":"767.0",
    "gn:asciiname":"Lidhult",
    "gn:country_code":"SE",
    "gn:dem":177,
    "gn:feature_class":"P",
    "gn:feature_code":"PPL",
    "gn:name":"Lidhult",
    "gn:population":0,
    "gn:timezone":"Europe/Stockholm",
    "iso:country":"SE",
    "name:deu_x_preferred":[
        "Lidhult"
    ],
    "name:ita_x_preferred":[
        "Lidhult"
    ],
    "name:nld_x_preferred":[
        "Lidhult"
    ],
    "name:nno_x_preferred":[
        "Lidhult"
    ],
    "name:nor_x_preferred":[
        "Lidhult"
    ],
    "name:sme_x_preferred":[
        "Lidhult"
    ],
    "name:swe_x_preferred":[
        "Lidhult"
    ],
    "wof:name":"Lidhult",
    "wof:placetype":"locality"
},
  "geometry": {"coordinates":[13.65,56.58333],"type":"Point"}
}