{
  "type": "Feature",
  "properties": {
    "gn:admin1_code":"7.0",
    "gn:admin2_code":"2326.0",
    "gn:asciiname":"Digerberg",
    "gn:cc2":"SE",
    "gn:country_code":"SE",
    "gn:dem":425,
    "gn:feature_class":"P",
    "gn:feature_code":"PPL",
    "gn:name":"Digerberg",
    "gn:population":0,
    "gn:timezone":"Europe/Stockholm",
    "iso:country":"SE",
    "name:und_x_variant":[
        "Digerberget",
        "Digerberg"
    ],
    "wof:name":"Digerberg",
    "wof:placetype":"locality"
},
  "geometry": {"coordinates":[14.66667,62.56667],"type":"Point"}
}