{
  "type": "Feature",
  "properties": {
    "gn:admin1_code":"7.0",
    "gn:admin2_code":"2309.0",
    "gn:asciiname":"Nordvalla",
    "gn:country_code":"SE",
    "gn:dem":307,
    "gn:feature_class":"P",
    "gn:feature_code":"PPL",
    "gn:name":"Nordvalla",
    "gn:population":0,
    "gn:timezone":"Europe/Stockholm",
    "iso:country":"SE",
    "wof:name":"Nordvalla",
    "wof:placetype":"locality"
},
  "geometry": {"coordinates":[14.65,63.73333],"type":"Point"}
}