{
  "type": "Feature",
  "properties": {
    "gn:admin1_code":"10.0",
    "gn:admin2_code":"2026.0",
    "gn:admin3_code":"202602.0",
    "gn:admin4_code":"2350.0",
    "gn:asciiname":"Bodarna",
    "gn:country_code":"SE",
    "gn:dem":139,
    "gn:feature_class":"P",
    "gn:feature_code":"PPL",
    "gn:name":"Bodarna",
    "gn:population":0,
    "gn:timezone":"Europe/Stockholm",
    "iso:country":"SE",
    "wof:name":"Bodarna",
    "wof:placetype":"locality"
},
  "geometry": {"coordinates":[15.1283,60.54188000000001],"type":"Point"}
}