{
  "type": "Feature",
  "properties": {
    "gn:admin1_code":"9.0",
    "gn:admin2_code":"881.0",
    "gn:asciiname":"Norra Savsjo",
    "gn:country_code":"SE",
    "gn:dem":100,
    "gn:feature_class":"P",
    "gn:feature_code":"PPL",
    "gn:name":"Norra S\u00e4vsj\u00f6",
    "gn:population":0,
    "gn:timezone":"Europe/Stockholm",
    "iso:country":"SE",
    "wof:name":"Norra Savsjo",
    "wof:placetype":"locality"
},
  "geometry": {"coordinates":[15.78333,56.73333],"type":"Point"}
}