{
  "type": "Feature",
  "properties": {
    "gn:admin1_code":"28.0",
    "gn:admin2_code":"1480.0",
    "gn:asciiname":"Hagen",
    "gn:country_code":"SE",
    "gn:dem":3,
    "gn:feature_class":"P",
    "gn:feature_code":"PPL",
    "gn:name":"Hagen",
    "gn:population":0,
    "gn:timezone":"Europe/Stockholm",
    "iso:country":"SE",
    "wof:name":"Hagen",
    "wof:placetype":"locality"
},
  "geometry": {"coordinates":[11.94278,57.57528000000001],"type":"Point"}
}