{
  "type": "Feature",
  "properties": {
    "gn:admin1_code":"10.0",
    "gn:admin2_code":"2061.0",
    "gn:asciiname":"Jobsbo",
    "gn:country_code":"SE",
    "gn:dem":124,
    "gn:feature_class":"P",
    "gn:feature_code":"PPL",
    "gn:name":"Jobsbo",
    "gn:population":0,
    "gn:timezone":"Europe/Stockholm",
    "iso:country":"SE",
    "wof:name":"Jobsbo",
    "wof:placetype":"locality"
},
  "geometry": {"coordinates":[15.43333,60.16667],"type":"Point"}
}