{
  "type": "Feature",
  "properties": {
    "gn:admin1_code":"26.0",
    "gn:admin2_code":"188.0",
    "gn:asciiname":"Unungehojden",
    "gn:country_code":"SE",
    "gn:dem":30,
    "gn:feature_class":"P",
    "gn:feature_code":"PPL",
    "gn:name":"Unungeh\u00f6jden",
    "gn:population":0,
    "gn:timezone":"Europe/Stockholm",
    "iso:country":"SE",
    "name:nor_x_preferred":[
        "Unungeh\u00f6jden"
    ],
    "name:nor_x_variant":[
        "Unungeh\u00f8jden"
    ],
    "name:und_x_variant":[
        "Unungeh\u00f6jden"
    ],
    "wof:name":"Unungehojden",
    "wof:placetype":"locality"
},
  "geometry": {"coordinates":[18.58306,59.89972],"type":"Point"}
}