{
  "type": "Feature",
  "properties": {
    "gn:admin1_code":"10.0",
    "gn:admin2_code":"2083.0",
    "gn:asciiname":"Laggarbo",
    "gn:country_code":"SE",
    "gn:dem":151,
    "gn:feature_class":"P",
    "gn:feature_code":"PPL",
    "gn:name":"Laggarbo",
    "gn:population":0,
    "gn:timezone":"Europe/Stockholm",
    "iso:country":"SE",
    "wof:name":"Laggarbo",
    "wof:placetype":"locality"
},
  "geometry": {"coordinates":[15.88333,60.28333000000001],"type":"Point"}
}