{
  "type": "Feature",
  "properties": {
    "gn:gn_country":"SE",
    "gn:gn_fcode":"PPL",
    "gn:gn_pop":670,
    "gn:population":671,
    "iso:country":"SE",
    "name:dut_x_preferred":[
        "M\u00e5nkarbo"
    ],
    "name:eng_x_preferred":[
        "M\u00e5nkarbo"
    ],
    "name:ita_x_preferred":[
        "M\u00e5nkarbo"
    ],
    "name:nan_x_preferred":[
        "M\u00e5nkarbo"
    ],
    "name:nno_x_preferred":[
        "M\u00e5nkarbo"
    ],
    "name:nob_x_preferred":[
        "M\u00e5nkarbo"
    ],
    "name:swe_x_preferred":[
        "M\u00e5nkarbo"
    ],
    "qs_pg:aaroncc":"SE",
    "qs_pg:gn_country":"SE",
    "qs_pg:gn_fcode":"PPL",
    "qs_pg:gn_pop":670,
    "qs_pg:name":"M\u00e5nkarbo",
    "qs_pg:name_adm0":"Sverige",
    "qs_pg:name_adm1":"Uppsala L\u00e4n",
    "qs_pg:photos_9k":1,
    "qs_pg:photos_9r":1,
    "qs_pg:photos_all":1,
    "qs_pg:photos_sr":0,
    "qs_pg:pop_sr":2,
    "qs_pg:qs_pg_placetype":"locality",
    "qs_pg:qs_pg_placetype_gp":"Town",
    "qs_pg:woe_adm0":23424954,
    "woe:adm0_id":23424954,
    "woe:name_adm0":"Sverige",
    "woe:name_adm1":"Uppsala L\u00e4n",
    "woe:placetype":"Town",
    "wof:name":"M\u00e5nkarbo",
    "wof:placetype":"locality",
    "wof:population":671
},
  "geometry": {"coordinates":[17.46667,60.23333],"type":"Point"}
}