{
  "type": "Feature",
  "properties": {
    "gn:admin1_code":"7.0",
    "gn:admin2_code":"2321.0",
    "gn:asciiname":"Getasen",
    "gn:country_code":"SE",
    "gn:dem":341,
    "gn:feature_class":"P",
    "gn:feature_code":"PPL",
    "gn:name":"Get\u00e5sen",
    "gn:population":0,
    "gn:timezone":"Europe/Stockholm",
    "iso:country":"SE",
    "wof:name":"Getasen",
    "wof:placetype":"locality"
},
  "geometry": {"coordinates":[14.26667,63.08333],"type":"Point"}
}