{
  "type": "Feature",
  "properties": {
    "gn:gn_country":"SE",
    "gn:gn_fcode":"PPL",
    "gn:gn_pop":0,
    "iso:country":"SE",
    "name:dan_x_preferred":[
        "R\u00f6ddinge"
    ],
    "name:dut_x_preferred":[
        "R\u00f6ddinge"
    ],
    "name:eng_x_preferred":[
        "R\u00f6ddinge"
    ],
    "name:fre_x_preferred":[
        "R\u00f6ddinge"
    ],
    "name:ger_x_preferred":[
        "R\u00f6ddinge"
    ],
    "name:nds_x_preferred":[
        "R\u00f6ddinge"
    ],
    "name:nno_x_preferred":[
        "R\u00f6ddinge"
    ],
    "name:nob_x_preferred":[
        "R\u00f6ddinge"
    ],
    "name:nor_x_preferred":[
        "R\u00f8ddinge"
    ],
    "name:nor_x_variant":[
        "R\u00f6ddinge"
    ],
    "name:swe_x_preferred":[
        "R\u00f6ddinge"
    ],
    "qs_pg:aaroncc":"SE",
    "qs_pg:gn_country":"SE",
    "qs_pg:gn_fcode":"PPL",
    "qs_pg:gn_pop":0,
    "qs_pg:name":"R\u00f6ddinge",
    "qs_pg:name_adm0":"Sverige",
    "qs_pg:name_adm1":"Sk\u00e5ne L\u00e4n",
    "qs_pg:photos":49,
    "qs_pg:photos_1k":10,
    "qs_pg:photos_9k":1,
    "qs_pg:photos_9r":2,
    "qs_pg:photos_all":49,
    "qs_pg:photos_sr":2,
    "qs_pg:pop_sr":0,
    "qs_pg:qs_pg_placetype":"locality",
    "qs_pg:qs_pg_placetype_gp":"Town",
    "qs_pg:woe_adm0":23424954,
    "woe:adm0_id":23424954,
    "woe:name_adm0":"Sverige",
    "woe:name_adm1":"Sk\u00e5ne L\u00e4n",
    "woe:placetype":"Town",
    "wof:name":"R\u00f6ddinge",
    "wof:placetype":"locality"
},
  "geometry": {"coordinates":[13.83333,55.58333],"type":"Point"}
}