{
  "type": "Feature",
  "properties": {
    "gn:admin1_code":"8.0",
    "gn:admin2_code":"685.0",
    "gn:asciiname":"Rosas",
    "gn:country_code":"SE",
    "gn:dem":230,
    "gn:feature_class":"P",
    "gn:feature_code":"PPL",
    "gn:name":"R\u00f6s\u00e5s",
    "gn:population":0,
    "gn:timezone":"Europe/Stockholm",
    "iso:country":"SE",
    "name:cat_x_preferred":[
        "Rosas"
    ],
    "name:ceb_x_preferred":[
        "Rosas"
    ],
    "name:deu_x_preferred":[
        "Rosas"
    ],
    "name:fin_x_preferred":[
        "Rosas"
    ],
    "name:fra_x_preferred":[
        "Rosas"
    ],
    "name:ita_x_preferred":[
        "Rosas"
    ],
    "name:nld_x_preferred":[
        "Rosas"
    ],
    "name:nor_x_preferred":[
        "R\u00f6s\u00e5s"
    ],
    "name:nor_x_variant":[
        "R\u00f8s\u00e5s"
    ],
    "name:rus_x_preferred":[
        "\u0420\u043e\u0441\u0430\u0441"
    ],
    "name:spa_x_preferred":[
        "Rosas"
    ],
    "name:srp_x_preferred":[
        "\u0420\u043e\u0441\u0430\u0441"
    ],
    "name:swe_x_preferred":[
        "Rosas"
    ],
    "name:tgl_x_preferred":[
        "Rosas"
    ],
    "name:und_x_variant":[
        "R\u00f6s\u00e5s"
    ],
    "name:vie_x_preferred":[
        "Rosas"
    ],
    "wof:name":"Rosas",
    "wof:placetype":"locality"
},
  "geometry": {"coordinates":[14.85,57.41667],"type":"Point"}
}