{
  "type": "Feature",
  "properties": {
    "gn:gn_country":"SE",
    "gn:gn_fcode":"PPL",
    "gn:gn_pop":285,
    "gn:population":285,
    "iso:country":"SE",
    "name:ceb_x_preferred":[
        "Saltvik"
    ],
    "name:deu_x_preferred":[
        "Saltvik"
    ],
    "name:epo_x_preferred":[
        "Saltvik"
    ],
    "name:est_x_preferred":[
        "Saltviki vald"
    ],
    "name:eus_x_preferred":[
        "Saltvik"
    ],
    "name:fao_x_preferred":[
        "Saltvik"
    ],
    "name:fas_x_preferred":[
        "\u0633\u0627\u0644\u062a\u0648\u06cc\u06a9"
    ],
    "name:fin_x_preferred":[
        "Saltvik"
    ],
    "name:fra_x_preferred":[
        "Saltvik"
    ],
    "name:glg_x_preferred":[
        "Saltvik"
    ],
    "name:ind_x_preferred":[
        "Saltvik"
    ],
    "name:ita_x_preferred":[
        "Saltvik"
    ],
    "name:msa_x_preferred":[
        "Saltvik"
    ],
    "name:nld_x_preferred":[
        "Saltvik"
    ],
    "name:nor_x_preferred":[
        "Saltvik"
    ],
    "name:pol_x_preferred":[
        "Saltvik"
    ],
    "name:ron_x_preferred":[
        "Saltvik"
    ],
    "name:rus_x_preferred":[
        "\u0421\u0430\u043b\u044c\u0442\u0432\u0438\u043a"
    ],
    "name:sco_x_preferred":[
        "Saltvik"
    ],
    "name:sqi_x_preferred":[
        "Saltvik"
    ],
    "name:swe_x_preferred":[
        "Saltvik"
    ],
    "name:tur_x_preferred":[
        "Saltvik"
    ],
    "name:vie_x_preferred":[
        "Saltvik"
    ],
    "name:zho_x_preferred":[
        "\u85a9\u723e\u7279\u7dad\u514b"
    ],
    "qs_pg:aaroncc":"SE",
    "qs_pg:gn_country":"SE",
    "qs_pg:gn_fcode":"PPL",
    "qs_pg:gn_pop":285,
    "qs_pg:name":"Saltvik",
    "qs_pg:photos_9r":0,
    "qs_pg:photos_sr":0,
    "qs_pg:pop_sr":2,
    "qs_pg:qs_pg_placetype":"locality",
    "wof:name":"Saltvik",
    "wof:placetype":"locality",
    "wof:population":285
},
  "geometry": {"coordinates":[17.86667,62.66667],"type":"Point"}
}