{
  "type": "Feature",
  "properties": {
    "gn:admin1_code":"7.0",
    "gn:admin2_code":"2361.0",
    "gn:asciiname":"Djursvallen",
    "gn:country_code":"SE",
    "gn:dem":631,
    "gn:feature_class":"P",
    "gn:feature_code":"PPL",
    "gn:name":"Djursvallen",
    "gn:population":0,
    "gn:timezone":"Europe/Stockholm",
    "iso:country":"SE",
    "wof:name":"Djursvallen",
    "wof:placetype":"locality"
},
  "geometry": {"coordinates":[13.51667,62.01667],"type":"Point"}
}