{
  "type": "Feature",
  "properties": {
    "gn:admin1_code":"5.0",
    "gn:admin2_code":"980.0",
    "gn:asciiname":"Alvare",
    "gn:country_code":"SE",
    "gn:dem":7,
    "gn:feature_class":"P",
    "gn:feature_code":"PPL",
    "gn:name":"Alvare",
    "gn:population":0,
    "gn:timezone":"Europe/Stockholm",
    "iso:country":"SE",
    "name:und_x_variant":[
        "Alfvare",
        "Alvare"
    ],
    "wof:name":"Alvare",
    "wof:placetype":"locality"
},
  "geometry": {"coordinates":[18.59552,57.25216999999999],"type":"Point"}
}