{
  "type": "Feature",
  "properties": {
    "gn:admin1_code":"28.0",
    "gn:admin2_code":"1466.0",
    "gn:asciiname":"Sotestorp",
    "gn:country_code":"SE",
    "gn:dem":189,
    "gn:feature_class":"P",
    "gn:feature_code":"PPL",
    "gn:name":"S\u00f6testorp",
    "gn:population":0,
    "gn:timezone":"Europe/Stockholm",
    "iso:country":"SE",
    "name:nor_x_preferred":[
        "S\u00f6testorp"
    ],
    "name:nor_x_variant":[
        "S\u00f8testorp"
    ],
    "name:und_x_variant":[
        "S\u00f6testorp"
    ],
    "wof:name":"Sotestorp",
    "wof:placetype":"locality"
},
  "geometry": {"coordinates":[13.16667,58.03333000000001],"type":"Point"}
}