{
  "type": "Feature",
  "properties": {
    "gn:admin1_code":"24.0",
    "gn:admin2_code":"2262.0",
    "gn:admin3_code":"226204.0",
    "gn:admin4_code":"2506.0",
    "gn:asciiname":"Smedsbole",
    "gn:country_code":"SE",
    "gn:dem":88,
    "gn:feature_class":"P",
    "gn:feature_code":"PPL",
    "gn:name":"Smedsb\u00f6le",
    "gn:population":0,
    "gn:timezone":"Europe/Stockholm",
    "iso:country":"SE",
    "name:nor_x_preferred":[
        "Smedsb\u00f6le"
    ],
    "name:nor_x_variant":[
        "Smedsb\u00f8le"
    ],
    "wof:name":"Smedsbole",
    "wof:placetype":"locality"
},
  "geometry": {"coordinates":[17.5686,62.47524],"type":"Point"}
}