{
  "type": "Feature",
  "properties": {
    "gn:gn_country":"SE",
    "gn:gn_fcode":"PPL",
    "gn:gn_pop":339,
    "gn:population":339,
    "iso:country":"SE",
    "name:ceb_x_preferred":[
        "Bratt\u00e5s"
    ],
    "name:fra_x_preferred":[
        "Bratt\u00e5s"
    ],
    "name:ita_x_preferred":[
        "Bratt\u00e5s"
    ],
    "name:nld_x_preferred":[
        "Bratt\u00e5s"
    ],
    "name:nor_x_preferred":[
        "Bratt\u00e5s"
    ],
    "qs_pg:aaroncc":"SE",
    "qs_pg:gn_country":"SE",
    "qs_pg:gn_fcode":"PPL",
    "qs_pg:gn_pop":339,
    "qs_pg:name":"Bratt\u00e5s",
    "qs_pg:photos_9r":0,
    "qs_pg:photos_sr":0,
    "qs_pg:pop_sr":2,
    "qs_pg:qs_pg_placetype":"locality",
    "wof:name":"Bratt\u00e5s",
    "wof:placetype":"locality",
    "wof:population":339
},
  "geometry": {"coordinates":[21.51667,64.45],"type":"Point"}
}