{
  "type": "Feature",
  "properties": {
    "gn:admin1_code":"7.0",
    "gn:admin2_code":"2313.0",
    "gn:asciiname":"Nedre Lillviken",
    "gn:country_code":"SE",
    "gn:dem":290,
    "gn:feature_class":"P",
    "gn:feature_code":"PPL",
    "gn:name":"Nedre Lillviken",
    "gn:population":0,
    "gn:timezone":"Europe/Stockholm",
    "iso:country":"SE",
    "wof:name":"Nedre Lillviken",
    "wof:placetype":"locality"
},
  "geometry": {"coordinates":[15.48333,64.23333000000001],"type":"Point"}
}