{
  "type": "Feature",
  "properties": {
    "gn:admin1_code":"16.0",
    "gn:admin2_code":"562.0",
    "gn:asciiname":"Rad",
    "gn:country_code":"SE",
    "gn:dem":74,
    "gn:feature_class":"P",
    "gn:feature_code":"PPL",
    "gn:name":"R\u00e5d",
    "gn:population":0,
    "gn:timezone":"Europe/Stockholm",
    "iso:country":"SE",
    "wof:name":"Rad",
    "wof:placetype":"locality"
},
  "geometry": {"coordinates":[15.75,58.91667],"type":"Point"}
}