{
  "type": "Feature",
  "properties": {
    "gn:admin1_code":"25.0",
    "gn:admin2_code":"1981.0",
    "gn:asciiname":"Hagaberg",
    "gn:country_code":"SE",
    "gn:dem":67,
    "gn:feature_class":"P",
    "gn:feature_code":"PPL",
    "gn:name":"Hagaberg",
    "gn:population":0,
    "gn:timezone":"Europe/Stockholm",
    "iso:country":"SE",
    "wof:name":"Hagaberg",
    "wof:placetype":"locality"
},
  "geometry": {"coordinates":[16.33333,59.93333000000001],"type":"Point"}
}