{
  "type": "Feature",
  "properties": {
    "gn:admin1_code":"8.0",
    "gn:admin2_code":"687.0",
    "gn:asciiname":"Finnanas",
    "gn:country_code":"SE",
    "gn:dem":178,
    "gn:feature_class":"P",
    "gn:feature_code":"PPL",
    "gn:name":"Finnan\u00e4s",
    "gn:population":0,
    "gn:timezone":"Europe/Stockholm",
    "iso:country":"SE",
    "wof:name":"Finnanas",
    "wof:placetype":"locality"
},
  "geometry": {"coordinates":[14.83333,57.98333],"type":"Point"}
}