{
  "type": "Feature",
  "properties": {
    "iso:country":"SE",
    "name:dan_x_preferred":[
        "J\u00e4ravallen"
    ],
    "name:deu_x_preferred":[
        "J\u00e4ravallen"
    ],
    "name:eng_x_preferred":[
        "J\u00e4ravallen"
    ],
    "name:fra_x_preferred":[
        "J\u00e4ravallen"
    ],
    "name:nds_x_preferred":[
        "J\u00e4ravallen"
    ],
    "name:nld_x_preferred":[
        "J\u00e4ravallen"
    ],
    "name:nno_x_preferred":[
        "J\u00e4ravallen"
    ],
    "name:nob_x_preferred":[
        "J\u00e4ravallen"
    ],
    "name:swe_x_preferred":[
        "J\u00e4ravallen"
    ],
    "qs_pg:aaroncc":"SE",
    "qs_pg:name":"J\u00e4ravallen",
    "qs_pg:name_adm0":"Sverige",
    "qs_pg:name_adm1":"Sk\u00e5ne L\u00e4n",
    "qs_pg:photos":328,
    "qs_pg:photos_1k":66,
    "qs_pg:photos_9k":1,
    "qs_pg:photos_9r":5,
    "qs_pg:photos_all":328,
    "qs_pg:photos_sr":5,
    "qs_pg:pop_sr":0,
    "qs_pg:qs_pg_placetype":"locality",
    "qs_pg:qs_pg_placetype_gp":"Town",
    "qs_pg:woe_adm0":23424954,
    "woe:adm0_id":23424954,
    "woe:name_adm0":"Sverige",
    "woe:name_adm1":"Sk\u00e5ne L\u00e4n",
    "woe:placetype":"Town",
    "wof:name":"J\u00e4ravallen",
    "wof:placetype":"locality"
},
  "geometry": {"coordinates":[12.94979,55.791052],"type":"Point"}
}