{
  "type": "Feature",
  "properties": {
    "gn:admin1_code":"28.0",
    "gn:admin2_code":"1497.0",
    "gn:asciiname":"Svedbrata",
    "gn:cc2":"SE",
    "gn:country_code":"SE",
    "gn:dem":120,
    "gn:feature_class":"P",
    "gn:feature_code":"PPL",
    "gn:name":"Svedbr\u00e5ta",
    "gn:population":0,
    "gn:timezone":"Europe/Stockholm",
    "iso:country":"SE",
    "name:und_x_variant":[
        "Svebr\u00e5ta",
        "Svedbr\u00e5ta"
    ],
    "wof:name":"Svedbrata",
    "wof:placetype":"locality"
},
  "geometry": {"coordinates":[14.13333,58.35],"type":"Point"}
}