{
  "type": "Feature",
  "properties": {
    "gn:admin1_code":"14.0",
    "gn:admin2_code":"2584.0",
    "gn:asciiname":"Laimoluokta",
    "gn:country_code":"SE",
    "gn:dem":347,
    "gn:feature_class":"P",
    "gn:feature_code":"PPL",
    "gn:name":"L\u00e1imoluokta",
    "gn:population":0,
    "gn:timezone":"Europe/Stockholm",
    "iso:country":"SE",
    "name:sme_x_preferred":[
        "L\u00e1imoluokta"
    ],
    "name:und_x_variant":[
        "Kattuvuoma",
        "Kattavuoma",
        "Kattovuoma",
        "Lajmoviken"
    ],
    "wof:name":"Laimoluokta",
    "wof:placetype":"locality"
},
  "geometry": {"coordinates":[19.81984,68.3212],"type":"Point"}
}