{
  "type": "Feature",
  "properties": {
    "gn:admin1_code":"22.0",
    "gn:admin2_code":"1730.0",
    "gn:asciiname":"Lunden",
    "gn:country_code":"SE",
    "gn:dem":158,
    "gn:feature_class":"P",
    "gn:feature_code":"PPL",
    "gn:name":"Lunden",
    "gn:population":0,
    "gn:timezone":"Europe/Stockholm",
    "iso:country":"SE",
    "name:ceb_x_preferred":[
        "Lunden"
    ],
    "name:dan_x_preferred":[
        "Lunden"
    ],
    "name:deu_x_preferred":[
        "Lunden"
    ],
    "name:epo_x_preferred":[
        "Lunden"
    ],
    "name:eus_x_preferred":[
        "Lunden"
    ],
    "name:fas_x_preferred":[
        "\u0644\u0648\u0646\u062f\u0646"
    ],
    "name:fra_x_preferred":[
        "Lunden"
    ],
    "name:hun_x_preferred":[
        "Lunden"
    ],
    "name:ind_x_preferred":[
        "Lunden"
    ],
    "name:ita_x_preferred":[
        "Lunden"
    ],
    "name:mkd_x_preferred":[
        "\u041b\u0443\u043d\u0434\u0435\u043d"
    ],
    "name:msa_x_preferred":[
        "Lunden"
    ],
    "name:nld_x_preferred":[
        "Lunden"
    ],
    "name:nor_x_preferred":[
        "Lunden"
    ],
    "name:pol_x_preferred":[
        "Lunden"
    ],
    "name:por_x_preferred":[
        "Lunden"
    ],
    "name:ron_x_preferred":[
        "Lunden"
    ],
    "name:rus_x_preferred":[
        "\u041b\u0443\u043d\u0434\u0435\u043d"
    ],
    "name:srp_x_preferred":[
        "\u041b\u0443\u043d\u0434\u0435\u043d"
    ],
    "name:tur_x_preferred":[
        "Lunden"
    ],
    "name:ukr_x_preferred":[
        "\u041b\u0443\u043d\u0434\u0435\u043d"
    ],
    "name:uzb_x_preferred":[
        "Lunden"
    ],
    "name:vie_x_preferred":[
        "Lunden"
    ],
    "name:vol_x_preferred":[
        "Lunden"
    ],
    "name:war_x_preferred":[
        "Lunden"
    ],
    "wof:name":"Lunden",
    "wof:placetype":"locality"
},
  "geometry": {"coordinates":[12.15,59.76667],"type":"Point"}
}