{
  "type": "Feature",
  "properties": {
    "gn:admin1_code":"21.0",
    "gn:admin2_code":"360.0",
    "gn:asciiname":"Norrby",
    "gn:country_code":"SE",
    "gn:dem":24,
    "gn:feature_class":"P",
    "gn:feature_code":"PPL",
    "gn:name":"Norrby",
    "gn:population":0,
    "gn:timezone":"Europe/Stockholm",
    "iso:country":"SE",
    "name:swe_x_preferred":[
        "Norrby"
    ],
    "wof:name":"Norrby",
    "wof:placetype":"locality"
},
  "geometry": {"coordinates":[17.56667,60.38333000000001],"type":"Point"}
}