{
  "type": "Feature",
  "properties": {
    "gn:admin1_code":"26.0",
    "gn:admin2_code":"117.0",
    "gn:asciiname":"Skeppsbol",
    "gn:country_code":"SE",
    "gn:dem":60,
    "gn:feature_class":"P",
    "gn:feature_code":"PPL",
    "gn:name":"Skeppsbol",
    "gn:population":0,
    "gn:timezone":"Europe/Stockholm",
    "iso:country":"SE",
    "wof:name":"Skeppsbol",
    "wof:placetype":"locality"
},
  "geometry": {"coordinates":[18.36667000000001,59.51667],"type":"Point"}
}