{
  "type": "Feature",
  "properties": {
    "gn:admin1_code":"27.0",
    "gn:admin2_code":"1280.0",
    "gn:asciiname":"Husie",
    "gn:country_code":"SE",
    "gn:dem":32,
    "gn:feature_class":"P",
    "gn:feature_code":"PPL",
    "gn:name":"Husie",
    "gn:population":0,
    "gn:timezone":"Europe/Stockholm",
    "iso:country":"SE",
    "wof:name":"Husie",
    "wof:placetype":"locality"
},
  "geometry": {"coordinates":[13.08333,55.56667],"type":"Point"}
}