{
  "type": "Feature",
  "properties": {
    "gn:admin1_code":"6.0",
    "gn:asciiname":"Troenningenaes",
    "gn:country_code":"SE",
    "gn:dem":6,
    "gn:feature_class":"P",
    "gn:feature_code":"PPL",
    "gn:name":"Tr\u00f6nningen\u00e4s",
    "gn:population":743,
    "gn:timezone":"Europe/Stockholm",
    "iso:country":"SE",
    "wof:name":"Troenningenaes",
    "wof:placetype":"locality",
    "wof:population":743
},
  "geometry": {"coordinates":[12.22596,57.13846],"type":"Point"}
}