{
  "type": "Feature",
  "properties": {
    "gn:admin1_code":"7.0",
    "gn:admin2_code":"2326.0",
    "gn:asciiname":"Tangen",
    "gn:country_code":"SE",
    "gn:dem":384,
    "gn:feature_class":"P",
    "gn:feature_code":"PPL",
    "gn:name":"T\u00e5ngen",
    "gn:population":0,
    "gn:timezone":"Europe/Stockholm",
    "iso:country":"SE",
    "name:ceb_x_preferred":[
        "Tangen"
    ],
    "name:jav_x_preferred":[
        "Tangen"
    ],
    "name:nld_x_preferred":[
        "Tangen"
    ],
    "name:nor_x_preferred":[
        "Tangen"
    ],
    "name:ron_x_preferred":[
        "Tangen"
    ],
    "wof:name":"Tangen",
    "wof:placetype":"locality"
},
  "geometry": {"coordinates":[14.76667,62.68333000000001],"type":"Point"}
}