{
  "type": "Feature",
  "properties": {
    "gn:gn_country":"SE",
    "gn:gn_fcode":"PPL",
    "gn:gn_pop":620,
    "gn:population":671,
    "iso:country":"SE",
    "name:bul_x_preferred":[
        "\u042e\u0442\u0442\u043e\u0440\u043f"
    ],
    "name:ceb_x_preferred":[
        "Gyttorp"
    ],
    "name:deu_x_preferred":[
        "Gyttorp"
    ],
    "name:eng_x_preferred":[
        "Gyttorp"
    ],
    "name:ita_x_preferred":[
        "Gyttorp"
    ],
    "name:nan_x_preferred":[
        "Gyttorp"
    ],
    "name:nld_x_preferred":[
        "Gyttorp"
    ],
    "name:nno_x_preferred":[
        "Gyttorp"
    ],
    "name:nob_x_preferred":[
        "Gyttorp"
    ],
    "name:swe_x_preferred":[
        "Gyttorp"
    ],
    "qs_pg:aaroncc":"SE",
    "qs_pg:gn_country":"SE",
    "qs_pg:gn_fcode":"PPL",
    "qs_pg:gn_pop":620,
    "qs_pg:name":"Gyttorp",
    "qs_pg:name_adm0":"Sverige",
    "qs_pg:name_adm1":"\u00d6rebro L\u00e4n",
    "qs_pg:photos":205,
    "qs_pg:photos_1k":42,
    "qs_pg:photos_9k":1,
    "qs_pg:photos_9r":4,
    "qs_pg:photos_all":205,
    "qs_pg:photos_sr":4,
    "qs_pg:pop_sr":2,
    "qs_pg:qs_pg_placetype":"locality",
    "qs_pg:qs_pg_placetype_gp":"Town",
    "qs_pg:woe_adm0":23424954,
    "woe:adm0_id":23424954,
    "woe:name_adm0":"Sverige",
    "woe:name_adm1":"\u00d6rebro L\u00e4n",
    "woe:placetype":"Town",
    "wof:name":"Gyttorp",
    "wof:placetype":"locality",
    "wof:population":671
},
  "geometry": {"coordinates":[14.96667,59.51667],"type":"Point"}
}