{
  "type": "Feature",
  "properties": {
    "gn:gn_country":"SE",
    "gn:gn_fcode":"PPL",
    "gn:gn_pop":0,
    "iso:country":"SE",
    "name:dan_x_preferred":[
        "H\u00e4vla"
    ],
    "name:deu_x_preferred":[
        "H\u00e4vla"
    ],
    "name:eng_x_preferred":[
        "H\u00e4vla"
    ],
    "name:fra_x_preferred":[
        "H\u00e4vla"
    ],
    "name:ita_x_preferred":[
        "H\u00e4vla"
    ],
    "name:nds_x_preferred":[
        "H\u00e4vla"
    ],
    "name:nld_x_preferred":[
        "H\u00e4vla"
    ],
    "name:nno_x_preferred":[
        "H\u00e4vla"
    ],
    "name:nob_x_preferred":[
        "H\u00e4vla"
    ],
    "name:swe_x_preferred":[
        "H\u00e4vla"
    ],
    "name:unk_x_variant":[
        "H\u00e4vla Bruk"
    ],
    "qs_pg:aaroncc":"SE",
    "qs_pg:gn_country":"SE",
    "qs_pg:gn_fcode":"PPL",
    "qs_pg:gn_pop":0,
    "qs_pg:name":"H\u00e4vla",
    "qs_pg:name_adm0":"Sverige",
    "qs_pg:name_adm1":"\u00d6sterg\u00f6tlands L\u00e4n",
    "qs_pg:photos":89,
    "qs_pg:photos_1k":18,
    "qs_pg:photos_9k":1,
    "qs_pg:photos_9r":3,
    "qs_pg:photos_all":89,
    "qs_pg:photos_sr":3,
    "qs_pg:pop_sr":0,
    "qs_pg:qs_pg_placetype":"locality",
    "qs_pg:qs_pg_placetype_gp":"Town",
    "qs_pg:woe_adm0":23424954,
    "woe:adm0_id":23424954,
    "woe:name_adm0":"Sverige",
    "woe:name_adm1":"\u00d6sterg\u00f6tlands L\u00e4n",
    "woe:placetype":"Town",
    "wof:name":"H\u00e4vla",
    "wof:placetype":"locality"
},
  "geometry": {"coordinates":[15.86667,58.91667],"type":"Point"}
}