{
  "type": "Feature",
  "properties": {
    "gn:admin1_code":"22.0",
    "gn:admin2_code":"1784.0",
    "gn:asciiname":"Toresbol",
    "gn:country_code":"SE",
    "gn:dem":58,
    "gn:feature_class":"P",
    "gn:feature_code":"PPL",
    "gn:name":"T\u00f6resbol",
    "gn:population":0,
    "gn:timezone":"Europe/Stockholm",
    "iso:country":"SE",
    "name:nor_x_preferred":[
        "T\u00f6resbol"
    ],
    "name:nor_x_variant":[
        "T\u00f8resbol"
    ],
    "wof:name":"Toresbol",
    "wof:placetype":"locality"
},
  "geometry": {"coordinates":[12.55,59.56667],"type":"Point"}
}