{
  "type": "Feature",
  "properties": {
    "gn:admin1_code":"9.0",
    "gn:admin2_code":"884.0",
    "gn:asciiname":"Kalleberg",
    "gn:country_code":"SE",
    "gn:dem":205,
    "gn:feature_class":"P",
    "gn:feature_code":"PPL",
    "gn:name":"K\u00e4lleberg",
    "gn:population":0,
    "gn:timezone":"Europe/Stockholm",
    "iso:country":"SE",
    "wof:name":"Kalleberg",
    "wof:placetype":"locality"
},
  "geometry": {"coordinates":[15.55,57.66667],"type":"Point"}
}