{
  "type": "Feature",
  "properties": {
    "gn:admin1_code":"28.0",
    "gn:admin2_code":"1487.0",
    "gn:asciiname":"Norra Timmervik",
    "gn:cc2":"SE",
    "gn:country_code":"SE",
    "gn:dem":75,
    "gn:feature_class":"P",
    "gn:feature_code":"PPL",
    "gn:name":"Norra Timmervik",
    "gn:population":0,
    "gn:timezone":"Europe/Stockholm",
    "iso:country":"SE",
    "name:und_x_variant":[
        "Timmervik",
        "Norra Timmervik"
    ],
    "wof:name":"Norra Timmervik",
    "wof:placetype":"locality"
},
  "geometry": {"coordinates":[12.38333,58.48333],"type":"Point"}
}