{
  "type": "Feature",
  "properties": {
    "gn:admin1_code":"8.0",
    "gn:admin2_code":"662.0",
    "gn:asciiname":"Alabo",
    "gn:cc2":"SE",
    "gn:country_code":"SE",
    "gn:dem":173,
    "gn:feature_class":"P",
    "gn:feature_code":"PPL",
    "gn:name":"Alabo",
    "gn:population":0,
    "gn:timezone":"Europe/Stockholm",
    "iso:country":"SE",
    "name:und_x_variant":[
        "Alaby",
        "Alabo"
    ],
    "wof:name":"Alabo",
    "wof:placetype":"locality"
},
  "geometry": {"coordinates":[13.68333,57.51667],"type":"Point"}
}