{
  "type": "Feature",
  "properties": {
    "gn:admin1_code":"22.0",
    "gn:admin2_code":"1784.0",
    "gn:asciiname":"Kronan",
    "gn:country_code":"SE",
    "gn:dem":111,
    "gn:feature_class":"P",
    "gn:feature_code":"PPL",
    "gn:name":"Kronan",
    "gn:population":0,
    "gn:timezone":"Europe/Stockholm",
    "iso:country":"SE",
    "name:ceb_x_preferred":[
        "Kronan"
    ],
    "name:deu_x_preferred":[
        "Kronan"
    ],
    "name:nld_x_preferred":[
        "Kronan"
    ],
    "name:spa_x_preferred":[
        "Kronan"
    ],
    "name:swe_x_preferred":[
        "Kronan"
    ],
    "wof:name":"Kronan",
    "wof:placetype":"locality"
},
  "geometry": {"coordinates":[12.78333,59.68333000000001],"type":"Point"}
}