{
  "type": "Feature",
  "properties": {
    "gn:admin1_code":"24.0",
    "gn:admin2_code":"2262.0",
    "gn:asciiname":"Ostrand",
    "gn:country_code":"SE",
    "gn:dem":31,
    "gn:feature_class":"P",
    "gn:feature_code":"PPL",
    "gn:name":"\u00d6strand",
    "gn:population":0,
    "gn:timezone":"Europe/Stockholm",
    "iso:country":"SE",
    "name:nor_x_preferred":[
        "\u00d6strand"
    ],
    "name:nor_x_variant":[
        "\u00d8strand"
    ],
    "name:und_x_variant":[
        "\u00d6strand"
    ],
    "wof:name":"Ostrand",
    "wof:placetype":"locality"
},
  "geometry": {"coordinates":[17.32389,62.47889],"type":"Point"}
}