{
  "type": "Feature",
  "properties": {
    "gn:admin1_code":"22.0",
    "gn:admin2_code":"1760.0",
    "gn:asciiname":"Sundstorp",
    "gn:country_code":"SE",
    "gn:dem":130,
    "gn:feature_class":"P",
    "gn:feature_code":"PPL",
    "gn:name":"Sundstorp",
    "gn:population":0,
    "gn:timezone":"Europe/Stockholm",
    "iso:country":"SE",
    "wof:name":"Sundstorp",
    "wof:placetype":"locality"
},
  "geometry": {"coordinates":[14.28333,59.38333000000001],"type":"Point"}
}