{
  "type": "Feature",
  "properties": {
    "gn:admin1_code":"23.0",
    "gn:admin2_code":"2482.0",
    "gn:asciiname":"Smabacka",
    "gn:country_code":"SE",
    "gn:dem":101,
    "gn:feature_class":"P",
    "gn:feature_code":"PPL",
    "gn:name":"Sm\u00e5backa",
    "gn:population":0,
    "gn:timezone":"Europe/Stockholm",
    "iso:country":"SE",
    "wof:name":"Smabacka",
    "wof:placetype":"locality"
},
  "geometry": {"coordinates":[20.81667,64.45],"type":"Point"}
}