{
  "type": "Feature",
  "properties": {
    "gn:admin1_code":"9.0",
    "gn:admin2_code":"862.0",
    "gn:asciiname":"Grimmagarde",
    "gn:country_code":"SE",
    "gn:dem":149,
    "gn:feature_class":"P",
    "gn:feature_code":"PPL",
    "gn:name":"Grimmag\u00e4rde",
    "gn:population":0,
    "gn:timezone":"Europe/Stockholm",
    "iso:country":"SE",
    "wof:name":"Grimmagarde",
    "wof:placetype":"locality"
},
  "geometry": {"coordinates":[15.58333,56.66667],"type":"Point"}
}