{
  "type": "Feature",
  "properties": {
    "gn:admin1_code":"14.0",
    "gn:admin2_code":"2521.0",
    "gn:asciiname":"Hangasjarvi",
    "gn:country_code":"SE",
    "gn:dem":147,
    "gn:feature_class":"P",
    "gn:feature_code":"PPL",
    "gn:name":"Hangasj\u00e4rvi",
    "gn:population":0,
    "gn:timezone":"Europe/Stockholm",
    "iso:country":"SE",
    "wof:name":"Hangasjarvi",
    "wof:placetype":"locality"
},
  "geometry": {"coordinates":[23.11667000000001,66.68333],"type":"Point"}
}