{
  "type": "Feature",
  "properties": {
    "gn:admin1_code":"3.0",
    "gn:admin2_code":"2182.0",
    "gn:asciiname":"Nygarden",
    "gn:country_code":"SE",
    "gn:dem":93,
    "gn:feature_class":"P",
    "gn:feature_code":"PPL",
    "gn:name":"Nyg\u00e5rden",
    "gn:population":0,
    "gn:timezone":"Europe/Stockholm",
    "iso:country":"SE",
    "wof:name":"Nygarden",
    "wof:placetype":"locality"
},
  "geometry": {"coordinates":[16.86667000000001,61.16667],"type":"Point"}
}