{
  "type": "Feature",
  "properties": {
    "gn:admin1_code":"21.0",
    "gn:admin2_code":"380.0",
    "gn:asciiname":"Almtuna",
    "gn:country_code":"SE",
    "gn:dem":17,
    "gn:feature_class":"P",
    "gn:feature_code":"PPL",
    "gn:name":"Almtuna",
    "gn:population":0,
    "gn:timezone":"Europe/Stockholm",
    "iso:country":"SE",
    "wof:name":"Almtuna",
    "wof:placetype":"locality"
},
  "geometry": {"coordinates":[17.66464,59.86591],"type":"Point"}
}