{
  "type": "Feature",
  "properties": {
    "gn:admin1_code":"23.0",
    "gn:admin2_code":"2482.0",
    "gn:asciiname":"Rortrask",
    "gn:country_code":"SE",
    "gn:dem":284,
    "gn:feature_class":"P",
    "gn:feature_code":"PPL",
    "gn:name":"R\u00f6rtr\u00e4sk",
    "gn:population":0,
    "gn:timezone":"Europe/Stockholm",
    "iso:country":"SE",
    "wof:name":"Rortrask",
    "wof:placetype":"locality"
},
  "geometry": {"coordinates":[20.58333,65.05],"type":"Point"}
}