{
  "type": "Feature",
  "properties": {
    "gn:admin1_code":"28.0",
    "gn:admin2_code":"1496.0",
    "gn:asciiname":"Horn",
    "gn:country_code":"SE",
    "gn:dem":68,
    "gn:feature_class":"P",
    "gn:feature_code":"PPL",
    "gn:name":"Horn",
    "gn:population":0,
    "gn:timezone":"Europe/Stockholm",
    "iso:country":"SE",
    "name:bos_x_preferred":[
        "Horn"
    ],
    "name:bre_x_preferred":[
        "Horn"
    ],
    "name:bul_x_preferred":[
        "\u0425\u043e\u0440\u043d"
    ],
    "name:ceb_x_preferred":[
        "Horn"
    ],
    "name:ces_x_preferred":[
        "Horn"
    ],
    "name:dan_x_preferred":[
        "Horn"
    ],
    "name:deu_x_preferred":[
        "Horn"
    ],
    "name:ell_x_preferred":[
        "\u03a7\u03bf\u03c1\u03bd"
    ],
    "name:epo_x_preferred":[
        "Horn"
    ],
    "name:eus_x_preferred":[
        "Horn"
    ],
    "name:fas_x_preferred":[
        "\u0634\u0627\u062e"
    ],
    "name:fin_x_preferred":[
        "Horn"
    ],
    "name:fra_x_preferred":[
        "Horn"
    ],
    "name:heb_x_preferred":[
        "\u05d4\u05d5\u05e8\u05df"
    ],
    "name:isl_x_preferred":[
        "Horn"
    ],
    "name:ita_x_preferred":[
        "Horn"
    ],
    "name:jpn_x_preferred":[
        "\u30db\u30fc\u30f3"
    ],
    "name:lit_x_preferred":[
        "Hornas"
    ],
    "name:nld_x_preferred":[
        "Horn"
    ],
    "name:nor_x_preferred":[
        "Horn"
    ],
    "name:pol_x_preferred":[
        "Horn"
    ],
    "name:por_x_preferred":[
        "Horn"
    ],
    "name:rus_x_preferred":[
        "\u0425\u043e\u0440\u043d"
    ],
    "name:sco_x_preferred":[
        "Horn"
    ],
    "name:slk_x_preferred":[
        "Horn"
    ],
    "name:swe_x_preferred":[
        "Horn"
    ],
    "name:vol_x_preferred":[
        "Horn"
    ],
    "wof:name":"Horn",
    "wof:placetype":"locality"
},
  "geometry": {"coordinates":[13.88333,58.51667],"type":"Point"}
}