{
  "type": "Feature",
  "properties": {
    "gn:admin1_code":"12.0",
    "gn:admin2_code":"780.0",
    "gn:asciiname":"Bergsnas",
    "gn:country_code":"SE",
    "gn:dem":163,
    "gn:feature_class":"P",
    "gn:feature_code":"PPL",
    "gn:name":"Bergsn\u00e4s",
    "gn:population":0,
    "gn:timezone":"Europe/Stockholm",
    "iso:country":"SE",
    "wof:name":"Bergsnas",
    "wof:placetype":"locality"
},
  "geometry": {"coordinates":[14.75,56.88333000000001],"type":"Point"}
}