{
  "type": "Feature",
  "properties": {
    "gn:admin1_code":"6.0",
    "gn:admin2_code":"1384.0",
    "gn:asciiname":"Skarby",
    "gn:country_code":"SE",
    "gn:dem":82,
    "gn:feature_class":"P",
    "gn:feature_code":"PPL",
    "gn:name":"Sk\u00e5rby",
    "gn:population":0,
    "gn:timezone":"Europe/Stockholm",
    "iso:country":"SE",
    "wof:name":"Skarby",
    "wof:placetype":"locality"
},
  "geometry": {"coordinates":[12.06667,57.53333000000001],"type":"Point"}
}