{
  "type": "Feature",
  "properties": {
    "gn:admin1_code":"21.0",
    "gn:admin2_code":"381.0",
    "gn:admin3_code":"38119.0",
    "gn:admin4_code":"239.0",
    "gn:asciiname":"Viggeby",
    "gn:country_code":"SE",
    "gn:dem":33,
    "gn:feature_class":"P",
    "gn:feature_code":"PPL",
    "gn:name":"Viggeby",
    "gn:population":0,
    "gn:timezone":"Europe/Stockholm",
    "iso:country":"SE",
    "wof:name":"Viggeby",
    "wof:placetype":"locality"
},
  "geometry": {"coordinates":[17.33587,59.66005],"type":"Point"}
}