{
  "type": "Feature",
  "properties": {
    "gn:admin1_code":"6.0",
    "gn:admin2_code":"1381.0",
    "gn:asciiname":"Putsered",
    "gn:country_code":"SE",
    "gn:dem":115,
    "gn:feature_class":"P",
    "gn:feature_code":"PPL",
    "gn:name":"Putsered",
    "gn:population":0,
    "gn:timezone":"Europe/Stockholm",
    "iso:country":"SE",
    "wof:name":"Putsered",
    "wof:placetype":"locality"
},
  "geometry": {"coordinates":[13.41667,56.48333],"type":"Point"}
}