{
  "type": "Feature",
  "properties": {
    "gn:admin1_code":"26.0",
    "gn:admin2_code":"136.0",
    "gn:asciiname":"Malmen",
    "gn:country_code":"SE",
    "gn:dem":23,
    "gn:feature_class":"P",
    "gn:feature_code":"PPL",
    "gn:name":"Malmen",
    "gn:population":0,
    "gn:timezone":"Europe/Stockholm",
    "iso:country":"SE",
    "wof:name":"Malmen",
    "wof:placetype":"locality"
},
  "geometry": {"coordinates":[18.41667,59.15],"type":"Point"}
}