{
  "type": "Feature",
  "properties": {
    "gn:admin1_code":"6.0",
    "gn:admin2_code":"1315.0",
    "gn:asciiname":"Lindhult",
    "gn:country_code":"SE",
    "gn:dem":164,
    "gn:feature_class":"P",
    "gn:feature_code":"PPL",
    "gn:name":"Lindhult",
    "gn:population":0,
    "gn:timezone":"Europe/Stockholm",
    "iso:country":"SE",
    "wof:name":"Lindhult",
    "wof:placetype":"locality"
},
  "geometry": {"coordinates":[13.25,57.03333000000001],"type":"Point"}
}