{
  "type": "Feature",
  "properties": {
    "gn:admin1_code":"10.0",
    "gn:admin2_code":"2021.0",
    "gn:asciiname":"Bertils",
    "gn:country_code":"SE",
    "gn:dem":475,
    "gn:feature_class":"P",
    "gn:feature_code":"PPL",
    "gn:name":"Bertils",
    "gn:population":0,
    "gn:timezone":"Europe/Stockholm",
    "iso:country":"SE",
    "wof:name":"Bertils",
    "wof:placetype":"locality"
},
  "geometry": {"coordinates":[14.15,60.36666999999999],"type":"Point"}
}