{
  "type": "Feature",
  "properties": {
    "gn:admin1_code":"7.0",
    "gn:admin2_code":"2313.0",
    "gn:asciiname":"Granon",
    "gn:country_code":"SE",
    "gn:dem":249,
    "gn:feature_class":"P",
    "gn:feature_code":"PPL",
    "gn:name":"Gran\u00f6n",
    "gn:population":0,
    "gn:timezone":"Europe/Stockholm",
    "iso:country":"SE",
    "name:ceb_x_preferred":[
        "Granon"
    ],
    "name:ita_x_preferred":[
        "Granon"
    ],
    "name:nor_x_preferred":[
        "Gran\u00f6n"
    ],
    "name:nor_x_variant":[
        "Gran\u00f8n"
    ],
    "name:swe_x_preferred":[
        "Granon"
    ],
    "wof:name":"Granon",
    "wof:placetype":"locality"
},
  "geometry": {"coordinates":[15.56667,64.41667],"type":"Point"}
}