{
  "type": "Feature",
  "properties": {
    "gn:admin1_code":"3.0",
    "gn:admin2_code":"2184.0",
    "gn:asciiname":"Mora",
    "gn:country_code":"SE",
    "gn:dem":80,
    "gn:feature_class":"P",
    "gn:feature_code":"PPL",
    "gn:name":"Mora",
    "gn:population":0,
    "gn:timezone":"Europe/Stockholm",
    "iso:country":"SE",
    "wof:name":"Mora",
    "wof:placetype":"locality"
},
  "geometry": {"coordinates":[16.55,61.81667],"type":"Point"}
}