{
  "type": "Feature",
  "properties": {
    "gn:admin1_code":"18.0",
    "gn:admin2_code":"461.0",
    "gn:asciiname":"Sora",
    "gn:country_code":"SE",
    "gn:dem":28,
    "gn:feature_class":"P",
    "gn:feature_code":"PPL",
    "gn:name":"S\u00f6ra",
    "gn:population":0,
    "gn:timezone":"Europe/Stockholm",
    "iso:country":"SE",
    "name:arg_x_preferred":[
        "Sora"
    ],
    "name:bos_x_preferred":[
        "Sora"
    ],
    "name:cat_x_preferred":[
        "Sora"
    ],
    "name:ceb_x_preferred":[
        "Sora"
    ],
    "name:deu_x_preferred":[
        "Sora"
    ],
    "name:eus_x_preferred":[
        "Sora"
    ],
    "name:fin_x_preferred":[
        "Sora"
    ],
    "name:fra_x_preferred":[
        "Sora"
    ],
    "name:hun_x_preferred":[
        "Sora"
    ],
    "name:ita_x_preferred":[
        "Sora"
    ],
    "name:kor_x_preferred":[
        "\uc18c\ub77c"
    ],
    "name:kur_x_preferred":[
        "Sora"
    ],
    "name:lat_x_preferred":[
        "Sora"
    ],
    "name:nld_x_preferred":[
        "Sora"
    ],
    "name:nor_x_preferred":[
        "S\u00f6ra"
    ],
    "name:nor_x_variant":[
        "S\u00f8ra"
    ],
    "name:por_x_preferred":[
        "Sora"
    ],
    "name:ron_x_preferred":[
        "Sora"
    ],
    "name:rus_x_preferred":[
        "\u0421\u043e\u0440\u0430"
    ],
    "name:slv_x_preferred":[
        "Sora"
    ],
    "name:spa_x_preferred":[
        "Sora"
    ],
    "name:srp_x_preferred":[
        "Sora"
    ],
    "name:swe_x_preferred":[
        "Sora"
    ],
    "name:und_x_variant":[
        "S\u00f6ra"
    ],
    "name:war_x_preferred":[
        "Sora"
    ],
    "name:zho_x_preferred":[
        "Sora"
    ],
    "wof:name":"Sora",
    "wof:placetype":"locality"
},
  "geometry": {"coordinates":[17.25,59.05],"type":"Point"}
}