{
  "type": "Feature",
  "properties": {
    "gn:admin1_code":"27.0",
    "gn:admin2_code":"1293.0",
    "gn:asciiname":"Nosdala",
    "gn:country_code":"SE",
    "gn:dem":100,
    "gn:feature_class":"P",
    "gn:feature_code":"PPL",
    "gn:name":"N\u00f6sdala",
    "gn:population":0,
    "gn:timezone":"Europe/Stockholm",
    "iso:country":"SE",
    "name:nor_x_preferred":[
        "N\u00f6sdala"
    ],
    "name:nor_x_variant":[
        "N\u00f8sdala"
    ],
    "name:und_x_variant":[
        "N\u00f6sdala"
    ],
    "wof:name":"Nosdala",
    "wof:placetype":"locality"
},
  "geometry": {"coordinates":[13.73333,56.08333],"type":"Point"}
}