{
  "type": "Feature",
  "properties": {
    "gn:admin1_code":"14.0",
    "gn:admin2_code":"2521.0",
    "gn:asciiname":"Ruokojarvi",
    "gn:country_code":"SE",
    "gn:dem":210,
    "gn:feature_class":"P",
    "gn:feature_code":"PPL",
    "gn:name":"Ruokoj\u00e4rvi",
    "gn:population":0,
    "gn:timezone":"Europe/Stockholm",
    "iso:country":"SE",
    "wof:name":"Ruokojarvi",
    "wof:placetype":"locality"
},
  "geometry": {"coordinates":[22.25,67.33333],"type":"Point"}
}