{
  "type": "Feature",
  "properties": {
    "gn:admin1_code":"16.0",
    "gn:admin2_code":"583.0",
    "gn:asciiname":"Bjarka",
    "gn:country_code":"SE",
    "gn:dem":91,
    "gn:feature_class":"P",
    "gn:feature_code":"PPL",
    "gn:name":"Bj\u00e4rka",
    "gn:population":0,
    "gn:timezone":"Europe/Stockholm",
    "iso:country":"SE",
    "wof:name":"Bjarka",
    "wof:placetype":"locality"
},
  "geometry": {"coordinates":[15.36667,58.56667],"type":"Point"}
}