{
  "type": "Feature",
  "properties": {
    "gn:admin1_code":"12.0",
    "gn:asciiname":"Applaryd",
    "gn:cc2":"SE",
    "gn:country_code":"SE",
    "gn:dem":169,
    "gn:feature_class":"P",
    "gn:feature_code":"PPL",
    "gn:name":"Applaryd",
    "gn:population":0,
    "gn:timezone":"Europe/Stockholm",
    "iso:country":"SE",
    "name:und_x_variant":[
        "Aplaryd",
        "Applaryd"
    ],
    "wof:name":"Applaryd",
    "wof:placetype":"locality"
},
  "geometry": {"coordinates":[15.78333,56.88333000000001],"type":"Point"}
}