{
  "type": "Feature",
  "properties": {
    "gn:admin1_code":"6.0",
    "gn:admin2_code":"1383.0",
    "gn:asciiname":"Bjurum",
    "gn:country_code":"SE",
    "gn:dem":4,
    "gn:feature_class":"P",
    "gn:feature_code":"PPL",
    "gn:name":"Bjurum",
    "gn:population":0,
    "gn:timezone":"Europe/Stockholm",
    "iso:country":"SE",
    "name:deu_x_preferred":[
        "Stora Bjurum"
    ],
    "name:swe_x_preferred":[
        "Stora Bjurum"
    ],
    "wof:name":"Bjurum",
    "wof:placetype":"locality"
},
  "geometry": {"coordinates":[12.25,57.23333],"type":"Point"}
}