{
  "type": "Feature",
  "properties": {
    "gn:admin1_code":"10.0",
    "gn:admin2_code":"2029.0",
    "gn:asciiname":"Solarvet",
    "gn:cc2":"SE",
    "gn:country_code":"SE",
    "gn:dem":310,
    "gn:feature_class":"P",
    "gn:feature_code":"PPL",
    "gn:name":"Solarvet",
    "gn:population":0,
    "gn:timezone":"Europe/Stockholm",
    "iso:country":"SE",
    "name:und_x_variant":[
        "Solarfvet",
        "Solarvet"
    ],
    "wof:name":"Solarvet",
    "wof:placetype":"locality"
},
  "geometry": {"coordinates":[15.31667,60.68333000000001],"type":"Point"}
}