{
  "type": "Feature",
  "properties": {
    "iso:country":"SE",
    "wof:name":"St Svindal",
    "wof:placetype":"neighbourhood"
},
  "geometry": {"coordinates":[11.95281989046634,57.5886251587273],"type":"Point"}
}