{
  "type": "Feature",
  "properties": {
    "gn:admin1_code":"24.0",
    "gn:admin2_code":"2282.0",
    "gn:admin3_code":"228202.0",
    "gn:admin4_code":"2482.0",
    "gn:asciiname":"Langanget",
    "gn:country_code":"SE",
    "gn:dem":23,
    "gn:feature_class":"P",
    "gn:feature_code":"PPL",
    "gn:name":"L\u00e5ng\u00e4nget",
    "gn:population":0,
    "gn:timezone":"Europe/Stockholm",
    "iso:country":"SE",
    "wof:name":"Langanget",
    "wof:placetype":"locality"
},
  "geometry": {"coordinates":[18.08333,62.85],"type":"Point"}
}