{
  "type": "Feature",
  "properties": {
    "gn:admin1_code":"22.0",
    "gn:admin2_code":"1764.0",
    "gn:asciiname":"Sandaker",
    "gn:country_code":"SE",
    "gn:dem":96,
    "gn:feature_class":"P",
    "gn:feature_code":"PPL",
    "gn:name":"Sand\u00e5ker",
    "gn:population":0,
    "gn:timezone":"Europe/Stockholm",
    "iso:country":"SE",
    "wof:name":"Sandaker",
    "wof:placetype":"locality"
},
  "geometry": {"coordinates":[13.03333,59.36666999999999],"type":"Point"}
}