{
  "type": "Feature",
  "properties": {
    "gn:admin1_code":"24.0",
    "gn:admin2_code":"2262.0",
    "gn:admin3_code":"226204.0",
    "gn:admin4_code":"2506.0",
    "gn:asciiname":"Kallbacken",
    "gn:country_code":"SE",
    "gn:dem":45,
    "gn:feature_class":"P",
    "gn:feature_code":"PPL",
    "gn:name":"Kallb\u00e4cken",
    "gn:population":0,
    "gn:timezone":"Europe/Stockholm",
    "iso:country":"SE",
    "wof:name":"Kallbacken",
    "wof:placetype":"locality"
},
  "geometry": {"coordinates":[17.61349,62.47283],"type":"Point"}
}