{
  "type": "Feature",
  "properties": {
    "gn:admin1_code":"22.0",
    "gn:admin2_code":"1764.0",
    "gn:asciiname":"Varmerud",
    "gn:cc2":"SE",
    "gn:country_code":"SE",
    "gn:dem":112,
    "gn:feature_class":"P",
    "gn:feature_code":"PPL",
    "gn:name":"V\u00e4rmerud",
    "gn:population":0,
    "gn:timezone":"Europe/Stockholm",
    "iso:country":"SE",
    "name:und_x_variant":[
        "Vermerud",
        "V\u00e4rmerud"
    ],
    "wof:name":"Varmerud",
    "wof:placetype":"locality"
},
  "geometry": {"coordinates":[12.93333,59.38333000000001],"type":"Point"}
}