{
  "type": "Feature",
  "properties": {
    "gn:admin1_code":"6.0",
    "gn:admin2_code":"1383.0",
    "gn:asciiname":"Karl Gustav",
    "gn:country_code":"SE",
    "gn:dem":53,
    "gn:feature_class":"P",
    "gn:feature_code":"PPL",
    "gn:name":"Karl Gustav",
    "gn:population":0,
    "gn:timezone":"Europe/Stockholm",
    "iso:country":"SE",
    "wof:name":"Karl Gustav",
    "wof:placetype":"locality"
},
  "geometry": {"coordinates":[12.55,57.25],"type":"Point"}
}