{
  "type": "Feature",
  "properties": {
    "gn:admin1_code":"5.0",
    "gn:admin2_code":"980.0",
    "gn:asciiname":"Djauvik",
    "gn:country_code":"SE",
    "gn:dem":16,
    "gn:feature_class":"P",
    "gn:feature_code":"PPL",
    "gn:name":"Djauvik",
    "gn:population":0,
    "gn:timezone":"Europe/Stockholm",
    "iso:country":"SE",
    "name:und_x_variant":[
        "Djupviks Fiskl\u00e4ge",
        "Djauvik",
        "Djupvik"
    ],
    "wof:name":"Djauvik",
    "wof:placetype":"locality"
},
  "geometry": {"coordinates":[18.15037,57.30503],"type":"Point"}
}