{
  "type": "Feature",
  "properties": {
    "iso:country":"SE",
    "name:swe_x_preferred":[
        "\u00d6nneredshagen"
    ],
    "wof:name":"Onneredshagen",
    "wof:placetype":"neighbourhood"
},
  "geometry": {"coordinates":[11.8748136906283,57.63874456025191],"type":"Point"}
}