{
  "type": "Feature",
  "properties": {
    "gn:admin1_code":"10.0",
    "gn:admin2_code":"2085.0",
    "gn:asciiname":"Frosarasen",
    "gn:country_code":"SE",
    "gn:dem":372,
    "gn:feature_class":"P",
    "gn:feature_code":"PPL",
    "gn:name":"Fr\u00f6sar\u00e5sen",
    "gn:population":0,
    "gn:timezone":"Europe/Stockholm",
    "iso:country":"SE",
    "name:nor_x_preferred":[
        "Fr\u00f6sar\u00e5sen"
    ],
    "name:nor_x_variant":[
        "Fr\u00f8sar\u00e5sen"
    ],
    "name:und_x_variant":[
        "Fr\u00f6sar\u00e5sen"
    ],
    "wof:name":"Frosarasen",
    "wof:placetype":"locality"
},
  "geometry": {"coordinates":[14.46667,60.21666999999999],"type":"Point"}
}