{
  "type": "Feature",
  "properties": {
    "gn:admin1_code":"28.0",
    "gn:admin2_code":"1496.0",
    "gn:asciiname":"Snarvad",
    "gn:cc2":"SE",
    "gn:country_code":"SE",
    "gn:dem":72,
    "gn:feature_class":"P",
    "gn:feature_code":"PPL",
    "gn:name":"Snarvad",
    "gn:population":0,
    "gn:timezone":"Europe/Stockholm",
    "iso:country":"SE",
    "name:und_x_variant":[
        "Sn\u00e4rva",
        "Snarvad"
    ],
    "wof:name":"Snarvad",
    "wof:placetype":"locality"
},
  "geometry": {"coordinates":[13.96667,58.55],"type":"Point"}
}