{
  "type": "Feature",
  "properties": {
    "gn:admin1_code":"15.0",
    "gn:admin2_code":"1862.0",
    "gn:asciiname":"Sjoandan",
    "gn:country_code":"SE",
    "gn:dem":120,
    "gn:feature_class":"P",
    "gn:feature_code":"PPL",
    "gn:name":"Sj\u00f6\u00e4ndan",
    "gn:population":0,
    "gn:timezone":"Europe/Stockholm",
    "iso:country":"SE",
    "wof:name":"Sjoandan",
    "wof:placetype":"locality"
},
  "geometry": {"coordinates":[14.46667,59.25],"type":"Point"}
}