{
  "type": "Feature",
  "properties": {
    "gn:admin1_code":"15.0",
    "gn:admin2_code":"1863.0",
    "gn:asciiname":"Kampbacken",
    "gn:country_code":"SE",
    "gn:dem":219,
    "gn:feature_class":"P",
    "gn:feature_code":"PPL",
    "gn:name":"Kampbacken",
    "gn:population":0,
    "gn:timezone":"Europe/Stockholm",
    "iso:country":"SE",
    "wof:name":"Kampbacken",
    "wof:placetype":"locality"
},
  "geometry": {"coordinates":[14.66667,59.83333],"type":"Point"}
}