{
  "type": "Feature",
  "properties": {
    "gn:admin1_code":"9.0",
    "gn:admin2_code":"840.0",
    "gn:admin3_code":"84001.0",
    "gn:admin4_code":"858.0",
    "gn:asciiname":"Nytorp",
    "gn:country_code":"SE",
    "gn:dem":9,
    "gn:feature_class":"P",
    "gn:feature_code":"PPL",
    "gn:name":"Nytorp",
    "gn:population":0,
    "gn:timezone":"Europe/Stockholm",
    "iso:country":"SE",
    "wof:name":"Nytorp",
    "wof:placetype":"locality"
},
  "geometry": {"coordinates":[16.40327000000001,56.54415],"type":"Point"}
}