{
  "type": "Feature",
  "properties": {
    "gn:admin1_code":"15.0",
    "gn:admin2_code":"1884.0",
    "gn:asciiname":"Gammelhyttan",
    "gn:country_code":"SE",
    "gn:dem":211,
    "gn:feature_class":"P",
    "gn:feature_code":"PPL",
    "gn:name":"Gammelhyttan",
    "gn:population":0,
    "gn:timezone":"Europe/Stockholm",
    "iso:country":"SE",
    "wof:name":"Gammelhyttan",
    "wof:placetype":"locality"
},
  "geometry": {"coordinates":[14.83333,59.65],"type":"Point"}
}