{
  "type": "Feature",
  "properties": {
    "gn:admin1_code":"21.0",
    "gn:admin2_code":"319.0",
    "gn:asciiname":"Tallmon",
    "gn:country_code":"SE",
    "gn:dem":2,
    "gn:feature_class":"P",
    "gn:feature_code":"PPL",
    "gn:name":"Tallmon",
    "gn:population":0,
    "gn:timezone":"Europe/Stockholm",
    "iso:country":"SE",
    "wof:name":"Tallmon",
    "wof:placetype":"locality"
},
  "geometry": {"coordinates":[17.43333,60.61666999999999],"type":"Point"}
}