{
  "type": "Feature",
  "properties": {
    "gn:admin1_code":"26.0",
    "gn:admin2_code":"138.0",
    "gn:asciiname":"Solsidan",
    "gn:country_code":"SE",
    "gn:dem":9,
    "gn:feature_class":"P",
    "gn:feature_code":"PPL",
    "gn:name":"Solsidan",
    "gn:population":0,
    "gn:timezone":"Europe/Stockholm",
    "iso:country":"SE",
    "name:ita_x_preferred":[
        "Solsidan"
    ],
    "name:nno_x_preferred":[
        "Solsidan"
    ],
    "name:nor_x_preferred":[
        "Solsidan"
    ],
    "name:pol_x_preferred":[
        "Solsidan"
    ],
    "name:swe_x_preferred":[
        "Solsidan"
    ],
    "wof:name":"Solsidan",
    "wof:placetype":"locality"
},
  "geometry": {"coordinates":[18.29953,59.26812],"type":"Point"}
}