{
  "type": "Feature",
  "properties": {
    "gn:admin1_code":"22.0",
    "gn:admin2_code":"1762.0",
    "gn:asciiname":"Sodra Kvarntorp",
    "gn:cc2":"SE",
    "gn:country_code":"SE",
    "gn:dem":130,
    "gn:feature_class":"P",
    "gn:feature_code":"PPL",
    "gn:name":"S\u00f6dra Kvarntorp",
    "gn:population":0,
    "gn:timezone":"Europe/Stockholm",
    "iso:country":"SE",
    "name:nor_x_preferred":[
        "S\u00f6dra Kvarntorp"
    ],
    "name:nor_x_variant":[
        "S\u00f8dra Kvarntorp"
    ],
    "name:und_x_variant":[
        "S\u00f6dra Qvarntorp"
    ],
    "wof:name":"Sodra Kvarntorp",
    "wof:placetype":"locality"
},
  "geometry": {"coordinates":[13.51667,59.78333000000001],"type":"Point"}
}