{
  "type": "Feature",
  "properties": {
    "gn:admin1_code":"22.0",
    "gn:admin2_code":"1760.0",
    "gn:asciiname":"Bjorkhojden",
    "gn:country_code":"SE",
    "gn:dem":131,
    "gn:feature_class":"P",
    "gn:feature_code":"PPL",
    "gn:name":"Bj\u00f6rkh\u00f6jden",
    "gn:population":0,
    "gn:timezone":"Europe/Stockholm",
    "iso:country":"SE",
    "name:nor_x_preferred":[
        "Bj\u00f6rkh\u00f6jden"
    ],
    "name:nor_x_variant":[
        "Bj\u00f8rkh\u00f8jden"
    ],
    "wof:name":"Bjorkhojden",
    "wof:placetype":"locality"
},
  "geometry": {"coordinates":[14.35,59.46666999999999],"type":"Point"}
}