{
  "type": "Feature",
  "properties": {
    "gn:admin1_code":"7.0",
    "gn:admin2_code":"2309.0",
    "gn:asciiname":"Hov",
    "gn:cc2":"SE",
    "gn:country_code":"SE",
    "gn:dem":296,
    "gn:feature_class":"P",
    "gn:feature_code":"PPL",
    "gn:name":"Hov",
    "gn:population":0,
    "gn:timezone":"Europe/Stockholm",
    "iso:country":"SE",
    "name:ceb_x_preferred":[
        "Hov"
    ],
    "name:dan_x_preferred":[
        "Hov"
    ],
    "name:deu_x_preferred":[
        "Hov"
    ],
    "name:fin_x_preferred":[
        "Hov"
    ],
    "name:fra_x_preferred":[
        "Hov"
    ],
    "name:nld_x_preferred":[
        "Hov"
    ],
    "name:nor_x_preferred":[
        "Hov"
    ],
    "name:swe_x_preferred":[
        "Hov"
    ],
    "name:und_x_variant":[
        "H\u00e5f",
        "Hov"
    ],
    "wof:name":"Hov",
    "wof:placetype":"locality"
},
  "geometry": {"coordinates":[13.91667,63.38333000000001],"type":"Point"}
}