{
  "type": "Feature",
  "properties": {
    "gn:admin1_code":"28.0",
    "gn:admin2_code":"1461.0",
    "gn:asciiname":"Erikstad",
    "gn:country_code":"SE",
    "gn:dem":67,
    "gn:feature_class":"P",
    "gn:feature_code":"PPL",
    "gn:name":"Erikstad",
    "gn:population":0,
    "gn:timezone":"Europe/Stockholm",
    "iso:country":"SE",
    "name:fin_x_preferred":[
        "Erikstad"
    ],
    "name:jav_x_preferred":[
        "Erikstad"
    ],
    "name:msa_x_preferred":[
        "Erikstad"
    ],
    "name:nld_x_preferred":[
        "Erikstad"
    ],
    "name:swe_x_preferred":[
        "Erikstad"
    ],
    "wof:name":"Erikstad",
    "wof:placetype":"locality"
},
  "geometry": {"coordinates":[12.41667,58.63333000000001],"type":"Point"}
}