{
  "type": "Feature",
  "properties": {
    "gn:admin1_code":"28.0",
    "gn:admin2_code":"1470.0",
    "gn:asciiname":"Borga",
    "gn:country_code":"SE",
    "gn:dem":116,
    "gn:feature_class":"P",
    "gn:feature_code":"PPL",
    "gn:name":"Borga",
    "gn:population":0,
    "gn:timezone":"Europe/Stockholm",
    "iso:country":"SE",
    "wof:name":"Borga",
    "wof:placetype":"locality"
},
  "geometry": {"coordinates":[13.16667,58.21666999999999],"type":"Point"}
}