{
  "type": "Feature",
  "properties": {
    "gn:admin1_code":"28.0",
    "gn:admin2_code":"1495.0",
    "gn:asciiname":"Gallkvist",
    "gn:country_code":"SE",
    "gn:dem":118,
    "gn:feature_class":"P",
    "gn:feature_code":"PPL",
    "gn:name":"G\u00e4llkvist",
    "gn:population":0,
    "gn:timezone":"Europe/Stockholm",
    "iso:country":"SE",
    "wof:name":"Gallkvist",
    "wof:placetype":"locality"
},
  "geometry": {"coordinates":[13.43333,58.38333000000001],"type":"Point"}
}