{
  "type": "Feature",
  "properties": {
    "gn:admin1_code":"16",
    "gn:admin2_code":"581.0",
    "gn:admin3_code":"58113.0",
    "gn:admin4_code":"487.0",
    "gn:asciiname":"Soersjoen",
    "gn:country_code":"SE",
    "gn:dem":104,
    "gn:feature_class":"P",
    "gn:feature_code":"PPL",
    "gn:name":"S\u00f6rsj\u00f6n",
    "gn:population":0,
    "gn:timezone":"Europe/Stockholm",
    "iso:country":"SE",
    "wof:name":"Soersjoen",
    "wof:placetype":"locality"
},
  "geometry": {"coordinates":[16.0845,58.732],"type":"Point"}
}