{
  "type": "Feature",
  "properties": {
    "gn:admin1_code":"10.0",
    "gn:admin2_code":"2026.0",
    "gn:admin3_code":"202603.0",
    "gn:admin4_code":"2348.0",
    "gn:asciiname":"Forsgardet",
    "gn:country_code":"SE",
    "gn:dem":200,
    "gn:feature_class":"P",
    "gn:feature_code":"PPL",
    "gn:name":"Forsg\u00e4rdet",
    "gn:population":0,
    "gn:timezone":"Europe/Stockholm",
    "iso:country":"SE",
    "wof:name":"Forsgardet",
    "wof:placetype":"locality"
},
  "geometry": {"coordinates":[14.79558,60.49769000000001],"type":"Point"}
}