{
  "type": "Feature",
  "properties": {
    "gn:admin1_code":"27.0",
    "gn:admin2_code":"1275.0",
    "gn:asciiname":"Troedsberga",
    "gn:country_code":"SE",
    "gn:dem":90,
    "gn:feature_class":"P",
    "gn:feature_code":"PPL",
    "gn:name":"Troedsberga",
    "gn:population":0,
    "gn:timezone":"Europe/Stockholm",
    "iso:country":"SE",
    "wof:name":"Troedsberga",
    "wof:placetype":"locality"
},
  "geometry": {"coordinates":[13.33333,56.16667],"type":"Point"}
}