{
  "type": "Feature",
  "properties": {
    "gn:admin1_code":"27.0",
    "gn:admin2_code":"1277.0",
    "gn:asciiname":"Sanna",
    "gn:country_code":"SE",
    "gn:dem":23,
    "gn:feature_class":"P",
    "gn:feature_code":"PPL",
    "gn:name":"S\u00e5nna",
    "gn:population":0,
    "gn:timezone":"Europe/Stockholm",
    "iso:country":"SE",
    "name:ceb_x_preferred":[
        "Sanna"
    ],
    "name:deu_x_preferred":[
        "Sanna"
    ],
    "name:fra_x_preferred":[
        "Sanna"
    ],
    "name:ita_x_preferred":[
        "Sanna"
    ],
    "name:nld_x_preferred":[
        "Sanna"
    ],
    "name:nor_x_preferred":[
        "Sanna"
    ],
    "name:pol_x_preferred":[
        "Sanna"
    ],
    "name:swe_x_preferred":[
        "Sanna"
    ],
    "wof:name":"Sanna",
    "wof:placetype":"locality"
},
  "geometry": {"coordinates":[13.01667,56.15],"type":"Point"}
}