{
  "type": "Feature",
  "properties": {
    "gn:admin1_code":"8.0",
    "gn:admin2_code":"662.0",
    "gn:asciiname":"Brottjestad",
    "gn:country_code":"SE",
    "gn:dem":169,
    "gn:feature_class":"P",
    "gn:feature_code":"PPL",
    "gn:name":"Br\u00f6ttjestad",
    "gn:population":0,
    "gn:timezone":"Europe/Stockholm",
    "iso:country":"SE",
    "name:nor_x_preferred":[
        "Br\u00f6ttjestad"
    ],
    "name:nor_x_variant":[
        "Br\u00f8ttjestad"
    ],
    "wof:name":"Brottjestad",
    "wof:placetype":"locality"
},
  "geometry": {"coordinates":[13.71667,57.15],"type":"Point"}
}