{
  "type": "Feature",
  "properties": {
    "gn:admin1_code":"24.0",
    "gn:admin2_code":"2284.0",
    "gn:asciiname":"Kornsjo",
    "gn:country_code":"SE",
    "gn:dem":105,
    "gn:feature_class":"P",
    "gn:feature_code":"PPL",
    "gn:name":"Kornsj\u00f6",
    "gn:population":0,
    "gn:timezone":"Europe/Stockholm",
    "iso:country":"SE",
    "name:nor_x_preferred":[
        "Kornsj\u00f6"
    ],
    "name:nor_x_variant":[
        "Kornsj\u00f8"
    ],
    "name:und_x_variant":[
        "Kornsj\u00f6"
    ],
    "wof:name":"Kornsjo",
    "wof:placetype":"locality"
},
  "geometry": {"coordinates":[18.43333,63.21666999999999],"type":"Point"}
}