{
  "type": "Feature",
  "properties": {
    "gn:admin1_code":"7.0",
    "gn:admin2_code":"2326.0",
    "gn:asciiname":"Grossmyrbodarna",
    "gn:country_code":"SE",
    "gn:dem":425,
    "gn:feature_class":"P",
    "gn:feature_code":"PPL",
    "gn:name":"Grossmyrbodarna",
    "gn:population":0,
    "gn:timezone":"Europe/Stockholm",
    "iso:country":"SE",
    "wof:name":"Grossmyrbodarna",
    "wof:placetype":"locality"
},
  "geometry": {"coordinates":[14.31667,62.71666999999999],"type":"Point"}
}