{
  "type": "Feature",
  "properties": {
    "gn:gn_country":"SE",
    "gn:gn_fcode":"PPL",
    "gn:gn_pop":0,
    "gn:population":547,
    "iso:country":"SE",
    "name:dan_x_preferred":[
        "Kyrkesund"
    ],
    "name:deu_x_preferred":[
        "Kyrkesund"
    ],
    "name:eng_x_preferred":[
        "Kyrkesund"
    ],
    "name:fra_x_preferred":[
        "Kyrkesund"
    ],
    "name:nds_x_preferred":[
        "Kyrkesund"
    ],
    "name:nld_x_preferred":[
        "Kyrkesund"
    ],
    "name:nno_x_preferred":[
        "Kyrkesund"
    ],
    "name:nob_x_preferred":[
        "Kyrkesund"
    ],
    "name:swe_x_preferred":[
        "Kyrkesund"
    ],
    "qs_pg:aaroncc":"SE",
    "qs_pg:gn_country":"SE",
    "qs_pg:gn_fcode":"PPL",
    "qs_pg:gn_pop":0,
    "qs_pg:name":"Kyrkesund",
    "qs_pg:name_adm0":"Sverige",
    "qs_pg:name_adm1":"V\u00e4stra G\u00f6talands L\u00e4n",
    "qs_pg:photos":485,
    "qs_pg:photos_1k":98,
    "qs_pg:photos_9k":2,
    "qs_pg:photos_9r":5,
    "qs_pg:photos_all":485,
    "qs_pg:photos_sr":7,
    "qs_pg:pop_sr":0,
    "qs_pg:qs_pg_placetype":"locality",
    "qs_pg:qs_pg_placetype_gp":"Town",
    "qs_pg:woe_adm0":23424954,
    "woe:adm0_id":23424954,
    "woe:name_adm0":"Sverige",
    "woe:name_adm1":"V\u00e4stra G\u00f6talands L\u00e4n",
    "woe:placetype":"Town",
    "wof:name":"Kyrkesund",
    "wof:placetype":"locality",
    "wof:population":547
},
  "geometry": {"coordinates":[11.51667,58.01667],"type":"Point"}
}