{
  "type": "Feature",
  "properties": {
    "gn:admin1_code":"9.0",
    "gn:admin2_code":"882.0",
    "gn:asciiname":"Jamserum",
    "gn:country_code":"SE",
    "gn:dem":32,
    "gn:feature_class":"P",
    "gn:feature_code":"PPL",
    "gn:name":"J\u00e4mserum",
    "gn:population":0,
    "gn:timezone":"Europe/Stockholm",
    "iso:country":"SE",
    "wof:name":"Jamserum",
    "wof:placetype":"locality"
},
  "geometry": {"coordinates":[16.48333,57.41667],"type":"Point"}
}