{
  "type": "Feature",
  "properties": {
    "gn:admin1_code":"28.0",
    "gn:admin2_code":"1493.0",
    "gn:asciiname":"Madlyckan",
    "gn:country_code":"SE",
    "gn:dem":44,
    "gn:feature_class":"P",
    "gn:feature_code":"PPL",
    "gn:name":"Madlyckan",
    "gn:population":0,
    "gn:timezone":"Europe/Stockholm",
    "iso:country":"SE",
    "wof:name":"Madlyckan",
    "wof:placetype":"locality"
},
  "geometry": {"coordinates":[13.83333,58.71666999999999],"type":"Point"}
}