{
  "type": "Feature",
  "properties": {
    "gn:admin1_code":"25.0",
    "gn:admin2_code":"1981.0",
    "gn:asciiname":"Stentorpet",
    "gn:country_code":"SE",
    "gn:dem":86,
    "gn:feature_class":"P",
    "gn:feature_code":"PPL",
    "gn:name":"Stentorpet",
    "gn:population":0,
    "gn:timezone":"Europe/Stockholm",
    "iso:country":"SE",
    "wof:name":"Stentorpet",
    "wof:placetype":"locality"
},
  "geometry": {"coordinates":[16.51667,59.95],"type":"Point"}
}