{
  "type": "Feature",
  "properties": {
    "gn:admin1_code":"10.0",
    "gn:admin2_code":"2026.0",
    "gn:asciiname":"Vasttjarnlindan",
    "gn:country_code":"SE",
    "gn:dem":310,
    "gn:feature_class":"P",
    "gn:feature_code":"PPL",
    "gn:name":"V\u00e4sttj\u00e4rnlindan",
    "gn:population":0,
    "gn:timezone":"Europe/Stockholm",
    "iso:country":"SE",
    "wof:name":"Vasttjarnlindan",
    "wof:placetype":"locality"
},
  "geometry": {"coordinates":[14.98333,60.45],"type":"Point"}
}