{
  "type": "Feature",
  "properties": {
    "gn:admin1_code":"27.0",
    "gn:admin2_code":"1257.0",
    "gn:asciiname":"Sjunkamossa",
    "gn:country_code":"SE",
    "gn:dem":108,
    "gn:feature_class":"P",
    "gn:feature_code":"PPL",
    "gn:name":"Sjunkamossa",
    "gn:population":0,
    "gn:timezone":"Europe/Stockholm",
    "iso:country":"SE",
    "wof:name":"Sjunkamossa",
    "wof:placetype":"locality"
},
  "geometry": {"coordinates":[13.15,56.25],"type":"Point"}
}