{
  "type": "Feature",
  "properties": {
    "gn:country":"SE",
    "gn:fcode":"PPL",
    "gn:population":0,
    "iso:country":"SE",
    "name:dan_x_preferred":[
        "Norrmj\u00f6le"
    ],
    "name:deu_x_preferred":[
        "Norrmj\u00f6le"
    ],
    "name:eng_x_preferred":[
        "Norrmj\u00f6le"
    ],
    "name:fra_x_preferred":[
        "Norrmj\u00f6le"
    ],
    "name:nds_x_preferred":[
        "Norrmj\u00f6le"
    ],
    "name:nld_x_preferred":[
        "Norrmj\u00f6le"
    ],
    "name:nno_x_preferred":[
        "Norrmj\u00f6le"
    ],
    "name:nob_x_preferred":[
        "Norrmj\u00f6le"
    ],
    "name:nor_x_preferred":[
        "Norrmj\u00f8le"
    ],
    "name:nor_x_variant":[
        "Norrmj\u00f6le"
    ],
    "name:swe_x_preferred":[
        "Norrmj\u00f6le"
    ],
    "qs_pg:aaroncc":"SE",
    "qs_pg:gn_country":"SE",
    "qs_pg:gn_fcode":"PPL",
    "qs_pg:gn_pop":0,
    "qs_pg:name":"Norrmj\u00f6le",
    "qs_pg:name_adm0":"Sverige",
    "qs_pg:name_adm1":"V\u00e4sterbottens L\u00e4n",
    "qs_pg:photos":15,
    "qs_pg:photos_1k":3,
    "qs_pg:photos_9k":1,
    "qs_pg:photos_9r":1,
    "qs_pg:photos_all":15,
    "qs_pg:photos_sr":1,
    "qs_pg:pop_sr":0,
    "qs_pg:qs_pg_placetype":"locality",
    "qs_pg:qs_pg_placetype_gp":"Town",
    "qs_pg:woe_adm0":23424954,
    "woe:adm0_id":23424954,
    "woe:name_adm0":"Sverige",
    "woe:name_adm1":"V\u00e4sterbottens L\u00e4n",
    "woe:placetype":"Town",
    "wof:name":"Norrmj\u00f6le",
    "wof:placetype":"locality",
    "wof:population":228
},
  "geometry": {"coordinates":[20.11667,63.66667],"type":"Point"}
}