{
  "type": "Feature",
  "properties": {
    "gn:admin1_code":"24.0",
    "gn:admin2_code":"2260.0",
    "gn:admin3_code":"226003.0",
    "gn:admin4_code":"2465.0",
    "gn:asciiname":"Vassnas",
    "gn:country_code":"SE",
    "gn:dem":242,
    "gn:feature_class":"P",
    "gn:feature_code":"PPL",
    "gn:name":"Vassn\u00e4s",
    "gn:population":0,
    "gn:timezone":"Europe/Stockholm",
    "iso:country":"SE",
    "wof:name":"Vassnas",
    "wof:placetype":"locality"
},
  "geometry": {"coordinates":[15.27597,62.41886],"type":"Point"}
}