{
  "type": "Feature",
  "properties": {
    "gn:admin1_code":"6.0",
    "gn:admin2_code":"1383.0",
    "gn:asciiname":"Smedsgard",
    "gn:country_code":"SE",
    "gn:dem":4,
    "gn:feature_class":"P",
    "gn:feature_code":"PPL",
    "gn:name":"Smedsg\u00e5rd",
    "gn:population":0,
    "gn:timezone":"Europe/Stockholm",
    "iso:country":"SE",
    "wof:name":"Smedsgard",
    "wof:placetype":"locality"
},
  "geometry": {"coordinates":[12.35,57.01667],"type":"Point"}
}