{
  "type": "Feature",
  "properties": {
    "gn:admin1_code":"28.0",
    "gn:admin2_code":"1421.0",
    "gn:asciiname":"Bo",
    "gn:country_code":"SE",
    "gn:dem":41,
    "gn:feature_class":"P",
    "gn:feature_code":"PPL",
    "gn:name":"B\u00f6",
    "gn:population":0,
    "gn:timezone":"Europe/Stockholm",
    "iso:country":"SE",
    "name:dan_x_preferred":[
        "Bo"
    ],
    "name:hye_x_preferred":[
        "\u0532\u0578"
    ],
    "name:lit_x_preferred":[
        "Bo"
    ],
    "name:nor_x_preferred":[
        "B\u00f6"
    ],
    "name:nor_x_variant":[
        "B\u00f8"
    ],
    "wof:name":"Bo",
    "wof:placetype":"locality"
},
  "geometry": {"coordinates":[11.78333,58.16667],"type":"Point"}
}