{
  "type": "Feature",
  "properties": {
    "gn:admin1_code":"27.0",
    "gn:admin2_code":"1287.0",
    "gn:asciiname":"Gislov",
    "gn:cc2":"SE",
    "gn:country_code":"SE",
    "gn:dem":23,
    "gn:feature_class":"P",
    "gn:feature_code":"PPL",
    "gn:name":"Gisl\u00f6v",
    "gn:population":0,
    "gn:timezone":"Europe/Stockholm",
    "iso:country":"SE",
    "name:nor_x_preferred":[
        "Gisl\u00f6v"
    ],
    "name:nor_x_variant":[
        "Gisl\u00f8v"
    ],
    "name:und_x_variant":[
        "Gislof"
    ],
    "wof:name":"Gislov",
    "wof:placetype":"locality"
},
  "geometry": {"coordinates":[13.25,55.38333000000001],"type":"Point"}
}