{
  "type": "Feature",
  "properties": {
    "gn:admin1_code":"24.0",
    "gn:admin2_code":"2282.0",
    "gn:admin3_code":"228202.0",
    "gn:admin4_code":"2482.0",
    "gn:asciiname":"Arsta",
    "gn:country_code":"SE",
    "gn:dem":36,
    "gn:feature_class":"P",
    "gn:feature_code":"PPL",
    "gn:name":"\u00c4rsta",
    "gn:population":0,
    "gn:timezone":"Europe/Stockholm",
    "iso:country":"SE",
    "wof:name":"Arsta",
    "wof:placetype":"locality"
},
  "geometry": {"coordinates":[18.116,62.89536],"type":"Point"}
}