{
  "type": "Feature",
  "properties": {
    "gn:admin1_code":"7.0",
    "gn:admin2_code":"2321.0",
    "gn:asciiname":"Heljesund",
    "gn:country_code":"SE",
    "gn:dem":294,
    "gn:feature_class":"P",
    "gn:feature_code":"PPL",
    "gn:name":"Heljesund",
    "gn:population":0,
    "gn:timezone":"Europe/Stockholm",
    "iso:country":"SE",
    "wof:name":"Heljesund",
    "wof:placetype":"locality"
},
  "geometry": {"coordinates":[14.03333,63.25],"type":"Point"}
}