{
  "type": "Feature",
  "properties": {
    "gn:admin1_code":"10.0",
    "gn:admin2_code":"2029.0",
    "gn:asciiname":"Norrskog",
    "gn:cc2":"SE",
    "gn:country_code":"SE",
    "gn:dem":371,
    "gn:feature_class":"P",
    "gn:feature_code":"PPL",
    "gn:name":"Norrskog",
    "gn:population":0,
    "gn:timezone":"Europe/Stockholm",
    "iso:country":"SE",
    "name:und_x_variant":[
        "Norrskog F\u00e4bod",
        "Norrskog"
    ],
    "wof:name":"Norrskog",
    "wof:placetype":"locality"
},
  "geometry": {"coordinates":[14.76667,60.73333],"type":"Point"}
}