{
  "type": "Feature",
  "properties": {
    "gn:admin1_code":"2.0",
    "gn:admin2_code":"1081.0",
    "gn:asciiname":"Mortjuk",
    "gn:country_code":"SE",
    "gn:dem":14,
    "gn:feature_class":"P",
    "gn:feature_code":"PPL",
    "gn:name":"M\u00f6rtjuk",
    "gn:population":0,
    "gn:timezone":"Europe/Stockholm",
    "iso:country":"SE",
    "name:nor_x_preferred":[
        "M\u00f6rtjuk"
    ],
    "name:nor_x_variant":[
        "M\u00f8rtjuk"
    ],
    "name:und_x_variant":[
        "M\u00f6rtjuk"
    ],
    "wof:name":"Mortjuk",
    "wof:placetype":"locality"
},
  "geometry": {"coordinates":[15.11667,56.21666999999999],"type":"Point"}
}