{
  "type": "Feature",
  "properties": {
    "gn:admin1_code":"18.0",
    "gn:admin2_code":"482.0",
    "gn:asciiname":"Silinge",
    "gn:country_code":"SE",
    "gn:dem":54,
    "gn:feature_class":"P",
    "gn:feature_code":"PPL",
    "gn:name":"Silinge",
    "gn:population":0,
    "gn:timezone":"Europe/Stockholm",
    "iso:country":"SE",
    "wof:name":"Silinge",
    "wof:placetype":"locality"
},
  "geometry": {"coordinates":[16.56667,59.01667],"type":"Point"}
}