{
  "type": "Feature",
  "properties": {
    "gn:admin1_code":"3.0",
    "gn:admin2_code":"2132.0",
    "gn:asciiname":"Norra Algered",
    "gn:cc2":"SE",
    "gn:country_code":"SE",
    "gn:dem":97,
    "gn:feature_class":"P",
    "gn:feature_code":"PPL",
    "gn:name":"Norra \u00c4lgered",
    "gn:population":0,
    "gn:timezone":"Europe/Stockholm",
    "iso:country":"SE",
    "name:und_x_variant":[
        "\u00c4lgered",
        "Norra \u00c4lgered"
    ],
    "wof:name":"Norra Algered",
    "wof:placetype":"locality"
},
  "geometry": {"coordinates":[16.95,62.01667],"type":"Point"}
}