{
  "type": "Feature",
  "properties": {
    "gn:admin1_code":"9.0",
    "gn:admin2_code":"821.0",
    "gn:asciiname":"Tamshult",
    "gn:country_code":"SE",
    "gn:dem":180,
    "gn:feature_class":"P",
    "gn:feature_code":"PPL",
    "gn:name":"T\u00e4mshult",
    "gn:population":0,
    "gn:timezone":"Europe/Stockholm",
    "iso:country":"SE",
    "wof:name":"Tamshult",
    "wof:placetype":"locality"
},
  "geometry": {"coordinates":[15.75,57.06667],"type":"Point"}
}