{
  "type": "Feature",
  "properties": {
    "gn:admin1_code":"12.0",
    "gn:admin2_code":"763.0",
    "gn:asciiname":"Svenshult",
    "gn:country_code":"SE",
    "gn:dem":142,
    "gn:feature_class":"P",
    "gn:feature_code":"PPL",
    "gn:name":"Svenshult",
    "gn:population":0,
    "gn:timezone":"Europe/Stockholm",
    "iso:country":"SE",
    "wof:name":"Svenshult",
    "wof:placetype":"locality"
},
  "geometry": {"coordinates":[15.03333,56.61666999999999],"type":"Point"}
}