{
  "type": "Feature",
  "properties": {
    "gn:admin1_code":"8.0",
    "gn:admin2_code":"662.0",
    "gn:asciiname":"Ostra Bararyd",
    "gn:country_code":"SE",
    "gn:dem":221,
    "gn:feature_class":"P",
    "gn:feature_code":"PPL",
    "gn:name":"\u00d6stra B\u00e5raryd",
    "gn:population":0,
    "gn:timezone":"Europe/Stockholm",
    "iso:country":"SE",
    "name:nor_x_preferred":[
        "\u00d6stra B\u00e5raryd"
    ],
    "name:nor_x_variant":[
        "\u00d8stra B\u00e5raryd"
    ],
    "name:und_x_variant":[
        "\u00d6stra B\u00e5raryd"
    ],
    "wof:name":"Ostra Bararyd",
    "wof:placetype":"locality"
},
  "geometry": {"coordinates":[13.51667,57.35],"type":"Point"}
}