{
  "type": "Feature",
  "properties": {
    "gn:admin1_code":"15.0",
    "gn:admin2_code":"1860.0",
    "gn:asciiname":"Backgarden",
    "gn:country_code":"SE",
    "gn:dem":129,
    "gn:feature_class":"P",
    "gn:feature_code":"PPL",
    "gn:name":"Backg\u00e5rden",
    "gn:population":0,
    "gn:timezone":"Europe/Stockholm",
    "iso:country":"SE",
    "wof:name":"Backgarden",
    "wof:placetype":"locality"
},
  "geometry": {"coordinates":[14.53333,58.96666999999999],"type":"Point"}
}