{
  "type": "Feature",
  "properties": {
    "gn:admin1_code":"23.0",
    "gn:admin2_code":"2422.0",
    "gn:asciiname":"Hogbranna",
    "gn:country_code":"SE",
    "gn:dem":396,
    "gn:feature_class":"P",
    "gn:feature_code":"PPL",
    "gn:name":"H\u00f6gbr\u00e4nna",
    "gn:population":0,
    "gn:timezone":"Europe/Stockholm",
    "iso:country":"SE",
    "wof:name":"Hogbranna",
    "wof:placetype":"locality"
},
  "geometry": {"coordinates":[18.08333,65.41667],"type":"Point"}
}