{
  "type": "Feature",
  "properties": {
    "gn:admin1_code":"24.0",
    "gn:admin2_code":"2283.0",
    "gn:asciiname":"Ostansjo",
    "gn:country_code":"SE",
    "gn:dem":201,
    "gn:feature_class":"P",
    "gn:feature_code":"PPL",
    "gn:name":"\u00d6stansj\u00f6",
    "gn:population":0,
    "gn:timezone":"Europe/Stockholm",
    "iso:country":"SE",
    "name:nor_x_preferred":[
        "\u00d6stansj\u00f6"
    ],
    "name:nor_x_variant":[
        "\u00d8stansj\u00f8"
    ],
    "name:und_x_variant":[
        "\u00d6stansj\u00f6"
    ],
    "wof:name":"Ostansjo",
    "wof:placetype":"locality"
},
  "geometry": {"coordinates":[17.06667,63.65],"type":"Point"}
}