{
  "type": "Feature",
  "properties": {
    "gn:admin1_code":"2.0",
    "gn:admin2_code":"1080.0",
    "gn:asciiname":"Hinderas",
    "gn:country_code":"SE",
    "gn:dem":114,
    "gn:feature_class":"P",
    "gn:feature_code":"PPL",
    "gn:name":"Hinder\u00e5s",
    "gn:population":0,
    "gn:timezone":"Europe/Stockholm",
    "iso:country":"SE",
    "wof:name":"Hinderas",
    "wof:placetype":"locality"
},
  "geometry": {"coordinates":[15.65,56.35],"type":"Point"}
}