{
  "type": "Feature",
  "properties": {
    "gn:admin1_code":"27.0",
    "gn:admin2_code":"1284.0",
    "gn:asciiname":"Nyrup",
    "gn:country_code":"SE",
    "gn:dem":11,
    "gn:feature_class":"P",
    "gn:feature_code":"PPL",
    "gn:name":"Nyrup",
    "gn:population":0,
    "gn:timezone":"Europe/Stockholm",
    "iso:country":"SE",
    "wof:name":"Nyrup",
    "wof:placetype":"locality"
},
  "geometry": {"coordinates":[12.55,56.23333],"type":"Point"}
}