{
  "type": "Feature",
  "properties": {
    "gn:admin1_code":"27.0",
    "gn:admin2_code":"1257.0",
    "gn:asciiname":"Mattarp",
    "gn:country_code":"SE",
    "gn:dem":143,
    "gn:feature_class":"P",
    "gn:feature_code":"PPL",
    "gn:name":"Mattarp",
    "gn:population":0,
    "gn:timezone":"Europe/Stockholm",
    "iso:country":"SE",
    "wof:name":"Mattarp",
    "wof:placetype":"locality"
},
  "geometry": {"coordinates":[13.28333,56.31667],"type":"Point"}
}