{
  "type": "Feature",
  "properties": {
    "gn:admin1_code":"10.0",
    "gn:admin2_code":"2061.0",
    "gn:asciiname":"Bommarsbo",
    "gn:country_code":"SE",
    "gn:dem":147,
    "gn:feature_class":"P",
    "gn:feature_code":"PPL",
    "gn:name":"Bommarsbo",
    "gn:population":0,
    "gn:timezone":"Europe/Stockholm",
    "iso:country":"SE",
    "wof:name":"Bommarsbo",
    "wof:placetype":"locality"
},
  "geometry": {"coordinates":[15.46667,60.25],"type":"Point"}
}