{
  "type": "Feature",
  "properties": {
    "gn:admin1_code":"5.0",
    "gn:admin2_code":"980.0",
    "gn:asciiname":"Smissarve",
    "gn:country_code":"SE",
    "gn:dem":19,
    "gn:feature_class":"P",
    "gn:feature_code":"PPL",
    "gn:name":"Smissarve",
    "gn:population":0,
    "gn:timezone":"Europe/Stockholm",
    "iso:country":"SE",
    "name:und_x_variant":[
        "Smittsarfve",
        "Smissarve"
    ],
    "wof:name":"Smissarve",
    "wof:placetype":"locality"
},
  "geometry": {"coordinates":[18.42559,57.18755],"type":"Point"}
}