{
  "type": "Feature",
  "properties": {
    "gn:admin1_code":"6.0",
    "gn:asciiname":"Traslovslage",
    "gn:country_code":"SE",
    "gn:dem":6,
    "gn:feature_class":"P",
    "gn:feature_code":"PPL",
    "gn:name":"Tr\u00e4sl\u00f6vsl\u00e4ge",
    "gn:population":0,
    "gn:timezone":"Europe/Stockholm",
    "iso:country":"SE",
    "name:ceb_x_preferred":[
        "Tr\u00e4sl\u00f6vsl\u00e4ge"
    ],
    "name:fas_x_preferred":[
        "\u062a\u0631\u0627\u0633\u0644\u0648\u0633\u0644\u0627\u06af"
    ],
    "name:fra_x_preferred":[
        "Tr\u00e4sl\u00f6vsl\u00e4ge"
    ],
    "name:ita_x_preferred":[
        "Tr\u00e4sl\u00f6vsl\u00e4ge"
    ],
    "name:nld_x_preferred":[
        "Tr\u00e4sl\u00f6vsl\u00e4ge"
    ],
    "name:nno_x_preferred":[
        "Tr\u00e4sl\u00f6vsl\u00e4ge"
    ],
    "name:nor_x_preferred":[
        "Tr\u00e4sl\u00f6vsl\u00e4ge"
    ],
    "wof:name":"Traslovslage",
    "wof:placetype":"locality"
},
  "geometry": {"coordinates":[12.275,57.05833000000001],"type":"Point"}
}