{
  "type": "Feature",
  "properties": {
    "gn:admin1_code":"6.0",
    "gn:asciiname":"Traslovslage",
    "gn:country_code":"SE",
    "gn:dem":6,
    "gn:feature_class":"P",
    "gn:feature_code":"PPL",
    "gn:name":"Tr\u00e4sl\u00f6vsl\u00e4ge",
    "gn:population":0,
    "gn:timezone":"Europe/Stockholm",
    "iso:country":"SE",
    "name:und_x_variant":[
        "Tr\u00e4sl\u00f6vsl\u00e4ge"
    ],
    "wof:name":"Traslovslage",
    "wof:placetype":"locality"
},
  "geometry": {"coordinates":[12.275,57.05833000000001],"type":"Point"}
}