{
  "type": "Feature",
  "properties": {
    "gn:admin1_code":"8.0",
    "gn:admin2_code":"682.0",
    "gn:asciiname":"Holsteryd",
    "gn:country_code":"SE",
    "gn:dem":234,
    "gn:feature_class":"P",
    "gn:feature_code":"PPL",
    "gn:name":"Holsteryd",
    "gn:population":0,
    "gn:timezone":"Europe/Stockholm",
    "iso:country":"SE",
    "wof:name":"Holsteryd",
    "wof:placetype":"locality"
},
  "geometry": {"coordinates":[14.78333,57.48333],"type":"Point"}
}