{
  "type": "Feature",
  "properties": {
    "gn:admin1_code":"26.0",
    "gn:admin2_code":"117.0",
    "gn:asciiname":"Hummelmora",
    "gn:cc2":"SE",
    "gn:country_code":"SE",
    "gn:dem":21,
    "gn:feature_class":"P",
    "gn:feature_code":"PPL",
    "gn:name":"Hummelmora",
    "gn:population":0,
    "gn:timezone":"Europe/Stockholm",
    "iso:country":"SE",
    "name:und_x_variant":[
        "Hummelmora\u00f6n",
        "Hummelmora"
    ],
    "wof:name":"Hummelmora",
    "wof:placetype":"locality"
},
  "geometry": {"coordinates":[18.59417,59.45889],"type":"Point"}
}