{
  "type": "Feature",
  "properties": {
    "gn:admin1_code":"27.0",
    "gn:admin2_code":"1276.0",
    "gn:asciiname":"Mammarp",
    "gn:country_code":"SE",
    "gn:dem":32,
    "gn:feature_class":"P",
    "gn:feature_code":"PPL",
    "gn:name":"Mammarp",
    "gn:population":0,
    "gn:timezone":"Europe/Stockholm",
    "iso:country":"SE",
    "wof:name":"Mammarp",
    "wof:placetype":"locality"
},
  "geometry": {"coordinates":[13.15,56.11666999999999],"type":"Point"}
}