{
  "type": "Feature",
  "properties": {
    "gn:admin1_code":"27.0",
    "gn:admin2_code":"1230.0",
    "gn:asciiname":"Onsvala",
    "gn:country_code":"SE",
    "gn:dem":5,
    "gn:feature_class":"P",
    "gn:feature_code":"PPL",
    "gn:name":"\u00d6nsvala",
    "gn:population":0,
    "gn:timezone":"Europe/Stockholm",
    "iso:country":"SE",
    "name:nor_x_preferred":[
        "\u00d6nsvala"
    ],
    "name:nor_x_variant":[
        "\u00d8nsvala"
    ],
    "name:und_x_variant":[
        "\u00d6nsvala"
    ],
    "wof:name":"Onsvala",
    "wof:placetype":"locality"
},
  "geometry": {"coordinates":[13.18333,55.61666999999999],"type":"Point"}
}