{
  "type": "Feature",
  "properties": {
    "gn:admin1_code":"27.0",
    "gn:admin2_code":"1262.0",
    "gn:asciiname":"Strandhusen",
    "gn:country_code":"SE",
    "gn:dem":2,
    "gn:feature_class":"P",
    "gn:feature_code":"PPL",
    "gn:name":"Strandhusen",
    "gn:population":0,
    "gn:timezone":"Europe/Stockholm",
    "iso:country":"SE",
    "wof:name":"Strandhusen",
    "wof:placetype":"locality"
},
  "geometry": {"coordinates":[13.06667,55.66667],"type":"Point"}
}