{
  "type": "Feature",
  "properties": {
    "gn:admin1_code":"3.0",
    "gn:admin2_code":"2132.0",
    "gn:asciiname":"Grangsjo",
    "gn:cc2":"SE",
    "gn:country_code":"SE",
    "gn:dem":80,
    "gn:feature_class":"P",
    "gn:feature_code":"PPL",
    "gn:name":"Gr\u00e4ngsj\u00f6",
    "gn:population":0,
    "gn:timezone":"Europe/Stockholm",
    "iso:country":"SE",
    "name:und_x_variant":[
        "Vastra Gr\u00e4ngsj\u00f6",
        "V\u00e4stergr\u00e4ngsj\u00f6",
        "Gr\u00e4ngsj\u00f6"
    ],
    "wof:name":"Grangsjo",
    "wof:placetype":"locality"
},
  "geometry": {"coordinates":[17.11667000000001,62.05],"type":"Point"}
}