{
  "type": "Feature",
  "properties": {
    "gn:admin1_code":"15.0",
    "gn:admin2_code":"1861.0",
    "gn:asciiname":"Vala",
    "gn:country_code":"SE",
    "gn:dem":75,
    "gn:feature_class":"P",
    "gn:feature_code":"PPL",
    "gn:name":"V\u00e4la",
    "gn:population":0,
    "gn:timezone":"Europe/Stockholm",
    "iso:country":"SE",
    "name:ceb_x_preferred":[
        "Vala"
    ],
    "name:ces_x_preferred":[
        "Vala"
    ],
    "name:deu_x_preferred":[
        "Vala"
    ],
    "name:fin_x_preferred":[
        "Vala"
    ],
    "name:fra_x_preferred":[
        "Vala"
    ],
    "name:hun_x_preferred":[
        "Vala"
    ],
    "name:ita_x_preferred":[
        "Vala"
    ],
    "name:jpn_x_preferred":[
        "\u30f4\u30a1\u30e9"
    ],
    "name:lat_x_preferred":[
        "Vala"
    ],
    "name:nld_x_preferred":[
        "Vala"
    ],
    "name:pol_x_preferred":[
        "Vala"
    ],
    "name:por_x_preferred":[
        "Vala"
    ],
    "name:spa_x_preferred":[
        "Vala"
    ],
    "name:sqi_x_preferred":[
        "Vala"
    ],
    "name:swe_x_preferred":[
        "Vala"
    ],
    "wof:name":"Vala",
    "wof:placetype":"locality"
},
  "geometry": {"coordinates":[14.88333,59.06667],"type":"Point"}
}