{
  "type": "Feature",
  "properties": {
    "gn:admin1_code":"6.0",
    "gn:admin2_code":"1382.0",
    "gn:asciiname":"Grytas",
    "gn:country_code":"SE",
    "gn:dem":5,
    "gn:feature_class":"P",
    "gn:feature_code":"PPL",
    "gn:name":"Gryt\u00e5s",
    "gn:population":0,
    "gn:timezone":"Europe/Stockholm",
    "iso:country":"SE",
    "wof:name":"Grytas",
    "wof:placetype":"locality"
},
  "geometry": {"coordinates":[12.36667,56.98333],"type":"Point"}
}