{
  "type": "Feature",
  "properties": {
    "gn:admin1_code":"9.0",
    "gn:admin2_code":"862.0",
    "gn:asciiname":"Gramnamala",
    "gn:cc2":"SE",
    "gn:country_code":"SE",
    "gn:dem":112,
    "gn:feature_class":"P",
    "gn:feature_code":"PPL",
    "gn:name":"Gr\u00e4mnam\u00e5la",
    "gn:population":0,
    "gn:timezone":"Europe/Stockholm",
    "iso:country":"SE",
    "name:und_x_variant":[
        "Gr\u00e4mnem\u00e5la",
        "Gr\u00e4mnam\u00e5la"
    ],
    "wof:name":"Gramnamala",
    "wof:placetype":"locality"
},
  "geometry": {"coordinates":[15.58333,56.56667],"type":"Point"}
}