{
  "type": "Feature",
  "properties": {
    "gn:admin1_code":"10.0",
    "gn:admin2_code":"2039.0",
    "gn:asciiname":"Synnanat",
    "gn:country_code":"SE",
    "gn:dem":575,
    "gn:feature_class":"P",
    "gn:feature_code":"PPL",
    "gn:name":"Synnan\u00e5t",
    "gn:population":0,
    "gn:timezone":"Europe/Stockholm",
    "iso:country":"SE",
    "wof:name":"Synnanat",
    "wof:placetype":"locality"
},
  "geometry": {"coordinates":[12.71667,61.83306],"type":"Point"}
}