{
  "type": "Feature",
  "properties": {
    "gn:admin1_code":"10.0",
    "gn:asciiname":"Sodra Allmanningbo",
    "gn:country_code":"SE",
    "gn:dem":124,
    "gn:feature_class":"P",
    "gn:feature_code":"PPL",
    "gn:name":"S\u00f6dra Allm\u00e4nningbo",
    "gn:population":0,
    "gn:timezone":"Europe/Stockholm",
    "iso:country":"SE",
    "wof:name":"Sodra Allmanningbo",
    "wof:placetype":"locality"
},
  "geometry": {"coordinates":[15.51667,59.73333],"type":"Point"}
}