{
  "type": "Feature",
  "properties": {
    "gn:admin1_code":"3.0",
    "gn:admin2_code":"2184.0",
    "gn:asciiname":"Finflo",
    "gn:cc2":"SE",
    "gn:country_code":"SE",
    "gn:dem":21,
    "gn:feature_class":"P",
    "gn:feature_code":"PPL",
    "gn:name":"Finflo",
    "gn:population":0,
    "gn:timezone":"Europe/Stockholm",
    "iso:country":"SE",
    "name:und_x_variant":[
        "Finnflo",
        "Finflo"
    ],
    "wof:name":"Finflo",
    "wof:placetype":"locality"
},
  "geometry": {"coordinates":[17.05,61.76667],"type":"Point"}
}