{
  "type": "Feature",
  "properties": {
    "gn:admin1_code":"18.0",
    "gn:admin2_code":"428.0",
    "gn:asciiname":"Rude",
    "gn:cc2":"SE",
    "gn:country_code":"SE",
    "gn:dem":43,
    "gn:feature_class":"P",
    "gn:feature_code":"PPL",
    "gn:name":"Rude",
    "gn:population":0,
    "gn:timezone":"Europe/Stockholm",
    "iso:country":"SE",
    "name:und_x_variant":[
        "Ruda",
        "Rude"
    ],
    "wof:name":"Rude",
    "wof:placetype":"locality"
},
  "geometry": {"coordinates":[16.05,59.01667],"type":"Point"}
}