{
  "type": "Feature",
  "properties": {
    "gn:admin1_code":"24.0",
    "gn:admin2_code":"2260.0",
    "gn:admin3_code":"226003.0",
    "gn:admin4_code":"2465.0",
    "gn:asciiname":"Juanaset",
    "gn:country_code":"SE",
    "gn:dem":242,
    "gn:feature_class":"P",
    "gn:feature_code":"PPL",
    "gn:name":"Ju\u00e5n\u00e4set",
    "gn:population":0,
    "gn:timezone":"Europe/Stockholm",
    "iso:country":"SE",
    "wof:name":"Juanaset",
    "wof:placetype":"locality"
},
  "geometry": {"coordinates":[15.38333,62.41667],"type":"Point"}
}