{
  "type": "Feature",
  "properties": {
    "gn:admin1_code":"14.0",
    "gn:admin2_code":"2521.0",
    "gn:asciiname":"Siikavaara",
    "gn:country_code":"SE",
    "gn:dem":176,
    "gn:feature_class":"P",
    "gn:feature_code":"PPL",
    "gn:name":"Siikavaara",
    "gn:population":0,
    "gn:timezone":"Europe/Stockholm",
    "iso:country":"SE",
    "wof:name":"Siikavaara",
    "wof:placetype":"locality"
},
  "geometry": {"coordinates":[22.78333,67.26666999999999],"type":"Point"}
}