{
  "type": "Feature",
  "properties": {
    "gn:admin1_code":"14.0",
    "gn:admin2_code":"2582.0",
    "gn:asciiname":"Ostra Bodvallen",
    "gn:country_code":"SE",
    "gn:dem":24,
    "gn:feature_class":"P",
    "gn:feature_code":"PPL",
    "gn:name":"\u00d6stra Bodvallen",
    "gn:population":0,
    "gn:timezone":"Europe/Stockholm",
    "iso:country":"SE",
    "name:nor_x_preferred":[
        "\u00d6stra Bodvallen"
    ],
    "name:nor_x_variant":[
        "\u00d8stra Bodvallen"
    ],
    "name:und_x_variant":[
        "\u00d6stra Bodvallen"
    ],
    "wof:name":"Ostra Bodvallen",
    "wof:placetype":"locality"
},
  "geometry": {"coordinates":[21.03333,66.03333000000001],"type":"Point"}
}