{
  "type": "Feature",
  "properties": {
    "gn:admin1_code":"23.0",
    "gn:admin2_code":"2409.0",
    "gn:asciiname":"Gumbodaholmen",
    "gn:cc2":"SE",
    "gn:country_code":"SE",
    "gn:dem":12,
    "gn:feature_class":"P",
    "gn:feature_code":"PPL",
    "gn:name":"Gumbodaholmen",
    "gn:population":0,
    "gn:timezone":"Europe/Stockholm",
    "iso:country":"SE",
    "name:und_x_variant":[
        "Gumboholmen",
        "Gumbodaholmen"
    ],
    "wof:name":"Gumbodaholmen",
    "wof:placetype":"locality"
},
  "geometry": {"coordinates":[21.06667,64.23333000000001],"type":"Point"}
}