{
  "type": "Feature",
  "properties": {
    "gn:admin1_code":"16.0",
    "gn:admin2_code":"560.0",
    "gn:asciiname":"Manhult",
    "gn:country_code":"SE",
    "gn:dem":213,
    "gn:feature_class":"P",
    "gn:feature_code":"PPL",
    "gn:name":"M\u00e5nhult",
    "gn:population":0,
    "gn:timezone":"Europe/Stockholm",
    "iso:country":"SE",
    "wof:name":"Manhult",
    "wof:placetype":"locality"
},
  "geometry": {"coordinates":[15.35,58.08333],"type":"Point"}
}