{
  "type": "Feature",
  "properties": {
    "gn:admin1_code":"9.0",
    "gn:admin2_code":"883.0",
    "gn:asciiname":"Blackstad",
    "gn:cc2":"SE",
    "gn:country_code":"SE",
    "gn:dem":114,
    "gn:feature_class":"P",
    "gn:feature_code":"PPL",
    "gn:name":"Blackstad",
    "gn:population":0,
    "gn:timezone":"Europe/Stockholm",
    "iso:country":"SE",
    "name:und_x_variant":[
        "Biackstad",
        "Blackstad"
    ],
    "wof:name":"Blackstad",
    "wof:placetype":"locality"
},
  "geometry": {"coordinates":[16.18333,57.78333000000001],"type":"Point"}
}