{
  "type": "Feature",
  "properties": {
    "gn:admin1_code":"7.0",
    "gn:admin2_code":"2326.0",
    "gn:asciiname":"Galhammar",
    "gn:country_code":"SE",
    "gn:dem":299,
    "gn:feature_class":"P",
    "gn:feature_code":"PPL",
    "gn:name":"Galhammar",
    "gn:population":0,
    "gn:timezone":"Europe/Stockholm",
    "iso:country":"SE",
    "wof:name":"Galhammar",
    "wof:placetype":"locality"
},
  "geometry": {"coordinates":[14.41667,62.78333000000001],"type":"Point"}
}