{
  "type": "Feature",
  "properties": {
    "gn:admin1_code":"23.0",
    "gn:admin2_code":"2403.0",
    "gn:asciiname":"Balsjo",
    "gn:country_code":"SE",
    "gn:dem":196,
    "gn:feature_class":"P",
    "gn:feature_code":"PPL",
    "gn:name":"Balsj\u00f6",
    "gn:population":0,
    "gn:timezone":"Europe/Stockholm",
    "iso:country":"SE",
    "name:nor_x_preferred":[
        "Balsj\u00f6"
    ],
    "name:nor_x_variant":[
        "Balsj\u00f8"
    ],
    "name:und_x_variant":[
        "Balsj\u00f6"
    ],
    "wof:name":"Balsjo",
    "wof:placetype":"locality"
},
  "geometry": {"coordinates":[19.05,63.91667],"type":"Point"}
}