{
  "type": "Feature",
  "properties": {
    "gn:admin1_code":"9.0",
    "gn:admin2_code":"880.0",
    "gn:asciiname":"Skarvsjo",
    "gn:country_code":"SE",
    "gn:dem":107,
    "gn:feature_class":"P",
    "gn:feature_code":"PPL",
    "gn:name":"Sk\u00e4rvsj\u00f6",
    "gn:population":0,
    "gn:timezone":"Europe/Stockholm",
    "iso:country":"SE",
    "wof:name":"Skarvsjo",
    "wof:placetype":"locality"
},
  "geometry": {"coordinates":[15.83333,56.58333],"type":"Point"}
}