{
  "type": "Feature",
  "properties": {
    "gn:admin1_code":"2.0",
    "gn:admin2_code":"1081.0",
    "gn:asciiname":"Vang",
    "gn:country_code":"SE",
    "gn:dem":78,
    "gn:feature_class":"P",
    "gn:feature_code":"PPL",
    "gn:name":"V\u00e5ng",
    "gn:population":0,
    "gn:timezone":"Europe/Stockholm",
    "iso:country":"SE",
    "name:cat_x_preferred":[
        "Vang"
    ],
    "name:ceb_x_preferred":[
        "Vang"
    ],
    "name:dan_x_preferred":[
        "Vang"
    ],
    "name:deu_x_preferred":[
        "Vang"
    ],
    "name:est_x_preferred":[
        "Vang"
    ],
    "name:hrv_x_preferred":[
        "Vang"
    ],
    "name:ita_x_preferred":[
        "Vang"
    ],
    "name:lat_x_preferred":[
        "Vang"
    ],
    "name:nld_x_preferred":[
        "Vang"
    ],
    "name:nno_x_preferred":[
        "Vang"
    ],
    "name:nor_x_preferred":[
        "Vang"
    ],
    "name:pol_x_preferred":[
        "Vang"
    ],
    "name:ron_x_preferred":[
        "Vang"
    ],
    "name:swe_x_preferred":[
        "Vang"
    ],
    "name:vie_x_preferred":[
        "Vang"
    ],
    "wof:name":"Vang",
    "wof:placetype":"locality"
},
  "geometry": {"coordinates":[15.41667,56.26667],"type":"Point"}
}