{
  "type": "Feature",
  "properties": {
    "gn:admin1_code":"26.0",
    "gn:admin2_code":"115.0",
    "gn:asciiname":"Vaxtuna",
    "gn:country_code":"SE",
    "gn:dem":17,
    "gn:feature_class":"P",
    "gn:feature_code":"PPL",
    "gn:name":"Vaxtuna",
    "gn:population":0,
    "gn:timezone":"Europe/Stockholm",
    "iso:country":"SE",
    "wof:name":"Vaxtuna",
    "wof:placetype":"locality"
},
  "geometry": {"coordinates":[18.06667,59.61666999999999],"type":"Point"}
}