{
  "type": "Feature",
  "properties": {
    "gn:admin1_code":"9.0",
    "gn:admin2_code":"881.0",
    "gn:asciiname":"Lilla Skedsbygd",
    "gn:country_code":"SE",
    "gn:dem":123,
    "gn:feature_class":"P",
    "gn:feature_code":"PPL",
    "gn:name":"Lilla Skedsbygd",
    "gn:population":0,
    "gn:timezone":"Europe/Stockholm",
    "iso:country":"SE",
    "wof:name":"Lilla Skedsbygd",
    "wof:placetype":"locality"
},
  "geometry": {"coordinates":[15.83333,56.93333000000001],"type":"Point"}
}