{
  "type": "Feature",
  "properties": {
    "gn:admin1_code":"8.0",
    "gn:admin2_code":"617.0",
    "gn:asciiname":"Norra Svano",
    "gn:country_code":"SE",
    "gn:dem":180,
    "gn:feature_class":"P",
    "gn:feature_code":"PPL",
    "gn:name":"Norra Sv\u00e4n\u00f6",
    "gn:population":0,
    "gn:timezone":"Europe/Stockholm",
    "iso:country":"SE",
    "wof:name":"Norra Svano",
    "wof:placetype":"locality"
},
  "geometry": {"coordinates":[13.98333,57.33333],"type":"Point"}
}