{
  "type": "Feature",
  "properties": {
    "gn:gn_country":"SE",
    "gn:gn_fcode":"PPL",
    "gn:gn_pop":231,
    "gn:population":231,
    "iso:country":"SE",
    "name:bul_x_preferred":[
        "\u0410\u0440\u043e\u043d\u0442\u043e\u0440\u043f"
    ],
    "name:dan_x_preferred":[
        "Arontorp"
    ],
    "name:dut_x_preferred":[
        "Arontorp"
    ],
    "name:eng_x_preferred":[
        "Arontorp"
    ],
    "name:fre_x_preferred":[
        "Arontorp"
    ],
    "name:ger_x_preferred":[
        "Arontorp"
    ],
    "name:nan_x_preferred":[
        "Arontorp"
    ],
    "name:nds_x_preferred":[
        "Arontorp"
    ],
    "name:nno_x_preferred":[
        "Arontorp"
    ],
    "name:nob_x_preferred":[
        "Arontorp"
    ],
    "name:swe_x_preferred":[
        "Arontorp"
    ],
    "qs_pg:aaroncc":"SE",
    "qs_pg:gn_country":"SE",
    "qs_pg:gn_fcode":"PPL",
    "qs_pg:gn_pop":231,
    "qs_pg:name":"Arontorp",
    "qs_pg:name_adm0":"Sverige",
    "qs_pg:name_adm1":"Kalmar L\u00e4n",
    "qs_pg:photos":2,
    "qs_pg:photos_1k":1,
    "qs_pg:photos_9k":1,
    "qs_pg:photos_9r":1,
    "qs_pg:photos_all":2,
    "qs_pg:photos_sr":1,
    "qs_pg:pop_sr":2,
    "qs_pg:qs_pg_placetype":"locality",
    "qs_pg:qs_pg_placetype_gp":"Town",
    "qs_pg:woe_adm0":23424954,
    "woe:adm0_id":23424954,
    "woe:name_adm0":"Sverige",
    "woe:name_adm1":"Kalmar L\u00e4n",
    "woe:placetype":"Town",
    "wof:name":"Arontorp",
    "wof:placetype":"locality",
    "wof:population":231
},
  "geometry": {"coordinates":[16.53333,56.65],"type":"Point"}
}