{
  "type": "Feature",
  "properties": {
    "gn:admin1_code":"23.0",
    "gn:admin2_code":"2460.0",
    "gn:asciiname":"Pengsjo",
    "gn:country_code":"SE",
    "gn:dem":149,
    "gn:feature_class":"P",
    "gn:feature_code":"PPL",
    "gn:name":"Pengsj\u00f6",
    "gn:population":0,
    "gn:timezone":"Europe/Stockholm",
    "iso:country":"SE",
    "name:nor_x_preferred":[
        "Pengsj\u00f6"
    ],
    "name:nor_x_variant":[
        "Pengsj\u00f8"
    ],
    "wof:name":"Pengsjo",
    "wof:placetype":"locality"
},
  "geometry": {"coordinates":[19.65,63.86666999999999],"type":"Point"}
}