{
  "type": "Feature",
  "properties": {
    "gn:admin1_code":"15.0",
    "gn:admin2_code":"1864.0",
    "gn:asciiname":"Norra Lovfallet",
    "gn:cc2":"SE",
    "gn:country_code":"SE",
    "gn:dem":288,
    "gn:feature_class":"P",
    "gn:feature_code":"PPL",
    "gn:name":"Norra L\u00f6vfallet",
    "gn:population":0,
    "gn:timezone":"Europe/Stockholm",
    "iso:country":"SE",
    "name:nor_x_preferred":[
        "Norra L\u00f6vfallet"
    ],
    "name:nor_x_variant":[
        "Norra L\u00f8vfallet"
    ],
    "name:und_x_variant":[
        "Norra L\u00f6ffallet",
        "Norra L\u00f6vfallet"
    ],
    "wof:name":"Norra Lovfallet",
    "wof:placetype":"locality"
},
  "geometry": {"coordinates":[14.95,59.98333],"type":"Point"}
}