{
  "type": "Feature",
  "properties": {
    "gn:admin1_code":"22.0",
    "gn:admin2_code":"1785.0",
    "gn:asciiname":"Nolby",
    "gn:country_code":"SE",
    "gn:dem":50,
    "gn:feature_class":"P",
    "gn:feature_code":"PPL",
    "gn:name":"Nolby",
    "gn:population":0,
    "gn:timezone":"Europe/Stockholm",
    "iso:country":"SE",
    "wof:name":"Nolby",
    "wof:placetype":"locality"
},
  "geometry": {"coordinates":[12.95,59.08333],"type":"Point"}
}