{
  "type": "Feature",
  "properties": {
    "gn:admin1_code":"28.0",
    "gn:admin2_code":"1438.0",
    "gn:asciiname":"Mellbyn",
    "gn:country_code":"SE",
    "gn:dem":136,
    "gn:feature_class":"P",
    "gn:feature_code":"PPL",
    "gn:name":"Mellbyn",
    "gn:population":0,
    "gn:timezone":"Europe/Stockholm",
    "iso:country":"SE",
    "wof:name":"Mellbyn",
    "wof:placetype":"locality"
},
  "geometry": {"coordinates":[11.88333,58.86666999999999],"type":"Point"}
}