{
  "type": "Feature",
  "properties": {
    "gn:admin1_code":"10.0",
    "gn:admin2_code":"2082.0",
    "gn:asciiname":"Ansta",
    "gn:cc2":"SE",
    "gn:country_code":"SE",
    "gn:dem":79,
    "gn:feature_class":"P",
    "gn:feature_code":"PPL",
    "gn:name":"Ansta",
    "gn:population":0,
    "gn:timezone":"Europe/Stockholm",
    "iso:country":"SE",
    "name:und_x_variant":[
        "Anstahyttan",
        "Ansta"
    ],
    "wof:name":"Ansta",
    "wof:placetype":"locality"
},
  "geometry": {"coordinates":[15.91667,60.38333000000001],"type":"Point"}
}