{
  "type": "Feature",
  "properties": {
    "gn:admin1_code":"9.0",
    "gn:admin2_code":"861.0",
    "gn:asciiname":"Molstad",
    "gn:country_code":"SE",
    "gn:dem":9,
    "gn:feature_class":"P",
    "gn:feature_code":"PPL",
    "gn:name":"M\u00f6lstad",
    "gn:population":0,
    "gn:timezone":"Europe/Stockholm",
    "iso:country":"SE",
    "name:nor_x_preferred":[
        "M\u00f6lstad"
    ],
    "name:nor_x_variant":[
        "M\u00f8lstad"
    ],
    "name:und_x_variant":[
        "M\u00f6lstad"
    ],
    "wof:name":"Molstad",
    "wof:placetype":"locality"
},
  "geometry": {"coordinates":[16.41667,57.05],"type":"Point"}
}