{
  "type": "Feature",
  "properties": {
    "gn:admin1_code":"23.0",
    "gn:admin2_code":"2462.0",
    "gn:asciiname":"Stennas",
    "gn:country_code":"SE",
    "gn:dem":488,
    "gn:feature_class":"P",
    "gn:feature_code":"PPL",
    "gn:name":"Stenn\u00e4s",
    "gn:population":0,
    "gn:timezone":"Europe/Stockholm",
    "iso:country":"SE",
    "wof:name":"Stennas",
    "wof:placetype":"locality"
},
  "geometry": {"coordinates":[15.75,65.23333000000001],"type":"Point"}
}