{
  "type": "Feature",
  "properties": {
    "gn:admin1_code":"3.0",
    "gn:admin2_code":"2183.0",
    "gn:asciiname":"Tomterna",
    "gn:country_code":"SE",
    "gn:dem":208,
    "gn:feature_class":"P",
    "gn:feature_code":"PPL",
    "gn:name":"Tomterna",
    "gn:population":0,
    "gn:timezone":"Europe/Stockholm",
    "iso:country":"SE",
    "wof:name":"Tomterna",
    "wof:placetype":"locality"
},
  "geometry": {"coordinates":[16.35,61.63333000000001],"type":"Point"}
}