{
  "type": "Feature",
  "properties": {
    "gn:admin1_code":"26.0",
    "gn:admin2_code":"188.0",
    "gn:asciiname":"Langrudan",
    "gn:country_code":"SE",
    "gn:dem":26,
    "gn:feature_class":"P",
    "gn:feature_code":"PPL",
    "gn:name":"L\u00e5ngrudan",
    "gn:population":0,
    "gn:timezone":"Europe/Stockholm",
    "iso:country":"SE",
    "wof:name":"Langrudan",
    "wof:placetype":"locality"
},
  "geometry": {"coordinates":[18.85,59.75],"type":"Point"}
}