{
  "type": "Feature",
  "properties": {
    "gn:admin1_code":"8.0",
    "gn:admin2_code":"617.0",
    "gn:asciiname":"Granstorp",
    "gn:country_code":"SE",
    "gn:dem":268,
    "gn:feature_class":"P",
    "gn:feature_code":"PPL",
    "gn:name":"Granstorp",
    "gn:population":0,
    "gn:timezone":"Europe/Stockholm",
    "iso:country":"SE",
    "wof:name":"Granstorp",
    "wof:placetype":"locality"
},
  "geometry": {"coordinates":[13.81667,57.46666999999999],"type":"Point"}
}