{
  "type": "Feature",
  "properties": {
    "gn:admin1_code":"24.0",
    "gn:admin2_code":"2283.0",
    "gn:asciiname":"Tarasjoberg",
    "gn:country_code":"SE",
    "gn:dem":203,
    "gn:feature_class":"P",
    "gn:feature_code":"PPL",
    "gn:name":"Tarasj\u00f6berg",
    "gn:population":0,
    "gn:timezone":"Europe/Stockholm",
    "iso:country":"SE",
    "name:nor_x_preferred":[
        "Tarasj\u00f6berg"
    ],
    "name:nor_x_variant":[
        "Tarasj\u00f8berg"
    ],
    "wof:name":"Tarasjoberg",
    "wof:placetype":"locality"
},
  "geometry": {"coordinates":[16.73333,63.68333000000001],"type":"Point"}
}