{
  "type": "Feature",
  "properties": {
    "gn:admin1_code":"18.0",
    "gn:admin2_code":"483.0",
    "gn:asciiname":"Sunnansjo",
    "gn:country_code":"SE",
    "gn:dem":54,
    "gn:feature_class":"P",
    "gn:feature_code":"PPL",
    "gn:name":"Sunnansj\u00f6",
    "gn:population":0,
    "gn:timezone":"Europe/Stockholm",
    "iso:country":"SE",
    "name:nor_x_preferred":[
        "Sunnansj\u00f6"
    ],
    "name:nor_x_variant":[
        "Sunnansj\u00f8"
    ],
    "name:und_x_variant":[
        "Sunnansj\u00f6"
    ],
    "wof:name":"Sunnansjo",
    "wof:placetype":"locality"
},
  "geometry": {"coordinates":[16.31667,59.05],"type":"Point"}
}