{
  "type": "Feature",
  "properties": {
    "gn:admin1_code":"3.0",
    "gn:admin2_code":"2184.0",
    "gn:asciiname":"Lonnanger",
    "gn:country_code":"SE",
    "gn:dem":1,
    "gn:feature_class":"P",
    "gn:feature_code":"PPL",
    "gn:name":"L\u00f6nn\u00e5nger",
    "gn:population":0,
    "gn:timezone":"Europe/Stockholm",
    "iso:country":"SE",
    "name:nor_x_preferred":[
        "L\u00f6nn\u00e5nger"
    ],
    "name:nor_x_variant":[
        "L\u00f8nn\u00e5nger"
    ],
    "name:und_x_variant":[
        "L\u00f6nn\u00e5nger"
    ],
    "wof:name":"Lonnanger",
    "wof:placetype":"locality"
},
  "geometry": {"coordinates":[17.23575,61.78997],"type":"Point"}
}