{
  "type": "Feature",
  "properties": {
    "gn:country":"SE",
    "gn:fcode":"PPL",
    "gn:population":0,
    "iso:country":"SE",
    "qs_pg:aaroncc":"SE",
    "qs_pg:gn_country":"SE",
    "qs_pg:gn_fcode":"PPL",
    "qs_pg:gn_pop":0,
    "qs_pg:name":"Backadalen",
    "qs_pg:name_adm0":"Sverige",
    "qs_pg:name_adm1":"V\u00e4stra G\u00f6talands L\u00e4n",
    "qs_pg:photos":120,
    "qs_pg:photos_1k":24,
    "qs_pg:photos_9k":1,
    "qs_pg:photos_9r":3,
    "qs_pg:photos_all":120,
    "qs_pg:photos_sr":3,
    "qs_pg:pop_sr":0,
    "qs_pg:qs_pg_placetype":"locality",
    "qs_pg:qs_pg_placetype_gp":"Town",
    "qs_pg:woe_adm0":23424954,
    "woe:adm0_id":23424954,
    "woe:name_adm0":"Sverige",
    "woe:name_adm1":"V\u00e4stra G\u00f6talands L\u00e4n",
    "woe:placetype":"Town",
    "wof:name":"Backadalen",
    "wof:placetype":"locality"
},
  "geometry": {"coordinates":[11.96667,57.75],"type":"Point"}
}