{
  "type": "Feature",
  "properties": {
    "gn:admin1_code":"23.0",
    "gn:admin2_code":"2482.0",
    "gn:asciiname":"Lovvattnet",
    "gn:cc2":"SE",
    "gn:country_code":"SE",
    "gn:dem":46,
    "gn:feature_class":"P",
    "gn:feature_code":"PPL",
    "gn:name":"L\u00f6vvattnet",
    "gn:population":0,
    "gn:timezone":"Europe/Stockholm",
    "iso:country":"SE",
    "name:nor_x_preferred":[
        "L\u00f6vvattnet"
    ],
    "name:nor_x_variant":[
        "L\u00f8vvattnet"
    ],
    "name:und_x_variant":[
        "L\u00f6fvattnet",
        "L\u00f6vvattnet"
    ],
    "wof:name":"Lovvattnet",
    "wof:placetype":"locality"
},
  "geometry": {"coordinates":[21.16667,64.38333],"type":"Point"}
}