{
  "type": "Feature",
  "properties": {
    "gn:admin1_code":"28.0",
    "gn:admin2_code":"1485.0",
    "gn:asciiname":"Utby",
    "gn:country_code":"SE",
    "gn:dem":41,
    "gn:feature_class":"P",
    "gn:feature_code":"PPL",
    "gn:name":"Utby",
    "gn:population":410,
    "gn:timezone":"Europe/Stockholm",
    "iso:country":"SE",
    "name:fra_x_preferred":[
        "Utby"
    ],
    "name:ita_x_preferred":[
        "Utby"
    ],
    "name:swe_x_preferred":[
        "Utby"
    ],
    "wof:name":"Utby",
    "wof:placetype":"locality",
    "wof:population":410
},
  "geometry": {"coordinates":[11.7868,58.33272],"type":"Point"}
}