{
  "type": "Feature",
  "properties": {
    "gn:admin1_code":"7.0",
    "gn:admin2_code":"2326.0",
    "gn:asciiname":"Bolasen",
    "gn:country_code":"SE",
    "gn:dem":322,
    "gn:feature_class":"P",
    "gn:feature_code":"PPL",
    "gn:name":"B\u00f6l\u00e5sen",
    "gn:population":0,
    "gn:timezone":"Europe/Stockholm",
    "iso:country":"SE",
    "name:nor_x_preferred":[
        "B\u00f6l\u00e5sen"
    ],
    "name:nor_x_variant":[
        "B\u00f8l\u00e5sen"
    ],
    "wof:name":"Bolasen",
    "wof:placetype":"locality"
},
  "geometry": {"coordinates":[14.35,63.03333000000001],"type":"Point"}
}