{
  "type": "Feature",
  "properties": {
    "gn:gn_country":"SE",
    "gn:gn_fcode":"PPL",
    "gn:gn_pop":530,
    "gn:population":746,
    "iso:country":"SE",
    "name:dut_x_preferred":[
        "\u00c5sensbruk"
    ],
    "name:eng_x_preferred":[
        "\u00c5sensbruk"
    ],
    "name:nan_x_preferred":[
        "\u00c5sensbruk"
    ],
    "name:nno_x_preferred":[
        "\u00c5sensbruk"
    ],
    "name:nob_x_preferred":[
        "\u00c5sensbruk"
    ],
    "name:rus_x_preferred":[
        "\u041e\u0441\u0435\u043d\u0441\u0431\u0440\u044e\u043a"
    ],
    "name:swe_x_preferred":[
        "\u00c5sensbruk"
    ],
    "qs_pg:aaroncc":"SE",
    "qs_pg:gn_country":"SE",
    "qs_pg:gn_fcode":"PPL",
    "qs_pg:gn_pop":530,
    "qs_pg:name":"\u00c5sensbruk",
    "qs_pg:name_adm0":"Sverige",
    "qs_pg:name_adm1":"V\u00e4stra G\u00f6talands L\u00e4n",
    "qs_pg:photos":33,
    "qs_pg:photos_1k":7,
    "qs_pg:photos_9k":1,
    "qs_pg:photos_9r":2,
    "qs_pg:photos_all":33,
    "qs_pg:photos_sr":2,
    "qs_pg:pop_sr":2,
    "qs_pg:qs_pg_placetype":"locality",
    "qs_pg:qs_pg_placetype_gp":"Town",
    "qs_pg:woe_adm0":23424954,
    "woe:adm0_id":23424954,
    "woe:name_adm0":"Sverige",
    "woe:name_adm1":"V\u00e4stra G\u00f6talands L\u00e4n",
    "woe:placetype":"Town",
    "wof:name":"\u00c5sensbruk",
    "wof:placetype":"locality",
    "wof:population":746
},
  "geometry": {"coordinates":[12.41667,58.79972],"type":"Point"}
}