{
  "type": "Feature",
  "properties": {
    "gn:admin1_code":"22.0",
    "gn:admin2_code":"1730.0",
    "gn:asciiname":"Torgilsrud",
    "gn:country_code":"SE",
    "gn:dem":121,
    "gn:feature_class":"P",
    "gn:feature_code":"PPL",
    "gn:name":"Torgilsrud",
    "gn:population":0,
    "gn:timezone":"Europe/Stockholm",
    "iso:country":"SE",
    "wof:name":"Torgilsrud",
    "wof:placetype":"locality"
},
  "geometry": {"coordinates":[12.18333,59.81667],"type":"Point"}
}