{
  "type": "Feature",
  "properties": {
    "gn:admin1_code":"10.0",
    "gn:admin2_code":"2083.0",
    "gn:asciiname":"Fensjo",
    "gn:country_code":"SE",
    "gn:dem":118,
    "gn:feature_class":"P",
    "gn:feature_code":"PPL",
    "gn:name":"Fensj\u00f6",
    "gn:population":0,
    "gn:timezone":"Europe/Stockholm",
    "iso:country":"SE",
    "name:nor_x_preferred":[
        "Fensj\u00f6"
    ],
    "name:nor_x_variant":[
        "Fensj\u00f8"
    ],
    "name:und_x_variant":[
        "Fensj\u00f6"
    ],
    "wof:name":"Fensjo",
    "wof:placetype":"locality"
},
  "geometry": {"coordinates":[16.18333,60.25],"type":"Point"}
}