{
  "type": "Feature",
  "properties": {
    "gn:country":"SE",
    "gn:fcode":"PPL",
    "gn:population":372,
    "iso:country":"SE",
    "name:ceb_x_preferred":[
        "V\u00e4sterljung"
    ],
    "name:eng_x_preferred":[
        "V\u00e4sterljung"
    ],
    "name:ita_x_preferred":[
        "V\u00e4sterljung"
    ],
    "name:nan_x_preferred":[
        "V\u00e4sterljung"
    ],
    "name:nld_x_preferred":[
        "V\u00e4sterljung"
    ],
    "name:nno_x_preferred":[
        "V\u00e4sterljung"
    ],
    "name:nob_x_preferred":[
        "V\u00e4sterljung"
    ],
    "name:pol_x_preferred":[
        "V\u00e4sterljung"
    ],
    "name:swe_x_preferred":[
        "V\u00e4sterljung"
    ],
    "qs_pg:aaroncc":"SE",
    "qs_pg:gn_country":"SE",
    "qs_pg:gn_fcode":"PPL",
    "qs_pg:gn_pop":372,
    "qs_pg:name":"V\u00e4sterljung",
    "qs_pg:name_adm0":"Sverige",
    "qs_pg:name_adm1":"S\u00f6dermanlands L\u00e4n",
    "qs_pg:photos":48,
    "qs_pg:photos_1k":10,
    "qs_pg:photos_9k":1,
    "qs_pg:photos_9r":2,
    "qs_pg:photos_all":48,
    "qs_pg:photos_sr":2,
    "qs_pg:pop_sr":2,
    "qs_pg:qs_pg_placetype":"locality",
    "qs_pg:qs_pg_placetype_gp":"Town",
    "qs_pg:woe_adm0":23424954,
    "woe:adm0_id":23424954,
    "woe:name_adm0":"Sverige",
    "woe:name_adm1":"S\u00f6dermanlands L\u00e4n",
    "woe:placetype":"Town",
    "wof:name":"V\u00e4sterljung",
    "wof:placetype":"locality",
    "wof:population":377
},
  "geometry": {"coordinates":[17.43333,58.91667],"type":"Point"}
}