{
  "type": "Feature",
  "properties": {
    "gn:admin1_code":"10.0",
    "gn:admin2_code":"2026.0",
    "gn:asciiname":"Sal",
    "gn:country_code":"SE",
    "gn:dem":268,
    "gn:feature_class":"P",
    "gn:feature_code":"PPL",
    "gn:name":"S\u00e4l",
    "gn:population":0,
    "gn:timezone":"Europe/Stockholm",
    "iso:country":"SE",
    "name:arg_x_preferred":[
        "Sal"
    ],
    "name:ast_x_preferred":[
        "Sal"
    ],
    "name:ben_x_preferred":[
        "\u09b8\u09be\u09b2"
    ],
    "name:cat_x_preferred":[
        "Sal"
    ],
    "name:ceb_x_preferred":[
        "Sal"
    ],
    "name:ces_x_preferred":[
        "Sal"
    ],
    "name:dan_x_preferred":[
        "Sal"
    ],
    "name:fas_x_preferred":[
        "\u0633\u0627\u0644"
    ],
    "name:fin_x_preferred":[
        "Sal"
    ],
    "name:fra_x_preferred":[
        "Sal"
    ],
    "name:glg_x_preferred":[
        "Sal"
    ],
    "name:hat_x_preferred":[
        "Sal"
    ],
    "name:heb_x_preferred":[
        "\u05e1\u05d0\u05dc"
    ],
    "name:hun_x_preferred":[
        "Sal"
    ],
    "name:nds_x_preferred":[
        "Sal"
    ],
    "name:nld_x_preferred":[
        "Sal"
    ],
    "name:nno_x_preferred":[
        "Sal"
    ],
    "name:nor_x_preferred":[
        "Sal"
    ],
    "name:por_x_preferred":[
        "Sal"
    ],
    "name:slk_x_preferred":[
        "Sal"
    ],
    "name:spa_x_preferred":[
        "Sal"
    ],
    "name:swe_x_preferred":[
        "Sal"
    ],
    "name:tur_x_preferred":[
        "Sal"
    ],
    "name:vie_x_preferred":[
        "\u0110\u1ea3o Sal"
    ],
    "wof:name":"Sal",
    "wof:placetype":"locality"
},
  "geometry": {"coordinates":[15.05,60.48333],"type":"Point"}
}