{
  "type": "Feature",
  "properties": {
    "gn:country":"SE",
    "gn:fcode":"PPL",
    "gn:population":0,
    "iso:country":"SE",
    "name:dan_x_preferred":[
        "\u00d6ttum"
    ],
    "name:deu_x_preferred":[
        "\u00d6ttum"
    ],
    "name:eng_x_preferred":[
        "\u00d6ttum"
    ],
    "name:fra_x_preferred":[
        "\u00d6ttum"
    ],
    "name:jpn_x_preferred":[
        "\u30a8\u30c3\u30c8\u30a5\u30e0"
    ],
    "name:nds_x_preferred":[
        "\u00d6ttum"
    ],
    "name:nld_x_preferred":[
        "\u00d6ttum"
    ],
    "name:nno_x_preferred":[
        "\u00d6ttum"
    ],
    "name:nob_x_preferred":[
        "\u00d6ttum"
    ],
    "name:nor_x_preferred":[
        "\u00d8ttum"
    ],
    "name:nor_x_variant":[
        "\u00d6ttum"
    ],
    "name:swe_x_preferred":[
        "\u00d6ttum"
    ],
    "qs_pg:aaroncc":"SE",
    "qs_pg:gn_country":"SE",
    "qs_pg:gn_fcode":"PPL",
    "qs_pg:gn_pop":0,
    "qs_pg:name":"\u00d6ttum",
    "qs_pg:name_adm0":"Sverige",
    "qs_pg:name_adm1":"V\u00e4stra G\u00f6talands L\u00e4n",
    "qs_pg:photos_9k":1,
    "qs_pg:photos_9r":1,
    "qs_pg:photos_all":1,
    "qs_pg:photos_sr":0,
    "qs_pg:pop_sr":0,
    "qs_pg:qs_pg_placetype":"locality",
    "qs_pg:qs_pg_placetype_gp":"Town",
    "qs_pg:woe_adm0":23424954,
    "woe:adm0_id":23424954,
    "woe:name_adm0":"Sverige",
    "woe:name_adm1":"V\u00e4stra G\u00f6talands L\u00e4n",
    "woe:placetype":"Town",
    "wof:name":"\u00d6ttum",
    "wof:placetype":"locality"
},
  "geometry": {"coordinates":[13.21667,58.31667],"type":"Point"}
}