{
  "type": "Feature",
  "properties": {
    "gn:admin1_code":"24.0",
    "gn:admin2_code":"2284.0",
    "gn:asciiname":"Getingstabodum",
    "gn:country_code":"SE",
    "gn:dem":107,
    "gn:feature_class":"P",
    "gn:feature_code":"PPL",
    "gn:name":"Getingstabodum",
    "gn:population":0,
    "gn:timezone":"Europe/Stockholm",
    "iso:country":"SE",
    "wof:name":"Getingstabodum",
    "wof:placetype":"locality"
},
  "geometry": {"coordinates":[18.71667,63.51667],"type":"Point"}
}