{
  "type": "Feature",
  "properties": {
    "gn:admin1_code":"28.0",
    "gn:admin2_code":"1461.0",
    "gn:asciiname":"Palbon",
    "gn:country_code":"SE",
    "gn:dem":63,
    "gn:feature_class":"P",
    "gn:feature_code":"PPL",
    "gn:name":"P\u00e5lb\u00f6n",
    "gn:population":0,
    "gn:timezone":"Europe/Stockholm",
    "iso:country":"SE",
    "name:nor_x_preferred":[
        "P\u00e5lb\u00f6n"
    ],
    "name:nor_x_variant":[
        "P\u00e5lb\u00f8n"
    ],
    "name:und_x_variant":[
        "P\u00e5lb\u00f6n"
    ],
    "wof:name":"Palbon",
    "wof:placetype":"locality"
},
  "geometry": {"coordinates":[12.43333,58.66667],"type":"Point"}
}