{
  "type": "Feature",
  "properties": {
    "gn:admin1_code":"23.0",
    "gn:admin2_code":"2481.0",
    "gn:asciiname":"Karonsbo",
    "gn:country_code":"SE",
    "gn:dem":213,
    "gn:feature_class":"P",
    "gn:feature_code":"PPL",
    "gn:name":"Karonsbo",
    "gn:population":0,
    "gn:timezone":"Europe/Stockholm",
    "iso:country":"SE",
    "wof:name":"Karonsbo",
    "wof:placetype":"locality"
},
  "geometry": {"coordinates":[18.75,64.53333000000001],"type":"Point"}
}