{
  "type": "Feature",
  "properties": {
    "gn:gn_country":"SE",
    "gn:gn_fcode":"PPL",
    "gn:gn_pop":273,
    "gn:population":273,
    "iso:country":"SE",
    "name:ara_x_preferred":[
        "\u0647\u0648\u0644\u0648"
    ],
    "name:ast_x_preferred":[
        "Hulu"
    ],
    "name:azb_x_preferred":[
        "\u0647\u0648\u0644\u0648"
    ],
    "name:cat_x_preferred":[
        "Hulu"
    ],
    "name:cym_x_preferred":[
        "Hulu"
    ],
    "name:deu_x_preferred":[
        "Hulu"
    ],
    "name:ell_x_preferred":[
        "Hulu"
    ],
    "name:fas_x_preferred":[
        "\u0647\u0648\u0644\u0648"
    ],
    "name:fin_x_preferred":[
        "Hulu"
    ],
    "name:fra_x_preferred":[
        "Hulu"
    ],
    "name:heb_x_preferred":[
        "\u05d4\u05d5\u05dc\u05d5"
    ],
    "name:hun_x_preferred":[
        "Hulu"
    ],
    "name:ind_x_preferred":[
        "Hulu"
    ],
    "name:ita_x_preferred":[
        "Hulu"
    ],
    "name:jpn_x_preferred":[
        "Hulu"
    ],
    "name:lit_x_preferred":[
        "Hulu"
    ],
    "name:msa_x_preferred":[
        "Hulu"
    ],
    "name:nld_x_preferred":[
        "Hulu"
    ],
    "name:nor_x_preferred":[
        "Hulu"
    ],
    "name:por_x_preferred":[
        "Hulu"
    ],
    "name:rus_x_preferred":[
        "Hulu"
    ],
    "name:spa_x_preferred":[
        "Hulu"
    ],
    "name:srp_x_preferred":[
        "\u0425\u0443\u043b\u0443"
    ],
    "name:swe_x_preferred":[
        "Hulu"
    ],
    "name:tur_x_preferred":[
        "Hulu"
    ],
    "name:ukr_x_preferred":[
        "Hulu"
    ],
    "name:vie_x_preferred":[
        "Hulu"
    ],
    "name:zho_x_preferred":[
        "Hulu"
    ],
    "qs_pg:aaroncc":"SE",
    "qs_pg:gn_country":"SE",
    "qs_pg:gn_fcode":"PPL",
    "qs_pg:gn_pop":273,
    "qs_pg:name":"Hulu",
    "qs_pg:photos_9r":0,
    "qs_pg:photos_sr":0,
    "qs_pg:pop_sr":2,
    "qs_pg:qs_pg_placetype":"locality",
    "wof:name":"Hulu",
    "wof:placetype":"locality",
    "wof:population":273
},
  "geometry": {"coordinates":[14.63333,57.88333],"type":"Point"}
}