{
  "type": "Feature",
  "properties": {
    "gn:gn_country":"SE",
    "gn:gn_fcode":"PPL",
    "gn:gn_pop":230,
    "gn:population":230,
    "iso:country":"SE",
    "name:bul_x_preferred":[
        "\u0423\u043b\u0430\u0442\u0438"
    ],
    "name:ceb_x_preferred":[
        "Ullatti"
    ],
    "name:dan_x_preferred":[
        "Ullatti"
    ],
    "name:deu_x_preferred":[
        "Ullatti"
    ],
    "name:eng_x_preferred":[
        "Ullatti"
    ],
    "name:fra_x_preferred":[
        "Ullatti"
    ],
    "name:ita_x_preferred":[
        "Ullatti"
    ],
    "name:nan_x_preferred":[
        "Ullatti"
    ],
    "name:nds_x_preferred":[
        "Ullatti"
    ],
    "name:nld_x_preferred":[
        "Ullatti"
    ],
    "name:nno_x_preferred":[
        "Ullatti"
    ],
    "name:nob_x_preferred":[
        "Ullatti"
    ],
    "name:pol_x_preferred":[
        "Ullatti"
    ],
    "name:swe_x_preferred":[
        "Ullatti"
    ],
    "name:unk_x_variant":[
        "Ulatti"
    ],
    "qs_pg:aaroncc":"SE",
    "qs_pg:gn_country":"SE",
    "qs_pg:gn_fcode":"PPL",
    "qs_pg:gn_pop":230,
    "qs_pg:name":"Ullatti",
    "qs_pg:name_adm0":"Sverige",
    "qs_pg:name_adm1":"Norrbottens L\u00e4n",
    "qs_pg:photos_9k":1,
    "qs_pg:photos_9r":1,
    "qs_pg:photos_all":2,
    "qs_pg:photos_sr":0,
    "qs_pg:pop_sr":2,
    "qs_pg:qs_pg_placetype":"locality",
    "qs_pg:qs_pg_placetype_gp":"Town",
    "qs_pg:woe_adm0":23424954,
    "woe:adm0_id":23424954,
    "woe:name_adm0":"Sverige",
    "woe:name_adm1":"Norrbottens L\u00e4n",
    "woe:placetype":"Town",
    "wof:name":"Ullatti",
    "wof:placetype":"locality",
    "wof:population":230
},
  "geometry": {"coordinates":[21.81667,67.01667],"type":"Point"}
}