{
  "type": "Feature",
  "properties": {
    "gn:admin1_code":"8.0",
    "gn:admin2_code":"665.0",
    "gn:asciiname":"Ljungberg",
    "gn:country_code":"SE",
    "gn:dem":269,
    "gn:feature_class":"P",
    "gn:feature_code":"PPL",
    "gn:name":"Ljungberg",
    "gn:population":0,
    "gn:timezone":"Europe/Stockholm",
    "iso:country":"SE",
    "name:deu_x_preferred":[
        "Ljungberg"
    ],
    "name:fin_x_preferred":[
        "Ljungberg"
    ],
    "name:nld_x_preferred":[
        "Ljungberg"
    ],
    "name:rus_x_preferred":[
        "\u042e\u043d\u0433\u0431\u0435\u0440\u0433"
    ],
    "name:swe_x_preferred":[
        "Ljungberg"
    ],
    "name:ukr_x_preferred":[
        "\u042e\u043d\u0433\u0431\u0435\u0440\u0433"
    ],
    "wof:name":"Ljungberg",
    "wof:placetype":"locality"
},
  "geometry": {"coordinates":[13.98333,57.43333000000001],"type":"Point"}
}