{
  "type": "Feature",
  "properties": {
    "gn:admin1_code":"3.0",
    "gn:admin2_code":"2184.0",
    "gn:asciiname":"Fagerstrand",
    "gn:country_code":"SE",
    "gn:dem":10,
    "gn:feature_class":"P",
    "gn:feature_code":"PPL",
    "gn:name":"Fagerstrand",
    "gn:population":0,
    "gn:timezone":"Europe/Stockholm",
    "iso:country":"SE",
    "wof:name":"Fagerstrand",
    "wof:placetype":"locality"
},
  "geometry": {"coordinates":[17.2645,61.8081],"type":"Point"}
}