{
  "type": "Feature",
  "properties": {
    "gn:admin1_code":"3.0",
    "gn:admin2_code":"2184.0",
    "gn:asciiname":"Fagerstrand",
    "gn:country_code":"SE",
    "gn:dem":10,
    "gn:feature_class":"P",
    "gn:feature_code":"PPL",
    "gn:name":"Fagerstrand",
    "gn:population":0,
    "gn:timezone":"Europe/Stockholm",
    "iso:country":"SE",
    "name:ceb_x_preferred":[
        "Fagerstrand"
    ],
    "name:jav_x_preferred":[
        "Fagerstrand"
    ],
    "name:msa_x_preferred":[
        "Fagerstrand"
    ],
    "name:nld_x_preferred":[
        "Fagerstrand"
    ],
    "name:nno_x_preferred":[
        "Fagerstrand"
    ],
    "name:nor_x_preferred":[
        "Fagerstrand"
    ],
    "name:ron_x_preferred":[
        "Fagerstrand"
    ],
    "name:spa_x_preferred":[
        "Fagerstrand"
    ],
    "name:swe_x_preferred":[
        "Fagerstrand"
    ],
    "name:urd_x_preferred":[
        "\u0641\u0627\u06af\u06cc\u0631\u0633\u0679\u0631\u0627\u0646\u0688"
    ],
    "name:vie_x_preferred":[
        "Fagerstrand"
    ],
    "wof:name":"Fagerstrand",
    "wof:placetype":"locality"
},
  "geometry": {"coordinates":[17.2645,61.8081],"type":"Point"}
}