{
  "type": "Feature",
  "properties": {
    "gn:admin1_code":"10.0",
    "gn:admin2_code":"2021.0",
    "gn:asciiname":"Snoborg",
    "gn:country_code":"SE",
    "gn:dem":229,
    "gn:feature_class":"P",
    "gn:feature_code":"PPL",
    "gn:name":"Sn\u00f6borg",
    "gn:population":0,
    "gn:timezone":"Europe/Stockholm",
    "iso:country":"SE",
    "name:nor_x_preferred":[
        "Sn\u00f6borg"
    ],
    "name:nor_x_variant":[
        "Sn\u00f8borg"
    ],
    "name:und_x_variant":[
        "Sn\u00f6borg"
    ],
    "wof:name":"Snoborg",
    "wof:placetype":"locality"
},
  "geometry": {"coordinates":[14.41667,60.53333000000001],"type":"Point"}
}