{
  "type": "Feature",
  "properties": {
    "gn:admin1_code":"18.0",
    "gn:admin2_code":"428.0",
    "gn:asciiname":"Katrineberg",
    "gn:country_code":"SE",
    "gn:dem":57,
    "gn:feature_class":"P",
    "gn:feature_code":"PPL",
    "gn:name":"Katrineberg",
    "gn:population":0,
    "gn:timezone":"Europe/Stockholm",
    "iso:country":"SE",
    "wof:name":"Katrineberg",
    "wof:placetype":"locality"
},
  "geometry": {"coordinates":[15.96667,58.98333],"type":"Point"}
}