{
  "type": "Feature",
  "properties": {
    "gn:admin1_code":"24.0",
    "gn:admin2_code":"2281.0",
    "gn:admin3_code":"228105.0",
    "gn:admin4_code":"2500.0",
    "gn:asciiname":"Norafors",
    "gn:country_code":"SE",
    "gn:dem":143,
    "gn:feature_class":"P",
    "gn:feature_code":"PPL",
    "gn:name":"Norafors",
    "gn:population":0,
    "gn:timezone":"Europe/Stockholm",
    "iso:country":"SE",
    "wof:name":"Norafors",
    "wof:placetype":"locality"
},
  "geometry": {"coordinates":[17.00272,62.49688],"type":"Point"}
}