{
  "type": "Feature",
  "properties": {
    "gn:admin1_code":"7.0",
    "gn:admin2_code":"2303.0",
    "gn:admin3_code":"230302.0",
    "gn:admin4_code":"2526.0",
    "gn:asciiname":"Utanede",
    "gn:country_code":"SE",
    "gn:dem":192,
    "gn:feature_class":"P",
    "gn:feature_code":"PPL",
    "gn:name":"Utanede",
    "gn:population":0,
    "gn:timezone":"Europe/Stockholm",
    "iso:country":"SE",
    "wof:name":"Utanede",
    "wof:placetype":"locality"
},
  "geometry": {"coordinates":[16.67791,62.96168],"type":"Point"}
}