{
  "type": "Feature",
  "properties": {
    "gn:admin1_code":"28.0",
    "gn:admin2_code":"1442.0",
    "gn:asciiname":"Horla",
    "gn:country_code":"SE",
    "gn:dem":137,
    "gn:feature_class":"P",
    "gn:feature_code":"PPL",
    "gn:name":"Horla",
    "gn:population":209,
    "gn:timezone":"Europe/Stockholm",
    "iso:country":"SE",
    "wof:name":"Horla",
    "wof:placetype":"locality",
    "wof:population":209
},
  "geometry": {"coordinates":[12.71667,57.96666999999999],"type":"Point"}
}