{
  "type": "Feature",
  "properties": {
    "gn:admin1_code":"10.0",
    "gn:admin2_code":"2084.0",
    "gn:asciiname":"Bollsjo",
    "gn:country_code":"SE",
    "gn:dem":65,
    "gn:feature_class":"P",
    "gn:feature_code":"PPL",
    "gn:name":"Bollsj\u00f6",
    "gn:population":0,
    "gn:timezone":"Europe/Stockholm",
    "iso:country":"SE",
    "name:nor_x_preferred":[
        "Bollsj\u00f6"
    ],
    "name:nor_x_variant":[
        "Bollsj\u00f8"
    ],
    "wof:name":"Bollsjo",
    "wof:placetype":"locality"
},
  "geometry": {"coordinates":[16.31667,60.16667],"type":"Point"}
}