{
  "type": "Feature",
  "properties": {
    "gn:admin1_code":"24.0",
    "gn:admin2_code":"2260.0",
    "gn:admin3_code":"226004.0",
    "gn:admin4_code":"2502.0",
    "gn:asciiname":"Hampsanke",
    "gn:country_code":"SE",
    "gn:dem":62,
    "gn:feature_class":"P",
    "gn:feature_code":"PPL",
    "gn:name":"Hamps\u00e4nke",
    "gn:population":0,
    "gn:timezone":"Europe/Stockholm",
    "iso:country":"SE",
    "wof:name":"Hampsanke",
    "wof:placetype":"locality"
},
  "geometry": {"coordinates":[16.26024,62.48853],"type":"Point"}
}