{
  "type": "Feature",
  "properties": {
    "gn:admin1_code":"23.0",
    "gn:admin2_code":"2421.0",
    "gn:asciiname":"Tarnamo",
    "gn:country_code":"SE",
    "gn:dem":471,
    "gn:feature_class":"P",
    "gn:feature_code":"PPL",
    "gn:name":"T\u00e4rnamo",
    "gn:population":0,
    "gn:timezone":"Europe/Stockholm",
    "iso:country":"SE",
    "wof:name":"Tarnamo",
    "wof:placetype":"locality"
},
  "geometry": {"coordinates":[15.13333,65.65000000000001],"type":"Point"}
}