{
  "type": "Feature",
  "properties": {
    "gn:admin1_code":"18.0",
    "gn:admin2_code":"461.0",
    "gn:asciiname":"Kolke",
    "gn:country_code":"SE",
    "gn:dem":12,
    "gn:feature_class":"P",
    "gn:feature_code":"PPL",
    "gn:name":"Kolke",
    "gn:population":0,
    "gn:timezone":"Europe/Stockholm",
    "iso:country":"SE",
    "wof:name":"Kolke",
    "wof:placetype":"locality"
},
  "geometry": {"coordinates":[17.23333,59.06667],"type":"Point"}
}