{
  "type": "Feature",
  "properties": {
    "gn:admin1_code":"12.0",
    "gn:admin2_code":"781.0",
    "gn:asciiname":"Vedasa",
    "gn:country_code":"SE",
    "gn:dem":158,
    "gn:feature_class":"P",
    "gn:feature_code":"PPL",
    "gn:name":"Ved\u00e5sa",
    "gn:population":0,
    "gn:timezone":"Europe/Stockholm",
    "iso:country":"SE",
    "wof:name":"Vedasa",
    "wof:placetype":"locality"
},
  "geometry": {"coordinates":[14.16667,56.71666999999999],"type":"Point"}
}