{
  "type": "Feature",
  "properties": {
    "gn:admin1_code":"12.0",
    "gn:admin2_code":"780.0",
    "gn:asciiname":"Norra Helgo",
    "gn:cc2":"SE",
    "gn:country_code":"SE",
    "gn:dem":161,
    "gn:feature_class":"P",
    "gn:feature_code":"PPL",
    "gn:name":"Norra Helg\u00f6",
    "gn:population":0,
    "gn:timezone":"Europe/Stockholm",
    "iso:country":"SE",
    "name:nor_x_preferred":[
        "Norra Helg\u00f6"
    ],
    "name:nor_x_variant":[
        "Norra Helg\u00f8"
    ],
    "name:und_x_variant":[
        "Helg\u00f6"
    ],
    "wof:name":"Norra Helgo",
    "wof:placetype":"locality"
},
  "geometry": {"coordinates":[14.75,56.96666999999999],"type":"Point"}
}