{
  "type": "Feature",
  "properties": {
    "gn:admin1_code":"10.0",
    "gn:admin2_code":"2085.0",
    "gn:asciiname":"Norra Vastansjo",
    "gn:country_code":"SE",
    "gn:dem":171,
    "gn:feature_class":"P",
    "gn:feature_code":"PPL",
    "gn:name":"Norra V\u00e4stansj\u00f6",
    "gn:population":0,
    "gn:timezone":"Europe/Stockholm",
    "iso:country":"SE",
    "wof:name":"Norra Vastansjo",
    "wof:placetype":"locality"
},
  "geometry": {"coordinates":[14.95,60.25],"type":"Point"}
}