{
  "type": "Feature",
  "properties": {
    "gn:admin1_code":"9.0",
    "gn:admin2_code":"821.0",
    "gn:asciiname":"Gillberga",
    "gn:country_code":"SE",
    "gn:dem":94,
    "gn:feature_class":"P",
    "gn:feature_code":"PPL",
    "gn:name":"Gillberga",
    "gn:population":0,
    "gn:timezone":"Europe/Stockholm",
    "iso:country":"SE",
    "name:nld_x_preferred":[
        "Gillberga"
    ],
    "name:swe_x_preferred":[
        "Gillberga"
    ],
    "wof:name":"Gillberga",
    "wof:placetype":"locality"
},
  "geometry": {"coordinates":[16.06667,57.13333000000001],"type":"Point"}
}