{
  "type": "Feature",
  "properties": {
    "gn:admin1_code":"12.0",
    "gn:admin2_code":"763.0",
    "gn:asciiname":"Bjornalycke",
    "gn:country_code":"SE",
    "gn:dem":163,
    "gn:feature_class":"P",
    "gn:feature_code":"PPL",
    "gn:name":"Bj\u00f6rnalycke",
    "gn:population":0,
    "gn:timezone":"Europe/Stockholm",
    "iso:country":"SE",
    "name:nor_x_preferred":[
        "Bj\u00f6rnalycke"
    ],
    "name:nor_x_variant":[
        "Bj\u00f8rnalycke"
    ],
    "wof:name":"Bjornalycke",
    "wof:placetype":"locality"
},
  "geometry": {"coordinates":[15.05,56.58333],"type":"Point"}
}