{
  "type": "Feature",
  "properties": {
    "gn:admin1_code":"25.0",
    "gn:admin2_code":"1980.0",
    "gn:asciiname":"Frandesta",
    "gn:country_code":"SE",
    "gn:dem":41,
    "gn:feature_class":"P",
    "gn:feature_code":"PPL",
    "gn:name":"Fr\u00e4ndesta",
    "gn:population":0,
    "gn:timezone":"Europe/Stockholm",
    "iso:country":"SE",
    "wof:name":"Frandesta",
    "wof:placetype":"locality"
},
  "geometry": {"coordinates":[16.53333,59.71666999999999],"type":"Point"}
}