{
  "type": "Feature",
  "properties": {
    "gn:admin1_code":"3.0",
    "gn:admin2_code":"2132.0",
    "gn:asciiname":"Ostana",
    "gn:country_code":"SE",
    "gn:dem":70,
    "gn:feature_class":"P",
    "gn:feature_code":"PPL",
    "gn:name":"\u00d6stan\u00e5",
    "gn:population":0,
    "gn:timezone":"Europe/Stockholm",
    "iso:country":"SE",
    "name:nor_x_preferred":[
        "\u00d6stan\u00e5"
    ],
    "name:nor_x_variant":[
        "\u00d8stan\u00e5"
    ],
    "name:und_x_variant":[
        "\u00d6stan\u00e5"
    ],
    "wof:name":"Ostana",
    "wof:placetype":"locality"
},
  "geometry": {"coordinates":[17.06667,61.85],"type":"Point"}
}