{
  "type": "Feature",
  "properties": {
    "gn:admin1_code":"3.0",
    "gn:admin2_code":"2132.0",
    "gn:asciiname":"Ostana",
    "gn:country_code":"SE",
    "gn:dem":70,
    "gn:feature_class":"P",
    "gn:feature_code":"PPL",
    "gn:name":"\u00d6stan\u00e5",
    "gn:population":0,
    "gn:timezone":"Europe/Stockholm",
    "iso:country":"SE",
    "name:azb_x_preferred":[
        "\u0627\u0648\u0633\u062a\u0627\u0646\u0627"
    ],
    "name:bel_x_preferred":[
        "\u0410\u0441\u0442\u0430\u043d\u0430"
    ],
    "name:bul_x_preferred":[
        "\u041e\u0441\u0442\u0430\u043d\u0430"
    ],
    "name:cat_x_preferred":[
        "Ostana"
    ],
    "name:ceb_x_preferred":[
        "Ostana"
    ],
    "name:deu_x_preferred":[
        "Ostana"
    ],
    "name:epo_x_preferred":[
        "Ostana"
    ],
    "name:est_x_preferred":[
        "Ostana"
    ],
    "name:eus_x_preferred":[
        "Ostana"
    ],
    "name:fas_x_preferred":[
        "\u0627\u0648\u0633\u062a\u0627\u0646\u0627"
    ],
    "name:fin_x_preferred":[
        "Ostana"
    ],
    "name:fra_x_preferred":[
        "Ostana"
    ],
    "name:hun_x_preferred":[
        "Ostana"
    ],
    "name:hye_x_preferred":[
        "\u0555\u057d\u057f\u0561\u0576\u0561"
    ],
    "name:ind_x_preferred":[
        "Ostana"
    ],
    "name:ita_x_preferred":[
        "Ostana"
    ],
    "name:jpn_x_preferred":[
        "\u30aa\u30b9\u30bf\u30fc\u30ca"
    ],
    "name:kaz_x_preferred":[
        "\u041e\u0441\u0442\u0430\u043d\u0430"
    ],
    "name:lat_x_preferred":[
        "Augustana"
    ],
    "name:lmo_x_preferred":[
        "Ostana"
    ],
    "name:msa_x_preferred":[
        "Ostana"
    ],
    "name:nap_x_preferred":[
        "Ostana"
    ],
    "name:nld_x_preferred":[
        "Ostana"
    ],
    "name:nor_x_preferred":[
        "\u00d6stan\u00e5"
    ],
    "name:nor_x_variant":[
        "\u00d8stan\u00e5"
    ],
    "name:oci_x_preferred":[
        "Ostana"
    ],
    "name:pms_x_preferred":[
        "Ostan-a"
    ],
    "name:pol_x_preferred":[
        "Ostana"
    ],
    "name:por_x_preferred":[
        "Ostana"
    ],
    "name:ron_x_preferred":[
        "Ostana"
    ],
    "name:rus_x_preferred":[
        "\u041e\u0441\u0442\u0430\u043d\u0430"
    ],
    "name:scn_x_preferred":[
        "Ostana"
    ],
    "name:spa_x_preferred":[
        "Ostana"
    ],
    "name:srp_x_preferred":[
        "\u041e\u0441\u0442\u0430\u043d\u0430"
    ],
    "name:tgl_x_preferred":[
        "Ostana"
    ],
    "name:ukr_x_preferred":[
        "\u041e\u0441\u0442\u0430\u043d\u0430"
    ],
    "name:uzb_x_preferred":[
        "Ostana"
    ],
    "name:vie_x_preferred":[
        "Ostana"
    ],
    "name:vol_x_preferred":[
        "Ostana"
    ],
    "name:war_x_preferred":[
        "Ostana"
    ],
    "name:zho_x_preferred":[
        "\u5965\u65af\u5854\u7eb3"
    ],
    "wof:name":"Ostana",
    "wof:placetype":"locality"
},
  "geometry": {"coordinates":[17.06667,61.85],"type":"Point"}
}