{
  "type": "Feature",
  "properties": {
    "gn:admin1_code":"22.0",
    "gn:admin2_code":"1766.0",
    "gn:asciiname":"Anneborg",
    "gn:country_code":"SE",
    "gn:dem":262,
    "gn:feature_class":"P",
    "gn:feature_code":"PPL",
    "gn:name":"Anneborg",
    "gn:population":0,
    "gn:timezone":"Europe/Stockholm",
    "iso:country":"SE",
    "wof:name":"Anneborg",
    "wof:placetype":"locality"
},
  "geometry": {"coordinates":[12.88333,59.95],"type":"Point"}
}