{
  "type": "Feature",
  "properties": {
    "gn:gn_country":"SE",
    "gn:gn_fcode":"PPL",
    "gn:gn_pop":341,
    "gn:population":565,
    "iso:country":"SE",
    "name:deu_x_preferred":[
        "Yngsj\u00f6"
    ],
    "name:eng_x_preferred":[
        "Yngsj\u00f6"
    ],
    "name:fra_x_preferred":[
        "Yngsj\u00f6"
    ],
    "name:ita_x_preferred":[
        "Yngsj\u00f6"
    ],
    "name:nan_x_preferred":[
        "Yngsj\u00f6"
    ],
    "name:nld_x_preferred":[
        "Yngsj\u00f6"
    ],
    "name:nno_x_preferred":[
        "Yngsj\u00f6"
    ],
    "name:nob_x_preferred":[
        "Yngsj\u00f6"
    ],
    "name:nor_x_preferred":[
        "Yngsj\u00f8"
    ],
    "name:nor_x_variant":[
        "Yngsj\u00f6"
    ],
    "name:pol_x_preferred":[
        "Yngsj\u00f6"
    ],
    "name:swe_x_preferred":[
        "Yngsj\u00f6"
    ],
    "name:urd_x_preferred":[
        "\u06cc\u0646\u06af\u0633\u062c\u0648"
    ],
    "qs_pg:aaroncc":"SE",
    "qs_pg:gn_country":"SE",
    "qs_pg:gn_fcode":"PPL",
    "qs_pg:gn_pop":341,
    "qs_pg:name":"Yngsj\u00f6",
    "qs_pg:name_adm0":"Sverige",
    "qs_pg:name_adm1":"Sk\u00e5ne L\u00e4n",
    "qs_pg:photos":183,
    "qs_pg:photos_1k":37,
    "qs_pg:photos_9k":1,
    "qs_pg:photos_9r":4,
    "qs_pg:photos_all":183,
    "qs_pg:photos_sr":4,
    "qs_pg:pop_sr":2,
    "qs_pg:qs_pg_placetype":"locality",
    "qs_pg:qs_pg_placetype_gp":"Town",
    "qs_pg:woe_adm0":23424954,
    "woe:adm0_id":23424954,
    "woe:name_adm0":"Sverige",
    "woe:name_adm1":"Sk\u00e5ne L\u00e4n",
    "woe:placetype":"Town",
    "wof:name":"Yngsj\u00f6",
    "wof:placetype":"locality",
    "wof:population":565
},
  "geometry": {"coordinates":[14.21667,55.88333],"type":"Point"}
}