{
  "type": "Feature",
  "properties": {
    "iso:country":"SE",
    "name:dan_x_preferred":[
        "L\u00e5ngasand"
    ],
    "name:deu_x_preferred":[
        "L\u00e5ngasand"
    ],
    "name:eng_x_preferred":[
        "L\u00e5ngasand"
    ],
    "name:fra_x_preferred":[
        "L\u00e5ngasand"
    ],
    "name:nds_x_preferred":[
        "L\u00e5ngasand"
    ],
    "name:nld_x_preferred":[
        "L\u00e5ngasand"
    ],
    "name:nno_x_preferred":[
        "L\u00e5ngasand"
    ],
    "name:nob_x_preferred":[
        "L\u00e5ngasand"
    ],
    "name:swe_x_preferred":[
        "L\u00e5ngasand"
    ],
    "qs_pg:aaroncc":"SE",
    "qs_pg:name":"L\u00e5ngasand",
    "qs_pg:name_adm0":"Sverige",
    "qs_pg:name_adm1":"Hallands L\u00e4n",
    "qs_pg:photos":156,
    "qs_pg:photos_1k":32,
    "qs_pg:photos_9k":1,
    "qs_pg:photos_9r":4,
    "qs_pg:photos_all":156,
    "qs_pg:photos_sr":4,
    "qs_pg:pop_sr":0,
    "qs_pg:qs_pg_placetype":"locality",
    "qs_pg:qs_pg_placetype_gp":"Town",
    "qs_pg:woe_adm0":23424954,
    "woe:adm0_id":23424954,
    "woe:name_adm0":"Sverige",
    "woe:name_adm1":"Hallands L\u00e4n",
    "woe:placetype":"Town",
    "wof:name":"L\u00e5ngasand",
    "wof:placetype":"locality"
},
  "geometry": {"coordinates":[12.588497,56.8341955],"type":"Point"}
}