{
  "type": "Feature",
  "properties": {
    "gn:admin1_code":"27.0",
    "gn:admin2_code":"1284.0",
    "gn:asciiname":"Tunneberga",
    "gn:country_code":"SE",
    "gn:dem":2,
    "gn:feature_class":"P",
    "gn:feature_code":"PPL",
    "gn:name":"Tunneberga",
    "gn:population":0,
    "gn:timezone":"Europe/Stockholm",
    "iso:country":"SE",
    "wof:name":"Tunneberga",
    "wof:placetype":"locality"
},
  "geometry": {"coordinates":[12.66667,56.21666999999999],"type":"Point"}
}