{
  "type": "Feature",
  "properties": {
    "gn:admin1_code":"23.0",
    "gn:admin2_code":"2482.0",
    "gn:asciiname":"Nya Risliden",
    "gn:country_code":"SE",
    "gn:dem":268,
    "gn:feature_class":"P",
    "gn:feature_code":"PPL",
    "gn:name":"Nya Risliden",
    "gn:population":0,
    "gn:timezone":"Europe/Stockholm",
    "iso:country":"SE",
    "wof:name":"Nya Risliden",
    "wof:placetype":"locality"
},
  "geometry": {"coordinates":[20.31667,64.65000000000001],"type":"Point"}
}