{
  "type": "Feature",
  "properties": {
    "gn:admin1_code":"28.0",
    "gn:admin2_code":"1492.0",
    "gn:asciiname":"Ylingebol",
    "gn:cc2":"SE",
    "gn:country_code":"SE",
    "gn:dem":60,
    "gn:feature_class":"P",
    "gn:feature_code":"PPL",
    "gn:name":"Ylingebol",
    "gn:population":0,
    "gn:timezone":"Europe/Stockholm",
    "iso:country":"SE",
    "name:und_x_variant":[
        "Yllingebol",
        "Ylingebol"
    ],
    "wof:name":"Ylingebol",
    "wof:placetype":"locality"
},
  "geometry": {"coordinates":[12.56667,58.85],"type":"Point"}
}