{
  "type": "Feature",
  "properties": {
    "gn:admin1_code":"24.0",
    "gn:admin2_code":"2284.0",
    "gn:asciiname":"Varvsudden",
    "gn:country_code":"SE",
    "gn:dem":96,
    "gn:feature_class":"P",
    "gn:feature_code":"PPL",
    "gn:name":"Varvsudden",
    "gn:population":0,
    "gn:timezone":"Europe/Stockholm",
    "iso:country":"SE",
    "wof:name":"Varvsudden",
    "wof:placetype":"locality"
},
  "geometry": {"coordinates":[18.66667,63.21666999999999],"type":"Point"}
}