{
  "type": "Feature",
  "properties": {
    "gn:admin1_code":"10.0",
    "gn:admin2_code":"2081.0",
    "gn:admin3_code":"208103.0",
    "gn:admin4_code":"2386.0",
    "gn:asciiname":"Dalvik",
    "gn:country_code":"SE",
    "gn:dem":122,
    "gn:feature_class":"P",
    "gn:feature_code":"PPL",
    "gn:name":"Dalvik",
    "gn:population":0,
    "gn:timezone":"Europe/Stockholm",
    "iso:country":"SE",
    "name:ces_x_preferred":[
        "Dalvik"
    ],
    "name:deu_x_preferred":[
        "Dalvik"
    ],
    "name:fra_x_preferred":[
        "Dalvik"
    ],
    "name:nld_x_preferred":[
        "Dalvik"
    ],
    "name:pol_x_preferred":[
        "Dalvik"
    ],
    "name:slk_x_preferred":[
        "Dalvik"
    ],
    "name:swe_x_preferred":[
        "Dalvik"
    ],
    "wof:name":"Dalvik",
    "wof:placetype":"locality"
},
  "geometry": {"coordinates":[15.65251,60.4686],"type":"Point"}
}