{
  "type": "Feature",
  "properties": {
    "gn:admin1_code":"3.0",
    "gn:asciiname":"Vatnas",
    "gn:cc2":"SE",
    "gn:country_code":"SE",
    "gn:dem":-9999,
    "gn:feature_class":"P",
    "gn:feature_code":"PPL",
    "gn:name":"V\u00e5tn\u00e4s",
    "gn:population":0,
    "gn:timezone":"Europe/Stockholm",
    "iso:country":"SE",
    "name:und_x_variant":[
        "V\u00e5tn\u00e4sudde",
        "V\u00e5tn\u00e4s"
    ],
    "wof:name":"Vatnas",
    "wof:placetype":"locality"
},
  "geometry": {"coordinates":[17.21667,61.55],"type":"Point"}
}