{
  "type": "Feature",
  "properties": {
    "gn:admin1_code":"8.0",
    "gn:admin2_code":"686.0",
    "gn:asciiname":"Gynnesnot",
    "gn:cc2":"SE",
    "gn:country_code":"SE",
    "gn:dem":235,
    "gn:feature_class":"P",
    "gn:feature_code":"PPL",
    "gn:name":"Gynnesn\u00f6t",
    "gn:population":0,
    "gn:timezone":"Europe/Stockholm",
    "iso:country":"SE",
    "name:nor_x_preferred":[
        "Gynnesn\u00f6t"
    ],
    "name:nor_x_variant":[
        "Gynnesn\u00f8t"
    ],
    "name:und_x_variant":[
        "Gynnersn\u00e4s"
    ],
    "wof:name":"Gynnesnot",
    "wof:placetype":"locality"
},
  "geometry": {"coordinates":[15.34084,57.57466],"type":"Point"}
}