{
  "type": "Feature",
  "properties": {
    "gn:admin1_code":"3.0",
    "gn:admin2_code":"2184.0",
    "gn:asciiname":"Alsjo",
    "gn:country_code":"SE",
    "gn:dem":229,
    "gn:feature_class":"P",
    "gn:feature_code":"PPL",
    "gn:name":"Alsj\u00f6",
    "gn:population":0,
    "gn:timezone":"Europe/Stockholm",
    "iso:country":"SE",
    "name:nor_x_preferred":[
        "Alsj\u00f6"
    ],
    "name:nor_x_variant":[
        "Alsj\u00f8"
    ],
    "wof:name":"Alsjo",
    "wof:placetype":"locality"
},
  "geometry": {"coordinates":[16.38332999999999,62.05],"type":"Point"}
}