{
  "type": "Feature",
  "properties": {
    "iso:country":"SE",
    "name:dan_x_preferred":[
        "Graversfors"
    ],
    "name:deu_x_preferred":[
        "Graversfors"
    ],
    "name:eng_x_preferred":[
        "Graversfors"
    ],
    "name:fra_x_preferred":[
        "Graversfors"
    ],
    "name:gle_x_preferred":[
        "Graversfors"
    ],
    "name:lld_x_preferred":[
        "Graversfors"
    ],
    "name:nan_x_preferred":[
        "Graversfors"
    ],
    "name:nds_x_preferred":[
        "Graversfors"
    ],
    "name:nld_x_preferred":[
        "Graversfors"
    ],
    "name:nno_x_preferred":[
        "Graversfors"
    ],
    "name:nob_x_preferred":[
        "Graversfors"
    ],
    "name:pol_x_preferred":[
        "Graversfors"
    ],
    "name:swe_x_preferred":[
        "Graversfors"
    ],
    "qs_pg:aaroncc":"SE",
    "qs_pg:name":"Graversfors",
    "qs_pg:name_adm0":"Sverige",
    "qs_pg:name_adm1":"\u00d6sterg\u00f6tlands L\u00e4n",
    "qs_pg:photos":15,
    "qs_pg:photos_1k":3,
    "qs_pg:photos_9k":1,
    "qs_pg:photos_9r":1,
    "qs_pg:photos_all":15,
    "qs_pg:photos_sr":1,
    "qs_pg:pop_sr":0,
    "qs_pg:qs_pg_placetype":"locality",
    "qs_pg:qs_pg_placetype_gp":"Town",
    "qs_pg:woe_adm0":23424954,
    "woe:adm0_id":23424954,
    "woe:name_adm0":"Sverige",
    "woe:name_adm1":"\u00d6sterg\u00f6tlands L\u00e4n",
    "woe:placetype":"Town",
    "wof:name":"Graversfors",
    "wof:placetype":"locality"
},
  "geometry": {"coordinates":[16.151189,58.721105],"type":"Point"}
}