{
  "type": "Feature",
  "properties": {
    "gn:admin1_code":"26.0",
    "gn:admin2_code":"123.0",
    "gn:asciiname":"Vaestra Jakobsberg",
    "gn:country_code":"SE",
    "gn:dem":39,
    "gn:feature_class":"P",
    "gn:feature_code":"PPL",
    "gn:name":"V\u00e4stra Jakobsberg",
    "gn:population":0,
    "gn:timezone":"Europe/Stockholm",
    "iso:country":"SE",
    "wof:name":"Vaestra Jakobsberg",
    "wof:placetype":"locality"
},
  "geometry": {"coordinates":[17.81244,59.42509],"type":"Point"}
}