{
  "type": "Feature",
  "properties": {
    "gn:admin1_code":"23.0",
    "gn:admin2_code":"2401.0",
    "gn:asciiname":"Haknas",
    "gn:country_code":"SE",
    "gn:dem":40,
    "gn:feature_class":"P",
    "gn:feature_code":"PPL",
    "gn:name":"H\u00e5kn\u00e4s",
    "gn:population":0,
    "gn:timezone":"Europe/Stockholm",
    "iso:country":"SE",
    "wof:name":"Haknas",
    "wof:placetype":"locality"
},
  "geometry": {"coordinates":[19.66667,63.56667],"type":"Point"}
}