{
  "type": "Feature",
  "properties": {
    "gn:admin1_code":"21.0",
    "gn:asciiname":"Huddungeby",
    "gn:country_code":"SE",
    "gn:dem":37,
    "gn:feature_class":"P",
    "gn:feature_code":"PPL",
    "gn:name":"Huddungeby",
    "gn:population":0,
    "gn:timezone":"Europe/Stockholm",
    "iso:country":"SE",
    "name:und_x_variant":[
        "Huddunge",
        "Huddungeby"
    ],
    "wof:name":"Huddungeby",
    "wof:placetype":"locality"
},
  "geometry": {"coordinates":[16.98333,60.05],"type":"Point"}
}