{
  "type": "Feature",
  "properties": {
    "gn:admin1_code":"23.0",
    "gn:admin2_code":"2480.0",
    "gn:asciiname":"Haggnas",
    "gn:country_code":"SE",
    "gn:dem":27,
    "gn:feature_class":"P",
    "gn:feature_code":"PPL",
    "gn:name":"H\u00e4ggn\u00e4s",
    "gn:population":0,
    "gn:timezone":"Europe/Stockholm",
    "iso:country":"SE",
    "wof:name":"Haggnas",
    "wof:placetype":"locality"
},
  "geometry": {"coordinates":[19.91667,63.68333000000001],"type":"Point"}
}