{
  "type": "Feature",
  "properties": {
    "gn:admin1_code":"10.0",
    "gn:admin2_code":"2039.0",
    "gn:asciiname":"Stromshogen",
    "gn:country_code":"SE",
    "gn:dem":672,
    "gn:feature_class":"P",
    "gn:feature_code":"PPL",
    "gn:name":"Str\u00f6msh\u00f6gen",
    "gn:population":0,
    "gn:timezone":"Europe/Stockholm",
    "iso:country":"SE",
    "name:nor_x_preferred":[
        "Str\u00f6msh\u00f6gen"
    ],
    "name:nor_x_variant":[
        "Str\u00f8msh\u00f8gen"
    ],
    "name:und_x_variant":[
        "Str\u00f6msh\u00f6gen"
    ],
    "wof:name":"Stromshogen",
    "wof:placetype":"locality"
},
  "geometry": {"coordinates":[12.21667,61.85],"type":"Point"}
}