{
  "type": "Feature",
  "properties": {
    "gn:admin1_code":"24.0",
    "gn:admin2_code":"2284.0",
    "gn:admin3_code":"228408.0",
    "gn:admin4_code":"2489.0",
    "gn:asciiname":"OEsteralnaes",
    "gn:country_code":"SE",
    "gn:dem":127,
    "gn:elevation":"50.0",
    "gn:feature_class":"P",
    "gn:feature_code":"PPL",
    "gn:name":"\u00d6steraln\u00e4s",
    "gn:population":0,
    "gn:timezone":"Europe/Stockholm",
    "iso:country":"SE",
    "name:und_x_variant":[
        "Aln\u00e4s",
        "\u00d6steraln\u00e4s"
    ],
    "wof:name":"OEsteralnaes",
    "wof:placetype":"locality"
},
  "geometry": {"coordinates":[18.5711,63.31087],"type":"Point"}
}