{
  "type": "Feature",
  "properties": {
    "gn:admin1_code":"15.0",
    "gn:admin2_code":"1885.0",
    "gn:asciiname":"Lovasen",
    "gn:country_code":"SE",
    "gn:dem":113,
    "gn:feature_class":"P",
    "gn:feature_code":"PPL",
    "gn:name":"L\u00f6v\u00e5sen",
    "gn:population":0,
    "gn:timezone":"Europe/Stockholm",
    "iso:country":"SE",
    "name:nor_x_preferred":[
        "L\u00f6v\u00e5sen"
    ],
    "name:nor_x_variant":[
        "L\u00f8v\u00e5sen"
    ],
    "wof:name":"Lovasen",
    "wof:placetype":"locality"
},
  "geometry": {"coordinates":[15.18333,59.63333000000001],"type":"Point"}
}