{
  "type": "Feature",
  "properties": {
    "gn:admin1_code":"23.0",
    "gn:admin2_code":"2404.0",
    "gn:asciiname":"Brannforssund",
    "gn:country_code":"SE",
    "gn:dem":234,
    "gn:feature_class":"P",
    "gn:feature_code":"PPL",
    "gn:name":"Br\u00e4nnforssund",
    "gn:population":0,
    "gn:timezone":"Europe/Stockholm",
    "iso:country":"SE",
    "wof:name":"Brannforssund",
    "wof:placetype":"locality"
},
  "geometry": {"coordinates":[19.36667000000001,64.65000000000001],"type":"Point"}
}