{
  "type": "Feature",
  "properties": {
    "gn:country":"SE",
    "gn:fcode":"PPL",
    "gn:population":0,
    "iso:country":"SE",
    "name:ceb_x_preferred":[
        "Ulrika"
    ],
    "name:dan_x_preferred":[
        "Ulrika"
    ],
    "name:deu_x_preferred":[
        "Ulrika"
    ],
    "name:eng_x_preferred":[
        "Ulrika"
    ],
    "name:fra_x_preferred":[
        "Ulrika"
    ],
    "name:ita_x_preferred":[
        "Ulrika"
    ],
    "name:lat_x_preferred":[
        "Ulrica"
    ],
    "name:nan_x_preferred":[
        "Ulrika"
    ],
    "name:nds_x_preferred":[
        "Ulrika"
    ],
    "name:nld_x_preferred":[
        "Ulrika"
    ],
    "name:nno_x_preferred":[
        "Ulrika"
    ],
    "name:nob_x_preferred":[
        "Ulrika"
    ],
    "name:swe_x_preferred":[
        "Ulrika"
    ],
    "qs_pg:aaroncc":"SE",
    "qs_pg:gn_country":"SE",
    "qs_pg:gn_fcode":"PPL",
    "qs_pg:gn_pop":0,
    "qs_pg:name":"Ulrika",
    "qs_pg:name_adm0":"Sverige",
    "qs_pg:name_adm1":"\u00d6sterg\u00f6tlands L\u00e4n",
    "qs_pg:photos":11,
    "qs_pg:photos_1k":2,
    "qs_pg:photos_9k":1,
    "qs_pg:photos_9r":1,
    "qs_pg:photos_all":11,
    "qs_pg:photos_sr":1,
    "qs_pg:pop_sr":0,
    "qs_pg:qs_pg_placetype":"locality",
    "qs_pg:qs_pg_placetype_gp":"Town",
    "qs_pg:woe_adm0":23424954,
    "woe:adm0_id":23424954,
    "woe:name_adm0":"Sverige",
    "woe:name_adm1":"\u00d6sterg\u00f6tlands L\u00e4n",
    "woe:placetype":"Town",
    "wof:name":"Ulrika",
    "wof:placetype":"locality",
    "wof:population":204
},
  "geometry": {"coordinates":[15.43333,58.11667],"type":"Point"}
}