{
  "type": "Feature",
  "properties": {
    "gn:admin1_code":"8.0",
    "gn:admin2_code":"685.0",
    "gn:asciiname":"Soragard",
    "gn:cc2":"SE",
    "gn:country_code":"SE",
    "gn:dem":238,
    "gn:feature_class":"P",
    "gn:feature_code":"PPL",
    "gn:name":"S\u00f6rag\u00e5rd",
    "gn:population":0,
    "gn:timezone":"Europe/Stockholm",
    "iso:country":"SE",
    "name:nor_x_preferred":[
        "S\u00f6rag\u00e5rd"
    ],
    "name:nor_x_variant":[
        "S\u00f8rag\u00e5rd"
    ],
    "name:und_x_variant":[
        "S\u00f6reg\u00e5rd",
        "S\u00f6rag\u00e5rd"
    ],
    "wof:name":"Soragard",
    "wof:placetype":"locality"
},
  "geometry": {"coordinates":[15.53333,57.53333000000001],"type":"Point"}
}