{
  "type": "Feature",
  "properties": {
    "gn:admin1_code":"22.0",
    "gn:admin2_code":"1765.0",
    "gn:asciiname":"Rok",
    "gn:country_code":"SE",
    "gn:dem":108,
    "gn:feature_class":"P",
    "gn:feature_code":"PPL",
    "gn:name":"R\u00f6k",
    "gn:population":0,
    "gn:timezone":"Europe/Stockholm",
    "iso:country":"SE",
    "name:nor_x_preferred":[
        "R\u00f6k"
    ],
    "name:nor_x_variant":[
        "R\u00f8k"
    ],
    "name:und_x_variant":[
        "R\u00f6k"
    ],
    "wof:name":"Rok",
    "wof:placetype":"locality"
},
  "geometry": {"coordinates":[12.38333,59.21666999999999],"type":"Point"}
}