{
  "type": "Feature",
  "properties": {
    "gn:admin1_code":"22.0",
    "gn:admin2_code":"1765.0",
    "gn:asciiname":"Rok",
    "gn:country_code":"SE",
    "gn:dem":108,
    "gn:feature_class":"P",
    "gn:feature_code":"PPL",
    "gn:name":"R\u00f6k",
    "gn:population":0,
    "gn:timezone":"Europe/Stockholm",
    "iso:country":"SE",
    "name:bre_x_preferred":[
        "Rok"
    ],
    "name:ces_x_preferred":[
        "Rok"
    ],
    "name:dan_x_preferred":[
        "Rok"
    ],
    "name:deu_x_preferred":[
        "Rok"
    ],
    "name:nld_x_preferred":[
        "Rok"
    ],
    "name:nor_x_preferred":[
        "R\u00f6k"
    ],
    "name:nor_x_variant":[
        "R\u00f8k"
    ],
    "name:slk_x_preferred":[
        "Rok"
    ],
    "name:spa_x_preferred":[
        "Rok"
    ],
    "name:szl_x_preferred":[
        "Rok"
    ],
    "name:uzb_x_preferred":[
        "Rok"
    ],
    "wof:name":"Rok",
    "wof:placetype":"locality"
},
  "geometry": {"coordinates":[12.38333,59.21666999999999],"type":"Point"}
}