{
  "type": "Feature",
  "properties": {
    "gn:admin1_code":"14.0",
    "gn:admin2_code":"2505.0",
    "gn:asciiname":"Jerfojaur",
    "gn:country_code":"SE",
    "gn:dem":428,
    "gn:feature_class":"P",
    "gn:feature_code":"PPL",
    "gn:name":"Jerfojaur",
    "gn:population":0,
    "gn:timezone":"Europe/Stockholm",
    "iso:country":"SE",
    "name:sju_x_preferred":[
        "Je\u00e4rffure"
    ],
    "name:swe_x_preferred":[
        "Jerfojaur"
    ],
    "wof:name":"Jerfojaur",
    "wof:placetype":"locality"
},
  "geometry": {"coordinates":[18.64761,65.9141],"type":"Point"}
}