{
  "type": "Feature",
  "properties": {
    "gn:admin1_code":"7.0",
    "gn:admin2_code":"2380.0",
    "gn:asciiname":"Nyby",
    "gn:country_code":"SE",
    "gn:dem":422,
    "gn:feature_class":"P",
    "gn:feature_code":"PPL",
    "gn:name":"Nyby",
    "gn:population":0,
    "gn:timezone":"Europe/Stockholm",
    "iso:country":"SE",
    "wof:name":"Nyby",
    "wof:placetype":"locality"
},
  "geometry": {"coordinates":[15.18333,63.33333],"type":"Point"}
}