{
  "type": "Feature",
  "properties": {
    "gn:admin1_code":"7.0",
    "gn:admin2_code":"2309.0",
    "gn:asciiname":"Axelasmoarna",
    "gn:cc2":"SE",
    "gn:country_code":"SE",
    "gn:dem":348,
    "gn:feature_class":"P",
    "gn:feature_code":"PPL",
    "gn:name":"Axel\u00e5smoarna",
    "gn:population":0,
    "gn:timezone":"Europe/Stockholm",
    "iso:country":"SE",
    "name:und_x_variant":[
        "Axel\u00e5sell",
        "Axel\u00e5smoarna"
    ],
    "wof:name":"Axelasmoarna",
    "wof:placetype":"locality"
},
  "geometry": {"coordinates":[14.75,63.71666999999999],"type":"Point"}
}