{
  "type": "Feature",
  "properties": {
    "gn:admin1_code":"24",
    "gn:admin2_code":"2262.0",
    "gn:admin3_code":"226201.0",
    "gn:admin4_code":"2501.0",
    "gn:asciiname":"Skyttberg",
    "gn:country_code":"SE",
    "gn:dem":17,
    "gn:feature_class":"P",
    "gn:feature_code":"PPL",
    "gn:name":"Skyttberg",
    "gn:population":0,
    "gn:timezone":"Europe/Stockholm",
    "iso:country":"SE",
    "wof:name":"Skyttberg",
    "wof:placetype":"locality"
},
  "geometry": {"coordinates":[17.31900000000001,62.47173000000001],"type":"Point"}
}