{
  "type": "Feature",
  "properties": {
    "gn:admin1_code":"26.0",
    "gn:admin2_code":"136.0",
    "gn:asciiname":"Guldboda",
    "gn:cc2":"SE",
    "gn:country_code":"SE",
    "gn:dem":14,
    "gn:feature_class":"P",
    "gn:feature_code":"PPL",
    "gn:name":"Guldboda",
    "gn:population":0,
    "gn:timezone":"Europe/Stockholm",
    "iso:country":"SE",
    "name:und_x_variant":[
        "Gullboda",
        "Guldboda"
    ],
    "wof:name":"Guldboda",
    "wof:placetype":"locality"
},
  "geometry": {"coordinates":[18.07056,58.97639],"type":"Point"}
}