{
  "type": "Feature",
  "properties": {
    "gn:admin1_code":"16.0",
    "gn:admin2_code":"561.0",
    "gn:asciiname":"Ondhult",
    "gn:cc2":"SE",
    "gn:country_code":"SE",
    "gn:dem":116,
    "gn:feature_class":"P",
    "gn:feature_code":"PPL",
    "gn:name":"\u00d6ndhult",
    "gn:population":0,
    "gn:timezone":"Europe/Stockholm",
    "iso:country":"SE",
    "name:nor_x_preferred":[
        "\u00d6ndhult"
    ],
    "name:nor_x_variant":[
        "\u00d8ndhult"
    ],
    "name:und_x_variant":[
        "\u00d6nhult"
    ],
    "wof:name":"Ondhult",
    "wof:placetype":"locality"
},
  "geometry": {"coordinates":[16.05,58.08333],"type":"Point"}
}