{
  "type": "Feature",
  "properties": {
    "gn:admin1_code":"22.0",
    "gn:admin2_code":"1765.0",
    "gn:asciiname":"Sundsbyn",
    "gn:country_code":"SE",
    "gn:dem":145,
    "gn:feature_class":"P",
    "gn:feature_code":"PPL",
    "gn:name":"Sundsbyn",
    "gn:population":0,
    "gn:timezone":"Europe/Stockholm",
    "iso:country":"SE",
    "wof:name":"Sundsbyn",
    "wof:placetype":"locality"
},
  "geometry": {"coordinates":[12.01667,59.23333],"type":"Point"}
}