{
  "type": "Feature",
  "properties": {
    "iso:country":"SE",
    "name:dan_x_preferred":[
        "Skalstugan"
    ],
    "name:eng_x_preferred":[
        "Skalstugan"
    ],
    "name:fra_x_preferred":[
        "Skalstugan"
    ],
    "name:nld_x_preferred":[
        "Skalstugan"
    ],
    "name:nob_x_preferred":[
        "Skalstugan"
    ],
    "name:swe_x_preferred":[
        "Skalstugan"
    ],
    "qs_pg:aaroncc":"SE",
    "qs_pg:name":"Skalstugan",
    "qs_pg:name_adm0":"Sverige",
    "qs_pg:name_adm1":"J\u00e4mtlands L\u00e4n",
    "qs_pg:photos":23,
    "qs_pg:photos_1k":5,
    "qs_pg:photos_9k":1,
    "qs_pg:photos_9r":1,
    "qs_pg:photos_all":23,
    "qs_pg:photos_sr":1,
    "qs_pg:pop_sr":0,
    "qs_pg:qs_pg_placetype":"locality",
    "qs_pg:qs_pg_placetype_gp":"Town",
    "qs_pg:woe_adm0":23424954,
    "woe:adm0_id":23424954,
    "woe:name_adm0":"Sverige",
    "woe:name_adm1":"J\u00e4mtlands L\u00e4n",
    "woe:placetype":"Town",
    "wof:name":"Skalstugan",
    "wof:placetype":"locality"
},
  "geometry": {"coordinates":[12.277221,63.568426],"type":"Point"}
}