{
  "type": "Feature",
  "properties": {
    "gn:admin1_code":"14.0",
    "gn:admin2_code":"2584.0",
    "gn:asciiname":"Rensjon",
    "gn:country_code":"SE",
    "gn:dem":493,
    "gn:feature_class":"P",
    "gn:feature_code":"PPL",
    "gn:name":"Rensj\u00f6n",
    "gn:population":0,
    "gn:timezone":"Europe/Stockholm",
    "iso:country":"SE",
    "name:nor_x_preferred":[
        "Rensj\u00f6n"
    ],
    "name:nor_x_variant":[
        "Rensj\u00f8n"
    ],
    "wof:name":"Rensjon",
    "wof:placetype":"locality"
},
  "geometry": {"coordinates":[19.8309,68.06881],"type":"Point"}
}