{
  "type": "Feature",
  "properties": {
    "gn:country":"SE",
    "gn:fcode":"PPL",
    "gn:population":254,
    "iso:country":"SE",
    "name:und_x_variant":[
        "Eda glasbruksamhalle"
    ],
    "qs_pg:aaroncc":"SE",
    "qs_pg:gn_country":"SE",
    "qs_pg:gn_fcode":"PPL",
    "qs_pg:gn_pop":254,
    "qs_pg:name":"Eda",
    "qs_pg:name_adm0":"Sverige",
    "qs_pg:name_adm1":"V\u00e4rmlands L\u00e4n",
    "qs_pg:photos":5,
    "qs_pg:photos_1k":1,
    "qs_pg:photos_9k":1,
    "qs_pg:photos_9r":1,
    "qs_pg:photos_all":5,
    "qs_pg:photos_sr":1,
    "qs_pg:pop_sr":2,
    "qs_pg:qs_pg_placetype":"locality",
    "qs_pg:qs_pg_placetype_gp":"Town",
    "qs_pg:woe_adm0":23424954,
    "woe:adm0_id":23424954,
    "woe:name_adm0":"Sverige",
    "woe:name_adm1":"V\u00e4rmlands L\u00e4n",
    "woe:placetype":"Town",
    "wof:name":"Eda",
    "wof:placetype":"locality",
    "wof:population":254
},
  "geometry": {"coordinates":[12.26667,59.91667],"type":"Point"}
}