{
  "type": "Feature",
  "properties": {
    "gn:admin1_code":"27.0",
    "gn:admin2_code":"1261.0",
    "gn:asciiname":"Lundakra",
    "gn:country_code":"SE",
    "gn:dem":-1,
    "gn:feature_class":"P",
    "gn:feature_code":"PPL",
    "gn:name":"Lund\u00e5kra",
    "gn:population":0,
    "gn:timezone":"Europe/Stockholm",
    "iso:country":"SE",
    "wof:name":"Lundakra",
    "wof:placetype":"locality"
},
  "geometry": {"coordinates":[12.95,55.78333000000001],"type":"Point"}
}