{
  "type": "Feature",
  "properties": {
    "gn:admin1_code":"27.0",
    "gn:admin2_code":"1273.0",
    "gn:asciiname":"Karhult",
    "gn:country_code":"SE",
    "gn:dem":141,
    "gn:feature_class":"P",
    "gn:feature_code":"PPL",
    "gn:name":"Karhult",
    "gn:population":0,
    "gn:timezone":"Europe/Stockholm",
    "iso:country":"SE",
    "wof:name":"Karhult",
    "wof:placetype":"locality"
},
  "geometry": {"coordinates":[14.08333,56.46666999999999],"type":"Point"}
}