{
  "type": "Feature",
  "properties": {
    "gn:country":"SE",
    "gn:fcode":"PPL",
    "gn:population":911,
    "iso:country":"SE",
    "name:bul_x_preferred":[
        "\u0420\u0443\u043d\u0434\u0432\u0438\u043a"
    ],
    "name:ceb_x_preferred":[
        "Rundvik"
    ],
    "name:eng_x_preferred":[
        "Rundvik"
    ],
    "name:ita_x_preferred":[
        "Rundvik"
    ],
    "name:nan_x_preferred":[
        "Rundvik"
    ],
    "name:nld_x_preferred":[
        "Rundvik"
    ],
    "name:nno_x_preferred":[
        "Rundvik"
    ],
    "name:nob_x_preferred":[
        "Rundvik"
    ],
    "name:swe_x_preferred":[
        "Rundvik"
    ],
    "qs_pg:aaroncc":"SE",
    "qs_pg:gn_country":"SE",
    "qs_pg:gn_fcode":"PPL",
    "qs_pg:gn_pop":911,
    "qs_pg:name":"Rundvik",
    "qs_pg:name_adm0":"Sverige",
    "qs_pg:name_adm1":"V\u00e4sterbottens L\u00e4n",
    "qs_pg:photos_9k":1,
    "qs_pg:photos_9r":1,
    "qs_pg:photos_all":4,
    "qs_pg:photos_sr":0,
    "qs_pg:pop_sr":2,
    "qs_pg:qs_pg_placetype":"locality",
    "qs_pg:qs_pg_placetype_gp":"Town",
    "qs_pg:woe_adm0":23424954,
    "woe:adm0_id":23424954,
    "woe:name_adm0":"Sverige",
    "woe:name_adm1":"V\u00e4sterbottens L\u00e4n",
    "woe:placetype":"Town",
    "wof:name":"Rundvik",
    "wof:placetype":"locality",
    "wof:population":810
},
  "geometry": {"coordinates":[19.43333,63.53333],"type":"Point"}
}