{
  "type": "Feature",
  "properties": {
    "gn:admin1_code":"28.0",
    "gn:admin2_code":"1493.0",
    "gn:asciiname":"Dyrenas",
    "gn:country_code":"SE",
    "gn:dem":116,
    "gn:feature_class":"P",
    "gn:feature_code":"PPL",
    "gn:name":"Dyren\u00e4s",
    "gn:population":0,
    "gn:timezone":"Europe/Stockholm",
    "iso:country":"SE",
    "wof:name":"Dyrenas",
    "wof:placetype":"locality"
},
  "geometry": {"coordinates":[13.73333,58.58333],"type":"Point"}
}