{
  "type": "Feature",
  "properties": {
    "gn:admin1_code":"24.0",
    "gn:admin2_code":"2281.0",
    "gn:admin3_code":"228107.0",
    "gn:admin4_code":"2496.0",
    "gn:asciiname":"Fanbyn",
    "gn:country_code":"SE",
    "gn:dem":71,
    "gn:feature_class":"P",
    "gn:feature_code":"PPL",
    "gn:name":"Fanbyn",
    "gn:population":599,
    "gn:timezone":"Europe/Stockholm",
    "iso:country":"SE",
    "name:ita_x_preferred":[
        "Fanbyn"
    ],
    "name:nld_x_preferred":[
        "Fanbyn"
    ],
    "name:nno_x_preferred":[
        "Fanbyn"
    ],
    "name:nor_x_preferred":[
        "Fanbyn"
    ],
    "name:swe_x_preferred":[
        "Fanbyn"
    ],
    "name:und_x_variant":[
        "Fannbyn",
        "Fannby"
    ],
    "wof:name":"Fanbyn",
    "wof:placetype":"locality",
    "wof:population":599
},
  "geometry": {"coordinates":[16.58549,62.4074],"type":"Point"}
}