{
  "type": "Feature",
  "properties": {
    "gn:gn_country":"SE",
    "gn:gn_fcode":"PPL",
    "gn:gn_pop":862,
    "gn:population":829,
    "iso:country":"SE",
    "name:bul_x_preferred":[
        "\u0424\u0435\u0440\u044c\u043e\u0441\u0443\u043d\u0434"
    ],
    "name:ceb_x_preferred":[
        "F\u00e5r\u00f6sund"
    ],
    "name:deu_x_preferred":[
        "F\u00e5r\u00f6sund"
    ],
    "name:eng_x_preferred":[
        "F\u00e5r\u00f6sund"
    ],
    "name:fas_x_preferred":[
        "\u0641\u0648\u0631\u0634\u0648\u0646\u062f"
    ],
    "name:fin_x_preferred":[
        "F\u00e5r\u00f6sund"
    ],
    "name:fra_x_preferred":[
        "F\u00e5r\u00f6sund"
    ],
    "name:heb_x_preferred":[
        "\u05e4\u05d5\u05e8\u05d0\u05e1\u05d5\u05e0\u05d3"
    ],
    "name:ita_x_preferred":[
        "F\u00e5r\u00f6sund"
    ],
    "name:jpn_x_preferred":[
        "\u30d5\u30a9\u30fc\u30ec\u30b9\u30f3\u30c9"
    ],
    "name:nan_x_preferred":[
        "F\u00e5r\u00f6sund"
    ],
    "name:nld_x_preferred":[
        "F\u00e5r\u00f6sund"
    ],
    "name:nno_x_preferred":[
        "F\u00e5r\u00f6sund"
    ],
    "name:nob_x_preferred":[
        "F\u00e5r\u00f6sund"
    ],
    "name:nor_x_preferred":[
        "F\u00e5r\u00f8sund"
    ],
    "name:nor_x_variant":[
        "F\u00e5r\u00f6sund"
    ],
    "name:pol_x_preferred":[
        "F\u00e5r\u00f6sund"
    ],
    "name:por_x_preferred":[
        "F\u00e5r\u00f6sund"
    ],
    "name:swe_x_preferred":[
        "F\u00e5r\u00f6sund"
    ],
    "qs_pg:aaroncc":"SE",
    "qs_pg:gn_country":"SE",
    "qs_pg:gn_fcode":"PPL",
    "qs_pg:gn_pop":862,
    "qs_pg:name":"F\u00e5r\u00f6sund",
    "qs_pg:name_adm0":"Sverige",
    "qs_pg:name_adm1":"Gotlands L\u00e4n",
    "qs_pg:photos":470,
    "qs_pg:photos_1k":95,
    "qs_pg:photos_9k":2,
    "qs_pg:photos_9r":5,
    "qs_pg:photos_all":470,
    "qs_pg:photos_sr":7,
    "qs_pg:pop_sr":2,
    "qs_pg:qs_pg_placetype":"locality",
    "qs_pg:qs_pg_placetype_gp":"Town",
    "qs_pg:woe_adm0":23424954,
    "woe:adm0_id":23424954,
    "woe:name_adm0":"Sverige",
    "woe:name_adm1":"Gotlands L\u00e4n",
    "woe:placetype":"Town",
    "wof:name":"F\u00e5r\u00f6sund",
    "wof:placetype":"locality",
    "wof:population":829
},
  "geometry": {"coordinates":[19.05,57.86667],"type":"Point"}
}