{
  "type": "Feature",
  "properties": {
    "gn:gn_country":"SE",
    "gn:gn_fcode":"PPL",
    "gn:gn_pop":499,
    "gn:population":862,
    "iso:country":"SE",
    "name:bul_x_preferred":[
        "\u0410\u043b\u0433\u0443\u0442\u0441\u0440\u0443\u043c"
    ],
    "name:ceb_x_preferred":[
        "Algutsrum"
    ],
    "name:deu_x_preferred":[
        "Algutsrum"
    ],
    "name:eng_x_preferred":[
        "Algutsrum"
    ],
    "name:fas_x_preferred":[
        "\u0627\u0644\u06af\u0627\u062a\u0633\u0631\u0627\u0645"
    ],
    "name:fra_x_preferred":[
        "Algutsrum"
    ],
    "name:ita_x_preferred":[
        "Algutsrum"
    ],
    "name:nan_x_preferred":[
        "Algutsrum"
    ],
    "name:nld_x_preferred":[
        "Algutsrum"
    ],
    "name:nno_x_preferred":[
        "Algutsrum"
    ],
    "name:nob_x_preferred":[
        "Algutsrum"
    ],
    "name:swe_x_preferred":[
        "Algutsrum"
    ],
    "qs_pg:aaroncc":"SE",
    "qs_pg:gn_country":"SE",
    "qs_pg:gn_fcode":"PPL",
    "qs_pg:gn_pop":499,
    "qs_pg:name":"Algutsrum",
    "qs_pg:name_adm0":"Sverige",
    "qs_pg:name_adm1":"Kalmar L\u00e4n",
    "qs_pg:photos":41,
    "qs_pg:photos_1k":8,
    "qs_pg:photos_9k":1,
    "qs_pg:photos_9r":2,
    "qs_pg:photos_all":41,
    "qs_pg:photos_sr":2,
    "qs_pg:pop_sr":2,
    "qs_pg:qs_pg_placetype":"locality",
    "qs_pg:qs_pg_placetype_gp":"Town",
    "qs_pg:woe_adm0":23424954,
    "woe:adm0_id":23424954,
    "woe:name_adm0":"Sverige",
    "woe:name_adm1":"Kalmar L\u00e4n",
    "woe:placetype":"Town",
    "wof:name":"Algutsrum",
    "wof:placetype":"locality",
    "wof:population":862
},
  "geometry": {"coordinates":[16.51667,56.68333],"type":"Point"}
}