{
  "type": "Feature",
  "properties": {
    "gn:admin1_code":"23.0",
    "gn:admin2_code":"2417.0",
    "gn:asciiname":"Finnliden",
    "gn:country_code":"SE",
    "gn:dem":296,
    "gn:feature_class":"P",
    "gn:feature_code":"PPL",
    "gn:name":"Finnliden",
    "gn:population":0,
    "gn:timezone":"Europe/Stockholm",
    "iso:country":"SE",
    "wof:name":"Finnliden",
    "wof:placetype":"locality"
},
  "geometry": {"coordinates":[19.45,65.03333000000001],"type":"Point"}
}