{
  "type": "Feature",
  "properties": {
    "gn:admin1_code":"23.0",
    "gn:admin2_code":"2482.0",
    "gn:asciiname":"Tuvan",
    "gn:cc2":"SE",
    "gn:country_code":"SE",
    "gn:dem":27,
    "gn:feature_class":"P",
    "gn:feature_code":"PPL",
    "gn:name":"Tuvan",
    "gn:population":0,
    "gn:timezone":"Europe/Stockholm",
    "iso:country":"SE",
    "name:ceb_x_preferred":[
        "Tuvan"
    ],
    "name:ita_x_preferred":[
        "Tuvano"
    ],
    "name:jpn_x_preferred":[
        "\u30c8\u30a5\u30f4\u30a1\u30f3"
    ],
    "name:swe_x_preferred":[
        "Tuvan"
    ],
    "name:und_x_variant":[
        "Tufvan"
    ],
    "wof:name":"Tuvan",
    "wof:placetype":"locality"
},
  "geometry": {"coordinates":[21.03333,64.73333000000001],"type":"Point"}
}