{
  "type": "Feature",
  "properties": {
    "gn:admin1_code":"14.0",
    "gn:asciiname":"Pissiniemi",
    "gn:country_code":"SE",
    "gn:dem":190,
    "gn:feature_class":"P",
    "gn:feature_code":"PPL",
    "gn:name":"Pissiniemi",
    "gn:population":0,
    "gn:timezone":"Europe/Stockholm",
    "iso:country":"SE",
    "wof:name":"Pissiniemi",
    "wof:placetype":"locality"
},
  "geometry": {"coordinates":[23.55,67.58333],"type":"Point"}
}