{
  "type": "Feature",
  "properties": {
    "gn:admin1_code":"24.0",
    "gn:admin2_code":"2281.0",
    "gn:admin3_code":"228109.0",
    "gn:admin4_code":"2451.0",
    "gn:asciiname":"Sorlindsjo",
    "gn:cc2":"SE",
    "gn:country_code":"SE",
    "gn:dem":61,
    "gn:feature_class":"P",
    "gn:feature_code":"PPL",
    "gn:name":"S\u00f6rlindsj\u00f6",
    "gn:population":0,
    "gn:timezone":"Europe/Stockholm",
    "iso:country":"SE",
    "name:nor_x_preferred":[
        "S\u00f6rlindsj\u00f6"
    ],
    "name:nor_x_variant":[
        "S\u00f8rlindsj\u00f8"
    ],
    "name:und_x_variant":[
        "S\u00f6dra Lindsj\u00f6",
        "S\u00f6rlindsj\u00f6"
    ],
    "wof:name":"Sorlindsjo",
    "wof:placetype":"locality"
},
  "geometry": {"coordinates":[16.97903,62.27596],"type":"Point"}
}