{
  "type": "Feature",
  "properties": {
    "gn:admin1_code":"16.0",
    "gn:admin2_code":"582.0",
    "gn:asciiname":"Ekenaset",
    "gn:cc2":"SE",
    "gn:country_code":"SE",
    "gn:dem":1,
    "gn:feature_class":"P",
    "gn:feature_code":"PPL",
    "gn:name":"Eken\u00e4set",
    "gn:population":0,
    "gn:timezone":"Europe/Stockholm",
    "iso:country":"SE",
    "name:und_x_variant":[
        "Ekn\u00e4s",
        "Eken\u00e4set"
    ],
    "wof:name":"Ekenaset",
    "wof:placetype":"locality"
},
  "geometry": {"coordinates":[16.75,58.26667],"type":"Point"}
}