{
  "type": "Feature",
  "properties": {
    "gn:admin1_code":"3.0",
    "gn:admin2_code":"2132.0",
    "gn:asciiname":"Gnarps Masugn",
    "gn:cc2":"SE",
    "gn:country_code":"SE",
    "gn:dem":11,
    "gn:feature_class":"P",
    "gn:feature_code":"PPL",
    "gn:name":"Gnarps Masugn",
    "gn:population":0,
    "gn:timezone":"Europe/Stockholm",
    "iso:country":"SE",
    "name:und_x_variant":[
        "Gnarpsmasuga",
        "Gnarps Masugn"
    ],
    "wof:name":"Gnarps Masugn",
    "wof:placetype":"locality"
},
  "geometry": {"coordinates":[17.4125,62.03778000000001],"type":"Point"}
}