{
  "type": "Feature",
  "properties": {
    "gn:admin1_code":"9.0",
    "gn:admin2_code":"862.0",
    "gn:asciiname":"Parismala",
    "gn:country_code":"SE",
    "gn:dem":119,
    "gn:feature_class":"P",
    "gn:feature_code":"PPL",
    "gn:name":"Parism\u00e5la",
    "gn:population":0,
    "gn:timezone":"Europe/Stockholm",
    "iso:country":"SE",
    "wof:name":"Parismala",
    "wof:placetype":"locality"
},
  "geometry": {"coordinates":[15.48333,56.58333],"type":"Point"}
}