{
  "type": "Feature",
  "properties": {
    "iso:country":"SE",
    "wof:name":"Rannebergen",
    "wof:placetype":"neighbourhood"
},
  "geometry": {"coordinates":[12.07116579442813,57.80233947465408],"type":"Point"}
}