{
  "type": "Feature",
  "properties": {
    "gn:admin1_code":"21.0",
    "gn:admin2_code":"360.0",
    "gn:asciiname":"Falandbo",
    "gn:country_code":"SE",
    "gn:dem":29,
    "gn:feature_class":"P",
    "gn:feature_code":"PPL",
    "gn:name":"F\u00e4landbo",
    "gn:population":0,
    "gn:timezone":"Europe/Stockholm",
    "iso:country":"SE",
    "wof:name":"Falandbo",
    "wof:placetype":"locality"
},
  "geometry": {"coordinates":[17.81667000000001,60.33333],"type":"Point"}
}