{
  "type": "Feature",
  "properties": {
    "gn:admin1_code":"2.0",
    "gn:admin2_code":"1080.0",
    "gn:admin3_code":"108015.0",
    "gn:admin4_code":"992.0",
    "gn:asciiname":"Bjorkeryd",
    "gn:country_code":"SE",
    "gn:dem":40,
    "gn:feature_class":"P",
    "gn:feature_code":"PPL",
    "gn:name":"Bj\u00f6rkeryd",
    "gn:population":0,
    "gn:timezone":"Europe/Stockholm",
    "iso:country":"SE",
    "name:nld_x_preferred":[
        "Bj\u00f6rkeryd"
    ],
    "name:nor_x_preferred":[
        "Bj\u00f6rkeryd"
    ],
    "name:nor_x_variant":[
        "Bj\u00f8rkeryd"
    ],
    "name:swe_x_preferred":[
        "Bj\u00f6rkeryd"
    ],
    "name:und_x_variant":[
        "Bj\u00f6rkeryd"
    ],
    "wof:name":"Bjorkeryd",
    "wof:placetype":"locality"
},
  "geometry": {"coordinates":[15.509,56.26114000000001],"type":"Point"}
}