{
  "type": "Feature",
  "properties": {
    "gn:admin1_code":"28.0",
    "gn:admin2_code":"1485.0",
    "gn:asciiname":"Eriksberg",
    "gn:country_code":"SE",
    "gn:dem":29,
    "gn:feature_class":"P",
    "gn:feature_code":"PPL",
    "gn:name":"Eriksberg",
    "gn:population":0,
    "gn:timezone":"Europe/Stockholm",
    "iso:country":"SE",
    "name:ceb_x_preferred":[
        "Eriksberg"
    ],
    "name:nld_x_preferred":[
        "Eriksberg"
    ],
    "name:por_x_preferred":[
        "Eriksberg"
    ],
    "name:swe_x_preferred":[
        "Eriksberg"
    ],
    "wof:name":"Eriksberg",
    "wof:placetype":"locality"
},
  "geometry": {"coordinates":[11.61667,58.26667],"type":"Point"}
}