{
  "type": "Feature",
  "properties": {
    "gn:admin1_code":"2.0",
    "gn:admin2_code":"1080.0",
    "gn:admin3_code":"108010.0",
    "gn:admin4_code":"1017.0",
    "gn:asciiname":"Hastholmen",
    "gn:cc2":"SE",
    "gn:country_code":"SE",
    "gn:dem":10,
    "gn:feature_class":"P",
    "gn:feature_code":"PPL",
    "gn:name":"H\u00e4stholmen",
    "gn:population":0,
    "gn:timezone":"Europe/Stockholm",
    "iso:country":"SE",
    "name:und_x_variant":[
        "\u00d6stra H\u00e4stholmen",
        "H\u00e4stholmen"
    ],
    "wof:name":"Hastholmen",
    "wof:placetype":"locality"
},
  "geometry": {"coordinates":[15.76369,56.08038000000001],"type":"Point"}
}