{
  "type": "Feature",
  "properties": {
    "gn:admin1_code":"22.0",
    "gn:admin2_code":"1765.0",
    "gn:admin3_code":"176503.0",
    "gn:admin4_code":"2148.0",
    "gn:asciiname":"Gardtveten",
    "gn:country_code":"SE",
    "gn:dem":128,
    "gn:feature_class":"P",
    "gn:feature_code":"PPL",
    "gn:name":"G\u00e5rdtveten",
    "gn:population":0,
    "gn:timezone":"Europe/Stockholm",
    "iso:country":"SE",
    "wof:name":"Gardtveten",
    "wof:placetype":"locality"
},
  "geometry": {"coordinates":[11.90763,59.45847],"type":"Point"}
}