{
  "type": "Feature",
  "properties": {
    "gn:admin1_code":"15.0",
    "gn:admin2_code":"1860.0",
    "gn:asciiname":"Svenstorp",
    "gn:country_code":"SE",
    "gn:dem":182,
    "gn:feature_class":"P",
    "gn:feature_code":"PPL",
    "gn:name":"Svenstorp",
    "gn:population":0,
    "gn:timezone":"Europe/Stockholm",
    "iso:country":"SE",
    "name:ita_x_preferred":[
        "Svenstorp"
    ],
    "name:nld_x_preferred":[
        "Svenstorp"
    ],
    "name:nno_x_preferred":[
        "Svenstorp"
    ],
    "name:nor_x_preferred":[
        "Svenstorp"
    ],
    "name:swe_x_preferred":[
        "Svenstorp"
    ],
    "wof:name":"Svenstorp",
    "wof:placetype":"locality"
},
  "geometry": {"coordinates":[14.51667,58.73333],"type":"Point"}
}