{
  "type": "Feature",
  "properties": {
    "gn:admin1_code":"28.0",
    "gn:admin2_code":"1452.0",
    "gn:asciiname":"Morkhult",
    "gn:country_code":"SE",
    "gn:dem":207,
    "gn:feature_class":"P",
    "gn:feature_code":"PPL",
    "gn:name":"M\u00f6rkhult",
    "gn:population":0,
    "gn:timezone":"Europe/Stockholm",
    "iso:country":"SE",
    "name:nor_x_preferred":[
        "M\u00f6rkhult"
    ],
    "name:nor_x_variant":[
        "M\u00f8rkhult"
    ],
    "wof:name":"Morkhult",
    "wof:placetype":"locality"
},
  "geometry": {"coordinates":[13.33333,57.38333000000001],"type":"Point"}
}