{
  "type": "Feature",
  "properties": {
    "gn:admin1_code":"28.0",
    "gn:admin2_code":"1490.0",
    "gn:asciiname":"Ondered",
    "gn:country_code":"SE",
    "gn:dem":286,
    "gn:feature_class":"P",
    "gn:feature_code":"PPL",
    "gn:name":"\u00d6ndered",
    "gn:population":0,
    "gn:timezone":"Europe/Stockholm",
    "iso:country":"SE",
    "name:nor_x_preferred":[
        "\u00d6ndered"
    ],
    "name:nor_x_variant":[
        "\u00d8ndered"
    ],
    "wof:name":"Ondered",
    "wof:placetype":"locality"
},
  "geometry": {"coordinates":[12.83333,57.75],"type":"Point"}
}