{
  "type": "Feature",
  "properties": {
    "gn:admin1_code":"21.0",
    "gn:admin2_code":"360.0",
    "gn:asciiname":"Ubblixbo",
    "gn:country_code":"SE",
    "gn:dem":34,
    "gn:feature_class":"P",
    "gn:feature_code":"PPL",
    "gn:name":"Ubblixbo",
    "gn:population":0,
    "gn:timezone":"Europe/Stockholm",
    "iso:country":"SE",
    "wof:name":"Ubblixbo",
    "wof:placetype":"locality"
},
  "geometry": {"coordinates":[17.41667,60.21666999999999],"type":"Point"}
}