{
  "type": "Feature",
  "properties": {
    "gn:admin1_code":"7.0",
    "gn:admin2_code":"2380.0",
    "gn:asciiname":"Pallerasen",
    "gn:country_code":"SE",
    "gn:dem":353,
    "gn:feature_class":"P",
    "gn:feature_code":"PPL",
    "gn:name":"Paller\u00e5sen",
    "gn:population":0,
    "gn:timezone":"Europe/Stockholm",
    "iso:country":"SE",
    "wof:name":"Pallerasen",
    "wof:placetype":"locality"
},
  "geometry": {"coordinates":[14.91667,63.28333000000001],"type":"Point"}
}