{
  "type": "Feature",
  "properties": {
    "gn:admin1_code":"18.0",
    "gn:admin2_code":"461.0",
    "gn:asciiname":"Ormsta",
    "gn:country_code":"SE",
    "gn:dem":61,
    "gn:feature_class":"P",
    "gn:feature_code":"PPL",
    "gn:name":"Ormsta",
    "gn:population":0,
    "gn:timezone":"Europe/Stockholm",
    "iso:country":"SE",
    "wof:name":"Ormsta",
    "wof:placetype":"locality"
},
  "geometry": {"coordinates":[17.13332999999999,59.11666999999999],"type":"Point"}
}