{
  "type": "Feature",
  "properties": {
    "gn:admin1_code":"28.0",
    "gn:admin2_code":"1496.0",
    "gn:asciiname":"Djursatra",
    "gn:country_code":"SE",
    "gn:dem":123,
    "gn:feature_class":"P",
    "gn:feature_code":"PPL",
    "gn:name":"Djurs\u00e4tra",
    "gn:population":0,
    "gn:timezone":"Europe/Stockholm",
    "iso:country":"SE",
    "wof:name":"Djursatra",
    "wof:placetype":"locality"
},
  "geometry": {"coordinates":[14.06667,58.33333],"type":"Point"}
}