{
  "type": "Feature",
  "properties": {
    "gn:admin1_code":"12.0",
    "gn:admin2_code":"765.0",
    "gn:asciiname":"Kalvshult",
    "gn:country_code":"SE",
    "gn:dem":105,
    "gn:feature_class":"P",
    "gn:feature_code":"PPL",
    "gn:name":"Kalvshult",
    "gn:population":0,
    "gn:timezone":"Europe/Stockholm",
    "iso:country":"SE",
    "wof:name":"Kalvshult",
    "wof:placetype":"locality"
},
  "geometry": {"coordinates":[13.96667,56.46666999999999],"type":"Point"}
}