{
  "type": "Feature",
  "properties": {
    "gn:admin1_code":"7.0",
    "gn:admin2_code":"2313.0",
    "gn:asciiname":"Rorstrom",
    "gn:cc2":"SE",
    "gn:country_code":"SE",
    "gn:dem":273,
    "gn:feature_class":"P",
    "gn:feature_code":"PPL",
    "gn:name":"R\u00f6rstr\u00f6m",
    "gn:population":0,
    "gn:timezone":"Europe/Stockholm",
    "iso:country":"SE",
    "name:nor_x_preferred":[
        "R\u00f6rstr\u00f6m"
    ],
    "name:nor_x_variant":[
        "R\u00f8rstr\u00f8m"
    ],
    "name:und_x_variant":[
        "R\u00f6str\u00f6m",
        "R\u00f6rstr\u00f6m"
    ],
    "wof:name":"Rorstrom",
    "wof:placetype":"locality"
},
  "geometry": {"coordinates":[16.26667,64.16667],"type":"Point"}
}