{
  "type": "Feature",
  "properties": {
    "gn:admin1_code":"5.0",
    "gn:admin2_code":"980.0",
    "gn:asciiname":"Austre",
    "gn:country_code":"SE",
    "gn:dem":19,
    "gn:feature_class":"P",
    "gn:feature_code":"PPL",
    "gn:name":"Austre",
    "gn:population":0,
    "gn:timezone":"Europe/Stockholm",
    "iso:country":"SE",
    "wof:name":"Austre",
    "wof:placetype":"locality"
},
  "geometry": {"coordinates":[18.26154,56.94716999999999],"type":"Point"}
}