{
  "type": "Feature",
  "properties": {
    "gn:admin1_code":"2.0",
    "gn:asciiname":"Ostra Hala",
    "gn:country_code":"SE",
    "gn:dem":-9999,
    "gn:feature_class":"P",
    "gn:feature_code":"PPL",
    "gn:name":"\u00d6stra H\u00e5la",
    "gn:population":0,
    "gn:timezone":"Europe/Stockholm",
    "iso:country":"SE",
    "name:nor_x_preferred":[
        "\u00d6stra H\u00e5la"
    ],
    "name:nor_x_variant":[
        "\u00d8stra H\u00e5la"
    ],
    "name:und_x_variant":[
        "\u00d6stra H\u00e5la"
    ],
    "wof:name":"Ostra Hala",
    "wof:placetype":"locality"
},
  "geometry": {"coordinates":[14.83333,56.13333000000001],"type":"Point"}
}