{
  "type": "Feature",
  "properties": {
    "gn:admin1_code":"25.0",
    "gn:admin2_code":"1907.0",
    "gn:asciiname":"Farmansbo",
    "gn:country_code":"SE",
    "gn:dem":107,
    "gn:feature_class":"P",
    "gn:feature_code":"PPL",
    "gn:name":"F\u00e4rmansbo",
    "gn:population":0,
    "gn:timezone":"Europe/Stockholm",
    "iso:country":"SE",
    "wof:name":"Farmansbo",
    "wof:placetype":"locality"
},
  "geometry": {"coordinates":[16.16667,59.81667],"type":"Point"}
}