{
  "type": "Feature",
  "properties": {
    "gn:admin1_code":"24.0",
    "gn:admin2_code":"2284.0",
    "gn:asciiname":"Sorflarke",
    "gn:country_code":"SE",
    "gn:dem":156,
    "gn:feature_class":"P",
    "gn:feature_code":"PPL",
    "gn:name":"S\u00f6rfl\u00e4rke",
    "gn:population":0,
    "gn:timezone":"Europe/Stockholm",
    "iso:country":"SE",
    "wof:name":"Sorflarke",
    "wof:placetype":"locality"
},
  "geometry": {"coordinates":[17.91667,63.48333],"type":"Point"}
}