{
  "type": "Feature",
  "properties": {
    "gn:admin1_code":"10.0",
    "gn:admin2_code":"2023.0",
    "gn:asciiname":"Grasbrickan",
    "gn:country_code":"SE",
    "gn:dem":490,
    "gn:feature_class":"P",
    "gn:feature_code":"PPL",
    "gn:name":"Gr\u00e4sbrickan",
    "gn:population":0,
    "gn:timezone":"Europe/Stockholm",
    "iso:country":"SE",
    "wof:name":"Grasbrickan",
    "wof:placetype":"locality"
},
  "geometry": {"coordinates":[13.05,60.83306],"type":"Point"}
}