{
  "type": "Feature",
  "properties": {
    "iso:country":"SE",
    "qs_pg:aaroncc":"SE",
    "qs_pg:name":"Kopanm\u00e4ki",
    "qs_pg:name_adm0":"Suomi",
    "qs_pg:name_adm1":"Lapin maakunta",
    "qs_pg:photos":8,
    "qs_pg:photos_1k":2,
    "qs_pg:photos_9k":1,
    "qs_pg:photos_9r":1,
    "qs_pg:photos_all":8,
    "qs_pg:photos_sr":1,
    "qs_pg:pop_sr":0,
    "qs_pg:qs_pg_placetype":"locality",
    "qs_pg:qs_pg_placetype_gp":"Town",
    "qs_pg:woe_adm0":23424812,
    "woe:adm0_id":23424812,
    "woe:name_adm0":"Suomi",
    "woe:name_adm1":"Lapin maakunta",
    "woe:placetype":"Town",
    "wof:name":"Kopanm\u00e4ki",
    "wof:placetype":"locality"
},
  "geometry": {"coordinates":[23.608074,66.31644799999999],"type":"Point"}
}