{
  "type": "Feature",
  "properties": {
    "gn:admin1_code":"14.0",
    "gn:admin2_code":"2506.0",
    "gn:asciiname":"Forsnas",
    "gn:country_code":"SE",
    "gn:dem":404,
    "gn:feature_class":"P",
    "gn:feature_code":"PPL",
    "gn:name":"Forsn\u00e4s",
    "gn:population":0,
    "gn:timezone":"Europe/Stockholm",
    "iso:country":"SE",
    "name:swe_x_preferred":[
        "Forsn\u00e4s"
    ],
    "wof:name":"Forsnas",
    "wof:placetype":"locality"
},
  "geometry": {"coordinates":[18.63933,66.23684],"type":"Point"}
}