{
  "type": "Feature",
  "properties": {
    "gn:admin1_code":"24.0",
    "gn:admin2_code":"2284.0",
    "gn:admin3_code":"228407.0",
    "gn:admin4_code":"2484.0",
    "gn:asciiname":"Eden",
    "gn:country_code":"SE",
    "gn:dem":61,
    "gn:feature_class":"P",
    "gn:feature_code":"PPL",
    "gn:name":"Eden",
    "gn:population":0,
    "gn:timezone":"Europe/Stockholm",
    "iso:country":"SE",
    "name:bre_x_preferred":[
        "Eden"
    ],
    "name:cat_x_preferred":[
        "Eden"
    ],
    "name:ceb_x_preferred":[
        "Eden"
    ],
    "name:ces_x_preferred":[
        "Eden"
    ],
    "name:cym_x_preferred":[
        "Eden"
    ],
    "name:deu_x_preferred":[
        "Eden"
    ],
    "name:est_x_preferred":[
        "Eden"
    ],
    "name:fin_x_preferred":[
        "Eden"
    ],
    "name:fra_x_preferred":[
        "Eden"
    ],
    "name:heb_x_preferred":[
        "\u05e2\u05d3\u05df"
    ],
    "name:ita_x_preferred":[
        "Eden"
    ],
    "name:jpn_x_preferred":[
        "\u30a8\u30c7\u30f3"
    ],
    "name:lav_x_preferred":[
        "Eden"
    ],
    "name:mlg_x_preferred":[
        "Eden"
    ],
    "name:nld_x_preferred":[
        "Eden"
    ],
    "name:nno_x_preferred":[
        "Eden"
    ],
    "name:nor_x_preferred":[
        "Eden"
    ],
    "name:pol_x_preferred":[
        "Eden"
    ],
    "name:por_x_preferred":[
        "Eden"
    ],
    "name:ron_x_preferred":[
        "Categorie:Gr\u0103dina Edenului"
    ],
    "name:rus_x_preferred":[
        "\u042d\u0434\u0435\u043d"
    ],
    "name:slk_x_preferred":[
        "Eden"
    ],
    "name:slv_x_preferred":[
        "Eden"
    ],
    "name:spa_x_preferred":[
        "Eden"
    ],
    "name:srp_x_preferred":[
        "Eden"
    ],
    "name:swe_x_preferred":[
        "Eden"
    ],
    "name:vol_x_preferred":[
        "Eden"
    ],
    "wof:name":"Eden",
    "wof:placetype":"locality"
},
  "geometry": {"coordinates":[18.38333,63.234],"type":"Point"}
}