{
  "type": "Feature",
  "properties": {
    "gn:admin1_code":"24.0",
    "gn:admin2_code":"2284.0",
    "gn:admin3_code":"228407.0",
    "gn:admin4_code":"2484.0",
    "gn:asciiname":"Eden",
    "gn:country_code":"SE",
    "gn:dem":61,
    "gn:feature_class":"P",
    "gn:feature_code":"PPL",
    "gn:name":"Eden",
    "gn:population":0,
    "gn:timezone":"Europe/Stockholm",
    "iso:country":"SE",
    "wof:name":"Eden",
    "wof:placetype":"locality"
},
  "geometry": {"coordinates":[18.38333,63.234],"type":"Point"}
}