{
  "type": "Feature",
  "properties": {
    "gn:admin1_code":"22.0",
    "gn:admin2_code":"1784.0",
    "gn:asciiname":"Ostra Furtan",
    "gn:cc2":"SE",
    "gn:country_code":"SE",
    "gn:dem":156,
    "gn:feature_class":"P",
    "gn:feature_code":"PPL",
    "gn:name":"\u00d6stra Furtan",
    "gn:population":0,
    "gn:timezone":"Europe/Stockholm",
    "iso:country":"SE",
    "name:nor_x_preferred":[
        "\u00d6stra Furtan"
    ],
    "name:nor_x_variant":[
        "\u00d8stra Furtan"
    ],
    "name:und_x_variant":[
        "Furtan"
    ],
    "wof:name":"Ostra Furtan",
    "wof:placetype":"locality"
},
  "geometry": {"coordinates":[12.76667,59.65],"type":"Point"}
}