{
  "type": "Feature",
  "properties": {
    "gn:admin1_code":"22.0",
    "gn:admin2_code":"1765.0",
    "gn:asciiname":"Ostra Boda",
    "gn:country_code":"SE",
    "gn:dem":198,
    "gn:feature_class":"P",
    "gn:feature_code":"PPL",
    "gn:name":"\u00d6stra Boda",
    "gn:population":0,
    "gn:timezone":"Europe/Stockholm",
    "iso:country":"SE",
    "name:nor_x_preferred":[
        "\u00d6stra Boda"
    ],
    "name:nor_x_variant":[
        "\u00d8stra Boda"
    ],
    "name:und_x_variant":[
        "\u00d6stra Boda"
    ],
    "wof:name":"Ostra Boda",
    "wof:placetype":"locality"
},
  "geometry": {"coordinates":[12.38333,59.36666999999999],"type":"Point"}
}