{
  "type": "Feature",
  "properties": {
    "gn:admin1_code":"7.0",
    "gn:admin2_code":"2321.0",
    "gn:asciiname":"Mockelasen",
    "gn:cc2":"SE",
    "gn:country_code":"SE",
    "gn:dem":373,
    "gn:feature_class":"P",
    "gn:feature_code":"PPL",
    "gn:name":"M\u00f6ckel\u00e5sen",
    "gn:population":0,
    "gn:timezone":"Europe/Stockholm",
    "iso:country":"SE",
    "name:nor_x_preferred":[
        "M\u00f6ckel\u00e5sen"
    ],
    "name:nor_x_variant":[
        "M\u00f8ckel\u00e5sen"
    ],
    "name:und_x_variant":[
        "Myckel\u00e5sen",
        "M\u00f6ckel\u00e5sen"
    ],
    "wof:name":"Mockelasen",
    "wof:placetype":"locality"
},
  "geometry": {"coordinates":[14.23333,63.05],"type":"Point"}
}