{
  "type": "Feature",
  "properties": {
    "gn:admin1_code":"28.0",
    "gn:admin2_code":"1490.0",
    "gn:asciiname":"Funningen",
    "gn:country_code":"SE",
    "gn:dem":160,
    "gn:feature_class":"P",
    "gn:feature_code":"PPL",
    "gn:name":"Funningen",
    "gn:population":0,
    "gn:timezone":"Europe/Stockholm",
    "iso:country":"SE",
    "wof:name":"Funningen",
    "wof:placetype":"locality"
},
  "geometry": {"coordinates":[12.85,57.68333000000001],"type":"Point"}
}