{
  "type": "Feature",
  "properties": {
    "gn:admin1_code":"28.0",
    "gn:admin2_code":"1465.0",
    "gn:asciiname":"Landboarp",
    "gn:country_code":"SE",
    "gn:dem":158,
    "gn:feature_class":"P",
    "gn:feature_code":"PPL",
    "gn:name":"Landboarp",
    "gn:population":0,
    "gn:timezone":"Europe/Stockholm",
    "iso:country":"SE",
    "wof:name":"Landboarp",
    "wof:placetype":"locality"
},
  "geometry": {"coordinates":[13.13333,57.33333],"type":"Point"}
}