{
  "type": "Feature",
  "properties": {
    "gn:admin1_code":"26.0",
    "gn:asciiname":"Engarn",
    "gn:country_code":"SE",
    "gn:dem":26,
    "gn:feature_class":"P",
    "gn:feature_code":"PPL",
    "gn:name":"Engarn",
    "gn:population":0,
    "gn:timezone":"Europe/Stockholm",
    "iso:country":"SE",
    "wof:name":"Engarn",
    "wof:placetype":"locality"
},
  "geometry": {"coordinates":[18.30537,59.41931999999999],"type":"Point"}
}