{
  "type": "Feature",
  "properties": {
    "gn:admin1_code":"27.0",
    "gn:admin2_code":"1266.0",
    "gn:asciiname":"Harphult",
    "gn:country_code":"SE",
    "gn:dem":173,
    "gn:feature_class":"P",
    "gn:feature_code":"PPL",
    "gn:name":"Harphult",
    "gn:population":0,
    "gn:timezone":"Europe/Stockholm",
    "iso:country":"SE",
    "wof:name":"Harphult",
    "wof:placetype":"locality"
},
  "geometry": {"coordinates":[13.86667,55.85],"type":"Point"}
}