{
  "type": "Feature",
  "properties": {
    "gn:admin1_code":"28.0",
    "gn:admin2_code":"1439.0",
    "gn:asciiname":"Hallebo",
    "gn:country_code":"SE",
    "gn:dem":151,
    "gn:feature_class":"P",
    "gn:feature_code":"PPL",
    "gn:name":"Hallebo",
    "gn:population":0,
    "gn:timezone":"Europe/Stockholm",
    "iso:country":"SE",
    "wof:name":"Hallebo",
    "wof:placetype":"locality"
},
  "geometry": {"coordinates":[12.03306,58.71666999999999],"type":"Point"}
}