{
  "type": "Feature",
  "properties": {
    "gn:admin1_code":"16.0",
    "gn:admin2_code":"512.0",
    "gn:asciiname":"Mosshult",
    "gn:country_code":"SE",
    "gn:dem":194,
    "gn:feature_class":"P",
    "gn:feature_code":"PPL",
    "gn:name":"Mosshult",
    "gn:population":0,
    "gn:timezone":"Europe/Stockholm",
    "iso:country":"SE",
    "wof:name":"Mosshult",
    "wof:placetype":"locality"
},
  "geometry": {"coordinates":[15.28333,57.83333],"type":"Point"}
}