{
  "type": "Feature",
  "properties": {
    "gn:admin1_code":"28.0",
    "gn:admin2_code":"1481.0",
    "gn:asciiname":"Gastorp",
    "gn:country_code":"SE",
    "gn:dem":49,
    "gn:feature_class":"P",
    "gn:feature_code":"PPL",
    "gn:name":"Gastorp",
    "gn:population":0,
    "gn:timezone":"Europe/Stockholm",
    "iso:country":"SE",
    "wof:name":"Gastorp",
    "wof:placetype":"locality"
},
  "geometry": {"coordinates":[12.06667,57.58333],"type":"Point"}
}