{
  "type": "Feature",
  "properties": {
    "gn:admin1_code":"24.0",
    "gn:admin2_code":"2283.0",
    "gn:admin3_code":"228307.0",
    "gn:admin4_code":"2466.0",
    "gn:asciiname":"Valviken",
    "gn:country_code":"SE",
    "gn:dem":139,
    "gn:feature_class":"P",
    "gn:feature_code":"PPL",
    "gn:name":"Valviken",
    "gn:population":0,
    "gn:timezone":"Europe/Stockholm",
    "iso:country":"SE",
    "wof:name":"Valviken",
    "wof:placetype":"locality"
},
  "geometry": {"coordinates":[16.95,63.15],"type":"Point"}
}