{
  "type": "Feature",
  "properties": {
    "gn:admin1_code":"9.0",
    "gn:admin2_code":"885.0",
    "gn:asciiname":"Unnestad",
    "gn:country_code":"SE",
    "gn:dem":14,
    "gn:feature_class":"P",
    "gn:feature_code":"PPL",
    "gn:name":"Unnestad",
    "gn:population":0,
    "gn:timezone":"Europe/Stockholm",
    "iso:country":"SE",
    "wof:name":"Unnestad",
    "wof:placetype":"locality"
},
  "geometry": {"coordinates":[16.78333,56.91667],"type":"Point"}
}