{
  "type": "Feature",
  "properties": {
    "gn:admin1_code":"14.0",
    "gn:admin2_code":"2514.0",
    "gn:asciiname":"Kalvfors",
    "gn:country_code":"SE",
    "gn:dem":51,
    "gn:feature_class":"P",
    "gn:feature_code":"PPL",
    "gn:name":"K\u00e4lvfors",
    "gn:population":0,
    "gn:timezone":"Europe/Stockholm",
    "iso:country":"SE",
    "wof:name":"Kalvfors",
    "wof:placetype":"locality"
},
  "geometry": {"coordinates":[22.73333,66.15000000000001],"type":"Point"}
}