{
  "type": "Feature",
  "properties": {
    "gn:admin1_code":"27.0",
    "gn:admin2_code":"1290.0",
    "gn:asciiname":"Bjarnhult",
    "gn:country_code":"SE",
    "gn:dem":163,
    "gn:feature_class":"P",
    "gn:feature_code":"PPL",
    "gn:name":"Bj\u00e4rnhult",
    "gn:population":0,
    "gn:timezone":"Europe/Stockholm",
    "iso:country":"SE",
    "wof:name":"Bjarnhult",
    "wof:placetype":"locality"
},
  "geometry": {"coordinates":[13.76667,55.95],"type":"Point"}
}