{
  "type": "Feature",
  "properties": {
    "gn:admin1_code":"16.0",
    "gn:admin2_code":"562.0",
    "gn:asciiname":"Frantorp",
    "gn:country_code":"SE",
    "gn:dem":58,
    "gn:feature_class":"P",
    "gn:feature_code":"PPL",
    "gn:name":"Fr\u00e4ntorp",
    "gn:population":0,
    "gn:timezone":"Europe/Stockholm",
    "iso:country":"SE",
    "wof:name":"Frantorp",
    "wof:placetype":"locality"
},
  "geometry": {"coordinates":[15.65,58.71666999999999],"type":"Point"}
}