{
  "type": "Feature",
  "properties": {
    "gn:admin1_code":"24.0",
    "gn:admin2_code":"2282.0",
    "gn:asciiname":"Svedje",
    "gn:country_code":"SE",
    "gn:dem":87,
    "gn:feature_class":"P",
    "gn:feature_code":"PPL",
    "gn:name":"Svedje",
    "gn:population":0,
    "gn:timezone":"Europe/Stockholm",
    "iso:country":"SE",
    "wof:name":"Svedje",
    "wof:placetype":"locality"
},
  "geometry": {"coordinates":[18.16667,62.98333],"type":"Point"}
}