{
  "type": "Feature",
  "properties": {
    "gn:admin1_code":"10.0",
    "gn:admin2_code":"2026.0",
    "gn:admin3_code":"202602.0",
    "gn:admin4_code":"2350.0",
    "gn:asciiname":"Arvslindan",
    "gn:cc2":"SE",
    "gn:country_code":"SE",
    "gn:dem":192,
    "gn:feature_class":"P",
    "gn:feature_code":"PPL",
    "gn:name":"Arvslindan",
    "gn:population":0,
    "gn:timezone":"Europe/Stockholm",
    "iso:country":"SE",
    "name:und_x_variant":[
        "Arfslindan",
        "Arvslindan"
    ],
    "wof:name":"Arvslindan",
    "wof:placetype":"locality"
},
  "geometry": {"coordinates":[15.16088,60.53301],"type":"Point"}
}