{
  "type": "Feature",
  "properties": {
    "gn:admin1_code":"27.0",
    "gn:admin2_code":"1260.0",
    "gn:asciiname":"Norra Vram",
    "gn:country_code":"SE",
    "gn:dem":28,
    "gn:feature_class":"P",
    "gn:feature_code":"PPL",
    "gn:name":"Norra Vram",
    "gn:population":0,
    "gn:timezone":"Europe/Stockholm",
    "iso:country":"SE",
    "wof:name":"Norra Vram",
    "wof:placetype":"locality"
},
  "geometry": {"coordinates":[12.96667,56.08333],"type":"Point"}
}