{
  "type": "Feature",
  "properties": {
    "gn:admin1_code":"23.0",
    "gn:admin2_code":"2418.0",
    "gn:asciiname":"Langudden",
    "gn:country_code":"SE",
    "gn:dem":344,
    "gn:feature_class":"P",
    "gn:feature_code":"PPL",
    "gn:name":"L\u00e5ngudden",
    "gn:population":0,
    "gn:timezone":"Europe/Stockholm",
    "iso:country":"SE",
    "wof:name":"Langudden",
    "wof:placetype":"locality"
},
  "geometry": {"coordinates":[18.53333,65.18333],"type":"Point"}
}