{
  "type": "Feature",
  "properties": {
    "gn:admin1_code":"27.0",
    "gn:admin2_code":"1278.0",
    "gn:asciiname":"Lya",
    "gn:country_code":"SE",
    "gn:dem":180,
    "gn:elevation":"170.0",
    "gn:feature_class":"P",
    "gn:feature_code":"PPL",
    "gn:name":"Lya",
    "gn:population":0,
    "gn:timezone":"Europe/Stockholm",
    "iso:country":"SE",
    "name:ceb_x_preferred":[
        "Lya"
    ],
    "name:swe_x_preferred":[
        "Lya"
    ],
    "wof:name":"Lya",
    "wof:placetype":"locality"
},
  "geometry": {"coordinates":[12.88456,56.40953],"type":"Point"}
}