{
  "type": "Feature",
  "properties": {
    "gn:admin1_code":"24",
    "gn:admin2_code":"2281.0",
    "gn:admin3_code":"228101.0",
    "gn:admin4_code":"2497.0",
    "gn:asciiname":"Pettersvik",
    "gn:country_code":"SE",
    "gn:dem":1,
    "gn:feature_class":"P",
    "gn:feature_code":"PPLL",
    "gn:name":"Pettersvik",
    "gn:population":0,
    "gn:timezone":"Europe/Stockholm",
    "iso:country":"SE",
    "wof:name":"Pettersvik",
    "wof:placetype":"locality"
},
  "geometry": {"coordinates":[17.38767,62.39788000000001],"type":"Point"}
}