{
  "type": "Feature",
  "properties": {
    "gn:admin1_code":"23.0",
    "gn:admin2_code":"2409.0",
    "gn:asciiname":"Ostra Sjulsmark",
    "gn:cc2":"SE",
    "gn:country_code":"SE",
    "gn:dem":116,
    "gn:feature_class":"P",
    "gn:feature_code":"PPL",
    "gn:name":"\u00d6stra Sjulsmark",
    "gn:population":0,
    "gn:timezone":"Europe/Stockholm",
    "iso:country":"SE",
    "name:nor_x_preferred":[
        "\u00d6stra Sjulsmark"
    ],
    "name:nor_x_variant":[
        "\u00d8stra Sjulsmark"
    ],
    "name:und_x_variant":[
        "Sjulsmark",
        "\u00d6stra Sjulsmark"
    ],
    "wof:name":"Ostra Sjulsmark",
    "wof:placetype":"locality"
},
  "geometry": {"coordinates":[20.65,64.16667],"type":"Point"}
}