{
  "type": "Feature",
  "properties": {
    "gn:admin1_code":"9.0",
    "gn:asciiname":"Bjornsbodar",
    "gn:country_code":"SE",
    "gn:dem":3,
    "gn:feature_class":"P",
    "gn:feature_code":"PPL",
    "gn:name":"Bj\u00f6rnsbodar",
    "gn:population":0,
    "gn:timezone":"Europe/Stockholm",
    "iso:country":"SE",
    "name:nor_x_preferred":[
        "Bj\u00f6rnsbodar"
    ],
    "name:nor_x_variant":[
        "Bj\u00f8rnsbodar"
    ],
    "name:und_x_variant":[
        "Bj\u00f6rnsbodar"
    ],
    "wof:name":"Bjornsbodar",
    "wof:placetype":"locality"
},
  "geometry": {"coordinates":[16.73333,56.925],"type":"Point"}
}