{
  "type": "Feature",
  "properties": {
    "gn:admin1_code":"28.0",
    "gn:admin2_code":"1447.0",
    "gn:asciiname":"Prastkila",
    "gn:country_code":"SE",
    "gn:dem":108,
    "gn:feature_class":"P",
    "gn:feature_code":"PPL",
    "gn:name":"Pr\u00e4stkila",
    "gn:population":0,
    "gn:timezone":"Europe/Stockholm",
    "iso:country":"SE",
    "wof:name":"Prastkila",
    "wof:placetype":"locality"
},
  "geometry": {"coordinates":[14.16667,58.86666999999999],"type":"Point"}
}