{
  "type": "Feature",
  "properties": {
    "gn:admin1_code":"21.0",
    "gn:admin2_code":"380.0",
    "gn:asciiname":"Soderby",
    "gn:country_code":"SE",
    "gn:dem":22,
    "gn:feature_class":"P",
    "gn:feature_code":"PPL",
    "gn:name":"S\u00f6derby",
    "gn:population":0,
    "gn:timezone":"Europe/Stockholm",
    "iso:country":"SE",
    "name:nor_x_preferred":[
        "S\u00f6derby"
    ],
    "name:nor_x_variant":[
        "S\u00f8derby"
    ],
    "name:und_x_variant":[
        "S\u00f6derby"
    ],
    "wof:name":"Soderby",
    "wof:placetype":"locality"
},
  "geometry": {"coordinates":[17.83333,59.83333],"type":"Point"}
}