{
  "type": "Feature",
  "properties": {
    "gn:admin1_code":"22.0",
    "gn:admin2_code":"1764.0",
    "gn:asciiname":"Grinsbol",
    "gn:country_code":"SE",
    "gn:dem":108,
    "gn:feature_class":"P",
    "gn:feature_code":"PPL",
    "gn:name":"Grinsbol",
    "gn:population":0,
    "gn:timezone":"Europe/Stockholm",
    "iso:country":"SE",
    "wof:name":"Grinsbol",
    "wof:placetype":"locality"
},
  "geometry": {"coordinates":[12.93333,59.43333000000001],"type":"Point"}
}