{
  "type": "Feature",
  "properties": {
    "gn:gn_country":"SE",
    "gn:gn_fcode":"PPL",
    "gn:gn_pop":0,
    "iso:country":"SE",
    "name:dan_x_preferred":[
        "Gruvstugan"
    ],
    "name:deu_x_preferred":[
        "Gruvstugan"
    ],
    "name:eng_x_preferred":[
        "Gruvstugan"
    ],
    "name:fra_x_preferred":[
        "Gruvstugan"
    ],
    "name:nds_x_preferred":[
        "Gruvstugan"
    ],
    "name:nld_x_preferred":[
        "Gruvstugan"
    ],
    "name:nno_x_preferred":[
        "Gruvstugan"
    ],
    "name:nob_x_preferred":[
        "Gruvstugan"
    ],
    "name:swe_x_preferred":[
        "Gruvstugan"
    ],
    "qs_pg:aaroncc":"SE",
    "qs_pg:gn_country":"SE",
    "qs_pg:gn_fcode":"PPL",
    "qs_pg:gn_pop":0,
    "qs_pg:name":"Gruvstugan",
    "qs_pg:name_adm0":"Sverige",
    "qs_pg:name_adm1":"\u00d6sterg\u00f6tlands L\u00e4n",
    "qs_pg:photos":726,
    "qs_pg:photos_1k":147,
    "qs_pg:photos_9k":3,
    "qs_pg:photos_9r":5,
    "qs_pg:photos_all":726,
    "qs_pg:photos_sr":8,
    "qs_pg:pop_sr":0,
    "qs_pg:qs_pg_placetype":"locality",
    "qs_pg:qs_pg_placetype_gp":"Town",
    "qs_pg:woe_adm0":23424954,
    "woe:adm0_id":23424954,
    "woe:name_adm0":"Sverige",
    "woe:name_adm1":"\u00d6sterg\u00f6tlands L\u00e4n",
    "woe:placetype":"Town",
    "wof:name":"Gruvstugan",
    "wof:placetype":"locality"
},
  "geometry": {"coordinates":[16.45,58.66667],"type":"Point"}
}