{
  "type": "Feature",
  "properties": {
    "gn:admin1_code":"26.0",
    "gn:admin2_code":"138.0",
    "gn:asciiname":"Tyreso Strand",
    "gn:cc2":"SE",
    "gn:country_code":"SE",
    "gn:dem":52,
    "gn:feature_class":"P",
    "gn:feature_code":"PPL",
    "gn:name":"Tyres\u00f6 Strand",
    "gn:population":0,
    "gn:timezone":"Europe/Stockholm",
    "iso:country":"SE",
    "name:nor_x_preferred":[
        "Tyres\u00f6 Strand"
    ],
    "name:nor_x_variant":[
        "Tyres\u00f8 Strand"
    ],
    "name:und_x_variant":[
        "Strand"
    ],
    "wof:name":"Tyreso Strand",
    "wof:placetype":"locality"
},
  "geometry": {"coordinates":[18.28333,59.25],"type":"Point"}
}