{
  "type": "Feature",
  "properties": {
    "gn:gn_country":"SE",
    "gn:gn_fcode":"PPL",
    "gn:gn_pop":0,
    "iso:country":"SE",
    "name:eng_x_preferred":[
        "N\u00e4sbypark"
    ],
    "name:fra_x_preferred":[
        "N\u00e4sbypark"
    ],
    "name:jpn_x_preferred":[
        "\u30cd\u30b9\u30d3\u30e5\u30fc\u30d1\u30eb\u30af\u99c5"
    ],
    "name:swe_x_preferred":[
        "N\u00e4sbypark"
    ],
    "name:unk_x_variant":[
        "N\u00e4sby \u00d6stra Park"
    ],
    "qs_pg:aaroncc":"SE",
    "qs_pg:gn_country":"SE",
    "qs_pg:gn_fcode":"PPL",
    "qs_pg:gn_pop":0,
    "qs_pg:name":"N\u00e4sbypark",
    "qs_pg:name_adm0":"Sverige",
    "qs_pg:name_adm1":"Stockholms L\u00e4n",
    "qs_pg:photos_9k":1,
    "qs_pg:photos_9r":2,
    "qs_pg:photos_all":38,
    "qs_pg:photos_sr":0,
    "qs_pg:pop_sr":0,
    "qs_pg:qs_pg_placetype":"locality",
    "qs_pg:qs_pg_placetype_gp":"Town",
    "qs_pg:woe_adm0":23424954,
    "woe:adm0_id":23424954,
    "woe:name_adm0":"Sverige",
    "woe:name_adm1":"Stockholms L\u00e4n",
    "woe:placetype":"Town",
    "wof:name":"N\u00e4sbypark",
    "wof:placetype":"locality"
},
  "geometry": {"coordinates":[18.0847,59.42858],"type":"Point"}
}