{
  "type": "Feature",
  "properties": {
    "gn:admin1_code":"18",
    "gn:admin2_code":"486.0",
    "gn:admin3_code":"48604.0",
    "gn:admin4_code":"343.0",
    "gn:asciiname":"Marielund",
    "gn:country_code":"SE",
    "gn:dem":9,
    "gn:feature_class":"P",
    "gn:feature_code":"PPL",
    "gn:name":"Marielund",
    "gn:population":532,
    "gn:timezone":"Europe/Stockholm",
    "iso:country":"SE",
    "name:ita_x_preferred":[
        "Marielund"
    ],
    "name:nld_x_preferred":[
        "Marielund"
    ],
    "name:swe_x_preferred":[
        "Marielund"
    ],
    "wof:name":"Marielund",
    "wof:placetype":"locality",
    "wof:population":532
},
  "geometry": {"coordinates":[17.18215,59.25101],"type":"Point"}
}