{
  "type": "Feature",
  "properties": {
    "gn:gn_country":"SE",
    "gn:gn_fcode":"PPL",
    "gn:gn_pop":0,
    "iso:country":"SE",
    "name:dan_x_preferred":[
        "Gr\u00e4v"
    ],
    "name:deu_x_preferred":[
        "Gr\u00e4v"
    ],
    "name:eng_x_preferred":[
        "Gr\u00e4v"
    ],
    "name:fra_x_preferred":[
        "Gr\u00e4v"
    ],
    "name:nds_x_preferred":[
        "Gr\u00e4v"
    ],
    "name:nld_x_preferred":[
        "Gr\u00e4v"
    ],
    "name:nno_x_preferred":[
        "Gr\u00e4v"
    ],
    "name:nob_x_preferred":[
        "Gr\u00e4v"
    ],
    "name:swe_x_preferred":[
        "Gr\u00e4v"
    ],
    "name:unk_x_variant":[
        "Gr\u00e4f"
    ],
    "qs_pg:aaroncc":"SE",
    "qs_pg:gn_country":"SE",
    "qs_pg:gn_fcode":"PPL",
    "qs_pg:gn_pop":0,
    "qs_pg:name":"Gr\u00e4v",
    "qs_pg:name_adm0":"Sverige",
    "qs_pg:name_adm1":"Dalarnas L\u00e4n",
    "qs_pg:photos_9r":0,
    "qs_pg:photos_sr":0,
    "qs_pg:pop_sr":0,
    "qs_pg:qs_pg_placetype":"locality",
    "qs_pg:qs_pg_placetype_gp":"Town",
    "qs_pg:woe_adm0":23424954,
    "woe:adm0_id":23424954,
    "woe:name_adm0":"Sverige",
    "woe:name_adm1":"Dalarnas L\u00e4n",
    "woe:placetype":"Town",
    "wof:name":"Gr\u00e4v",
    "wof:placetype":"locality"
},
  "geometry": {"coordinates":[15.03333,60.61667],"type":"Point"}
}