{
  "type": "Feature",
  "properties": {
    "gn:admin1_code":"3.0",
    "gn:admin2_code":"2180.0",
    "gn:asciiname":"Kusbo",
    "gn:country_code":"SE",
    "gn:dem":45,
    "gn:feature_class":"P",
    "gn:feature_code":"PPL",
    "gn:name":"Kusbo",
    "gn:population":0,
    "gn:timezone":"Europe/Stockholm",
    "iso:country":"SE",
    "wof:name":"Kusbo",
    "wof:placetype":"locality"
},
  "geometry": {"coordinates":[17.01667,60.63333000000001],"type":"Point"}
}