{
  "type": "Feature",
  "properties": {
    "gn:admin1_code":"9.0",
    "gn:admin2_code":"880.0",
    "gn:asciiname":"Ramneryd",
    "gn:country_code":"SE",
    "gn:dem":39,
    "gn:feature_class":"P",
    "gn:feature_code":"PPL",
    "gn:name":"Ramneryd",
    "gn:population":0,
    "gn:timezone":"Europe/Stockholm",
    "iso:country":"SE",
    "wof:name":"Ramneryd",
    "wof:placetype":"locality"
},
  "geometry": {"coordinates":[16.13332999999999,56.73333],"type":"Point"}
}