{
  "type": "Feature",
  "properties": {
    "gn:admin1_code":"27.0",
    "gn:admin2_code":"1273.0",
    "gn:asciiname":"Ostra Kalhult",
    "gn:country_code":"SE",
    "gn:dem":88,
    "gn:feature_class":"P",
    "gn:feature_code":"PPL",
    "gn:name":"\u00d6stra Kalhult",
    "gn:population":0,
    "gn:timezone":"Europe/Stockholm",
    "iso:country":"SE",
    "name:nor_x_preferred":[
        "\u00d6stra Kalhult"
    ],
    "name:nor_x_variant":[
        "\u00d8stra Kalhult"
    ],
    "wof:name":"Ostra Kalhult",
    "wof:placetype":"locality"
},
  "geometry": {"coordinates":[14.01667,56.36666999999999],"type":"Point"}
}