{
  "type": "Feature",
  "properties": {
    "gn:admin1_code":"14.0",
    "gn:admin2_code":"2521.0",
    "gn:asciiname":"Saitaniemi",
    "gn:country_code":"SE",
    "gn:dem":109,
    "gn:feature_class":"P",
    "gn:feature_code":"PPL",
    "gn:name":"Saitaniemi",
    "gn:population":0,
    "gn:timezone":"Europe/Stockholm",
    "iso:country":"SE",
    "name:und_x_variant":[
        "Saittaniemi",
        "Saitanoja",
        "Saitaniemi"
    ],
    "wof:name":"Saitaniemi",
    "wof:placetype":"locality"
},
  "geometry": {"coordinates":[23.74158,67.01373000000001],"type":"Point"}
}