{
  "type": "Feature",
  "properties": {
    "gn:admin1_code":"16.0",
    "gn:admin2_code":"563.0",
    "gn:asciiname":"Holmtebo",
    "gn:country_code":"SE",
    "gn:dem":70,
    "gn:feature_class":"P",
    "gn:feature_code":"PPL",
    "gn:name":"Holmtebo",
    "gn:population":0,
    "gn:timezone":"Europe/Stockholm",
    "iso:country":"SE",
    "wof:name":"Holmtebo",
    "wof:placetype":"locality"
},
  "geometry": {"coordinates":[16.55,58.18333000000001],"type":"Point"}
}