{
  "type": "Feature",
  "properties": {
    "gn:admin1_code":"7.0",
    "gn:admin2_code":"2303.0",
    "gn:asciiname":"Fullsjon",
    "gn:country_code":"SE",
    "gn:dem":361,
    "gn:feature_class":"P",
    "gn:feature_code":"PPL",
    "gn:name":"Fullsj\u00f6n",
    "gn:population":0,
    "gn:timezone":"Europe/Stockholm",
    "iso:country":"SE",
    "name:nor_x_preferred":[
        "Fullsj\u00f6n"
    ],
    "name:nor_x_variant":[
        "Fullsj\u00f8n"
    ],
    "name:und_x_variant":[
        "Fullsj\u00f6n"
    ],
    "wof:name":"Fullsjon",
    "wof:placetype":"locality"
},
  "geometry": {"coordinates":[15.93333,63.45],"type":"Point"}
}