{
  "type": "Feature",
  "properties": {
    "gn:admin1_code":"27.0",
    "gn:admin2_code":"1292.0",
    "gn:admin3_code":"129209.0",
    "gn:admin4_code":"1024.0",
    "gn:asciiname":"Skalderviken",
    "gn:country_code":"SE",
    "gn:dem":1,
    "gn:feature_class":"P",
    "gn:feature_code":"PPL",
    "gn:name":"Sk\u00e4lderviken",
    "gn:population":0,
    "gn:timezone":"Europe/Stockholm",
    "iso:country":"SE",
    "wof:name":"Skalderviken",
    "wof:placetype":"locality"
},
  "geometry": {"coordinates":[12.84302,56.26709],"type":"Point"}
}