{
  "type": "Feature",
  "properties": {
    "gn:admin1_code":"7.0",
    "gn:admin2_code":"2321.0",
    "gn:asciiname":"Mattmar",
    "gn:country_code":"SE",
    "gn:dem":341,
    "gn:feature_class":"P",
    "gn:feature_code":"PPL",
    "gn:name":"Mattmar",
    "gn:population":0,
    "gn:timezone":"Europe/Stockholm",
    "iso:country":"SE",
    "wof:name":"Mattmar",
    "wof:placetype":"locality"
},
  "geometry": {"coordinates":[13.83333,63.31667],"type":"Point"}
}