{
  "type": "Feature",
  "properties": {
    "gn:admin1_code":"21.0",
    "gn:admin2_code":"382.0",
    "gn:asciiname":"Marma",
    "gn:country_code":"SE",
    "gn:dem":25,
    "gn:feature_class":"P",
    "gn:feature_code":"PPL",
    "gn:name":"Marma",
    "gn:population":0,
    "gn:timezone":"Europe/Stockholm",
    "iso:country":"SE",
    "name:ceb_x_preferred":[
        "Marma"
    ],
    "name:fra_x_preferred":[
        "Marma"
    ],
    "name:ita_x_preferred":[
        "Marma"
    ],
    "name:nld_x_preferred":[
        "Marma"
    ],
    "wof:name":"Marma",
    "wof:placetype":"locality"
},
  "geometry": {"coordinates":[18.08333,60.08333],"type":"Point"}
}