{
  "type": "Feature",
  "properties": {
    "gn:admin1_code":"24.0",
    "gn:admin2_code":"2281.0",
    "gn:admin3_code":"228104.0",
    "gn:admin4_code":"2448.0",
    "gn:asciiname":"Sandarna",
    "gn:country_code":"SE",
    "gn:dem":-9999,
    "gn:feature_class":"P",
    "gn:feature_code":"PPL",
    "gn:name":"Sandarna",
    "gn:population":0,
    "gn:timezone":"Europe/Stockholm",
    "iso:country":"SE",
    "wof:name":"Sandarna",
    "wof:placetype":"locality"
},
  "geometry": {"coordinates":[17.41778,62.36611],"type":"Point"}
}