{
  "type": "Feature",
  "properties": {
    "gn:admin1_code":"16.0",
    "gn:admin2_code":"582.0",
    "gn:asciiname":"Horno",
    "gn:country_code":"SE",
    "gn:dem":9,
    "gn:feature_class":"P",
    "gn:feature_code":"PPL",
    "gn:name":"Horn\u00f6",
    "gn:population":0,
    "gn:timezone":"Europe/Stockholm",
    "iso:country":"SE",
    "name:ara_x_preferred":[
        "\u0641\u0631\u0646 \u0637\u064a\u0646\u064a"
    ],
    "name:nor_x_preferred":[
        "Horn\u00f6"
    ],
    "name:nor_x_variant":[
        "Horn\u00f8"
    ],
    "wof:name":"Horno",
    "wof:placetype":"locality"
},
  "geometry": {"coordinates":[16.75,58.36666999999999],"type":"Point"}
}