{
  "type": "Feature",
  "properties": {
    "gn:admin1_code":"10.0",
    "gn:admin2_code":"2026.0",
    "gn:asciiname":"Lindbyn",
    "gn:country_code":"SE",
    "gn:dem":200,
    "gn:feature_class":"P",
    "gn:feature_code":"PPL",
    "gn:name":"Lindbyn",
    "gn:population":0,
    "gn:timezone":"Europe/Stockholm",
    "iso:country":"SE",
    "wof:name":"Lindbyn",
    "wof:placetype":"locality"
},
  "geometry": {"coordinates":[14.96667,60.51667],"type":"Point"}
}