{
  "type": "Feature",
  "properties": {
    "gn:admin1_code":"27.0",
    "gn:admin2_code":"1273.0",
    "gn:asciiname":"Bokeberga",
    "gn:country_code":"SE",
    "gn:dem":97,
    "gn:feature_class":"P",
    "gn:feature_code":"PPL",
    "gn:name":"B\u00f6keberga",
    "gn:population":0,
    "gn:timezone":"Europe/Stockholm",
    "iso:country":"SE",
    "name:nor_x_preferred":[
        "B\u00f6keberga"
    ],
    "name:nor_x_variant":[
        "B\u00f8keberga"
    ],
    "wof:name":"Bokeberga",
    "wof:placetype":"locality"
},
  "geometry": {"coordinates":[14.05,56.41667],"type":"Point"}
}