{
  "type": "Feature",
  "properties": {
    "gn:admin1_code":"8.0",
    "gn:admin2_code":"617.0",
    "gn:asciiname":"Lid",
    "gn:country_code":"SE",
    "gn:dem":183,
    "gn:feature_class":"P",
    "gn:feature_code":"PPL",
    "gn:name":"Lid",
    "gn:population":0,
    "gn:timezone":"Europe/Stockholm",
    "iso:country":"SE",
    "name:aym_x_preferred":[
        "Qhupi\u00f1a"
    ],
    "name:cat_x_preferred":[
        "Tapadora"
    ],
    "name:dan_x_preferred":[
        "L\u00e5g"
    ],
    "name:eml_x_preferred":[
        "Cu\u00ear\u0107"
    ],
    "name:fra_x_preferred":[
        "Couvercle"
    ],
    "name:glg_x_preferred":[
        "Tapa"
    ],
    "name:ido_x_preferred":[
        "Lido"
    ],
    "name:kaz_x_preferred":[
        "\u049a\u0430\u049b\u043f\u0430\u049b\u0448\u0430 \u0442\u04af\u0440\u043b\u0435\u0440\u0456"
    ],
    "name:kir_x_preferred":[
        "\u041a\u0430\u043f\u043a\u0430\u043a"
    ],
    "name:nld_x_preferred":[
        "Deksel"
    ],
    "name:por_x_preferred":[
        "Tampa"
    ],
    "name:ron_x_preferred":[
        "Capac"
    ],
    "name:rus_x_preferred":[
        "\u041a\u0440\u044b\u0448\u043a\u0430"
    ],
    "name:scn_x_preferred":[
        "Cummogghiu"
    ],
    "name:spa_x_preferred":[
        "Tapa"
    ],
    "name:sqi_x_preferred":[
        "Kapaku"
    ],
    "name:srp_x_preferred":[
        "\u041f\u043e\u043a\u043b\u043e\u043f\u0430\u0446"
    ],
    "name:swe_x_preferred":[
        "Lock"
    ],
    "name:tur_x_preferred":[
        "Ge\u00e7meli kapak"
    ],
    "name:ukr_x_preferred":[
        "\u041a\u0440\u0438\u0448\u043a\u0430"
    ],
    "wof:name":"Lid",
    "wof:placetype":"locality"
},
  "geometry": {"coordinates":[13.75,57.35],"type":"Point"}
}