{
  "type": "Feature",
  "properties": {
    "gn:admin1_code":"26.0",
    "gn:admin2_code":"160.0",
    "gn:asciiname":"Haegernaes",
    "gn:country_code":"SE",
    "gn:dem":43,
    "gn:feature_class":"P",
    "gn:feature_code":"PPL",
    "gn:name":"H\u00e4gern\u00e4s",
    "gn:population":0,
    "gn:timezone":"Europe/Stockholm",
    "iso:country":"SE",
    "wof:name":"Haegernaes",
    "wof:placetype":"locality"
},
  "geometry": {"coordinates":[18.11972,59.45031],"type":"Point"}
}