{
  "type": "Feature",
  "properties": {
    "gn:admin1_code":"23.0",
    "gn:admin2_code":"2462.0",
    "gn:asciiname":"Hornsjo",
    "gn:cc2":"SE",
    "gn:country_code":"SE",
    "gn:dem":410,
    "gn:feature_class":"P",
    "gn:feature_code":"PPL",
    "gn:name":"Hornsj\u00f6",
    "gn:population":0,
    "gn:timezone":"Europe/Stockholm",
    "iso:country":"SE",
    "name:nor_x_preferred":[
        "Hornsj\u00f6"
    ],
    "name:nor_x_variant":[
        "Hornsj\u00f8"
    ],
    "name:und_x_variant":[
        "Hornsby",
        "Hornsj\u00f6"
    ],
    "wof:name":"Hornsjo",
    "wof:placetype":"locality"
},
  "geometry": {"coordinates":[16.08333,64.84999999999999],"type":"Point"}
}