{
  "type": "Feature",
  "properties": {
    "gn:admin1_code":"27.0",
    "gn:admin2_code":"1290.0",
    "gn:asciiname":"Borrakra",
    "gn:country_code":"SE",
    "gn:dem":140,
    "gn:feature_class":"P",
    "gn:feature_code":"PPL",
    "gn:name":"Borr\u00e5kra",
    "gn:population":0,
    "gn:timezone":"Europe/Stockholm",
    "iso:country":"SE",
    "wof:name":"Borrakra",
    "wof:placetype":"locality"
},
  "geometry": {"coordinates":[14.05,55.83333],"type":"Point"}
}