{
  "type": "Feature",
  "properties": {
    "gn:admin1_code":"22.0",
    "gn:admin2_code":"1765.0",
    "gn:asciiname":"Molnerud",
    "gn:country_code":"SE",
    "gn:dem":154,
    "gn:feature_class":"P",
    "gn:feature_code":"PPL",
    "gn:name":"M\u00f6lnerud",
    "gn:population":0,
    "gn:timezone":"Europe/Stockholm",
    "iso:country":"SE",
    "name:nor_x_preferred":[
        "M\u00f6lnerud"
    ],
    "name:nor_x_variant":[
        "M\u00f8lnerud"
    ],
    "name:und_x_variant":[
        "M\u00f6lnerud"
    ],
    "wof:name":"Molnerud",
    "wof:placetype":"locality"
},
  "geometry": {"coordinates":[11.98333,59.43333000000001],"type":"Point"}
}