{
  "type": "Feature",
  "properties": {
    "gn:admin1_code":"22.0",
    "gn:admin2_code":"1783.0",
    "gn:asciiname":"By",
    "gn:country_code":"SE",
    "gn:dem":113,
    "gn:feature_class":"P",
    "gn:feature_code":"PPL",
    "gn:name":"By",
    "gn:population":0,
    "gn:timezone":"Europe/Stockholm",
    "iso:country":"SE",
    "wof:name":"By",
    "wof:placetype":"locality"
},
  "geometry": {"coordinates":[13.58333,59.93333000000001],"type":"Point"}
}