{
  "type": "Feature",
  "properties": {
    "gn:population":1012,
    "iso:country":"SE",
    "name:ceb_x_preferred":[
        "Str\u00f6velstorp"
    ],
    "name:eng_x_preferred":[
        "Str\u00f6velstorp"
    ],
    "name:ita_x_preferred":[
        "Str\u00f6velstorp"
    ],
    "name:nan_x_preferred":[
        "Str\u00f6velstorp"
    ],
    "name:nld_x_preferred":[
        "Str\u00f6velstorp"
    ],
    "name:nno_x_preferred":[
        "Str\u00f6velstorp"
    ],
    "name:nob_x_preferred":[
        "Str\u00f6velstorp"
    ],
    "name:nor_x_preferred":[
        "Str\u00f6velstorp"
    ],
    "name:nor_x_variant":[
        "Str\u00f8velstorp"
    ],
    "name:swe_x_colloquial":[
        "Stroevelstorp",
        "Stroevelstorps",
        "Strovelstorp",
        "Strovelstorps"
    ],
    "name:swe_x_preferred":[
        "Str\u00f6velstorp"
    ],
    "name:swe_x_variant":[
        "Str\u00f6velstorps"
    ],
    "name:zho_min_nan_x_preferred":[
        "Str\u00f6velstorp"
    ],
    "qs:a0":"Sverige",
    "qs:a1":"*Sk\u00e5ne l\u00e4n",
    "qs:a1r":"0",
    "qs:adm0":"Sverige",
    "qs:la_lc":"*",
    "qs:level":"locality",
    "qs:loc":"Str\u00f6velstorp",
    "qs:loc_alt":"Strovelstorp",
    "qs:pop":0,
    "qs:type":"buffered point",
    "wd:wordcount":45,
    "wof:name":"Str\u00f6velstorp",
    "wof:placetype":"locality",
    "wof:population":1012
},
  "geometry": {"coordinates":[12.822099,56.161194],"type":"Point"}
}