{
  "type": "Feature",
  "properties": {
    "gn:admin1_code":"14.0",
    "gn:admin2_code":"2580.0",
    "gn:asciiname":"Gruvan",
    "gn:country_code":"SE",
    "gn:dem":-9999,
    "gn:feature_class":"P",
    "gn:feature_code":"PPL",
    "gn:name":"Gruvan",
    "gn:population":0,
    "gn:timezone":"Europe/Stockholm",
    "iso:country":"SE",
    "wof:name":"Gruvan",
    "wof:placetype":"locality"
},
  "geometry": {"coordinates":[22.58333,65.58750000000001],"type":"Point"}
}