{
  "type": "Feature",
  "properties": {
    "iso:country":"SE",
    "name:ara_x_preferred":[
        "\u0623\u0633\u0643\u064a\u0645"
    ],
    "name:bpy_x_preferred":[
        "\u0986\u09b8\u09cd\u0995\u09bf\u09ae"
    ],
    "name:bul_x_preferred":[
        "\u0410\u0448\u0438\u043c"
    ],
    "name:cat_x_preferred":[
        "Askim"
    ],
    "name:ceb_x_preferred":[
        "Askim"
    ],
    "name:dan_x_preferred":[
        "Askim"
    ],
    "name:deu_x_preferred":[
        "Askim"
    ],
    "name:epo_x_preferred":[
        "Askim"
    ],
    "name:est_x_preferred":[
        "Askimi vald"
    ],
    "name:eus_x_preferred":[
        "Askim"
    ],
    "name:fas_x_preferred":[
        "\u0622\u0634\u06cc\u0645"
    ],
    "name:fin_x_preferred":[
        "Askim"
    ],
    "name:fra_x_preferred":[
        "Askim"
    ],
    "name:hye_x_preferred":[
        "\u0531\u057d\u0584\u056b\u0574"
    ],
    "name:ind_x_preferred":[
        "Askim"
    ],
    "name:ita_x_preferred":[
        "Askim"
    ],
    "name:jav_x_preferred":[
        "Askim"
    ],
    "name:lat_x_preferred":[
        "Askim"
    ],
    "name:lim_x_preferred":[
        "Askim"
    ],
    "name:msa_x_preferred":[
        "Askim"
    ],
    "name:nds_x_preferred":[
        "Kommun Askim"
    ],
    "name:nld_x_preferred":[
        "Askim"
    ],
    "name:nno_x_preferred":[
        "Askim kommune"
    ],
    "name:nor_x_preferred":[
        "Askim"
    ],
    "name:pol_x_preferred":[
        "Askim"
    ],
    "name:por_x_preferred":[
        "Askim"
    ],
    "name:ron_x_preferred":[
        "Askim"
    ],
    "name:rus_x_preferred":[
        "\u0410\u0448\u0438\u043c"
    ],
    "name:sme_x_preferred":[
        "Askim"
    ],
    "name:spa_x_preferred":[
        "Askim"
    ],
    "name:sqi_x_preferred":[
        "Askim"
    ],
    "name:srp_x_preferred":[
        "\u0410\u0448\u0438\u043c"
    ],
    "name:swe_x_preferred":[
        "Askims kommun"
    ],
    "name:szl_x_preferred":[
        "Askim"
    ],
    "name:tur_x_preferred":[
        "Askim"
    ],
    "name:war_x_preferred":[
        "Askim"
    ],
    "name:zho_x_preferred":[
        "\u963f\u5e0c\u59c6"
    ],
    "wof:name":"Askim",
    "wof:placetype":"neighbourhood"
},
  "geometry": {"coordinates":[11.93931585535144,57.63919524047328],"type":"Point"}
}