{
  "type": "Feature",
  "properties": {
    "iso:country":"SE",
    "wof:name":"Askim",
    "wof:placetype":"neighbourhood"
},
  "geometry": {"coordinates":[11.93931585535144,57.63919524047328],"type":"Point"}
}