{
  "type": "Feature",
  "properties": {
    "gn:admin1_code":"5.0",
    "gn:admin2_code":"980.0",
    "gn:asciiname":"Eskelhem",
    "gn:country_code":"SE",
    "gn:dem":21,
    "gn:feature_class":"P",
    "gn:feature_code":"PPL",
    "gn:name":"Eskelhem",
    "gn:population":0,
    "gn:timezone":"Europe/Stockholm",
    "iso:country":"SE",
    "wof:name":"Eskelhem",
    "wof:placetype":"locality"
},
  "geometry": {"coordinates":[18.21638,57.48778000000001],"type":"Point"}
}