{
  "type": "Feature",
  "properties": {
    "gn:admin1_code":"28.0",
    "gn:admin2_code":"1438.0",
    "gn:asciiname":"Rorviken",
    "gn:country_code":"SE",
    "gn:dem":109,
    "gn:feature_class":"P",
    "gn:feature_code":"PPL",
    "gn:name":"R\u00f6rviken",
    "gn:population":0,
    "gn:timezone":"Europe/Stockholm",
    "iso:country":"SE",
    "name:nor_x_preferred":[
        "R\u00f6rviken"
    ],
    "name:nor_x_variant":[
        "R\u00f8rviken"
    ],
    "wof:name":"Rorviken",
    "wof:placetype":"locality"
},
  "geometry": {"coordinates":[11.81667,59.11666999999999],"type":"Point"}
}