{
  "type": "Feature",
  "properties": {
    "gn:admin1_code":"22.0",
    "gn:admin2_code":"1784.0",
    "gn:asciiname":"Sodra Fjall",
    "gn:cc2":"SE",
    "gn:country_code":"SE",
    "gn:dem":76,
    "gn:feature_class":"P",
    "gn:feature_code":"PPL",
    "gn:name":"S\u00f6dra Fj\u00e4ll",
    "gn:population":0,
    "gn:timezone":"Europe/Stockholm",
    "iso:country":"SE",
    "name:und_x_variant":[
        "Fj\u00e4ll",
        "S\u00f6dra Fj\u00e4ll"
    ],
    "wof:name":"Sodra Fjall",
    "wof:placetype":"locality"
},
  "geometry": {"coordinates":[12.78306,59.53306],"type":"Point"}
}