{
  "type": "Feature",
  "properties": {
    "gn:admin1_code":"24.0",
    "gn:admin2_code":"2260.0",
    "gn:admin3_code":"226004.0",
    "gn:admin4_code":"2502.0",
    "gn:asciiname":"Saxen",
    "gn:country_code":"SE",
    "gn:dem":452,
    "gn:feature_class":"P",
    "gn:feature_code":"PPL",
    "gn:name":"Saxen",
    "gn:population":0,
    "gn:timezone":"Europe/Stockholm",
    "iso:country":"SE",
    "name:ceb_x_preferred":[
        "Saxen"
    ],
    "name:deu_x_preferred":[
        "Saxen"
    ],
    "name:fas_x_preferred":[
        "\u0632\u0627\u06a9\u0633\u0646"
    ],
    "name:fra_x_preferred":[
        "Saxen"
    ],
    "name:hun_x_preferred":[
        "Saxen"
    ],
    "name:ita_x_preferred":[
        "Saxen"
    ],
    "name:kaz_x_preferred":[
        "\u0417\u0430\u043a\u0441\u0435\u043d"
    ],
    "name:nld_x_preferred":[
        "Saxen"
    ],
    "name:pol_x_preferred":[
        "Saxen"
    ],
    "name:por_x_preferred":[
        "Saxen"
    ],
    "name:rus_x_preferred":[
        "\u0417\u0430\u043a\u0441\u0435\u043d"
    ],
    "name:slk_x_preferred":[
        "Saxen"
    ],
    "name:spa_x_preferred":[
        "Saxen"
    ],
    "name:swe_x_preferred":[
        "Saxen"
    ],
    "name:uzb_x_preferred":[
        "Saxen"
    ],
    "name:vie_x_preferred":[
        "Saxen"
    ],
    "name:vol_x_preferred":[
        "Saxen"
    ],
    "name:war_x_preferred":[
        "Saxen"
    ],
    "name:zho_x_preferred":[
        "\u8428\u514b\u68ee"
    ],
    "wof:name":"Saxen",
    "wof:placetype":"locality"
},
  "geometry": {"coordinates":[16.33238,62.32288000000001],"type":"Point"}
}