{
  "type": "Feature",
  "properties": {
    "gn:admin1_code":"21.0",
    "gn:admin2_code":"380.0",
    "gn:asciiname":"Tensta",
    "gn:country_code":"SE",
    "gn:dem":18,
    "gn:feature_class":"P",
    "gn:feature_code":"PPL",
    "gn:name":"Tensta",
    "gn:population":0,
    "gn:timezone":"Europe/Stockholm",
    "iso:country":"SE",
    "name:cat_x_preferred":[
        "Tensta"
    ],
    "name:ces_x_preferred":[
        "Tensta"
    ],
    "name:fas_x_preferred":[
        "\u062a\u06cc\u0646\u0633\u062a\u0627"
    ],
    "name:fin_x_preferred":[
        "Tensta"
    ],
    "name:fra_x_preferred":[
        "Tensta"
    ],
    "name:ita_x_preferred":[
        "Tensta"
    ],
    "name:nld_x_preferred":[
        "Tensta"
    ],
    "name:nor_x_preferred":[
        "Tensta"
    ],
    "name:pol_x_preferred":[
        "Tensta"
    ],
    "name:por_x_preferred":[
        "Tensta"
    ],
    "name:spa_x_preferred":[
        "Tensta"
    ],
    "name:swe_x_preferred":[
        "Tensta"
    ],
    "wof:name":"Tensta",
    "wof:placetype":"locality"
},
  "geometry": {"coordinates":[17.66667,60.03306],"type":"Point"}
}