{
  "type": "Feature",
  "properties": {
    "gn:admin1_code":"14.0",
    "gn:admin2_code":"2523.0",
    "gn:asciiname":"Suobbat",
    "gn:cc2":"SE",
    "gn:country_code":"SE",
    "gn:dem":290,
    "gn:feature_class":"P",
    "gn:feature_code":"PPL",
    "gn:name":"Suobbat",
    "gn:population":0,
    "gn:timezone":"Europe/Stockholm",
    "iso:country":"SE",
    "name:und_x_variant":[
        "Suppat",
        "Suobbat"
    ],
    "wof:name":"Suobbat",
    "wof:placetype":"locality"
},
  "geometry": {"coordinates":[21.85,66.45],"type":"Point"}
}