{
  "type": "Feature",
  "properties": {
    "gn:admin1_code":"24",
    "gn:admin2_code":"2260.0",
    "gn:admin3_code":"226002.0",
    "gn:admin4_code":"2455.0",
    "gn:asciiname":"Vaesterede",
    "gn:country_code":"SE",
    "gn:dem":130,
    "gn:feature_class":"P",
    "gn:feature_code":"PPL",
    "gn:name":"V\u00e4sterede",
    "gn:population":0,
    "gn:timezone":"Europe/Stockholm",
    "iso:country":"SE",
    "wof:name":"Vaesterede",
    "wof:placetype":"locality"
},
  "geometry": {"coordinates":[15.82761,62.53488],"type":"Point"}
}