{
  "type": "Feature",
  "properties": {
    "gn:admin1_code":"23.0",
    "gn:admin2_code":"2418.0",
    "gn:asciiname":"Kuorbevare",
    "gn:cc2":"SE",
    "gn:country_code":"SE",
    "gn:dem":436,
    "gn:feature_class":"P",
    "gn:feature_code":"PPL",
    "gn:name":"Kuorbevare",
    "gn:population":0,
    "gn:timezone":"Europe/Stockholm",
    "iso:country":"SE",
    "name:und_x_variant":[
        "Kvorbevare",
        "Kuorbevare"
    ],
    "wof:name":"Kuorbevare",
    "wof:placetype":"locality"
},
  "geometry": {"coordinates":[18.66667,65.36667],"type":"Point"}
}