{
  "type": "Feature",
  "properties": {
    "gn:admin1_code":"12.0",
    "gn:admin2_code":"765.0",
    "gn:asciiname":"Varaberga",
    "gn:country_code":"SE",
    "gn:dem":148,
    "gn:feature_class":"P",
    "gn:feature_code":"PPL",
    "gn:name":"V\u00e4raberga",
    "gn:population":0,
    "gn:timezone":"Europe/Stockholm",
    "iso:country":"SE",
    "wof:name":"Varaberga",
    "wof:placetype":"locality"
},
  "geometry": {"coordinates":[13.96667,56.58333],"type":"Point"}
}