{
  "type": "Feature",
  "properties": {
    "gn:admin1_code":"27.0",
    "gn:admin2_code":"1280.0",
    "gn:asciiname":"Gullvik",
    "gn:country_code":"SE",
    "gn:dem":27,
    "gn:feature_class":"P",
    "gn:feature_code":"PPL",
    "gn:name":"Gullvik",
    "gn:population":0,
    "gn:timezone":"Europe/Stockholm",
    "iso:country":"SE",
    "name:nld_x_preferred":[
        "Gullvik"
    ],
    "name:swe_x_preferred":[
        "Gullvik"
    ],
    "wof:name":"Gullvik",
    "wof:placetype":"locality"
},
  "geometry": {"coordinates":[13.01667,55.56667],"type":"Point"}
}