{
  "type": "Feature",
  "properties": {
    "gn:admin1_code":"28.0",
    "gn:admin2_code":"1435.0",
    "gn:asciiname":"Rorvik",
    "gn:country_code":"SE",
    "gn:dem":61,
    "gn:feature_class":"P",
    "gn:feature_code":"PPL",
    "gn:name":"R\u00f6rvik",
    "gn:population":0,
    "gn:timezone":"Europe/Stockholm",
    "iso:country":"SE",
    "name:nor_x_preferred":[
        "R\u00f6rvik"
    ],
    "name:nor_x_variant":[
        "R\u00f8rvik"
    ],
    "name:und_x_variant":[
        "R\u00f6rvik"
    ],
    "wof:name":"Rorvik",
    "wof:placetype":"locality"
},
  "geometry": {"coordinates":[11.28333,58.55],"type":"Point"}
}