{
  "type": "Feature",
  "properties": {
    "gn:admin1_code":"9.0",
    "gn:admin2_code":"834.0",
    "gn:asciiname":"Stora Glosebo",
    "gn:cc2":"SE",
    "gn:country_code":"SE",
    "gn:dem":111,
    "gn:feature_class":"P",
    "gn:feature_code":"PPL",
    "gn:name":"Stora Glosebo",
    "gn:population":0,
    "gn:timezone":"Europe/Stockholm",
    "iso:country":"SE",
    "name:und_x_variant":[
        "Glosebo",
        "Stora Glosebo"
    ],
    "wof:name":"Stora Glosebo",
    "wof:placetype":"locality"
},
  "geometry": {"coordinates":[15.78333,56.48333],"type":"Point"}
}