{
  "type": "Feature",
  "properties": {
    "gn:gn_country":"SE",
    "gn:gn_fcode":"PPL",
    "gn:gn_pop":238,
    "gn:population":250,
    "iso:country":"SE",
    "name:ceb_x_preferred":[
        "Ingelstr\u00e4de"
    ],
    "name:eng_x_preferred":[
        "Ingelstr\u00e4de"
    ],
    "name:ita_x_preferred":[
        "Ingelstr\u00e4de"
    ],
    "name:nan_x_preferred":[
        "Ingelstr\u00e4de"
    ],
    "name:nld_x_preferred":[
        "Ingelstr\u00e4de"
    ],
    "name:nno_x_preferred":[
        "Ingelstr\u00e4de"
    ],
    "name:nob_x_preferred":[
        "Ingelstr\u00e4de"
    ],
    "name:swe_x_preferred":[
        "Ingelstr\u00e4de"
    ],
    "qs_pg:aaroncc":"SE",
    "qs_pg:gn_country":"SE",
    "qs_pg:gn_fcode":"PPL",
    "qs_pg:gn_pop":238,
    "qs_pg:name":"Ingelstr\u00e4de",
    "qs_pg:name_adm0":"Sverige",
    "qs_pg:name_adm1":"Sk\u00e5ne L\u00e4n",
    "qs_pg:photos":19,
    "qs_pg:photos_1k":4,
    "qs_pg:photos_9k":1,
    "qs_pg:photos_9r":1,
    "qs_pg:photos_all":19,
    "qs_pg:photos_sr":1,
    "qs_pg:pop_sr":2,
    "qs_pg:qs_pg_placetype":"locality",
    "qs_pg:qs_pg_placetype_gp":"Town",
    "qs_pg:woe_adm0":23424954,
    "woe:adm0_id":23424954,
    "woe:name_adm0":"Sverige",
    "woe:name_adm1":"Sk\u00e5ne L\u00e4n",
    "woe:placetype":"Town",
    "wof:name":"Ingelstr\u00e4de",
    "wof:placetype":"locality",
    "wof:population":250
},
  "geometry": {"coordinates":[12.61667,56.18333],"type":"Point"}
}