{
  "type": "Feature",
  "properties": {
    "gn:admin1_code":"6.0",
    "gn:admin2_code":"1315.0",
    "gn:asciiname":"Langaryd",
    "gn:country_code":"SE",
    "gn:dem":149,
    "gn:feature_class":"P",
    "gn:feature_code":"PPL",
    "gn:name":"L\u00e5ngaryd",
    "gn:population":0,
    "gn:timezone":"Europe/Stockholm",
    "iso:country":"SE",
    "name:und_x_variant":[
        "L\u00e5ngaryd"
    ],
    "wof:name":"Langaryd",
    "wof:placetype":"locality"
},
  "geometry": {"coordinates":[13.35,57.03333000000001],"type":"Point"}
}