{
  "type": "Feature",
  "properties": {
    "gn:admin1_code":"28.0",
    "gn:admin2_code":"1489.0",
    "gn:asciiname":"Ranne",
    "gn:country_code":"SE",
    "gn:dem":116,
    "gn:feature_class":"P",
    "gn:feature_code":"PPL",
    "gn:name":"R\u00e4nne",
    "gn:population":0,
    "gn:timezone":"Europe/Stockholm",
    "iso:country":"SE",
    "wof:name":"Ranne",
    "wof:placetype":"locality"
},
  "geometry": {"coordinates":[12.66667,58.13333000000001],"type":"Point"}
}