{
  "type": "Feature",
  "properties": {
    "gn:admin1_code":"16.0",
    "gn:admin2_code":"581.0",
    "gn:asciiname":"Balderum",
    "gn:country_code":"SE",
    "gn:dem":40,
    "gn:feature_class":"P",
    "gn:feature_code":"PPL",
    "gn:name":"Balderum",
    "gn:population":0,
    "gn:timezone":"Europe/Stockholm",
    "iso:country":"SE",
    "wof:name":"Balderum",
    "wof:placetype":"locality"
},
  "geometry": {"coordinates":[15.78333,58.58333],"type":"Point"}
}