{
  "type": "Feature",
  "properties": {
    "gn:admin1_code":"7.0",
    "gn:admin2_code":"2326.0",
    "gn:asciiname":"Kesuvallen",
    "gn:country_code":"SE",
    "gn:dem":978,
    "gn:feature_class":"P",
    "gn:feature_code":"PPL",
    "gn:name":"Kesuvallen",
    "gn:population":0,
    "gn:timezone":"Europe/Stockholm",
    "iso:country":"SE",
    "wof:name":"Kesuvallen",
    "wof:placetype":"locality"
},
  "geometry": {"coordinates":[12.66667,62.88333000000001],"type":"Point"}
}