{
  "type": "Feature",
  "properties": {
    "gn:admin1_code":"23.0",
    "gn:admin2_code":"2482.0",
    "gn:asciiname":"Bygdetrask",
    "gn:country_code":"SE",
    "gn:dem":132,
    "gn:feature_class":"P",
    "gn:feature_code":"PPL",
    "gn:name":"Bygdetr\u00e4sk",
    "gn:population":0,
    "gn:timezone":"Europe/Stockholm",
    "iso:country":"SE",
    "name:und_x_variant":[
        "Bygdetr\u00e4sk"
    ],
    "wof:name":"Bygdetrask",
    "wof:placetype":"locality"
},
  "geometry": {"coordinates":[20.53333,64.43333],"type":"Point"}
}