{
  "type": "Feature",
  "properties": {
    "gn:admin1_code":"23.0",
    "gn:admin2_code":"2463.0",
    "gn:asciiname":"Torvsjo",
    "gn:cc2":"SE",
    "gn:country_code":"SE",
    "gn:dem":389,
    "gn:feature_class":"P",
    "gn:feature_code":"PPL",
    "gn:name":"Torvsj\u00f6",
    "gn:population":0,
    "gn:timezone":"Europe/Stockholm",
    "iso:country":"SE",
    "name:nor_x_preferred":[
        "Torvsj\u00f6"
    ],
    "name:nor_x_variant":[
        "Torvsj\u00f8"
    ],
    "name:und_x_variant":[
        "Torfsj\u00f6"
    ],
    "wof:name":"Torvsjo",
    "wof:placetype":"locality"
},
  "geometry": {"coordinates":[17.26667,64.38333],"type":"Point"}
}