{
  "type": "Feature",
  "properties": {
    "gn:admin1_code":"2.0",
    "gn:admin2_code":"1081.0",
    "gn:asciiname":"Kalleberga",
    "gn:country_code":"SE",
    "gn:dem":51,
    "gn:feature_class":"P",
    "gn:feature_code":"PPL",
    "gn:name":"Kalleberga",
    "gn:population":0,
    "gn:timezone":"Europe/Stockholm",
    "iso:country":"SE",
    "wof:name":"Kalleberga",
    "wof:placetype":"locality"
},
  "geometry": {"coordinates":[15.28333,56.25],"type":"Point"}
}