{
  "type": "Feature",
  "properties": {
    "gn:gn_country":"SE",
    "gn:gn_fcode":"PPL",
    "gn:gn_pop":0,
    "iso:country":"SE",
    "name:dan_x_preferred":[
        "J\u00e4rrestad"
    ],
    "name:deu_x_preferred":[
        "J\u00e4rrestad"
    ],
    "name:eng_x_preferred":[
        "J\u00e4rrestad"
    ],
    "name:fao_x_preferred":[
        "J\u00e4rrestad"
    ],
    "name:fra_x_preferred":[
        "J\u00e4rrestad"
    ],
    "name:nds_x_preferred":[
        "J\u00e4rrestad"
    ],
    "name:nld_x_preferred":[
        "J\u00e4rrestad"
    ],
    "name:nno_x_preferred":[
        "J\u00e4rrestad"
    ],
    "name:nob_x_preferred":[
        "J\u00e4rrestad"
    ],
    "name:swe_x_preferred":[
        "J\u00e4rrestad"
    ],
    "qs_pg:aaroncc":"SE",
    "qs_pg:gn_country":"SE",
    "qs_pg:gn_fcode":"PPL",
    "qs_pg:gn_pop":0,
    "qs_pg:name":"J\u00e4rrestad",
    "qs_pg:name_adm0":"Sverige",
    "qs_pg:name_adm1":"Sk\u00e5ne L\u00e4n",
    "qs_pg:photos":24,
    "qs_pg:photos_1k":5,
    "qs_pg:photos_9k":1,
    "qs_pg:photos_9r":1,
    "qs_pg:photos_all":24,
    "qs_pg:photos_sr":1,
    "qs_pg:pop_sr":0,
    "qs_pg:qs_pg_placetype":"locality",
    "qs_pg:qs_pg_placetype_gp":"Town",
    "qs_pg:woe_adm0":23424954,
    "woe:adm0_id":23424954,
    "woe:name_adm0":"Sverige",
    "woe:name_adm1":"Sk\u00e5ne L\u00e4n",
    "woe:placetype":"Town",
    "wof:name":"J\u00e4rrestad",
    "wof:placetype":"locality"
},
  "geometry": {"coordinates":[14.26667,55.53333],"type":"Point"}
}