{
  "type": "Feature",
  "properties": {
    "gn:admin1_code":"3.0",
    "gn:admin2_code":"2184.0",
    "gn:admin3_code":"218404.0",
    "gn:admin4_code":"2434.0",
    "gn:asciiname":"Blasta",
    "gn:country_code":"SE",
    "gn:dem":20,
    "gn:feature_class":"P",
    "gn:feature_code":"PPL",
    "gn:name":"Bl\u00e4sta",
    "gn:population":0,
    "gn:timezone":"Europe/Stockholm",
    "iso:country":"SE",
    "wof:name":"Blasta",
    "wof:placetype":"locality"
},
  "geometry": {"coordinates":[17.19103,61.75826],"type":"Point"}
}