{
  "type": "Feature",
  "properties": {
    "gn:admin1_code":"24.0",
    "gn:admin2_code":"2280.0",
    "gn:admin3_code":"228006.0",
    "gn:admin4_code":"2499.0",
    "gn:asciiname":"Kittjarn",
    "gn:country_code":"SE",
    "gn:dem":106,
    "gn:feature_class":"P",
    "gn:feature_code":"PPL",
    "gn:name":"Kittj\u00e4rn",
    "gn:population":0,
    "gn:timezone":"Europe/Stockholm",
    "iso:country":"SE",
    "wof:name":"Kittjarn",
    "wof:placetype":"locality"
},
  "geometry": {"coordinates":[17.83192,62.61429],"type":"Point"}
}