{
  "type": "Feature",
  "properties": {
    "gn:admin1_code":"27.0",
    "gn:admin2_code":"1273.0",
    "gn:asciiname":"Hanavra",
    "gn:country_code":"SE",
    "gn:dem":137,
    "gn:feature_class":"P",
    "gn:feature_code":"PPL",
    "gn:name":"Hanavr\u00e5",
    "gn:population":0,
    "gn:timezone":"Europe/Stockholm",
    "iso:country":"SE",
    "wof:name":"Hanavra",
    "wof:placetype":"locality"
},
  "geometry": {"coordinates":[13.81667,56.41667],"type":"Point"}
}