{
  "type": "Feature",
  "properties": {
    "gn:admin1_code":"21.0",
    "gn:admin2_code":"380.0",
    "gn:asciiname":"Finsta",
    "gn:cc2":"SE",
    "gn:country_code":"SE",
    "gn:dem":36,
    "gn:feature_class":"P",
    "gn:feature_code":"PPL",
    "gn:name":"Finsta",
    "gn:population":0,
    "gn:timezone":"Europe/Stockholm",
    "iso:country":"SE",
    "name:fin_x_preferred":[
        "Finsta"
    ],
    "name:ita_x_preferred":[
        "Finsta"
    ],
    "name:nld_x_preferred":[
        "Finsta"
    ],
    "name:nor_x_preferred":[
        "Finsta"
    ],
    "name:swe_x_preferred":[
        "Finsta"
    ],
    "name:und_x_variant":[
        "Finnsta"
    ],
    "wof:name":"Finsta",
    "wof:placetype":"locality"
},
  "geometry": {"coordinates":[17.43333,59.86666999999999],"type":"Point"}
}