{
  "type": "Feature",
  "properties": {
    "gn:admin1_code":"9.0",
    "gn:admin2_code":"821.0",
    "gn:asciiname":"Hogsbyarhult",
    "gn:country_code":"SE",
    "gn:dem":180,
    "gn:feature_class":"P",
    "gn:feature_code":"PPL",
    "gn:name":"Hogsby\u00e5rhult",
    "gn:population":0,
    "gn:timezone":"Europe/Stockholm",
    "iso:country":"SE",
    "wof:name":"Hogsbyarhult",
    "wof:placetype":"locality"
},
  "geometry": {"coordinates":[15.73333,57.08333],"type":"Point"}
}