{
  "type": "Feature",
  "properties": {
    "gn:admin1_code":"23.0",
    "gn:admin2_code":"2422.0",
    "gn:asciiname":"Vuvosberg",
    "gn:country_code":"SE",
    "gn:dem":479,
    "gn:feature_class":"P",
    "gn:feature_code":"PPL",
    "gn:name":"Vuvosberg",
    "gn:population":0,
    "gn:timezone":"Europe/Stockholm",
    "iso:country":"SE",
    "wof:name":"Vuvosberg",
    "wof:placetype":"locality"
},
  "geometry": {"coordinates":[16.65,65.86667],"type":"Point"}
}