{
  "type": "Feature",
  "properties": {
    "gn:admin1_code":"22.0",
    "gn:admin2_code":"1780.0",
    "gn:asciiname":"Hallsbyn",
    "gn:cc2":"SE",
    "gn:country_code":"SE",
    "gn:dem":130,
    "gn:feature_class":"P",
    "gn:feature_code":"PPL",
    "gn:name":"H\u00e5llsbyn",
    "gn:population":0,
    "gn:timezone":"Europe/Stockholm",
    "iso:country":"SE",
    "name:und_x_variant":[
        "H\u00e5ltsbyn",
        "H\u00e5llsbyn"
    ],
    "wof:name":"Hallsbyn",
    "wof:placetype":"locality"
},
  "geometry": {"coordinates":[13.63333,59.66667],"type":"Point"}
}