{
  "type": "Feature",
  "properties": {
    "gn:gn_country":"SE",
    "gn:gn_fcode":"PPLX",
    "gn:gn_pop":0,
    "iso:country":"SE",
    "qs_pg:aaroncc":"SE",
    "qs_pg:gn_country":"SE",
    "qs_pg:gn_fcode":"PPLX",
    "qs_pg:gn_pop":0,
    "qs_pg:name":"Yttermora",
    "qs_pg:name_adm0":"Sverige",
    "qs_pg:name_adm1":"Dalarnas L\u00e4n",
    "qs_pg:photos":1,
    "qs_pg:photos_1k":1,
    "qs_pg:photos_9k":1,
    "qs_pg:photos_9r":1,
    "qs_pg:photos_all":1,
    "qs_pg:photos_sr":1,
    "qs_pg:pop_sr":0,
    "qs_pg:qs_pg_placetype":"neighbourhood",
    "qs_pg:qs_pg_placetype_gp":"Suburb",
    "qs_pg:woe_adm0":23424954,
    "woe:adm0_id":23424954,
    "woe:name_adm0":"Sverige",
    "woe:name_adm1":"Dalarnas L\u00e4n",
    "woe:placetype":"Suburb",
    "wof:name":"Yttermora",
    "wof:placetype":"neighbourhood"
},
  "geometry": {"coordinates":[15.41667,60.51667],"type":"Point"}
}