{
  "type": "Feature",
  "properties": {
    "gn:country":"SE",
    "gn:fcode":"PPL",
    "gn:population":0,
    "iso:country":"SE",
    "name:dan_x_preferred":[
        "S\u00f6rberge"
    ],
    "name:deu_x_preferred":[
        "S\u00f6rberge"
    ],
    "name:eng_x_preferred":[
        "S\u00f6rberge"
    ],
    "name:gle_x_preferred":[
        "S\u00f6rberge"
    ],
    "name:lld_x_preferred":[
        "S\u00f6rberge"
    ],
    "name:nor_x_preferred":[
        "S\u00f8rberge"
    ],
    "name:nor_x_variant":[
        "S\u00f6rberge"
    ],
    "name:swe_x_preferred":[
        "S\u00f6rberge"
    ],
    "qs_pg:aaroncc":"SE",
    "qs_pg:gn_country":"SE",
    "qs_pg:gn_fcode":"PPL",
    "qs_pg:gn_pop":0,
    "qs_pg:name":"S\u00f6rberge",
    "qs_pg:name_adm0":"Sverige",
    "qs_pg:name_adm1":"V\u00e4sternorrlands L\u00e4n",
    "qs_pg:photos":25,
    "qs_pg:photos_1k":5,
    "qs_pg:photos_9k":1,
    "qs_pg:photos_9r":1,
    "qs_pg:photos_all":25,
    "qs_pg:photos_sr":1,
    "qs_pg:pop_sr":0,
    "qs_pg:qs_pg_placetype":"locality",
    "qs_pg:qs_pg_placetype_gp":"Town",
    "qs_pg:woe_adm0":23424954,
    "woe:adm0_id":23424954,
    "woe:name_adm0":"Sverige",
    "woe:name_adm1":"V\u00e4sternorrlands L\u00e4n",
    "woe:placetype":"Town",
    "wof:name":"S\u00f6rberge",
    "wof:placetype":"locality"
},
  "geometry": {"coordinates":[17.37139,62.51],"type":"Point"}
}