{
  "type": "Feature",
  "properties": {
    "gn:admin1_code":"7.0",
    "gn:admin2_code":"2309.0",
    "gn:asciiname":"Norra Vike",
    "gn:country_code":"SE",
    "gn:dem":308,
    "gn:feature_class":"P",
    "gn:feature_code":"PPL",
    "gn:name":"Norra Vike",
    "gn:population":0,
    "gn:timezone":"Europe/Stockholm",
    "iso:country":"SE",
    "wof:name":"Norra Vike",
    "wof:placetype":"locality"
},
  "geometry": {"coordinates":[14.46667,63.25],"type":"Point"}
}