{
  "type": "Feature",
  "properties": {
    "gn:admin1_code":"9.0",
    "gn:asciiname":"Ytterby",
    "gn:country_code":"SE",
    "gn:dem":15,
    "gn:feature_class":"P",
    "gn:feature_code":"PPL",
    "gn:name":"Ytterby",
    "gn:population":0,
    "gn:timezone":"Europe/Stockholm",
    "iso:country":"SE",
    "name:cat_x_preferred":[
        "Ytterby"
    ],
    "name:dan_x_preferred":[
        "Ytterby grube"
    ],
    "name:deu_x_preferred":[
        "Grube Ytterby"
    ],
    "name:epo_x_preferred":[
        "Ytterby"
    ],
    "name:fin_x_preferred":[
        "Ytterby"
    ],
    "name:fra_x_preferred":[
        "Ytterby"
    ],
    "name:heb_x_preferred":[
        "\u05d0\u05d9\u05d8\u05e8\u05d1\u05d9"
    ],
    "name:hrv_x_preferred":[
        "Ytterby"
    ],
    "name:ita_x_preferred":[
        "Ytterby"
    ],
    "name:jpn_x_preferred":[
        "\u30a4\u30c3\u30c6\u30eb\u30d3\u30fc"
    ],
    "name:kor_x_preferred":[
        "\uc704\ud14c\ub974\ubdd4"
    ],
    "name:lav_x_preferred":[
        "Iterb\u012b"
    ],
    "name:lit_x_preferred":[
        "Iterbiu"
    ],
    "name:nld_x_preferred":[
        "Ytterby"
    ],
    "name:nno_x_preferred":[
        "Ytterby gruve"
    ],
    "name:nor_x_preferred":[
        "Ytterby gruve"
    ],
    "name:pol_x_preferred":[
        "Ytterby"
    ],
    "name:por_x_preferred":[
        "Ytterby"
    ],
    "name:rus_x_preferred":[
        "\u0418\u0442\u0442\u0435\u0440\u0431\u044e"
    ],
    "name:spa_x_preferred":[
        "Ytterby"
    ],
    "name:swe_x_preferred":[
        "Ytterby gruva"
    ],
    "name:ukr_x_preferred":[
        "\u0406\u0442\u0442\u0435\u0440\u0431\u044e"
    ],
    "name:vie_x_preferred":[
        "Ytterby"
    ],
    "name:zho_x_preferred":[
        "\u4f0a\u7279\u6bd4"
    ],
    "wof:name":"Ytterby",
    "wof:placetype":"locality"
},
  "geometry": {"coordinates":[16.78333,57.98333],"type":"Point"}
}