{
  "type": "Feature",
  "properties": {
    "gn:gn_country":"SE",
    "gn:gn_fcode":"PPL",
    "gn:gn_pop":477,
    "gn:population":488,
    "iso:country":"SE",
    "name:ceb_x_preferred":[
        "Sj\u00f6sa"
    ],
    "name:eng_x_preferred":[
        "Sj\u00f6sa"
    ],
    "name:ita_x_preferred":[
        "Sj\u00f6sa"
    ],
    "name:nan_x_preferred":[
        "Sj\u00f6sa"
    ],
    "name:nld_x_preferred":[
        "Sj\u00f6sa"
    ],
    "name:nno_x_preferred":[
        "Sj\u00f6sa"
    ],
    "name:nob_x_preferred":[
        "Sj\u00f6sa"
    ],
    "name:nor_x_preferred":[
        "Sj\u00f8sa"
    ],
    "name:nor_x_variant":[
        "Sj\u00f6sa"
    ],
    "name:pol_x_preferred":[
        "Sj\u00f6sa"
    ],
    "name:swe_x_preferred":[
        "Sj\u00f6sa"
    ],
    "qs_pg:aaroncc":"SE",
    "qs_pg:gn_country":"SE",
    "qs_pg:gn_fcode":"PPL",
    "qs_pg:gn_pop":477,
    "qs_pg:name":"Sj\u00f6sa",
    "qs_pg:name_adm0":"Sverige",
    "qs_pg:name_adm1":"S\u00f6dermanlands L\u00e4n",
    "qs_pg:photos_9k":1,
    "qs_pg:photos_9r":1,
    "qs_pg:photos_all":1,
    "qs_pg:photos_sr":0,
    "qs_pg:pop_sr":2,
    "qs_pg:qs_pg_placetype":"locality",
    "qs_pg:qs_pg_placetype_gp":"Town",
    "qs_pg:woe_adm0":23424954,
    "woe:adm0_id":23424954,
    "woe:name_adm0":"Sverige",
    "woe:name_adm1":"S\u00f6dermanlands L\u00e4n",
    "woe:placetype":"Town",
    "wof:name":"Sj\u00f6sa",
    "wof:placetype":"locality",
    "wof:population":488
},
  "geometry": {"coordinates":[17.08333,58.76667],"type":"Point"}
}