{
  "type": "Feature",
  "properties": {
    "gn:admin1_code":"3.0",
    "gn:admin2_code":"2161.0",
    "gn:asciiname":"Letsbo",
    "gn:country_code":"SE",
    "gn:dem":145,
    "gn:feature_class":"P",
    "gn:feature_code":"PPL",
    "gn:name":"Letsbo",
    "gn:population":0,
    "gn:timezone":"Europe/Stockholm",
    "iso:country":"SE",
    "wof:name":"Letsbo",
    "wof:placetype":"locality"
},
  "geometry": {"coordinates":[15.86667,61.93333000000001],"type":"Point"}
}