{
  "type": "Feature",
  "properties": {
    "gn:admin1_code":"7.0",
    "gn:admin2_code":"2361.0",
    "gn:asciiname":"Angersjo",
    "gn:country_code":"SE",
    "gn:dem":397,
    "gn:feature_class":"P",
    "gn:feature_code":"PPL",
    "gn:name":"\u00c4ngersj\u00f6",
    "gn:population":0,
    "gn:timezone":"Europe/Stockholm",
    "iso:country":"SE",
    "wof:name":"Angersjo",
    "wof:placetype":"locality"
},
  "geometry": {"coordinates":[14.86667,61.98333],"type":"Point"}
}