{
  "type": "Feature",
  "properties": {
    "gn:admin1_code":"23.0",
    "gn:admin2_code":"2462.0",
    "gn:asciiname":"Karlsbacka",
    "gn:country_code":"SE",
    "gn:dem":404,
    "gn:feature_class":"P",
    "gn:feature_code":"PPL",
    "gn:name":"Karlsbacka",
    "gn:population":0,
    "gn:timezone":"Europe/Stockholm",
    "iso:country":"SE",
    "wof:name":"Karlsbacka",
    "wof:placetype":"locality"
},
  "geometry": {"coordinates":[16.55,64.61667],"type":"Point"}
}