{
  "type": "Feature",
  "properties": {
    "gn:admin1_code":"22.0",
    "gn:admin2_code":"1765.0",
    "gn:asciiname":"Vaxlanda",
    "gn:country_code":"SE",
    "gn:dem":162,
    "gn:feature_class":"P",
    "gn:feature_code":"PPL",
    "gn:name":"V\u00e5xlanda",
    "gn:population":0,
    "gn:timezone":"Europe/Stockholm",
    "iso:country":"SE",
    "wof:name":"Vaxlanda",
    "wof:placetype":"locality"
},
  "geometry": {"coordinates":[12.13333,59.46666999999999],"type":"Point"}
}