{
  "type": "Feature",
  "properties": {
    "gn:admin1_code":"26.0",
    "gn:admin2_code":"188.0",
    "gn:asciiname":"Kulla",
    "gn:country_code":"SE",
    "gn:dem":19,
    "gn:feature_class":"P",
    "gn:feature_code":"PPL",
    "gn:name":"Kulla",
    "gn:population":0,
    "gn:timezone":"Europe/Stockholm",
    "iso:country":"SE",
    "name:deu_x_preferred":[
        "Kulla"
    ],
    "name:fin_x_preferred":[
        "Kulla"
    ],
    "name:swe_x_preferred":[
        "Kulla"
    ],
    "wof:name":"Kulla",
    "wof:placetype":"locality"
},
  "geometry": {"coordinates":[19.05,59.85],"type":"Point"}
}