{
  "type": "Feature",
  "properties": {
    "gn:admin1_code":"28.0",
    "gn:admin2_code":"1499.0",
    "gn:asciiname":"Ravelstorp",
    "gn:country_code":"SE",
    "gn:dem":224,
    "gn:feature_class":"P",
    "gn:feature_code":"PPL",
    "gn:name":"Ravelstorp",
    "gn:population":0,
    "gn:timezone":"Europe/Stockholm",
    "iso:country":"SE",
    "wof:name":"Ravelstorp",
    "wof:placetype":"locality"
},
  "geometry": {"coordinates":[13.43333,58.16667],"type":"Point"}
}