{
  "type": "Feature",
  "properties": {
    "gn:admin1_code":"24.0",
    "gn:admin2_code":"2280.0",
    "gn:admin3_code":"228003.0",
    "gn:admin4_code":"2469.0",
    "gn:asciiname":"Malviken",
    "gn:cc2":"SE",
    "gn:country_code":"SE",
    "gn:dem":-9999,
    "gn:feature_class":"P",
    "gn:feature_code":"PPL",
    "gn:name":"Malviken",
    "gn:population":0,
    "gn:timezone":"Europe/Stockholm",
    "iso:country":"SE",
    "name:und_x_variant":[
        "Malvikens Fiskel\u00e4ge",
        "Malviken"
    ],
    "wof:name":"Malviken",
    "wof:placetype":"locality"
},
  "geometry": {"coordinates":[17.79332999999999,62.49806],"type":"Point"}
}