{
  "type": "Feature",
  "properties": {
    "gn:admin1_code":"9.0",
    "gn:admin2_code":"885.0",
    "gn:asciiname":"Kalleguta",
    "gn:country_code":"SE",
    "gn:dem":15,
    "gn:feature_class":"P",
    "gn:feature_code":"PPL",
    "gn:name":"Kalleguta",
    "gn:population":0,
    "gn:timezone":"Europe/Stockholm",
    "iso:country":"SE",
    "name:nld_x_preferred":[
        "Kalleguta"
    ],
    "wof:name":"Kalleguta",
    "wof:placetype":"locality"
},
  "geometry": {"coordinates":[16.78333,56.88333000000001],"type":"Point"}
}