{
  "type": "Feature",
  "properties": {
    "gn:admin1_code":"6.0",
    "gn:admin2_code":"1382.0",
    "gn:asciiname":"Hasslas",
    "gn:country_code":"SE",
    "gn:dem":19,
    "gn:feature_class":"P",
    "gn:feature_code":"PPL",
    "gn:name":"H\u00e4ssl\u00e5s",
    "gn:population":0,
    "gn:timezone":"Europe/Stockholm",
    "iso:country":"SE",
    "wof:name":"Hasslas",
    "wof:placetype":"locality"
},
  "geometry": {"coordinates":[12.48333,56.96666999999999],"type":"Point"}
}