{
  "type": "Feature",
  "properties": {
    "gn:admin1_code":"16.0",
    "gn:asciiname":"Finnkroken",
    "gn:country_code":"SE",
    "gn:dem":2,
    "gn:feature_class":"P",
    "gn:feature_code":"PPL",
    "gn:name":"Finnkroken",
    "gn:population":0,
    "gn:timezone":"Europe/Stockholm",
    "iso:country":"SE",
    "wof:name":"Finnkroken",
    "wof:placetype":"locality"
},
  "geometry": {"coordinates":[16.81667,58.29971999999999],"type":"Point"}
}