{
  "type": "Feature",
  "properties": {
    "gn:admin1_code":"9.0",
    "gn:admin2_code":"860.0",
    "gn:asciiname":"Framsteby",
    "gn:country_code":"SE",
    "gn:dem":107,
    "gn:feature_class":"P",
    "gn:feature_code":"PPL",
    "gn:name":"Fr\u00e4msteby",
    "gn:population":0,
    "gn:timezone":"Europe/Stockholm",
    "iso:country":"SE",
    "wof:name":"Framsteby",
    "wof:placetype":"locality"
},
  "geometry": {"coordinates":[15.98333,57.51667],"type":"Point"}
}