{
  "type": "Feature",
  "properties": {
    "gn:admin1_code":"24.0",
    "gn:admin2_code":"2281.0",
    "gn:admin3_code":"228106.0",
    "gn:admin4_code":"2487.0",
    "gn:asciiname":"Hogom",
    "gn:country_code":"SE",
    "gn:dem":68,
    "gn:feature_class":"P",
    "gn:feature_code":"PPL",
    "gn:name":"H\u00f6gom",
    "gn:population":0,
    "gn:timezone":"Europe/Stockholm",
    "iso:country":"SE",
    "name:nor_x_preferred":[
        "H\u00f6gom"
    ],
    "name:nor_x_variant":[
        "H\u00f8gom"
    ],
    "wof:name":"Hogom",
    "wof:placetype":"locality"
},
  "geometry": {"coordinates":[17.25836,62.40114000000001],"type":"Point"}
}