{
  "type": "Feature",
  "properties": {
    "gn:admin1_code":"14.0",
    "gn:admin2_code":"2580.0",
    "gn:asciiname":"Arbyn",
    "gn:cc2":"SE",
    "gn:country_code":"SE",
    "gn:dem":23,
    "gn:feature_class":"P",
    "gn:feature_code":"PPL",
    "gn:name":"\u00c5rbyn",
    "gn:population":0,
    "gn:timezone":"Europe/Stockholm",
    "iso:country":"SE",
    "name:und_x_variant":[
        "Orrbyn",
        "\u00c5rbyn"
    ],
    "wof:name":"Arbyn",
    "wof:placetype":"locality"
},
  "geometry": {"coordinates":[22.11667000000001,65.95],"type":"Point"}
}