{
  "type": "Feature",
  "properties": {
    "gn:admin1_code":"5.0",
    "gn:admin2_code":"980.0",
    "gn:asciiname":"Hagsarve",
    "gn:country_code":"SE",
    "gn:dem":16,
    "gn:feature_class":"P",
    "gn:feature_code":"PPL",
    "gn:name":"Hagsarve",
    "gn:population":0,
    "gn:timezone":"Europe/Stockholm",
    "iso:country":"SE",
    "name:und_x_variant":[
        "Haxarfve",
        "Hagsarve"
    ],
    "wof:name":"Hagsarve",
    "wof:placetype":"locality"
},
  "geometry": {"coordinates":[18.24633,57.18704],"type":"Point"}
}