{
  "type": "Feature",
  "properties": {
    "gn:admin1_code":"27.0",
    "gn:admin2_code":"1278.0",
    "gn:asciiname":"Dejarp",
    "gn:country_code":"SE",
    "gn:dem":129,
    "gn:feature_class":"P",
    "gn:feature_code":"PPL",
    "gn:name":"Dejarp",
    "gn:population":0,
    "gn:timezone":"Europe/Stockholm",
    "iso:country":"SE",
    "wof:name":"Dejarp",
    "wof:placetype":"locality"
},
  "geometry": {"coordinates":[12.73333,56.45],"type":"Point"}
}