{
  "type": "Feature",
  "properties": {
    "gn:admin1_code":"27.0",
    "gn:admin2_code":"1287.0",
    "gn:asciiname":"Bodarp",
    "gn:country_code":"SE",
    "gn:dem":14,
    "gn:feature_class":"P",
    "gn:feature_code":"PPL",
    "gn:name":"Bodarp",
    "gn:population":0,
    "gn:timezone":"Europe/Stockholm",
    "iso:country":"SE",
    "wof:name":"Bodarp",
    "wof:placetype":"locality"
},
  "geometry": {"coordinates":[13.06667,55.43333000000001],"type":"Point"}
}