{
  "type": "Feature",
  "properties": {
    "gn:admin1_code":"23.0",
    "gn:admin2_code":"2463.0",
    "gn:asciiname":"Gavsele",
    "gn:cc2":"SE",
    "gn:country_code":"SE",
    "gn:dem":288,
    "gn:feature_class":"P",
    "gn:feature_code":"PPL",
    "gn:name":"Gavsele",
    "gn:population":0,
    "gn:timezone":"Europe/Stockholm",
    "iso:country":"SE",
    "name:swe_x_preferred":[
        "Gafsele"
    ],
    "name:und_x_variant":[
        "Gavsele"
    ],
    "wof:name":"Gavsele",
    "wof:placetype":"locality"
},
  "geometry": {"coordinates":[17.25,64.01666999999999],"type":"Point"}
}