{
  "type": "Feature",
  "properties": {
    "gn:admin1_code":"3.0",
    "gn:admin2_code":"2132.0",
    "gn:asciiname":"Forsa",
    "gn:country_code":"SE",
    "gn:dem":23,
    "gn:feature_class":"P",
    "gn:feature_code":"PPL",
    "gn:name":"Forsa",
    "gn:population":0,
    "gn:timezone":"Europe/Stockholm",
    "iso:country":"SE",
    "name:fin_x_preferred":[
        "Forssa"
    ],
    "name:swe_x_preferred":[
        "Forsa"
    ],
    "name:tur_x_preferred":[
        "Forsa"
    ],
    "wof:name":"Forsa",
    "wof:placetype":"locality"
},
  "geometry": {"coordinates":[17.17601,61.93758],"type":"Point"}
}