{
  "type": "Feature",
  "properties": {
    "gn:admin1_code":"23.0",
    "gn:admin2_code":"2482.0",
    "gn:asciiname":"Onnanget",
    "gn:cc2":"SE",
    "gn:country_code":"SE",
    "gn:dem":-9999,
    "gn:feature_class":"P",
    "gn:feature_code":"PPL",
    "gn:name":"\u00d6nn\u00e4nget",
    "gn:population":0,
    "gn:timezone":"Europe/Stockholm",
    "iso:country":"SE",
    "name:und_x_variant":[
        "\u00d6rn\u00e4nget",
        "\u00d6nn\u00e4nget"
    ],
    "wof:name":"Onnanget",
    "wof:placetype":"locality"
},
  "geometry": {"coordinates":[21.06667,64.84999999999999],"type":"Point"}
}