{
  "type": "Feature",
  "properties": {
    "gn:admin1_code":"16.0",
    "gn:admin2_code":"586.0",
    "gn:asciiname":"Lovsberg",
    "gn:country_code":"SE",
    "gn:dem":127,
    "gn:feature_class":"P",
    "gn:feature_code":"PPL",
    "gn:name":"L\u00f6vsberg",
    "gn:population":0,
    "gn:timezone":"Europe/Stockholm",
    "iso:country":"SE",
    "name:nor_x_preferred":[
        "L\u00f6vsberg"
    ],
    "name:nor_x_variant":[
        "L\u00f8vsberg"
    ],
    "wof:name":"Lovsberg",
    "wof:placetype":"locality"
},
  "geometry": {"coordinates":[15.26667,58.31667],"type":"Point"}
}