{
  "type": "Feature",
  "properties": {
    "gn:admin1_code":"10.0",
    "gn:admin2_code":"2023.0",
    "gn:asciiname":"Tallbyn",
    "gn:country_code":"SE",
    "gn:dem":300,
    "gn:feature_class":"P",
    "gn:feature_code":"PPL",
    "gn:name":"T\u00e4llbyn",
    "gn:population":0,
    "gn:timezone":"Europe/Stockholm",
    "iso:country":"SE",
    "wof:name":"Tallbyn",
    "wof:placetype":"locality"
},
  "geometry": {"coordinates":[13.71667,60.66667],"type":"Point"}
}