{
  "type": "Feature",
  "properties": {
    "gn:admin1_code":"5.0",
    "gn:admin2_code":"980.0",
    "gn:asciiname":"Lilla Snogrinde",
    "gn:country_code":"SE",
    "gn:dem":37,
    "gn:feature_class":"P",
    "gn:feature_code":"PPL",
    "gn:name":"Lilla Sn\u00f6grinde",
    "gn:population":0,
    "gn:timezone":"Europe/Stockholm",
    "iso:country":"SE",
    "name:nor_x_preferred":[
        "Lilla Sn\u00f6grinda"
    ],
    "name:nor_x_variant":[
        "Lilla Sn\u00f8grinda"
    ],
    "name:und_x_variant":[
        "Lilla Sn\u00f6grinda",
        "Lilla Sn\u00f6grinde"
    ],
    "wof:name":"Lilla Snogrinde",
    "wof:placetype":"locality"
},
  "geometry": {"coordinates":[18.25114,57.38282],"type":"Point"}
}