{
  "type": "Feature",
  "properties": {
    "gn:admin1_code":"2.0",
    "gn:admin2_code":"1083.0",
    "gn:asciiname":"Istaby",
    "gn:country_code":"SE",
    "gn:dem":31,
    "gn:feature_class":"P",
    "gn:feature_code":"PPL",
    "gn:name":"Istaby",
    "gn:population":0,
    "gn:timezone":"Europe/Stockholm",
    "iso:country":"SE",
    "wof:name":"Istaby",
    "wof:placetype":"locality"
},
  "geometry": {"coordinates":[14.65,56.01667],"type":"Point"}
}