{
  "type": "Feature",
  "properties": {
    "gn:admin1_code":"27.0",
    "gn:admin2_code":"1263.0",
    "gn:asciiname":"Beddinge Lage",
    "gn:cc2":"SE",
    "gn:country_code":"SE",
    "gn:dem":61,
    "gn:feature_class":"P",
    "gn:feature_code":"PPL",
    "gn:name":"Beddinge L\u00e4ge",
    "gn:population":0,
    "gn:timezone":"Europe/Stockholm",
    "iso:country":"SE",
    "name:und_x_variant":[
        "Bedinge L\u00e4ge",
        "Beddingestrand",
        "Beddinge L\u00e4ge"
    ],
    "wof:name":"Beddinge Lage",
    "wof:placetype":"locality"
},
  "geometry": {"coordinates":[13.43333,55.53333000000001],"type":"Point"}
}