{
  "type": "Feature",
  "properties": {
    "iso:country":"SE",
    "name:swe_x_preferred":[
        "Sandviken"
    ],
    "name:unk_x_variant":[
        "Sandviken"
    ],
    "qs:gn_adm0_cc":"SE",
    "qs:gn_fcode":"PPL",
    "qs:gn_local":2663540,
    "qs:gn_nam_loc":"Vaxholm, Vaxholm, Stockholms L\u00e4n, SE",
    "qs:gn_namadm1":"26",
    "qs:gn_name":"Sandviken",
    "qs:local_max":572,
    "qs:local_sum":1935,
    "qs:localhoods":11,
    "qs:name":"Sandviken",
    "qs:name_adm0":"Sverige",
    "qs:name_adm1":"Stockholms L\u00e4n",
    "qs:name_adm2":"\u00d6ster\u00e5ker",
    "qs:name_local":"Vaxholm",
    "qs:photo_max":138,
    "qs:photo_sum":224,
    "qs:placetype":"Suburb",
    "qs:quad_count":20,
    "qs:woe_adm0":23424954,
    "qs:woe_adm1":2347067,
    "qs:woe_adm2":12587472,
    "qs:woe_lau":0,
    "qs:woe_local":909710,
    "qs:woe_ver":"7.10.0",
    "wof:lang":[
        "swe"
    ],
    "wof:name":"Sandviken",
    "wof:placetype":"neighbourhood"
},
  "geometry": {"coordinates":[18.149309,59.452451],"type":"Point"}
}