{
  "type": "Feature",
  "properties": {
    "gn:admin1_code":"27.0",
    "gn:admin2_code":"1257.0",
    "gn:asciiname":"Smormyr",
    "gn:country_code":"SE",
    "gn:dem":120,
    "gn:feature_class":"P",
    "gn:feature_code":"PPL",
    "gn:name":"Sm\u00f6rmyr",
    "gn:population":0,
    "gn:timezone":"Europe/Stockholm",
    "iso:country":"SE",
    "name:nor_x_preferred":[
        "Sm\u00f6rmyr"
    ],
    "name:nor_x_variant":[
        "Sm\u00f8rmyr"
    ],
    "wof:name":"Smormyr",
    "wof:placetype":"locality"
},
  "geometry": {"coordinates":[13.28333,56.23333],"type":"Point"}
}