{
  "type": "Feature",
  "properties": {
    "gn:admin1_code":"25.0",
    "gn:admin2_code":"1980.0",
    "gn:asciiname":"Vasby",
    "gn:country_code":"SE",
    "gn:dem":51,
    "gn:feature_class":"P",
    "gn:feature_code":"PPL",
    "gn:name":"V\u00e4sby",
    "gn:population":0,
    "gn:timezone":"Europe/Stockholm",
    "iso:country":"SE",
    "wof:name":"Vasby",
    "wof:placetype":"locality"
},
  "geometry": {"coordinates":[16.71667,59.75],"type":"Point"}
}