{
  "type": "Feature",
  "properties": {
    "gn:admin1_code":"27.0",
    "gn:admin2_code":"1214.0",
    "gn:asciiname":"Langarod",
    "gn:country_code":"SE",
    "gn:dem":132,
    "gn:feature_class":"P",
    "gn:feature_code":"PPL",
    "gn:name":"L\u00e5ngar\u00f6d",
    "gn:population":0,
    "gn:timezone":"Europe/Stockholm",
    "iso:country":"SE",
    "name:nor_x_preferred":[
        "L\u00e5ngar\u00f6d"
    ],
    "name:nor_x_variant":[
        "L\u00e5ngar\u00f8d"
    ],
    "wof:name":"Langarod",
    "wof:placetype":"locality"
},
  "geometry": {"coordinates":[13.16667,55.96666999999999],"type":"Point"}
}