{
  "type": "Feature",
  "properties": {
    "gn:admin1_code":"6.0",
    "gn:admin2_code":"1382.0",
    "gn:asciiname":"Arstad",
    "gn:country_code":"SE",
    "gn:dem":61,
    "gn:feature_class":"P",
    "gn:feature_code":"PPL",
    "gn:name":"\u00c5rstad",
    "gn:population":321,
    "gn:timezone":"Europe/Stockholm",
    "iso:country":"SE",
    "name:fra_x_preferred":[
        "\u00c5rstad"
    ],
    "name:ita_x_preferred":[
        "\u00c5rstad"
    ],
    "name:nld_x_preferred":[
        "\u00c5rstad"
    ],
    "name:nor_x_preferred":[
        "\u00c5rstad"
    ],
    "name:swe_x_preferred":[
        "\u00c5rstad"
    ],
    "name:und_x_variant":[
        "\u00c5rstad"
    ],
    "wof:name":"Arstad",
    "wof:placetype":"locality",
    "wof:population":321
},
  "geometry": {"coordinates":[12.67758,56.91682],"type":"Point"}
}