{
  "type": "Feature",
  "properties": {
    "gn:admin1_code":"6.0",
    "gn:asciiname":"Hanhals",
    "gn:country_code":"SE",
    "gn:dem":34,
    "gn:feature_class":"P",
    "gn:feature_code":"PPL",
    "gn:name":"Hanhals",
    "gn:population":0,
    "gn:timezone":"Europe/Stockholm",
    "iso:country":"SE",
    "wof:name":"Hanhals",
    "wof:placetype":"locality"
},
  "geometry": {"coordinates":[12.0835,57.44389],"type":"Point"}
}