{
  "type": "Feature",
  "properties": {
    "gn:admin1_code":"12.0",
    "gn:admin2_code":"765.0",
    "gn:asciiname":"Kolaboda",
    "gn:country_code":"SE",
    "gn:dem":144,
    "gn:feature_class":"P",
    "gn:feature_code":"PPL",
    "gn:name":"K\u00f6laboda",
    "gn:population":0,
    "gn:timezone":"Europe/Stockholm",
    "iso:country":"SE",
    "name:nor_x_preferred":[
        "K\u00f6laboda"
    ],
    "name:nor_x_variant":[
        "K\u00f8laboda"
    ],
    "wof:name":"Kolaboda",
    "wof:placetype":"locality"
},
  "geometry": {"coordinates":[13.98333,56.55],"type":"Point"}
}