{
  "type": "Feature",
  "properties": {
    "gn:admin1_code":"15.0",
    "gn:admin2_code":"1884.0",
    "gn:asciiname":"Nyttorp",
    "gn:country_code":"SE",
    "gn:dem":166,
    "gn:feature_class":"P",
    "gn:feature_code":"PPL",
    "gn:name":"Nyttorp",
    "gn:population":0,
    "gn:timezone":"Europe/Stockholm",
    "iso:country":"SE",
    "wof:name":"Nyttorp",
    "wof:placetype":"locality"
},
  "geometry": {"coordinates":[14.73333,59.46666999999999],"type":"Point"}
}