{
  "type": "Feature",
  "properties": {
    "gn:admin1_code":"21.0",
    "gn:asciiname":"Skinnaesviken",
    "gn:country_code":"SE",
    "gn:dem":14,
    "gn:feature_class":"P",
    "gn:feature_code":"PPL",
    "gn:name":"Skinn\u00e4sviken",
    "gn:population":0,
    "gn:timezone":"Europe/Stockholm",
    "iso:country":"SE",
    "wof:name":"Skinnaesviken",
    "wof:placetype":"locality"
},
  "geometry": {"coordinates":[18.38333,60.33333],"type":"Point"}
}