{
  "type": "Feature",
  "properties": {
    "gn:admin1_code":"10.0",
    "gn:admin2_code":"2082.0",
    "gn:admin3_code":"208201.0",
    "gn:admin4_code":"2384.0",
    "gn:asciiname":"Klacken",
    "gn:country_code":"SE",
    "gn:dem":162,
    "gn:feature_class":"P",
    "gn:feature_code":"PPL",
    "gn:name":"Klacken",
    "gn:population":0,
    "gn:timezone":"Europe/Stockholm",
    "iso:country":"SE",
    "wof:name":"Klacken",
    "wof:placetype":"locality"
},
  "geometry": {"coordinates":[15.7898,60.34069],"type":"Point"}
}