{
  "type": "Feature",
  "properties": {
    "gn:admin1_code":"7.0",
    "gn:admin2_code":"2326.0",
    "gn:asciiname":"Rojvallen",
    "gn:country_code":"SE",
    "gn:dem":546,
    "gn:feature_class":"P",
    "gn:feature_code":"PPL",
    "gn:name":"R\u00f6jvallen",
    "gn:population":0,
    "gn:timezone":"Europe/Stockholm",
    "iso:country":"SE",
    "name:nor_x_preferred":[
        "R\u00f6jvallen"
    ],
    "name:nor_x_variant":[
        "R\u00f8jvallen"
    ],
    "name:und_x_variant":[
        "R\u00f6jvallen"
    ],
    "wof:name":"Rojvallen",
    "wof:placetype":"locality"
},
  "geometry": {"coordinates":[14.21667,62.45],"type":"Point"}
}