{
  "type": "Feature",
  "properties": {
    "gn:admin1_code":"15.0",
    "gn:admin2_code":"1860.0",
    "gn:asciiname":"Otterbacken",
    "gn:country_code":"SE",
    "gn:dem":69,
    "gn:feature_class":"P",
    "gn:feature_code":"PPL",
    "gn:name":"Otterb\u00e4cken",
    "gn:population":0,
    "gn:timezone":"Europe/Stockholm",
    "iso:country":"SE",
    "wof:name":"Otterbacken",
    "wof:placetype":"locality"
},
  "geometry": {"coordinates":[14.33333,58.93333000000001],"type":"Point"}
}