{
  "type": "Feature",
  "properties": {
    "gn:admin1_code":"24.0",
    "gn:admin2_code":"2282.0",
    "gn:admin3_code":"228211.0",
    "gn:admin4_code":"2511.0",
    "gn:asciiname":"Bursjo",
    "gn:country_code":"SE",
    "gn:dem":95,
    "gn:feature_class":"P",
    "gn:feature_code":"PPL",
    "gn:name":"Bursj\u00f6",
    "gn:population":0,
    "gn:timezone":"Europe/Stockholm",
    "iso:country":"SE",
    "name:nor_x_preferred":[
        "Bursj\u00f6"
    ],
    "name:nor_x_variant":[
        "Bursj\u00f8"
    ],
    "name:und_x_variant":[
        "Bursj\u00f6"
    ],
    "wof:name":"Bursjo",
    "wof:placetype":"locality"
},
  "geometry": {"coordinates":[17.57838,63.00009],"type":"Point"}
}