{
  "type": "Feature",
  "properties": {
    "gn:admin1_code":"28.0",
    "gn:admin2_code":"1482.0",
    "gn:asciiname":"Synnerod",
    "gn:country_code":"SE",
    "gn:dem":54,
    "gn:feature_class":"P",
    "gn:feature_code":"PPL",
    "gn:name":"Synner\u00f6d",
    "gn:population":0,
    "gn:timezone":"Europe/Stockholm",
    "iso:country":"SE",
    "name:nor_x_preferred":[
        "Synner\u00f6d"
    ],
    "name:nor_x_variant":[
        "Synner\u00f8d"
    ],
    "name:und_x_variant":[
        "Synner\u00f6d"
    ],
    "wof:name":"Synnerod",
    "wof:placetype":"locality"
},
  "geometry": {"coordinates":[11.85,57.85],"type":"Point"}
}