{
  "type": "Feature",
  "properties": {
    "gn:admin1_code":"22.0",
    "gn:admin2_code":"1781.0",
    "gn:asciiname":"Ostra Sunnas",
    "gn:country_code":"SE",
    "gn:dem":69,
    "gn:feature_class":"P",
    "gn:feature_code":"PPL",
    "gn:name":"\u00d6stra Sunn\u00e4s",
    "gn:population":0,
    "gn:timezone":"Europe/Stockholm",
    "iso:country":"SE",
    "wof:name":"Ostra Sunnas",
    "wof:placetype":"locality"
},
  "geometry": {"coordinates":[14.01667,59.33333],"type":"Point"}
}