{
  "type": "Feature",
  "properties": {
    "gn:admin1_code":"10.0",
    "gn:admin2_code":"2082.0",
    "gn:asciiname":"Karlsgardarna",
    "gn:country_code":"SE",
    "gn:dem":164,
    "gn:feature_class":"P",
    "gn:feature_code":"PPL",
    "gn:name":"Karlsg\u00e5rdarna",
    "gn:population":0,
    "gn:timezone":"Europe/Stockholm",
    "iso:country":"SE",
    "wof:name":"Karlsgardarna",
    "wof:placetype":"locality"
},
  "geometry": {"coordinates":[15.78333,60.33333],"type":"Point"}
}