{
  "type": "Feature",
  "properties": {
    "gn:admin1_code":"15.0",
    "gn:admin2_code":"1860.0",
    "gn:asciiname":"Kyrkhavden",
    "gn:cc2":"SE",
    "gn:country_code":"SE",
    "gn:dem":147,
    "gn:feature_class":"P",
    "gn:feature_code":"PPL",
    "gn:name":"Kyrkh\u00e4vden",
    "gn:population":0,
    "gn:timezone":"Europe/Stockholm",
    "iso:country":"SE",
    "name:und_x_variant":[
        "Kyrkoh\u00e4vden",
        "Kyrkh\u00e4fdan",
        "Kyrkh\u00e4vden"
    ],
    "wof:name":"Kyrkhavden",
    "wof:placetype":"locality"
},
  "geometry": {"coordinates":[14.43333,58.91667],"type":"Point"}
}