{
  "type": "Feature",
  "properties": {
    "gn:admin1_code":"26.0",
    "gn:admin2_code":"120.0",
    "gn:asciiname":"Morto",
    "gn:country_code":"SE",
    "gn:dem":22,
    "gn:feature_class":"P",
    "gn:feature_code":"PPL",
    "gn:name":"M\u00f6rt\u00f6",
    "gn:population":0,
    "gn:timezone":"Europe/Stockholm",
    "iso:country":"SE",
    "name:nor_x_preferred":[
        "M\u00f6rt\u00f6"
    ],
    "name:nor_x_variant":[
        "M\u00f8rt\u00f8"
    ],
    "name:und_x_variant":[
        "M\u00f6rt\u00f6"
    ],
    "wof:name":"Morto",
    "wof:placetype":"locality"
},
  "geometry": {"coordinates":[18.6371,59.16185],"type":"Point"}
}