{
  "type": "Feature",
  "properties": {
    "gn:admin1_code":"28.0",
    "gn:admin2_code":"1452.0",
    "gn:asciiname":"Skummenas",
    "gn:country_code":"SE",
    "gn:dem":210,
    "gn:feature_class":"P",
    "gn:feature_code":"PPL",
    "gn:name":"Skummen\u00e4s",
    "gn:population":0,
    "gn:timezone":"Europe/Stockholm",
    "iso:country":"SE",
    "wof:name":"Skummenas",
    "wof:placetype":"locality"
},
  "geometry": {"coordinates":[13.25,57.43333000000001],"type":"Point"}
}