{
  "type": "Feature",
  "properties": {
    "gn:admin1_code":"9.0",
    "gn:asciiname":"Krakelund",
    "gn:country_code":"SE",
    "gn:dem":-9999,
    "gn:feature_class":"P",
    "gn:feature_code":"PPL",
    "gn:name":"Kr\u00e5kelund",
    "gn:population":0,
    "gn:timezone":"Europe/Stockholm",
    "iso:country":"SE",
    "wof:name":"Krakelund",
    "wof:placetype":"locality"
},
  "geometry": {"coordinates":[16.71667,57.43333000000001],"type":"Point"}
}