{
  "type": "Feature",
  "properties": {
    "gn:admin1_code":"14.0",
    "gn:admin2_code":"2518.0",
    "gn:asciiname":"Mettajarvi",
    "gn:country_code":"SE",
    "gn:dem":167,
    "gn:feature_class":"P",
    "gn:feature_code":"PPL",
    "gn:name":"Mett\u00e4j\u00e4rvi",
    "gn:population":0,
    "gn:timezone":"Europe/Stockholm",
    "iso:country":"SE",
    "name:fin_x_preferred":[
        "Mett\u00e4j\u00e4rvi"
    ],
    "wof:name":"Mettajarvi",
    "wof:placetype":"locality"
},
  "geometry": {"coordinates":[23.58109,66.72789],"type":"Point"}
}