{
  "type": "Feature",
  "properties": {
    "gn:admin1_code":"2.0",
    "gn:admin2_code":"1082.0",
    "gn:asciiname":"Loberget",
    "gn:country_code":"SE",
    "gn:dem":96,
    "gn:feature_class":"P",
    "gn:feature_code":"PPL",
    "gn:name":"Loberget",
    "gn:population":0,
    "gn:timezone":"Europe/Stockholm",
    "iso:country":"SE",
    "wof:name":"Loberget",
    "wof:placetype":"locality"
},
  "geometry": {"coordinates":[14.86667,56.35],"type":"Point"}
}