{
  "type": "Feature",
  "properties": {
    "gn:admin1_code":"26.0",
    "gn:admin2_code":"138.0",
    "gn:admin3_code":"13801.0",
    "gn:admin4_code":"103.0",
    "gn:asciiname":"Nyfors",
    "gn:country_code":"SE",
    "gn:dem":48,
    "gn:feature_class":"P",
    "gn:feature_code":"PPL",
    "gn:name":"Nyfors",
    "gn:population":0,
    "gn:timezone":"Europe/Stockholm",
    "iso:country":"SE",
    "wof:name":"Nyfors",
    "wof:placetype":"locality"
},
  "geometry": {"coordinates":[18.26477,59.22476],"type":"Point"}
}