{
  "type": "Feature",
  "properties": {
    "gn:admin1_code":"8.0",
    "gn:admin2_code":"662.0",
    "gn:asciiname":"Bojeryd",
    "gn:country_code":"SE",
    "gn:dem":131,
    "gn:feature_class":"P",
    "gn:feature_code":"PPL",
    "gn:name":"B\u00f6jeryd",
    "gn:population":0,
    "gn:timezone":"Europe/Stockholm",
    "iso:country":"SE",
    "name:nor_x_preferred":[
        "B\u00f6jeryd"
    ],
    "name:nor_x_variant":[
        "B\u00f8jeryd"
    ],
    "wof:name":"Bojeryd",
    "wof:placetype":"locality"
},
  "geometry": {"coordinates":[13.13333,57.06667],"type":"Point"}
}