{
  "type": "Feature",
  "properties": {
    "gn:admin1_code":"15.0",
    "gn:admin2_code":"1864.0",
    "gn:asciiname":"Dunderbo",
    "gn:country_code":"SE",
    "gn:dem":163,
    "gn:feature_class":"P",
    "gn:feature_code":"PPL",
    "gn:name":"Dunderbo",
    "gn:population":0,
    "gn:timezone":"Europe/Stockholm",
    "iso:country":"SE",
    "wof:name":"Dunderbo",
    "wof:placetype":"locality"
},
  "geometry": {"coordinates":[14.95,59.93333000000001],"type":"Point"}
}