{
  "type": "Feature",
  "properties": {
    "gn:admin1_code":"22.0",
    "gn:admin2_code":"1784.0",
    "gn:asciiname":"Vastra Skyberg",
    "gn:cc2":"SE",
    "gn:country_code":"SE",
    "gn:dem":100,
    "gn:feature_class":"P",
    "gn:feature_code":"PPL",
    "gn:name":"V\u00e4stra Skyberg",
    "gn:population":0,
    "gn:timezone":"Europe/Stockholm",
    "iso:country":"SE",
    "name:und_x_variant":[
        "Skyberg",
        "V\u00e4stra Skyberg"
    ],
    "wof:name":"Vastra Skyberg",
    "wof:placetype":"locality"
},
  "geometry": {"coordinates":[12.46667,59.63333000000001],"type":"Point"}
}