{
  "type": "Feature",
  "properties": {
    "gn:admin1_code":"9.0",
    "gn:admin2_code":"882.0",
    "gn:asciiname":"Mollekulla",
    "gn:country_code":"SE",
    "gn:dem":86,
    "gn:feature_class":"P",
    "gn:feature_code":"PPL",
    "gn:name":"M\u00f6llekulla",
    "gn:population":0,
    "gn:timezone":"Europe/Stockholm",
    "iso:country":"SE",
    "name:nor_x_preferred":[
        "M\u00f6llekulla"
    ],
    "name:nor_x_variant":[
        "M\u00f8llekulla"
    ],
    "name:und_x_variant":[
        "M\u00f6llekulla"
    ],
    "wof:name":"Mollekulla",
    "wof:placetype":"locality"
},
  "geometry": {"coordinates":[16.23333,57.45],"type":"Point"}
}