{
  "type": "Feature",
  "properties": {
    "gn:admin1_code":"7.0",
    "gn:admin2_code":"2321.0",
    "gn:asciiname":"Kall",
    "gn:country_code":"SE",
    "gn:dem":384,
    "gn:feature_class":"P",
    "gn:feature_code":"PPL",
    "gn:name":"Kall",
    "gn:population":0,
    "gn:timezone":"Europe/Stockholm",
    "iso:country":"SE",
    "wof:name":"Kall",
    "wof:placetype":"locality"
},
  "geometry": {"coordinates":[13.23333,63.46666999999999],"type":"Point"}
}