{
  "type": "Feature",
  "properties": {
    "gn:admin1_code":"6.0",
    "gn:admin2_code":"1382.0",
    "gn:asciiname":"Ry",
    "gn:cc2":"SE",
    "gn:country_code":"SE",
    "gn:dem":129,
    "gn:feature_class":"P",
    "gn:feature_code":"PPL",
    "gn:name":"Ry",
    "gn:population":0,
    "gn:timezone":"Europe/Stockholm",
    "iso:country":"SE",
    "name:und_x_variant":[
        "Ryd",
        "Ry"
    ],
    "wof:name":"Ry",
    "wof:placetype":"locality"
},
  "geometry": {"coordinates":[12.73333,56.91667],"type":"Point"}
}