{
  "type": "Feature",
  "properties": {
    "gn:admin1_code":"28.0",
    "gn:admin2_code":"1463.0",
    "gn:asciiname":"Abborrhult",
    "gn:country_code":"SE",
    "gn:dem":168,
    "gn:feature_class":"P",
    "gn:feature_code":"PPL",
    "gn:name":"Abborrhult",
    "gn:population":0,
    "gn:timezone":"Europe/Stockholm",
    "iso:country":"SE",
    "wof:name":"Abborrhult",
    "wof:placetype":"locality"
},
  "geometry": {"coordinates":[12.66667,57.35],"type":"Point"}
}