{
  "type": "Feature",
  "properties": {
    "gn:admin1_code":"23.0",
    "gn:admin2_code":"2481.0",
    "gn:asciiname":"Kroksjo",
    "gn:country_code":"SE",
    "gn:dem":478,
    "gn:feature_class":"P",
    "gn:feature_code":"PPL",
    "gn:name":"Kroksj\u00f6",
    "gn:population":0,
    "gn:timezone":"Europe/Stockholm",
    "iso:country":"SE",
    "name:nor_x_preferred":[
        "Kroksj\u00f6"
    ],
    "name:nor_x_variant":[
        "Kroksj\u00f8"
    ],
    "name:und_x_variant":[
        "Kroksj\u00f6"
    ],
    "wof:name":"Kroksjo",
    "wof:placetype":"locality"
},
  "geometry": {"coordinates":[17.98333,64.51666999999999],"type":"Point"}
}