{
  "type": "Feature",
  "properties": {
    "gn:admin1_code":"5.0",
    "gn:admin2_code":"980.0",
    "gn:asciiname":"Skals",
    "gn:country_code":"SE",
    "gn:dem":3,
    "gn:feature_class":"P",
    "gn:feature_code":"PPL",
    "gn:name":"Sk\u00e5ls",
    "gn:population":0,
    "gn:timezone":"Europe/Stockholm",
    "iso:country":"SE",
    "name:dan_x_preferred":[
        "Skals"
    ],
    "name:nld_x_preferred":[
        "Skals"
    ],
    "name:nor_x_preferred":[
        "Skals"
    ],
    "name:spa_x_preferred":[
        "Skals"
    ],
    "wof:name":"Skals",
    "wof:placetype":"locality"
},
  "geometry": {"coordinates":[18.25459,57.09793000000001],"type":"Point"}
}