{
  "type": "Feature",
  "properties": {
    "gn:admin1_code":"15.0",
    "gn:admin2_code":"1861.0",
    "gn:asciiname":"Hoga",
    "gn:country_code":"SE",
    "gn:dem":62,
    "gn:feature_class":"P",
    "gn:feature_code":"PPL",
    "gn:name":"H\u00f6ga",
    "gn:population":0,
    "gn:timezone":"Europe/Stockholm",
    "iso:country":"SE",
    "name:nor_x_preferred":[
        "H\u00f6ga"
    ],
    "name:nor_x_variant":[
        "H\u00f8ga"
    ],
    "name:und_x_variant":[
        "H\u00f6ga"
    ],
    "wof:name":"Hoga",
    "wof:placetype":"locality"
},
  "geometry": {"coordinates":[14.91667,59.05],"type":"Point"}
}