{
  "type": "Feature",
  "properties": {
    "gn:admin1_code":"9.0",
    "gn:admin2_code":"862.0",
    "gn:asciiname":"Vastra Alsjo",
    "gn:cc2":"SE",
    "gn:country_code":"SE",
    "gn:dem":151,
    "gn:feature_class":"P",
    "gn:feature_code":"PPL",
    "gn:name":"V\u00e4stra Alsj\u00f6",
    "gn:population":0,
    "gn:timezone":"Europe/Stockholm",
    "iso:country":"SE",
    "name:und_x_variant":[
        "Alsj\u00f6",
        "V\u00e4stra Alsj\u00f6"
    ],
    "wof:name":"Vastra Alsjo",
    "wof:placetype":"locality"
},
  "geometry": {"coordinates":[15.61667,56.63333000000001],"type":"Point"}
}