{
  "type": "Feature",
  "properties": {
    "gn:admin1_code":"7.0",
    "gn:admin2_code":"2380.0",
    "gn:asciiname":"Knutkaribranna",
    "gn:cc2":"SE",
    "gn:country_code":"SE",
    "gn:dem":523,
    "gn:feature_class":"P",
    "gn:feature_code":"PPL",
    "gn:name":"Knutkaribr\u00e4nna",
    "gn:population":0,
    "gn:timezone":"Europe/Stockholm",
    "iso:country":"SE",
    "name:und_x_variant":[
        "Knulkuribranna",
        "Knutkaribr\u00e4nna"
    ],
    "wof:name":"Knutkaribranna",
    "wof:placetype":"locality"
},
  "geometry": {"coordinates":[14.96667,63.53333000000001],"type":"Point"}
}