{
  "type": "Feature",
  "properties": {
    "gn:admin1_code":"15.0",
    "gn:admin2_code":"1882.0",
    "gn:asciiname":"Norra Torpa",
    "gn:country_code":"SE",
    "gn:dem":131,
    "gn:feature_class":"P",
    "gn:feature_code":"PPL",
    "gn:name":"Norra Torpa",
    "gn:population":0,
    "gn:timezone":"Europe/Stockholm",
    "iso:country":"SE",
    "wof:name":"Norra Torpa",
    "wof:placetype":"locality"
},
  "geometry": {"coordinates":[14.83333,58.96666999999999],"type":"Point"}
}