{
  "type": "Feature",
  "properties": {
    "gn:admin1_code":"14.0",
    "gn:admin2_code":"2560.0",
    "gn:asciiname":"Strycktjarn",
    "gn:country_code":"SE",
    "gn:dem":49,
    "gn:feature_class":"P",
    "gn:feature_code":"PPL",
    "gn:name":"Strycktj\u00e4rn",
    "gn:population":0,
    "gn:timezone":"Europe/Stockholm",
    "iso:country":"SE",
    "wof:name":"Strycktjarn",
    "wof:placetype":"locality"
},
  "geometry": {"coordinates":[21.13333,65.58333],"type":"Point"}
}