{
  "type": "Feature",
  "properties": {
    "gn:admin1_code":"16.0",
    "gn:admin2_code":"583.0",
    "gn:asciiname":"Hackeryd",
    "gn:country_code":"SE",
    "gn:dem":71,
    "gn:feature_class":"P",
    "gn:feature_code":"PPL",
    "gn:name":"Hackeryd",
    "gn:population":0,
    "gn:timezone":"Europe/Stockholm",
    "iso:country":"SE",
    "wof:name":"Hackeryd",
    "wof:placetype":"locality"
},
  "geometry": {"coordinates":[15.31667,58.45],"type":"Point"}
}