{
  "type": "Feature",
  "properties": {
    "gn:admin1_code":"12.0",
    "gn:admin2_code":"765.0",
    "gn:asciiname":"Jamnhult",
    "gn:country_code":"SE",
    "gn:dem":153,
    "gn:feature_class":"P",
    "gn:feature_code":"PPL",
    "gn:name":"J\u00e4mnhult",
    "gn:population":0,
    "gn:timezone":"Europe/Stockholm",
    "iso:country":"SE",
    "wof:name":"Jamnhult",
    "wof:placetype":"locality"
},
  "geometry": {"coordinates":[13.86667,56.53333000000001],"type":"Point"}
}