{
  "type": "Feature",
  "properties": {
    "gn:admin1_code":"7.0",
    "gn:admin2_code":"2305.0",
    "gn:asciiname":"Hemsjo",
    "gn:country_code":"SE",
    "gn:dem":204,
    "gn:feature_class":"P",
    "gn:feature_code":"PPL",
    "gn:name":"Hemsj\u00f6",
    "gn:population":0,
    "gn:timezone":"Europe/Stockholm",
    "iso:country":"SE",
    "name:nor_x_preferred":[
        "Hemsj\u00f6"
    ],
    "name:nor_x_variant":[
        "Hemsj\u00f8"
    ],
    "wof:name":"Hemsjo",
    "wof:placetype":"locality"
},
  "geometry": {"coordinates":[16.18333,62.78333000000001],"type":"Point"}
}