{
  "type": "Feature",
  "properties": {
    "gn:admin1_code":"23.0",
    "gn:admin2_code":"2482.0",
    "gn:asciiname":"Lidsjon",
    "gn:country_code":"SE",
    "gn:dem":245,
    "gn:feature_class":"P",
    "gn:feature_code":"PPL",
    "gn:name":"Lidsj\u00f6n",
    "gn:population":0,
    "gn:timezone":"Europe/Stockholm",
    "iso:country":"SE",
    "name:nor_x_preferred":[
        "Lidsj\u00f6n"
    ],
    "name:nor_x_variant":[
        "Lidsj\u00f8n"
    ],
    "name:und_x_variant":[
        "Lidsj\u00f6n"
    ],
    "wof:name":"Lidsjon",
    "wof:placetype":"locality"
},
  "geometry": {"coordinates":[20.26667,64.38333],"type":"Point"}
}