{
  "type": "Feature",
  "properties": {
    "gn:admin1_code":"2.0",
    "gn:admin2_code":"1082.0",
    "gn:asciiname":"Stilleryd",
    "gn:country_code":"SE",
    "gn:dem":2,
    "gn:feature_class":"P",
    "gn:feature_code":"PPL",
    "gn:name":"Stilleryd",
    "gn:population":355,
    "gn:timezone":"Europe/Stockholm",
    "iso:country":"SE",
    "wof:name":"Stilleryd",
    "wof:placetype":"locality",
    "wof:population":355
},
  "geometry": {"coordinates":[14.82127,56.17146],"type":"Point"}
}