{
  "type": "Feature",
  "properties": {
    "gn:gn_country":"SE",
    "gn:gn_fcode":"PPL",
    "gn:gn_pop":0,
    "iso:country":"SE",
    "name:dan_x_preferred":[
        "B\u00f6sta"
    ],
    "name:deu_x_preferred":[
        "B\u00f6sta"
    ],
    "name:eng_x_preferred":[
        "B\u00f6sta"
    ],
    "name:fra_x_preferred":[
        "B\u00f6sta"
    ],
    "name:hun_x_preferred":[
        "B\u00f6sta"
    ],
    "name:nds_x_preferred":[
        "B\u00f6sta"
    ],
    "name:nld_x_preferred":[
        "B\u00f6sta"
    ],
    "name:nno_x_preferred":[
        "B\u00f6sta"
    ],
    "name:nob_x_preferred":[
        "B\u00f6sta"
    ],
    "name:nor_x_preferred":[
        "B\u00f8sta"
    ],
    "name:nor_x_variant":[
        "B\u00f6sta"
    ],
    "name:swe_x_preferred":[
        "B\u00f6sta"
    ],
    "qs_pg:aaroncc":"SE",
    "qs_pg:gn_country":"SE",
    "qs_pg:gn_fcode":"PPL",
    "qs_pg:gn_pop":0,
    "qs_pg:name":"B\u00f6sta",
    "qs_pg:name_adm0":"Sverige",
    "qs_pg:name_adm1":"V\u00e4sterbottens L\u00e4n",
    "qs_pg:photos":200,
    "qs_pg:photos_1k":41,
    "qs_pg:photos_9k":1,
    "qs_pg:photos_9r":4,
    "qs_pg:photos_all":200,
    "qs_pg:photos_sr":4,
    "qs_pg:pop_sr":0,
    "qs_pg:qs_pg_placetype":"locality",
    "qs_pg:qs_pg_placetype_gp":"Town",
    "qs_pg:woe_adm0":23424954,
    "woe:adm0_id":23424954,
    "woe:name_adm0":"Sverige",
    "woe:name_adm1":"V\u00e4sterbottens L\u00e4n",
    "woe:placetype":"Town",
    "wof:name":"B\u00f6sta",
    "wof:placetype":"locality"
},
  "geometry": {"coordinates":[19.95,63.75],"type":"Point"}
}