{
  "type": "Feature",
  "properties": {
    "gn:admin1_code":"10.0",
    "gn:admin2_code":"2029.0",
    "gn:asciiname":"Bjorkberg",
    "gn:country_code":"SE",
    "gn:dem":251,
    "gn:feature_class":"P",
    "gn:feature_code":"PPL",
    "gn:name":"Bj\u00f6rkberg",
    "gn:population":0,
    "gn:timezone":"Europe/Stockholm",
    "iso:country":"SE",
    "name:nor_x_preferred":[
        "Bj\u00f6rkberg"
    ],
    "name:nor_x_variant":[
        "Bj\u00f8rkberg"
    ],
    "wof:name":"Bjorkberg",
    "wof:placetype":"locality"
},
  "geometry": {"coordinates":[15.08333,60.76667],"type":"Point"}
}