{
  "type": "Feature",
  "properties": {
    "gn:admin1_code":"7.0",
    "gn:admin2_code":"2309.0",
    "gn:asciiname":"Naversjoberg",
    "gn:cc2":"SE",
    "gn:country_code":"SE",
    "gn:dem":299,
    "gn:feature_class":"P",
    "gn:feature_code":"PPL",
    "gn:name":"N\u00e4versj\u00f6berg",
    "gn:population":0,
    "gn:timezone":"Europe/Stockholm",
    "iso:country":"SE",
    "name:und_x_variant":[
        "N\u00e4fversj\u00f6berg",
        "N\u00e4versj\u00f6berg"
    ],
    "wof:name":"Naversjoberg",
    "wof:placetype":"locality"
},
  "geometry": {"coordinates":[14.46667,63.41667],"type":"Point"}
}