{
  "type": "Feature",
  "properties": {
    "gn:admin1_code":"7.0",
    "gn:admin2_code":"2309.0",
    "gn:asciiname":"Hissmon",
    "gn:country_code":"SE",
    "gn:dem":292,
    "gn:feature_class":"P",
    "gn:feature_code":"PPL",
    "gn:name":"Hissmon",
    "gn:population":0,
    "gn:timezone":"Europe/Stockholm",
    "iso:country":"SE",
    "wof:name":"Hissmon",
    "wof:placetype":"locality"
},
  "geometry": {"coordinates":[14.45,63.33333],"type":"Point"}
}