{
  "type": "Feature",
  "properties": {
    "gn:admin1_code":"28.0",
    "gn:admin2_code":"1482.0",
    "gn:asciiname":"Hallbjortorp",
    "gn:cc2":"SE",
    "gn:country_code":"SE",
    "gn:dem":32,
    "gn:feature_class":"P",
    "gn:feature_code":"PPL",
    "gn:name":"Hallbj\u00f6rtorp",
    "gn:population":0,
    "gn:timezone":"Europe/Stockholm",
    "iso:country":"SE",
    "name:nor_x_preferred":[
        "Hallbj\u00f6rtorp"
    ],
    "name:nor_x_variant":[
        "Hallbj\u00f8rtorp"
    ],
    "name:und_x_variant":[
        "Hallbj\u00f6rntorp"
    ],
    "wof:name":"Hallbjortorp",
    "wof:placetype":"locality"
},
  "geometry": {"coordinates":[11.81667,57.85],"type":"Point"}
}