{
  "type": "Feature",
  "properties": {
    "gn:admin1_code":"6.0",
    "gn:admin2_code":"1384.0",
    "gn:asciiname":"Backa",
    "gn:country_code":"SE",
    "gn:dem":48,
    "gn:feature_class":"P",
    "gn:feature_code":"PPL",
    "gn:name":"Backa",
    "gn:population":0,
    "gn:timezone":"Europe/Stockholm",
    "iso:country":"SE",
    "wof:name":"Backa",
    "wof:placetype":"locality"
},
  "geometry": {"coordinates":[12.26667,57.38333000000001],"type":"Point"}
}