{
  "type": "Feature",
  "properties": {
    "gn:admin1_code":"28.0",
    "gn:admin2_code":"1493.0",
    "gn:asciiname":"Skalkarike",
    "gn:country_code":"SE",
    "gn:dem":67,
    "gn:feature_class":"P",
    "gn:feature_code":"PPL",
    "gn:name":"Skalkarike",
    "gn:population":0,
    "gn:timezone":"Europe/Stockholm",
    "iso:country":"SE",
    "wof:name":"Skalkarike",
    "wof:placetype":"locality"
},
  "geometry": {"coordinates":[13.88333,58.56667],"type":"Point"}
}