{
  "type": "Feature",
  "properties": {
    "gn:admin1_code":"28.0",
    "gn:admin2_code":"1401.0",
    "gn:asciiname":"Gokskulla",
    "gn:country_code":"SE",
    "gn:dem":128,
    "gn:feature_class":"P",
    "gn:feature_code":"PPL",
    "gn:name":"G\u00f6kskulla",
    "gn:population":0,
    "gn:timezone":"Europe/Stockholm",
    "iso:country":"SE",
    "name:nor_x_preferred":[
        "G\u00f6kskulla"
    ],
    "name:nor_x_variant":[
        "G\u00f8kskulla"
    ],
    "name:und_x_variant":[
        "G\u00f6kskulla"
    ],
    "wof:name":"Gokskulla",
    "wof:placetype":"locality"
},
  "geometry": {"coordinates":[12.16667,57.68333000000001],"type":"Point"}
}