{
  "type": "Feature",
  "properties": {
    "gn:admin1_code":"22.0",
    "gn:admin2_code":"1783.0",
    "gn:asciiname":"Skogaangarna",
    "gn:country_code":"SE",
    "gn:dem":161,
    "gn:feature_class":"P",
    "gn:feature_code":"PPL",
    "gn:name":"Skoga\u00e4ngarna",
    "gn:population":0,
    "gn:timezone":"Europe/Stockholm",
    "iso:country":"SE",
    "wof:name":"Skogaangarna",
    "wof:placetype":"locality"
},
  "geometry": {"coordinates":[13.46667,60.01667],"type":"Point"}
}