{
  "type": "Feature",
  "properties": {
    "gn:admin1_code":"10.0",
    "gn:admin2_code":"2080.0",
    "gn:asciiname":"Arnbo",
    "gn:country_code":"SE",
    "gn:dem":117,
    "gn:feature_class":"P",
    "gn:feature_code":"PPL",
    "gn:name":"Arnbo",
    "gn:population":0,
    "gn:timezone":"Europe/Stockholm",
    "iso:country":"SE",
    "wof:name":"Arnbo",
    "wof:placetype":"locality"
},
  "geometry": {"coordinates":[15.83333,60.73333],"type":"Point"}
}