{
  "type": "Feature",
  "properties": {
    "gn:admin1_code":"14.0",
    "gn:admin2_code":"2581.0",
    "gn:asciiname":"Storgranliden",
    "gn:country_code":"SE",
    "gn:dem":376,
    "gn:feature_class":"P",
    "gn:feature_code":"PPL",
    "gn:name":"Storgranliden",
    "gn:population":0,
    "gn:timezone":"Europe/Stockholm",
    "iso:country":"SE",
    "wof:name":"Storgranliden",
    "wof:placetype":"locality"
},
  "geometry": {"coordinates":[20.43333,65.36667],"type":"Point"}
}