{
  "type": "Feature",
  "properties": {
    "gn:admin1_code":"27.0",
    "gn:admin2_code":"1214.0",
    "gn:asciiname":"Galarp",
    "gn:country_code":"SE",
    "gn:dem":160,
    "gn:feature_class":"P",
    "gn:feature_code":"PPL",
    "gn:name":"G\u00e5larp",
    "gn:population":0,
    "gn:timezone":"Europe/Stockholm",
    "iso:country":"SE",
    "wof:name":"Galarp",
    "wof:placetype":"locality"
},
  "geometry": {"coordinates":[13.11667,56.06667],"type":"Point"}
}