{
  "type": "Feature",
  "properties": {
    "gn:admin1_code":"26.0",
    "gn:admin2_code":"138.0",
    "gn:asciiname":"Bjorndalen",
    "gn:country_code":"SE",
    "gn:dem":50,
    "gn:feature_class":"P",
    "gn:feature_code":"PPL",
    "gn:name":"Bj\u00f6rndalen",
    "gn:population":0,
    "gn:timezone":"Europe/Stockholm",
    "iso:country":"SE",
    "name:nor_x_preferred":[
        "Bj\u00f6rndalen"
    ],
    "name:nor_x_variant":[
        "Bj\u00f8rndalen"
    ],
    "wof:name":"Bjorndalen",
    "wof:placetype":"locality"
},
  "geometry": {"coordinates":[18.36667000000001,59.225],"type":"Point"}
}