{
  "type": "Feature",
  "properties": {
    "gn:gn_country":"SE",
    "iso:country":"SE",
    "name:ceb_x_preferred":[
        "Bulland\u00f6"
    ],
    "name:dan_x_preferred":[
        "Bulland\u00f6"
    ],
    "name:deu_x_preferred":[
        "Bulland\u00f6"
    ],
    "name:eng_x_preferred":[
        "Bulland\u00f6"
    ],
    "name:fra_x_preferred":[
        "Bulland\u00f6"
    ],
    "name:nds_x_preferred":[
        "Bulland\u00f6"
    ],
    "name:nld_x_preferred":[
        "Bulland\u00f6"
    ],
    "name:nno_x_preferred":[
        "Bulland\u00f6"
    ],
    "name:nob_x_preferred":[
        "Bulland\u00f6"
    ],
    "name:swe_x_preferred":[
        "Bulland\u00f6"
    ],
    "qs_pg:aaroncc":"SE",
    "qs_pg:gn_country":"SE",
    "qs_pg:name":"Bulland\u00f6",
    "qs_pg:name_adm0":"Sverige",
    "qs_pg:name_adm1":"Stockholms L\u00e4n",
    "qs_pg:photos":773,
    "qs_pg:photos_1k":157,
    "qs_pg:photos_9k":3,
    "qs_pg:photos_9r":6,
    "qs_pg:photos_all":773,
    "qs_pg:photos_sr":9,
    "qs_pg:pop_sr":0,
    "qs_pg:qs_pg_placetype":"locality",
    "qs_pg:qs_pg_placetype_gp":"Town",
    "qs_pg:woe_adm0":23424954,
    "woe:adm0_id":23424954,
    "woe:name_adm0":"Sverige",
    "woe:name_adm1":"Stockholms L\u00e4n",
    "woe:placetype":"Town",
    "wof:name":"Bulland\u00f6",
    "wof:placetype":"locality"
},
  "geometry": {"coordinates":[18.672115,59.297809],"type":"Point"}
}