{
  "type": "Feature",
  "properties": {
    "gn:admin1_code":"15.0",
    "gn:admin2_code":"1880.0",
    "gn:asciiname":"Karlsholm",
    "gn:country_code":"SE",
    "gn:dem":39,
    "gn:feature_class":"P",
    "gn:feature_code":"PPL",
    "gn:name":"Karlsholm",
    "gn:population":0,
    "gn:timezone":"Europe/Stockholm",
    "iso:country":"SE",
    "wof:name":"Karlsholm",
    "wof:placetype":"locality"
},
  "geometry": {"coordinates":[15.61667,59.13333000000001],"type":"Point"}
}