{
  "type": "Feature",
  "properties": {
    "gn:admin1_code":"22.0",
    "gn:admin2_code":"1784.0",
    "gn:asciiname":"Hillringsberg",
    "gn:cc2":"SE",
    "gn:country_code":"SE",
    "gn:dem":63,
    "gn:feature_class":"P",
    "gn:feature_code":"PPL",
    "gn:name":"Hillringsberg",
    "gn:population":0,
    "gn:timezone":"Europe/Stockholm",
    "iso:country":"SE",
    "name:und_x_variant":[
        "Hillrings",
        "Hillringsberg"
    ],
    "wof:name":"Hillringsberg",
    "wof:placetype":"locality"
},
  "geometry": {"coordinates":[12.61667,59.53333000000001],"type":"Point"}
}