{
  "type": "Feature",
  "properties": {
    "gn:admin1_code":"8.0",
    "gn:admin2_code":"685.0",
    "gn:asciiname":"Sodraskog",
    "gn:country_code":"SE",
    "gn:dem":185,
    "gn:feature_class":"P",
    "gn:feature_code":"PPL",
    "gn:name":"S\u00f6draskog",
    "gn:population":0,
    "gn:timezone":"Europe/Stockholm",
    "iso:country":"SE",
    "name:nor_x_preferred":[
        "S\u00f6draskog"
    ],
    "name:nor_x_variant":[
        "S\u00f8draskog"
    ],
    "wof:name":"Sodraskog",
    "wof:placetype":"locality"
},
  "geometry": {"coordinates":[14.96667,57.15],"type":"Point"}
}