{
  "type": "Feature",
  "properties": {
    "gn:admin1_code":"12.0",
    "gn:admin2_code":"767.0",
    "gn:asciiname":"Fjarholma",
    "gn:country_code":"SE",
    "gn:dem":125,
    "gn:feature_class":"P",
    "gn:feature_code":"PPL",
    "gn:name":"Fj\u00e4rholma",
    "gn:population":0,
    "gn:timezone":"Europe/Stockholm",
    "iso:country":"SE",
    "wof:name":"Fjarholma",
    "wof:placetype":"locality"
},
  "geometry": {"coordinates":[13.65,56.46666999999999],"type":"Point"}
}