{
  "type": "Feature",
  "properties": {
    "gn:admin1_code":"24.0",
    "gn:admin2_code":"2281.0",
    "gn:admin3_code":"228107.0",
    "gn:admin4_code":"2496.0",
    "gn:asciiname":"Edsta",
    "gn:country_code":"SE",
    "gn:dem":53,
    "gn:feature_class":"P",
    "gn:feature_code":"PPL",
    "gn:name":"Edsta",
    "gn:population":0,
    "gn:timezone":"Europe/Stockholm",
    "iso:country":"SE",
    "wof:name":"Edsta",
    "wof:placetype":"locality"
},
  "geometry": {"coordinates":[16.58281,62.41927],"type":"Point"}
}