{
  "type": "Feature",
  "properties": {
    "gn:admin1_code":"24.0",
    "gn:admin2_code":"2284.0",
    "gn:asciiname":"Bodum",
    "gn:country_code":"SE",
    "gn:dem":48,
    "gn:feature_class":"P",
    "gn:feature_code":"PPL",
    "gn:name":"Bodum",
    "gn:population":0,
    "gn:timezone":"Europe/Stockholm",
    "iso:country":"SE",
    "name:dan_x_preferred":[
        "Bodum"
    ],
    "name:deu_x_preferred":[
        "Bodum"
    ],
    "name:fin_x_preferred":[
        "Bodum"
    ],
    "name:fra_x_preferred":[
        "Bodum"
    ],
    "name:ita_x_preferred":[
        "Bodum"
    ],
    "name:nld_x_preferred":[
        "Bodum"
    ],
    "name:rus_x_preferred":[
        "Bodum"
    ],
    "name:spa_x_preferred":[
        "Bodum"
    ],
    "wof:name":"Bodum",
    "wof:placetype":"locality"
},
  "geometry": {"coordinates":[19.21667,63.38333000000001],"type":"Point"}
}