{
  "type": "Feature",
  "properties": {
    "gn:admin1_code":"12.0",
    "gn:admin2_code":"764.0",
    "gn:asciiname":"Hasthagen",
    "gn:country_code":"SE",
    "gn:dem":153,
    "gn:feature_class":"P",
    "gn:feature_code":"PPL",
    "gn:name":"H\u00e4sthagen",
    "gn:population":0,
    "gn:timezone":"Europe/Stockholm",
    "iso:country":"SE",
    "wof:name":"Hasthagen",
    "wof:placetype":"locality"
},
  "geometry": {"coordinates":[14.46667,56.76667],"type":"Point"}
}