{
  "type": "Feature",
  "properties": {
    "gn:gn_country":"SE",
    "gn:gn_fcode":"PPL",
    "gn:gn_pop":0,
    "iso:country":"SE",
    "name:dan_x_preferred":[
        "H\u00e4stevik"
    ],
    "name:dut_x_preferred":[
        "H\u00e4stevik"
    ],
    "name:eng_x_preferred":[
        "H\u00e4stevik"
    ],
    "name:fre_x_preferred":[
        "H\u00e4stevik"
    ],
    "name:ger_x_preferred":[
        "H\u00e4stevik"
    ],
    "name:nds_x_preferred":[
        "H\u00e4stevik"
    ],
    "name:nno_x_preferred":[
        "H\u00e4stevik"
    ],
    "name:nob_x_preferred":[
        "H\u00e4stevik"
    ],
    "name:swe_x_preferred":[
        "H\u00e4stevik"
    ],
    "qs_pg:aaroncc":"SE",
    "qs_pg:gn_country":"SE",
    "qs_pg:gn_fcode":"PPL",
    "qs_pg:gn_pop":0,
    "qs_pg:name":"H\u00e4stevik",
    "qs_pg:name_adm0":"Sverige",
    "qs_pg:name_adm1":"V\u00e4stra G\u00f6talands L\u00e4n",
    "qs_pg:photos":50,
    "qs_pg:photos_1k":10,
    "qs_pg:photos_9k":1,
    "qs_pg:photos_9r":2,
    "qs_pg:photos_all":50,
    "qs_pg:photos_sr":2,
    "qs_pg:pop_sr":0,
    "qs_pg:qs_pg_placetype":"locality",
    "qs_pg:qs_pg_placetype_gp":"Town",
    "qs_pg:woe_adm0":23424954,
    "woe:adm0_id":23424954,
    "woe:name_adm0":"Sverige",
    "woe:name_adm1":"V\u00e4stra G\u00f6talands L\u00e4n",
    "woe:placetype":"Town",
    "wof:name":"H\u00e4stevik",
    "wof:placetype":"locality"
},
  "geometry": {"coordinates":[11.72972,57.71333],"type":"Point"}
}