{
  "type": "Feature",
  "properties": {
    "gn:admin1_code":"21.0",
    "gn:admin2_code":"380.0",
    "gn:asciiname":"Mjolsta",
    "gn:country_code":"SE",
    "gn:dem":9,
    "gn:feature_class":"P",
    "gn:feature_code":"PPL",
    "gn:name":"Mj\u00f6lsta",
    "gn:population":0,
    "gn:timezone":"Europe/Stockholm",
    "iso:country":"SE",
    "name:nor_x_preferred":[
        "Mj\u00f6lsta"
    ],
    "name:nor_x_variant":[
        "Mj\u00f8lsta"
    ],
    "name:und_x_variant":[
        "Mj\u00f6lsta"
    ],
    "wof:name":"Mjolsta",
    "wof:placetype":"locality"
},
  "geometry": {"coordinates":[17.98333,60.01667],"type":"Point"}
}