{
  "type": "Feature",
  "properties": {
    "gn:admin1_code":"12.0",
    "gn:admin2_code":"761.0",
    "gn:asciiname":"Skrambohult",
    "gn:country_code":"SE",
    "gn:dem":147,
    "gn:feature_class":"P",
    "gn:feature_code":"PPL",
    "gn:name":"Skr\u00e4mbohult",
    "gn:population":0,
    "gn:timezone":"Europe/Stockholm",
    "iso:country":"SE",
    "wof:name":"Skrambohult",
    "wof:placetype":"locality"
},
  "geometry": {"coordinates":[15.38333,56.68333000000001],"type":"Point"}
}