{
  "type": "Feature",
  "properties": {
    "gn:admin1_code":"27.0",
    "gn:admin2_code":"1285.0",
    "gn:asciiname":"Bosarp",
    "gn:country_code":"SE",
    "gn:dem":63,
    "gn:feature_class":"P",
    "gn:feature_code":"PPL",
    "gn:name":"Bosarp",
    "gn:population":0,
    "gn:timezone":"Europe/Stockholm",
    "iso:country":"SE",
    "wof:name":"Bosarp",
    "wof:placetype":"locality"
},
  "geometry": {"coordinates":[13.31667,55.88333000000001],"type":"Point"}
}