{
  "type": "Feature",
  "properties": {
    "gn:admin1_code":"10.0",
    "gn:admin2_code":"2026.0",
    "gn:admin3_code":"202603.0",
    "gn:admin4_code":"2348.0",
    "gn:asciiname":"Salje",
    "gn:country_code":"SE",
    "gn:dem":203,
    "gn:feature_class":"P",
    "gn:feature_code":"PPL",
    "gn:name":"S\u00e4lje",
    "gn:population":0,
    "gn:timezone":"Europe/Stockholm",
    "iso:country":"SE",
    "wof:name":"Salje",
    "wof:placetype":"locality"
},
  "geometry": {"coordinates":[14.85008,60.49516],"type":"Point"}
}