{
  "type": "Feature",
  "properties": {
    "gn:admin1_code":"12.0",
    "gn:admin2_code":"763.0",
    "gn:asciiname":"Dammarskulla",
    "gn:cc2":"SE",
    "gn:country_code":"SE",
    "gn:dem":182,
    "gn:feature_class":"P",
    "gn:feature_code":"PPL",
    "gn:name":"Dammarskulla",
    "gn:population":0,
    "gn:timezone":"Europe/Stockholm",
    "iso:country":"SE",
    "name:und_x_variant":[
        "Dammerskulla",
        "Dammarskulla"
    ],
    "wof:name":"Dammarskulla",
    "wof:placetype":"locality"
},
  "geometry": {"coordinates":[15.05,56.53333000000001],"type":"Point"}
}