{
  "type": "Feature",
  "properties": {
    "gn:admin1_code":"24.0",
    "gn:admin2_code":"2260.0",
    "gn:admin3_code":"226004.0",
    "gn:admin4_code":"2502.0",
    "gn:asciiname":"Djuprora",
    "gn:country_code":"SE",
    "gn:dem":214,
    "gn:feature_class":"P",
    "gn:feature_code":"PPL",
    "gn:name":"Djupr\u00f6ra",
    "gn:population":0,
    "gn:timezone":"Europe/Stockholm",
    "iso:country":"SE",
    "name:nor_x_preferred":[
        "Djupr\u00f6ra"
    ],
    "name:nor_x_variant":[
        "Djupr\u00f8ra"
    ],
    "name:und_x_variant":[
        "Djupr\u00f6ra"
    ],
    "wof:name":"Djuprora",
    "wof:placetype":"locality"
},
  "geometry": {"coordinates":[16.34045,62.69141],"type":"Point"}
}