{
  "type": "Feature",
  "properties": {
    "gn:admin1_code":"23.0",
    "gn:admin2_code":"2482.0",
    "gn:asciiname":"Ersmark",
    "gn:country_code":"SE",
    "gn:dem":31,
    "gn:feature_class":"P",
    "gn:feature_code":"PPL",
    "gn:name":"Ersmark",
    "gn:population":875,
    "gn:timezone":"Europe/Stockholm",
    "iso:country":"SE",
    "wof:name":"Ersmark",
    "wof:placetype":"locality",
    "wof:population":875
},
  "geometry": {"coordinates":[20.896,64.84806],"type":"Point"}
}