{
  "type": "Feature",
  "properties": {
    "gn:admin1_code":"25.0",
    "gn:admin2_code":"1961.0",
    "gn:asciiname":"Bjorsbo",
    "gn:country_code":"SE",
    "gn:dem":69,
    "gn:feature_class":"P",
    "gn:feature_code":"PPL",
    "gn:name":"Bj\u00f6rsbo",
    "gn:population":0,
    "gn:timezone":"Europe/Stockholm",
    "iso:country":"SE",
    "name:nor_x_preferred":[
        "Bj\u00f6rsbo"
    ],
    "name:nor_x_variant":[
        "Bj\u00f8rsbo"
    ],
    "name:und_x_variant":[
        "Bj\u00f6rsbo"
    ],
    "wof:name":"Bjorsbo",
    "wof:placetype":"locality"
},
  "geometry": {"coordinates":[16.13332999999999,59.63333000000001],"type":"Point"}
}