{
  "type": "Feature",
  "properties": {
    "gn:admin1_code":"16.0",
    "gn:admin2_code":"563.0",
    "gn:asciiname":"Sorby",
    "gn:country_code":"SE",
    "gn:dem":38,
    "gn:feature_class":"P",
    "gn:feature_code":"PPL",
    "gn:name":"S\u00f6rby",
    "gn:population":0,
    "gn:timezone":"Europe/Stockholm",
    "iso:country":"SE",
    "name:nor_x_preferred":[
        "S\u00f6rby"
    ],
    "name:nor_x_variant":[
        "S\u00f8rby"
    ],
    "name:und_x_variant":[
        "S\u00f6rby"
    ],
    "wof:name":"Sorby",
    "wof:placetype":"locality"
},
  "geometry": {"coordinates":[16.45,58.33306],"type":"Point"}
}