{
  "type": "Feature",
  "properties": {
    "gn:admin1_code":"28.0",
    "gn:admin2_code":"1438.0",
    "gn:asciiname":"Toftedal",
    "gn:country_code":"SE",
    "gn:dem":138,
    "gn:feature_class":"P",
    "gn:feature_code":"PPL",
    "gn:name":"T\u00f6ftedal",
    "gn:population":0,
    "gn:timezone":"Europe/Stockholm",
    "iso:country":"SE",
    "name:nor_x_preferred":[
        "T\u00f6ftedal"
    ],
    "name:nor_x_variant":[
        "T\u00f8ftedal"
    ],
    "wof:name":"Toftedal",
    "wof:placetype":"locality"
},
  "geometry": {"coordinates":[11.78306,58.83306],"type":"Point"}
}