{
  "type": "Feature",
  "properties": {
    "gn:admin1_code":"14.0",
    "gn:admin2_code":"2514.0",
    "gn:asciiname":"Mjotrask",
    "gn:country_code":"SE",
    "gn:dem":72,
    "gn:feature_class":"P",
    "gn:feature_code":"PPL",
    "gn:name":"Mj\u00f6tr\u00e4sk",
    "gn:population":0,
    "gn:timezone":"Europe/Stockholm",
    "iso:country":"SE",
    "wof:name":"Mjotrask",
    "wof:placetype":"locality"
},
  "geometry": {"coordinates":[23.03333,65.95],"type":"Point"}
}