{
  "type": "Feature",
  "properties": {
    "gn:admin1_code":"21.0",
    "gn:admin2_code":"382.0",
    "gn:asciiname":"Grasbo",
    "gn:country_code":"SE",
    "gn:dem":29,
    "gn:feature_class":"P",
    "gn:feature_code":"PPL",
    "gn:name":"Gr\u00e4sbo",
    "gn:population":0,
    "gn:timezone":"Europe/Stockholm",
    "iso:country":"SE",
    "wof:name":"Grasbo",
    "wof:placetype":"locality"
},
  "geometry": {"coordinates":[17.95,60.31667],"type":"Point"}
}