{
  "type": "Feature",
  "properties": {
    "gn:admin1_code":"27.0",
    "gn:admin2_code":"1284.0",
    "gn:asciiname":"Sodra Danhult",
    "gn:cc2":"SE",
    "gn:country_code":"SE",
    "gn:dem":6,
    "gn:feature_class":"P",
    "gn:feature_code":"PPL",
    "gn:name":"S\u00f6dra Danhult",
    "gn:population":0,
    "gn:timezone":"Europe/Stockholm",
    "iso:country":"SE",
    "name:nor_x_preferred":[
        "S\u00f6dra Danhult"
    ],
    "name:nor_x_variant":[
        "S\u00f8dra Danhult"
    ],
    "name:und_x_variant":[
        "Danhult",
        "S\u00f6dra Danhult"
    ],
    "wof:name":"Sodra Danhult",
    "wof:placetype":"locality"
},
  "geometry": {"coordinates":[12.65,56.18333000000001],"type":"Point"}
}