{
  "type": "Feature",
  "properties": {
    "gn:admin1_code":"16.0",
    "gn:admin2_code":"584.0",
    "gn:asciiname":"Kallstad",
    "gn:country_code":"SE",
    "gn:dem":101,
    "gn:feature_class":"P",
    "gn:feature_code":"PPL",
    "gn:name":"K\u00e4llstad",
    "gn:population":0,
    "gn:timezone":"Europe/Stockholm",
    "iso:country":"SE",
    "wof:name":"Kallstad",
    "wof:placetype":"locality"
},
  "geometry": {"coordinates":[14.76667,58.38333000000001],"type":"Point"}
}