{
  "type": "Feature",
  "properties": {
    "gn:admin1_code":"3.0",
    "gn:admin2_code":"2180.0",
    "gn:asciiname":"Sand",
    "gn:country_code":"SE",
    "gn:dem":21,
    "gn:feature_class":"P",
    "gn:feature_code":"PPL",
    "gn:name":"Sand",
    "gn:population":0,
    "gn:timezone":"Europe/Stockholm",
    "iso:country":"SE",
    "wof:name":"Sand",
    "wof:placetype":"locality"
},
  "geometry": {"coordinates":[17.08333,60.91667],"type":"Point"}
}