{
  "type": "Feature",
  "properties": {
    "gn:admin1_code":"10.0",
    "gn:admin2_code":"2085.0",
    "gn:asciiname":"Kampfallet",
    "gn:country_code":"SE",
    "gn:dem":413,
    "gn:feature_class":"P",
    "gn:feature_code":"PPL",
    "gn:name":"Kampfallet",
    "gn:population":0,
    "gn:timezone":"Europe/Stockholm",
    "iso:country":"SE",
    "wof:name":"Kampfallet",
    "wof:placetype":"locality"
},
  "geometry": {"coordinates":[14.35,60.16667],"type":"Point"}
}