{
  "type": "Feature",
  "properties": {
    "gn:gn_country":"SE",
    "gn:gn_fcode":"PPL",
    "gn:gn_pop":559,
    "gn:population":574,
    "iso:country":"SE",
    "name:bul_x_preferred":[
        "\u041c\u0430\u043b\u0443\u043d\u0433\u0441\u0444\u043e\u0440\u0441"
    ],
    "name:dut_x_preferred":[
        "Malungsfors"
    ],
    "name:eng_x_preferred":[
        "Malungsfors"
    ],
    "name:nan_x_preferred":[
        "Malungsfors"
    ],
    "name:nno_x_preferred":[
        "Malungsfors"
    ],
    "name:nob_x_preferred":[
        "Malungsfors"
    ],
    "name:swe_x_preferred":[
        "Malungsfors"
    ],
    "qs_pg:aaroncc":"SE",
    "qs_pg:gn_country":"SE",
    "qs_pg:gn_fcode":"PPL",
    "qs_pg:gn_pop":559,
    "qs_pg:name":"Malungsfors",
    "qs_pg:photos_9r":0,
    "qs_pg:photos_sr":0,
    "qs_pg:pop_sr":2,
    "qs_pg:qs_pg_placetype":"locality",
    "wof:name":"Malungsfors",
    "wof:placetype":"locality",
    "wof:population":574
},
  "geometry": {"coordinates":[13.55,60.73333],"type":"Point"}
}