{
  "type": "Feature",
  "properties": {
    "gn:admin1_code":"22.0",
    "gn:admin2_code":"1780.0",
    "gn:asciiname":"Ostra Acksjon",
    "gn:country_code":"SE",
    "gn:dem":135,
    "gn:feature_class":"P",
    "gn:feature_code":"PPL",
    "gn:name":"\u00d6stra Acksj\u00f6n",
    "gn:population":0,
    "gn:timezone":"Europe/Stockholm",
    "iso:country":"SE",
    "name:nor_x_preferred":[
        "\u00d6stra Acksj\u00f6n"
    ],
    "name:nor_x_variant":[
        "\u00d8stra Acksj\u00f8n"
    ],
    "name:und_x_variant":[
        "\u00d6stra Acksj\u00f6n"
    ],
    "wof:name":"Ostra Acksjon",
    "wof:placetype":"locality"
},
  "geometry": {"coordinates":[13.75,59.65],"type":"Point"}
}