{
  "type": "Feature",
  "properties": {
    "gn:admin1_code":"10.0",
    "gn:admin2_code":"2039.0",
    "gn:asciiname":"Bruket",
    "gn:country_code":"SE",
    "gn:dem":475,
    "gn:feature_class":"P",
    "gn:feature_code":"PPL",
    "gn:name":"Bruket",
    "gn:population":0,
    "gn:timezone":"Europe/Stockholm",
    "iso:country":"SE",
    "wof:name":"Bruket",
    "wof:placetype":"locality"
},
  "geometry": {"coordinates":[13.11667,61.61666999999999],"type":"Point"}
}