{
  "type": "Feature",
  "properties": {
    "gn:admin1_code":"28.0",
    "gn:admin2_code":"1487.0",
    "gn:asciiname":"Lersater",
    "gn:country_code":"SE",
    "gn:dem":79,
    "gn:feature_class":"P",
    "gn:feature_code":"PPL",
    "gn:name":"Lers\u00e4ter",
    "gn:population":0,
    "gn:timezone":"Europe/Stockholm",
    "iso:country":"SE",
    "wof:name":"Lersater",
    "wof:placetype":"locality"
},
  "geometry": {"coordinates":[12.28333,58.58333],"type":"Point"}
}