{
  "type": "Feature",
  "properties": {
    "gn:admin1_code":"3.0",
    "gn:admin2_code":"2132.0",
    "gn:asciiname":"Morangsviken",
    "gn:country_code":"SE",
    "gn:dem":1,
    "gn:feature_class":"P",
    "gn:feature_code":"PPL",
    "gn:name":"Mor\u00e4ngsviken",
    "gn:population":0,
    "gn:timezone":"Europe/Stockholm",
    "iso:country":"SE",
    "wof:name":"Morangsviken",
    "wof:placetype":"locality"
},
  "geometry": {"coordinates":[17.33522,61.90744],"type":"Point"}
}