{
  "type": "Feature",
  "properties": {
    "gn:admin1_code":"27.0",
    "gn:admin2_code":"1285.0",
    "gn:asciiname":"Gryby",
    "gn:country_code":"SE",
    "gn:dem":68,
    "gn:feature_class":"P",
    "gn:feature_code":"PPL",
    "gn:name":"Gryby",
    "gn:population":0,
    "gn:timezone":"Europe/Stockholm",
    "iso:country":"SE",
    "wof:name":"Gryby",
    "wof:placetype":"locality"
},
  "geometry": {"coordinates":[13.31667,55.83333],"type":"Point"}
}