{
  "type": "Feature",
  "properties": {
    "gn:admin1_code":"7.0",
    "gn:admin2_code":"2303.0",
    "gn:asciiname":"Svarthalsforsen",
    "gn:country_code":"SE",
    "gn:dem":113,
    "gn:feature_class":"P",
    "gn:feature_code":"PPL",
    "gn:name":"Svarth\u00e5lsforsen",
    "gn:population":0,
    "gn:timezone":"Europe/Stockholm",
    "iso:country":"SE",
    "wof:name":"Svarthalsforsen",
    "wof:placetype":"locality"
},
  "geometry": {"coordinates":[16.56667,63.03333000000001],"type":"Point"}
}