{
  "type": "Feature",
  "properties": {
    "gn:admin1_code":"23.0",
    "gn:asciiname":"Stor-Snackhamnen",
    "gn:country_code":"SE",
    "gn:dem":-9999,
    "gn:feature_class":"P",
    "gn:feature_code":"PPL",
    "gn:name":"Stor-Sn\u00e4ckhamnen",
    "gn:population":0,
    "gn:timezone":"Europe/Stockholm",
    "iso:country":"SE",
    "wof:name":"Stor-Snackhamnen",
    "wof:placetype":"locality"
},
  "geometry": {"coordinates":[21.18333,64.78333000000001],"type":"Point"}
}