{
  "type": "Feature",
  "properties": {
    "gn:admin1_code":"21.0",
    "gn:admin2_code":"360.0",
    "gn:asciiname":"Nysater",
    "gn:country_code":"SE",
    "gn:dem":39,
    "gn:feature_class":"P",
    "gn:feature_code":"PPL",
    "gn:name":"Nys\u00e4ter",
    "gn:population":0,
    "gn:timezone":"Europe/Stockholm",
    "iso:country":"SE",
    "wof:name":"Nysater",
    "wof:placetype":"locality"
},
  "geometry": {"coordinates":[17.45,60.48333],"type":"Point"}
}