{
  "type": "Feature",
  "properties": {
    "gn:admin1_code":"14.0",
    "gn:admin2_code":"2581.0",
    "gn:asciiname":"Lillbron",
    "gn:country_code":"SE",
    "gn:dem":3,
    "gn:feature_class":"P",
    "gn:feature_code":"PPL",
    "gn:name":"Lillbron",
    "gn:population":0,
    "gn:timezone":"Europe/Stockholm",
    "iso:country":"SE",
    "wof:name":"Lillbron",
    "wof:placetype":"locality"
},
  "geometry": {"coordinates":[21.26667,65.36667],"type":"Point"}
}