{
  "type": "Feature",
  "properties": {
    "gn:admin1_code":"26.0",
    "gn:admin2_code":"126.0",
    "gn:asciiname":"Mortvik",
    "gn:country_code":"SE",
    "gn:dem":37,
    "gn:feature_class":"P",
    "gn:feature_code":"PPL",
    "gn:name":"M\u00f6rtvik",
    "gn:population":0,
    "gn:timezone":"Europe/Stockholm",
    "iso:country":"SE",
    "name:nor_x_preferred":[
        "M\u00f6rtvik"
    ],
    "name:nor_x_variant":[
        "M\u00f8rtvik"
    ],
    "wof:name":"Mortvik",
    "wof:placetype":"locality"
},
  "geometry": {"coordinates":[18.15,59.21666999999999],"type":"Point"}
}