{
  "type": "Feature",
  "properties": {
    "gn:country":"SE",
    "gn:fcode":"PPL",
    "gn:population":818,
    "iso:country":"SE",
    "name:bul_x_preferred":[
        "\u0415\u0441\u0432\u0438\u043a"
    ],
    "name:ceb_x_preferred":[
        "Essvik"
    ],
    "name:eng_x_preferred":[
        "Essvik"
    ],
    "name:ita_x_preferred":[
        "Essvik"
    ],
    "name:nan_x_preferred":[
        "Essvik"
    ],
    "name:nld_x_preferred":[
        "Essvik"
    ],
    "name:nno_x_preferred":[
        "Essvik"
    ],
    "name:nob_x_preferred":[
        "Essvik"
    ],
    "name:swe_x_preferred":[
        "Essvik"
    ],
    "name:und_x_variant":[
        "Essviken"
    ],
    "qs_pg:aaroncc":"SE",
    "qs_pg:gn_country":"SE",
    "qs_pg:gn_fcode":"PPL",
    "qs_pg:gn_pop":818,
    "qs_pg:name":"Essvik",
    "qs_pg:name_adm0":"Sverige",
    "qs_pg:name_adm1":"V\u00e4sternorrlands L\u00e4n",
    "qs_pg:photos_9k":1,
    "qs_pg:photos_9r":1,
    "qs_pg:photos_all":1,
    "qs_pg:photos_sr":0,
    "qs_pg:pop_sr":2,
    "qs_pg:qs_pg_placetype":"locality",
    "qs_pg:qs_pg_placetype_gp":"Town",
    "qs_pg:woe_adm0":23424954,
    "woe:adm0_id":23424954,
    "woe:name_adm0":"Sverige",
    "woe:name_adm1":"V\u00e4sternorrlands L\u00e4n",
    "woe:placetype":"Town",
    "wof:name":"Essvik",
    "wof:placetype":"locality",
    "wof:population":818
},
  "geometry": {"coordinates":[17.39306,62.31639],"type":"Point"}
}