{
  "type": "Feature",
  "properties": {
    "gn:admin1_code":"22.0",
    "gn:admin2_code":"1760.0",
    "gn:asciiname":"Herrsjotorp",
    "gn:country_code":"SE",
    "gn:dem":127,
    "gn:feature_class":"P",
    "gn:feature_code":"PPL",
    "gn:name":"Herrsj\u00f6torp",
    "gn:population":0,
    "gn:timezone":"Europe/Stockholm",
    "iso:country":"SE",
    "name:nor_x_preferred":[
        "Herrsj\u00f6torp"
    ],
    "name:nor_x_variant":[
        "Herrsj\u00f8torp"
    ],
    "wof:name":"Herrsjotorp",
    "wof:placetype":"locality"
},
  "geometry": {"coordinates":[14.36667,59.41667],"type":"Point"}
}