{
  "type": "Feature",
  "properties": {
    "gn:gn_country":"SE",
    "gn:gn_fcode":"PPL",
    "gn:gn_pop":0,
    "iso:country":"SE",
    "name:dan_x_preferred":[
        "Nyhamn"
    ],
    "name:dut_x_preferred":[
        "Nyhamn"
    ],
    "name:eng_x_preferred":[
        "Nyhamn"
    ],
    "name:fre_x_preferred":[
        "Nyhamn"
    ],
    "name:ger_x_preferred":[
        "Nyhamn"
    ],
    "name:nds_x_preferred":[
        "Nyhamn"
    ],
    "name:nno_x_preferred":[
        "Nyhamn"
    ],
    "name:nob_x_preferred":[
        "Nyhamn"
    ],
    "name:nor_x_preferred":[
        "S\u00f8dra Nyhamn"
    ],
    "name:nor_x_variant":[
        "S\u00f6dra Nyhamn"
    ],
    "name:swe_x_preferred":[
        "Nyhamn"
    ],
    "name:unk_x_variant":[
        "S\u00f6dra Nyhamn"
    ],
    "qs_pg:aaroncc":"SE",
    "qs_pg:gn_country":"SE",
    "qs_pg:gn_fcode":"PPL",
    "qs_pg:gn_pop":0,
    "qs_pg:name":"Nyhamn",
    "qs_pg:name_adm0":"Sverige",
    "qs_pg:name_adm1":"V\u00e4sternorrlands L\u00e4n",
    "qs_pg:photos":322,
    "qs_pg:photos_1k":65,
    "qs_pg:photos_9k":1,
    "qs_pg:photos_9r":5,
    "qs_pg:photos_all":322,
    "qs_pg:photos_sr":5,
    "qs_pg:pop_sr":0,
    "qs_pg:qs_pg_placetype":"locality",
    "qs_pg:qs_pg_placetype_gp":"Town",
    "qs_pg:woe_adm0":23424954,
    "woe:adm0_id":23424954,
    "woe:name_adm0":"Sverige",
    "woe:name_adm1":"V\u00e4sternorrlands L\u00e4n",
    "woe:placetype":"Town",
    "wof:name":"Nyhamn",
    "wof:placetype":"locality"
},
  "geometry": {"coordinates":[17.39778,62.32167],"type":"Point"}
}