{
  "type": "Feature",
  "properties": {
    "gn:admin1_code":"6.0",
    "gn:admin2_code":"1382.0",
    "gn:asciiname":"Bjorsgard",
    "gn:country_code":"SE",
    "gn:dem":27,
    "gn:feature_class":"P",
    "gn:feature_code":"PPL",
    "gn:name":"Bj\u00f6rsg\u00e5rd",
    "gn:population":0,
    "gn:timezone":"Europe/Stockholm",
    "iso:country":"SE",
    "name:nor_x_preferred":[
        "Bj\u00f6rsg\u00e5rd"
    ],
    "name:nor_x_variant":[
        "Bj\u00f8rsg\u00e5rd"
    ],
    "name:und_x_variant":[
        "Bj\u00f6rsg\u00e5rd"
    ],
    "wof:name":"Bjorsgard",
    "wof:placetype":"locality"
},
  "geometry": {"coordinates":[12.56667,56.85],"type":"Point"}
}