{
  "type": "Feature",
  "properties": {
    "gn:admin1_code":"14.0",
    "gn:admin2_code":"2514.0",
    "gn:asciiname":"Moan",
    "gn:country_code":"SE",
    "gn:dem":28,
    "gn:feature_class":"P",
    "gn:feature_code":"PPL",
    "gn:name":"Mo\u00e5n",
    "gn:population":0,
    "gn:timezone":"Europe/Stockholm",
    "iso:country":"SE",
    "wof:name":"Moan",
    "wof:placetype":"locality"
},
  "geometry": {"coordinates":[23.31667,65.93333],"type":"Point"}
}