{
  "type": "Feature",
  "properties": {
    "gn:gn_country":"SE",
    "gn:gn_fcode":"PPL",
    "gn:gn_pop":0,
    "iso:country":"SE",
    "name:dan_x_preferred":[
        "Hara"
    ],
    "name:dut_x_preferred":[
        "Hara"
    ],
    "name:eng_x_preferred":[
        "Hara"
    ],
    "name:fre_x_preferred":[
        "Hara"
    ],
    "name:ger_x_preferred":[
        "Hara"
    ],
    "name:nds_x_preferred":[
        "Hara"
    ],
    "name:nno_x_preferred":[
        "Hara"
    ],
    "name:nob_x_preferred":[
        "Hara"
    ],
    "name:swe_x_preferred":[
        "Hara"
    ],
    "qs_pg:aaroncc":"SE",
    "qs_pg:gn_country":"SE",
    "qs_pg:gn_fcode":"PPL",
    "qs_pg:gn_pop":0,
    "qs_pg:name":"Hara",
    "qs_pg:name_adm0":"Sverige",
    "qs_pg:name_adm1":"V\u00e4rmlands L\u00e4n",
    "qs_pg:photos":29,
    "qs_pg:photos_1k":6,
    "qs_pg:photos_9k":1,
    "qs_pg:photos_9r":2,
    "qs_pg:photos_all":29,
    "qs_pg:photos_sr":2,
    "qs_pg:pop_sr":0,
    "qs_pg:qs_pg_placetype":"locality",
    "qs_pg:qs_pg_placetype_gp":"Town",
    "qs_pg:woe_adm0":23424954,
    "woe:adm0_id":23424954,
    "woe:name_adm0":"Sverige",
    "woe:name_adm1":"V\u00e4rmlands L\u00e4n",
    "woe:placetype":"Town",
    "wof:name":"Hara",
    "wof:placetype":"locality"
},
  "geometry": {"coordinates":[13.48333,60.21667],"type":"Point"}
}