{
  "type": "Feature",
  "properties": {
    "gn:admin1_code":"28.0",
    "gn:admin2_code":"1446.0",
    "gn:asciiname":"Skacka",
    "gn:country_code":"SE",
    "gn:dem":95,
    "gn:feature_class":"P",
    "gn:feature_code":"PPL",
    "gn:name":"Skacka",
    "gn:population":0,
    "gn:timezone":"Europe/Stockholm",
    "iso:country":"SE",
    "name:und_x_variant":[
        "Skacken",
        "Skacka"
    ],
    "wof:name":"Skacka",
    "wof:placetype":"locality"
},
  "geometry": {"coordinates":[14.46299,58.5421],"type":"Point"}
}