{
  "type": "Feature",
  "properties": {
    "gn:admin1_code":"26.0",
    "gn:asciiname":"Alsunda",
    "gn:country_code":"SE",
    "gn:dem":20,
    "gn:feature_class":"P",
    "gn:feature_code":"PPL",
    "gn:name":"\u00c5lsunda",
    "gn:population":0,
    "gn:timezone":"Europe/Stockholm",
    "iso:country":"SE",
    "wof:name":"Alsunda",
    "wof:placetype":"locality"
},
  "geometry": {"coordinates":[18.16667,60.03333000000001],"type":"Point"}
}