{
  "type": "Feature",
  "properties": {
    "gn:admin1_code":"2.0",
    "gn:admin2_code":"1081.0",
    "gn:asciiname":"Orseryd",
    "gn:country_code":"SE",
    "gn:dem":62,
    "gn:feature_class":"P",
    "gn:feature_code":"PPL",
    "gn:name":"\u00d6rseryd",
    "gn:population":0,
    "gn:timezone":"Europe/Stockholm",
    "iso:country":"SE",
    "name:nor_x_preferred":[
        "\u00d6rseryd"
    ],
    "name:nor_x_variant":[
        "\u00d8rseryd"
    ],
    "wof:name":"Orseryd",
    "wof:placetype":"locality"
},
  "geometry": {"coordinates":[15.06667,56.33333],"type":"Point"}
}