{
  "type": "Feature",
  "properties": {
    "gn:admin1_code":"15.0",
    "gn:admin2_code":"1863.0",
    "gn:asciiname":"Limmingen",
    "gn:country_code":"SE",
    "gn:dem":250,
    "gn:feature_class":"P",
    "gn:feature_code":"PPL",
    "gn:name":"Limmingen",
    "gn:population":0,
    "gn:timezone":"Europe/Stockholm",
    "iso:country":"SE",
    "wof:name":"Limmingen",
    "wof:placetype":"locality"
},
  "geometry": {"coordinates":[14.53333,59.58333],"type":"Point"}
}