{
  "type": "Feature",
  "properties": {
    "gn:admin1_code":"3.0",
    "gn:asciiname":"Trollharen",
    "gn:country_code":"SE",
    "gn:dem":1,
    "gn:feature_class":"P",
    "gn:feature_code":"PPL",
    "gn:name":"Trollharen",
    "gn:population":0,
    "gn:timezone":"Europe/Stockholm",
    "iso:country":"SE",
    "wof:name":"Trollharen",
    "wof:placetype":"locality"
},
  "geometry": {"coordinates":[17.20194,61.09056],"type":"Point"}
}