{
  "type": "Feature",
  "properties": {
    "gn:admin1_code":"22.0",
    "gn:admin2_code":"1780.0",
    "gn:asciiname":"Bregarden",
    "gn:cc2":"SE",
    "gn:country_code":"SE",
    "gn:dem":107,
    "gn:feature_class":"P",
    "gn:feature_code":"PPL",
    "gn:name":"Breg\u00e5rden",
    "gn:population":0,
    "gn:timezone":"Europe/Stockholm",
    "iso:country":"SE",
    "name:und_x_variant":[
        "Bredg\u00e5rden",
        "Breg\u00e5rden"
    ],
    "wof:name":"Bregarden",
    "wof:placetype":"locality"
},
  "geometry": {"coordinates":[13.75,59.46666999999999],"type":"Point"}
}