{
  "type": "Feature",
  "properties": {
    "gn:admin1_code":"15.0",
    "gn:admin2_code":"1864.0",
    "gn:asciiname":"Sundet",
    "gn:country_code":"SE",
    "gn:dem":185,
    "gn:feature_class":"P",
    "gn:feature_code":"PPL",
    "gn:name":"Sundet",
    "gn:population":0,
    "gn:timezone":"Europe/Stockholm",
    "iso:country":"SE",
    "name:nor_x_preferred":[
        "Sundet"
    ],
    "wof:name":"Sundet",
    "wof:placetype":"locality"
},
  "geometry": {"coordinates":[14.95,59.91667],"type":"Point"}
}