{
  "type": "Feature",
  "properties": {
    "gn:admin1_code":"7.0",
    "gn:admin2_code":"2380.0",
    "gn:asciiname":"Holmarna",
    "gn:cc2":"SE",
    "gn:country_code":"SE",
    "gn:dem":334,
    "gn:feature_class":"P",
    "gn:feature_code":"PPL",
    "gn:name":"Holmarna",
    "gn:population":0,
    "gn:timezone":"Europe/Stockholm",
    "iso:country":"SE",
    "name:und_x_variant":[
        "Homarna",
        "Holmarna"
    ],
    "wof:name":"Holmarna",
    "wof:placetype":"locality"
},
  "geometry": {"coordinates":[14.85,63.01667],"type":"Point"}
}