{
  "type": "Feature",
  "properties": {
    "gn:admin1_code":"12.0",
    "gn:admin2_code":"760.0",
    "gn:asciiname":"Stodsboda",
    "gn:country_code":"SE",
    "gn:dem":201,
    "gn:feature_class":"P",
    "gn:feature_code":"PPL",
    "gn:name":"St\u00f6dsboda",
    "gn:population":0,
    "gn:timezone":"Europe/Stockholm",
    "iso:country":"SE",
    "name:nor_x_preferred":[
        "St\u00f6dsboda"
    ],
    "name:nor_x_variant":[
        "St\u00f8dsboda"
    ],
    "name:und_x_variant":[
        "St\u00f6dsboda"
    ],
    "wof:name":"Stodsboda",
    "wof:placetype":"locality"
},
  "geometry": {"coordinates":[15.55,57.13333000000001],"type":"Point"}
}