{
  "type": "Feature",
  "properties": {
    "gn:admin1_code":"28.0",
    "gn:admin2_code":"1498.0",
    "gn:asciiname":"Bosarp",
    "gn:country_code":"SE",
    "gn:dem":210,
    "gn:feature_class":"P",
    "gn:feature_code":"PPL",
    "gn:name":"Bosarp",
    "gn:population":0,
    "gn:timezone":"Europe/Stockholm",
    "iso:country":"SE",
    "wof:name":"Bosarp",
    "wof:placetype":"locality"
},
  "geometry": {"coordinates":[13.86667,58.05],"type":"Point"}
}