{
  "type": "Feature",
  "properties": {
    "gn:gn_country":"SE",
    "gn:gn_fcode":"PPL",
    "gn:gn_pop":306,
    "gn:population":249,
    "iso:country":"SE",
    "name:bul_x_preferred":[
        "\u041f\u0435\u0440\u0441\u0431\u0435\u0440\u0433"
    ],
    "name:deu_x_preferred":[
        "Persberg"
    ],
    "name:eng_x_preferred":[
        "Persberg"
    ],
    "name:nan_x_preferred":[
        "Persberg"
    ],
    "name:nld_x_preferred":[
        "Persberg"
    ],
    "name:nno_x_preferred":[
        "Persberg"
    ],
    "name:nob_x_preferred":[
        "Persberg"
    ],
    "name:swe_x_preferred":[
        "Persberg"
    ],
    "qs_pg:aaroncc":"SE",
    "qs_pg:gn_country":"SE",
    "qs_pg:gn_fcode":"PPL",
    "qs_pg:gn_pop":306,
    "qs_pg:name":"Persberg",
    "qs_pg:name_adm0":"Sverige",
    "qs_pg:name_adm1":"V\u00e4rmlands L\u00e4n",
    "qs_pg:photos":8,
    "qs_pg:photos_1k":2,
    "qs_pg:photos_9k":1,
    "qs_pg:photos_9r":1,
    "qs_pg:photos_all":8,
    "qs_pg:photos_sr":1,
    "qs_pg:pop_sr":2,
    "qs_pg:qs_pg_placetype":"locality",
    "qs_pg:qs_pg_placetype_gp":"Town",
    "qs_pg:woe_adm0":23424954,
    "woe:adm0_id":23424954,
    "woe:name_adm0":"Sverige",
    "woe:name_adm1":"V\u00e4rmlands L\u00e4n",
    "woe:placetype":"Town",
    "wof:name":"Persberg",
    "wof:placetype":"locality",
    "wof:population":249
},
  "geometry": {"coordinates":[14.25,59.75],"type":"Point"}
}