{
  "type": "Feature",
  "properties": {
    "gn:admin1_code":"28.0",
    "gn:admin2_code":"1444.0",
    "gn:asciiname":"Astorp",
    "gn:country_code":"SE",
    "gn:dem":52,
    "gn:feature_class":"P",
    "gn:feature_code":"PPL",
    "gn:name":"\u00c5storp",
    "gn:population":0,
    "gn:timezone":"Europe/Stockholm",
    "iso:country":"SE",
    "wof:name":"Astorp",
    "wof:placetype":"locality"
},
  "geometry": {"coordinates":[12.63333,58.36666999999999],"type":"Point"}
}