{
  "type": "Feature",
  "properties": {
    "gn:country":"SE",
    "gn:fcode":"PPL",
    "gn:population":0,
    "iso:country":"SE",
    "name:dan_x_preferred":[
        "Str\u00f6mma"
    ],
    "name:deu_x_preferred":[
        "Str\u00f6mma"
    ],
    "name:eng_x_preferred":[
        "Str\u00f6mma"
    ],
    "name:fra_x_preferred":[
        "Str\u00f6mma"
    ],
    "name:ita_x_preferred":[
        "Str\u00f6mma"
    ],
    "name:nan_x_preferred":[
        "Str\u00f6mma"
    ],
    "name:nds_x_preferred":[
        "Str\u00f6mma"
    ],
    "name:nld_x_preferred":[
        "Str\u00f6mma"
    ],
    "name:nno_x_preferred":[
        "Str\u00f6mma"
    ],
    "name:nob_x_preferred":[
        "Str\u00f6mma"
    ],
    "name:nor_x_preferred":[
        "Str\u00f8mma"
    ],
    "name:nor_x_variant":[
        "Str\u00f6mma"
    ],
    "name:swe_x_preferred":[
        "Str\u00f6mma"
    ],
    "qs_pg:aaroncc":"SE",
    "qs_pg:gn_country":"SE",
    "qs_pg:gn_fcode":"PPL",
    "qs_pg:gn_pop":0,
    "qs_pg:name":"Str\u00f6mma",
    "qs_pg:name_adm0":"Sverige",
    "qs_pg:name_adm1":"Stockholms L\u00e4n",
    "qs_pg:photos":48,
    "qs_pg:photos_1k":10,
    "qs_pg:photos_9k":1,
    "qs_pg:photos_9r":2,
    "qs_pg:photos_all":48,
    "qs_pg:photos_sr":2,
    "qs_pg:pop_sr":0,
    "qs_pg:qs_pg_placetype":"locality",
    "qs_pg:qs_pg_placetype_gp":"Town",
    "qs_pg:woe_adm0":23424954,
    "woe:adm0_id":23424954,
    "woe:name_adm0":"Sverige",
    "woe:name_adm1":"Stockholms L\u00e4n",
    "woe:placetype":"Town",
    "wof:name":"Str\u00f6mma",
    "wof:placetype":"locality",
    "wof:population":2468
},
  "geometry": {"coordinates":[18.53333,59.28333],"type":"Point"}
}