{
  "type": "Feature",
  "properties": {
    "gn:country":"SE",
    "gn:fcode":"PPL",
    "gn:population":25,
    "iso:country":"SE",
    "name:und_x_variant":[
        "Raltindor"
    ],
    "qs_pg:aaroncc":"SE",
    "qs_pg:gn_country":"SE",
    "qs_pg:gn_fcode":"PPL",
    "qs_pg:gn_pop":25,
    "qs_pg:name":"R\u00e4ltlindor",
    "qs_pg:photos_9r":0,
    "qs_pg:photos_sr":0,
    "qs_pg:pop_sr":1,
    "qs_pg:qs_pg_placetype":"locality",
    "wof:name":"R\u00e4ltlindor",
    "wof:placetype":"locality",
    "wof:population":25
},
  "geometry": {"coordinates":[14.97908,60.65078],"type":"Point"}
}