{
  "type": "Feature",
  "properties": {
    "gn:admin1_code":"14.0",
    "gn:admin2_code":"2521.0",
    "gn:asciiname":"Antinrova",
    "gn:country_code":"SE",
    "gn:dem":177,
    "gn:feature_class":"P",
    "gn:feature_code":"PPL",
    "gn:name":"Antinrova",
    "gn:population":0,
    "gn:timezone":"Europe/Stockholm",
    "iso:country":"SE",
    "wof:name":"Antinrova",
    "wof:placetype":"locality"
},
  "geometry": {"coordinates":[22.75,67.25],"type":"Point"}
}