{
  "type": "Feature",
  "properties": {
    "gn:admin1_code":"25.0",
    "gn:admin2_code":"1962.0",
    "gn:asciiname":"Olsbenning",
    "gn:country_code":"SE",
    "gn:dem":106,
    "gn:feature_class":"P",
    "gn:feature_code":"PPL",
    "gn:name":"Olsbenning",
    "gn:population":0,
    "gn:timezone":"Europe/Stockholm",
    "iso:country":"SE",
    "wof:name":"Olsbenning",
    "wof:placetype":"locality"
},
  "geometry": {"coordinates":[16.08333,60.06667],"type":"Point"}
}