{
  "type": "Feature",
  "properties": {
    "iso:country":"SE",
    "name:swe_x_preferred":[
        "Stensjohojd"
    ],
    "qs:gn_adm0_cc":"SE",
    "qs:gn_local":2691459,
    "qs:gn_nam_loc":"M\u00f6lndal, M\u00f6lndal, V\u00e4stra G\u00f6talands L\u00e4n, SE",
    "qs:gn_namadm1":"28",
    "qs:local_max":1511,
    "qs:local_sum":2950,
    "qs:localhoods":6,
    "qs:name":"Stensjohojd",
    "qs:name_adm0":"Sverige",
    "qs:name_adm1":"V\u00e4stra G\u00f6talands L\u00e4n",
    "qs:name_adm2":"M\u00f6lndal",
    "qs:name_local":"M\u00f6lndal",
    "qs:photo_max":104,
    "qs:photo_sum":640,
    "qs:placetype":"Suburb",
    "qs:quad_count":40,
    "qs:woe_adm0":23424954,
    "qs:woe_adm1":20070562,
    "qs:woe_adm2":12587237,
    "qs:woe_lau":0,
    "qs:woe_local":898653,
    "qs:woe_ver":"7.10.0",
    "wof:lang":[
        "swe"
    ],
    "wof:name":"Stensjohojd",
    "wof:placetype":"neighbourhood"
},
  "geometry": {"coordinates":[12.03977,57.659024],"type":"Point"}
}