{
  "type": "Feature",
  "properties": {
    "gn:admin1_code":"7.0",
    "gn:admin2_code":"2361.0",
    "gn:asciiname":"Ovre Harjastugan",
    "gn:country_code":"SE",
    "gn:dem":560,
    "gn:feature_class":"P",
    "gn:feature_code":"PPL",
    "gn:name":"\u00d6vre H\u00e4rj\u00e5stugan",
    "gn:population":0,
    "gn:timezone":"Europe/Stockholm",
    "iso:country":"SE",
    "wof:name":"Ovre Harjastugan",
    "wof:placetype":"locality"
},
  "geometry": {"coordinates":[13.71667,61.79971999999999],"type":"Point"}
}