{
  "type": "Feature",
  "properties": {
    "gn:admin1_code":"28.0",
    "gn:admin2_code":"1460.0",
    "gn:asciiname":"Narsbyn",
    "gn:cc2":"SE",
    "gn:country_code":"SE",
    "gn:dem":76,
    "gn:feature_class":"P",
    "gn:feature_code":"PPL",
    "gn:name":"N\u00e4rsbyn",
    "gn:population":0,
    "gn:timezone":"Europe/Stockholm",
    "iso:country":"SE",
    "name:und_x_variant":[
        "N\u00e4resbyn",
        "N\u00e4rsbyn"
    ],
    "wof:name":"Narsbyn",
    "wof:placetype":"locality"
},
  "geometry": {"coordinates":[12.31667,59.03333000000001],"type":"Point"}
}