{
  "type": "Feature",
  "properties": {
    "gn:admin1_code":"15.0",
    "gn:admin2_code":"1884.0",
    "gn:asciiname":"Bastnas",
    "gn:country_code":"SE",
    "gn:dem":130,
    "gn:feature_class":"P",
    "gn:feature_code":"PPL",
    "gn:name":"Bastn\u00e4s",
    "gn:population":0,
    "gn:timezone":"Europe/Stockholm",
    "iso:country":"SE",
    "wof:name":"Bastnas",
    "wof:placetype":"locality"
},
  "geometry": {"coordinates":[14.93333,59.51667],"type":"Point"}
}