{
  "type": "Feature",
  "properties": {
    "gn:admin1_code":"28.0",
    "gn:admin2_code":"1489.0",
    "gn:asciiname":"Torpet",
    "gn:country_code":"SE",
    "gn:dem":58,
    "gn:feature_class":"P",
    "gn:feature_code":"PPL",
    "gn:name":"Torpet",
    "gn:population":0,
    "gn:timezone":"Europe/Stockholm",
    "iso:country":"SE",
    "wof:name":"Torpet",
    "wof:placetype":"locality"
},
  "geometry": {"coordinates":[12.41667,57.96666999999999],"type":"Point"}
}