{
  "type": "Feature",
  "properties": {
    "gn:admin1_code":"24.0",
    "gn:admin2_code":"2280.0",
    "gn:asciiname":"Ostby",
    "gn:country_code":"SE",
    "gn:dem":1,
    "gn:feature_class":"P",
    "gn:feature_code":"PPL",
    "gn:name":"\u00d6stby",
    "gn:population":0,
    "gn:timezone":"Europe/Stockholm",
    "iso:country":"SE",
    "name:nor_x_preferred":[
        "\u00d6stby"
    ],
    "name:nor_x_variant":[
        "\u00d8stby"
    ],
    "name:und_x_variant":[
        "\u00d6stby"
    ],
    "wof:name":"Ostby",
    "wof:placetype":"locality"
},
  "geometry": {"coordinates":[17.85,62.83333],"type":"Point"}
}