{
  "type": "Feature",
  "properties": {
    "gn:admin1_code":"27.0",
    "gn:admin2_code":"1278.0",
    "gn:asciiname":"Varan",
    "gn:country_code":"SE",
    "gn:dem":49,
    "gn:feature_class":"P",
    "gn:feature_code":"PPL",
    "gn:name":"Varan",
    "gn:population":0,
    "gn:timezone":"Europe/Stockholm",
    "iso:country":"SE",
    "wof:name":"Varan",
    "wof:placetype":"locality"
},
  "geometry": {"coordinates":[12.66667,56.43333000000001],"type":"Point"}
}