{
  "type": "Feature",
  "properties": {
    "gn:admin1_code":"28.0",
    "gn:asciiname":"Yttre Storshult",
    "gn:country_code":"SE",
    "gn:dem":159,
    "gn:feature_class":"P",
    "gn:feature_code":"PPL",
    "gn:name":"Yttre St\u00f6rshult",
    "gn:population":0,
    "gn:timezone":"Europe/Stockholm",
    "iso:country":"SE",
    "name:nor_x_preferred":[
        "Yttre St\u00f6rshult"
    ],
    "name:nor_x_variant":[
        "Yttre St\u00f8rshult"
    ],
    "name:und_x_variant":[
        "Yttre St\u00f6rshult"
    ],
    "wof:name":"Yttre Storshult",
    "wof:placetype":"locality"
},
  "geometry": {"coordinates":[12.98333,57.01667],"type":"Point"}
}