{
  "type": "Feature",
  "properties": {
    "gn:admin1_code":"12.0",
    "gn:admin2_code":"780.0",
    "gn:asciiname":"Ostra Malajord",
    "gn:cc2":"SE",
    "gn:country_code":"SE",
    "gn:dem":191,
    "gn:feature_class":"P",
    "gn:feature_code":"PPL",
    "gn:name":"\u00d6stra M\u00e5lajord",
    "gn:population":0,
    "gn:timezone":"Europe/Stockholm",
    "iso:country":"SE",
    "name:nor_x_preferred":[
        "\u00d6stra M\u00e5lajord"
    ],
    "name:nor_x_variant":[
        "\u00d8stra M\u00e5lajord"
    ],
    "name:und_x_variant":[
        "M\u00e5lajord"
    ],
    "wof:name":"Ostra Malajord",
    "wof:placetype":"locality"
},
  "geometry": {"coordinates":[14.96667,57.03333000000001],"type":"Point"}
}