{
  "type": "Feature",
  "properties": {
    "gn:admin1_code":"23.0",
    "gn:admin2_code":"2480.0",
    "gn:asciiname":"Aheden",
    "gn:country_code":"SE",
    "gn:dem":5,
    "gn:feature_class":"P",
    "gn:feature_code":"PPL",
    "gn:name":"\u00c5heden",
    "gn:population":0,
    "gn:timezone":"Europe/Stockholm",
    "iso:country":"SE",
    "name:swe_x_preferred":[
        "\u00c5heden"
    ],
    "wof:name":"Aheden",
    "wof:placetype":"locality"
},
  "geometry": {"coordinates":[20.05,63.68333000000001],"type":"Point"}
}