{
  "type": "Feature",
  "properties": {
    "gn:admin1_code":"9.0",
    "gn:admin2_code":"884.0",
    "gn:asciiname":"Backhult",
    "gn:country_code":"SE",
    "gn:dem":211,
    "gn:feature_class":"P",
    "gn:feature_code":"PPL",
    "gn:name":"B\u00e4ckhult",
    "gn:population":0,
    "gn:timezone":"Europe/Stockholm",
    "iso:country":"SE",
    "wof:name":"Backhult",
    "wof:placetype":"locality"
},
  "geometry": {"coordinates":[15.68333,57.76667],"type":"Point"}
}