{
  "type": "Feature",
  "properties": {
    "gn:admin1_code":"10.0",
    "gn:admin2_code":"2061.0",
    "gn:asciiname":"Silvhyttan",
    "gn:cc2":"SE",
    "gn:country_code":"SE",
    "gn:dem":138,
    "gn:feature_class":"P",
    "gn:feature_code":"PPL",
    "gn:name":"Silvhyttan",
    "gn:population":0,
    "gn:timezone":"Europe/Stockholm",
    "iso:country":"SE",
    "name:und_x_variant":[
        "Silfhyttan",
        "Silvhyttan"
    ],
    "wof:name":"Silvhyttan",
    "wof:placetype":"locality"
},
  "geometry": {"coordinates":[15.28333,60.18333000000001],"type":"Point"}
}