{
  "type": "Feature",
  "properties": {
    "gn:admin1_code":"26",
    "gn:admin2_code":"191.0",
    "gn:admin3_code":"19106.0",
    "gn:admin4_code":"32.0",
    "gn:asciiname":"Arlanda",
    "gn:country_code":"SE",
    "gn:dem":42,
    "gn:feature_class":"P",
    "gn:feature_code":"PPL",
    "gn:name":"Arlanda",
    "gn:population":0,
    "gn:timezone":"Europe/Stockholm",
    "iso:country":"SE",
    "wof:name":"Arlanda",
    "wof:placetype":"locality"
},
  "geometry": {"coordinates":[17.92999,59.64897],"type":"Point"}
}