{
  "type": "Feature",
  "properties": {
    "gn:admin1_code":"14.0",
    "gn:admin2_code":"2523.0",
    "gn:asciiname":"Hornberg",
    "gn:cc2":"SE",
    "gn:country_code":"SE",
    "gn:dem":267,
    "gn:feature_class":"P",
    "gn:feature_code":"PPL",
    "gn:name":"Hornberg",
    "gn:population":0,
    "gn:timezone":"Europe/Stockholm",
    "iso:country":"SE",
    "name:und_x_variant":[
        "Tj\u00e5rvek",
        "Hornberg"
    ],
    "wof:name":"Hornberg",
    "wof:placetype":"locality"
},
  "geometry": {"coordinates":[21.31667,66.41667],"type":"Point"}
}