{
  "type": "Feature",
  "properties": {
    "gn:admin1_code":"22.0",
    "gn:admin2_code":"1762.0",
    "gn:asciiname":"Tjarne",
    "gn:country_code":"SE",
    "gn:dem":89,
    "gn:feature_class":"P",
    "gn:feature_code":"PPL",
    "gn:name":"Tj\u00e4rne",
    "gn:population":0,
    "gn:timezone":"Europe/Stockholm",
    "iso:country":"SE",
    "wof:name":"Tjarne",
    "wof:placetype":"locality"
},
  "geometry": {"coordinates":[13.48306,59.78306],"type":"Point"}
}