{
  "type": "Feature",
  "properties": {
    "gn:admin1_code":"7.0",
    "gn:admin2_code":"2361.0",
    "gn:asciiname":"Stradalen",
    "gn:cc2":"SE",
    "gn:country_code":"SE",
    "gn:dem":700,
    "gn:feature_class":"P",
    "gn:feature_code":"PPL",
    "gn:name":"Str\u00e5dalen",
    "gn:population":0,
    "gn:timezone":"Europe/Stockholm",
    "iso:country":"SE",
    "name:und_x_variant":[
        "Str\u00e5dalsstugan",
        "Str\u00e5dalen"
    ],
    "wof:name":"Stradalen",
    "wof:placetype":"locality"
},
  "geometry": {"coordinates":[13.15,62.13333000000001],"type":"Point"}
}