{
  "type": "Feature",
  "properties": {
    "gn:admin1_code":"10.0",
    "gn:admin2_code":"2061.0",
    "gn:asciiname":"Geratjarn",
    "gn:country_code":"SE",
    "gn:dem":252,
    "gn:feature_class":"P",
    "gn:feature_code":"PPL",
    "gn:name":"Ger\u00e5tj\u00e4rn",
    "gn:population":0,
    "gn:timezone":"Europe/Stockholm",
    "iso:country":"SE",
    "wof:name":"Geratjarn",
    "wof:placetype":"locality"
},
  "geometry": {"coordinates":[15.53333,59.96666999999999],"type":"Point"}
}