{
  "type": "Feature",
  "properties": {
    "gn:admin1_code":"3.0",
    "gn:admin2_code":"2161.0",
    "gn:asciiname":"Gartsbo",
    "gn:country_code":"SE",
    "gn:dem":192,
    "gn:feature_class":"P",
    "gn:feature_code":"PPL",
    "gn:name":"Gartsbo",
    "gn:population":0,
    "gn:timezone":"Europe/Stockholm",
    "iso:country":"SE",
    "wof:name":"Gartsbo",
    "wof:placetype":"locality"
},
  "geometry": {"coordinates":[16.23333,61.75],"type":"Point"}
}