{
  "type": "Feature",
  "properties": {
    "gn:admin1_code":"27.0",
    "gn:admin2_code":"1276.0",
    "gn:asciiname":"Vastra Forestad",
    "gn:country_code":"SE",
    "gn:dem":49,
    "gn:feature_class":"P",
    "gn:feature_code":"PPL",
    "gn:name":"V\u00e4stra Forestad",
    "gn:population":0,
    "gn:timezone":"Europe/Stockholm",
    "iso:country":"SE",
    "wof:name":"Vastra Forestad",
    "wof:placetype":"locality"
},
  "geometry": {"coordinates":[13.33333,56.03333000000001],"type":"Point"}
}