{
  "type": "Feature",
  "properties": {
    "gn:admin1_code":"8.0",
    "gn:admin2_code":"686.0",
    "gn:asciiname":"Bjorka",
    "gn:country_code":"SE",
    "gn:dem":256,
    "gn:feature_class":"P",
    "gn:feature_code":"PPL",
    "gn:name":"Bj\u00f6rka",
    "gn:population":0,
    "gn:timezone":"Europe/Stockholm",
    "iso:country":"SE",
    "name:nor_x_preferred":[
        "Bj\u00f6rka"
    ],
    "name:nor_x_variant":[
        "Bj\u00f8rka"
    ],
    "wof:name":"Bjorka",
    "wof:placetype":"locality"
},
  "geometry": {"coordinates":[15.01667,57.65],"type":"Point"}
}