{
  "type": "Feature",
  "properties": {
    "gn:admin1_code":"21.0",
    "gn:admin2_code":"381.0",
    "gn:asciiname":"Lundby",
    "gn:country_code":"SE",
    "gn:dem":38,
    "gn:feature_class":"P",
    "gn:feature_code":"PPL",
    "gn:name":"Lundby",
    "gn:population":0,
    "gn:timezone":"Europe/Stockholm",
    "iso:country":"SE",
    "wof:name":"Lundby",
    "wof:placetype":"locality"
},
  "geometry": {"coordinates":[16.93333,59.66667],"type":"Point"}
}