{
  "type": "Feature",
  "properties": {
    "gn:admin1_code":"15.0",
    "gn:admin2_code":"1885.0",
    "gn:asciiname":"Fornabohyttan",
    "gn:cc2":"SE",
    "gn:country_code":"SE",
    "gn:dem":208,
    "gn:feature_class":"P",
    "gn:feature_code":"PPL",
    "gn:name":"Fornabohyttan",
    "gn:population":0,
    "gn:timezone":"Europe/Stockholm",
    "iso:country":"SE",
    "name:und_x_variant":[
        "Fornbohyttan",
        "Fornebohyttan",
        "Fornabohyttan"
    ],
    "wof:name":"Fornabohyttan",
    "wof:placetype":"locality"
},
  "geometry": {"coordinates":[15.13333,59.63333000000001],"type":"Point"}
}