{
  "type": "Feature",
  "properties": {
    "gn:admin1_code":"8.0",
    "gn:admin2_code":"685.0",
    "gn:asciiname":"Magebo",
    "gn:country_code":"SE",
    "gn:dem":233,
    "gn:feature_class":"P",
    "gn:feature_code":"PPL",
    "gn:name":"M\u00e5gebo",
    "gn:population":0,
    "gn:timezone":"Europe/Stockholm",
    "iso:country":"SE",
    "wof:name":"Magebo",
    "wof:placetype":"locality"
},
  "geometry": {"coordinates":[15.06667,57.31667],"type":"Point"}
}