{
  "type": "Feature",
  "properties": {
    "gn:admin1_code":"26.0",
    "gn:admin2_code":"117.0",
    "gn:asciiname":"Undal",
    "gn:country_code":"SE",
    "gn:dem":44,
    "gn:feature_class":"P",
    "gn:feature_code":"PPL",
    "gn:name":"Undal",
    "gn:population":0,
    "gn:timezone":"Europe/Stockholm",
    "iso:country":"SE",
    "wof:name":"Undal",
    "wof:placetype":"locality"
},
  "geometry": {"coordinates":[18.43333,59.55],"type":"Point"}
}