{
  "type": "Feature",
  "properties": {
    "gn:admin1_code":"7.0",
    "gn:admin2_code":"2326.0",
    "gn:asciiname":"Vikbacken",
    "gn:cc2":"SE",
    "gn:country_code":"SE",
    "gn:dem":330,
    "gn:feature_class":"P",
    "gn:feature_code":"PPL",
    "gn:name":"Vikb\u00e4cken",
    "gn:population":0,
    "gn:timezone":"Europe/Stockholm",
    "iso:country":"SE",
    "name:und_x_variant":[
        "Vilb\u00e4cken",
        "Vikb\u00e4cken"
    ],
    "wof:name":"Vikbacken",
    "wof:placetype":"locality"
},
  "geometry": {"coordinates":[14.53333,62.86666999999999],"type":"Point"}
}