{
  "type": "Feature",
  "properties": {
    "gn:gn_country":"SE",
    "iso:country":"SE",
    "qs_pg:aaroncc":"SE",
    "qs_pg:gn_country":"SE",
    "qs_pg:name":"\u00d6rsundstorpet",
    "qs_pg:name_adm0":"Sverige",
    "qs_pg:name_adm1":"Stockholms L\u00e4n",
    "qs_pg:photos":87,
    "qs_pg:photos_1k":18,
    "qs_pg:photos_9k":1,
    "qs_pg:photos_9r":3,
    "qs_pg:photos_all":87,
    "qs_pg:photos_sr":3,
    "qs_pg:pop_sr":0,
    "qs_pg:qs_pg_placetype":"locality",
    "qs_pg:qs_pg_placetype_gp":"Town",
    "qs_pg:woe_adm0":23424954,
    "woe:adm0_id":23424954,
    "woe:name_adm0":"Sverige",
    "woe:name_adm1":"Stockholms L\u00e4n",
    "woe:placetype":"Town",
    "wof:name":"\u00d6rsundstorpet",
    "wof:placetype":"locality"
},
  "geometry": {"coordinates":[18.630366,59.256053],"type":"Point"}
}