{
  "type": "Feature",
  "properties": {
    "gn:admin1_code":"22.0",
    "gn:admin2_code":"1766.0",
    "gn:asciiname":"Backen",
    "gn:country_code":"SE",
    "gn:dem":81,
    "gn:feature_class":"P",
    "gn:feature_code":"PPL",
    "gn:name":"B\u00e4cken",
    "gn:population":0,
    "gn:timezone":"Europe/Stockholm",
    "iso:country":"SE",
    "wof:name":"Backen",
    "wof:placetype":"locality"
},
  "geometry": {"coordinates":[13.15,59.95],"type":"Point"}
}