{
  "type": "Feature",
  "properties": {
    "gn:admin1_code":"9.0",
    "gn:admin2_code":"881.0",
    "gn:asciiname":"Stora Kolfly",
    "gn:country_code":"SE",
    "gn:dem":155,
    "gn:feature_class":"P",
    "gn:feature_code":"PPL",
    "gn:name":"Stora Kolfly",
    "gn:population":0,
    "gn:timezone":"Europe/Stockholm",
    "iso:country":"SE",
    "wof:name":"Stora Kolfly",
    "wof:placetype":"locality"
},
  "geometry": {"coordinates":[15.71667,56.66667],"type":"Point"}
}