{
  "type": "Feature",
  "properties": {
    "gn:country":"SE",
    "gn:fcode":"PPL",
    "gn:population":0,
    "iso:country":"SE",
    "name:dan_x_preferred":[
        "V\u00e4stermyrriset"
    ],
    "name:eng_x_preferred":[
        "V\u00e4stermyrriset"
    ],
    "name:fra_x_preferred":[
        "V\u00e4stermyrriset"
    ],
    "name:nld_x_preferred":[
        "V\u00e4stermyrriset"
    ],
    "name:nob_x_preferred":[
        "V\u00e4stermyrriset"
    ],
    "name:swe_x_preferred":[
        "V\u00e4stermyrriset"
    ],
    "qs_pg:aaroncc":"SE",
    "qs_pg:gn_country":"SE",
    "qs_pg:gn_fcode":"PPL",
    "qs_pg:gn_pop":0,
    "qs_pg:name":"V\u00e4stermyrriset",
    "qs_pg:name_adm0":"Sverige",
    "qs_pg:name_adm1":"V\u00e4sterbottens L\u00e4n",
    "qs_pg:photos":113,
    "qs_pg:photos_1k":23,
    "qs_pg:photos_9k":1,
    "qs_pg:photos_9r":3,
    "qs_pg:photos_all":113,
    "qs_pg:photos_sr":3,
    "qs_pg:pop_sr":0,
    "qs_pg:qs_pg_placetype":"locality",
    "qs_pg:qs_pg_placetype_gp":"Town",
    "qs_pg:woe_adm0":23424954,
    "woe:adm0_id":23424954,
    "woe:name_adm0":"Sverige",
    "woe:name_adm1":"V\u00e4sterbottens L\u00e4n",
    "woe:placetype":"Town",
    "wof:name":"V\u00e4stermyrriset",
    "wof:placetype":"locality"
},
  "geometry": {"coordinates":[17.98333,64.40000000000001],"type":"Point"}
}