{
  "type": "Feature",
  "properties": {
    "gn:admin1_code":"6.0",
    "gn:asciiname":"Stavershult",
    "gn:country_code":"SE",
    "gn:dem":175,
    "gn:feature_class":"P",
    "gn:feature_code":"PPL",
    "gn:name":"Stavershult",
    "gn:population":0,
    "gn:timezone":"Europe/Stockholm",
    "iso:country":"SE",
    "wof:name":"Stavershult",
    "wof:placetype":"locality"
},
  "geometry": {"coordinates":[13.15,56.33333],"type":"Point"}
}