{
  "type": "Feature",
  "properties": {
    "gn:admin1_code":"8.0",
    "gn:admin2_code":"683.0",
    "gn:asciiname":"Hjalmsanga",
    "gn:country_code":"SE",
    "gn:dem":198,
    "gn:feature_class":"P",
    "gn:feature_code":"PPL",
    "gn:name":"Hj\u00e4lms\u00e4nga",
    "gn:population":0,
    "gn:timezone":"Europe/Stockholm",
    "iso:country":"SE",
    "wof:name":"Hjalmsanga",
    "wof:placetype":"locality"
},
  "geometry": {"coordinates":[14.21667,56.96666999999999],"type":"Point"}
}