{
  "type": "Feature",
  "properties": {
    "gn:admin1_code":"9.0",
    "gn:admin2_code":"885.0",
    "gn:asciiname":"Ovra Sandby",
    "gn:cc2":"SE",
    "gn:country_code":"SE",
    "gn:dem":13,
    "gn:feature_class":"P",
    "gn:feature_code":"PPL",
    "gn:name":"\u00d6vra Sandby",
    "gn:population":0,
    "gn:timezone":"Europe/Stockholm",
    "iso:country":"SE",
    "name:nor_x_preferred":[
        "\u00d6vra Sandby"
    ],
    "name:nor_x_variant":[
        "\u00d8vra Sandby"
    ],
    "name:und_x_variant":[
        "Sandby",
        "\u00d6vra Sandby"
    ],
    "wof:name":"Ovra Sandby",
    "wof:placetype":"locality"
},
  "geometry": {"coordinates":[16.76667,56.83333],"type":"Point"}
}