{
  "type": "Feature",
  "properties": {
    "gn:admin1_code":"14.0",
    "gn:admin2_code":"2521.0",
    "gn:asciiname":"Narken",
    "gn:country_code":"SE",
    "gn:dem":101,
    "gn:feature_class":"P",
    "gn:feature_code":"PPL",
    "gn:name":"Narken",
    "gn:population":0,
    "gn:timezone":"Europe/Stockholm",
    "iso:country":"SE",
    "wof:name":"Narken",
    "wof:placetype":"locality"
},
  "geometry": {"coordinates":[22.75,66.93333],"type":"Point"}
}