{
  "type": "Feature",
  "properties": {
    "gn:admin1_code":"22.0",
    "gn:admin2_code":"1765.0",
    "gn:asciiname":"Tvardalen",
    "gn:country_code":"SE",
    "gn:dem":191,
    "gn:feature_class":"P",
    "gn:feature_code":"PPL",
    "gn:name":"Tv\u00e4rdalen",
    "gn:population":0,
    "gn:timezone":"Europe/Stockholm",
    "iso:country":"SE",
    "wof:name":"Tvardalen",
    "wof:placetype":"locality"
},
  "geometry": {"coordinates":[12.08333,59.43333000000001],"type":"Point"}
}