{
  "type": "Feature",
  "properties": {
    "gn:admin1_code":"28.0",
    "gn:admin2_code":"1492.0",
    "gn:asciiname":"Jakobsbyn",
    "gn:country_code":"SE",
    "gn:dem":93,
    "gn:feature_class":"P",
    "gn:feature_code":"PPL",
    "gn:name":"Jakobsbyn",
    "gn:population":0,
    "gn:timezone":"Europe/Stockholm",
    "iso:country":"SE",
    "wof:name":"Jakobsbyn",
    "wof:placetype":"locality"
},
  "geometry": {"coordinates":[12.61667,59.03333000000001],"type":"Point"}
}