{
  "type": "Feature",
  "properties": {
    "gn:admin1_code":"9.0",
    "gn:admin2_code":"840.0",
    "gn:admin3_code":"84008.0",
    "gn:admin4_code":"809.0",
    "gn:asciiname":"Ossby",
    "gn:country_code":"SE",
    "gn:dem":6,
    "gn:feature_class":"P",
    "gn:feature_code":"PPL",
    "gn:name":"\u00d6ssby",
    "gn:population":0,
    "gn:timezone":"Europe/Stockholm",
    "iso:country":"SE",
    "name:nor_x_preferred":[
        "\u00d6ssby"
    ],
    "name:nor_x_variant":[
        "\u00d8ssby"
    ],
    "name:und_x_variant":[
        "\u00d6ssby"
    ],
    "wof:name":"Ossby",
    "wof:placetype":"locality"
},
  "geometry": {"coordinates":[16.49421,56.27701],"type":"Point"}
}