{
  "type": "Feature",
  "properties": {
    "gn:admin1_code":"3.0",
    "gn:admin2_code":"2184.0",
    "gn:asciiname":"Brannas",
    "gn:country_code":"SE",
    "gn:dem":137,
    "gn:feature_class":"P",
    "gn:feature_code":"PPL",
    "gn:name":"Br\u00e4nn\u00e5s",
    "gn:population":0,
    "gn:timezone":"Europe/Stockholm",
    "iso:country":"SE",
    "wof:name":"Brannas",
    "wof:placetype":"locality"
},
  "geometry": {"coordinates":[16.25,62.05],"type":"Point"}
}