{
  "type": "Feature",
  "properties": {
    "gn:admin1_code":"28.0",
    "gn:admin2_code":"1494.0",
    "gn:asciiname":"Hasslosa",
    "gn:country_code":"SE",
    "gn:dem":84,
    "gn:feature_class":"P",
    "gn:feature_code":"PPL",
    "gn:name":"Hassl\u00f6sa",
    "gn:population":0,
    "gn:timezone":"Europe/Stockholm",
    "iso:country":"SE",
    "name:nor_x_preferred":[
        "Hassl\u00f6sa"
    ],
    "name:nor_x_variant":[
        "Hassl\u00f8sa"
    ],
    "name:und_x_variant":[
        "Hassl\u00f6sa"
    ],
    "wof:name":"Hasslosa",
    "wof:placetype":"locality"
},
  "geometry": {"coordinates":[13.26667,58.41667],"type":"Point"}
}