{
  "type": "Feature",
  "properties": {
    "gn:admin1_code":"12.0",
    "gn:admin2_code":"760.0",
    "gn:asciiname":"Almedal",
    "gn:country_code":"SE",
    "gn:dem":282,
    "gn:feature_class":"P",
    "gn:feature_code":"PPL",
    "gn:name":"\u00c4lmedal",
    "gn:population":0,
    "gn:timezone":"Europe/Stockholm",
    "iso:country":"SE",
    "wof:name":"Almedal",
    "wof:placetype":"locality"
},
  "geometry": {"coordinates":[15.26667,57.16667],"type":"Point"}
}