{
  "type": "Feature",
  "properties": {
    "gn:admin1_code":"24.0",
    "gn:admin2_code":"2281.0",
    "gn:admin3_code":"228110.0",
    "gn:admin4_code":"2481.0",
    "gn:asciiname":"Holmen",
    "gn:country_code":"SE",
    "gn:dem":1,
    "gn:feature_class":"P",
    "gn:feature_code":"PPL",
    "gn:name":"Holmen",
    "gn:population":0,
    "gn:timezone":"Europe/Stockholm",
    "iso:country":"SE",
    "name:ceb_x_preferred":[
        "Holmen"
    ],
    "name:dan_x_preferred":[
        "Holmen"
    ],
    "name:deu_x_preferred":[
        "Holmen"
    ],
    "name:est_x_preferred":[
        "Holmen"
    ],
    "name:fra_x_preferred":[
        "Holmen"
    ],
    "name:nld_x_preferred":[
        "Holmen"
    ],
    "name:nor_x_preferred":[
        "Holmen"
    ],
    "name:swe_x_preferred":[
        "Holmen"
    ],
    "wof:name":"Holmen",
    "wof:placetype":"locality"
},
  "geometry": {"coordinates":[17.55139,62.23111],"type":"Point"}
}