{
  "type": "Feature",
  "properties": {
    "gn:admin1_code":"28.0",
    "gn:admin2_code":"1471.0",
    "gn:asciiname":"Bernstorp",
    "gn:country_code":"SE",
    "gn:dem":59,
    "gn:feature_class":"P",
    "gn:feature_code":"PPL",
    "gn:name":"Bernstorp",
    "gn:population":0,
    "gn:timezone":"Europe/Stockholm",
    "iso:country":"SE",
    "wof:name":"Bernstorp",
    "wof:placetype":"locality"
},
  "geometry": {"coordinates":[13.56667,58.66667],"type":"Point"}
}