{
  "type": "Feature",
  "properties": {
    "gn:admin1_code":"8.0",
    "gn:admin2_code":"604.0",
    "gn:asciiname":"Hestra",
    "gn:country_code":"SE",
    "gn:dem":286,
    "gn:feature_class":"P",
    "gn:feature_code":"PPL",
    "gn:name":"Hestra",
    "gn:population":1326,
    "gn:timezone":"Europe/Stockholm",
    "iso:country":"SE",
    "name:swe_x_preferred":[
        "Hestra-Handsken"
    ],
    "wof:name":"Hestra",
    "wof:placetype":"locality",
    "wof:population":1326
},
  "geometry": {"coordinates":[14.58333,57.91667],"type":"Point"}
}