{
  "type": "Feature",
  "properties": {
    "iso:country":"SE",
    "name:dan_x_preferred":[
        "K\u00e4rrmar\u00e4ng"
    ],
    "name:eng_x_preferred":[
        "K\u00e4rrmar\u00e4ng"
    ],
    "name:fre_x_preferred":[
        "K\u00e4rrmar\u00e4ng"
    ],
    "name:ger_x_preferred":[
        "K\u00e4rrmar\u00e4ng"
    ],
    "name:nds_x_preferred":[
        "K\u00e4rrmar\u00e4ng"
    ],
    "name:nno_x_preferred":[
        "K\u00e4rrmar\u00e4ng"
    ],
    "name:nob_x_preferred":[
        "K\u00e4rrmar\u00e4ng"
    ],
    "name:swe_x_preferred":[
        "K\u00e4rrmar\u00e4ng"
    ],
    "qs_pg:aaroncc":"SE",
    "qs_pg:name":"K\u00e4rrmar\u00e4ng",
    "qs_pg:name_adm0":"Sverige",
    "qs_pg:name_adm1":"Stockholms L\u00e4n",
    "qs_pg:photos":220,
    "qs_pg:photos_1k":45,
    "qs_pg:photos_9k":1,
    "qs_pg:photos_9r":4,
    "qs_pg:photos_all":220,
    "qs_pg:photos_sr":4,
    "qs_pg:pop_sr":0,
    "qs_pg:qs_pg_placetype":"locality",
    "qs_pg:qs_pg_placetype_gp":"Town",
    "qs_pg:woe_adm0":23424954,
    "woe:adm0_id":23424954,
    "woe:name_adm0":"Sverige",
    "woe:name_adm1":"Stockholms L\u00e4n",
    "woe:placetype":"Town",
    "wof:name":"K\u00e4rrmar\u00e4ng",
    "wof:placetype":"locality"
},
  "geometry": {"coordinates":[18.2647485,59.105551],"type":"Point"}
}