{
  "type": "Feature",
  "properties": {
    "gn:admin1_code":"28.0",
    "gn:admin2_code":"1482.0",
    "gn:asciiname":"Ulvesund",
    "gn:country_code":"SE",
    "gn:dem":46,
    "gn:feature_class":"P",
    "gn:feature_code":"PPL",
    "gn:name":"Ulvesund",
    "gn:population":0,
    "gn:timezone":"Europe/Stockholm",
    "iso:country":"SE",
    "wof:name":"Ulvesund",
    "wof:placetype":"locality"
},
  "geometry": {"coordinates":[11.88333,57.83333],"type":"Point"}
}