{
  "type": "Feature",
  "properties": {
    "gn:admin1_code":"24.0",
    "gn:admin2_code":"2284.0",
    "gn:asciiname":"Sorbyn",
    "gn:country_code":"SE",
    "gn:dem":50,
    "gn:feature_class":"P",
    "gn:feature_code":"PPL",
    "gn:name":"S\u00f6rbyn",
    "gn:population":0,
    "gn:timezone":"Europe/Stockholm",
    "iso:country":"SE",
    "name:nor_x_preferred":[
        "S\u00f6rbyn"
    ],
    "name:nor_x_variant":[
        "S\u00f8rbyn"
    ],
    "name:und_x_variant":[
        "S\u00f6rbyn"
    ],
    "wof:name":"Sorbyn",
    "wof:placetype":"locality"
},
  "geometry": {"coordinates":[18.63333,63.03333000000001],"type":"Point"}
}