{
  "type": "Feature",
  "properties": {
    "gn:admin1_code":"21.0",
    "gn:admin2_code":"360.0",
    "gn:asciiname":"Lonno",
    "gn:country_code":"SE",
    "gn:dem":14,
    "gn:feature_class":"P",
    "gn:feature_code":"PPL",
    "gn:name":"L\u00f6nn\u00f6",
    "gn:population":0,
    "gn:timezone":"Europe/Stockholm",
    "iso:country":"SE",
    "name:nor_x_preferred":[
        "L\u00f6nn\u00f6"
    ],
    "name:nor_x_variant":[
        "L\u00f8nn\u00f8"
    ],
    "name:und_x_variant":[
        "L\u00f6nn\u00f6"
    ],
    "wof:name":"Lonno",
    "wof:placetype":"locality"
},
  "geometry": {"coordinates":[17.85,60.53333000000001],"type":"Point"}
}