{
  "type": "Feature",
  "properties": {
    "gn:country":"SE",
    "gn:fcode":"PPL",
    "gn:population":201,
    "iso:country":"SE",
    "name:ceb_x_preferred":[
        "Bergs\u00e4ng"
    ],
    "name:dan_x_preferred":[
        "Bergs\u00e4ng"
    ],
    "name:deu_x_preferred":[
        "Bergs\u00e4ng"
    ],
    "name:eng_x_preferred":[
        "Bergs\u00e4ng"
    ],
    "name:fra_x_preferred":[
        "Bergs\u00e4ng"
    ],
    "name:gle_x_preferred":[
        "Bergs\u00e4ng"
    ],
    "name:ita_x_preferred":[
        "Bergs\u00e4ng"
    ],
    "name:lld_x_preferred":[
        "Bergs\u00e4ng"
    ],
    "name:nds_x_preferred":[
        "Bergs\u00e4ng"
    ],
    "name:nld_x_preferred":[
        "Bergs\u00e4ng"
    ],
    "name:nno_x_preferred":[
        "Bergs\u00e4ng"
    ],
    "name:nob_x_preferred":[
        "Bergs\u00e4ng"
    ],
    "name:swe_x_preferred":[
        "Bergs\u00e4ng"
    ],
    "qs_pg:aaroncc":"SE",
    "qs_pg:gn_country":"SE",
    "qs_pg:gn_fcode":"PPL",
    "qs_pg:gn_pop":201,
    "qs_pg:name":"Bergs\u00e4ng",
    "qs_pg:name_adm0":"Sverige",
    "qs_pg:name_adm1":"V\u00e4rmlands L\u00e4n",
    "qs_pg:photos_9k":1,
    "qs_pg:photos_9r":3,
    "qs_pg:photos_all":86,
    "qs_pg:photos_sr":0,
    "qs_pg:pop_sr":2,
    "qs_pg:qs_pg_placetype":"locality",
    "qs_pg:qs_pg_placetype_gp":"Town",
    "qs_pg:woe_adm0":23424954,
    "woe:adm0_id":23424954,
    "woe:name_adm0":"Sverige",
    "woe:name_adm1":"V\u00e4rmlands L\u00e4n",
    "woe:placetype":"Town",
    "wof:name":"Bergs\u00e4ng",
    "wof:placetype":"locality",
    "wof:population":203
},
  "geometry": {"coordinates":[13.55,60.13333],"type":"Point"}
}