{
  "type": "Feature",
  "properties": {
    "gn:country":"SE",
    "gn:fcode":"PPL",
    "gn:population":719,
    "iso:country":"SE",
    "name:ara_x_preferred":[
        "\u0641\u0627\u0644\u0633\u0643\u0648\u063a"
    ],
    "name:bul_x_preferred":[
        "\u0412\u0430\u043b\u0441\u043a\u043e\u0433"
    ],
    "name:ceb_x_preferred":[
        "Valskog"
    ],
    "name:deu_x_preferred":[
        "Valskog"
    ],
    "name:eng_x_preferred":[
        "Valskog"
    ],
    "name:ita_x_preferred":[
        "Valskog"
    ],
    "name:nan_x_preferred":[
        "Valskog"
    ],
    "name:nld_x_preferred":[
        "Valskog"
    ],
    "name:nno_x_preferred":[
        "Valskog"
    ],
    "name:nob_x_preferred":[
        "Valskog"
    ],
    "name:swe_x_preferred":[
        "Valskog"
    ],
    "qs_pg:aaroncc":"SE",
    "qs_pg:gn_country":"SE",
    "qs_pg:gn_fcode":"PPL",
    "qs_pg:gn_pop":719,
    "qs_pg:name":"Valskog",
    "qs_pg:name_adm0":"Sverige",
    "qs_pg:name_adm1":"V\u00e4stmanlands L\u00e4n",
    "qs_pg:photos":44,
    "qs_pg:photos_1k":9,
    "qs_pg:photos_9k":1,
    "qs_pg:photos_9r":2,
    "qs_pg:photos_all":44,
    "qs_pg:photos_sr":2,
    "qs_pg:pop_sr":2,
    "qs_pg:qs_pg_placetype":"locality",
    "qs_pg:qs_pg_placetype_gp":"Town",
    "qs_pg:woe_adm0":23424954,
    "woe:adm0_id":23424954,
    "woe:name_adm0":"Sverige",
    "woe:name_adm1":"V\u00e4stmanlands L\u00e4n",
    "woe:placetype":"Town",
    "wof:name":"Valskog",
    "wof:placetype":"locality",
    "wof:population":693
},
  "geometry": {"coordinates":[15.95,59.45],"type":"Point"}
}