{
  "type": "Feature",
  "properties": {
    "gn:admin1_code":"22.0",
    "gn:admin2_code":"1730.0",
    "gn:asciiname":"Langelanda",
    "gn:cc2":"SE",
    "gn:country_code":"SE",
    "gn:dem":125,
    "gn:feature_class":"P",
    "gn:feature_code":"PPL",
    "gn:name":"L\u00e5ngelanda",
    "gn:population":0,
    "gn:timezone":"Europe/Stockholm",
    "iso:country":"SE",
    "name:und_x_variant":[
        "L\u00e5nglanda",
        "L\u00e5ngelanda"
    ],
    "wof:name":"Langelanda",
    "wof:placetype":"locality"
},
  "geometry": {"coordinates":[12.25,59.85],"type":"Point"}
}