{
  "type": "Feature",
  "properties": {
    "gn:admin1_code":"23.0",
    "gn:admin2_code":"2422.0",
    "gn:asciiname":"Risnas",
    "gn:country_code":"SE",
    "gn:dem":353,
    "gn:feature_class":"P",
    "gn:feature_code":"PPL",
    "gn:name":"Risn\u00e4s",
    "gn:population":0,
    "gn:timezone":"Europe/Stockholm",
    "iso:country":"SE",
    "name:swe_x_preferred":[
        "Risn\u00e4s"
    ],
    "wof:name":"Risnas",
    "wof:placetype":"locality"
},
  "geometry": {"coordinates":[17.31439,65.68723],"type":"Point"}
}