{
  "type": "Feature",
  "properties": {
    "gn:admin1_code":"15.0",
    "gn:admin2_code":"1880.0",
    "gn:asciiname":"Svensboda",
    "gn:country_code":"SE",
    "gn:dem":180,
    "gn:feature_class":"P",
    "gn:feature_code":"PPL",
    "gn:name":"Svensboda",
    "gn:population":0,
    "gn:timezone":"Europe/Stockholm",
    "iso:country":"SE",
    "wof:name":"Svensboda",
    "wof:placetype":"locality"
},
  "geometry": {"coordinates":[14.88333,59.28333000000001],"type":"Point"}
}