{
  "type": "Feature",
  "properties": {
    "gn:admin1_code":"27.0",
    "gn:admin2_code":"1266.0",
    "gn:asciiname":"Slagtofta",
    "gn:country_code":"SE",
    "gn:dem":120,
    "gn:feature_class":"P",
    "gn:feature_code":"PPL",
    "gn:name":"Slagtofta",
    "gn:population":0,
    "gn:timezone":"Europe/Stockholm",
    "iso:country":"SE",
    "wof:name":"Slagtofta",
    "wof:placetype":"locality"
},
  "geometry": {"coordinates":[13.66667,55.86666999999999],"type":"Point"}
}