{
  "type": "Feature",
  "properties": {
    "gn:admin1_code":"23.0",
    "gn:admin2_code":"2463.0",
    "gn:asciiname":"Sandsjo",
    "gn:country_code":"SE",
    "gn:dem":441,
    "gn:feature_class":"P",
    "gn:feature_code":"PPL",
    "gn:name":"Sandsj\u00f6",
    "gn:population":0,
    "gn:timezone":"Europe/Stockholm",
    "iso:country":"SE",
    "name:nor_x_preferred":[
        "Sandsj\u00f6"
    ],
    "name:nor_x_variant":[
        "Sandsj\u00f8"
    ],
    "wof:name":"Sandsjo",
    "wof:placetype":"locality"
},
  "geometry": {"coordinates":[17.75,64.45],"type":"Point"}
}