{
  "type": "Feature",
  "properties": {
    "gn:admin1_code":"23.0",
    "gn:admin2_code":"2462.0",
    "gn:asciiname":"Strandkullen",
    "gn:country_code":"SE",
    "gn:dem":480,
    "gn:feature_class":"P",
    "gn:feature_code":"PPL",
    "gn:name":"Strandkullen",
    "gn:population":0,
    "gn:timezone":"Europe/Stockholm",
    "iso:country":"SE",
    "wof:name":"Strandkullen",
    "wof:placetype":"locality"
},
  "geometry": {"coordinates":[17.05,64.76666999999999],"type":"Point"}
}