{
  "type": "Feature",
  "properties": {
    "gn:admin1_code":"26.0",
    "gn:admin2_code":"127.0",
    "gn:asciiname":"Tuna",
    "gn:country_code":"SE",
    "gn:dem":37,
    "gn:feature_class":"P",
    "gn:feature_code":"PPL",
    "gn:name":"Tuna",
    "gn:population":0,
    "gn:timezone":"Europe/Stockholm",
    "iso:country":"SE",
    "wof:name":"Tuna",
    "wof:placetype":"locality"
},
  "geometry": {"coordinates":[17.83333,59.21666999999999],"type":"Point"}
}