{
  "type": "Feature",
  "properties": {
    "gn:admin1_code":"10.0",
    "gn:asciiname":"Algsjobo",
    "gn:cc2":"SE",
    "gn:country_code":"SE",
    "gn:dem":145,
    "gn:feature_class":"P",
    "gn:feature_code":"PPL",
    "gn:name":"\u00c4lgsj\u00f6bo",
    "gn:population":0,
    "gn:timezone":"Europe/Stockholm",
    "iso:country":"SE",
    "name:und_x_variant":[
        "Elgsj\u00f6bo",
        "\u00c4lgsj\u00f6bo"
    ],
    "wof:name":"Algsjobo",
    "wof:placetype":"locality"
},
  "geometry": {"coordinates":[15.69826,60.06463000000001],"type":"Point"}
}