{
  "type": "Feature",
  "properties": {
    "gn:admin1_code":"28.0",
    "gn:admin2_code":"1427.0",
    "gn:asciiname":"Grosshamn",
    "gn:country_code":"SE",
    "gn:dem":20,
    "gn:feature_class":"P",
    "gn:feature_code":"PPL",
    "gn:name":"Grosshamn",
    "gn:population":0,
    "gn:timezone":"Europe/Stockholm",
    "iso:country":"SE",
    "wof:name":"Grosshamn",
    "wof:placetype":"locality"
},
  "geometry": {"coordinates":[11.25,58.42916999999999],"type":"Point"}
}