{
  "type": "Feature",
  "properties": {
    "gn:admin1_code":"9.0",
    "gn:admin2_code":"883.0",
    "gn:asciiname":"Dynestad",
    "gn:country_code":"SE",
    "gn:dem":78,
    "gn:feature_class":"P",
    "gn:feature_code":"PPL",
    "gn:name":"Dynestad",
    "gn:population":0,
    "gn:timezone":"Europe/Stockholm",
    "iso:country":"SE",
    "wof:name":"Dynestad",
    "wof:placetype":"locality"
},
  "geometry": {"coordinates":[16.28333,57.71666999999999],"type":"Point"}
}