{
  "type": "Feature",
  "properties": {
    "gn:gn_country":"SE",
    "gn:gn_fcode":"PPL",
    "gn:gn_pop":0,
    "iso:country":"SE",
    "name:dan_x_preferred":[
        "Sillre"
    ],
    "name:deu_x_preferred":[
        "Sillre"
    ],
    "name:eng_x_preferred":[
        "Sillre"
    ],
    "name:fra_x_preferred":[
        "Sillre"
    ],
    "name:nds_x_preferred":[
        "Sillre"
    ],
    "name:nld_x_preferred":[
        "Sillre"
    ],
    "name:nno_x_preferred":[
        "Sillre"
    ],
    "name:nob_x_preferred":[
        "Sillre"
    ],
    "name:swe_x_preferred":[
        "Sillre"
    ],
    "qs_pg:aaroncc":"SE",
    "qs_pg:gn_country":"SE",
    "qs_pg:gn_fcode":"PPL",
    "qs_pg:gn_pop":0,
    "qs_pg:name":"Sillre",
    "qs_pg:name_adm0":"Sverige",
    "qs_pg:name_adm1":"V\u00e4sternorrlands L\u00e4n",
    "qs_pg:photos":9,
    "qs_pg:photos_1k":2,
    "qs_pg:photos_9k":1,
    "qs_pg:photos_9r":1,
    "qs_pg:photos_all":9,
    "qs_pg:photos_sr":1,
    "qs_pg:pop_sr":4,
    "qs_pg:qs_pg_placetype":"locality",
    "qs_pg:qs_pg_placetype_gp":"Town",
    "qs_pg:woe_adm0":23424954,
    "woe:adm0_id":23424954,
    "woe:name_adm0":"Sverige",
    "woe:name_adm1":"V\u00e4sternorrlands L\u00e4n",
    "woe:placetype":"Town",
    "wof:name":"Sillre",
    "wof:placetype":"locality"
},
  "geometry": {"coordinates":[16.71667,62.76667],"type":"Point"}
}