{
  "type": "Feature",
  "properties": {
    "gn:admin1_code":"8.0",
    "gn:admin2_code":"683.0",
    "gn:asciiname":"Boestad",
    "gn:country_code":"SE",
    "gn:dem":248,
    "gn:feature_class":"P",
    "gn:feature_code":"PPL",
    "gn:name":"Boestad",
    "gn:population":0,
    "gn:timezone":"Europe/Stockholm",
    "iso:country":"SE",
    "wof:name":"Boestad",
    "wof:placetype":"locality"
},
  "geometry": {"coordinates":[14.36667,57.33333],"type":"Point"}
}