{
  "type": "Feature",
  "properties": {
    "gn:admin1_code":"24.0",
    "gn:admin2_code":"2284.0",
    "gn:asciiname":"Nordana",
    "gn:country_code":"SE",
    "gn:dem":140,
    "gn:feature_class":"P",
    "gn:feature_code":"PPL",
    "gn:name":"Nordan\u00e5",
    "gn:population":0,
    "gn:timezone":"Europe/Stockholm",
    "iso:country":"SE",
    "wof:name":"Nordana",
    "wof:placetype":"locality"
},
  "geometry": {"coordinates":[17.85,63.38333000000001],"type":"Point"}
}