{
  "type": "Feature",
  "properties": {
    "gn:admin1_code":"23.0",
    "gn:admin2_code":"2463.0",
    "gn:asciiname":"Oster-Storsjo",
    "gn:country_code":"SE",
    "gn:dem":429,
    "gn:feature_class":"P",
    "gn:feature_code":"PPL",
    "gn:name":"\u00d6ster-Storsj\u00f6",
    "gn:population":0,
    "gn:timezone":"Europe/Stockholm",
    "iso:country":"SE",
    "name:nor_x_preferred":[
        "\u00d6ster-Storsj\u00f6"
    ],
    "name:nor_x_variant":[
        "\u00d8ster-Storsj\u00f8"
    ],
    "name:und_x_variant":[
        "\u00d6ster-Storsj\u00f6"
    ],
    "wof:name":"Oster-Storsjo",
    "wof:placetype":"locality"
},
  "geometry": {"coordinates":[17.68332999999999,64.13333],"type":"Point"}
}