{
  "type": "Feature",
  "properties": {
    "gn:admin1_code":"23.0",
    "gn:admin2_code":"2421.0",
    "gn:asciiname":"Norra Fjallnas",
    "gn:cc2":"SE",
    "gn:country_code":"SE",
    "gn:dem":469,
    "gn:feature_class":"P",
    "gn:feature_code":"PPL",
    "gn:name":"Norra Fj\u00e4lln\u00e4s",
    "gn:population":0,
    "gn:timezone":"Europe/Stockholm",
    "iso:country":"SE",
    "name:und_x_variant":[
        "Oltoken",
        "Norra Fj\u00e4lin\u00e4s",
        "N\u00f6rre Fj\u00e4lln\u00e4s",
        "Norra Fj\u00e4lln\u00e4s"
    ],
    "wof:name":"Norra Fjallnas",
    "wof:placetype":"locality"
},
  "geometry": {"coordinates":[15.46667,65.75],"type":"Point"}
}