{
  "type": "Feature",
  "properties": {
    "gn:admin1_code":"8.0",
    "gn:admin2_code":"683.0",
    "gn:asciiname":"Tagel",
    "gn:country_code":"SE",
    "gn:dem":178,
    "gn:feature_class":"P",
    "gn:feature_code":"PPL",
    "gn:name":"Tagel",
    "gn:population":0,
    "gn:timezone":"Europe/Stockholm",
    "iso:country":"SE",
    "wof:name":"Tagel",
    "wof:placetype":"locality"
},
  "geometry": {"coordinates":[14.16667,57.13333000000001],"type":"Point"}
}