{
  "type": "Feature",
  "properties": {
    "gn:admin1_code":"10.0",
    "gn:admin2_code":"2081.0",
    "gn:asciiname":"Pusselbo",
    "gn:country_code":"SE",
    "gn:dem":152,
    "gn:feature_class":"P",
    "gn:feature_code":"PPL",
    "gn:name":"Pusselbo",
    "gn:population":0,
    "gn:timezone":"Europe/Stockholm",
    "iso:country":"SE",
    "wof:name":"Pusselbo",
    "wof:placetype":"locality"
},
  "geometry": {"coordinates":[15.33333,60.51667],"type":"Point"}
}