{
  "type": "Feature",
  "properties": {
    "gn:gn_country":"SE",
    "gn:gn_fcode":"PPL",
    "gn:gn_pop":539,
    "gn:population":593,
    "iso:country":"SE",
    "name:eng_x_preferred":[
        "Slaka"
    ],
    "name:ita_x_preferred":[
        "Slaka"
    ],
    "name:nan_x_preferred":[
        "Slaka"
    ],
    "name:nld_x_preferred":[
        "Slaka"
    ],
    "name:nno_x_preferred":[
        "Slaka"
    ],
    "name:nob_x_preferred":[
        "Slaka"
    ],
    "name:swe_x_preferred":[
        "Slaka"
    ],
    "qs_pg:aaroncc":"SE",
    "qs_pg:gn_country":"SE",
    "qs_pg:gn_fcode":"PPL",
    "qs_pg:gn_pop":539,
    "qs_pg:name":"Slaka",
    "qs_pg:name_adm0":"Sverige",
    "qs_pg:name_adm1":"\u00d6sterg\u00f6tlands L\u00e4n",
    "qs_pg:photos":127,
    "qs_pg:photos_1k":26,
    "qs_pg:photos_9k":1,
    "qs_pg:photos_9r":3,
    "qs_pg:photos_all":127,
    "qs_pg:photos_sr":3,
    "qs_pg:pop_sr":2,
    "qs_pg:qs_pg_placetype":"locality",
    "qs_pg:qs_pg_placetype_gp":"Town",
    "qs_pg:woe_adm0":23424954,
    "woe:adm0_id":23424954,
    "woe:name_adm0":"Sverige",
    "woe:name_adm1":"\u00d6sterg\u00f6tlands L\u00e4n",
    "woe:placetype":"Town",
    "wof:name":"Slaka",
    "wof:placetype":"locality",
    "wof:population":593
},
  "geometry": {"coordinates":[15.55,58.36667],"type":"Point"}
}