{
  "type": "Feature",
  "properties": {
    "gn:admin1_code":"28.0",
    "gn:admin2_code":"1482.0",
    "gn:asciiname":"Haltorp",
    "gn:cc2":"SE",
    "gn:country_code":"SE",
    "gn:dem":53,
    "gn:feature_class":"P",
    "gn:feature_code":"PPL",
    "gn:name":"H\u00e4ltorp",
    "gn:population":0,
    "gn:timezone":"Europe/Stockholm",
    "iso:country":"SE",
    "name:und_x_variant":[
        "H\u00e4lltorp",
        "H\u00e4ltorp"
    ],
    "wof:name":"Haltorp",
    "wof:placetype":"locality"
},
  "geometry": {"coordinates":[11.86667,57.85],"type":"Point"}
}