{
  "type": "Feature",
  "properties": {
    "gn:admin1_code":"14.0",
    "gn:admin2_code":"2523.0",
    "gn:asciiname":"Storberget",
    "gn:country_code":"SE",
    "gn:dem":300,
    "gn:feature_class":"P",
    "gn:feature_code":"PPL",
    "gn:name":"Storberget",
    "gn:population":0,
    "gn:timezone":"Europe/Stockholm",
    "iso:country":"SE",
    "wof:name":"Storberget",
    "wof:placetype":"locality"
},
  "geometry": {"coordinates":[21.75,66.76666999999999],"type":"Point"}
}