{
  "type": "Feature",
  "properties": {
    "gn:admin1_code":"9.0",
    "gn:admin2_code":"860.0",
    "gn:asciiname":"Kangsebo",
    "gn:country_code":"SE",
    "gn:dem":146,
    "gn:feature_class":"P",
    "gn:feature_code":"PPL",
    "gn:name":"K\u00e4ngsebo",
    "gn:population":0,
    "gn:timezone":"Europe/Stockholm",
    "iso:country":"SE",
    "wof:name":"Kangsebo",
    "wof:placetype":"locality"
},
  "geometry": {"coordinates":[15.75,57.21666999999999],"type":"Point"}
}