{
  "type": "Feature",
  "properties": {
    "gn:admin1_code":"28.0",
    "gn:admin2_code":"1462.0",
    "gn:asciiname":"Hogen",
    "gn:country_code":"SE",
    "gn:dem":117,
    "gn:feature_class":"P",
    "gn:feature_code":"PPL",
    "gn:name":"H\u00f6gen",
    "gn:population":0,
    "gn:timezone":"Europe/Stockholm",
    "iso:country":"SE",
    "name:nor_x_preferred":[
        "H\u00f6gen"
    ],
    "name:nor_x_variant":[
        "H\u00f8gen"
    ],
    "wof:name":"Hogen",
    "wof:placetype":"locality"
},
  "geometry": {"coordinates":[12.01667,58.15],"type":"Point"}
}