{
  "type": "Feature",
  "properties": {
    "gn:admin1_code":"23.0",
    "gn:admin2_code":"2421.0",
    "gn:asciiname":"Norrheden",
    "gn:country_code":"SE",
    "gn:dem":438,
    "gn:feature_class":"P",
    "gn:feature_code":"PPL",
    "gn:name":"Norrheden",
    "gn:population":0,
    "gn:timezone":"Europe/Stockholm",
    "iso:country":"SE",
    "wof:name":"Norrheden",
    "wof:placetype":"locality"
},
  "geometry": {"coordinates":[17.03333,64.90000000000001],"type":"Point"}
}