{
  "type": "Feature",
  "properties": {
    "gn:admin1_code":"27.0",
    "gn:admin2_code":"1290.0",
    "gn:asciiname":"Gronhult",
    "gn:country_code":"SE",
    "gn:dem":103,
    "gn:feature_class":"P",
    "gn:feature_code":"PPL",
    "gn:name":"Gr\u00f6nhult",
    "gn:population":0,
    "gn:timezone":"Europe/Stockholm",
    "iso:country":"SE",
    "name:nor_x_preferred":[
        "Gr\u00f6nhult"
    ],
    "name:nor_x_variant":[
        "Gr\u00f8nhult"
    ],
    "wof:name":"Gronhult",
    "wof:placetype":"locality"
},
  "geometry": {"coordinates":[14.38333,56.23333],"type":"Point"}
}