{
  "type": "Feature",
  "properties": {
    "gn:admin1_code":"24.0",
    "gn:admin2_code":"2284.0",
    "gn:asciiname":"Djupsjo",
    "gn:country_code":"SE",
    "gn:dem":131,
    "gn:feature_class":"P",
    "gn:feature_code":"PPL",
    "gn:name":"Djupsj\u00f6",
    "gn:population":0,
    "gn:timezone":"Europe/Stockholm",
    "iso:country":"SE",
    "name:nor_x_preferred":[
        "Djupsj\u00f6"
    ],
    "name:nor_x_variant":[
        "Djupsj\u00f8"
    ],
    "wof:name":"Djupsjo",
    "wof:placetype":"locality"
},
  "geometry": {"coordinates":[18.01667,63.33333],"type":"Point"}
}