{
  "type": "Feature",
  "properties": {
    "gn:gn_country":"SE",
    "gn:gn_fcode":"PPL",
    "gn:gn_pop":0,
    "iso:country":"SE",
    "name:dan_x_preferred":[
        "Mariedamm"
    ],
    "name:deu_x_preferred":[
        "Mariedamm"
    ],
    "name:eng_x_preferred":[
        "Mariedamm"
    ],
    "name:fra_x_preferred":[
        "Mariedamm"
    ],
    "name:nds_x_preferred":[
        "Mariedamm"
    ],
    "name:nld_x_preferred":[
        "Mariedamm"
    ],
    "name:nno_x_preferred":[
        "Mariedamm"
    ],
    "name:nob_x_preferred":[
        "Mariedamm"
    ],
    "name:swe_x_preferred":[
        "Mariedamm"
    ],
    "name:unk_x_variant":[
        "Mariedam"
    ],
    "qs_pg:aaroncc":"SE",
    "qs_pg:gn_country":"SE",
    "qs_pg:gn_fcode":"PPL",
    "qs_pg:gn_pop":0,
    "qs_pg:name":"Mariedamm",
    "qs_pg:name_adm0":"Sverige",
    "qs_pg:name_adm1":"\u00d6rebro L\u00e4n",
    "qs_pg:photos":2,
    "qs_pg:photos_1k":1,
    "qs_pg:photos_9k":1,
    "qs_pg:photos_9r":1,
    "qs_pg:photos_all":2,
    "qs_pg:photos_sr":1,
    "qs_pg:pop_sr":0,
    "qs_pg:qs_pg_placetype":"locality",
    "qs_pg:qs_pg_placetype_gp":"Town",
    "qs_pg:woe_adm0":23424954,
    "woe:adm0_id":23424954,
    "woe:name_adm0":"Sverige",
    "woe:name_adm1":"\u00d6rebro L\u00e4n",
    "woe:placetype":"Town",
    "wof:name":"Mariedamm",
    "wof:placetype":"locality"
},
  "geometry": {"coordinates":[15.15,58.85],"type":"Point"}
}