{
  "type": "Feature",
  "properties": {
    "gn:admin1_code":"24.0",
    "gn:admin2_code":"2280.0",
    "gn:admin3_code":"228003.0",
    "gn:admin4_code":"2469.0",
    "gn:asciiname":"Lindom",
    "gn:country_code":"SE",
    "gn:dem":53,
    "gn:feature_class":"P",
    "gn:feature_code":"PPL",
    "gn:name":"Lindom",
    "gn:population":0,
    "gn:timezone":"Europe/Stockholm",
    "iso:country":"SE",
    "wof:name":"Lindom",
    "wof:placetype":"locality"
},
  "geometry": {"coordinates":[17.81667000000001,62.55],"type":"Point"}
}