{
  "type": "Feature",
  "properties": {
    "gn:admin1_code":"9.0",
    "gn:admin2_code":"883.0",
    "gn:asciiname":"Stora Spanga",
    "gn:country_code":"SE",
    "gn:dem":55,
    "gn:feature_class":"P",
    "gn:feature_code":"PPL",
    "gn:name":"Stora Sp\u00e5nga",
    "gn:population":0,
    "gn:timezone":"Europe/Stockholm",
    "iso:country":"SE",
    "wof:name":"Stora Spanga",
    "wof:placetype":"locality"
},
  "geometry": {"coordinates":[16.26667,57.81667],"type":"Point"}
}