{
  "type": "Feature",
  "properties": {
    "gn:admin1_code":"10.0",
    "gn:admin2_code":"2061.0",
    "gn:asciiname":"Stimmerbo",
    "gn:country_code":"SE",
    "gn:dem":115,
    "gn:feature_class":"P",
    "gn:feature_code":"PPL",
    "gn:name":"Stimmerbo",
    "gn:population":0,
    "gn:timezone":"Europe/Stockholm",
    "iso:country":"SE",
    "wof:name":"Stimmerbo",
    "wof:placetype":"locality"
},
  "geometry": {"coordinates":[15.51667,60.16667],"type":"Point"}
}