{
  "type": "Feature",
  "properties": {
    "gn:admin1_code":"3.0",
    "gn:admin2_code":"2132.0",
    "gn:asciiname":"Rosta",
    "gn:country_code":"SE",
    "gn:dem":16,
    "gn:feature_class":"P",
    "gn:feature_code":"PPL",
    "gn:name":"R\u00f6sta",
    "gn:population":0,
    "gn:timezone":"Europe/Stockholm",
    "iso:country":"SE",
    "name:ita_x_preferred":[
        "Rosta"
    ],
    "name:nor_x_preferred":[
        "R\u00f6sta"
    ],
    "name:nor_x_variant":[
        "R\u00f8sta"
    ],
    "wof:name":"Rosta",
    "wof:placetype":"locality"
},
  "geometry": {"coordinates":[17.20871,61.93213000000001],"type":"Point"}
}