{
  "type": "Feature",
  "properties": {
    "gn:admin1_code":"27.0",
    "gn:admin2_code":"1257.0",
    "gn:asciiname":"Porkenahult",
    "gn:country_code":"SE",
    "gn:dem":136,
    "gn:feature_class":"P",
    "gn:feature_code":"PPL",
    "gn:name":"Porkenahult",
    "gn:population":0,
    "gn:timezone":"Europe/Stockholm",
    "iso:country":"SE",
    "wof:name":"Porkenahult",
    "wof:placetype":"locality"
},
  "geometry": {"coordinates":[13.38333,56.36666999999999],"type":"Point"}
}