{
  "type": "Feature",
  "properties": {
    "gn:admin1_code":"15.0",
    "gn:admin2_code":"1883.0",
    "gn:asciiname":"Lerangen",
    "gn:country_code":"SE",
    "gn:dem":224,
    "gn:feature_class":"P",
    "gn:feature_code":"PPL",
    "gn:name":"Ler\u00e4ngen",
    "gn:population":0,
    "gn:timezone":"Europe/Stockholm",
    "iso:country":"SE",
    "wof:name":"Lerangen",
    "wof:placetype":"locality"
},
  "geometry": {"coordinates":[14.56667,59.36666999999999],"type":"Point"}
}