{
  "type": "Feature",
  "properties": {
    "gn:admin1_code":"7.0",
    "gn:admin2_code":"2380.0",
    "gn:asciiname":"Lillsjohogen",
    "gn:country_code":"SE",
    "gn:dem":276,
    "gn:feature_class":"P",
    "gn:feature_code":"PPL",
    "gn:name":"Lillsj\u00f6h\u00f6gen",
    "gn:population":0,
    "gn:timezone":"Europe/Stockholm",
    "iso:country":"SE",
    "name:nor_x_preferred":[
        "Lillsj\u00f6h\u00f6gen"
    ],
    "name:nor_x_variant":[
        "Lillsj\u00f8h\u00f8gen"
    ],
    "name:und_x_variant":[
        "Lillsj\u00f6h\u00f6gen"
    ],
    "wof:name":"Lillsjohogen",
    "wof:placetype":"locality"
},
  "geometry": {"coordinates":[15.18333,63.18333000000001],"type":"Point"}
}