{
  "type": "Feature",
  "properties": {
    "gn:admin1_code":"26.0",
    "gn:admin2_code":"192.0",
    "gn:asciiname":"Over Soderby",
    "gn:country_code":"SE",
    "gn:dem":46,
    "gn:feature_class":"P",
    "gn:feature_code":"PPL",
    "gn:name":"\u00d6ver S\u00f6derby",
    "gn:population":0,
    "gn:timezone":"Europe/Stockholm",
    "iso:country":"SE",
    "name:nor_x_preferred":[
        "\u00d6ver S\u00f6derby"
    ],
    "name:nor_x_variant":[
        "\u00d8ver S\u00f8derby"
    ],
    "wof:name":"Over Soderby",
    "wof:placetype":"locality"
},
  "geometry": {"coordinates":[17.91667,59.08306],"type":"Point"}
}