{
  "type": "Feature",
  "properties": {
    "gn:admin1_code":"9.0",
    "gn:admin2_code":"834.0",
    "gn:asciiname":"Appleryd",
    "gn:cc2":"SE",
    "gn:country_code":"SE",
    "gn:dem":28,
    "gn:feature_class":"P",
    "gn:feature_code":"PPL",
    "gn:name":"Appleryd",
    "gn:population":0,
    "gn:timezone":"Europe/Stockholm",
    "iso:country":"SE",
    "name:und_x_variant":[
        "Apleryd",
        "Appleryd"
    ],
    "wof:name":"Appleryd",
    "wof:placetype":"locality"
},
  "geometry": {"coordinates":[15.96667,56.33333],"type":"Point"}
}