{
  "type": "Feature",
  "properties": {
    "gn:admin1_code":"27.0",
    "gn:admin2_code":"1290.0",
    "gn:asciiname":"Ostra Vram",
    "gn:country_code":"SE",
    "gn:dem":39,
    "gn:feature_class":"P",
    "gn:feature_code":"PPL",
    "gn:name":"\u00d6stra Vram",
    "gn:population":0,
    "gn:timezone":"Europe/Stockholm",
    "iso:country":"SE",
    "name:nor_x_preferred":[
        "\u00d6stra Vram"
    ],
    "name:nor_x_variant":[
        "\u00d8stra Vram"
    ],
    "wof:name":"Ostra Vram",
    "wof:placetype":"locality"
},
  "geometry": {"coordinates":[13.98333,55.93333000000001],"type":"Point"}
}