{
  "type": "Feature",
  "properties": {
    "gn:admin1_code":"28.0",
    "gn:admin2_code":"1452.0",
    "gn:asciiname":"Stjarnebo",
    "gn:cc2":"SE",
    "gn:country_code":"SE",
    "gn:dem":213,
    "gn:feature_class":"P",
    "gn:feature_code":"PPL",
    "gn:name":"Stj\u00e4rnebo",
    "gn:population":0,
    "gn:timezone":"Europe/Stockholm",
    "iso:country":"SE",
    "name:und_x_variant":[
        "Stjernebo",
        "Stj\u00e4rnebo"
    ],
    "wof:name":"Stjarnebo",
    "wof:placetype":"locality"
},
  "geometry": {"coordinates":[13.35,57.41667],"type":"Point"}
}