{
  "type": "Feature",
  "properties": {
    "gn:admin1_code":"3.0",
    "gn:admin2_code":"2132.0",
    "gn:asciiname":"Kolfors",
    "gn:country_code":"SE",
    "gn:dem":323,
    "gn:feature_class":"P",
    "gn:feature_code":"PPL",
    "gn:name":"K\u00f6lfors",
    "gn:population":0,
    "gn:timezone":"Europe/Stockholm",
    "iso:country":"SE",
    "name:nor_x_preferred":[
        "K\u00f6lfors"
    ],
    "name:nor_x_variant":[
        "K\u00f8lfors"
    ],
    "name:und_x_variant":[
        "K\u00f6lfors"
    ],
    "wof:name":"Kolfors",
    "wof:placetype":"locality"
},
  "geometry": {"coordinates":[16.43333,62.16667],"type":"Point"}
}