{
  "type": "Feature",
  "properties": {
    "gn:gn_country":"SE",
    "gn:gn_fcode":"PPL",
    "gn:gn_pop":256,
    "gn:population":334,
    "iso:country":"SE",
    "name:eng_x_preferred":[
        "H\u00f6gboda"
    ],
    "name:nan_x_preferred":[
        "H\u00f6gboda"
    ],
    "name:nld_x_preferred":[
        "H\u00f6gboda"
    ],
    "name:nno_x_preferred":[
        "H\u00f6gboda"
    ],
    "name:nob_x_preferred":[
        "H\u00f6gboda"
    ],
    "name:nor_x_preferred":[
        "H\u00f8gboda"
    ],
    "name:nor_x_variant":[
        "H\u00f6gboda"
    ],
    "name:sco_x_preferred":[
        "H\u00f6gboda"
    ],
    "name:swe_x_preferred":[
        "H\u00f6gboda"
    ],
    "qs_pg:aaroncc":"SE",
    "qs_pg:gn_country":"SE",
    "qs_pg:gn_fcode":"PPL",
    "qs_pg:gn_pop":256,
    "qs_pg:name":"H\u00f6gboda",
    "qs_pg:name_adm0":"Sverige",
    "qs_pg:name_adm1":"V\u00e4rmlands L\u00e4n",
    "qs_pg:photos_9k":1,
    "qs_pg:photos_9r":1,
    "qs_pg:photos_all":1,
    "qs_pg:photos_sr":0,
    "qs_pg:pop_sr":2,
    "qs_pg:qs_pg_placetype":"locality",
    "qs_pg:qs_pg_placetype_gp":"Town",
    "qs_pg:woe_adm0":23424954,
    "woe:adm0_id":23424954,
    "woe:name_adm0":"Sverige",
    "woe:name_adm1":"V\u00e4rmlands L\u00e4n",
    "woe:placetype":"Town",
    "wof:name":"H\u00f6gboda",
    "wof:placetype":"locality",
    "wof:population":334
},
  "geometry": {"coordinates":[13.01667,59.56667],"type":"Point"}
}