{
  "type": "Feature",
  "properties": {
    "gn:admin1_code":"15.0",
    "gn:admin2_code":"1863.0",
    "gn:asciiname":"Sandsjohojden",
    "gn:country_code":"SE",
    "gn:dem":190,
    "gn:feature_class":"P",
    "gn:feature_code":"PPL",
    "gn:name":"Sandsj\u00f6h\u00f6jden",
    "gn:population":0,
    "gn:timezone":"Europe/Stockholm",
    "iso:country":"SE",
    "name:nor_x_preferred":[
        "Sandsj\u00f6h\u00f6jden"
    ],
    "name:nor_x_variant":[
        "Sandsj\u00f8h\u00f8jden"
    ],
    "wof:name":"Sandsjohojden",
    "wof:placetype":"locality"
},
  "geometry": {"coordinates":[14.63333,59.56667],"type":"Point"}
}