{
  "type": "Feature",
  "properties": {
    "gn:admin1_code":"28.0",
    "gn:admin2_code":"1452.0",
    "gn:asciiname":"Nygard",
    "gn:country_code":"SE",
    "gn:dem":204,
    "gn:feature_class":"P",
    "gn:feature_code":"PPL",
    "gn:name":"Nyg\u00e5rd",
    "gn:population":0,
    "gn:timezone":"Europe/Stockholm",
    "iso:country":"SE",
    "wof:name":"Nygard",
    "wof:placetype":"locality"
},
  "geometry": {"coordinates":[13.46667,57.55],"type":"Point"}
}