{
  "type": "Feature",
  "properties": {
    "gn:admin1_code":"23.0",
    "gn:admin2_code":"2482.0",
    "gn:asciiname":"Selsliden",
    "gn:country_code":"SE",
    "gn:dem":319,
    "gn:feature_class":"P",
    "gn:feature_code":"PPL",
    "gn:name":"Selsliden",
    "gn:population":0,
    "gn:timezone":"Europe/Stockholm",
    "iso:country":"SE",
    "wof:name":"Selsliden",
    "wof:placetype":"locality"
},
  "geometry": {"coordinates":[20.16667,65.05],"type":"Point"}
}