{
  "type": "Feature",
  "properties": {
    "gn:admin1_code":"7.0",
    "gn:admin2_code":"2326.0",
    "gn:asciiname":"Bjartan",
    "gn:country_code":"SE",
    "gn:dem":588,
    "gn:feature_class":"P",
    "gn:feature_code":"PPL",
    "gn:name":"Bjartan",
    "gn:population":0,
    "gn:timezone":"Europe/Stockholm",
    "iso:country":"SE",
    "wof:name":"Bjartan",
    "wof:placetype":"locality"
},
  "geometry": {"coordinates":[14.25,62.56667],"type":"Point"}
}