{
  "type": "Feature",
  "properties": {
    "gn:admin1_code":"24.0",
    "gn:admin2_code":"2262.0",
    "gn:admin3_code":"226204.0",
    "gn:admin4_code":"2506.0",
    "gn:asciiname":"Holmo",
    "gn:cc2":"SE",
    "gn:country_code":"SE",
    "gn:dem":9,
    "gn:feature_class":"P",
    "gn:feature_code":"PPL",
    "gn:name":"Holm\u00f6",
    "gn:population":0,
    "gn:timezone":"Europe/Stockholm",
    "iso:country":"SE",
    "name:nor_x_preferred":[
        "Holm\u00f6"
    ],
    "name:nor_x_variant":[
        "Holm\u00f8"
    ],
    "name:und_x_variant":[
        "Holme"
    ],
    "wof:name":"Holmo",
    "wof:placetype":"locality"
},
  "geometry": {"coordinates":[17.62945,62.44193000000001],"type":"Point"}
}