{
  "type": "Feature",
  "properties": {
    "gn:admin1_code":"28.0",
    "gn:admin2_code":"1496.0",
    "gn:asciiname":"Bjorstorp",
    "gn:country_code":"SE",
    "gn:dem":117,
    "gn:feature_class":"P",
    "gn:feature_code":"PPL",
    "gn:name":"Bj\u00f6rstorp",
    "gn:population":0,
    "gn:timezone":"Europe/Stockholm",
    "iso:country":"SE",
    "name:nor_x_preferred":[
        "Bj\u00f6rstorp"
    ],
    "name:nor_x_variant":[
        "Bj\u00f8rstorp"
    ],
    "wof:name":"Bjorstorp",
    "wof:placetype":"locality"
},
  "geometry": {"coordinates":[14.01667,58.41667],"type":"Point"}
}