{
  "type": "Feature",
  "properties": {
    "gn:admin1_code":"27.0",
    "gn:admin2_code":"1230.0",
    "gn:asciiname":"Grevie",
    "gn:country_code":"SE",
    "gn:dem":16,
    "gn:feature_class":"P",
    "gn:feature_code":"PPL",
    "gn:name":"Grevie",
    "gn:population":0,
    "gn:timezone":"Europe/Stockholm",
    "iso:country":"SE",
    "name:ceb_x_preferred":[
        "Grevie"
    ],
    "name:ita_x_preferred":[
        "Grevie"
    ],
    "name:nld_x_preferred":[
        "Grevie"
    ],
    "name:nno_x_preferred":[
        "Grevie"
    ],
    "name:nor_x_preferred":[
        "Grevie"
    ],
    "name:swe_x_preferred":[
        "Grevie"
    ],
    "wof:name":"Grevie",
    "wof:placetype":"locality"
},
  "geometry": {"coordinates":[13.20471,55.62246999999999],"type":"Point"}
}