{
  "type": "Feature",
  "properties": {
    "gn:gn_country":"SE",
    "iso:country":"SE",
    "name:dan_x_preferred":[
        "S\u00f6nnerbergen"
    ],
    "name:deu_x_preferred":[
        "S\u00f6nnerbergen"
    ],
    "name:eng_x_preferred":[
        "S\u00f6nnerbergen"
    ],
    "name:fra_x_preferred":[
        "S\u00f6nnerbergen"
    ],
    "name:nds_x_preferred":[
        "S\u00f6nnerbergen"
    ],
    "name:nld_x_preferred":[
        "S\u00f6nnerbergen"
    ],
    "name:nno_x_preferred":[
        "S\u00f6nnerbergen"
    ],
    "name:nob_x_preferred":[
        "S\u00f6nnerbergen"
    ],
    "name:swe_x_preferred":[
        "S\u00f6nnerbergen"
    ],
    "qs_pg:aaroncc":"SE",
    "qs_pg:gn_country":"SE",
    "qs_pg:name":"S\u00f6nnerbergen",
    "qs_pg:name_adm0":"Sverige",
    "qs_pg:name_adm1":"Hallands L\u00e4n",
    "qs_pg:photos":15,
    "qs_pg:photos_1k":3,
    "qs_pg:photos_9k":1,
    "qs_pg:photos_9r":1,
    "qs_pg:photos_all":15,
    "qs_pg:photos_sr":1,
    "qs_pg:pop_sr":0,
    "qs_pg:qs_pg_placetype":"locality",
    "qs_pg:qs_pg_placetype_gp":"Town",
    "qs_pg:woe_adm0":23424954,
    "woe:adm0_id":23424954,
    "woe:name_adm0":"Sverige",
    "woe:name_adm1":"Hallands L\u00e4n",
    "woe:placetype":"Town",
    "wof:name":"S\u00f6nnerbergen",
    "wof:placetype":"locality"
},
  "geometry": {"coordinates":[11.958618,57.359613],"type":"Point"}
}