{
  "type": "Feature",
  "properties": {
    "gn:admin1_code":"3.0",
    "gn:admin2_code":"2121.0",
    "gn:asciiname":"Galvsbo",
    "gn:country_code":"SE",
    "gn:dem":175,
    "gn:feature_class":"P",
    "gn:feature_code":"PPL",
    "gn:name":"Galvsbo",
    "gn:population":0,
    "gn:timezone":"Europe/Stockholm",
    "iso:country":"SE",
    "wof:name":"Galvsbo",
    "wof:placetype":"locality"
},
  "geometry": {"coordinates":[16.13332999999999,61.45],"type":"Point"}
}