{
  "type": "Feature",
  "properties": {
    "gn:gn_country":"SE",
    "gn:gn_fcode":"PPL",
    "gn:gn_pop":0,
    "iso:country":"SE",
    "name:dan_x_preferred":[
        "Ravlunda"
    ],
    "name:dut_x_preferred":[
        "Ravlunda"
    ],
    "name:eng_x_preferred":[
        "Ravlunda"
    ],
    "name:fao_x_preferred":[
        "Ravlunda"
    ],
    "name:fre_x_preferred":[
        "Ravlunda"
    ],
    "name:ger_x_preferred":[
        "Ravlunda"
    ],
    "name:nds_x_preferred":[
        "Ravlunda"
    ],
    "name:nno_x_preferred":[
        "Ravlunda"
    ],
    "name:nob_x_preferred":[
        "Ravlunda"
    ],
    "name:swe_x_preferred":[
        "Ravlunda"
    ],
    "qs_pg:aaroncc":"SE",
    "qs_pg:gn_country":"SE",
    "qs_pg:gn_fcode":"PPL",
    "qs_pg:gn_pop":0,
    "qs_pg:name":"Ravlunda",
    "qs_pg:name_adm0":"Sverige",
    "qs_pg:name_adm1":"Sk\u00e5ne L\u00e4n",
    "qs_pg:photos":73,
    "qs_pg:photos_1k":15,
    "qs_pg:photos_9k":1,
    "qs_pg:photos_9r":2,
    "qs_pg:photos_all":73,
    "qs_pg:photos_sr":2,
    "qs_pg:pop_sr":0,
    "qs_pg:qs_pg_placetype":"locality",
    "qs_pg:qs_pg_placetype_gp":"Town",
    "qs_pg:woe_adm0":23424954,
    "woe:adm0_id":23424954,
    "woe:name_adm0":"Sverige",
    "woe:name_adm1":"Sk\u00e5ne L\u00e4n",
    "woe:placetype":"Town",
    "wof:name":"Ravlunda",
    "wof:placetype":"locality"
},
  "geometry": {"coordinates":[14.15,55.71667],"type":"Point"}
}