{
  "type": "Feature",
  "properties": {
    "gn:admin1_code":"6.0",
    "gn:admin2_code":"1315.0",
    "gn:asciiname":"Skarkehylte",
    "gn:cc2":"SE",
    "gn:country_code":"SE",
    "gn:dem":142,
    "gn:feature_class":"P",
    "gn:feature_code":"PPL",
    "gn:name":"Sk\u00e4rkehylte",
    "gn:population":0,
    "gn:timezone":"Europe/Stockholm",
    "iso:country":"SE",
    "name:und_x_variant":[
        "Sk\u00e4rkehytte",
        "Sk\u00e4rkehylte"
    ],
    "wof:name":"Skarkehylte",
    "wof:placetype":"locality"
},
  "geometry": {"coordinates":[13.21667,57.03333000000001],"type":"Point"}
}