{
  "type": "Feature",
  "properties": {
    "gn:admin1_code":"14.0",
    "gn:admin2_code":"2583.0",
    "gn:asciiname":"Kukkola",
    "gn:country_code":"SE",
    "gn:dem":16,
    "gn:feature_class":"P",
    "gn:feature_code":"PPL",
    "gn:name":"Kukkola",
    "gn:population":0,
    "gn:timezone":"Europe/Stockholm",
    "iso:country":"SE",
    "name:fit_x_preferred":[
        "Kukkola"
    ],
    "wof:name":"Kukkola",
    "wof:placetype":"locality"
},
  "geometry": {"coordinates":[24.03635,65.96035999999999],"type":"Point"}
}