{
  "type": "Feature",
  "properties": {
    "gn:admin1_code":"24.0",
    "gn:admin2_code":"2280.0",
    "gn:admin3_code":"228003.0",
    "gn:admin4_code":"2469.0",
    "gn:asciiname":"Glon",
    "gn:country_code":"SE",
    "gn:dem":1,
    "gn:feature_class":"P",
    "gn:feature_code":"PPL",
    "gn:name":"Glon",
    "gn:population":0,
    "gn:timezone":"Europe/Stockholm",
    "iso:country":"SE",
    "wof:name":"Glon",
    "wof:placetype":"locality"
},
  "geometry": {"coordinates":[17.85361,62.50417],"type":"Point"}
}