{
  "type": "Feature",
  "properties": {
    "gn:admin1_code":"28.0",
    "gn:admin2_code":"1470.0",
    "gn:asciiname":"Karlsberg",
    "gn:country_code":"SE",
    "gn:dem":119,
    "gn:feature_class":"P",
    "gn:feature_code":"PPL",
    "gn:name":"Karlsberg",
    "gn:population":0,
    "gn:timezone":"Europe/Stockholm",
    "iso:country":"SE",
    "name:ceb_x_preferred":[
        "Karlsberg"
    ],
    "name:deu_x_preferred":[
        "Karlsberg"
    ],
    "name:swe_x_preferred":[
        "Karlsberg"
    ],
    "wof:name":"Karlsberg",
    "wof:placetype":"locality"
},
  "geometry": {"coordinates":[13.11667,58.16667],"type":"Point"}
}