{
  "type": "Feature",
  "properties": {
    "gn:admin1_code":"24.0",
    "gn:admin2_code":"2262.0",
    "gn:admin3_code":"226201.0",
    "gn:admin4_code":"2501.0",
    "gn:asciiname":"Solbacka",
    "gn:country_code":"SE",
    "gn:dem":48,
    "gn:feature_class":"P",
    "gn:feature_code":"PPL",
    "gn:name":"Solbacka",
    "gn:population":0,
    "gn:timezone":"Europe/Stockholm",
    "iso:country":"SE",
    "wof:name":"Solbacka",
    "wof:placetype":"locality"
},
  "geometry": {"coordinates":[17.35145,62.50088],"type":"Point"}
}