{
  "type": "Feature",
  "properties": {
    "gn:admin1_code":"26",
    "gn:admin2_code":"120.0",
    "gn:admin3_code":"12003.0",
    "gn:admin4_code":"11.0",
    "gn:asciiname":"Timmerdalen",
    "gn:country_code":"SE",
    "gn:dem":26,
    "gn:feature_class":"P",
    "gn:feature_code":"PPL",
    "gn:name":"Timmerdalen",
    "gn:population":0,
    "gn:timezone":"Europe/Stockholm",
    "iso:country":"SE",
    "wof:name":"Timmerdalen",
    "wof:placetype":"locality"
},
  "geometry": {"coordinates":[18.65384,59.37115],"type":"Point"}
}