{
  "type": "Feature",
  "properties": {
    "gn:admin1_code":"10.0",
    "gn:admin2_code":"2081.0",
    "gn:admin3_code":"208102.0",
    "gn:admin4_code":"2378.0",
    "gn:asciiname":"Uvberget",
    "gn:cc2":"SE",
    "gn:country_code":"SE",
    "gn:dem":95,
    "gn:feature_class":"P",
    "gn:feature_code":"PPL",
    "gn:name":"Uvberget",
    "gn:population":0,
    "gn:timezone":"Europe/Stockholm",
    "iso:country":"SE",
    "name:und_x_variant":[
        "Ufberget",
        "Uvberget"
    ],
    "wof:name":"Uvberget",
    "wof:placetype":"locality"
},
  "geometry": {"coordinates":[15.56033,60.47600000000001],"type":"Point"}
}