{
  "type": "Feature",
  "properties": {
    "gn:admin1_code":"12.0",
    "gn:admin2_code":"780.0",
    "gn:asciiname":"Toftahojden",
    "gn:country_code":"SE",
    "gn:dem":163,
    "gn:feature_class":"P",
    "gn:feature_code":"PPL",
    "gn:name":"Toftah\u00f6jden",
    "gn:population":0,
    "gn:timezone":"Europe/Stockholm",
    "iso:country":"SE",
    "name:nor_x_preferred":[
        "Toftah\u00f6jden"
    ],
    "name:nor_x_variant":[
        "Toftah\u00f8jden"
    ],
    "name:und_x_variant":[
        "Toftah\u00f6jden"
    ],
    "wof:name":"Toftahojden",
    "wof:placetype":"locality"
},
  "geometry": {"coordinates":[14.88333,56.93333000000001],"type":"Point"}
}