{
  "type": "Feature",
  "properties": {
    "gn:admin1_code":"28.0",
    "gn:admin2_code":"1401.0",
    "gn:asciiname":"Assmundtorp",
    "gn:cc2":"SE",
    "gn:country_code":"SE",
    "gn:dem":153,
    "gn:feature_class":"P",
    "gn:feature_code":"PPL",
    "gn:name":"Assmundtorp",
    "gn:population":0,
    "gn:timezone":"Europe/Stockholm",
    "iso:country":"SE",
    "name:und_x_variant":[
        "Asmundtorp",
        "Assmundtorp"
    ],
    "wof:name":"Assmundtorp",
    "wof:placetype":"locality"
},
  "geometry": {"coordinates":[12.28333,57.68333000000001],"type":"Point"}
}