{
  "type": "Feature",
  "properties": {
    "gn:admin1_code":"10.0",
    "gn:admin2_code":"2029.0",
    "gn:asciiname":"Sunnanang",
    "gn:country_code":"SE",
    "gn:dem":210,
    "gn:feature_class":"P",
    "gn:feature_code":"PPL",
    "gn:name":"Sunnan\u00e4ng",
    "gn:population":0,
    "gn:timezone":"Europe/Stockholm",
    "iso:country":"SE",
    "wof:name":"Sunnanang",
    "wof:placetype":"locality"
},
  "geometry": {"coordinates":[14.96667,60.78333000000001],"type":"Point"}
}