{
  "type": "Feature",
  "properties": {
    "gn:admin1_code":"9.0",
    "gn:admin2_code":"834.0",
    "gn:asciiname":"Frobbestorp",
    "gn:country_code":"SE",
    "gn:dem":72,
    "gn:feature_class":"P",
    "gn:feature_code":"PPL",
    "gn:name":"Fr\u00f6bbestorp",
    "gn:population":0,
    "gn:timezone":"Europe/Stockholm",
    "iso:country":"SE",
    "name:nor_x_preferred":[
        "Fr\u00f6bbestorp"
    ],
    "name:nor_x_variant":[
        "Fr\u00f8bbestorp"
    ],
    "name:und_x_variant":[
        "Fr\u00f6bbestorp"
    ],
    "wof:name":"Frobbestorp",
    "wof:placetype":"locality"
},
  "geometry": {"coordinates":[15.85,56.33333],"type":"Point"}
}