{
  "type": "Feature",
  "properties": {
    "gn:admin1_code":"15.0",
    "gn:admin2_code":"1880.0",
    "gn:asciiname":"Tangsater",
    "gn:cc2":"SE",
    "gn:country_code":"SE",
    "gn:dem":57,
    "gn:feature_class":"P",
    "gn:feature_code":"PPL",
    "gn:name":"T\u00e5ngs\u00e4ter",
    "gn:population":0,
    "gn:timezone":"Europe/Stockholm",
    "iso:country":"SE",
    "name:und_x_variant":[
        "T\u00e5ngs\u00e4tter",
        "T\u00e5ngs\u00e4ter"
    ],
    "wof:name":"Tangsater",
    "wof:placetype":"locality"
},
  "geometry": {"coordinates":[15.46667,59.13333000000001],"type":"Point"}
}