{
  "type": "Feature",
  "properties": {
    "gn:admin1_code":"28.0",
    "gn:admin2_code":"1472.0",
    "gn:asciiname":"Stora Lakenas",
    "gn:country_code":"SE",
    "gn:dem":118,
    "gn:feature_class":"P",
    "gn:feature_code":"PPL",
    "gn:name":"Stora Laken\u00e4s",
    "gn:population":0,
    "gn:timezone":"Europe/Stockholm",
    "iso:country":"SE",
    "wof:name":"Stora Lakenas",
    "wof:placetype":"locality"
},
  "geometry": {"coordinates":[14.28333,58.48333],"type":"Point"}
}