{
  "type": "Feature",
  "properties": {
    "gn:admin1_code":"3.0",
    "gn:admin2_code":"2182.0",
    "gn:asciiname":"Sillvik",
    "gn:country_code":"SE",
    "gn:dem":2,
    "gn:feature_class":"P",
    "gn:feature_code":"PPL",
    "gn:name":"Sillvik",
    "gn:population":0,
    "gn:timezone":"Europe/Stockholm",
    "iso:country":"SE",
    "wof:name":"Sillvik",
    "wof:placetype":"locality"
},
  "geometry": {"coordinates":[17.14056,61.08416999999999],"type":"Point"}
}