{
  "type": "Feature",
  "properties": {
    "gn:admin1_code":"16.0",
    "gn:admin2_code":"580.0",
    "gn:asciiname":"Kolbyttemon",
    "gn:country_code":"SE",
    "gn:dem":129,
    "gn:feature_class":"P",
    "gn:feature_code":"PPL",
    "gn:name":"Kolbyttemon",
    "gn:population":0,
    "gn:timezone":"Europe/Stockholm",
    "iso:country":"SE",
    "wof:name":"Kolbyttemon",
    "wof:placetype":"locality"
},
  "geometry": {"coordinates":[15.63333,58.33333],"type":"Point"}
}