{
  "type": "Feature",
  "properties": {
    "gn:admin1_code":"10.0",
    "gn:admin2_code":"2061.0",
    "gn:asciiname":"Grasberg",
    "gn:country_code":"SE",
    "gn:dem":356,
    "gn:feature_class":"P",
    "gn:feature_code":"PPL",
    "gn:name":"Gr\u00e4sberg",
    "gn:population":0,
    "gn:timezone":"Europe/Stockholm",
    "iso:country":"SE",
    "name:ceb_x_preferred":[
        "Grasberg"
    ],
    "name:deu_x_preferred":[
        "Grasberg"
    ],
    "name:epo_x_preferred":[
        "Grasberg"
    ],
    "name:est_x_preferred":[
        "Grasbergi vald"
    ],
    "name:eus_x_preferred":[
        "Grasberg"
    ],
    "name:fas_x_preferred":[
        "\u06af\u0631\u0627\u0633\u0628\u0631\u06af"
    ],
    "name:fra_x_preferred":[
        "Grasberg"
    ],
    "name:hun_x_preferred":[
        "Grasberg"
    ],
    "name:ita_x_preferred":[
        "Grasberg"
    ],
    "name:kaz_x_preferred":[
        "\u0413\u0440\u0430\u0441\u0431\u0435\u0440\u0433"
    ],
    "name:kir_x_preferred":[
        "\u0413\u0440\u0430\u0441\u0431\u0435\u0440\u0433"
    ],
    "name:msa_x_preferred":[
        "Grasberg"
    ],
    "name:nds_x_preferred":[
        "Gemeen Grasbarg"
    ],
    "name:nld_x_preferred":[
        "Grasberg"
    ],
    "name:pol_x_preferred":[
        "Grasberg"
    ],
    "name:por_x_preferred":[
        "Grasberg"
    ],
    "name:ron_x_preferred":[
        "Grasberg"
    ],
    "name:rus_x_preferred":[
        "\u0413\u0440\u0430\u0441\u0431\u0435\u0440\u0433"
    ],
    "name:spa_x_preferred":[
        "Grasberg"
    ],
    "name:srp_x_preferred":[
        "\u0413\u0440\u0430\u0441\u0431\u0435\u0440\u0433"
    ],
    "name:ukr_x_preferred":[
        "\u0413\u0440\u0430\u0441\u0431\u0435\u0440\u0433"
    ],
    "name:uzb_x_preferred":[
        "Grasberg"
    ],
    "name:vol_x_preferred":[
        "Grasberg"
    ],
    "name:war_x_preferred":[
        "Grasberg"
    ],
    "name:zho_x_preferred":[
        "\u683c\u62c9\u65af\u8d1d\u683c"
    ],
    "wof:name":"Grasberg",
    "wof:placetype":"locality"
},
  "geometry": {"coordinates":[15.31667,59.95],"type":"Point"}
}