{
  "type": "Feature",
  "properties": {
    "gn:admin1_code":"12.0",
    "gn:admin2_code":"781.0",
    "gn:asciiname":"Hov",
    "gn:country_code":"SE",
    "gn:dem":161,
    "gn:feature_class":"P",
    "gn:feature_code":"PPL",
    "gn:name":"Hov",
    "gn:population":0,
    "gn:timezone":"Europe/Stockholm",
    "iso:country":"SE",
    "name:ceb_x_preferred":[
        "Hov"
    ],
    "name:dan_x_preferred":[
        "Hov"
    ],
    "name:deu_x_preferred":[
        "Hov"
    ],
    "name:fin_x_preferred":[
        "Hov"
    ],
    "name:fra_x_preferred":[
        "Hov"
    ],
    "name:nld_x_preferred":[
        "Hov"
    ],
    "name:nor_x_preferred":[
        "Hov"
    ],
    "name:swe_x_preferred":[
        "Hov"
    ],
    "wof:name":"Hov",
    "wof:placetype":"locality"
},
  "geometry": {"coordinates":[13.75,56.96666999999999],"type":"Point"}
}