{
  "type": "Feature",
  "properties": {
    "gn:admin1_code":"22.0",
    "gn:admin2_code":"1784.0",
    "gn:asciiname":"Hoge",
    "gn:country_code":"SE",
    "gn:dem":59,
    "gn:feature_class":"P",
    "gn:feature_code":"PPL",
    "gn:name":"H\u00f6ge",
    "gn:population":0,
    "gn:timezone":"Europe/Stockholm",
    "iso:country":"SE",
    "name:nor_x_preferred":[
        "H\u00f6ge"
    ],
    "name:nor_x_variant":[
        "H\u00f8ge"
    ],
    "name:und_x_variant":[
        "H\u00f6ge"
    ],
    "wof:name":"Hoge",
    "wof:placetype":"locality"
},
  "geometry": {"coordinates":[12.53333,59.56667],"type":"Point"}
}