{
  "type": "Feature",
  "properties": {
    "gn:admin1_code":"3.0",
    "gn:admin2_code":"2121.0",
    "gn:asciiname":"Sandbergs",
    "gn:country_code":"SE",
    "gn:dem":240,
    "gn:feature_class":"P",
    "gn:feature_code":"PPL",
    "gn:name":"Sandbergs",
    "gn:population":0,
    "gn:timezone":"Europe/Stockholm",
    "iso:country":"SE",
    "wof:name":"Sandbergs",
    "wof:placetype":"locality"
},
  "geometry": {"coordinates":[16.23333,61.43333000000001],"type":"Point"}
}