{
  "type": "Feature",
  "properties": {
    "gn:admin1_code":"24.0",
    "gn:admin2_code":"2260.0",
    "gn:admin3_code":"226003.0",
    "gn:admin4_code":"2465.0",
    "gn:asciiname":"Viken",
    "gn:country_code":"SE",
    "gn:dem":245,
    "gn:feature_class":"P",
    "gn:feature_code":"PPL",
    "gn:name":"Viken",
    "gn:population":0,
    "gn:timezone":"Europe/Stockholm",
    "iso:country":"SE",
    "name:ceb_x_preferred":[
        "Viken"
    ],
    "name:dan_x_preferred":[
        "Viken"
    ],
    "name:deu_x_preferred":[
        "Viken"
    ],
    "name:fin_x_preferred":[
        "Viken"
    ],
    "name:fra_x_preferred":[
        "Viken"
    ],
    "name:ita_x_preferred":[
        "Viken"
    ],
    "name:nld_x_preferred":[
        "Viken"
    ],
    "name:nor_x_preferred":[
        "Viken"
    ],
    "name:swe_x_preferred":[
        "Viken"
    ],
    "wof:name":"Viken",
    "wof:placetype":"locality"
},
  "geometry": {"coordinates":[15.1686,62.3847],"type":"Point"}
}