{
  "type": "Feature",
  "properties": {
    "gn:admin1_code":"9.0",
    "gn:admin2_code":"882.0",
    "gn:asciiname":"Fridhem",
    "gn:country_code":"SE",
    "gn:dem":11,
    "gn:feature_class":"P",
    "gn:feature_code":"PPL",
    "gn:name":"Fridhem",
    "gn:population":0,
    "gn:timezone":"Europe/Stockholm",
    "iso:country":"SE",
    "wof:name":"Fridhem",
    "wof:placetype":"locality"
},
  "geometry": {"coordinates":[16.58333,57.55222],"type":"Point"}
}