{
  "type": "Feature",
  "properties": {
    "gn:admin1_code":"9.0",
    "gn:admin2_code":"883.0",
    "gn:asciiname":"Dalen",
    "gn:country_code":"SE",
    "gn:dem":88,
    "gn:feature_class":"P",
    "gn:feature_code":"PPL",
    "gn:name":"Dalen",
    "gn:population":0,
    "gn:timezone":"Europe/Stockholm",
    "iso:country":"SE",
    "name:ceb_x_preferred":[
        "Dalen"
    ],
    "name:cym_x_preferred":[
        "Dalen"
    ],
    "name:fra_x_preferred":[
        "Dalen"
    ],
    "name:fry_x_preferred":[
        "Dalen"
    ],
    "name:ita_x_preferred":[
        "Dalen"
    ],
    "name:nld_x_preferred":[
        "Dalen"
    ],
    "name:pol_x_preferred":[
        "Dalen"
    ],
    "wof:name":"Dalen",
    "wof:placetype":"locality"
},
  "geometry": {"coordinates":[16.31667,58.03333000000001],"type":"Point"}
}