{
  "type": "Feature",
  "properties": {
    "gn:admin1_code":"27.0",
    "gn:admin2_code":"1265.0",
    "gn:asciiname":"Vanstad",
    "gn:country_code":"SE",
    "gn:dem":81,
    "gn:feature_class":"P",
    "gn:feature_code":"PPL",
    "gn:name":"Vanstad",
    "gn:population":0,
    "gn:timezone":"Europe/Stockholm",
    "iso:country":"SE",
    "wof:name":"Vanstad",
    "wof:placetype":"locality"
},
  "geometry": {"coordinates":[13.85,55.61666999999999],"type":"Point"}
}