{
  "type": "Feature",
  "properties": {
    "gn:admin1_code":"22.0",
    "gn:admin2_code":"1765.0",
    "gn:asciiname":"Ostra Bon",
    "gn:cc2":"SE",
    "gn:country_code":"SE",
    "gn:dem":120,
    "gn:feature_class":"P",
    "gn:feature_code":"PPL",
    "gn:name":"\u00d6stra B\u00f6n",
    "gn:population":0,
    "gn:timezone":"Europe/Stockholm",
    "iso:country":"SE",
    "name:nor_x_preferred":[
        "\u00d6stra B\u00f6n"
    ],
    "name:nor_x_variant":[
        "\u00d8stra B\u00f8n"
    ],
    "name:und_x_variant":[
        "B\u00f6n"
    ],
    "wof:name":"Ostra Bon",
    "wof:placetype":"locality"
},
  "geometry": {"coordinates":[11.83333,59.51667],"type":"Point"}
}