{
  "type": "Feature",
  "properties": {
    "gn:admin1_code":"9.0",
    "gn:admin2_code":"881.0",
    "gn:asciiname":"Stora Skedsbygd",
    "gn:country_code":"SE",
    "gn:dem":152,
    "gn:feature_class":"P",
    "gn:feature_code":"PPL",
    "gn:name":"Stora Skedsbygd",
    "gn:population":0,
    "gn:timezone":"Europe/Stockholm",
    "iso:country":"SE",
    "wof:name":"Stora Skedsbygd",
    "wof:placetype":"locality"
},
  "geometry": {"coordinates":[15.81667,56.91667],"type":"Point"}
}