{
  "type": "Feature",
  "properties": {
    "gn:admin1_code":"24.0",
    "gn:admin2_code":"2280.0",
    "gn:admin3_code":"228001.0",
    "gn:admin4_code":"2470.0",
    "gn:asciiname":"Kolva",
    "gn:country_code":"SE",
    "gn:dem":66,
    "gn:feature_class":"P",
    "gn:feature_code":"PPL",
    "gn:name":"K\u00f6lva",
    "gn:population":0,
    "gn:timezone":"Europe/Stockholm",
    "iso:country":"SE",
    "name:nor_x_preferred":[
        "K\u00f6lva"
    ],
    "name:nor_x_variant":[
        "K\u00f8lva"
    ],
    "wof:name":"Kolva",
    "wof:placetype":"locality"
},
  "geometry": {"coordinates":[17.98222,62.58101],"type":"Point"}
}