{
  "type": "Feature",
  "properties": {
    "gn:admin1_code":"21.0",
    "gn:asciiname":"Persbo",
    "gn:country_code":"SE",
    "gn:dem":55,
    "gn:feature_class":"P",
    "gn:feature_code":"PPL",
    "gn:name":"Persbo",
    "gn:population":0,
    "gn:timezone":"Europe/Stockholm",
    "iso:country":"SE",
    "wof:name":"Persbo",
    "wof:placetype":"locality"
},
  "geometry": {"coordinates":[16.98333,60.03333000000001],"type":"Point"}
}