{
  "type": "Feature",
  "properties": {
    "gn:admin1_code":"28.0",
    "gn:admin2_code":"1460.0",
    "gn:asciiname":"Sodra Kvarnviken",
    "gn:cc2":"SE",
    "gn:country_code":"SE",
    "gn:dem":134,
    "gn:feature_class":"P",
    "gn:feature_code":"PPL",
    "gn:name":"S\u00f6dra Kvarnviken",
    "gn:population":0,
    "gn:timezone":"Europe/Stockholm",
    "iso:country":"SE",
    "name:nor_x_preferred":[
        "S\u00f6dra Kvarnviken"
    ],
    "name:nor_x_variant":[
        "S\u00f8dra Kvarnviken"
    ],
    "name:und_x_variant":[
        "S\u00f6dra Qvarnviken"
    ],
    "wof:name":"Sodra Kvarnviken",
    "wof:placetype":"locality"
},
  "geometry": {"coordinates":[12.16667,59.08333],"type":"Point"}
}