{
  "type": "Feature",
  "properties": {
    "gn:admin1_code":"28.0",
    "gn:admin2_code":"1461.0",
    "gn:asciiname":"Prastgarden",
    "gn:country_code":"SE",
    "gn:dem":53,
    "gn:feature_class":"P",
    "gn:feature_code":"PPL",
    "gn:name":"Pr\u00e4stg\u00e5rden",
    "gn:population":0,
    "gn:timezone":"Europe/Stockholm",
    "iso:country":"SE",
    "wof:name":"Prastgarden",
    "wof:placetype":"locality"
},
  "geometry": {"coordinates":[12.48306,58.56667],"type":"Point"}
}