{
  "type": "Feature",
  "properties": {
    "gn:admin1_code":"9.0",
    "gn:asciiname":"Sodra Flaka",
    "gn:country_code":"SE",
    "gn:dem":134,
    "gn:feature_class":"P",
    "gn:feature_code":"PPL",
    "gn:name":"S\u00f6dra Flaka",
    "gn:population":0,
    "gn:timezone":"Europe/Stockholm",
    "iso:country":"SE",
    "name:nor_x_preferred":[
        "S\u00f6dra Flaka"
    ],
    "name:nor_x_variant":[
        "S\u00f8dra Flaka"
    ],
    "name:und_x_variant":[
        "S\u00f6dra Flaka"
    ],
    "wof:name":"Sodra Flaka",
    "wof:placetype":"locality"
},
  "geometry": {"coordinates":[15.78333,57.83333],"type":"Point"}
}