{
  "type": "Feature",
  "properties": {
    "gn:admin1_code":"14.0",
    "gn:admin2_code":"2510.0",
    "gn:asciiname":"Nautijaur",
    "gn:cc2":"SE",
    "gn:country_code":"SE",
    "gn:dem":346,
    "gn:feature_class":"P",
    "gn:feature_code":"PPL",
    "gn:name":"Nautijaur",
    "gn:population":0,
    "gn:timezone":"Europe/Stockholm",
    "iso:country":"SE",
    "name:smj_x_preferred":[
        "Bidja"
    ],
    "name:und_x_variant":[
        "Nautijaure",
        "Nautejaure",
        "Nautijaur"
    ],
    "wof:name":"Nautijaur",
    "wof:placetype":"locality"
},
  "geometry": {"coordinates":[19.23333,66.90000000000001],"type":"Point"}
}