{
  "type": "Feature",
  "properties": {
    "gn:admin1_code":"7.0",
    "gn:admin2_code":"2313.0",
    "gn:asciiname":"Nackasen",
    "gn:cc2":"SE",
    "gn:country_code":"SE",
    "gn:dem":304,
    "gn:feature_class":"P",
    "gn:feature_code":"PPL",
    "gn:name":"N\u00e4ck\u00e5sen",
    "gn:population":0,
    "gn:timezone":"Europe/Stockholm",
    "iso:country":"SE",
    "name:und_x_variant":[
        "N\u00e4x\u00e5sen",
        "N\u00e4cks\u00e5sen",
        "N\u00e4ck\u00e5sen"
    ],
    "wof:name":"Nackasen",
    "wof:placetype":"locality"
},
  "geometry": {"coordinates":[15.35,64.13333],"type":"Point"}
}