{
  "type": "Feature",
  "properties": {
    "gn:admin1_code":"10.0",
    "gn:admin2_code":"2023.0",
    "gn:asciiname":"Roskknolen",
    "gn:country_code":"SE",
    "gn:dem":350,
    "gn:feature_class":"P",
    "gn:feature_code":"PPL",
    "gn:name":"Roskkn\u00f6len",
    "gn:population":0,
    "gn:timezone":"Europe/Stockholm",
    "iso:country":"SE",
    "name:nor_x_preferred":[
        "Roskkn\u00f6len"
    ],
    "name:nor_x_variant":[
        "Roskkn\u00f8len"
    ],
    "wof:name":"Roskknolen",
    "wof:placetype":"locality"
},
  "geometry": {"coordinates":[13.73333,60.41667],"type":"Point"}
}