{
  "type": "Feature",
  "properties": {
    "gn:admin1_code":"9.0",
    "gn:admin2_code":"862.0",
    "gn:asciiname":"Fiskesjo",
    "gn:country_code":"SE",
    "gn:dem":186,
    "gn:feature_class":"P",
    "gn:feature_code":"PPL",
    "gn:name":"Fiskesj\u00f6",
    "gn:population":0,
    "gn:timezone":"Europe/Stockholm",
    "iso:country":"SE",
    "name:nor_x_preferred":[
        "Fiskesj\u00f6"
    ],
    "name:nor_x_variant":[
        "Fiskesj\u00f8"
    ],
    "wof:name":"Fiskesjo",
    "wof:placetype":"locality"
},
  "geometry": {"coordinates":[15.53333,56.76667],"type":"Point"}
}