{
  "type": "Feature",
  "properties": {
    "gn:admin1_code":"7.0",
    "gn:admin2_code":"2309.0",
    "gn:asciiname":"Forsasen",
    "gn:country_code":"SE",
    "gn:dem":359,
    "gn:feature_class":"P",
    "gn:feature_code":"PPL",
    "gn:name":"Fors\u00e5sen",
    "gn:population":0,
    "gn:timezone":"Europe/Stockholm",
    "iso:country":"SE",
    "wof:name":"Forsasen",
    "wof:placetype":"locality"
},
  "geometry": {"coordinates":[14.71667,63.68333000000001],"type":"Point"}
}