{
  "type": "Feature",
  "properties": {
    "gn:admin1_code":"18.0",
    "gn:admin2_code":"461.0",
    "gn:asciiname":"Ekeberga",
    "gn:country_code":"SE",
    "gn:dem":75,
    "gn:feature_class":"P",
    "gn:feature_code":"PPL",
    "gn:name":"Ekeberga",
    "gn:population":0,
    "gn:timezone":"Europe/Stockholm",
    "iso:country":"SE",
    "wof:name":"Ekeberga",
    "wof:placetype":"locality"
},
  "geometry": {"coordinates":[17.13332999999999,59.18333000000001],"type":"Point"}
}