{
  "type": "Feature",
  "properties": {
    "gn:admin1_code":"24.0",
    "gn:admin2_code":"2262.0",
    "gn:admin3_code":"226201.0",
    "gn:admin4_code":"2501.0",
    "gn:asciiname":"Vivsta",
    "gn:cc2":"SE",
    "gn:country_code":"SE",
    "gn:dem":1,
    "gn:feature_class":"P",
    "gn:feature_code":"PPL",
    "gn:name":"Vivsta",
    "gn:population":0,
    "gn:timezone":"Europe/Stockholm",
    "iso:country":"SE",
    "name:und_x_variant":[
        "Vifsta",
        "Vivstavarv",
        "Wifst",
        "Vivsta"
    ],
    "wof:name":"Vivsta",
    "wof:placetype":"locality"
},
  "geometry": {"coordinates":[17.32836,62.48674000000001],"type":"Point"}
}