{
  "type": "Feature",
  "properties": {
    "gn:admin1_code":"26.0",
    "gn:admin2_code":"188.0",
    "gn:asciiname":"Haverodal",
    "gn:cc2":"SE",
    "gn:country_code":"SE",
    "gn:dem":22,
    "gn:feature_class":"P",
    "gn:feature_code":"PPL",
    "gn:name":"H\u00e4ver\u00f6dal",
    "gn:population":0,
    "gn:timezone":"Europe/Stockholm",
    "iso:country":"SE",
    "name:und_x_variant":[
        "H\u00e4ver\u00f6sund",
        "H\u00e4ver\u00f6dal"
    ],
    "wof:name":"Haverodal",
    "wof:placetype":"locality"
},
  "geometry": {"coordinates":[18.58333,60.03333000000001],"type":"Point"}
}