{
  "type": "Feature",
  "properties": {
    "gn:admin1_code":"18.0",
    "gn:admin2_code":"486.0",
    "gn:asciiname":"Bjorklund",
    "gn:country_code":"SE",
    "gn:dem":57,
    "gn:feature_class":"P",
    "gn:feature_code":"PPL",
    "gn:name":"Bj\u00f6rklund",
    "gn:population":0,
    "gn:timezone":"Europe/Stockholm",
    "iso:country":"SE",
    "name:nor_x_preferred":[
        "Bj\u00f6rklund"
    ],
    "name:nor_x_variant":[
        "Bj\u00f8rklund"
    ],
    "name:und_x_variant":[
        "Bj\u00f6rklund"
    ],
    "wof:name":"Bjorklund",
    "wof:placetype":"locality"
},
  "geometry": {"coordinates":[17.26667,59.21666999999999],"type":"Point"}
}