{
  "type": "Feature",
  "properties": {
    "gn:admin1_code":"22.0",
    "gn:admin2_code":"1766.0",
    "gn:admin3_code":"176605.0",
    "gn:admin4_code":"2161.0",
    "gn:asciiname":"Ostra Berga",
    "gn:country_code":"SE",
    "gn:dem":75,
    "gn:feature_class":"P",
    "gn:feature_code":"PPL",
    "gn:name":"\u00d6stra Berga",
    "gn:population":0,
    "gn:timezone":"Europe/Stockholm",
    "iso:country":"SE",
    "name:nor_x_preferred":[
        "\u00d6stra Berga"
    ],
    "name:nor_x_variant":[
        "\u00d8stra Berga"
    ],
    "wof:name":"Ostra Berga",
    "wof:placetype":"locality"
},
  "geometry": {"coordinates":[13.12978,60.01735],"type":"Point"}
}