{
  "type": "Feature",
  "properties": {
    "gn:admin1_code":"9.0",
    "gn:admin2_code":"840.0",
    "gn:asciiname":"Ryd",
    "gn:country_code":"SE",
    "gn:dem":36,
    "gn:feature_class":"P",
    "gn:feature_code":"PPL",
    "gn:name":"Ryd",
    "gn:population":0,
    "gn:timezone":"Europe/Stockholm",
    "iso:country":"SE",
    "name:ceb_x_preferred":[
        "Ryd"
    ],
    "name:deu_x_preferred":[
        "Ryd"
    ],
    "name:fra_x_preferred":[
        "Ryd"
    ],
    "name:nld_x_preferred":[
        "Ryd"
    ],
    "name:swe_x_preferred":[
        "Ryd"
    ],
    "wof:name":"Ryd",
    "wof:placetype":"locality"
},
  "geometry": {"coordinates":[16.58333,56.73333],"type":"Point"}
}