{
  "type": "Feature",
  "properties": {
    "gn:admin1_code":"24.0",
    "gn:admin2_code":"2260.0",
    "gn:admin3_code":"226004.0",
    "gn:admin4_code":"2502.0",
    "gn:asciiname":"Nordanede",
    "gn:country_code":"SE",
    "gn:dem":157,
    "gn:feature_class":"P",
    "gn:feature_code":"PPL",
    "gn:name":"Nordanede",
    "gn:population":0,
    "gn:timezone":"Europe/Stockholm",
    "iso:country":"SE",
    "wof:name":"Nordanede",
    "wof:placetype":"locality"
},
  "geometry": {"coordinates":[16.42971,62.56139],"type":"Point"}
}