{
  "type": "Feature",
  "properties": {
    "gn:admin1_code":"27.0",
    "gn:admin2_code":"1263.0",
    "gn:asciiname":"Hyltarp",
    "gn:country_code":"SE",
    "gn:dem":37,
    "gn:feature_class":"P",
    "gn:feature_code":"PPL",
    "gn:name":"Hyltarp",
    "gn:population":0,
    "gn:timezone":"Europe/Stockholm",
    "iso:country":"SE",
    "wof:name":"Hyltarp",
    "wof:placetype":"locality"
},
  "geometry": {"coordinates":[13.18333,55.51667],"type":"Point"}
}