{
  "type": "Feature",
  "properties": {
    "gn:admin1_code":"7.0",
    "gn:admin2_code":"2309.0",
    "gn:asciiname":"By",
    "gn:country_code":"SE",
    "gn:dem":300,
    "gn:feature_class":"P",
    "gn:feature_code":"PPL",
    "gn:name":"By",
    "gn:population":0,
    "gn:timezone":"Europe/Stockholm",
    "iso:country":"SE",
    "name:ceb_x_preferred":[
        "By"
    ],
    "name:swe_x_preferred":[
        "By"
    ],
    "wof:name":"By",
    "wof:placetype":"locality"
},
  "geometry": {"coordinates":[14.45,63.23333],"type":"Point"}
}