{
  "type": "Feature",
  "properties": {
    "gn:admin1_code":"28.0",
    "gn:admin2_code":"1419.0",
    "gn:asciiname":"Langekarr",
    "gn:country_code":"SE",
    "gn:dem":31,
    "gn:feature_class":"P",
    "gn:feature_code":"PPL",
    "gn:name":"L\u00e5ngek\u00e4rr",
    "gn:population":0,
    "gn:timezone":"Europe/Stockholm",
    "iso:country":"SE",
    "wof:name":"Langekarr",
    "wof:placetype":"locality"
},
  "geometry": {"coordinates":[11.55,58.03333000000001],"type":"Point"}
}