{
  "type": "Feature",
  "properties": {
    "gn:admin1_code":"10.0",
    "gn:admin2_code":"2062.0",
    "gn:asciiname":"Blecket",
    "gn:country_code":"SE",
    "gn:dem":488,
    "gn:feature_class":"P",
    "gn:feature_code":"PPL",
    "gn:name":"Blecket",
    "gn:population":0,
    "gn:timezone":"Europe/Stockholm",
    "iso:country":"SE",
    "wof:name":"Blecket",
    "wof:placetype":"locality"
},
  "geometry": {"coordinates":[14.33306,61.26667],"type":"Point"}
}