{
  "type": "Feature",
  "properties": {
    "gn:admin1_code":"28.0",
    "gn:admin2_code":"1490.0",
    "gn:asciiname":"Gullestorp",
    "gn:country_code":"SE",
    "gn:dem":260,
    "gn:feature_class":"P",
    "gn:feature_code":"PPL",
    "gn:name":"Gullestorp",
    "gn:population":0,
    "gn:timezone":"Europe/Stockholm",
    "iso:country":"SE",
    "wof:name":"Gullestorp",
    "wof:placetype":"locality"
},
  "geometry": {"coordinates":[13.18333,57.75],"type":"Point"}
}