{
  "type": "Feature",
  "properties": {
    "gn:admin1_code":"28.0",
    "gn:admin2_code":"1490.0",
    "gn:asciiname":"Fagersberg",
    "gn:country_code":"SE",
    "gn:dem":130,
    "gn:feature_class":"P",
    "gn:feature_code":"PPL",
    "gn:name":"Fagersberg",
    "gn:population":0,
    "gn:timezone":"Europe/Stockholm",
    "iso:country":"SE",
    "wof:name":"Fagersberg",
    "wof:placetype":"locality"
},
  "geometry": {"coordinates":[12.86667,57.61666999999999],"type":"Point"}
}