{
  "type": "Feature",
  "properties": {
    "gn:admin1_code":"24.0",
    "gn:admin2_code":"2282.0",
    "gn:admin3_code":"228211.0",
    "gn:admin4_code":"2511.0",
    "gn:asciiname":"Hyndtjarn",
    "gn:country_code":"SE",
    "gn:dem":372,
    "gn:feature_class":"P",
    "gn:feature_code":"PPL",
    "gn:name":"Hyndtj\u00e4rn",
    "gn:population":0,
    "gn:timezone":"Europe/Stockholm",
    "iso:country":"SE",
    "wof:name":"Hyndtjarn",
    "wof:placetype":"locality"
},
  "geometry": {"coordinates":[17.28333,62.98333],"type":"Point"}
}