{
  "type": "Feature",
  "properties": {
    "gn:admin1_code":"7.0",
    "gn:admin2_code":"2303.0",
    "gn:asciiname":"Midskog",
    "gn:country_code":"SE",
    "gn:dem":259,
    "gn:feature_class":"P",
    "gn:feature_code":"PPL",
    "gn:name":"Midskog",
    "gn:population":0,
    "gn:timezone":"Europe/Stockholm",
    "iso:country":"SE",
    "wof:name":"Midskog",
    "wof:placetype":"locality"
},
  "geometry": {"coordinates":[15.23333,63.23333],"type":"Point"}
}