{
  "type": "Feature",
  "properties": {
    "gn:admin1_code":"14.0",
    "gn:admin2_code":"2521.0",
    "gn:asciiname":"Kompelusvaara",
    "gn:cc2":"SE",
    "gn:country_code":"SE",
    "gn:dem":254,
    "gn:feature_class":"P",
    "gn:feature_code":"PPL",
    "gn:name":"Kompelusvaara",
    "gn:population":0,
    "gn:timezone":"Europe/Stockholm",
    "iso:country":"SE",
    "name:und_x_variant":[
        "Kompelusvara",
        "Kompelusvaara"
    ],
    "wof:name":"Kompelusvaara",
    "wof:placetype":"locality"
},
  "geometry": {"coordinates":[22.26667,67.06667],"type":"Point"}
}