{
  "type": "Feature",
  "properties": {
    "gn:admin1_code":"16.0",
    "gn:admin2_code":"512.0",
    "gn:asciiname":"Torpa",
    "gn:country_code":"SE",
    "gn:dem":177,
    "gn:feature_class":"P",
    "gn:feature_code":"PPL",
    "gn:name":"Torpa",
    "gn:population":0,
    "gn:timezone":"Europe/Stockholm",
    "iso:country":"SE",
    "wof:name":"Torpa",
    "wof:placetype":"locality"
},
  "geometry": {"coordinates":[15.13333,57.96666999999999],"type":"Point"}
}