{
  "type": "Feature",
  "properties": {
    "gn:admin1_code":"26.0",
    "gn:admin2_code":"181.0",
    "gn:asciiname":"Svartbro",
    "gn:country_code":"SE",
    "gn:dem":41,
    "gn:feature_class":"P",
    "gn:feature_code":"PPL",
    "gn:name":"Svartbro",
    "gn:population":0,
    "gn:timezone":"Europe/Stockholm",
    "iso:country":"SE",
    "wof:name":"Svartbro",
    "wof:placetype":"locality"
},
  "geometry": {"coordinates":[17.35,59.18333000000001],"type":"Point"}
}