{
  "type": "Feature",
  "properties": {
    "gn:admin1_code":"28.0",
    "gn:admin2_code":"1489.0",
    "gn:asciiname":"Lilla Lo",
    "gn:country_code":"SE",
    "gn:dem":84,
    "gn:feature_class":"P",
    "gn:feature_code":"PPL",
    "gn:name":"Lilla Lo",
    "gn:population":0,
    "gn:timezone":"Europe/Stockholm",
    "iso:country":"SE",
    "wof:name":"Lilla Lo",
    "wof:placetype":"locality"
},
  "geometry": {"coordinates":[12.58333,58.06667],"type":"Point"}
}