{
  "type": "Feature",
  "properties": {
    "gn:admin1_code":"27.0",
    "gn:admin2_code":"1267.0",
    "gn:asciiname":"Jularp",
    "gn:country_code":"SE",
    "gn:dem":99,
    "gn:feature_class":"P",
    "gn:feature_code":"PPL",
    "gn:name":"Jularp",
    "gn:population":0,
    "gn:timezone":"Europe/Stockholm",
    "iso:country":"SE",
    "wof:name":"Jularp",
    "wof:placetype":"locality"
},
  "geometry": {"coordinates":[13.53333,55.95],"type":"Point"}
}