{
  "type": "Feature",
  "properties": {
    "gn:admin1_code":"2.0",
    "gn:admin2_code":"1081.0",
    "gn:asciiname":"Ostra Skorje",
    "gn:country_code":"SE",
    "gn:dem":104,
    "gn:feature_class":"P",
    "gn:feature_code":"PPL",
    "gn:name":"\u00d6stra Sk\u00f6rje",
    "gn:population":0,
    "gn:timezone":"Europe/Stockholm",
    "iso:country":"SE",
    "name:nor_x_preferred":[
        "\u00d6stra Sk\u00f6rje"
    ],
    "name:nor_x_variant":[
        "\u00d8stra Sk\u00f8rje"
    ],
    "wof:name":"Ostra Skorje",
    "wof:placetype":"locality"
},
  "geometry": {"coordinates":[15.13333,56.36666999999999],"type":"Point"}
}