{
  "type": "Feature",
  "properties": {
    "gn:admin1_code":"28.0",
    "gn:admin2_code":"1442.0",
    "gn:asciiname":"Lagmansholm",
    "gn:country_code":"SE",
    "gn:dem":121,
    "gn:feature_class":"P",
    "gn:feature_code":"PPL",
    "gn:name":"Lagmansholm",
    "gn:population":0,
    "gn:timezone":"Europe/Stockholm",
    "iso:country":"SE",
    "wof:name":"Lagmansholm",
    "wof:placetype":"locality"
},
  "geometry": {"coordinates":[12.66667,58.01667],"type":"Point"}
}