{
  "type": "Feature",
  "properties": {
    "gn:admin1_code":"28.0",
    "gn:admin2_code":"1494.0",
    "gn:asciiname":"Skatteg",
    "gn:country_code":"SE",
    "gn:dem":63,
    "gn:feature_class":"P",
    "gn:feature_code":"PPL",
    "gn:name":"Skatteg",
    "gn:population":0,
    "gn:timezone":"Europe/Stockholm",
    "iso:country":"SE",
    "wof:name":"Skatteg",
    "wof:placetype":"locality"
},
  "geometry": {"coordinates":[13.16667,58.58306],"type":"Point"}
}