{
  "type": "Feature",
  "properties": {
    "gn:admin1_code":"3.0",
    "gn:admin2_code":"2161.0",
    "gn:asciiname":"Hedsjo",
    "gn:country_code":"SE",
    "gn:dem":336,
    "gn:feature_class":"P",
    "gn:feature_code":"PPL",
    "gn:name":"Hedsj\u00f6",
    "gn:population":0,
    "gn:timezone":"Europe/Stockholm",
    "iso:country":"SE",
    "name:nor_x_preferred":[
        "Hedsj\u00f6"
    ],
    "name:nor_x_variant":[
        "Hedsj\u00f8"
    ],
    "name:und_x_variant":[
        "Hedsj\u00f6"
    ],
    "wof:name":"Hedsjo",
    "wof:placetype":"locality"
},
  "geometry": {"coordinates":[15.73333,62.28333000000001],"type":"Point"}
}