{
  "type": "Feature",
  "properties": {
    "gn:admin1_code":"8.0",
    "gn:admin2_code":"687.0",
    "gn:asciiname":"Vatinge",
    "gn:country_code":"SE",
    "gn:dem":165,
    "gn:feature_class":"P",
    "gn:feature_code":"PPL",
    "gn:name":"V\u00e4tinge",
    "gn:population":0,
    "gn:timezone":"Europe/Stockholm",
    "iso:country":"SE",
    "wof:name":"Vatinge",
    "wof:placetype":"locality"
},
  "geometry": {"coordinates":[14.85,57.98333],"type":"Point"}
}