{
  "type": "Feature",
  "properties": {
    "gn:admin1_code":"14.0",
    "gn:admin2_code":"2510.0",
    "gn:asciiname":"Skarjakatan",
    "gn:country_code":"SE",
    "gn:dem":831,
    "gn:feature_class":"P",
    "gn:feature_code":"PPL",
    "gn:name":"Skarjak\u00e5tan",
    "gn:population":0,
    "gn:timezone":"Europe/Stockholm",
    "iso:country":"SE",
    "wof:name":"Skarjakatan",
    "wof:placetype":"locality"
},
  "geometry": {"coordinates":[17.61667000000001,67.40000000000001],"type":"Point"}
}