{
  "type": "Feature",
  "properties": {
    "gn:admin1_code":"28.0",
    "gn:asciiname":"Bobygd",
    "gn:country_code":"SE",
    "gn:dem":54,
    "gn:feature_class":"P",
    "gn:feature_code":"PPL",
    "gn:name":"Bobygd",
    "gn:population":0,
    "gn:timezone":"Europe/Stockholm",
    "iso:country":"SE",
    "wof:name":"Bobygd",
    "wof:placetype":"locality"
},
  "geometry": {"coordinates":[12.31667,57.51667],"type":"Point"}
}