{
  "type": "Feature",
  "properties": {
    "gn:admin1_code":"28.0",
    "gn:admin2_code":"1463.0",
    "gn:asciiname":"Limsjobacke",
    "gn:country_code":"SE",
    "gn:dem":81,
    "gn:feature_class":"P",
    "gn:feature_code":"PPL",
    "gn:name":"Limsj\u00f6backe",
    "gn:population":0,
    "gn:timezone":"Europe/Stockholm",
    "iso:country":"SE",
    "name:nor_x_preferred":[
        "Limsj\u00f6backe"
    ],
    "name:nor_x_variant":[
        "Limsj\u00f8backe"
    ],
    "wof:name":"Limsjobacke",
    "wof:placetype":"locality"
},
  "geometry": {"coordinates":[12.78333,57.55],"type":"Point"}
}