{
  "type": "Feature",
  "properties": {
    "gn:admin1_code":"27.0",
    "gn:admin2_code":"1290.0",
    "gn:asciiname":"Horrod",
    "gn:country_code":"SE",
    "gn:dem":125,
    "gn:feature_class":"P",
    "gn:feature_code":"PPL",
    "gn:name":"H\u00f6rr\u00f6d",
    "gn:population":0,
    "gn:timezone":"Europe/Stockholm",
    "iso:country":"SE",
    "name:nor_x_preferred":[
        "H\u00f6rr\u00f6d"
    ],
    "name:nor_x_variant":[
        "H\u00f8rr\u00f8d"
    ],
    "wof:name":"Horrod",
    "wof:placetype":"locality"
},
  "geometry": {"coordinates":[14.03333,55.78333000000001],"type":"Point"}
}