{
  "type": "Feature",
  "properties": {
    "gn:admin1_code":"3.0",
    "gn:admin2_code":"2161.0",
    "gn:asciiname":"Gronas",
    "gn:country_code":"SE",
    "gn:dem":150,
    "gn:feature_class":"P",
    "gn:feature_code":"PPL",
    "gn:name":"Gr\u00f6n\u00e5s",
    "gn:population":0,
    "gn:timezone":"Europe/Stockholm",
    "iso:country":"SE",
    "name:nor_x_preferred":[
        "Gr\u00f6n\u00e5s"
    ],
    "name:nor_x_variant":[
        "Gr\u00f8n\u00e5s"
    ],
    "name:und_x_variant":[
        "Gr\u00f6n\u00e5s"
    ],
    "wof:name":"Gronas",
    "wof:placetype":"locality"
},
  "geometry": {"coordinates":[16.06667,61.68333000000001],"type":"Point"}
}