{
  "type": "Feature",
  "properties": {
    "gn:admin1_code":"8.0",
    "gn:admin2_code":"683.0",
    "gn:asciiname":"Norra Brusas",
    "gn:country_code":"SE",
    "gn:dem":170,
    "gn:feature_class":"P",
    "gn:feature_code":"PPL",
    "gn:name":"Norra Brus\u00e5s",
    "gn:population":0,
    "gn:timezone":"Europe/Stockholm",
    "iso:country":"SE",
    "wof:name":"Norra Brusas",
    "wof:placetype":"locality"
},
  "geometry": {"coordinates":[13.93333,57.11666999999999],"type":"Point"}
}