{
  "type": "Feature",
  "properties": {
    "gn:admin1_code":"28.0",
    "gn:admin2_code":"1419.0",
    "gn:asciiname":"Halsback",
    "gn:cc2":"SE",
    "gn:country_code":"SE",
    "gn:dem":17,
    "gn:feature_class":"P",
    "gn:feature_code":"PPL",
    "gn:name":"Halsb\u00e4ck",
    "gn:population":0,
    "gn:timezone":"Europe/Stockholm",
    "iso:country":"SE",
    "name:und_x_variant":[
        "Norra Hallsb\u00e4ck",
        "Halsb\u00e4ck"
    ],
    "wof:name":"Halsback",
    "wof:placetype":"locality"
},
  "geometry": {"coordinates":[11.53333,58.05],"type":"Point"}
}