{
  "type": "Feature",
  "properties": {
    "gn:admin1_code":"22.0",
    "gn:admin2_code":"1784.0",
    "gn:asciiname":"Finneback",
    "gn:cc2":"SE",
    "gn:country_code":"SE",
    "gn:dem":106,
    "gn:feature_class":"P",
    "gn:feature_code":"PPL",
    "gn:name":"Finneb\u00e4ck",
    "gn:population":0,
    "gn:timezone":"Europe/Stockholm",
    "iso:country":"SE",
    "name:und_x_variant":[
        "Finnb\u00e4ck",
        "Finneb\u00e4ck"
    ],
    "wof:name":"Finneback",
    "wof:placetype":"locality"
},
  "geometry": {"coordinates":[12.95,59.65],"type":"Point"}
}