{
  "type": "Feature",
  "properties": {
    "gn:admin1_code":"3.0",
    "gn:admin2_code":"2184.0",
    "gn:asciiname":"Risange",
    "gn:country_code":"SE",
    "gn:dem":7,
    "gn:feature_class":"P",
    "gn:feature_code":"PPL",
    "gn:name":"Ris\u00e4nge",
    "gn:population":0,
    "gn:timezone":"Europe/Stockholm",
    "iso:country":"SE",
    "wof:name":"Risange",
    "wof:placetype":"locality"
},
  "geometry": {"coordinates":[17.26667,61.81667],"type":"Point"}
}