{
  "type": "Feature",
  "properties": {
    "gn:admin1_code":"27.0",
    "gn:admin2_code":"1287.0",
    "gn:asciiname":"Bronnestad",
    "gn:country_code":"SE",
    "gn:dem":41,
    "gn:feature_class":"P",
    "gn:feature_code":"PPL",
    "gn:name":"Br\u00f6nnestad",
    "gn:population":0,
    "gn:timezone":"Europe/Stockholm",
    "iso:country":"SE",
    "name:nor_x_preferred":[
        "Br\u00f6nnestad"
    ],
    "name:nor_x_variant":[
        "Br\u00f8nnestad"
    ],
    "name:und_x_variant":[
        "Br\u00f6nnestad"
    ],
    "wof:name":"Bronnestad",
    "wof:placetype":"locality"
},
  "geometry": {"coordinates":[13.36667,55.41667],"type":"Point"}
}