{
  "type": "Feature",
  "properties": {
    "gn:admin1_code":"14.0",
    "gn:admin2_code":"2582.0",
    "gn:asciiname":"Ovre Svartla",
    "gn:cc2":"SE",
    "gn:country_code":"SE",
    "gn:dem":51,
    "gn:feature_class":"P",
    "gn:feature_code":"PPL",
    "gn:name":"\u00d6vre Svartl\u00e5",
    "gn:population":0,
    "gn:timezone":"Europe/Stockholm",
    "iso:country":"SE",
    "name:deu_x_preferred":[
        "Svartl\u00e5"
    ],
    "name:fra_x_preferred":[
        "\u00d6vre Svartl\u00e5"
    ],
    "name:nld_x_preferred":[
        "\u00d6vre Svartl\u00e5"
    ],
    "name:nor_x_preferred":[
        "\u00d6vre Svartl\u00e5"
    ],
    "name:nor_x_variant":[
        "\u00d8vre Svartl\u00e5"
    ],
    "name:swe_x_preferred":[
        "Svartl\u00e5"
    ],
    "name:und_x_variant":[
        "\u00d6ver Svartl\u00e5",
        "\u00d6fvre Svartl\u00e5",
        "\u00d6vre Svartl\u00e5"
    ],
    "wof:name":"Ovre Svartla",
    "wof:placetype":"locality"
},
  "geometry": {"coordinates":[21.15,66.01666999999999],"type":"Point"}
}