{
  "type": "Feature",
  "properties": {
    "gn:admin1_code":"24.0",
    "gn:admin2_code":"2281.0",
    "gn:admin3_code":"228110.0",
    "gn:admin4_code":"2481.0",
    "gn:asciiname":"Bjorkon",
    "gn:country_code":"SE",
    "gn:dem":1,
    "gn:feature_class":"P",
    "gn:feature_code":"PPL",
    "gn:name":"Bj\u00f6rk\u00f6n",
    "gn:population":0,
    "gn:timezone":"Europe/Stockholm",
    "iso:country":"SE",
    "name:nor_x_preferred":[
        "Bj\u00f6rk\u00f6n"
    ],
    "name:nor_x_variant":[
        "Bj\u00f8rk\u00f8n"
    ],
    "wof:name":"Bjorkon",
    "wof:placetype":"locality"
},
  "geometry": {"coordinates":[17.54444,62.23444],"type":"Point"}
}