{
  "type": "Feature",
  "properties": {
    "gn:admin1_code":"24",
    "gn:admin2_code":"2262.0",
    "gn:admin3_code":"226201.0",
    "gn:admin4_code":"2501.0",
    "gn:asciiname":"Vaevland",
    "gn:country_code":"SE",
    "gn:dem":51,
    "gn:feature_class":"P",
    "gn:feature_code":"PPL",
    "gn:name":"V\u00e4vland",
    "gn:population":0,
    "gn:timezone":"Europe/Stockholm",
    "iso:country":"SE",
    "wof:name":"Vaevland",
    "wof:placetype":"locality"
},
  "geometry": {"coordinates":[17.29231,62.48067],"type":"Point"}
}