{
  "type": "Feature",
  "properties": {
    "gn:admin1_code":"8.0",
    "gn:admin2_code":"682.0",
    "gn:asciiname":"Paskarp",
    "gn:country_code":"SE",
    "gn:dem":250,
    "gn:feature_class":"P",
    "gn:feature_code":"PPL",
    "gn:name":"P\u00e5skarp",
    "gn:population":0,
    "gn:timezone":"Europe/Stockholm",
    "iso:country":"SE",
    "wof:name":"Paskarp",
    "wof:placetype":"locality"
},
  "geometry": {"coordinates":[14.76781,57.73019],"type":"Point"}
}