{
  "type": "Feature",
  "properties": {
    "gn:admin1_code":"22.0",
    "gn:admin2_code":"1765.0",
    "gn:asciiname":"Sopplanda",
    "gn:country_code":"SE",
    "gn:dem":178,
    "gn:feature_class":"P",
    "gn:feature_code":"PPL",
    "gn:name":"S\u00f6pplanda",
    "gn:population":0,
    "gn:timezone":"Europe/Stockholm",
    "iso:country":"SE",
    "name:nor_x_preferred":[
        "S\u00f6pplanda"
    ],
    "name:nor_x_variant":[
        "S\u00f8pplanda"
    ],
    "name:und_x_variant":[
        "S\u00f6pplanda"
    ],
    "wof:name":"Sopplanda",
    "wof:placetype":"locality"
},
  "geometry": {"coordinates":[12.08333,59.28333000000001],"type":"Point"}
}