{
  "type": "Feature",
  "properties": {
    "gn:admin1_code":"24.0",
    "gn:admin2_code":"2282.0",
    "gn:asciiname":"Norrgallsta",
    "gn:country_code":"SE",
    "gn:dem":127,
    "gn:feature_class":"P",
    "gn:feature_code":"PPL",
    "gn:name":"Norrg\u00e4llsta",
    "gn:population":0,
    "gn:timezone":"Europe/Stockholm",
    "iso:country":"SE",
    "wof:name":"Norrgallsta",
    "wof:placetype":"locality"
},
  "geometry": {"coordinates":[18.33333,63.08333],"type":"Point"}
}