{
  "type": "Feature",
  "properties": {
    "gn:admin1_code":"22.0",
    "gn:admin2_code":"1780.0",
    "gn:asciiname":"Goranstorp",
    "gn:country_code":"SE",
    "gn:dem":103,
    "gn:feature_class":"P",
    "gn:feature_code":"PPL",
    "gn:name":"G\u00f6ranstorp",
    "gn:population":0,
    "gn:timezone":"Europe/Stockholm",
    "iso:country":"SE",
    "name:nor_x_preferred":[
        "G\u00f6ranstorp"
    ],
    "name:nor_x_variant":[
        "G\u00f8ranstorp"
    ],
    "name:und_x_variant":[
        "G\u00f6ranstorp"
    ],
    "wof:name":"Goranstorp",
    "wof:placetype":"locality"
},
  "geometry": {"coordinates":[13.91667,59.51667],"type":"Point"}
}