{
  "type": "Feature",
  "properties": {
    "gn:admin1_code":"23.0",
    "gn:admin2_code":"2482.0",
    "gn:asciiname":"Bodan",
    "gn:country_code":"SE",
    "gn:dem":58,
    "gn:feature_class":"P",
    "gn:feature_code":"PPL",
    "gn:name":"Bodan",
    "gn:population":0,
    "gn:timezone":"Europe/Stockholm",
    "iso:country":"SE",
    "wof:name":"Bodan",
    "wof:placetype":"locality"
},
  "geometry": {"coordinates":[21.28333,64.41667],"type":"Point"}
}