{
  "type": "Feature",
  "properties": {
    "gn:admin1_code":"7.0",
    "gn:admin2_code":"2305.0",
    "gn:asciiname":"Mellgard",
    "gn:country_code":"SE",
    "gn:dem":354,
    "gn:feature_class":"P",
    "gn:feature_code":"PPL",
    "gn:name":"Mellg\u00e5rd",
    "gn:population":0,
    "gn:timezone":"Europe/Stockholm",
    "iso:country":"SE",
    "wof:name":"Mellgard",
    "wof:placetype":"locality"
},
  "geometry": {"coordinates":[15.26667,62.88333000000001],"type":"Point"}
}