{
  "type": "Feature",
  "properties": {
    "gn:admin1_code":"26.0",
    "gn:admin2_code":"181.0",
    "gn:asciiname":"Brunnsang",
    "gn:country_code":"SE",
    "gn:dem":49,
    "gn:feature_class":"P",
    "gn:feature_code":"PPL",
    "gn:name":"Brunns\u00e4ng",
    "gn:population":0,
    "gn:timezone":"Europe/Stockholm",
    "iso:country":"SE",
    "wof:name":"Brunnsang",
    "wof:placetype":"locality"
},
  "geometry": {"coordinates":[17.63332999999999,59.21666999999999],"type":"Point"}
}