{
  "type": "Feature",
  "properties": {
    "gn:admin1_code":"23.0",
    "gn:admin2_code":"2418.0",
    "gn:asciiname":"Fridhem",
    "gn:country_code":"SE",
    "gn:dem":279,
    "gn:feature_class":"P",
    "gn:feature_code":"PPL",
    "gn:name":"Fridhem",
    "gn:population":0,
    "gn:timezone":"Europe/Stockholm",
    "iso:country":"SE",
    "wof:name":"Fridhem",
    "wof:placetype":"locality"
},
  "geometry": {"coordinates":[19.35,65.13333],"type":"Point"}
}