{
  "type": "Feature",
  "properties": {
    "gn:admin1_code":"8.0",
    "gn:admin2_code":"604.0",
    "gn:asciiname":"Vrangsjo",
    "gn:country_code":"SE",
    "gn:dem":252,
    "gn:feature_class":"P",
    "gn:feature_code":"PPL",
    "gn:name":"Vrangsj\u00f6",
    "gn:population":0,
    "gn:timezone":"Europe/Stockholm",
    "iso:country":"SE",
    "name:nor_x_preferred":[
        "Vrangsj\u00f6"
    ],
    "name:nor_x_variant":[
        "Vrangsj\u00f8"
    ],
    "wof:name":"Vrangsjo",
    "wof:placetype":"locality"
},
  "geometry": {"coordinates":[14.88333,57.88333000000001],"type":"Point"}
}