{
  "type": "Feature",
  "properties": {
    "gn:admin1_code":"2.0",
    "gn:admin2_code":"1081.0",
    "gn:asciiname":"Bokenas",
    "gn:country_code":"SE",
    "gn:dem":3,
    "gn:feature_class":"P",
    "gn:feature_code":"PPL",
    "gn:name":"B\u00f6ken\u00e4s",
    "gn:population":0,
    "gn:timezone":"Europe/Stockholm",
    "iso:country":"SE",
    "wof:name":"Bokenas",
    "wof:placetype":"locality"
},
  "geometry": {"coordinates":[15.38333,56.15833000000001],"type":"Point"}
}