{
  "type": "Feature",
  "properties": {
    "gn:admin1_code":"9.0",
    "gn:admin2_code":"885.0",
    "gn:asciiname":"Nedre Bagby",
    "gn:country_code":"SE",
    "gn:dem":17,
    "gn:feature_class":"P",
    "gn:feature_code":"PPL",
    "gn:name":"Nedre B\u00e4gby",
    "gn:population":0,
    "gn:timezone":"Europe/Stockholm",
    "iso:country":"SE",
    "wof:name":"Nedre Bagby",
    "wof:placetype":"locality"
},
  "geometry": {"coordinates":[16.73333,56.76667],"type":"Point"}
}