{
  "type": "Feature",
  "properties": {
    "gn:admin1_code":"28.0",
    "gn:admin2_code":"1401.0",
    "gn:asciiname":"Honekulla",
    "gn:country_code":"SE",
    "gn:dem":94,
    "gn:feature_class":"P",
    "gn:feature_code":"PPL",
    "gn:name":"H\u00f6nekulla",
    "gn:population":0,
    "gn:timezone":"Europe/Stockholm",
    "iso:country":"SE",
    "name:nor_x_preferred":[
        "H\u00f6nekulla"
    ],
    "name:nor_x_variant":[
        "H\u00f8nekulla"
    ],
    "name:und_x_variant":[
        "H\u00f6nekulla"
    ],
    "wof:name":"Honekulla",
    "wof:placetype":"locality"
},
  "geometry": {"coordinates":[12.13333,57.65],"type":"Point"}
}