{
  "type": "Feature",
  "properties": {
    "gn:admin1_code":"28.0",
    "gn:admin2_code":"1482.0",
    "gn:asciiname":"Honerod",
    "gn:cc2":"SE",
    "gn:country_code":"SE",
    "gn:dem":0,
    "gn:feature_class":"P",
    "gn:feature_code":"PPL",
    "gn:name":"Honer\u00f6d",
    "gn:population":0,
    "gn:timezone":"Europe/Stockholm",
    "iso:country":"SE",
    "name:nor_x_preferred":[
        "Honer\u00f6d"
    ],
    "name:nor_x_variant":[
        "Honer\u00f8d"
    ],
    "name:und_x_variant":[
        "Honered",
        "Honer\u00f6d"
    ],
    "wof:name":"Honerod",
    "wof:placetype":"locality"
},
  "geometry": {"coordinates":[12.06667,57.93333000000001],"type":"Point"}
}