{
  "type": "Feature",
  "properties": {
    "gn:admin1_code":"22.0",
    "gn:admin2_code":"1765.0",
    "gn:asciiname":"Navarsviken",
    "gn:cc2":"SE",
    "gn:country_code":"SE",
    "gn:dem":138,
    "gn:feature_class":"P",
    "gn:feature_code":"PPL",
    "gn:name":"Navarsviken",
    "gn:population":0,
    "gn:timezone":"Europe/Stockholm",
    "iso:country":"SE",
    "name:und_x_variant":[
        "Nafvarsviken",
        "Navarsviken"
    ],
    "wof:name":"Navarsviken",
    "wof:placetype":"locality"
},
  "geometry": {"coordinates":[11.85,59.63333000000001],"type":"Point"}
}