{
  "type": "Feature",
  "properties": {
    "gn:admin1_code":"8.0",
    "gn:admin2_code":"682.0",
    "gn:asciiname":"Spexhult",
    "gn:country_code":"SE",
    "gn:dem":309,
    "gn:feature_class":"P",
    "gn:feature_code":"PPL",
    "gn:name":"Spexhult",
    "gn:population":0,
    "gn:timezone":"Europe/Stockholm",
    "iso:country":"SE",
    "wof:name":"Spexhult",
    "wof:placetype":"locality"
},
  "geometry": {"coordinates":[14.68333,57.61666999999999],"type":"Point"}
}