{
  "type": "Feature",
  "properties": {
    "gn:admin1_code":"16.0",
    "gn:admin2_code":"583.0",
    "gn:asciiname":"Bjorkeberg",
    "gn:country_code":"SE",
    "gn:dem":64,
    "gn:feature_class":"P",
    "gn:feature_code":"PPL",
    "gn:name":"Bj\u00f6rkeberg",
    "gn:population":0,
    "gn:timezone":"Europe/Stockholm",
    "iso:country":"SE",
    "name:nor_x_preferred":[
        "Bj\u00f6rkeberg"
    ],
    "name:nor_x_variant":[
        "Bj\u00f8rkeberg"
    ],
    "name:und_x_variant":[
        "Bj\u00f6rkeberg"
    ],
    "wof:name":"Bjorkeberg",
    "wof:placetype":"locality"
},
  "geometry": {"coordinates":[15.38333,58.46666999999999],"type":"Point"}
}