{
  "type": "Feature",
  "properties": {
    "gn:admin1_code":"28.0",
    "gn:admin2_code":"1497.0",
    "gn:asciiname":"Svartan",
    "gn:country_code":"SE",
    "gn:dem":142,
    "gn:feature_class":"P",
    "gn:feature_code":"PPL",
    "gn:name":"Sv\u00e4rtan",
    "gn:population":0,
    "gn:timezone":"Europe/Stockholm",
    "iso:country":"SE",
    "wof:name":"Svartan",
    "wof:placetype":"locality"
},
  "geometry": {"coordinates":[14.25,58.31667],"type":"Point"}
}