{
  "type": "Feature",
  "properties": {
    "gn:country":"SE",
    "gn:fcode":"PPL",
    "gn:population":287,
    "iso:country":"SE",
    "name:ceb_x_preferred":[
        "Musk\u00f6"
    ],
    "name:dan_x_preferred":[
        "Musk\u00f6"
    ],
    "name:deu_x_preferred":[
        "Musk\u00f6"
    ],
    "name:eng_x_preferred":[
        "Musk\u00f6"
    ],
    "name:fin_x_preferred":[
        "Musk\u00f6"
    ],
    "name:fra_x_preferred":[
        "Musk\u00f6"
    ],
    "name:gle_x_preferred":[
        "Musk\u00f6"
    ],
    "name:ita_x_preferred":[
        "Musk\u00f6"
    ],
    "name:lld_x_preferred":[
        "Musk\u00f6"
    ],
    "name:nan_x_preferred":[
        "Musk\u00f6"
    ],
    "name:nds_x_preferred":[
        "Musk\u00f6"
    ],
    "name:nld_x_preferred":[
        "Musk\u00f6"
    ],
    "name:nno_x_preferred":[
        "Musk\u00f6"
    ],
    "name:nob_x_preferred":[
        "Musk\u00f6"
    ],
    "name:nor_x_preferred":[
        "Musk\u00f8"
    ],
    "name:nor_x_variant":[
        "Musk\u00f6"
    ],
    "name:por_x_preferred":[
        "Musk\u00f6"
    ],
    "name:rus_x_preferred":[
        "\u041c\u0443\u0441\u043a\u0451"
    ],
    "name:swe_x_preferred":[
        "Musk\u00f6"
    ],
    "name:zho_x_preferred":[
        "\u7a46\u65af\u514b\u5cf6"
    ],
    "qs_pg:aaroncc":"SE",
    "qs_pg:gn_country":"SE",
    "qs_pg:gn_fcode":"PPL",
    "qs_pg:gn_pop":287,
    "qs_pg:name":"Musk\u00f6",
    "qs_pg:name_adm0":"Sverige",
    "qs_pg:name_adm1":"Stockholms L\u00e4n",
    "qs_pg:photos":299,
    "qs_pg:photos_1k":61,
    "qs_pg:photos_9k":1,
    "qs_pg:photos_9r":4,
    "qs_pg:photos_all":299,
    "qs_pg:photos_sr":5,
    "qs_pg:pop_sr":2,
    "qs_pg:qs_pg_placetype":"locality",
    "qs_pg:qs_pg_placetype_gp":"Town",
    "qs_pg:woe_adm0":23424954,
    "woe:adm0_id":23424954,
    "woe:name_adm0":"Sverige",
    "woe:name_adm1":"Stockholms L\u00e4n",
    "woe:placetype":"Town",
    "wof:name":"Musk\u00f6",
    "wof:placetype":"locality",
    "wof:population":271
},
  "geometry": {"coordinates":[18.13306,58.98306],"type":"Point"}
}