{
  "type": "Feature",
  "properties": {
    "gn:admin1_code":"28.0",
    "gn:admin2_code":"1439.0",
    "gn:asciiname":"Elleno",
    "gn:cc2":"SE",
    "gn:country_code":"SE",
    "gn:dem":90,
    "gn:feature_class":"P",
    "gn:feature_code":"PPL",
    "gn:name":"Ellen\u00f6",
    "gn:population":0,
    "gn:timezone":"Europe/Stockholm",
    "iso:country":"SE",
    "name:nor_x_preferred":[
        "Ellen\u00f6"
    ],
    "name:nor_x_variant":[
        "Ellen\u00f8"
    ],
    "name:und_x_variant":[
        "Elne"
    ],
    "wof:name":"Elleno",
    "wof:placetype":"locality"
},
  "geometry": {"coordinates":[11.95,58.51667],"type":"Point"}
}