{
  "type": "Feature",
  "properties": {
    "gn:admin1_code":"10.0",
    "gn:admin2_code":"2062.0",
    "gn:asciiname":"Hokberget",
    "gn:country_code":"SE",
    "gn:dem":250,
    "gn:feature_class":"P",
    "gn:feature_code":"PPL",
    "gn:name":"H\u00f6kberget",
    "gn:population":0,
    "gn:timezone":"Europe/Stockholm",
    "iso:country":"SE",
    "name:nor_x_preferred":[
        "H\u00f6kberget"
    ],
    "name:nor_x_variant":[
        "H\u00f8kberget"
    ],
    "name:und_x_variant":[
        "H\u00f6kberget"
    ],
    "wof:name":"Hokberget",
    "wof:placetype":"locality"
},
  "geometry": {"coordinates":[14.31667,61.06667],"type":"Point"}
}