{
  "type": "Feature",
  "properties": {
    "gn:admin1_code":"28.0",
    "gn:admin2_code":"1435.0",
    "gn:asciiname":"Varvet",
    "gn:country_code":"SE",
    "gn:dem":10,
    "gn:feature_class":"P",
    "gn:feature_code":"PPL",
    "gn:name":"Varvet",
    "gn:population":0,
    "gn:timezone":"Europe/Stockholm",
    "iso:country":"SE",
    "wof:name":"Varvet",
    "wof:placetype":"locality"
},
  "geometry": {"coordinates":[11.26667,58.53056],"type":"Point"}
}