{
  "type": "Feature",
  "properties": {
    "gn:admin1_code":"21.0",
    "gn:admin2_code":"380.0",
    "gn:asciiname":"Forsby",
    "gn:country_code":"SE",
    "gn:dem":27,
    "gn:feature_class":"P",
    "gn:feature_code":"PPL",
    "gn:name":"Forsby",
    "gn:population":0,
    "gn:timezone":"Europe/Stockholm",
    "iso:country":"SE",
    "name:ceb_x_preferred":[
        "Forsby"
    ],
    "name:ita_x_preferred":[
        "Forsby"
    ],
    "name:nld_x_preferred":[
        "Forsby"
    ],
    "name:nor_x_preferred":[
        "Forsby"
    ],
    "name:swe_x_preferred":[
        "Forsby"
    ],
    "wof:name":"Forsby",
    "wof:placetype":"locality"
},
  "geometry": {"coordinates":[17.48333,60.05],"type":"Point"}
}