{
  "type": "Feature",
  "properties": {
    "gn:admin1_code":"10.0",
    "gn:admin2_code":"2085.0",
    "gn:asciiname":"Palahojden",
    "gn:country_code":"SE",
    "gn:dem":325,
    "gn:feature_class":"P",
    "gn:feature_code":"PPL",
    "gn:name":"Palah\u00f6jden",
    "gn:population":0,
    "gn:timezone":"Europe/Stockholm",
    "iso:country":"SE",
    "name:nor_x_preferred":[
        "Palah\u00f6jden"
    ],
    "name:nor_x_variant":[
        "Palah\u00f8jden"
    ],
    "name:und_x_variant":[
        "Palah\u00f6jden"
    ],
    "wof:name":"Palahojden",
    "wof:placetype":"locality"
},
  "geometry": {"coordinates":[14.68333,60.05],"type":"Point"}
}