{
  "type": "Feature",
  "properties": {
    "gn:admin1_code":"23.0",
    "gn:admin2_code":"2460.0",
    "gn:asciiname":"Gullsjo",
    "gn:country_code":"SE",
    "gn:dem":199,
    "gn:feature_class":"P",
    "gn:feature_code":"PPL",
    "gn:name":"Gullsj\u00f6",
    "gn:population":0,
    "gn:timezone":"Europe/Stockholm",
    "iso:country":"SE",
    "name:nor_x_preferred":[
        "Gullsj\u00f6"
    ],
    "name:nor_x_variant":[
        "Gullsj\u00f8"
    ],
    "name:und_x_variant":[
        "Gullsj\u00f6"
    ],
    "wof:name":"Gullsjo",
    "wof:placetype":"locality"
},
  "geometry": {"coordinates":[19.83333,64.06667],"type":"Point"}
}