{
  "type": "Feature",
  "properties": {
    "gn:admin1_code":"24.0",
    "gn:admin2_code":"2281.0",
    "gn:admin3_code":"228104.0",
    "gn:admin4_code":"2448.0",
    "gn:asciiname":"Rippsand",
    "gn:country_code":"SE",
    "gn:dem":1,
    "gn:feature_class":"P",
    "gn:feature_code":"PPL",
    "gn:name":"Rippsand",
    "gn:population":0,
    "gn:timezone":"Europe/Stockholm",
    "iso:country":"SE",
    "wof:name":"Rippsand",
    "wof:placetype":"locality"
},
  "geometry": {"coordinates":[17.44303,62.35949],"type":"Point"}
}