{
  "type": "Feature",
  "properties": {
    "gn:admin1_code":"14.0",
    "gn:admin2_code":"2506.0",
    "gn:asciiname":"Alla",
    "gn:country_code":"SE",
    "gn:dem":704,
    "gn:feature_class":"P",
    "gn:feature_code":"PPL",
    "gn:name":"All\u00e1",
    "gn:population":0,
    "gn:timezone":"Europe/Stockholm",
    "iso:country":"SE",
    "name:ceb_x_preferred":[
        "Alla"
    ],
    "name:deu_x_preferred":[
        "Alla"
    ],
    "name:fra_x_preferred":[
        "Alla"
    ],
    "name:glg_x_preferred":[
        "Alla"
    ],
    "name:ita_x_preferred":[
        "Alla"
    ],
    "name:rus_x_preferred":[
        "\u0410\u043b\u043b\u0430"
    ],
    "name:smj_x_preferred":[
        "All\u00e1"
    ],
    "name:swe_x_preferred":[
        "Alla"
    ],
    "name:ukr_x_preferred":[
        "\u0410\u043b\u043b\u0430"
    ],
    "name:uzb_x_preferred":[
        "Alla"
    ],
    "name:zho_x_preferred":[
        "\u963f\u62c9"
    ],
    "wof:name":"Alla",
    "wof:placetype":"locality"
},
  "geometry": {"coordinates":[17.42149,66.58674999999999],"type":"Point"}
}