{
  "type": "Feature",
  "properties": {
    "gn:admin1_code":"7.0",
    "gn:admin2_code":"2380.0",
    "gn:asciiname":"Lockne",
    "gn:country_code":"SE",
    "gn:dem":328,
    "gn:feature_class":"P",
    "gn:feature_code":"PPL",
    "gn:name":"Lockne",
    "gn:population":0,
    "gn:timezone":"Europe/Stockholm",
    "iso:country":"SE",
    "wof:name":"Lockne",
    "wof:placetype":"locality"
},
  "geometry": {"coordinates":[14.83333,63.03333000000001],"type":"Point"}
}