{
  "type": "Feature",
  "properties": {
    "gn:admin1_code":"10.0",
    "gn:admin2_code":"2031.0",
    "gn:asciiname":"Ostanvik",
    "gn:country_code":"SE",
    "gn:dem":230,
    "gn:feature_class":"P",
    "gn:feature_code":"PPL",
    "gn:name":"\u00d6stanvik",
    "gn:population":0,
    "gn:timezone":"Europe/Stockholm",
    "iso:country":"SE",
    "name:nor_x_preferred":[
        "\u00d6stanvik"
    ],
    "name:nor_x_variant":[
        "\u00d8stanvik"
    ],
    "wof:name":"Ostanvik",
    "wof:placetype":"locality"
},
  "geometry": {"coordinates":[15.21667,61.16667],"type":"Point"}
}