{
  "type": "Feature",
  "properties": {
    "iso:country":"SE",
    "name:dan_x_preferred":[
        "T\u00e5nebro"
    ],
    "name:deu_x_preferred":[
        "T\u00e5nebro"
    ],
    "name:eng_x_preferred":[
        "T\u00e5nebro"
    ],
    "name:fra_x_preferred":[
        "T\u00e5nebro"
    ],
    "name:nds_x_preferred":[
        "T\u00e5nebro"
    ],
    "name:nld_x_preferred":[
        "T\u00e5nebro"
    ],
    "name:nno_x_preferred":[
        "T\u00e5nebro"
    ],
    "name:nob_x_preferred":[
        "T\u00e5nebro"
    ],
    "name:swe_x_preferred":[
        "T\u00e5nebro"
    ],
    "qs_pg:aaroncc":"SE",
    "qs_pg:name":"T\u00e5nebro",
    "qs_pg:name_adm0":"Sverige",
    "qs_pg:name_adm1":"Sk\u00e5ne L\u00e4n",
    "qs_pg:photos":14,
    "qs_pg:photos_1k":3,
    "qs_pg:photos_9k":1,
    "qs_pg:photos_9r":1,
    "qs_pg:photos_all":14,
    "qs_pg:photos_sr":1,
    "qs_pg:pop_sr":0,
    "qs_pg:qs_pg_placetype":"locality",
    "qs_pg:qs_pg_placetype_gp":"Town",
    "qs_pg:woe_adm0":23424954,
    "woe:adm0_id":23424954,
    "woe:name_adm0":"Sverige",
    "woe:name_adm1":"Sk\u00e5ne L\u00e4n",
    "woe:placetype":"Town",
    "wof:name":"T\u00e5nebro",
    "wof:placetype":"locality"
},
  "geometry": {"coordinates":[13.651,55.4531665],"type":"Point"}
}