{
  "type": "Feature",
  "properties": {
    "gn:admin1_code":"14.0",
    "gn:admin2_code":"2582.0",
    "gn:asciiname":"Flakaberg",
    "gn:country_code":"SE",
    "gn:dem":140,
    "gn:feature_class":"P",
    "gn:feature_code":"PPL",
    "gn:name":"Flakaberg",
    "gn:population":0,
    "gn:timezone":"Europe/Stockholm",
    "iso:country":"SE",
    "name:nld_x_preferred":[
        "Flakaberg"
    ],
    "name:swe_x_preferred":[
        "Flakaberg"
    ],
    "wof:name":"Flakaberg",
    "wof:placetype":"locality"
},
  "geometry": {"coordinates":[21.78333,66.34999999999999],"type":"Point"}
}