{
  "type": "Feature",
  "properties": {
    "gn:admin1_code":"09",
    "gn:admin2_code":"840.0",
    "gn:admin3_code":"84008.0",
    "gn:admin4_code":"866.0",
    "gn:asciiname":"Lilla Smedby",
    "gn:country_code":"SE",
    "gn:dem":36,
    "gn:feature_class":"P",
    "gn:feature_code":"PPL",
    "gn:name":"Lilla Smedby",
    "gn:population":0,
    "gn:timezone":"Europe/Stockholm",
    "iso:country":"SE",
    "wof:name":"Lilla Smedby",
    "wof:placetype":"locality"
},
  "geometry": {"coordinates":[16.42987999999999,56.41591999999999],"type":"Point"}
}