{
  "type": "Feature",
  "properties": {
    "gn:admin1_code":"2.0",
    "gn:admin2_code":"1080.0",
    "gn:asciiname":"Gronadal",
    "gn:country_code":"SE",
    "gn:dem":14,
    "gn:feature_class":"P",
    "gn:feature_code":"PPL",
    "gn:name":"Gr\u00f6nadal",
    "gn:population":0,
    "gn:timezone":"Europe/Stockholm",
    "iso:country":"SE",
    "name:nld_x_preferred":[
        "Gr\u00f6nadal"
    ],
    "name:nor_x_preferred":[
        "Gr\u00f6nadal"
    ],
    "name:nor_x_variant":[
        "Gr\u00f8nadal"
    ],
    "name:swe_x_preferred":[
        "Gr\u00f6nadal"
    ],
    "wof:name":"Gronadal",
    "wof:placetype":"locality"
},
  "geometry": {"coordinates":[15.50833,56.18333000000001],"type":"Point"}
}