{
  "type": "Feature",
  "properties": {
    "gn:admin1_code":"3.0",
    "gn:admin2_code":"2132.0",
    "gn:asciiname":"Kyrkbacken",
    "gn:country_code":"SE",
    "gn:dem":238,
    "gn:feature_class":"P",
    "gn:feature_code":"PPL",
    "gn:name":"Kyrkbacken",
    "gn:population":0,
    "gn:timezone":"Europe/Stockholm",
    "iso:country":"SE",
    "wof:name":"Kyrkbacken",
    "wof:placetype":"locality"
},
  "geometry": {"coordinates":[16.76667,62.11666999999999],"type":"Point"}
}