{
  "type": "Feature",
  "properties": {
    "gn:admin1_code":"23.0",
    "gn:admin2_code":"2417.0",
    "gn:asciiname":"Haraliden",
    "gn:country_code":"SE",
    "gn:dem":306,
    "gn:feature_class":"P",
    "gn:feature_code":"PPL",
    "gn:name":"Haraliden",
    "gn:population":0,
    "gn:timezone":"Europe/Stockholm",
    "iso:country":"SE",
    "wof:name":"Haraliden",
    "wof:placetype":"locality"
},
  "geometry": {"coordinates":[19.68333,65.11667],"type":"Point"}
}