{
  "type": "Feature",
  "properties": {
    "gn:admin1_code":"2.0",
    "gn:admin2_code":"1083.0",
    "gn:asciiname":"Mjallby",
    "gn:country_code":"SE",
    "gn:dem":6,
    "gn:feature_class":"P",
    "gn:feature_code":"PPL",
    "gn:name":"Mj\u00e4llby",
    "gn:population":0,
    "gn:timezone":"Europe/Stockholm",
    "iso:country":"SE",
    "wof:name":"Mjallby",
    "wof:placetype":"locality"
},
  "geometry": {"coordinates":[14.71667,56.05],"type":"Point"}
}