{
  "type": "Feature",
  "properties": {
    "gn:admin1_code":"5.0",
    "gn:asciiname":"Broa",
    "gn:country_code":"SE",
    "gn:dem":4,
    "gn:feature_class":"P",
    "gn:feature_code":"PPL",
    "gn:name":"Broa",
    "gn:population":0,
    "gn:timezone":"Europe/Stockholm",
    "iso:country":"SE",
    "name:fra_x_preferred":[
        "Broa"
    ],
    "name:glg_x_preferred":[
        "Broa"
    ],
    "name:ita_x_preferred":[
        "Broa"
    ],
    "name:kor_x_preferred":[
        "\ube0c\ub85c\uc544"
    ],
    "name:msa_x_preferred":[
        "Broa"
    ],
    "name:por_x_preferred":[
        "Broa"
    ],
    "name:spa_x_preferred":[
        "Broa"
    ],
    "name:zho_x_preferred":[
        "Broa"
    ],
    "wof:name":"Broa",
    "wof:placetype":"locality"
},
  "geometry": {"coordinates":[19.09206,57.86827],"type":"Point"}
}