{
  "type": "Feature",
  "properties": {
    "gn:admin1_code":"5.0",
    "gn:asciiname":"Broa",
    "gn:country_code":"SE",
    "gn:dem":4,
    "gn:feature_class":"P",
    "gn:feature_code":"PPL",
    "gn:name":"Broa",
    "gn:population":0,
    "gn:timezone":"Europe/Stockholm",
    "iso:country":"SE",
    "wof:name":"Broa",
    "wof:placetype":"locality"
},
  "geometry": {"coordinates":[19.09206,57.86827],"type":"Point"}
}