{
  "type": "Feature",
  "properties": {
    "gn:admin1_code":"3.0",
    "gn:admin2_code":"2182.0",
    "gn:asciiname":"Skensta",
    "gn:country_code":"SE",
    "gn:dem":6,
    "gn:feature_class":"P",
    "gn:feature_code":"PPL",
    "gn:name":"Skensta",
    "gn:population":0,
    "gn:timezone":"Europe/Stockholm",
    "iso:country":"SE",
    "wof:name":"Skensta",
    "wof:placetype":"locality"
},
  "geometry": {"coordinates":[17.03333,61.35],"type":"Point"}
}