{
  "type": "Feature",
  "properties": {
    "iso:country":"SE",
    "name:eng_x_preferred":[
        "Tollered"
    ],
    "name:fra_x_preferred":[
        "Tollered"
    ],
    "name:ita_x_preferred":[
        "Tollered"
    ],
    "name:nan_x_preferred":[
        "Tollered"
    ],
    "name:nld_x_preferred":[
        "Tollered"
    ],
    "name:nno_x_preferred":[
        "Tollered"
    ],
    "name:nob_x_preferred":[
        "Tollered"
    ],
    "name:nor_x_preferred":[
        "Tollered"
    ],
    "name:swe_x_preferred":[
        "Tollered"
    ],
    "name:swe_x_variant":[
        "Tollereds"
    ],
    "name:unk_x_variant":[
        "Tollered"
    ],
    "name:zho_min_nan_x_preferred":[
        "Tollered"
    ],
    "qs:gn_adm0_cc":"SE",
    "qs:gn_fcode":"PPL",
    "qs:gn_local":2668423,
    "qs:gn_nam_loc":"Tollered, Lerum, V\u00e4stra G\u00f6talands L\u00e4n, SE",
    "qs:gn_namadm1":"28",
    "qs:gn_name":"Tollered",
    "qs:local_max":1,
    "qs:local_sum":1,
    "qs:localhoods":1,
    "qs:name":"Tollered",
    "qs:name_adm0":"Sverige",
    "qs:name_adm1":"V\u00e4stra G\u00f6talands L\u00e4n",
    "qs:name_adm2":"Lerum",
    "qs:name_local":"Tollered",
    "qs:photo_max":1,
    "qs:photo_sum":1,
    "qs:placetype":"Town",
    "qs:quad_count":1,
    "qs:woe_adm0":23424954,
    "qs:woe_adm1":20070562,
    "qs:woe_adm2":12587208,
    "qs:woe_lau":0,
    "qs:woe_local":907612,
    "qs:woe_ver":"7.10.0",
    "wd:wordcount":47,
    "wof:lang":[
        "swe"
    ],
    "wof:name":"Tollered",
    "wof:placetype":"neighbourhood"
},
  "geometry": {"coordinates":[12.433777,57.814041],"type":"Point"}
}