{
  "type": "Feature",
  "properties": {
    "gn:gn_country":"SE",
    "gn:gn_fcode":"PPL",
    "gn:gn_pop":0,
    "iso:country":"SE",
    "name:deu_x_preferred":[
        "Bramstorp"
    ],
    "name:eng_x_preferred":[
        "Bramstorp"
    ],
    "name:fin_x_preferred":[
        "Bramstorp"
    ],
    "name:nld_x_preferred":[
        "Bramstorp"
    ],
    "name:swe_x_preferred":[
        "Bramstorp"
    ],
    "qs_pg:aaroncc":"SE",
    "qs_pg:gn_country":"SE",
    "qs_pg:gn_fcode":"PPL",
    "qs_pg:gn_pop":0,
    "qs_pg:name":"Bramstorp",
    "qs_pg:name_adm0":"Sverige",
    "qs_pg:name_adm1":"Kronobergs L\u00e4n",
    "qs_pg:photos":44,
    "qs_pg:photos_1k":9,
    "qs_pg:photos_9k":1,
    "qs_pg:photos_9r":2,
    "qs_pg:photos_all":44,
    "qs_pg:photos_sr":2,
    "qs_pg:pop_sr":0,
    "qs_pg:qs_pg_placetype":"locality",
    "qs_pg:qs_pg_placetype_gp":"Town",
    "qs_pg:woe_adm0":23424954,
    "woe:adm0_id":23424954,
    "woe:name_adm0":"Sverige",
    "woe:name_adm1":"Kronobergs L\u00e4n",
    "woe:placetype":"Town",
    "wof:name":"Bramstorp",
    "wof:placetype":"locality"
},
  "geometry": {"coordinates":[14.86667,56.81667],"type":"Point"}
}