{
  "type": "Feature",
  "properties": {
    "gn:admin1_code":"22.0",
    "gn:admin2_code":"1782.0",
    "gn:asciiname":"Nyhyttan",
    "gn:country_code":"SE",
    "gn:dem":225,
    "gn:feature_class":"P",
    "gn:feature_code":"PPL",
    "gn:name":"Nyhyttan",
    "gn:population":0,
    "gn:timezone":"Europe/Stockholm",
    "iso:country":"SE",
    "wof:name":"Nyhyttan",
    "wof:placetype":"locality"
},
  "geometry": {"coordinates":[14.23333,59.71666999999999],"type":"Point"}
}