{
  "type": "Feature",
  "properties": {
    "gn:admin1_code":"9.0",
    "gn:admin2_code":"881.0",
    "gn:asciiname":"Toresbo",
    "gn:cc2":"SE",
    "gn:country_code":"SE",
    "gn:dem":103,
    "gn:feature_class":"P",
    "gn:feature_code":"PPL",
    "gn:name":"Toresbo",
    "gn:population":0,
    "gn:timezone":"Europe/Stockholm",
    "iso:country":"SE",
    "name:und_x_variant":[
        "Torsbo",
        "Toresbo"
    ],
    "wof:name":"Toresbo",
    "wof:placetype":"locality"
},
  "geometry": {"coordinates":[15.78333,56.68333000000001],"type":"Point"}
}