{
  "type": "Feature",
  "properties": {
    "gn:admin1_code":"16.0",
    "gn:admin2_code":"582.0",
    "gn:asciiname":"Udden",
    "gn:country_code":"SE",
    "gn:dem":45,
    "gn:feature_class":"P",
    "gn:feature_code":"PPL",
    "gn:name":"Udden",
    "gn:population":0,
    "gn:timezone":"Europe/Stockholm",
    "iso:country":"SE",
    "wof:name":"Udden",
    "wof:placetype":"locality"
},
  "geometry": {"coordinates":[16.46667,58.45],"type":"Point"}
}