{
  "type": "Feature",
  "properties": {
    "gn:admin1_code":"2.0",
    "gn:admin2_code":"1081.0",
    "gn:asciiname":"Oljehult",
    "gn:country_code":"SE",
    "gn:dem":123,
    "gn:feature_class":"P",
    "gn:feature_code":"PPL",
    "gn:name":"\u00d6ljehult",
    "gn:population":0,
    "gn:timezone":"Europe/Stockholm",
    "iso:country":"SE",
    "name:nor_x_preferred":[
        "\u00d6ljehult"
    ],
    "name:nor_x_variant":[
        "\u00d8ljehult"
    ],
    "name:und_x_variant":[
        "\u00d6ljehult"
    ],
    "wof:name":"Oljehult",
    "wof:placetype":"locality"
},
  "geometry": {"coordinates":[15.05,56.41667],"type":"Point"}
}