{
  "type": "Feature",
  "properties": {
    "gn:admin1_code":"28.0",
    "gn:admin2_code":"1419.0",
    "gn:asciiname":"Batevik",
    "gn:country_code":"SE",
    "gn:dem":23,
    "gn:feature_class":"P",
    "gn:feature_code":"PPL",
    "gn:name":"B\u00e5tevik",
    "gn:population":0,
    "gn:timezone":"Europe/Stockholm",
    "iso:country":"SE",
    "wof:name":"Batevik",
    "wof:placetype":"locality"
},
  "geometry": {"coordinates":[11.60833,57.93889],"type":"Point"}
}