{
  "type": "Feature",
  "properties": {
    "gn:country":"SE",
    "iso:country":"SE",
    "qs_pg:aaroncc":"SE",
    "qs_pg:gn_country":"SE",
    "qs_pg:name":"Lackevik",
    "qs_pg:name_adm0":"Sverige",
    "qs_pg:name_adm1":"Uppsala L\u00e4n",
    "qs_pg:photos":63,
    "qs_pg:photos_1k":13,
    "qs_pg:photos_9k":1,
    "qs_pg:photos_9r":2,
    "qs_pg:photos_all":63,
    "qs_pg:photos_sr":2,
    "qs_pg:pop_sr":0,
    "qs_pg:qs_pg_placetype":"locality",
    "qs_pg:qs_pg_placetype_gp":"Town",
    "qs_pg:woe_adm0":23424954,
    "woe:adm0_id":23424954,
    "woe:name_adm0":"Sverige",
    "woe:name_adm1":"Uppsala L\u00e4n",
    "woe:placetype":"Town",
    "wof:name":"Lackevik",
    "wof:placetype":"locality"
},
  "geometry": {"coordinates":[18.604692,60.254184],"type":"Point"}
}