{
  "type": "Feature",
  "properties": {
    "gn:admin1_code":"15.0",
    "gn:admin2_code":"1883.0",
    "gn:asciiname":"Fiskbo",
    "gn:country_code":"SE",
    "gn:dem":161,
    "gn:feature_class":"P",
    "gn:feature_code":"PPL",
    "gn:name":"Fiskbo",
    "gn:population":0,
    "gn:timezone":"Europe/Stockholm",
    "iso:country":"SE",
    "wof:name":"Fiskbo",
    "wof:placetype":"locality"
},
  "geometry": {"coordinates":[14.51667,59.43333000000001],"type":"Point"}
}