{
  "type": "Feature",
  "properties": {
    "gn:admin1_code":"22.0",
    "gn:admin2_code":"1785.0",
    "gn:asciiname":"Rullan",
    "gn:country_code":"SE",
    "gn:dem":226,
    "gn:feature_class":"P",
    "gn:feature_code":"PPL",
    "gn:name":"Rullan",
    "gn:population":0,
    "gn:timezone":"Europe/Stockholm",
    "iso:country":"SE",
    "wof:name":"Rullan",
    "wof:placetype":"locality"
},
  "geometry": {"coordinates":[12.55,59.28333000000001],"type":"Point"}
}