{
  "type": "Feature",
  "properties": {
    "gn:admin1_code":"16.0",
    "gn:admin2_code":"560.0",
    "gn:asciiname":"Skvathult",
    "gn:country_code":"SE",
    "gn:dem":184,
    "gn:feature_class":"P",
    "gn:feature_code":"PPL",
    "gn:name":"Skvathult",
    "gn:population":0,
    "gn:timezone":"Europe/Stockholm",
    "iso:country":"SE",
    "wof:name":"Skvathult",
    "wof:placetype":"locality"
},
  "geometry": {"coordinates":[15.15,58.15],"type":"Point"}
}