{
  "type": "Feature",
  "properties": {
    "gn:country":"SE",
    "gn:fcode":"PPL",
    "gn:population":241,
    "iso:country":"SE",
    "name:ita_x_preferred":[
        "B\u00e4ckebo"
    ],
    "name:nld_x_preferred":[
        "B\u00e4ckebo"
    ],
    "name:nno_x_preferred":[
        "B\u00e4ckebo"
    ],
    "name:nor_x_preferred":[
        "B\u00e4ckebo"
    ],
    "name:swe_x_preferred":[
        "B\u00e4ckebo"
    ],
    "qs_pg:aaroncc":"SE",
    "qs_pg:gn_country":"SE",
    "qs_pg:gn_fcode":"PPL",
    "qs_pg:gn_pop":241,
    "qs_pg:name":"B\u00e4ckebo",
    "qs_pg:photos_9r":0,
    "qs_pg:photos_sr":0,
    "qs_pg:pop_sr":2,
    "qs_pg:qs_pg_placetype":"locality",
    "wof:name":"B\u00e4ckebo",
    "wof:placetype":"locality",
    "wof:population":241
},
  "geometry": {"coordinates":[15.98333,61.88333],"type":"Point"}
}