{
  "type": "Feature",
  "properties": {
    "gn:admin1_code":"15.0",
    "gn:admin2_code":"1880.0",
    "gn:asciiname":"Hore",
    "gn:country_code":"SE",
    "gn:dem":49,
    "gn:feature_class":"P",
    "gn:feature_code":"PPL",
    "gn:name":"H\u00f6re",
    "gn:population":0,
    "gn:timezone":"Europe/Stockholm",
    "iso:country":"SE",
    "name:nor_x_preferred":[
        "H\u00f6re"
    ],
    "name:nor_x_variant":[
        "H\u00f8re"
    ],
    "name:und_x_variant":[
        "H\u00f6re"
    ],
    "wof:name":"Hore",
    "wof:placetype":"locality"
},
  "geometry": {"coordinates":[15.41667,59.13333000000001],"type":"Point"}
}