{
  "type": "Feature",
  "properties": {
    "gn:admin1_code":"24.0",
    "gn:admin2_code":"2281.0",
    "gn:admin3_code":"228110.0",
    "gn:admin4_code":"2481.0",
    "gn:asciiname":"Badarna",
    "gn:country_code":"SE",
    "gn:dem":1,
    "gn:feature_class":"P",
    "gn:feature_code":"PPL",
    "gn:name":"B\u00e5darna",
    "gn:population":0,
    "gn:timezone":"Europe/Stockholm",
    "iso:country":"SE",
    "name:swe_x_preferred":[
        "Badarna"
    ],
    "wof:name":"Badarna",
    "wof:placetype":"locality"
},
  "geometry": {"coordinates":[17.44306,62.31583000000001],"type":"Point"}
}