{
  "type": "Feature",
  "properties": {
    "gn:admin1_code":"8.0",
    "gn:asciiname":"Hokalt",
    "gn:cc2":"SE",
    "gn:country_code":"SE",
    "gn:dem":170,
    "gn:feature_class":"P",
    "gn:feature_code":"PPL",
    "gn:name":"Hokalt",
    "gn:population":0,
    "gn:timezone":"Europe/Stockholm",
    "iso:country":"SE",
    "name:und_x_variant":[
        "Hokhult",
        "Hokalt"
    ],
    "wof:name":"Hokalt",
    "wof:placetype":"locality"
},
  "geometry": {"coordinates":[13.41667,57.06667],"type":"Point"}
}