{
  "type": "Feature",
  "properties": {
    "gn:country":"SE",
    "gn:fcode":"PPL",
    "gn:population":291,
    "iso:country":"SE",
    "name:ceb_x_preferred":[
        "\u00d6stra S\u00f6nnarsl\u00f6v"
    ],
    "name:eng_x_preferred":[
        "\u00d6stra S\u00f6nnarsl\u00f6v"
    ],
    "name:fra_x_preferred":[
        "\u00d6stra S\u00f6nnarsl\u00f6v"
    ],
    "name:ita_x_preferred":[
        "\u00d6stra S\u00f6nnarsl\u00f6v"
    ],
    "name:nan_x_preferred":[
        "\u00d6stra S\u00f6nnarsl\u00f6v"
    ],
    "name:nld_x_preferred":[
        "\u00d6stra S\u00f6nnarsl\u00f6v"
    ],
    "name:nno_x_preferred":[
        "\u00d6stra S\u00f6nnarsl\u00f6v"
    ],
    "name:nob_x_preferred":[
        "\u00d6stra S\u00f6nnarsl\u00f6v"
    ],
    "name:nor_x_preferred":[
        "\u00d8stra S\u00f8nnarsl\u00f8v"
    ],
    "name:nor_x_variant":[
        "\u00d6stra S\u00f6nnarsl\u00f6v"
    ],
    "name:swe_x_preferred":[
        "\u00d6stra S\u00f6nnarsl\u00f6v"
    ],
    "qs_pg:aaroncc":"SE",
    "qs_pg:gn_country":"SE",
    "qs_pg:gn_fcode":"PPL",
    "qs_pg:gn_pop":291,
    "qs_pg:name":"\u00d6stra S\u00f6nnarsl\u00f6v",
    "qs_pg:name_adm0":"Sverige",
    "qs_pg:name_adm1":"Sk\u00e5ne L\u00e4n",
    "qs_pg:photos":62,
    "qs_pg:photos_1k":13,
    "qs_pg:photos_9k":1,
    "qs_pg:photos_9r":2,
    "qs_pg:photos_all":62,
    "qs_pg:photos_sr":2,
    "qs_pg:pop_sr":2,
    "qs_pg:qs_pg_placetype":"locality",
    "qs_pg:qs_pg_placetype_gp":"Town",
    "qs_pg:woe_adm0":23424954,
    "woe:adm0_id":23424954,
    "woe:name_adm0":"Sverige",
    "woe:name_adm1":"Sk\u00e5ne L\u00e4n",
    "woe:placetype":"Town",
    "wof:name":"\u00d6stra S\u00f6nnarsl\u00f6v",
    "wof:placetype":"locality",
    "wof:population":265
},
  "geometry": {"coordinates":[14.01667,55.88333],"type":"Point"}
}