{
  "type": "Feature",
  "properties": {
    "gn:admin1_code":"9.0",
    "gn:asciiname":"Norra Runno",
    "gn:cc2":"SE",
    "gn:country_code":"SE",
    "gn:dem":-9999,
    "gn:feature_class":"P",
    "gn:feature_code":"PPL",
    "gn:name":"Norra Runn\u00f6",
    "gn:population":0,
    "gn:timezone":"Europe/Stockholm",
    "iso:country":"SE",
    "name:nor_x_preferred":[
        "Norra Runn\u00f6"
    ],
    "name:nor_x_variant":[
        "Norra Runn\u00f8"
    ],
    "name:und_x_variant":[
        "Runn\u00f6"
    ],
    "wof:name":"Norra Runno",
    "wof:placetype":"locality"
},
  "geometry": {"coordinates":[16.51667,57.16667],"type":"Point"}
}