{
  "type": "Feature",
  "properties": {
    "gn:admin1_code":"18.0",
    "gn:admin2_code":"484.0",
    "gn:asciiname":"Vangso",
    "gn:country_code":"SE",
    "gn:dem":37,
    "gn:feature_class":"P",
    "gn:feature_code":"PPL",
    "gn:name":"V\u00e5ngs\u00f6",
    "gn:population":0,
    "gn:timezone":"Europe/Stockholm",
    "iso:country":"SE",
    "name:nor_x_preferred":[
        "V\u00e5ngs\u00f6"
    ],
    "name:nor_x_variant":[
        "V\u00e5ngs\u00f8"
    ],
    "wof:name":"Vangso",
    "wof:placetype":"locality"
},
  "geometry": {"coordinates":[16.08333,59.26667],"type":"Point"}
}