{
  "type": "Feature",
  "properties": {
    "gn:admin1_code":"21.0",
    "gn:admin2_code":"381.0",
    "gn:asciiname":"Mosta",
    "gn:country_code":"SE",
    "gn:dem":28,
    "gn:feature_class":"P",
    "gn:feature_code":"PPL",
    "gn:name":"Mosta",
    "gn:population":0,
    "gn:timezone":"Europe/Stockholm",
    "iso:country":"SE",
    "name:bul_x_preferred":[
        "\u041c\u043e\u0441\u0442\u0430"
    ],
    "name:cat_x_preferred":[
        "Mosta"
    ],
    "name:ceb_x_preferred":[
        "Mosta"
    ],
    "name:ces_x_preferred":[
        "Mosta"
    ],
    "name:che_x_preferred":[
        "\u041c\u043e\u0441\u0442\u0430"
    ],
    "name:ckb_x_preferred":[
        "\u0645\u06c6\u0633\u062a\u0627"
    ],
    "name:deu_x_preferred":[
        "Mosta"
    ],
    "name:epo_x_preferred":[
        "Mosta"
    ],
    "name:eus_x_preferred":[
        "Mosta"
    ],
    "name:fas_x_preferred":[
        "\u0645\u0648\u0633\u062a\u0627"
    ],
    "name:fra_x_preferred":[
        "Il-Mosta"
    ],
    "name:hrv_x_preferred":[
        "Mosta"
    ],
    "name:hun_x_preferred":[
        "Mosta"
    ],
    "name:hye_x_preferred":[
        "\u0544\u0578\u057d\u057f\u0561"
    ],
    "name:ind_x_preferred":[
        "Mosta"
    ],
    "name:ita_x_preferred":[
        "Mosta"
    ],
    "name:jpn_x_preferred":[
        "\u30e2\u30b9\u30bf"
    ],
    "name:kor_x_preferred":[
        "\ubaa8\uc2a4\ud0c0"
    ],
    "name:lit_x_preferred":[
        "Mosta"
    ],
    "name:mlt_x_preferred":[
        "Mosta"
    ],
    "name:nld_x_preferred":[
        "Mosta"
    ],
    "name:nno_x_preferred":[
        "Mosta"
    ],
    "name:nor_x_preferred":[
        "Mosta"
    ],
    "name:pol_x_preferred":[
        "Mosta"
    ],
    "name:por_x_preferred":[
        "Mosta"
    ],
    "name:rus_x_preferred":[
        "\u041c\u043e\u0441\u0442\u0430"
    ],
    "name:scn_x_preferred":[
        "Mosta"
    ],
    "name:slv_x_preferred":[
        "Mosta"
    ],
    "name:sme_x_preferred":[
        "Mosta"
    ],
    "name:spa_x_preferred":[
        "Mosta"
    ],
    "name:swe_x_preferred":[
        "Mosta"
    ],
    "name:urd_x_preferred":[
        "\u0645\u0648\u0633\u062a\u0627"
    ],
    "name:vol_x_preferred":[
        "Mosta"
    ],
    "name:xmf_x_preferred":[
        "\u10db\u10dd\u10e1\u10e2\u10d0"
    ],
    "name:zho_x_preferred":[
        "\u83ab\u65af\u5854"
    ],
    "wof:name":"Mosta",
    "wof:placetype":"locality"
},
  "geometry": {"coordinates":[17.23333,59.75],"type":"Point"}
}