{
  "type": "Feature",
  "properties": {
    "gn:admin1_code":"15.0",
    "gn:admin2_code":"1880.0",
    "gn:asciiname":"Aby",
    "gn:country_code":"SE",
    "gn:dem":52,
    "gn:feature_class":"P",
    "gn:feature_code":"PPL",
    "gn:name":"\u00c5by",
    "gn:population":0,
    "gn:timezone":"Europe/Stockholm",
    "iso:country":"SE",
    "name:cym_x_preferred":[
        "Aby"
    ],
    "name:pol_x_preferred":[
        "Aby"
    ],
    "wof:name":"Aby",
    "wof:placetype":"locality"
},
  "geometry": {"coordinates":[15.21667,59.36666999999999],"type":"Point"}
}