{
  "type": "Feature",
  "properties": {
    "gn:admin1_code":"10.0",
    "gn:admin2_code":"2039.0",
    "gn:asciiname":"Skinnarbodarna",
    "gn:country_code":"SE",
    "gn:dem":381,
    "gn:feature_class":"P",
    "gn:feature_code":"PPL",
    "gn:name":"Skinnarbodarna",
    "gn:population":0,
    "gn:timezone":"Europe/Stockholm",
    "iso:country":"SE",
    "wof:name":"Skinnarbodarna",
    "wof:placetype":"locality"
},
  "geometry": {"coordinates":[14.18306,61.18306],"type":"Point"}
}