{
  "type": "Feature",
  "properties": {
    "gn:admin1_code":"9.0",
    "gn:admin2_code":"821.0",
    "gn:asciiname":"Staby",
    "gn:country_code":"SE",
    "gn:dem":95,
    "gn:feature_class":"P",
    "gn:feature_code":"PPL",
    "gn:name":"Staby",
    "gn:population":0,
    "gn:timezone":"Europe/Stockholm",
    "iso:country":"SE",
    "wof:name":"Staby",
    "wof:placetype":"locality"
},
  "geometry": {"coordinates":[16.01667,57.15],"type":"Point"}
}