{
  "type": "Feature",
  "properties": {
    "gn:admin1_code":"10.0",
    "gn:admin2_code":"2029.0",
    "gn:asciiname":"Halgnas",
    "gn:country_code":"SE",
    "gn:dem":167,
    "gn:feature_class":"P",
    "gn:feature_code":"PPL",
    "gn:name":"H\u00e4lgn\u00e4s",
    "gn:population":0,
    "gn:timezone":"Europe/Stockholm",
    "iso:country":"SE",
    "wof:name":"Halgnas",
    "wof:placetype":"locality"
},
  "geometry": {"coordinates":[15.15,60.66667],"type":"Point"}
}