{
  "type": "Feature",
  "properties": {
    "gn:admin1_code":"12.0",
    "gn:admin2_code":"764.0",
    "gn:asciiname":"Hulevik",
    "gn:cc2":"SE",
    "gn:country_code":"SE",
    "gn:dem":184,
    "gn:feature_class":"P",
    "gn:feature_code":"PPL",
    "gn:name":"Hulevik",
    "gn:population":0,
    "gn:timezone":"Europe/Stockholm",
    "iso:country":"SE",
    "name:und_x_variant":[
        "Hullevik",
        "Hulevik"
    ],
    "wof:name":"Hulevik",
    "wof:placetype":"locality"
},
  "geometry": {"coordinates":[14.38333,57.08333],"type":"Point"}
}