{
  "type": "Feature",
  "properties": {
    "gn:admin1_code":"7.0",
    "gn:admin2_code":"2303.0",
    "gn:asciiname":"Lien",
    "gn:country_code":"SE",
    "gn:dem":124,
    "gn:feature_class":"P",
    "gn:feature_code":"PPL",
    "gn:name":"Lien",
    "gn:population":0,
    "gn:timezone":"Europe/Stockholm",
    "iso:country":"SE",
    "name:ara_x_preferred":[
        "\u062d\u0642 \u0627\u0644\u062d\u062c\u0632"
    ],
    "name:ces_x_preferred":[
        "Zadr\u017eovac\u00ed pr\u00e1vo"
    ],
    "name:deu_x_preferred":[
        "Zur\u00fcckbehaltungsrecht"
    ],
    "name:fas_x_preferred":[
        "\u062d\u0642 \u062d\u0628\u0633"
    ],
    "name:guj_x_preferred":[
        "\u0aaa\u0ac2\u0ab0\u0acd\u0ab5\u0abe\u0aa7\u0abf\u0a95\u0abe\u0ab0"
    ],
    "name:heb_x_preferred":[
        "\u05e2\u05d9\u05db\u05d1\u05d5\u05df"
    ],
    "name:jpn_x_preferred":[
        "\u30ea\u30fc\u30a8\u30f3"
    ],
    "name:nld_x_preferred":[
        "Retentierecht"
    ],
    "name:pol_x_preferred":[
        "Prawo zatrzymania"
    ],
    "wof:name":"Lien",
    "wof:placetype":"locality"
},
  "geometry": {"coordinates":[16.46667,63.08333],"type":"Point"}
}