{
  "type": "Feature",
  "properties": {
    "gn:admin1_code":"7.0",
    "gn:admin2_code":"2303.0",
    "gn:asciiname":"Lien",
    "gn:country_code":"SE",
    "gn:dem":124,
    "gn:feature_class":"P",
    "gn:feature_code":"PPL",
    "gn:name":"Lien",
    "gn:population":0,
    "gn:timezone":"Europe/Stockholm",
    "iso:country":"SE",
    "wof:name":"Lien",
    "wof:placetype":"locality"
},
  "geometry": {"coordinates":[16.46667,63.08333],"type":"Point"}
}