{
  "type": "Feature",
  "properties": {
    "gn:admin1_code":"27.0",
    "gn:admin2_code":"1287.0",
    "gn:admin3_code":"128721.0",
    "gn:admin4_code":"1292.0",
    "gn:asciiname":"Beddinge Lage",
    "gn:country_code":"SE",
    "gn:dem":5,
    "gn:feature_class":"P",
    "gn:feature_code":"PPL",
    "gn:name":"Beddinge L\u00e4ge",
    "gn:population":0,
    "gn:timezone":"Europe/Stockholm",
    "iso:country":"SE",
    "wof:name":"Beddinge Lage",
    "wof:placetype":"locality"
},
  "geometry": {"coordinates":[13.4125,55.35607],"type":"Point"}
}