{
  "type": "Feature",
  "properties": {
    "gn:admin1_code":"22.0",
    "gn:admin2_code":"1785.0",
    "gn:asciiname":"Hult",
    "gn:country_code":"SE",
    "gn:dem":68,
    "gn:feature_class":"P",
    "gn:feature_code":"PPL",
    "gn:name":"Hult",
    "gn:population":0,
    "gn:timezone":"Europe/Stockholm",
    "iso:country":"SE",
    "wof:name":"Hult",
    "wof:placetype":"locality"
},
  "geometry": {"coordinates":[13.16667,58.96666999999999],"type":"Point"}
}