{
  "type": "Feature",
  "properties": {
    "gn:admin1_code":"22.0",
    "gn:admin2_code":"1785.0",
    "gn:asciiname":"Hult",
    "gn:country_code":"SE",
    "gn:dem":68,
    "gn:feature_class":"P",
    "gn:feature_code":"PPL",
    "gn:name":"Hult",
    "gn:population":0,
    "gn:timezone":"Europe/Stockholm",
    "iso:country":"SE",
    "name:ceb_x_preferred":[
        "Hult"
    ],
    "name:deu_x_preferred":[
        "Hult"
    ],
    "name:fin_x_preferred":[
        "Hult"
    ],
    "name:fra_x_preferred":[
        "Hult"
    ],
    "name:nld_x_preferred":[
        "Hult"
    ],
    "name:swe_x_preferred":[
        "Hult"
    ],
    "name:zho_x_preferred":[
        "\u970d\u5c14\u7279"
    ],
    "wof:name":"Hult",
    "wof:placetype":"locality"
},
  "geometry": {"coordinates":[13.16667,58.96666999999999],"type":"Point"}
}