{
  "type": "Feature",
  "properties": {
    "iso:country":"SE",
    "name:dan_x_preferred":[
        "Storahults strand"
    ],
    "name:dut_x_preferred":[
        "Storahults strand"
    ],
    "name:eng_x_preferred":[
        "Storahults strand"
    ],
    "name:fre_x_preferred":[
        "Storahults strand"
    ],
    "name:ger_x_preferred":[
        "Storahults strand"
    ],
    "name:nds_x_preferred":[
        "Storahults strand"
    ],
    "name:nno_x_preferred":[
        "Storahults strand"
    ],
    "name:nob_x_preferred":[
        "Storahults strand"
    ],
    "name:swe_x_preferred":[
        "Storahults strand"
    ],
    "qs_pg:aaroncc":"SE",
    "qs_pg:name":"Storahults strand",
    "qs_pg:name_adm0":"Sverige",
    "qs_pg:name_adm1":"Sk\u00e5ne L\u00e4n",
    "qs_pg:photos":18,
    "qs_pg:photos_1k":4,
    "qs_pg:photos_9k":1,
    "qs_pg:photos_9r":1,
    "qs_pg:photos_all":18,
    "qs_pg:photos_sr":1,
    "qs_pg:pop_sr":0,
    "qs_pg:qs_pg_placetype":"locality",
    "qs_pg:qs_pg_placetype_gp":"Town",
    "qs_pg:woe_adm0":23424954,
    "woe:adm0_id":23424954,
    "woe:name_adm0":"Sverige",
    "woe:name_adm1":"Sk\u00e5ne L\u00e4n",
    "woe:placetype":"Town",
    "wof:name":"Storahults strand",
    "wof:placetype":"locality"
},
  "geometry": {"coordinates":[12.7594205,56.324538],"type":"Point"}
}