{
  "type": "Feature",
  "properties": {
    "gn:admin1_code":"28.0",
    "gn:admin2_code":"1438.0",
    "gn:asciiname":"Skotterud",
    "gn:country_code":"SE",
    "gn:dem":118,
    "gn:feature_class":"P",
    "gn:feature_code":"PPL",
    "gn:name":"Sk\u00f6tterud",
    "gn:population":0,
    "gn:timezone":"Europe/Stockholm",
    "iso:country":"SE",
    "name:nor_x_preferred":[
        "Sk\u00f6tterud"
    ],
    "name:nor_x_variant":[
        "Sk\u00f8tterud"
    ],
    "name:und_x_variant":[
        "Sk\u00f6tterud"
    ],
    "wof:name":"Skotterud",
    "wof:placetype":"locality"
},
  "geometry": {"coordinates":[11.93333,58.88333000000001],"type":"Point"}
}