{
  "type": "Feature",
  "properties": {
    "gn:admin1_code":"16.0",
    "gn:asciiname":"Vaestanvik",
    "gn:country_code":"SE",
    "gn:dem":104,
    "gn:feature_class":"P",
    "gn:feature_code":"PPL",
    "gn:name":"V\u00e4stanvik",
    "gn:population":201,
    "gn:timezone":"Europe/Stockholm",
    "iso:country":"SE",
    "wof:name":"Vaestanvik",
    "wof:placetype":"locality",
    "wof:population":201
},
  "geometry": {"coordinates":[14.93333,58.68333000000001],"type":"Point"}
}