{
  "type": "Feature",
  "properties": {
    "gn:admin1_code":"9.0",
    "gn:admin2_code":"880.0",
    "gn:asciiname":"Orntorp",
    "gn:country_code":"SE",
    "gn:dem":19,
    "gn:feature_class":"P",
    "gn:feature_code":"PPL",
    "gn:name":"\u00d6rntorp",
    "gn:population":0,
    "gn:timezone":"Europe/Stockholm",
    "iso:country":"SE",
    "name:nor_x_preferred":[
        "\u00d6rntorp"
    ],
    "name:nor_x_variant":[
        "\u00d8rntorp"
    ],
    "wof:name":"Orntorp",
    "wof:placetype":"locality"
},
  "geometry": {"coordinates":[16.26667,56.78333000000001],"type":"Point"}
}