{
  "type": "Feature",
  "properties": {
    "gn:country":"SE",
    "gn:fcode":"ADM3",
    "gn:population":17973,
    "iso:country":"SE",
    "name:amh_x_preferred":[
        "\u130b\u121d\u120b \u12a1\u1355\u1233\u120b"
    ],
    "name:ara_x_preferred":[
        "\u062c\u0645\u0644\u0627 \u0623\u0648\u0628\u0633\u0627\u0644\u0627"
    ],
    "name:bel_x_preferred":[
        "\u0421\u0442\u0430\u0440\u0430\u044f \u0423\u043f\u0441\u0430\u043b\u0430"
    ],
    "name:bul_x_preferred":[
        "\u0413\u0430\u043c\u043b\u0430 \u0423\u043f\u0441\u0430\u043b\u0430"
    ],
    "name:cat_x_preferred":[
        "Gamla Uppsala"
    ],
    "name:ceb_x_preferred":[
        "Gamla Uppsala"
    ],
    "name:dan_x_preferred":[
        "Gamla Uppsala"
    ],
    "name:deu_x_preferred":[
        "Alt-Uppsala"
    ],
    "name:eng_x_preferred":[
        "Gamla Uppsala"
    ],
    "name:fin_x_preferred":[
        "Vanha Uppsala"
    ],
    "name:fra_x_preferred":[
        "Gamla Uppsala"
    ],
    "name:hun_x_preferred":[
        "Gamla Uppsala"
    ],
    "name:ita_x_preferred":[
        "Gamla Uppsala"
    ],
    "name:jpn_x_preferred":[
        "\u30ac\u30e0\u30e9\u30fb\u30a6\u30d7\u30b5\u30e9"
    ],
    "name:kor_x_preferred":[
        "\uac10\ub77c\uc6c1\uc0b4\ub77c"
    ],
    "name:lav_x_preferred":[
        "Vec\u0101 Ups\u0101la"
    ],
    "name:nld_x_preferred":[
        "Gamla Uppsala"
    ],
    "name:nno_x_preferred":[
        "Gamle Uppsala"
    ],
    "name:nob_x_preferred":[
        "Gamle Uppsala"
    ],
    "name:pol_x_preferred":[
        "Gamla Uppsala"
    ],
    "name:por_x_preferred":[
        "Gamla Uppsala"
    ],
    "name:rus_x_preferred":[
        "\u0421\u0442\u0430\u0440\u0430\u044f \u0423\u043f\u043f\u0441\u0430\u043b\u0430"
    ],
    "name:spa_x_preferred":[
        "Gamla Uppsala"
    ],
    "name:swe_x_preferred":[
        "Gamla Uppsala"
    ],
    "name:ukr_x_preferred":[
        "\u0421\u0442\u0430\u0440\u0430 \u0423\u043f\u043f\u0441\u0430\u043b\u0430"
    ],
    "name:zho_x_preferred":[
        "\u8001\u70cf\u666e\u85a9\u62c9"
    ],
    "qs_pg:aaroncc":"SE",
    "qs_pg:gn_country":"SE",
    "qs_pg:gn_fcode":"ADM3",
    "qs_pg:gn_pop":17973,
    "qs_pg:name":"Gamla Uppsala",
    "qs_pg:name_adm0":"Sverige",
    "qs_pg:name_adm1":"Uppsala L\u00e4n",
    "qs_pg:photos":216,
    "qs_pg:photos_1k":44,
    "qs_pg:photos_9k":1,
    "qs_pg:photos_9r":4,
    "qs_pg:photos_all":216,
    "qs_pg:photos_sr":4,
    "qs_pg:pop_sr":6,
    "qs_pg:qs_pg_placetype":"locality",
    "qs_pg:qs_pg_placetype_gp":"Town",
    "qs_pg:woe_adm0":23424954,
    "woe:adm0_id":23424954,
    "woe:name_adm0":"Sverige",
    "woe:name_adm1":"Uppsala L\u00e4n",
    "woe:placetype":"Town",
    "wof:name":"Gamla Uppsala",
    "wof:placetype":"locality",
    "wof:population":17973
},
  "geometry": {"coordinates":[17.63188,59.89951],"type":"Point"}
}