{
  "type": "Feature",
  "properties": {
    "gn:admin1_code":"24.0",
    "gn:admin2_code":"2260.0",
    "gn:admin3_code":"226002.0",
    "gn:admin4_code":"2455.0",
    "gn:asciiname":"Ensillre",
    "gn:cc2":"SE",
    "gn:country_code":"SE",
    "gn:dem":124,
    "gn:feature_class":"P",
    "gn:feature_code":"PPL",
    "gn:name":"Ensillre",
    "gn:population":0,
    "gn:timezone":"Europe/Stockholm",
    "iso:country":"SE",
    "name:und_x_variant":[
        "Erisillre",
        "Ensillre"
    ],
    "wof:name":"Ensillre",
    "wof:placetype":"locality"
},
  "geometry": {"coordinates":[15.79285,62.53155],"type":"Point"}
}