{
  "type": "Feature",
  "properties": {
    "gn:admin1_code":"14.0",
    "gn:admin2_code":"2523.0",
    "gn:asciiname":"Sjisjka",
    "gn:country_code":"SE",
    "gn:dem":488,
    "gn:feature_class":"P",
    "gn:feature_code":"PPL",
    "gn:name":"Sjisjka",
    "gn:population":0,
    "gn:timezone":"Europe/Stockholm",
    "iso:country":"SE",
    "name:nld_x_preferred":[
        "Sjisjka"
    ],
    "name:swe_x_preferred":[
        "Sjisjka"
    ],
    "wof:name":"Sjisjka",
    "wof:placetype":"locality"
},
  "geometry": {"coordinates":[20.23333,67.61667],"type":"Point"}
}