{
  "type": "Feature",
  "properties": {
    "gn:admin1_code":"23.0",
    "gn:admin2_code":"2422.0",
    "gn:asciiname":"Braskafors",
    "gn:country_code":"SE",
    "gn:dem":342,
    "gn:feature_class":"P",
    "gn:feature_code":"PPL",
    "gn:name":"Br\u00e4skafors",
    "gn:population":0,
    "gn:timezone":"Europe/Stockholm",
    "iso:country":"SE",
    "name:swe_x_preferred":[
        "Br\u00e4skafors"
    ],
    "wof:name":"Braskafors",
    "wof:placetype":"locality"
},
  "geometry": {"coordinates":[17.43333,65.63333],"type":"Point"}
}