{
  "type": "Feature",
  "properties": {
    "gn:admin1_code":"24.0",
    "gn:admin2_code":"2282.0",
    "gn:admin3_code":"228211.0",
    "gn:admin4_code":"2511.0",
    "gn:asciiname":"Herrsjon",
    "gn:country_code":"SE",
    "gn:dem":154,
    "gn:feature_class":"P",
    "gn:feature_code":"PPL",
    "gn:name":"Herrsj\u00f6n",
    "gn:population":0,
    "gn:timezone":"Europe/Stockholm",
    "iso:country":"SE",
    "name:nor_x_preferred":[
        "Herrsj\u00f6n"
    ],
    "name:nor_x_variant":[
        "Herrsj\u00f8n"
    ],
    "name:und_x_variant":[
        "Herrsj\u00f6n"
    ],
    "wof:name":"Herrsjon",
    "wof:placetype":"locality"
},
  "geometry": {"coordinates":[17.56667,62.96666999999999],"type":"Point"}
}