{
  "type": "Feature",
  "properties": {
    "gn:admin1_code":"3.0",
    "gn:admin2_code":"2180.0",
    "gn:asciiname":"Gundbo",
    "gn:country_code":"SE",
    "gn:dem":50,
    "gn:feature_class":"P",
    "gn:feature_code":"PPL",
    "gn:name":"Gundbo",
    "gn:population":0,
    "gn:timezone":"Europe/Stockholm",
    "iso:country":"SE",
    "wof:name":"Gundbo",
    "wof:placetype":"locality"
},
  "geometry": {"coordinates":[17.06667,60.31667],"type":"Point"}
}