{
  "type": "Feature",
  "properties": {
    "gn:admin1_code":"5.0",
    "gn:admin2_code":"980.0",
    "gn:admin3_code":"98010.0",
    "gn:admin4_code":"929.0",
    "gn:asciiname":"Hallshuk",
    "gn:cc2":"SE",
    "gn:country_code":"SE",
    "gn:dem":15,
    "gn:feature_class":"P",
    "gn:feature_code":"PPL",
    "gn:name":"Hallshuk",
    "gn:population":0,
    "gn:timezone":"Europe/Stockholm",
    "iso:country":"SE",
    "name:und_x_variant":[
        "Halls Fiskl\u00e4ge",
        "Hallshuk"
    ],
    "wof:name":"Hallshuk",
    "wof:placetype":"locality"
},
  "geometry": {"coordinates":[18.74188,57.9242],"type":"Point"}
}