{
  "type": "Feature",
  "properties": {
    "gn:admin1_code":"24.0",
    "gn:admin2_code":"2280.0",
    "gn:admin3_code":"228005.0",
    "gn:admin4_code":"2510.0",
    "gn:asciiname":"Kackelbacken",
    "gn:country_code":"SE",
    "gn:dem":211,
    "gn:feature_class":"P",
    "gn:feature_code":"PPL",
    "gn:name":"K\u00e4ckelb\u00e4cken",
    "gn:population":0,
    "gn:timezone":"Europe/Stockholm",
    "iso:country":"SE",
    "wof:name":"Kackelbacken",
    "wof:placetype":"locality"
},
  "geometry": {"coordinates":[17.38332999999999,62.81667],"type":"Point"}
}