{
  "type": "Feature",
  "properties": {
    "gn:admin1_code":"23.0",
    "gn:admin2_code":"2418.0",
    "gn:asciiname":"Malatrask",
    "gn:country_code":"SE",
    "gn:dem":288,
    "gn:feature_class":"P",
    "gn:feature_code":"PPL",
    "gn:name":"Mal\u00e5tr\u00e4sk",
    "gn:population":0,
    "gn:timezone":"Europe/Stockholm",
    "iso:country":"SE",
    "wof:name":"Malatrask",
    "wof:placetype":"locality"
},
  "geometry": {"coordinates":[18.73333,65.18333],"type":"Point"}
}