{
  "type": "Feature",
  "properties": {
    "gn:admin1_code":"14.0",
    "gn:admin2_code":"2510.0",
    "gn:asciiname":"Randijaur",
    "gn:cc2":"SE",
    "gn:country_code":"SE",
    "gn:dem":278,
    "gn:feature_class":"P",
    "gn:feature_code":"PPL",
    "gn:name":"Randijaur",
    "gn:population":0,
    "gn:timezone":"Europe/Stockholm",
    "iso:country":"SE",
    "name:und_x_variant":[
        "Randijaure",
        "Randijaur"
    ],
    "wof:name":"Randijaur",
    "wof:placetype":"locality"
},
  "geometry": {"coordinates":[19.28333,66.75],"type":"Point"}
}