{
  "type": "Feature",
  "properties": {
    "gn:admin1_code":"28.0",
    "gn:admin2_code":"1482.0",
    "gn:asciiname":"Valler",
    "gn:cc2":"SE",
    "gn:country_code":"SE",
    "gn:dem":12,
    "gn:feature_class":"P",
    "gn:feature_code":"PPL",
    "gn:name":"Valler",
    "gn:population":0,
    "gn:timezone":"Europe/Stockholm",
    "iso:country":"SE",
    "name:und_x_variant":[
        "Valler\u00f6d",
        "Vallered",
        "Valler"
    ],
    "wof:name":"Valler",
    "wof:placetype":"locality"
},
  "geometry": {"coordinates":[12.05,57.95],"type":"Point"}
}