{
  "type": "Feature",
  "properties": {
    "gn:admin1_code":"18.0",
    "gn:admin2_code":"482.0",
    "gn:asciiname":"Helgesta",
    "gn:cc2":"SE",
    "gn:country_code":"SE",
    "gn:dem":26,
    "gn:feature_class":"P",
    "gn:feature_code":"PPL",
    "gn:name":"Helgesta",
    "gn:population":0,
    "gn:timezone":"Europe/Stockholm",
    "iso:country":"SE",
    "name:und_x_variant":[
        "Helgestag\u00e5rd",
        "Helgesta"
    ],
    "wof:name":"Helgesta",
    "wof:placetype":"locality"
},
  "geometry": {"coordinates":[16.78333,59.03333000000001],"type":"Point"}
}