{
  "type": "Feature",
  "properties": {
    "gn:admin1_code":"12.0",
    "gn:admin2_code":"780.0",
    "gn:asciiname":"Stojby",
    "gn:country_code":"SE",
    "gn:dem":169,
    "gn:feature_class":"P",
    "gn:feature_code":"PPL",
    "gn:name":"Stojby",
    "gn:population":0,
    "gn:timezone":"Europe/Stockholm",
    "iso:country":"SE",
    "wof:name":"Stojby",
    "wof:placetype":"locality"
},
  "geometry": {"coordinates":[14.83333,56.98333],"type":"Point"}
}