{
  "type": "Feature",
  "properties": {
    "gn:admin1_code":"21.0",
    "gn:admin2_code":"380.0",
    "gn:asciiname":"Vallby",
    "gn:country_code":"SE",
    "gn:dem":21,
    "gn:feature_class":"P",
    "gn:feature_code":"PPL",
    "gn:name":"Vallby",
    "gn:population":0,
    "gn:timezone":"Europe/Stockholm",
    "iso:country":"SE",
    "wof:name":"Vallby",
    "wof:placetype":"locality"
},
  "geometry": {"coordinates":[17.65,60.08333],"type":"Point"}
}