{
  "type": "Feature",
  "properties": {
    "gn:admin1_code":"15.0",
    "gn:admin2_code":"1864.0",
    "gn:asciiname":"Kolheden",
    "gn:country_code":"SE",
    "gn:dem":220,
    "gn:feature_class":"P",
    "gn:feature_code":"PPL",
    "gn:name":"Kolheden",
    "gn:population":0,
    "gn:timezone":"Europe/Stockholm",
    "iso:country":"SE",
    "wof:name":"Kolheden",
    "wof:placetype":"locality"
},
  "geometry": {"coordinates":[15.05,59.88333000000001],"type":"Point"}
}