{
  "type": "Feature",
  "properties": {
    "gn:admin1_code":"07",
    "gn:admin2_code":"2361.0",
    "gn:admin3_code":"236107.0",
    "gn:admin4_code":"2571.0",
    "gn:asciiname":"Slaettansvallen",
    "gn:country_code":"SE",
    "gn:dem":735,
    "gn:feature_class":"P",
    "gn:feature_code":"PPLL",
    "gn:name":"Sl\u00e4ttansvallen",
    "gn:population":0,
    "gn:timezone":"Europe/Stockholm",
    "iso:country":"SE",
    "wof:name":"Slaettansvallen",
    "wof:placetype":"locality"
},
  "geometry": {"coordinates":[12.33241,62.71684000000001],"type":"Point"}
}