{
  "type": "Feature",
  "properties": {
    "gn:admin1_code":"22.0",
    "gn:admin2_code":"1764.0",
    "gn:asciiname":"Degerbyn",
    "gn:country_code":"SE",
    "gn:dem":83,
    "gn:feature_class":"P",
    "gn:feature_code":"PPL",
    "gn:name":"Degerbyn",
    "gn:population":0,
    "gn:timezone":"Europe/Stockholm",
    "iso:country":"SE",
    "wof:name":"Degerbyn",
    "wof:placetype":"locality"
},
  "geometry": {"coordinates":[12.96667,59.45],"type":"Point"}
}