{
  "type": "Feature",
  "properties": {
    "gn:admin1_code":"23.0",
    "gn:admin2_code":"2480.0",
    "gn:asciiname":"Hossjo",
    "gn:country_code":"SE",
    "gn:dem":117,
    "gn:feature_class":"P",
    "gn:feature_code":"PPL",
    "gn:name":"H\u00f6ssj\u00f6",
    "gn:population":0,
    "gn:timezone":"Europe/Stockholm",
    "iso:country":"SE",
    "name:nor_x_preferred":[
        "H\u00f6ssj\u00f6"
    ],
    "name:nor_x_variant":[
        "H\u00f8ssj\u00f8"
    ],
    "name:und_x_variant":[
        "H\u00f6ssj\u00f6"
    ],
    "wof:name":"Hossjo",
    "wof:placetype":"locality"
},
  "geometry": {"coordinates":[19.83333,63.78333000000001],"type":"Point"}
}