{
  "type": "Feature",
  "properties": {
    "gn:admin1_code":"10.0",
    "gn:admin2_code":"2062.0",
    "gn:asciiname":"Johannisholm",
    "gn:country_code":"SE",
    "gn:dem":275,
    "gn:feature_class":"P",
    "gn:feature_code":"PPL",
    "gn:name":"Johannisholm",
    "gn:population":0,
    "gn:timezone":"Europe/Stockholm",
    "iso:country":"SE",
    "wof:name":"Johannisholm",
    "wof:placetype":"locality"
},
  "geometry": {"coordinates":[14.11667,60.83333],"type":"Point"}
}