{
  "type": "Feature",
  "properties": {
    "gn:admin1_code":"24.0",
    "gn:admin2_code":"2282.0",
    "gn:asciiname":"Mo",
    "gn:country_code":"SE",
    "gn:dem":31,
    "gn:feature_class":"P",
    "gn:feature_code":"PPL",
    "gn:name":"Mo",
    "gn:population":0,
    "gn:timezone":"Europe/Stockholm",
    "iso:country":"SE",
    "name:bar_x_preferred":[
        "Mo"
    ],
    "name:hun_x_preferred":[
        "Mo"
    ],
    "name:ind_x_preferred":[
        "Mo"
    ],
    "name:rus_x_preferred":[
        "Mo"
    ],
    "wof:name":"Mo",
    "wof:placetype":"locality"
},
  "geometry": {"coordinates":[17.58333,63.06667],"type":"Point"}
}