{
  "type": "Feature",
  "properties": {
    "iso:country":"SE",
    "name:eng_x_preferred":[
        "R\u00f6rsj\u00f6staden"
    ],
    "name:lat_x_preferred":[
        "R\u00f6rsj\u00f6staden"
    ],
    "name:nld_x_preferred":[
        "R\u00f6rsj\u00f6staden"
    ],
    "name:nor_x_preferred":[
        "R\u00f8rsj\u00f8staden"
    ],
    "name:nor_x_variant":[
        "R\u00f6rsj\u00f6staden"
    ],
    "name:swe_x_colloquial":[
        "Roersjoestaden",
        "Rorsjostaden"
    ],
    "name:swe_x_preferred":[
        "R\u00f6rsj\u00f6staden"
    ],
    "qs:gn_adm0_cc":"SE",
    "qs:gn_fcode":"PPLX",
    "qs:gn_local":2692969,
    "qs:gn_nam_loc":"Malm\u00f6, Malm\u00f6, Sk\u00e5ne L\u00e4n, SE",
    "qs:gn_namadm1":"27",
    "qs:gn_name":"R\u00f6rsj\u00f6staden",
    "qs:local_max":12498,
    "qs:local_sum":46560,
    "qs:localhoods":7,
    "qs:name":"R\u00f6rsj\u00f6staden",
    "qs:name_adm0":"Sverige",
    "qs:name_adm1":"Sk\u00e5ne L\u00e4n",
    "qs:name_adm2":"Malm\u00f6",
    "qs:name_local":"Malm\u00f6",
    "qs:photo_max":128,
    "qs:photo_sum":225,
    "qs:placetype":"Suburb",
    "qs:quad_count":3,
    "qs:woe_adm0":23424954,
    "qs:woe_adm1":20070561,
    "qs:woe_adm2":12587333,
    "qs:woe_lau":0,
    "qs:woe_local":898091,
    "qs:woe_ver":"7.10.0",
    "wd:wordcount":32,
    "wof:lang":[
        "swe"
    ],
    "wof:name":"R\u00f6rsj\u00f6staden",
    "wof:placetype":"neighbourhood"
},
  "geometry": {"coordinates":[13.003149,55.600668],"type":"Point"}
}