{
  "type": "Feature",
  "properties": {
    "gn:admin1_code":"21.0",
    "gn:admin2_code":"305.0",
    "gn:asciiname":"Horntorp",
    "gn:country_code":"SE",
    "gn:dem":16,
    "gn:feature_class":"P",
    "gn:feature_code":"PPL",
    "gn:name":"H\u00f6rntorp",
    "gn:population":0,
    "gn:timezone":"Europe/Stockholm",
    "iso:country":"SE",
    "name:nor_x_preferred":[
        "H\u00f6rntorp"
    ],
    "name:nor_x_variant":[
        "H\u00f8rntorp"
    ],
    "wof:name":"Horntorp",
    "wof:placetype":"locality"
},
  "geometry": {"coordinates":[17.53333,59.56667],"type":"Point"}
}