{
  "type": "Feature",
  "properties": {
    "gn:admin1_code":"24.0",
    "gn:admin2_code":"2262.0",
    "gn:admin3_code":"226203.0",
    "gn:admin4_code":"2471.0",
    "gn:asciiname":"Bondhamn",
    "gn:country_code":"SE",
    "gn:dem":4,
    "gn:feature_class":"P",
    "gn:feature_code":"PPL",
    "gn:name":"Bondhamn",
    "gn:population":0,
    "gn:timezone":"Europe/Stockholm",
    "iso:country":"SE",
    "wof:name":"Bondhamn",
    "wof:placetype":"locality"
},
  "geometry": {"coordinates":[17.70301,62.50255],"type":"Point"}
}