{
  "type": "Feature",
  "properties": {
    "gn:admin1_code":"8.0",
    "gn:admin2_code":"680.0",
    "gn:asciiname":"Hogstorp",
    "gn:country_code":"SE",
    "gn:dem":258,
    "gn:feature_class":"P",
    "gn:feature_code":"PPL",
    "gn:name":"H\u00f6gstorp",
    "gn:population":0,
    "gn:timezone":"Europe/Stockholm",
    "iso:country":"SE",
    "name:nor_x_preferred":[
        "H\u00f6gstorp"
    ],
    "name:nor_x_variant":[
        "H\u00f8gstorp"
    ],
    "name:und_x_variant":[
        "H\u00f6gstorp"
    ],
    "wof:name":"Hogstorp",
    "wof:placetype":"locality"
},
  "geometry": {"coordinates":[14.46667,57.85],"type":"Point"}
}