{
  "type": "Feature",
  "properties": {
    "gn:admin1_code":"10.0",
    "gn:admin2_code":"2083.0",
    "gn:asciiname":"Marken",
    "gn:country_code":"SE",
    "gn:dem":128,
    "gn:feature_class":"P",
    "gn:feature_code":"PPL",
    "gn:name":"Marken",
    "gn:population":0,
    "gn:timezone":"Europe/Stockholm",
    "iso:country":"SE",
    "name:bre_x_preferred":[
        "Marken"
    ],
    "name:ceb_x_preferred":[
        "Marken"
    ],
    "name:dan_x_preferred":[
        "Marken"
    ],
    "name:deu_x_preferred":[
        "Marken"
    ],
    "name:epo_x_preferred":[
        "Marken"
    ],
    "name:fas_x_preferred":[
        "\u0645\u0627\u0631\u06a9\u0646"
    ],
    "name:fra_x_preferred":[
        "Marken"
    ],
    "name:fry_x_preferred":[
        "Marken"
    ],
    "name:ita_x_preferred":[
        "Marken"
    ],
    "name:nld_x_preferred":[
        "Marken"
    ],
    "name:pol_x_preferred":[
        "Marken"
    ],
    "name:por_x_preferred":[
        "Marken"
    ],
    "name:rus_x_preferred":[
        "\u041c\u0430\u0440\u043a\u0435\u043d"
    ],
    "name:spa_x_preferred":[
        "Marken"
    ],
    "name:swe_x_preferred":[
        "Marken"
    ],
    "name:tur_x_preferred":[
        "Marken"
    ],
    "name:ukr_x_preferred":[
        "\u041c\u0430\u0440\u043a\u0435\u043d"
    ],
    "wof:name":"Marken",
    "wof:placetype":"locality"
},
  "geometry": {"coordinates":[15.95,60.18333000000001],"type":"Point"}
}