{
  "type": "Feature",
  "properties": {
    "gn:admin1_code":"9.0",
    "gn:admin2_code":"881.0",
    "gn:asciiname":"Sankt Sigfrid",
    "gn:cc2":"SE",
    "gn:country_code":"SE",
    "gn:dem":59,
    "gn:feature_class":"P",
    "gn:feature_code":"PPL",
    "gn:name":"Sankt Sigfrid",
    "gn:population":0,
    "gn:timezone":"Europe/Stockholm",
    "iso:country":"SE",
    "name:und_x_variant":[
        "Stora Sigfrid",
        "Sankt Sigfrid"
    ],
    "wof:name":"Sankt Sigfrid",
    "wof:placetype":"locality"
},
  "geometry": {"coordinates":[16.01667,56.68333000000001],"type":"Point"}
}