{
  "type": "Feature",
  "properties": {
    "gn:admin1_code":"18.0",
    "gn:admin2_code":"461.0",
    "gn:asciiname":"Hallesta",
    "gn:country_code":"SE",
    "gn:dem":35,
    "gn:feature_class":"P",
    "gn:feature_code":"PPL",
    "gn:name":"H\u00e4llesta",
    "gn:population":0,
    "gn:timezone":"Europe/Stockholm",
    "iso:country":"SE",
    "wof:name":"Hallesta",
    "wof:placetype":"locality"
},
  "geometry": {"coordinates":[17.21667,59.03333000000001],"type":"Point"}
}