{
  "type": "Feature",
  "properties": {
    "gn:admin1_code":"25.0",
    "gn:asciiname":"Lybeck",
    "gn:country_code":"SE",
    "gn:dem":14,
    "gn:feature_class":"P",
    "gn:feature_code":"PPL",
    "gn:name":"Lybeck",
    "gn:population":277,
    "gn:timezone":"Europe/Stockholm",
    "iso:country":"SE",
    "wof:name":"Lybeck",
    "wof:placetype":"locality",
    "wof:population":277
},
  "geometry": {"coordinates":[16.71865,59.52974],"type":"Point"}
}