{
  "type": "Feature",
  "properties": {
    "gn:country":"SE",
    "gn:fcode":"PPL",
    "gn:population":343,
    "iso:country":"SE",
    "name:ceb_x_preferred":[
        "Upplanda"
    ],
    "name:ita_x_preferred":[
        "Upplanda"
    ],
    "name:nld_x_preferred":[
        "Upplanda"
    ],
    "name:nno_x_preferred":[
        "Upplanda"
    ],
    "name:nor_x_preferred":[
        "Upplanda"
    ],
    "name:swe_x_preferred":[
        "Upplanda"
    ],
    "qs_pg:aaroncc":"SE",
    "qs_pg:gn_country":"SE",
    "qs_pg:gn_fcode":"PPL",
    "qs_pg:gn_pop":343,
    "qs_pg:name":"Upplanda",
    "qs_pg:name_adm0":"Sverige",
    "qs_pg:name_adm1":"Uppsala L\u00e4n",
    "qs_pg:photos_9r":0,
    "qs_pg:photos_sr":0,
    "qs_pg:pop_sr":2,
    "qs_pg:qs_pg_placetype":"locality",
    "qs_pg:qs_pg_placetype_gp":"Town",
    "qs_pg:woe_adm0":23424954,
    "woe:adm0_id":23424954,
    "woe:name_adm0":"Sverige",
    "woe:name_adm1":"Uppsala L\u00e4n",
    "woe:placetype":"Town",
    "wof:name":"Upplanda",
    "wof:placetype":"locality",
    "wof:population":222
},
  "geometry": {"coordinates":[17.73333,60.23333],"type":"Point"}
}