{
  "type": "Feature",
  "properties": {
    "gn:gn_country":"SE",
    "gn:gn_fcode":"PPL",
    "gn:gn_pop":0,
    "iso:country":"SE",
    "name:ceb_x_preferred":[
        "Grinner\u00f6d"
    ],
    "name:dan_x_preferred":[
        "Grinner\u00f6d"
    ],
    "name:deu_x_preferred":[
        "Grinner\u00f6d"
    ],
    "name:eng_x_preferred":[
        "Grinner\u00f6d"
    ],
    "name:fra_x_preferred":[
        "Grinner\u00f6d"
    ],
    "name:nds_x_preferred":[
        "Grinner\u00f6d"
    ],
    "name:nld_x_preferred":[
        "Grinner\u00f6d"
    ],
    "name:nno_x_preferred":[
        "Grinner\u00f6d"
    ],
    "name:nob_x_preferred":[
        "Grinner\u00f6d"
    ],
    "name:nor_x_preferred":[
        "Grinner\u00f8d"
    ],
    "name:nor_x_variant":[
        "Grinner\u00f6d"
    ],
    "name:swe_x_preferred":[
        "Grinner\u00f6d"
    ],
    "qs_pg:aaroncc":"SE",
    "qs_pg:gn_country":"SE",
    "qs_pg:gn_fcode":"PPL",
    "qs_pg:gn_pop":0,
    "qs_pg:name":"Grinner\u00f6d",
    "qs_pg:name_adm0":"Sverige",
    "qs_pg:name_adm1":"V\u00e4stra G\u00f6talands L\u00e4n",
    "qs_pg:photos":51,
    "qs_pg:photos_1k":10,
    "qs_pg:photos_9k":1,
    "qs_pg:photos_9r":2,
    "qs_pg:photos_all":51,
    "qs_pg:photos_sr":2,
    "qs_pg:pop_sr":0,
    "qs_pg:qs_pg_placetype":"locality",
    "qs_pg:qs_pg_placetype_gp":"Town",
    "qs_pg:woe_adm0":23424954,
    "woe:adm0_id":23424954,
    "woe:name_adm0":"Sverige",
    "woe:name_adm1":"V\u00e4stra G\u00f6talands L\u00e4n",
    "woe:placetype":"Town",
    "wof:name":"Grinner\u00f6d",
    "wof:placetype":"locality"
},
  "geometry": {"coordinates":[11.95,58.18306],"type":"Point"}
}