{
  "type": "Feature",
  "properties": {
    "gn:admin1_code":"23.0",
    "gn:admin2_code":"2404.0",
    "gn:asciiname":"Sundo",
    "gn:country_code":"SE",
    "gn:dem":200,
    "gn:feature_class":"P",
    "gn:feature_code":"PPL",
    "gn:name":"Sund\u00f6",
    "gn:population":0,
    "gn:timezone":"Europe/Stockholm",
    "iso:country":"SE",
    "name:nor_x_preferred":[
        "Sund\u00f6"
    ],
    "name:nor_x_variant":[
        "Sund\u00f8"
    ],
    "wof:name":"Sundo",
    "wof:placetype":"locality"
},
  "geometry": {"coordinates":[19.33333,64.15000000000001],"type":"Point"}
}