{
  "type": "Feature",
  "properties": {
    "gn:admin1_code":"28.0",
    "gn:admin2_code":"1499.0",
    "gn:asciiname":"Bestorp",
    "gn:country_code":"SE",
    "gn:dem":244,
    "gn:feature_class":"P",
    "gn:feature_code":"PPL",
    "gn:name":"Bestorp",
    "gn:population":0,
    "gn:timezone":"Europe/Stockholm",
    "iso:country":"SE",
    "name:ceb_x_preferred":[
        "Bestorp"
    ],
    "name:ita_x_preferred":[
        "Bestorp"
    ],
    "name:nld_x_preferred":[
        "Bestorp"
    ],
    "name:nno_x_preferred":[
        "Bestorp"
    ],
    "name:nor_x_preferred":[
        "Bestorp"
    ],
    "name:swe_x_preferred":[
        "Bestorp"
    ],
    "wof:name":"Bestorp",
    "wof:placetype":"locality"
},
  "geometry": {"coordinates":[13.51667,58.16667],"type":"Point"}
}