{
  "type": "Feature",
  "properties": {
    "iso:country":"SE",
    "wof:name":"Ekered",
    "wof:placetype":"neighbourhood"
},
  "geometry": {"coordinates":[12.08203768710537,57.78510881476267],"type":"Point"}
}