{
  "type": "Feature",
  "properties": {
    "gn:admin1_code":"8.0",
    "gn:admin2_code":"684.0",
    "gn:asciiname":"Hjalmseryd",
    "gn:country_code":"SE",
    "gn:dem":208,
    "gn:feature_class":"P",
    "gn:feature_code":"PPL",
    "gn:name":"Hj\u00e4lmseryd",
    "gn:population":0,
    "gn:timezone":"Europe/Stockholm",
    "iso:country":"SE",
    "wof:name":"Hjalmseryd",
    "wof:placetype":"locality"
},
  "geometry": {"coordinates":[14.51667,57.31667],"type":"Point"}
}