{
  "type": "Feature",
  "properties": {
    "gn:admin1_code":"21.0",
    "gn:admin2_code":"382.0",
    "gn:asciiname":"Vaddika",
    "gn:cc2":"SE",
    "gn:country_code":"SE",
    "gn:dem":8,
    "gn:feature_class":"P",
    "gn:feature_code":"PPL",
    "gn:name":"V\u00e4ddika",
    "gn:population":0,
    "gn:timezone":"Europe/Stockholm",
    "iso:country":"SE",
    "name:und_x_variant":[
        "Veddika",
        "V\u00e4ddika"
    ],
    "wof:name":"Vaddika",
    "wof:placetype":"locality"
},
  "geometry": {"coordinates":[18.23333,60.21666999999999],"type":"Point"}
}