{
  "type": "Feature",
  "properties": {
    "gn:admin1_code":"25.0",
    "gn:admin2_code":"1980.0",
    "gn:asciiname":"Skaelby",
    "gn:country_code":"SE",
    "gn:dem":18,
    "gn:feature_class":"P",
    "gn:feature_code":"PPLL",
    "gn:name":"Sk\u00e4lby",
    "gn:population":0,
    "gn:timezone":"Europe/Stockholm",
    "iso:country":"SE",
    "wof:name":"Skaelby",
    "wof:placetype":"locality"
},
  "geometry": {"coordinates":[16.45572,59.59675],"type":"Point"}
}