{
  "type": "Feature",
  "properties": {
    "gn:admin1_code":"27.0",
    "gn:admin2_code":"1278.0",
    "gn:asciiname":"Tvehoga",
    "gn:country_code":"SE",
    "gn:dem":130,
    "gn:feature_class":"P",
    "gn:feature_code":"PPL",
    "gn:name":"Tveh\u00f6ga",
    "gn:population":0,
    "gn:timezone":"Europe/Stockholm",
    "iso:country":"SE",
    "name:nor_x_preferred":[
        "Tveh\u00f6ga"
    ],
    "name:nor_x_variant":[
        "Tveh\u00f8ga"
    ],
    "wof:name":"Tvehoga",
    "wof:placetype":"locality"
},
  "geometry": {"coordinates":[12.93333,56.41667],"type":"Point"}
}