{
  "type": "Feature",
  "properties": {
    "gn:admin1_code":"16.0",
    "gn:admin2_code":"582.0",
    "gn:asciiname":"Froberga",
    "gn:country_code":"SE",
    "gn:dem":46,
    "gn:feature_class":"P",
    "gn:feature_code":"PPL",
    "gn:name":"Fr\u00f6berga",
    "gn:population":0,
    "gn:timezone":"Europe/Stockholm",
    "iso:country":"SE",
    "name:nor_x_preferred":[
        "Fr\u00f6berga"
    ],
    "name:nor_x_variant":[
        "Fr\u00f8berga"
    ],
    "name:und_x_variant":[
        "Fr\u00f6berga"
    ],
    "wof:name":"Froberga",
    "wof:placetype":"locality"
},
  "geometry": {"coordinates":[16.41667,58.39972],"type":"Point"}
}