{
  "type": "Feature",
  "properties": {
    "gn:admin1_code":"26",
    "gn:admin2_code":"160.0",
    "gn:admin3_code":"16001.0",
    "gn:admin4_code":"104.0",
    "gn:asciiname":"Norskogen",
    "gn:country_code":"SE",
    "gn:dem":34,
    "gn:feature_class":"P",
    "gn:feature_code":"PPL",
    "gn:name":"Norskogen",
    "gn:population":0,
    "gn:timezone":"Europe/Stockholm",
    "iso:country":"SE",
    "wof:name":"Norskogen",
    "wof:placetype":"locality"
},
  "geometry": {"coordinates":[18.08749,59.43638000000001],"type":"Point"}
}