{
  "type": "Feature",
  "properties": {
    "iso:country":"SE",
    "name:deu_x_preferred":[
        "Angas"
    ],
    "name:fra_x_preferred":[
        "Angas"
    ],
    "name:swe_x_preferred":[
        "\u00c4ng\u00e5s"
    ],
    "wof:name":"Angas",
    "wof:placetype":"neighbourhood"
},
  "geometry": {"coordinates":[11.91246477158423,57.64557387119284],"type":"Point"}
}