{
  "type": "Feature",
  "properties": {
    "gn:admin1_code":"7.0",
    "gn:admin2_code":"2326.0",
    "gn:asciiname":"Roron",
    "gn:cc2":"SE",
    "gn:country_code":"SE",
    "gn:dem":457,
    "gn:feature_class":"P",
    "gn:feature_code":"PPL",
    "gn:name":"R\u00f6r\u00f6n",
    "gn:population":0,
    "gn:timezone":"Europe/Stockholm",
    "iso:country":"SE",
    "name:nor_x_preferred":[
        "R\u00f6r\u00f6n"
    ],
    "name:nor_x_variant":[
        "R\u00f8r\u00f8n"
    ],
    "name:und_x_variant":[
        "R\u00f6r\u00f6"
    ],
    "wof:name":"Roron",
    "wof:placetype":"locality"
},
  "geometry": {"coordinates":[14.46667,62.73333],"type":"Point"}
}