{
  "type": "Feature",
  "properties": {
    "gn:country":"SE",
    "gn:fcode":"PPL",
    "gn:population":424,
    "iso:country":"SE",
    "name:ceb_x_preferred":[
        "Lanna"
    ],
    "name:deu_x_preferred":[
        "Lanna"
    ],
    "name:eng_x_preferred":[
        "Lanna"
    ],
    "name:fin_x_preferred":[
        "Lanna"
    ],
    "name:ita_x_preferred":[
        "Lanna"
    ],
    "name:nan_x_preferred":[
        "Lanna"
    ],
    "name:nld_x_preferred":[
        "Lanna"
    ],
    "name:nno_x_preferred":[
        "Lanna i N\u00e4rke"
    ],
    "name:nob_x_preferred":[
        "Lanna"
    ],
    "name:swe_x_preferred":[
        "Lanna"
    ],
    "name:urd_x_preferred":[
        "\u0644\u0627\u0646\u0627\u060c \u0644\u06cc\u06a9\u06cc\u0628\u06cc\u0631\u06af"
    ],
    "name:urd_x_variant":[
        "\u0644\u0627\u0646\u0627"
    ],
    "qs_pg:aaroncc":"SE",
    "qs_pg:gn_country":"SE",
    "qs_pg:gn_fcode":"PPL",
    "qs_pg:gn_pop":424,
    "qs_pg:name":"Lanna",
    "qs_pg:name_adm0":"Sverige",
    "qs_pg:name_adm1":"\u00d6rebro L\u00e4n",
    "qs_pg:photos":26,
    "qs_pg:photos_1k":5,
    "qs_pg:photos_9k":1,
    "qs_pg:photos_9r":2,
    "qs_pg:photos_all":26,
    "qs_pg:photos_sr":2,
    "qs_pg:pop_sr":2,
    "qs_pg:qs_pg_placetype":"locality",
    "qs_pg:qs_pg_placetype_gp":"Town",
    "qs_pg:woe_adm0":23424954,
    "woe:adm0_id":23424954,
    "woe:name_adm0":"Sverige",
    "woe:name_adm1":"\u00d6rebro L\u00e4n",
    "woe:placetype":"Town",
    "wof:name":"Lanna",
    "wof:placetype":"locality",
    "wof:population":424
},
  "geometry": {"coordinates":[14.91667,59.23333],"type":"Point"}
}