{
  "type": "Feature",
  "properties": {
    "gn:admin1_code":"10.0",
    "gn:admin2_code":"2085.0",
    "gn:asciiname":"Skallberget",
    "gn:country_code":"SE",
    "gn:dem":250,
    "gn:feature_class":"P",
    "gn:feature_code":"PPL",
    "gn:name":"Skallberget",
    "gn:population":0,
    "gn:timezone":"Europe/Stockholm",
    "iso:country":"SE",
    "wof:name":"Skallberget",
    "wof:placetype":"locality"
},
  "geometry": {"coordinates":[14.86667,60.36666999999999],"type":"Point"}
}