{
  "type": "Feature",
  "properties": {
    "iso:country":"SE",
    "name:swe_x_preferred":[
        "Visinge"
    ],
    "name:unk_x_variant":[
        "Visinge"
    ],
    "qs:gn_adm0_cc":"SE",
    "qs:gn_local":2669772,
    "qs:gn_nam_loc":"T\u00e4by, T\u00e4by, Stockholms L\u00e4n, SE",
    "qs:gn_namadm1":"26",
    "qs:local_max":409,
    "qs:local_sum":1647,
    "qs:localhoods":10,
    "qs:name":"Visinge",
    "qs:name_adm0":"Sverige",
    "qs:name_adm1":"Stockholms L\u00e4n",
    "qs:name_adm2":"T\u00e4by",
    "qs:name_local":"T\u00e4by",
    "qs:photo_max":38,
    "qs:photo_sum":185,
    "qs:placetype":"Suburb",
    "qs:quad_count":44,
    "qs:woe_adm0":23424954,
    "qs:woe_adm1":2347067,
    "qs:woe_adm2":12587480,
    "qs:woe_lau":0,
    "qs:woe_local":907140,
    "qs:woe_ver":"7.10.0",
    "wof:lang":[
        "swe"
    ],
    "wof:name":"Visinge",
    "wof:placetype":"neighbourhood"
},
  "geometry": {"coordinates":[18.048824,59.464703],"type":"Point"}
}