{
  "type": "Feature",
  "properties": {
    "gn:admin1_code":"25.0",
    "gn:admin2_code":"1981.0",
    "gn:asciiname":"Hornsjofors",
    "gn:cc2":"SE",
    "gn:country_code":"SE",
    "gn:dem":69,
    "gn:feature_class":"P",
    "gn:feature_code":"PPL",
    "gn:name":"H\u00f6rnsj\u00f6fors",
    "gn:population":0,
    "gn:timezone":"Europe/Stockholm",
    "iso:country":"SE",
    "name:nor_x_preferred":[
        "H\u00f6rnsj\u00f6fors"
    ],
    "name:nor_x_variant":[
        "H\u00f8rnsj\u00f8fors"
    ],
    "name:und_x_variant":[
        "Fors"
    ],
    "wof:name":"Hornsjofors",
    "wof:placetype":"locality"
},
  "geometry": {"coordinates":[16.21667,59.95],"type":"Point"}
}