{
  "type": "Feature",
  "properties": {
    "gn:admin1_code":"26.0",
    "gn:asciiname":"Karlsudd",
    "gn:country_code":"SE",
    "gn:dem":20,
    "gn:feature_class":"P",
    "gn:feature_code":"PPL",
    "gn:name":"Karlsudd",
    "gn:population":0,
    "gn:timezone":"Europe/Stockholm",
    "iso:country":"SE",
    "wof:name":"Karlsudd",
    "wof:placetype":"locality"
},
  "geometry": {"coordinates":[18.31481,59.38551],"type":"Point"}
}