{
  "type": "Feature",
  "properties": {
    "gn:admin1_code":"10.0",
    "gn:admin2_code":"2039.0",
    "gn:asciiname":"Gammelsatervallen",
    "gn:country_code":"SE",
    "gn:dem":747,
    "gn:feature_class":"P",
    "gn:feature_code":"PPL",
    "gn:name":"Gammels\u00e4tervallen",
    "gn:population":0,
    "gn:timezone":"Europe/Stockholm",
    "iso:country":"SE",
    "wof:name":"Gammelsatervallen",
    "wof:placetype":"locality"
},
  "geometry": {"coordinates":[12.81667,61.93306],"type":"Point"}
}