{
  "type": "Feature",
  "properties": {
    "gn:admin1_code":"8.0",
    "gn:admin2_code":"617.0",
    "gn:asciiname":"Kavsjo",
    "gn:cc2":"SE",
    "gn:country_code":"SE",
    "gn:dem":172,
    "gn:feature_class":"P",
    "gn:feature_code":"PPL",
    "gn:name":"K\u00e4vsj\u00f6",
    "gn:population":0,
    "gn:timezone":"Europe/Stockholm",
    "iso:country":"SE",
    "name:und_x_variant":[
        "K\u00e4fsj\u00f6",
        "K\u00e4vsj\u00f6"
    ],
    "wof:name":"Kavsjo",
    "wof:placetype":"locality"
},
  "geometry": {"coordinates":[13.91667,57.31667],"type":"Point"}
}