{
  "type": "Feature",
  "properties": {
    "gn:admin1_code":"28.0",
    "gn:admin2_code":"1480.0",
    "gn:asciiname":"Svindal",
    "gn:country_code":"SE",
    "gn:dem":32,
    "gn:feature_class":"P",
    "gn:feature_code":"PPL",
    "gn:name":"Svindal",
    "gn:population":0,
    "gn:timezone":"Europe/Stockholm",
    "iso:country":"SE",
    "wof:name":"Svindal",
    "wof:placetype":"locality"
},
  "geometry": {"coordinates":[11.95,57.58333],"type":"Point"}
}