{
  "type": "Feature",
  "properties": {
    "gn:admin1_code":"28.0",
    "gn:admin2_code":"1484.0",
    "gn:asciiname":"Skal",
    "gn:country_code":"SE",
    "gn:dem":18,
    "gn:feature_class":"P",
    "gn:feature_code":"PPL",
    "gn:name":"Skal",
    "gn:population":0,
    "gn:timezone":"Europe/Stockholm",
    "iso:country":"SE",
    "name:deu_x_preferred":[
        "Skal"
    ],
    "name:heb_x_preferred":[
        "\u05e1\u05e7\u05d0\u05dc"
    ],
    "name:rus_x_preferred":[
        "\u041e\u0431\u043e\u043b\u043e\u0447\u043a\u0430"
    ],
    "name:swe_x_preferred":[
        "Skal"
    ],
    "name:ukr_x_preferred":[
        "\u041e\u0431\u043e\u043b\u043e\u043d\u043a\u0430"
    ],
    "wof:name":"Skal",
    "wof:placetype":"locality"
},
  "geometry": {"coordinates":[11.46667,58.31667],"type":"Point"}
}