{
  "type": "Feature",
  "properties": {
    "gn:admin1_code":"28.0",
    "gn:admin2_code":"1484.0",
    "gn:asciiname":"Skal",
    "gn:country_code":"SE",
    "gn:dem":18,
    "gn:feature_class":"P",
    "gn:feature_code":"PPL",
    "gn:name":"Skal",
    "gn:population":0,
    "gn:timezone":"Europe/Stockholm",
    "iso:country":"SE",
    "wof:name":"Skal",
    "wof:placetype":"locality"
},
  "geometry": {"coordinates":[11.46667,58.31667],"type":"Point"}
}