{
  "type": "Feature",
  "properties": {
    "gn:admin1_code":"28.0",
    "gn:admin2_code":"1446.0",
    "gn:asciiname":"Lindhult",
    "gn:country_code":"SE",
    "gn:dem":166,
    "gn:feature_class":"P",
    "gn:feature_code":"PPL",
    "gn:name":"Lindhult",
    "gn:population":0,
    "gn:timezone":"Europe/Stockholm",
    "iso:country":"SE",
    "wof:name":"Lindhult",
    "wof:placetype":"locality"
},
  "geometry": {"coordinates":[14.41667,58.73333],"type":"Point"}
}