{
  "type": "Feature",
  "properties": {
    "gn:admin1_code":"9.0",
    "gn:admin2_code":"881.0",
    "gn:asciiname":"Sodra Svalehult",
    "gn:country_code":"SE",
    "gn:dem":102,
    "gn:feature_class":"P",
    "gn:feature_code":"PPL",
    "gn:name":"S\u00f6dra Svalehult",
    "gn:population":0,
    "gn:timezone":"Europe/Stockholm",
    "iso:country":"SE",
    "name:nor_x_preferred":[
        "S\u00f6dra Svalehult"
    ],
    "name:nor_x_variant":[
        "S\u00f8dra Svalehult"
    ],
    "name:und_x_variant":[
        "S\u00f6dra Svalehult"
    ],
    "wof:name":"Sodra Svalehult",
    "wof:placetype":"locality"
},
  "geometry": {"coordinates":[15.85,56.68333000000001],"type":"Point"}
}