{
  "type": "Feature",
  "properties": {
    "gn:admin1_code":"25.0",
    "gn:admin2_code":"1980.0",
    "gn:admin3_code":"198016.0",
    "gn:admin4_code":"2325.0",
    "gn:asciiname":"Hedensberg",
    "gn:country_code":"SE",
    "gn:dem":40,
    "gn:feature_class":"P",
    "gn:feature_code":"PPL",
    "gn:name":"Hedensberg",
    "gn:population":0,
    "gn:timezone":"Europe/Stockholm",
    "iso:country":"SE",
    "wof:name":"Hedensberg",
    "wof:placetype":"locality"
},
  "geometry": {"coordinates":[16.64909,59.6995],"type":"Point"}
}