{
  "type": "Feature",
  "properties": {
    "gn:admin1_code":"9.0",
    "gn:admin2_code":"880.0",
    "gn:asciiname":"Kettilshult",
    "gn:cc2":"SE",
    "gn:country_code":"SE",
    "gn:dem":59,
    "gn:feature_class":"P",
    "gn:feature_code":"PPL",
    "gn:name":"Kettilshult",
    "gn:population":0,
    "gn:timezone":"Europe/Stockholm",
    "iso:country":"SE",
    "name:und_x_variant":[
        "K\u00e4ttilhult",
        "Kettilshult"
    ],
    "wof:name":"Kettilshult",
    "wof:placetype":"locality"
},
  "geometry": {"coordinates":[15.96667,56.55],"type":"Point"}
}