{
  "type": "Feature",
  "properties": {
    "gn:admin1_code":"10.0",
    "gn:admin2_code":"2039.0",
    "gn:asciiname":"Flickerbacken",
    "gn:country_code":"SE",
    "gn:dem":647,
    "gn:feature_class":"P",
    "gn:feature_code":"PPL",
    "gn:name":"Flickerb\u00e4cken",
    "gn:population":0,
    "gn:timezone":"Europe/Stockholm",
    "iso:country":"SE",
    "wof:name":"Flickerbacken",
    "wof:placetype":"locality"
},
  "geometry": {"coordinates":[12.41667,61.81667],"type":"Point"}
}