{
  "type": "Feature",
  "properties": {
    "gn:admin1_code":"28.0",
    "gn:admin2_code":"1498.0",
    "gn:asciiname":"Homb",
    "gn:country_code":"SE",
    "gn:dem":142,
    "gn:feature_class":"P",
    "gn:feature_code":"PPL",
    "gn:name":"H\u00f6mb",
    "gn:population":0,
    "gn:timezone":"Europe/Stockholm",
    "iso:country":"SE",
    "name:nor_x_preferred":[
        "H\u00f6mb"
    ],
    "name:nor_x_variant":[
        "H\u00f8mb"
    ],
    "name:und_x_variant":[
        "H\u00f6mb"
    ],
    "wof:name":"Homb",
    "wof:placetype":"locality"
},
  "geometry": {"coordinates":[13.88333,58.23333],"type":"Point"}
}