{
  "type": "Feature",
  "properties": {
    "gn:admin1_code":"18.0",
    "gn:admin2_code":"484.0",
    "gn:asciiname":"Nybybruk",
    "gn:cc2":"SE",
    "gn:country_code":"SE",
    "gn:dem":14,
    "gn:feature_class":"P",
    "gn:feature_code":"PPL",
    "gn:name":"Nybybruk",
    "gn:population":0,
    "gn:timezone":"Europe/Stockholm",
    "iso:country":"SE",
    "name:und_x_variant":[
        "Nyby",
        "Nybybruk"
    ],
    "wof:name":"Nybybruk",
    "wof:placetype":"locality"
},
  "geometry": {"coordinates":[16.45,59.43333000000001],"type":"Point"}
}