{
  "type": "Feature",
  "properties": {
    "gn:gn_country":"SE",
    "gn:gn_fcode":"PPL",
    "gn:gn_pop":0,
    "iso:country":"SE",
    "name:dan_x_preferred":[
        "Rammsj\u00f6strand"
    ],
    "name:deu_x_preferred":[
        "Rammsj\u00f6strand"
    ],
    "name:eng_x_preferred":[
        "Rammsj\u00f6strand"
    ],
    "name:fra_x_preferred":[
        "Rammsj\u00f6strand"
    ],
    "name:nds_x_preferred":[
        "Rammsj\u00f6strand"
    ],
    "name:nld_x_preferred":[
        "Rammsj\u00f6strand"
    ],
    "name:nno_x_preferred":[
        "Rammsj\u00f6strand"
    ],
    "name:nob_x_preferred":[
        "Rammsj\u00f6strand"
    ],
    "name:nor_x_preferred":[
        "Rammsj\u00f8strand"
    ],
    "name:nor_x_variant":[
        "Rammsj\u00f6strand"
    ],
    "name:swe_x_preferred":[
        "Rammsj\u00f6strand"
    ],
    "name:unk_x_variant":[
        "Ramsj\u00f6hamn"
    ],
    "qs_pg:aaroncc":"SE",
    "qs_pg:gn_country":"SE",
    "qs_pg:gn_fcode":"PPL",
    "qs_pg:gn_pop":0,
    "qs_pg:name":"Ramsj\u00f6strand",
    "qs_pg:name_adm0":"Sverige",
    "qs_pg:name_adm1":"Sk\u00e5ne L\u00e4n",
    "qs_pg:photos":6,
    "qs_pg:photos_1k":1,
    "qs_pg:photos_9k":1,
    "qs_pg:photos_9r":1,
    "qs_pg:photos_all":6,
    "qs_pg:photos_sr":1,
    "qs_pg:pop_sr":0,
    "qs_pg:qs_pg_placetype":"locality",
    "qs_pg:qs_pg_placetype_gp":"Town",
    "qs_pg:woe_adm0":23424954,
    "woe:adm0_id":23424954,
    "woe:name_adm0":"Sverige",
    "woe:name_adm1":"Sk\u00e5ne L\u00e4n",
    "woe:placetype":"Town",
    "wof:name":"Ramsj\u00f6strand",
    "wof:placetype":"locality"
},
  "geometry": {"coordinates":[12.66667,56.38333],"type":"Point"}
}