{
  "type": "Feature",
  "properties": {
    "gn:admin1_code":"16.0",
    "gn:admin2_code":"580.0",
    "gn:asciiname":"Hult",
    "gn:country_code":"SE",
    "gn:dem":71,
    "gn:feature_class":"P",
    "gn:feature_code":"PPL",
    "gn:name":"Hult",
    "gn:population":0,
    "gn:timezone":"Europe/Stockholm",
    "iso:country":"SE",
    "wof:name":"Hult",
    "wof:placetype":"locality"
},
  "geometry": {"coordinates":[15.66667,58.55],"type":"Point"}
}