{
  "type": "Feature",
  "properties": {
    "gn:admin1_code":"21.0",
    "gn:asciiname":"Aby",
    "gn:country_code":"SE",
    "gn:dem":34,
    "gn:feature_class":"P",
    "gn:feature_code":"PPL",
    "gn:name":"\u00c5by",
    "gn:population":0,
    "gn:timezone":"Europe/Stockholm",
    "iso:country":"SE",
    "name:cym_x_preferred":[
        "Aby"
    ],
    "name:pol_x_preferred":[
        "Aby"
    ],
    "wof:name":"Aby",
    "wof:placetype":"locality"
},
  "geometry": {"coordinates":[17.18333,60.18333000000001],"type":"Point"}
}