{
  "type": "Feature",
  "properties": {
    "gn:admin1_code":"14.0",
    "gn:admin2_code":"2523.0",
    "gn:asciiname":"Sjungberget",
    "gn:cc2":"SE",
    "gn:country_code":"SE",
    "gn:dem":275,
    "gn:feature_class":"P",
    "gn:feature_code":"PPL",
    "gn:name":"Sjungberget",
    "gn:population":0,
    "gn:timezone":"Europe/Stockholm",
    "iso:country":"SE",
    "name:und_x_variant":[
        "Juoikam",
        "Sjungberget"
    ],
    "wof:name":"Sjungberget",
    "wof:placetype":"locality"
},
  "geometry": {"coordinates":[21.05,67.15000000000001],"type":"Point"}
}