{
  "type": "Feature",
  "properties": {
    "gn:admin1_code":"23.0",
    "gn:admin2_code":"2403.0",
    "gn:asciiname":"Hogas",
    "gn:country_code":"SE",
    "gn:dem":158,
    "gn:feature_class":"P",
    "gn:feature_code":"PPL",
    "gn:name":"H\u00f6g\u00e5s",
    "gn:population":0,
    "gn:timezone":"Europe/Stockholm",
    "iso:country":"SE",
    "name:nor_x_preferred":[
        "H\u00f6g\u00e5s"
    ],
    "name:nor_x_variant":[
        "H\u00f8g\u00e5s"
    ],
    "name:und_x_variant":[
        "H\u00f6g\u00e5s"
    ],
    "wof:name":"Hogas",
    "wof:placetype":"locality"
},
  "geometry": {"coordinates":[19.18333,63.91667],"type":"Point"}
}