{
  "type": "Feature",
  "properties": {
    "gn:admin1_code":"27.0",
    "gn:admin2_code":"1292.0",
    "gn:asciiname":"Harninge",
    "gn:cc2":"SE",
    "gn:country_code":"SE",
    "gn:dem":32,
    "gn:feature_class":"P",
    "gn:feature_code":"PPL",
    "gn:name":"H\u00e4rninge",
    "gn:population":0,
    "gn:timezone":"Europe/Stockholm",
    "iso:country":"SE",
    "name:und_x_variant":[
        "H\u00f6rninge",
        "H\u00e4rninge"
    ],
    "wof:name":"Harninge",
    "wof:placetype":"locality"
},
  "geometry": {"coordinates":[12.91667,56.18333000000001],"type":"Point"}
}