{
  "type": "Feature",
  "properties": {
    "gn:admin1_code":"12.0",
    "gn:admin2_code":"764.0",
    "gn:asciiname":"Braten",
    "gn:country_code":"SE",
    "gn:dem":232,
    "gn:feature_class":"P",
    "gn:feature_code":"PPL",
    "gn:name":"Br\u00e5ten",
    "gn:population":0,
    "gn:timezone":"Europe/Stockholm",
    "iso:country":"SE",
    "wof:name":"Braten",
    "wof:placetype":"locality"
},
  "geometry": {"coordinates":[14.48333,57.05],"type":"Point"}
}