{
  "type": "Feature",
  "properties": {
    "gn:gn_country":"SE",
    "gn:gn_fcode":"PPL",
    "gn:gn_pop":458,
    "gn:population":458,
    "iso:country":"SE",
    "name:ceb_x_preferred":[
        "Johansfors"
    ],
    "name:dan_x_preferred":[
        "Johansfors"
    ],
    "name:deu_x_preferred":[
        "Johansfors"
    ],
    "name:eng_x_preferred":[
        "Johansfors"
    ],
    "name:fra_x_preferred":[
        "Johansfors"
    ],
    "name:nds_x_preferred":[
        "Johansfors"
    ],
    "name:nld_x_preferred":[
        "Johansfors"
    ],
    "name:nno_x_preferred":[
        "Johansfors"
    ],
    "name:nob_x_preferred":[
        "Johansfors"
    ],
    "name:swe_x_preferred":[
        "Johansfors"
    ],
    "qs_pg:aaroncc":"SE",
    "qs_pg:gn_country":"SE",
    "qs_pg:gn_fcode":"PPL",
    "qs_pg:gn_pop":458,
    "qs_pg:name":"Johansfors",
    "qs_pg:name_adm0":"Sverige",
    "qs_pg:name_adm1":"Hallands L\u00e4n",
    "qs_pg:photos_9k":1,
    "qs_pg:photos_9r":3,
    "qs_pg:photos_all":104,
    "qs_pg:photos_sr":0,
    "qs_pg:pop_sr":2,
    "qs_pg:qs_pg_placetype":"locality",
    "qs_pg:qs_pg_placetype_gp":"Town",
    "qs_pg:woe_adm0":23424954,
    "woe:adm0_id":23424954,
    "woe:name_adm0":"Sverige",
    "woe:name_adm1":"Hallands L\u00e4n",
    "woe:placetype":"Town",
    "wof:name":"Johansfors",
    "wof:placetype":"locality",
    "wof:population":458
},
  "geometry": {"coordinates":[12.98333,56.83333],"type":"Point"}
}