{
  "type": "Feature",
  "properties": {
    "gn:admin1_code":"24.0",
    "gn:admin2_code":"2282.0",
    "gn:admin3_code":"228211.0",
    "gn:admin4_code":"2511.0",
    "gn:asciiname":"Sjobotten",
    "gn:country_code":"SE",
    "gn:dem":113,
    "gn:feature_class":"P",
    "gn:feature_code":"PPL",
    "gn:name":"Sj\u00f6botten",
    "gn:population":0,
    "gn:timezone":"Europe/Stockholm",
    "iso:country":"SE",
    "name:nor_x_preferred":[
        "Sj\u00f6botten"
    ],
    "name:nor_x_variant":[
        "Sj\u00f8botten"
    ],
    "wof:name":"Sjobotten",
    "wof:placetype":"locality"
},
  "geometry": {"coordinates":[17.45007,63.01956],"type":"Point"}
}