{
  "type": "Feature",
  "properties": {
    "gn:admin1_code":"10.0",
    "gn:admin2_code":"2083.0",
    "gn:asciiname":"Skottbo",
    "gn:country_code":"SE",
    "gn:dem":152,
    "gn:feature_class":"P",
    "gn:feature_code":"PPL",
    "gn:name":"Sk\u00f6ttbo",
    "gn:population":0,
    "gn:timezone":"Europe/Stockholm",
    "iso:country":"SE",
    "name:nor_x_preferred":[
        "Sk\u00f6ttbo"
    ],
    "name:nor_x_variant":[
        "Sk\u00f8ttbo"
    ],
    "name:und_x_variant":[
        "Sk\u00f6ttbo"
    ],
    "wof:name":"Skottbo",
    "wof:placetype":"locality"
},
  "geometry": {"coordinates":[15.88333,60.23333],"type":"Point"}
}