{
  "type": "Feature",
  "properties": {
    "gn:country":"SE",
    "gn:fcode":"PPLL",
    "gn:population":185,
    "iso:country":"SE",
    "name:ceb_x_preferred":[
        "Vita villorna"
    ],
    "name:dan_x_preferred":[
        "Vita villorna"
    ],
    "name:deu_x_preferred":[
        "Vita villorna"
    ],
    "name:eng_x_preferred":[
        "Vita villorna"
    ],
    "name:fra_x_preferred":[
        "Vita villorna"
    ],
    "name:nds_x_preferred":[
        "Vita villorna"
    ],
    "name:nld_x_preferred":[
        "Vita villorna"
    ],
    "name:nno_x_preferred":[
        "Vita villorna"
    ],
    "name:nob_x_preferred":[
        "Vita villorna"
    ],
    "name:swe_x_preferred":[
        "Vita villorna"
    ],
    "qs_pg:aaroncc":"SE",
    "qs_pg:gn_country":"SE",
    "qs_pg:gn_fcode":"PPLL",
    "qs_pg:gn_pop":185,
    "qs_pg:name":"Vita villorna",
    "qs_pg:name_adm0":"Sverige",
    "qs_pg:name_adm1":"Stockholms L\u00e4n",
    "qs_pg:photos_9k":1,
    "qs_pg:photos_9r":2,
    "qs_pg:photos_all":30,
    "qs_pg:photos_sr":0,
    "qs_pg:pop_sr":1,
    "qs_pg:qs_pg_placetype":"locality",
    "qs_pg:qs_pg_placetype_gp":"Town",
    "qs_pg:woe_adm0":23424954,
    "woe:adm0_id":23424954,
    "woe:name_adm0":"Sverige",
    "woe:name_adm1":"Stockholms L\u00e4n",
    "woe:placetype":"Town",
    "wof:name":"Vita villorna",
    "wof:placetype":"locality",
    "wof:population":185
},
  "geometry": {"coordinates":[17.87194,59.20861],"type":"Point"}
}