{
  "type": "Feature",
  "properties": {
    "gn:admin1_code":"9.0",
    "gn:admin2_code":"883.0",
    "gn:asciiname":"Berget",
    "gn:country_code":"SE",
    "gn:dem":9,
    "gn:feature_class":"P",
    "gn:feature_code":"PPL",
    "gn:name":"Berget",
    "gn:population":0,
    "gn:timezone":"Europe/Stockholm",
    "iso:country":"SE",
    "wof:name":"Berget",
    "wof:placetype":"locality"
},
  "geometry": {"coordinates":[16.42722,57.89056],"type":"Point"}
}