{
  "type": "Feature",
  "properties": {
    "gn:admin1_code":"27",
    "gn:admin2_code":"1286.0",
    "gn:admin3_code":"128617.0",
    "gn:admin4_code":"1086.0",
    "gn:asciiname":"Ekesakra",
    "gn:country_code":"SE",
    "gn:dem":8,
    "gn:feature_class":"P",
    "gn:feature_code":"PPL",
    "gn:name":"Ekes\u00e5kra",
    "gn:population":0,
    "gn:timezone":"Europe/Stockholm",
    "iso:country":"SE",
    "wof:name":"Ekesakra",
    "wof:placetype":"locality"
},
  "geometry": {"coordinates":[14.16346,55.4012],"type":"Point"}
}