{
  "type": "Feature",
  "properties": {
    "gn:admin1_code":"28.0",
    "gn:admin2_code":"1465.0",
    "gn:asciiname":"Malhult",
    "gn:country_code":"SE",
    "gn:dem":218,
    "gn:feature_class":"P",
    "gn:feature_code":"PPL",
    "gn:name":"M\u00e5lhult",
    "gn:population":0,
    "gn:timezone":"Europe/Stockholm",
    "iso:country":"SE",
    "wof:name":"Malhult",
    "wof:placetype":"locality"
},
  "geometry": {"coordinates":[12.91667,57.43333000000001],"type":"Point"}
}