{
  "type": "Feature",
  "properties": {
    "gn:admin1_code":"16.0",
    "gn:admin2_code":"513.0",
    "gn:asciiname":"Drattinge",
    "gn:country_code":"SE",
    "gn:dem":91,
    "gn:feature_class":"P",
    "gn:feature_code":"PPL",
    "gn:name":"Dr\u00e4ttinge",
    "gn:population":0,
    "gn:timezone":"Europe/Stockholm",
    "iso:country":"SE",
    "wof:name":"Drattinge",
    "wof:placetype":"locality"
},
  "geometry": {"coordinates":[15.75,58.06667],"type":"Point"}
}