{
  "type": "Feature",
  "properties": {
    "gn:admin1_code":"14.0",
    "gn:admin2_code":"2581.0",
    "gn:asciiname":"Risnabben",
    "gn:country_code":"SE",
    "gn:dem":356,
    "gn:feature_class":"P",
    "gn:feature_code":"PPL",
    "gn:name":"Risnabben",
    "gn:population":0,
    "gn:timezone":"Europe/Stockholm",
    "iso:country":"SE",
    "name:swe_x_preferred":[
        "Risnabben"
    ],
    "wof:name":"Risnabben",
    "wof:placetype":"locality"
},
  "geometry": {"coordinates":[19.95088,65.40136],"type":"Point"}
}