{
  "type": "Feature",
  "properties": {
    "gn:admin1_code":"21.0",
    "gn:admin2_code":"360.0",
    "gn:asciiname":"Stav",
    "gn:country_code":"SE",
    "gn:dem":29,
    "gn:feature_class":"P",
    "gn:feature_code":"PPL",
    "gn:name":"Stav",
    "gn:population":0,
    "gn:timezone":"Europe/Stockholm",
    "iso:country":"SE",
    "name:ceb_x_preferred":[
        "Stav"
    ],
    "name:ces_x_preferred":[
        "Stav"
    ],
    "name:deu_x_preferred":[
        "Stav"
    ],
    "name:slk_x_preferred":[
        "Stav"
    ],
    "name:srp_x_preferred":[
        "\u0421\u0442\u0430\u0432"
    ],
    "name:swe_x_preferred":[
        "Stav"
    ],
    "wof:name":"Stav",
    "wof:placetype":"locality"
},
  "geometry": {"coordinates":[17.61667000000001,60.45],"type":"Point"}
}