{
  "type": "Feature",
  "properties": {
    "gn:admin1_code":"3.0",
    "gn:admin2_code":"2161.0",
    "gn:asciiname":"Gunnarsbo",
    "gn:country_code":"SE",
    "gn:dem":162,
    "gn:feature_class":"P",
    "gn:feature_code":"PPL",
    "gn:name":"Gunnarsbo",
    "gn:population":0,
    "gn:timezone":"Europe/Stockholm",
    "iso:country":"SE",
    "wof:name":"Gunnarsbo",
    "wof:placetype":"locality"
},
  "geometry": {"coordinates":[16.28333,61.88333000000001],"type":"Point"}
}