{
  "type": "Feature",
  "properties": {
    "gn:gn_country":"SE",
    "gn:gn_fcode":"PPL",
    "gn:gn_pop":251,
    "gn:population":272,
    "iso:country":"SE",
    "name:eng_x_preferred":[
        "Hj\u00e4lm"
    ],
    "name:fra_x_preferred":[
        "Hj\u00e4lm"
    ],
    "name:nan_x_preferred":[
        "Hj\u00e4lm"
    ],
    "name:nld_x_preferred":[
        "Hj\u00e4lm"
    ],
    "name:nno_x_preferred":[
        "Hj\u00e4lm"
    ],
    "name:nob_x_preferred":[
        "Hj\u00e4lm"
    ],
    "name:swe_x_preferred":[
        "Hj\u00e4lm"
    ],
    "qs_pg:aaroncc":"SE",
    "qs_pg:gn_country":"SE",
    "qs_pg:gn_fcode":"PPL",
    "qs_pg:gn_pop":251,
    "qs_pg:name":"Hj\u00e4lm",
    "qs_pg:name_adm0":"Sverige",
    "qs_pg:name_adm1":"Hallands L\u00e4n",
    "qs_pg:photos_9k":1,
    "qs_pg:photos_9r":1,
    "qs_pg:photos_all":9,
    "qs_pg:photos_sr":0,
    "qs_pg:pop_sr":2,
    "qs_pg:qs_pg_placetype":"locality",
    "qs_pg:qs_pg_placetype_gp":"Town",
    "qs_pg:woe_adm0":23424954,
    "woe:adm0_id":23424954,
    "woe:name_adm0":"Sverige",
    "woe:name_adm1":"Hallands L\u00e4n",
    "woe:placetype":"Town",
    "wof:name":"Hj\u00e4lm",
    "wof:placetype":"locality",
    "wof:population":272
},
  "geometry": {"coordinates":[12.16607,57.49401],"type":"Point"}
}