{
  "type": "Feature",
  "properties": {
    "gn:admin1_code":"18.0",
    "gn:admin2_code":"428.0",
    "gn:asciiname":"Skogstorp",
    "gn:country_code":"SE",
    "gn:dem":48,
    "gn:feature_class":"P",
    "gn:feature_code":"PPL",
    "gn:name":"Skogstorp",
    "gn:population":0,
    "gn:timezone":"Europe/Stockholm",
    "iso:country":"SE",
    "name:fra_x_preferred":[
        "Skogstorp"
    ],
    "name:ita_x_preferred":[
        "Skogstorp"
    ],
    "name:nld_x_preferred":[
        "Skogstorp"
    ],
    "name:swe_x_preferred":[
        "Skogstorp"
    ],
    "wof:name":"Skogstorp",
    "wof:placetype":"locality"
},
  "geometry": {"coordinates":[15.91667,59.15],"type":"Point"}
}