{
  "type": "Feature",
  "properties": {
    "gn:admin1_code":"23.0",
    "gn:admin2_code":"2481.0",
    "gn:asciiname":"Knaften",
    "gn:country_code":"SE",
    "gn:dem":352,
    "gn:feature_class":"P",
    "gn:feature_code":"PPL",
    "gn:name":"Knaften",
    "gn:population":0,
    "gn:timezone":"Europe/Stockholm",
    "iso:country":"SE",
    "wof:name":"Knaften",
    "wof:placetype":"locality"
},
  "geometry": {"coordinates":[18.63333,64.45],"type":"Point"}
}