{
  "type": "Feature",
  "properties": {
    "gn:admin1_code":"16.0",
    "gn:admin2_code":"563.0",
    "gn:asciiname":"Mossebo",
    "gn:country_code":"SE",
    "gn:dem":26,
    "gn:feature_class":"P",
    "gn:feature_code":"PPL",
    "gn:name":"Mossebo",
    "gn:population":0,
    "gn:timezone":"Europe/Stockholm",
    "iso:country":"SE",
    "wof:name":"Mossebo",
    "wof:placetype":"locality"
},
  "geometry": {"coordinates":[16.55,58.21666999999999],"type":"Point"}
}