{
  "type": "Feature",
  "properties": {
    "gn:admin1_code":"8.0",
    "gn:admin2_code":"680.0",
    "gn:asciiname":"Fagerslatt",
    "gn:country_code":"SE",
    "gn:dem":279,
    "gn:feature_class":"P",
    "gn:feature_code":"PPL",
    "gn:name":"Fagersl\u00e4tt",
    "gn:population":0,
    "gn:timezone":"Europe/Stockholm",
    "iso:country":"SE",
    "wof:name":"Fagerslatt",
    "wof:placetype":"locality"
},
  "geometry": {"coordinates":[14.31667,57.68333000000001],"type":"Point"}
}