{
  "type": "Feature",
  "properties": {
    "gn:admin1_code":"28.0",
    "gn:admin2_code":"1481.0",
    "gn:asciiname":"Toltorp",
    "gn:country_code":"SE",
    "gn:dem":47,
    "gn:feature_class":"P",
    "gn:feature_code":"PPL",
    "gn:name":"Toltorp",
    "gn:population":0,
    "gn:timezone":"Europe/Stockholm",
    "iso:country":"SE",
    "wof:name":"Toltorp",
    "wof:placetype":"locality"
},
  "geometry": {"coordinates":[11.98333,57.66667],"type":"Point"}
}