{
  "type": "Feature",
  "properties": {
    "gn:admin1_code":"26.0",
    "gn:admin2_code":"192.0",
    "gn:asciiname":"Norsbol",
    "gn:cc2":"SE",
    "gn:country_code":"SE",
    "gn:dem":15,
    "gn:feature_class":"P",
    "gn:feature_code":"PPL",
    "gn:name":"Norsbol",
    "gn:population":0,
    "gn:timezone":"Europe/Stockholm",
    "iso:country":"SE",
    "name:und_x_variant":[
        "Norsbo",
        "Norsbol"
    ],
    "wof:name":"Norsbol",
    "wof:placetype":"locality"
},
  "geometry": {"coordinates":[17.86222,58.91861],"type":"Point"}
}