{
  "type": "Feature",
  "properties": {
    "gn:admin1_code":"28.0",
    "gn:admin2_code":"1492.0",
    "gn:asciiname":"Stora Kilane",
    "gn:country_code":"SE",
    "gn:dem":90,
    "gn:feature_class":"P",
    "gn:feature_code":"PPL",
    "gn:name":"Stora Kilane",
    "gn:population":0,
    "gn:timezone":"Europe/Stockholm",
    "iso:country":"SE",
    "wof:name":"Stora Kilane",
    "wof:placetype":"locality"
},
  "geometry": {"coordinates":[12.48333,58.86666999999999],"type":"Point"}
}