{
  "type": "Feature",
  "properties": {
    "gn:admin1_code":"22.0",
    "gn:admin2_code":"1766.0",
    "gn:asciiname":"Bogerud",
    "gn:country_code":"SE",
    "gn:dem":132,
    "gn:feature_class":"P",
    "gn:feature_code":"PPL",
    "gn:name":"Bogerud",
    "gn:population":0,
    "gn:timezone":"Europe/Stockholm",
    "iso:country":"SE",
    "name:nor_x_preferred":[
        "Bogerud"
    ],
    "wof:name":"Bogerud",
    "wof:placetype":"locality"
},
  "geometry": {"coordinates":[13.33333,59.76667],"type":"Point"}
}