{
  "type": "Feature",
  "properties": {
    "gn:admin1_code":"24.0",
    "gn:admin2_code":"2283.0",
    "gn:asciiname":"Stondar",
    "gn:country_code":"SE",
    "gn:dem":7,
    "gn:feature_class":"P",
    "gn:feature_code":"PPL",
    "gn:name":"St\u00f6ndar",
    "gn:population":0,
    "gn:timezone":"Europe/Stockholm",
    "iso:country":"SE",
    "name:nor_x_preferred":[
        "St\u00f6ndar"
    ],
    "name:nor_x_variant":[
        "St\u00f8ndar"
    ],
    "name:und_x_variant":[
        "St\u00f6ndar"
    ],
    "wof:name":"Stondar",
    "wof:placetype":"locality"
},
  "geometry": {"coordinates":[17.73333,63.15],"type":"Point"}
}