{
  "type": "Feature",
  "properties": {
    "gn:admin1_code":"7.0",
    "gn:admin2_code":"2313.0",
    "gn:asciiname":"Frostviksbranna",
    "gn:cc2":"SE",
    "gn:country_code":"SE",
    "gn:dem":338,
    "gn:feature_class":"P",
    "gn:feature_code":"PPL",
    "gn:name":"Frostviksbr\u00e4nna",
    "gn:population":0,
    "gn:timezone":"Europe/Stockholm",
    "iso:country":"SE",
    "name:und_x_variant":[
        "Frostviken",
        "Frostviksbr\u00e4nna"
    ],
    "wof:name":"Frostviksbranna",
    "wof:placetype":"locality"
},
  "geometry": {"coordinates":[13.76667,64.65000000000001],"type":"Point"}
}