{
  "type": "Feature",
  "properties": {
    "gn:admin1_code":"16.0",
    "gn:admin2_code":"561.0",
    "gn:asciiname":"Frangsbo",
    "gn:country_code":"SE",
    "gn:dem":93,
    "gn:feature_class":"P",
    "gn:feature_code":"PPL",
    "gn:name":"Fr\u00e4ngsbo",
    "gn:population":0,
    "gn:timezone":"Europe/Stockholm",
    "iso:country":"SE",
    "wof:name":"Frangsbo",
    "wof:placetype":"locality"
},
  "geometry": {"coordinates":[16.11667000000001,58.26667],"type":"Point"}
}