{
  "type": "Feature",
  "properties": {
    "gn:admin1_code":"22.0",
    "gn:admin2_code":"1783.0",
    "gn:asciiname":"Hornas",
    "gn:cc2":"SE",
    "gn:country_code":"SE",
    "gn:dem":150,
    "gn:feature_class":"P",
    "gn:feature_code":"PPL",
    "gn:name":"Horn\u00e4s",
    "gn:population":0,
    "gn:timezone":"Europe/Stockholm",
    "iso:country":"SE",
    "name:und_x_variant":[
        "Hornn\u00e4s",
        "Horn\u00e4s"
    ],
    "wof:name":"Hornas",
    "wof:placetype":"locality"
},
  "geometry": {"coordinates":[13.45,60.25],"type":"Point"}
}