{
  "type": "Feature",
  "properties": {
    "gn:admin1_code":"23.0",
    "gn:admin2_code":"2404.0",
    "gn:asciiname":"Norrliden",
    "gn:country_code":"SE",
    "gn:dem":255,
    "gn:feature_class":"P",
    "gn:feature_code":"PPL",
    "gn:name":"Norrliden",
    "gn:population":0,
    "gn:timezone":"Europe/Stockholm",
    "iso:country":"SE",
    "wof:name":"Norrliden",
    "wof:placetype":"locality"
},
  "geometry": {"coordinates":[19.76667,64.41667],"type":"Point"}
}