{
  "type": "Feature",
  "properties": {
    "gn:admin1_code":"18.0",
    "gn:admin2_code":"484.0",
    "gn:asciiname":"Viby",
    "gn:country_code":"SE",
    "gn:dem":18,
    "gn:feature_class":"P",
    "gn:feature_code":"PPL",
    "gn:name":"Viby",
    "gn:population":0,
    "gn:timezone":"Europe/Stockholm",
    "iso:country":"SE",
    "wof:name":"Viby",
    "wof:placetype":"locality"
},
  "geometry": {"coordinates":[16.65,59.38333000000001],"type":"Point"}
}