{
  "type": "Feature",
  "properties": {
    "gn:admin1_code":"28.0",
    "gn:admin2_code":"1463.0",
    "gn:asciiname":"Dangevik",
    "gn:country_code":"SE",
    "gn:dem":157,
    "gn:feature_class":"P",
    "gn:feature_code":"PPL",
    "gn:name":"D\u00e4ngevik",
    "gn:population":0,
    "gn:timezone":"Europe/Stockholm",
    "iso:country":"SE",
    "wof:name":"Dangevik",
    "wof:placetype":"locality"
},
  "geometry": {"coordinates":[12.91667,57.55],"type":"Point"}
}