{
  "type": "Feature",
  "properties": {
    "gn:admin1_code":"6.0",
    "gn:admin2_code":"1315.0",
    "gn:asciiname":"Boalt",
    "gn:country_code":"SE",
    "gn:dem":176,
    "gn:feature_class":"P",
    "gn:feature_code":"PPL",
    "gn:name":"Boalt",
    "gn:population":0,
    "gn:timezone":"Europe/Stockholm",
    "iso:country":"SE",
    "wof:name":"Boalt",
    "wof:placetype":"locality"
},
  "geometry": {"coordinates":[13.41667,56.91667],"type":"Point"}
}