{
  "type": "Feature",
  "properties": {
    "gn:admin1_code":"2.0",
    "gn:admin2_code":"1081.0",
    "gn:asciiname":"Molleryd",
    "gn:country_code":"SE",
    "gn:dem":56,
    "gn:feature_class":"P",
    "gn:feature_code":"PPL",
    "gn:name":"M\u00f6lleryd",
    "gn:population":0,
    "gn:timezone":"Europe/Stockholm",
    "iso:country":"SE",
    "name:nor_x_preferred":[
        "M\u00f6lleryd"
    ],
    "name:nor_x_variant":[
        "M\u00f8lleryd"
    ],
    "name:und_x_variant":[
        "M\u00f6lleryd"
    ],
    "wof:name":"Molleryd",
    "wof:placetype":"locality"
},
  "geometry": {"coordinates":[15.38333,56.25],"type":"Point"}
}