{
  "type": "Feature",
  "properties": {
    "gn:admin1_code":"27.0",
    "gn:admin2_code":"1283.0",
    "gn:asciiname":"Paarp",
    "gn:country_code":"SE",
    "gn:dem":54,
    "gn:feature_class":"P",
    "gn:feature_code":"PPL",
    "gn:name":"P\u00e5arp",
    "gn:population":2932,
    "gn:timezone":"Europe/Stockholm",
    "iso:country":"SE",
    "name:ceb_x_preferred":[
        "P\u00e5arp"
    ],
    "name:ita_x_preferred":[
        "P\u00e5arp"
    ],
    "name:nld_x_preferred":[
        "P\u00e5arp"
    ],
    "name:nno_x_preferred":[
        "P\u00e5arp"
    ],
    "name:nor_x_preferred":[
        "P\u00e5arp"
    ],
    "name:swe_x_preferred":[
        "P\u00e5arp"
    ],
    "wof:name":"Paarp",
    "wof:placetype":"locality",
    "wof:population":2932
},
  "geometry": {"coordinates":[12.81667,56.03333000000001],"type":"Point"}
}