{
  "type": "Feature",
  "properties": {
    "gn:admin1_code":"22.0",
    "gn:admin2_code":"1785.0",
    "gn:asciiname":"Torp",
    "gn:country_code":"SE",
    "gn:dem":63,
    "gn:feature_class":"P",
    "gn:feature_code":"PPL",
    "gn:name":"Torp",
    "gn:population":0,
    "gn:timezone":"Europe/Stockholm",
    "iso:country":"SE",
    "name:ceb_x_preferred":[
        "Torp"
    ],
    "name:dan_x_preferred":[
        "Torp"
    ],
    "name:deu_x_preferred":[
        "Torp"
    ],
    "name:fra_x_preferred":[
        "Torp"
    ],
    "name:nds_x_preferred":[
        "Torp"
    ],
    "name:nld_x_preferred":[
        "Torp"
    ],
    "name:nor_x_preferred":[
        "Torp"
    ],
    "name:srp_x_preferred":[
        "\u0422\u043e\u0440\u043f"
    ],
    "name:swe_x_preferred":[
        "Torp"
    ],
    "wof:name":"Torp",
    "wof:placetype":"locality"
},
  "geometry": {"coordinates":[12.75,59.26667],"type":"Point"}
}