{
  "type": "Feature",
  "properties": {
    "gn:admin1_code":"27.0",
    "gn:admin2_code":"1283.0",
    "gn:asciiname":"Rogle",
    "gn:country_code":"SE",
    "gn:dem":9,
    "gn:feature_class":"P",
    "gn:feature_code":"PPL",
    "gn:name":"R\u00f6gle",
    "gn:population":0,
    "gn:timezone":"Europe/Stockholm",
    "iso:country":"SE",
    "name:nor_x_preferred":[
        "R\u00f6gle"
    ],
    "name:nor_x_variant":[
        "R\u00f8gle"
    ],
    "wof:name":"Rogle",
    "wof:placetype":"locality"
},
  "geometry": {"coordinates":[12.78333,56.18333000000001],"type":"Point"}
}