{
  "type": "Feature",
  "properties": {
    "gn:admin1_code":"18.0",
    "gn:admin2_code":"484.0",
    "gn:asciiname":"Seldalen",
    "gn:country_code":"SE",
    "gn:dem":48,
    "gn:feature_class":"P",
    "gn:feature_code":"PPL",
    "gn:name":"Seldalen",
    "gn:population":0,
    "gn:timezone":"Europe/Stockholm",
    "iso:country":"SE",
    "wof:name":"Seldalen",
    "wof:placetype":"locality"
},
  "geometry": {"coordinates":[16.45,59.31667],"type":"Point"}
}