{
  "type": "Feature",
  "properties": {
    "gn:admin1_code":"21.0",
    "gn:admin2_code":"382.0",
    "gn:asciiname":"Ed",
    "gn:country_code":"SE",
    "gn:dem":14,
    "gn:feature_class":"P",
    "gn:feature_code":"PPL",
    "gn:name":"Ed",
    "gn:population":0,
    "gn:timezone":"Europe/Stockholm",
    "iso:country":"SE",
    "wof:name":"Ed",
    "wof:placetype":"locality"
},
  "geometry": {"coordinates":[18.33333,60.26667],"type":"Point"}
}