{
  "type": "Feature",
  "properties": {
    "iso:country":"SE",
    "name:bel_x_variant":[
        "\u0422\u044d\u0431\u044e"
    ],
    "name:bul_x_preferred":[
        "\u0422\u0435\u0431\u044e"
    ],
    "name:dan_x_preferred":[
        "T\u00e4by kommun"
    ],
    "name:deu_x_preferred":[
        "T\u00e4by"
    ],
    "name:epo_x_preferred":[
        "T\u00e4by"
    ],
    "name:est_x_preferred":[
        "T\u00e4by vald"
    ],
    "name:eus_x_preferred":[
        "T\u00e4by udalerria"
    ],
    "name:fas_x_preferred":[
        "\u062a\u0627\u0628\u06cc\u060c \u0633\u0648\u0626\u062f"
    ],
    "name:fin_x_preferred":[
        "T\u00e4by"
    ],
    "name:spa_x_preferred":[
        "T\u00e4by"
    ],
    "name:swe_x_preferred":[
        "Ella gard"
    ],
    "qs:gn_adm0_cc":"SE",
    "qs:gn_local":2669772,
    "qs:gn_nam_loc":"T\u00e4by, T\u00e4by, Stockholms L\u00e4n, SE",
    "qs:gn_namadm1":"26",
    "qs:local_max":409,
    "qs:local_sum":1647,
    "qs:localhoods":10,
    "qs:name":"Ella gard",
    "qs:name_adm0":"Sverige",
    "qs:name_adm1":"Stockholms L\u00e4n",
    "qs:name_adm2":"T\u00e4by",
    "qs:name_local":"T\u00e4by",
    "qs:photo_max":62,
    "qs:photo_sum":92,
    "qs:placetype":"Suburb",
    "qs:quad_count":7,
    "qs:woe_adm0":23424954,
    "qs:woe_adm1":2347067,
    "qs:woe_adm2":12587480,
    "qs:woe_lau":0,
    "qs:woe_local":907140,
    "qs:woe_ver":"7.10.0",
    "wof:lang":[
        "swe"
    ],
    "wof:name":"Ella g\u00e5rd",
    "wof:placetype":"neighbourhood"
},
  "geometry": {"coordinates":[18.047547,59.441642],"type":"Point"}
}