{
  "type": "Feature",
  "properties": {
    "gn:admin1_code":"8.0",
    "gn:admin2_code":"665.0",
    "gn:asciiname":"Gunnarsryd",
    "gn:country_code":"SE",
    "gn:dem":249,
    "gn:feature_class":"P",
    "gn:feature_code":"PPL",
    "gn:name":"Gunnarsryd",
    "gn:population":0,
    "gn:timezone":"Europe/Stockholm",
    "iso:country":"SE",
    "wof:name":"Gunnarsryd",
    "wof:placetype":"locality"
},
  "geometry": {"coordinates":[14.33333,57.53333000000001],"type":"Point"}
}