{
  "type": "Feature",
  "properties": {
    "gn:admin1_code":"9.0",
    "gn:admin2_code":"883.0",
    "gn:asciiname":"Vivastemala",
    "gn:country_code":"SE",
    "gn:dem":15,
    "gn:feature_class":"P",
    "gn:feature_code":"PPL",
    "gn:name":"Vivastem\u00e5la",
    "gn:population":0,
    "gn:timezone":"Europe/Stockholm",
    "iso:country":"SE",
    "wof:name":"Vivastemala",
    "wof:placetype":"locality"
},
  "geometry": {"coordinates":[16.60167,57.64583],"type":"Point"}
}