{
  "type": "Feature",
  "properties": {
    "gn:admin1_code":"24.0",
    "gn:admin2_code":"2281.0",
    "gn:asciiname":"Ostanback",
    "gn:country_code":"SE",
    "gn:dem":154,
    "gn:feature_class":"P",
    "gn:feature_code":"PPL",
    "gn:name":"\u00d6stanb\u00e4ck",
    "gn:population":0,
    "gn:timezone":"Europe/Stockholm",
    "iso:country":"SE",
    "wof:name":"Ostanback",
    "wof:placetype":"locality"
},
  "geometry": {"coordinates":[16.71667,62.61666999999999],"type":"Point"}
}