{
  "type": "Feature",
  "properties": {
    "gn:admin1_code":"25.0",
    "gn:admin2_code":"1904.0",
    "gn:asciiname":"Kallfallet",
    "gn:country_code":"SE",
    "gn:dem":236,
    "gn:feature_class":"P",
    "gn:feature_code":"PPL",
    "gn:name":"K\u00e4llfallet",
    "gn:population":0,
    "gn:timezone":"Europe/Stockholm",
    "iso:country":"SE",
    "wof:name":"Kallfallet",
    "wof:placetype":"locality"
},
  "geometry": {"coordinates":[15.51667,59.83333],"type":"Point"}
}