{
  "type": "Feature",
  "properties": {
    "gn:admin1_code":"8.0",
    "gn:admin2_code":"685.0",
    "gn:asciiname":"Rosa",
    "gn:country_code":"SE",
    "gn:dem":183,
    "gn:feature_class":"P",
    "gn:feature_code":"PPL",
    "gn:name":"R\u00f6sa",
    "gn:population":0,
    "gn:timezone":"Europe/Stockholm",
    "iso:country":"SE",
    "name:nor_x_preferred":[
        "R\u00f6sa"
    ],
    "name:nor_x_variant":[
        "R\u00f8sa"
    ],
    "name:und_x_variant":[
        "R\u00f6sa"
    ],
    "wof:name":"Rosa",
    "wof:placetype":"locality"
},
  "geometry": {"coordinates":[15.16667,57.45],"type":"Point"}
}