{
  "type": "Feature",
  "properties": {
    "gn:gn_country":"SE",
    "gn:gn_fcode":"PPL",
    "gn:gn_pop":385,
    "gn:population":472,
    "iso:country":"SE",
    "name:dut_x_preferred":[
        "V\u00e4stanvik"
    ],
    "name:eng_x_preferred":[
        "V\u00e4stanvik"
    ],
    "name:nan_x_preferred":[
        "V\u00e4stanvik"
    ],
    "name:nno_x_preferred":[
        "V\u00e4stanvik"
    ],
    "name:nob_x_preferred":[
        "V\u00e4stanvik"
    ],
    "name:swe_x_preferred":[
        "V\u00e4stanvik"
    ],
    "qs_pg:aaroncc":"SE",
    "qs_pg:gn_country":"SE",
    "qs_pg:gn_fcode":"PPL",
    "qs_pg:gn_pop":385,
    "qs_pg:name":"V\u00e4stanvik",
    "qs_pg:name_adm0":"Sverige",
    "qs_pg:name_adm1":"Dalarnas L\u00e4n",
    "qs_pg:photos_9k":1,
    "qs_pg:photos_9r":1,
    "qs_pg:photos_all":1,
    "qs_pg:photos_sr":0,
    "qs_pg:pop_sr":2,
    "qs_pg:qs_pg_placetype":"locality",
    "qs_pg:qs_pg_placetype_gp":"Town",
    "qs_pg:woe_adm0":23424954,
    "woe:adm0_id":23424954,
    "woe:name_adm0":"Sverige",
    "woe:name_adm1":"Dalarnas L\u00e4n",
    "woe:placetype":"Town",
    "wof:name":"V\u00e4stanvik",
    "wof:placetype":"locality",
    "wof:population":472
},
  "geometry": {"coordinates":[14.95,60.73333],"type":"Point"}
}