{
  "type": "Feature",
  "properties": {
    "gn:admin1_code":"9.0",
    "gn:admin2_code":"885.0",
    "gn:admin3_code":"88502.0",
    "gn:admin4_code":"804.0",
    "gn:asciiname":"Vastra Vassby",
    "gn:country_code":"SE",
    "gn:dem":6,
    "gn:feature_class":"P",
    "gn:feature_code":"PPL",
    "gn:name":"V\u00e4stra V\u00e4ssby",
    "gn:population":0,
    "gn:timezone":"Europe/Stockholm",
    "iso:country":"SE",
    "wof:name":"Vastra Vassby",
    "wof:placetype":"locality"
},
  "geometry": {"coordinates":[16.87118,57.02117],"type":"Point"}
}