{
  "type": "Feature",
  "properties": {
    "gn:admin1_code":"15.0",
    "gn:admin2_code":"1880.0",
    "gn:asciiname":"Lillan",
    "gn:country_code":"SE",
    "gn:dem":40,
    "gn:feature_class":"P",
    "gn:feature_code":"PPL",
    "gn:name":"Lill\u00e5n",
    "gn:population":0,
    "gn:timezone":"Europe/Stockholm",
    "iso:country":"SE",
    "wof:name":"Lillan",
    "wof:placetype":"locality"
},
  "geometry": {"coordinates":[15.21667,59.31667],"type":"Point"}
}