{
  "type": "Feature",
  "properties": {
    "gn:admin1_code":"10.0",
    "gn:admin2_code":"2082.0",
    "gn:asciiname":"Oversatra",
    "gn:cc2":"SE",
    "gn:country_code":"SE",
    "gn:dem":92,
    "gn:feature_class":"P",
    "gn:feature_code":"PPL",
    "gn:name":"\u00d6vers\u00e4tra",
    "gn:population":0,
    "gn:timezone":"Europe/Stockholm",
    "iso:country":"SE",
    "name:und_x_variant":[
        "\u00d6fre S\u00e4tra",
        "\u00d6vers\u00e4tra"
    ],
    "wof:name":"Oversatra",
    "wof:placetype":"locality"
},
  "geometry": {"coordinates":[15.76667,60.41667],"type":"Point"}
}