{
  "type": "Feature",
  "properties": {
    "gn:admin1_code":"14.0",
    "gn:admin2_code":"2506.0",
    "gn:asciiname":"Tjaktjus",
    "gn:country_code":"SE",
    "gn:dem":404,
    "gn:feature_class":"P",
    "gn:feature_code":"PPL",
    "gn:name":"Tj\u00e4ktjus",
    "gn:population":0,
    "gn:timezone":"Europe/Stockholm",
    "iso:country":"SE",
    "name:sju_x_preferred":[
        "Tj\u00e4ktjus"
    ],
    "name:swe_x_preferred":[
        "Tj\u00e4kkjokk"
    ],
    "name:und_x_variant":[
        "Tj\u00e4kjokk"
    ],
    "wof:name":"Tjaktjus",
    "wof:placetype":"locality"
},
  "geometry": {"coordinates":[18.08839,65.71717],"type":"Point"}
}