{
  "type": "Feature",
  "properties": {
    "gn:admin1_code":"14.0",
    "gn:admin2_code":"2506.0",
    "gn:asciiname":"Bergnasudden",
    "gn:country_code":"SE",
    "gn:dem":404,
    "gn:feature_class":"P",
    "gn:feature_code":"PPL",
    "gn:name":"Bergn\u00e4sudden",
    "gn:population":0,
    "gn:timezone":"Europe/Stockholm",
    "iso:country":"SE",
    "name:sju_x_preferred":[
        "Nju\u00f6niesv\u00e1rrie"
    ],
    "name:swe_x_preferred":[
        "Bergn\u00e4sudden"
    ],
    "name:und_x_variant":[
        "S\u00f6dra Bergn\u00e4s",
        "Bergn\u00e4s-udden",
        "Bergn\u00e4s"
    ],
    "wof:name":"Bergnasudden",
    "wof:placetype":"locality"
},
  "geometry": {"coordinates":[18.17502,65.68496999999999],"type":"Point"}
}