{
  "type": "Feature",
  "properties": {
    "iso:country":"SE",
    "name:swe_x_preferred":[
        "Bjursl\u00e4tt"
    ],
    "wof:name":"Bjurslatt",
    "wof:placetype":"neighbourhood"
},
  "geometry": {"coordinates":[11.93015898010304,57.72964207831076],"type":"Point"}
}