{
  "type": "Feature",
  "properties": {
    "gn:admin1_code":"25.0",
    "gn:admin2_code":"1904.0",
    "gn:asciiname":"Stjarnvik",
    "gn:country_code":"SE",
    "gn:dem":123,
    "gn:feature_class":"P",
    "gn:feature_code":"PPL",
    "gn:name":"Stj\u00e4rnvik",
    "gn:population":0,
    "gn:timezone":"Europe/Stockholm",
    "iso:country":"SE",
    "wof:name":"Stjarnvik",
    "wof:placetype":"locality"
},
  "geometry": {"coordinates":[15.83333,59.86666999999999],"type":"Point"}
}