{
  "type": "Feature",
  "properties": {
    "gn:admin1_code":"14.0",
    "gn:admin2_code":"2505.0",
    "gn:asciiname":"Granudden",
    "gn:country_code":"SE",
    "gn:dem":333,
    "gn:feature_class":"P",
    "gn:feature_code":"PPL",
    "gn:name":"Granudden",
    "gn:population":0,
    "gn:timezone":"Europe/Stockholm",
    "iso:country":"SE",
    "name:sju_x_preferred":[
        "Guossanju\u00f6nies"
    ],
    "name:swe_x_preferred":[
        "Granudden"
    ],
    "wof:name":"Granudden",
    "wof:placetype":"locality"
},
  "geometry": {"coordinates":[19.63774,65.51313],"type":"Point"}
}