{
  "type": "Feature",
  "properties": {
    "gn:admin1_code":"28.0",
    "gn:admin2_code":"1419.0",
    "gn:asciiname":"Vadholmen",
    "gn:country_code":"SE",
    "gn:dem":4,
    "gn:feature_class":"P",
    "gn:feature_code":"PPL",
    "gn:name":"Vadholmen",
    "gn:population":0,
    "gn:timezone":"Europe/Stockholm",
    "iso:country":"SE",
    "wof:name":"Vadholmen",
    "wof:placetype":"locality"
},
  "geometry": {"coordinates":[11.66667,58.05833000000001],"type":"Point"}
}