{
  "type": "Feature",
  "properties": {
    "gn:admin1_code":"26.0",
    "gn:admin2_code":"120.0",
    "gn:asciiname":"Ingmarso",
    "gn:country_code":"SE",
    "gn:dem":19,
    "gn:feature_class":"P",
    "gn:feature_code":"PPL",
    "gn:name":"Ingmars\u00f6",
    "gn:population":0,
    "gn:timezone":"Europe/Stockholm",
    "iso:country":"SE",
    "name:nor_x_preferred":[
        "Ingmars\u00f6"
    ],
    "name:nor_x_variant":[
        "Ingmars\u00f8"
    ],
    "name:und_x_variant":[
        "Ingmars\u00f6"
    ],
    "wof:name":"Ingmarso",
    "wof:placetype":"locality"
},
  "geometry": {"coordinates":[18.74944,59.4675],"type":"Point"}
}