{
  "type": "Feature",
  "properties": {
    "gn:admin1_code":"28.0",
    "gn:admin2_code":"1460.0",
    "gn:asciiname":"Tveten",
    "gn:country_code":"SE",
    "gn:dem":185,
    "gn:feature_class":"P",
    "gn:feature_code":"PPL",
    "gn:name":"Tveten",
    "gn:population":0,
    "gn:timezone":"Europe/Stockholm",
    "iso:country":"SE",
    "wof:name":"Tveten",
    "wof:placetype":"locality"
},
  "geometry": {"coordinates":[12.35,59.05],"type":"Point"}
}