{
  "type": "Feature",
  "properties": {
    "gn:admin1_code":"28.0",
    "gn:admin2_code":"1486.0",
    "gn:asciiname":"Saltbacken",
    "gn:country_code":"SE",
    "gn:dem":54,
    "gn:feature_class":"P",
    "gn:feature_code":"PPL",
    "gn:name":"Saltbacken",
    "gn:population":0,
    "gn:timezone":"Europe/Stockholm",
    "iso:country":"SE",
    "wof:name":"Saltbacken",
    "wof:placetype":"locality"
},
  "geometry": {"coordinates":[11.23333,59.08333],"type":"Point"}
}