{
  "type": "Feature",
  "properties": {
    "gn:admin1_code":"28.0",
    "gn:admin2_code":"1491.0",
    "gn:asciiname":"Gunnarsbo",
    "gn:country_code":"SE",
    "gn:dem":322,
    "gn:feature_class":"P",
    "gn:feature_code":"PPL",
    "gn:name":"Gunnarsbo",
    "gn:population":0,
    "gn:timezone":"Europe/Stockholm",
    "iso:country":"SE",
    "wof:name":"Gunnarsbo",
    "wof:placetype":"locality"
},
  "geometry": {"coordinates":[13.48333,57.73333],"type":"Point"}
}