{
  "type": "Feature",
  "properties": {
    "gn:admin1_code":"8.0",
    "gn:admin2_code":"685.0",
    "gn:asciiname":"Horeda",
    "gn:country_code":"SE",
    "gn:dem":198,
    "gn:feature_class":"P",
    "gn:feature_code":"PPL",
    "gn:name":"H\u00f6reda",
    "gn:population":0,
    "gn:timezone":"Europe/Stockholm",
    "iso:country":"SE",
    "name:nor_x_preferred":[
        "H\u00f6reda"
    ],
    "name:nor_x_variant":[
        "H\u00f8reda"
    ],
    "wof:name":"Horeda",
    "wof:placetype":"locality"
},
  "geometry": {"coordinates":[14.94783,57.22651],"type":"Point"}
}