{
  "type": "Feature",
  "properties": {
    "gn:admin1_code":"12.0",
    "gn:admin2_code":"761.0",
    "gn:asciiname":"Skargol",
    "gn:country_code":"SE",
    "gn:dem":247,
    "gn:feature_class":"P",
    "gn:feature_code":"PPL",
    "gn:name":"Sk\u00e4rg\u00f6l",
    "gn:population":0,
    "gn:timezone":"Europe/Stockholm",
    "iso:country":"SE",
    "wof:name":"Skargol",
    "wof:placetype":"locality"
},
  "geometry": {"coordinates":[15.38333,56.86666999999999],"type":"Point"}
}