{
  "type": "Feature",
  "properties": {
    "iso:country":"SE",
    "qs_pg:aaroncc":"SE",
    "qs_pg:name":"Sk\u00e4rsj\u00f6v\u00e5len Norra",
    "qs_pg:name_adm0":"Sverige",
    "qs_pg:name_adm1":"J\u00e4mtlands L\u00e4n",
    "qs_pg:photos":36,
    "qs_pg:photos_1k":7,
    "qs_pg:photos_9k":1,
    "qs_pg:photos_9r":2,
    "qs_pg:photos_all":36,
    "qs_pg:photos_sr":2,
    "qs_pg:pop_sr":0,
    "qs_pg:qs_pg_placetype":"locality",
    "qs_pg:qs_pg_placetype_gp":"Town",
    "qs_pg:woe_adm0":23424954,
    "woe:adm0_id":23424954,
    "woe:name_adm0":"Sverige",
    "woe:name_adm1":"J\u00e4mtlands L\u00e4n",
    "woe:placetype":"Town",
    "wof:name":"Sk\u00e4rsj\u00f6v\u00e5len Norra",
    "wof:placetype":"locality"
},
  "geometry": {"coordinates":[13.357375,62.292358],"type":"Point"}
}