{
  "type": "Feature",
  "properties": {
    "gn:gn_country":"SE",
    "gn:gn_fcode":"PPL",
    "gn:gn_pop":898,
    "gn:population":1062,
    "iso:country":"SE",
    "name:deu_x_preferred":[
        "Angered"
    ],
    "name:eng_x_preferred":[
        "Angered"
    ],
    "name:fra_x_preferred":[
        "Angered"
    ],
    "name:nan_x_preferred":[
        "Angered"
    ],
    "name:nld_x_preferred":[
        "Angered"
    ],
    "name:nno_x_preferred":[
        "Angered"
    ],
    "name:nob_x_preferred":[
        "Angered"
    ],
    "name:sco_x_preferred":[
        "Angered"
    ],
    "name:swe_x_preferred":[
        "Angered"
    ],
    "qs_pg:aaroncc":"SE",
    "qs_pg:gn_country":"SE",
    "qs_pg:gn_fcode":"PPL",
    "qs_pg:gn_pop":898,
    "qs_pg:name":"Angered",
    "qs_pg:name_adm0":"Sverige",
    "qs_pg:name_adm1":"V\u00e4stra G\u00f6talands L\u00e4n",
    "qs_pg:photos":1229,
    "qs_pg:photos_1k":249,
    "qs_pg:photos_9k":5,
    "qs_pg:photos_9r":7,
    "qs_pg:photos_all":1229,
    "qs_pg:photos_sr":11,
    "qs_pg:pop_sr":2,
    "qs_pg:qs_pg_placetype":"locality",
    "qs_pg:qs_pg_placetype_gp":"Town",
    "qs_pg:woe_adm0":23424954,
    "woe:adm0_id":23424954,
    "woe:name_adm0":"Sverige",
    "woe:name_adm1":"V\u00e4stra G\u00f6talands L\u00e4n",
    "woe:placetype":"Town",
    "wof:name":"Angered",
    "wof:placetype":"locality",
    "wof:population":1062
},
  "geometry": {"coordinates":[12.09852,57.78628],"type":"Point"}
}