{
  "type": "Feature",
  "properties": {
    "gn:admin1_code":"10.0",
    "gn:admin2_code":"2082.0",
    "gn:asciiname":"Ljusterangarna",
    "gn:country_code":"SE",
    "gn:dem":133,
    "gn:feature_class":"P",
    "gn:feature_code":"PPL",
    "gn:name":"Ljuster\u00e4ngarna",
    "gn:population":0,
    "gn:timezone":"Europe/Stockholm",
    "iso:country":"SE",
    "wof:name":"Ljusterangarna",
    "wof:placetype":"locality"
},
  "geometry": {"coordinates":[15.78333,60.38333000000001],"type":"Point"}
}