{
  "type": "Feature",
  "properties": {
    "gn:admin1_code":"25.0",
    "gn:admin2_code":"1960.0",
    "gn:asciiname":"Skillingsudd",
    "gn:country_code":"SE",
    "gn:dem":12,
    "gn:feature_class":"P",
    "gn:feature_code":"PPL",
    "gn:name":"Skillingsudd",
    "gn:population":0,
    "gn:timezone":"Europe/Stockholm",
    "iso:country":"SE",
    "wof:name":"Skillingsudd",
    "wof:placetype":"locality"
},
  "geometry": {"coordinates":[16.13332999999999,59.43333000000001],"type":"Point"}
}