{
  "type": "Feature",
  "properties": {
    "gn:admin1_code":"26.0",
    "gn:admin2_code":"120.0",
    "gn:asciiname":"Kapellet",
    "gn:country_code":"SE",
    "gn:dem":25,
    "gn:feature_class":"P",
    "gn:feature_code":"PPL",
    "gn:name":"Kapellet",
    "gn:population":0,
    "gn:timezone":"Europe/Stockholm",
    "iso:country":"SE",
    "wof:name":"Kapellet",
    "wof:placetype":"locality"
},
  "geometry": {"coordinates":[18.60722,59.29167],"type":"Point"}
}