{
  "type": "Feature",
  "properties": {
    "gn:admin1_code":"26.0",
    "gn:admin2_code":"114.0",
    "gn:asciiname":"Harvavik",
    "gn:country_code":"SE",
    "gn:dem":8,
    "gn:feature_class":"P",
    "gn:feature_code":"PPL",
    "gn:name":"Harvavik",
    "gn:population":0,
    "gn:timezone":"Europe/Stockholm",
    "iso:country":"SE",
    "wof:name":"Harvavik",
    "wof:placetype":"locality"
},
  "geometry": {"coordinates":[17.85,59.51667],"type":"Point"}
}