{
  "type": "Feature",
  "properties": {
    "gn:admin1_code":"21.0",
    "gn:admin2_code":"380.0",
    "gn:asciiname":"Samsta",
    "gn:country_code":"SE",
    "gn:dem":30,
    "gn:feature_class":"P",
    "gn:feature_code":"PPL",
    "gn:name":"S\u00e4msta",
    "gn:population":0,
    "gn:timezone":"Europe/Stockholm",
    "iso:country":"SE",
    "wof:name":"Samsta",
    "wof:placetype":"locality"
},
  "geometry": {"coordinates":[17.83333,59.93333000000001],"type":"Point"}
}