{
  "type": "Feature",
  "properties": {
    "gn:admin1_code":"10.0",
    "gn:admin2_code":"2062.0",
    "gn:asciiname":"Limback",
    "gn:country_code":"SE",
    "gn:dem":191,
    "gn:feature_class":"P",
    "gn:feature_code":"PPL",
    "gn:name":"Limb\u00e4ck",
    "gn:population":0,
    "gn:timezone":"Europe/Stockholm",
    "iso:country":"SE",
    "wof:name":"Limback",
    "wof:placetype":"locality"
},
  "geometry": {"coordinates":[14.45,61.11666999999999],"type":"Point"}
}