{
  "type": "Feature",
  "properties": {
    "gn:admin1_code":"28.0",
    "gn:admin2_code":"1480.0",
    "gn:asciiname":"Torvhog",
    "gn:country_code":"SE",
    "gn:dem":56,
    "gn:feature_class":"P",
    "gn:feature_code":"PPL",
    "gn:name":"Torvh\u00f6g",
    "gn:population":0,
    "gn:timezone":"Europe/Stockholm",
    "iso:country":"SE",
    "name:nor_x_preferred":[
        "Torvh\u00f6g"
    ],
    "name:nor_x_variant":[
        "Torvh\u00f8g"
    ],
    "wof:name":"Torvhog",
    "wof:placetype":"locality"
},
  "geometry": {"coordinates":[12.14234,57.80113000000001],"type":"Point"}
}