{
  "type": "Feature",
  "properties": {
    "gn:admin1_code":"10.0",
    "gn:admin2_code":"2084.0",
    "gn:asciiname":"Risbyn",
    "gn:country_code":"SE",
    "gn:dem":81,
    "gn:feature_class":"P",
    "gn:feature_code":"PPL",
    "gn:name":"Risbyn",
    "gn:population":0,
    "gn:timezone":"Europe/Stockholm",
    "iso:country":"SE",
    "wof:name":"Risbyn",
    "wof:placetype":"locality"
},
  "geometry": {"coordinates":[16.11667000000001,60.16667],"type":"Point"}
}