{
  "type": "Feature",
  "properties": {
    "gn:admin1_code":"14.0",
    "gn:admin2_code":"2581.0",
    "gn:asciiname":"Lakafors",
    "gn:country_code":"SE",
    "gn:dem":10,
    "gn:feature_class":"P",
    "gn:feature_code":"PPL",
    "gn:name":"Lakafors",
    "gn:population":0,
    "gn:timezone":"Europe/Stockholm",
    "iso:country":"SE",
    "wof:name":"Lakafors",
    "wof:placetype":"locality"
},
  "geometry": {"coordinates":[21.45,65.45],"type":"Point"}
}