{
  "type": "Feature",
  "properties": {
    "gn:admin1_code":"21.0",
    "gn:admin2_code":"360.0",
    "gn:asciiname":"Ruvelbo",
    "gn:country_code":"SE",
    "gn:dem":28,
    "gn:feature_class":"P",
    "gn:feature_code":"PPL",
    "gn:name":"Ruvelbo",
    "gn:population":0,
    "gn:timezone":"Europe/Stockholm",
    "iso:country":"SE",
    "wof:name":"Ruvelbo",
    "wof:placetype":"locality"
},
  "geometry": {"coordinates":[17.61667000000001,60.26667],"type":"Point"}
}