{
  "type": "Feature",
  "properties": {
    "gn:admin1_code":"23.0",
    "gn:admin2_code":"2463.0",
    "gn:asciiname":"Logda",
    "gn:country_code":"SE",
    "gn:dem":261,
    "gn:feature_class":"P",
    "gn:feature_code":"PPL",
    "gn:name":"L\u00f6gda",
    "gn:population":0,
    "gn:timezone":"Europe/Stockholm",
    "iso:country":"SE",
    "name:nor_x_preferred":[
        "L\u00f6gda"
    ],
    "name:nor_x_variant":[
        "L\u00f8gda"
    ],
    "wof:name":"Logda",
    "wof:placetype":"locality"
},
  "geometry": {"coordinates":[18.36667000000001,64.15000000000001],"type":"Point"}
}