{
  "type": "Feature",
  "properties": {
    "gn:admin1_code":"28.0",
    "gn:admin2_code":"1466.0",
    "gn:asciiname":"Kallunga",
    "gn:country_code":"SE",
    "gn:dem":168,
    "gn:feature_class":"P",
    "gn:feature_code":"PPL",
    "gn:name":"K\u00e4llunga",
    "gn:population":0,
    "gn:timezone":"Europe/Stockholm",
    "iso:country":"SE",
    "wof:name":"Kallunga",
    "wof:placetype":"locality"
},
  "geometry": {"coordinates":[13.16667,58.05],"type":"Point"}
}