{
  "type": "Feature",
  "properties": {
    "gn:admin1_code":"9.0",
    "gn:admin2_code":"880.0",
    "gn:asciiname":"Sodra Hagby",
    "gn:country_code":"SE",
    "gn:dem":10,
    "gn:feature_class":"P",
    "gn:feature_code":"PPL",
    "gn:name":"S\u00f6dra Hagby",
    "gn:population":0,
    "gn:timezone":"Europe/Stockholm",
    "iso:country":"SE",
    "name:nor_x_preferred":[
        "S\u00f6dra Hagby"
    ],
    "name:nor_x_variant":[
        "S\u00f8dra Hagby"
    ],
    "name:und_x_variant":[
        "S\u00f6dra Hagby"
    ],
    "wof:name":"Sodra Hagby",
    "wof:placetype":"locality"
},
  "geometry": {"coordinates":[16.18333,56.55],"type":"Point"}
}