{
  "type": "Feature",
  "properties": {
    "gn:gn_country":"SE",
    "gn:gn_fcode":"ADM3",
    "gn:gn_pop":178,
    "gn:population":178,
    "iso:country":"SE",
    "name:dan_x_preferred":[
        "Linde"
    ],
    "name:dut_x_preferred":[
        "Linde"
    ],
    "name:eng_x_preferred":[
        "Linde"
    ],
    "name:fre_x_preferred":[
        "Linde"
    ],
    "name:ger_x_preferred":[
        "Linde"
    ],
    "name:nds_x_preferred":[
        "Linde"
    ],
    "name:nno_x_preferred":[
        "Linde"
    ],
    "name:nob_x_preferred":[
        "Linde"
    ],
    "name:swe_x_preferred":[
        "Linde"
    ],
    "qs_pg:aaroncc":"SE",
    "qs_pg:gn_country":"SE",
    "qs_pg:gn_fcode":"ADM3",
    "qs_pg:gn_pop":178,
    "qs_pg:name":"Linde",
    "qs_pg:name_adm0":"Sverige",
    "qs_pg:name_adm1":"Gotlands L\u00e4n",
    "qs_pg:photos_9k":1,
    "qs_pg:photos_9r":1,
    "qs_pg:photos_all":4,
    "qs_pg:photos_sr":0,
    "qs_pg:pop_sr":1,
    "qs_pg:qs_pg_placetype":"locality",
    "qs_pg:qs_pg_placetype_gp":"Town",
    "qs_pg:woe_adm0":23424954,
    "woe:adm0_id":23424954,
    "woe:name_adm0":"Sverige",
    "woe:name_adm1":"Gotlands L\u00e4n",
    "woe:placetype":"Town",
    "wof:name":"Linde",
    "wof:placetype":"locality",
    "wof:population":178
},
  "geometry": {"coordinates":[18.38333,57.28333],"type":"Point"}
}