{
  "type": "Feature",
  "properties": {
    "gn:admin1_code":"24.0",
    "gn:admin2_code":"2260.0",
    "gn:admin3_code":"226004.0",
    "gn:admin4_code":"2502.0",
    "gn:asciiname":"Slattberget",
    "gn:country_code":"SE",
    "gn:dem":261,
    "gn:feature_class":"P",
    "gn:feature_code":"PPL",
    "gn:name":"Sl\u00e4ttberget",
    "gn:population":0,
    "gn:timezone":"Europe/Stockholm",
    "iso:country":"SE",
    "wof:name":"Slattberget",
    "wof:placetype":"locality"
},
  "geometry": {"coordinates":[16.19917,62.41429],"type":"Point"}
}