{
  "type": "Feature",
  "properties": {
    "gn:admin1_code":"24",
    "gn:admin2_code":"2260.0",
    "gn:admin3_code":"226003.0",
    "gn:admin4_code":"2465.0",
    "gn:asciiname":"Vaestansjoe",
    "gn:country_code":"SE",
    "gn:dem":246,
    "gn:feature_class":"P",
    "gn:feature_code":"PPLL",
    "gn:name":"V\u00e4stansj\u00f6",
    "gn:population":0,
    "gn:timezone":"Europe/Stockholm",
    "iso:country":"SE",
    "wof:name":"Vaestansjoe",
    "wof:placetype":"locality"
},
  "geometry": {"coordinates":[15.37296,62.39712],"type":"Point"}
}