{
  "type": "Feature",
  "properties": {
    "gn:admin1_code":"28.0",
    "gn:admin2_code":"1466.0",
    "gn:asciiname":"Jallby",
    "gn:country_code":"SE",
    "gn:dem":142,
    "gn:feature_class":"P",
    "gn:feature_code":"PPL",
    "gn:name":"J\u00e4llby",
    "gn:population":0,
    "gn:timezone":"Europe/Stockholm",
    "iso:country":"SE",
    "wof:name":"Jallby",
    "wof:placetype":"locality"
},
  "geometry": {"coordinates":[12.98333,58.01667],"type":"Point"}
}