{
  "type": "Feature",
  "properties": {
    "gn:admin1_code":"8.0",
    "gn:admin2_code":"685.0",
    "gn:asciiname":"Bodasjogle",
    "gn:cc2":"SE",
    "gn:country_code":"SE",
    "gn:dem":224,
    "gn:feature_class":"P",
    "gn:feature_code":"PPL",
    "gn:name":"Bodasj\u00f6gle",
    "gn:population":0,
    "gn:timezone":"Europe/Stockholm",
    "iso:country":"SE",
    "name:nor_x_preferred":[
        "Bodasj\u00f6gle"
    ],
    "name:nor_x_variant":[
        "Bodasj\u00f8gle"
    ],
    "name:und_x_variant":[
        "Bodask\u00f6gle",
        "Bodasj\u00f6gle"
    ],
    "wof:name":"Bodasjogle",
    "wof:placetype":"locality"
},
  "geometry": {"coordinates":[14.86667,57.58333],"type":"Point"}
}