{
  "type": "Feature",
  "properties": {
    "gn:admin1_code":"28.0",
    "gn:admin2_code":"1498.0",
    "gn:asciiname":"Dvarstorp",
    "gn:cc2":"SE",
    "gn:country_code":"SE",
    "gn:dem":240,
    "gn:feature_class":"P",
    "gn:feature_code":"PPL",
    "gn:name":"Dv\u00e4rstorp",
    "gn:population":0,
    "gn:timezone":"Europe/Stockholm",
    "iso:country":"SE",
    "name:und_x_variant":[
        "Dverstorp",
        "Dv\u00e4rstorp"
    ],
    "wof:name":"Dvarstorp",
    "wof:placetype":"locality"
},
  "geometry": {"coordinates":[13.76667,58.15],"type":"Point"}
}