{
  "type": "Feature",
  "properties": {
    "gn:admin1_code":"2.0",
    "gn:admin2_code":"1080.0",
    "gn:asciiname":"Jakobstorp",
    "gn:country_code":"SE",
    "gn:dem":105,
    "gn:feature_class":"P",
    "gn:feature_code":"PPL",
    "gn:name":"Jakobstorp",
    "gn:population":0,
    "gn:timezone":"Europe/Stockholm",
    "iso:country":"SE",
    "wof:name":"Jakobstorp",
    "wof:placetype":"locality"
},
  "geometry": {"coordinates":[15.41667,56.33333],"type":"Point"}
}