{
  "type": "Feature",
  "properties": {
    "gn:gn_country":"SE",
    "gn:gn_fcode":"PPL",
    "gn:gn_pop":0,
    "iso:country":"SE",
    "name:dan_x_preferred":[
        "Hagafors"
    ],
    "name:deu_x_preferred":[
        "Hagafors"
    ],
    "name:eng_x_preferred":[
        "Hagafors"
    ],
    "name:fra_x_preferred":[
        "Hagafors"
    ],
    "name:nds_x_preferred":[
        "Hagafors"
    ],
    "name:nld_x_preferred":[
        "Hagafors en Harkeryd"
    ],
    "name:nno_x_preferred":[
        "Hagafors"
    ],
    "name:nob_x_preferred":[
        "Hagafors"
    ],
    "name:swe_x_preferred":[
        "Hagafors"
    ],
    "name:unk_x_variant":[
        "Hagefors"
    ],
    "qs_pg:aaroncc":"SE",
    "qs_pg:gn_country":"SE",
    "qs_pg:gn_fcode":"PPL",
    "qs_pg:gn_pop":0,
    "qs_pg:name":"Hagafors",
    "qs_pg:name_adm0":"Sverige",
    "qs_pg:name_adm1":"J\u00f6nk\u00f6pings L\u00e4n",
    "qs_pg:photos":25,
    "qs_pg:photos_1k":5,
    "qs_pg:photos_9k":1,
    "qs_pg:photos_9r":1,
    "qs_pg:photos_all":25,
    "qs_pg:photos_sr":1,
    "qs_pg:pop_sr":0,
    "qs_pg:qs_pg_placetype":"locality",
    "qs_pg:qs_pg_placetype_gp":"Town",
    "qs_pg:woe_adm0":23424954,
    "woe:adm0_id":23424954,
    "woe:name_adm0":"Sverige",
    "woe:name_adm1":"J\u00f6nk\u00f6pings L\u00e4n",
    "woe:placetype":"Town",
    "wof:name":"Hagafors",
    "wof:placetype":"locality"
},
  "geometry": {"coordinates":[14.33333,57.46667],"type":"Point"}
}