{
  "type": "Feature",
  "properties": {
    "gn:admin1_code":"7.0",
    "gn:admin2_code":"2313.0",
    "gn:asciiname":"Tasjoedet",
    "gn:country_code":"SE",
    "gn:dem":260,
    "gn:feature_class":"P",
    "gn:feature_code":"PPL",
    "gn:name":"T\u00e5sj\u00f6edet",
    "gn:population":0,
    "gn:timezone":"Europe/Stockholm",
    "iso:country":"SE",
    "name:nor_x_preferred":[
        "T\u00e5sj\u00f6edet"
    ],
    "name:nor_x_variant":[
        "T\u00e5sj\u00f8edet"
    ],
    "wof:name":"Tasjoedet",
    "wof:placetype":"locality"
},
  "geometry": {"coordinates":[16.03333,64.15000000000001],"type":"Point"}
}