{
  "type": "Feature",
  "properties": {
    "gn:admin1_code":"21.0",
    "gn:admin2_code":"360.0",
    "gn:asciiname":"Grono",
    "gn:country_code":"SE",
    "gn:dem":-9999,
    "gn:feature_class":"P",
    "gn:feature_code":"PPL",
    "gn:name":"Gr\u00f6n\u00f6",
    "gn:population":0,
    "gn:timezone":"Europe/Stockholm",
    "iso:country":"SE",
    "name:ceb_x_preferred":[
        "Grono"
    ],
    "name:nor_x_preferred":[
        "Gr\u00f6n\u00f6"
    ],
    "name:nor_x_variant":[
        "Gr\u00f8n\u00f8"
    ],
    "name:pol_x_preferred":[
        "Grono"
    ],
    "wof:name":"Grono",
    "wof:placetype":"locality"
},
  "geometry": {"coordinates":[17.73333,60.51667],"type":"Point"}
}