{
  "type": "Feature",
  "properties": {
    "gn:admin1_code":"18.0",
    "gn:admin2_code":"486.0",
    "gn:asciiname":"Kilfroslunda",
    "gn:country_code":"SE",
    "gn:dem":19,
    "gn:feature_class":"P",
    "gn:feature_code":"PPL",
    "gn:name":"Kilfr\u00f6slunda",
    "gn:population":0,
    "gn:timezone":"Europe/Stockholm",
    "iso:country":"SE",
    "name:nor_x_preferred":[
        "Kilfr\u00f6slunda"
    ],
    "name:nor_x_variant":[
        "Kilfr\u00f8slunda"
    ],
    "name:und_x_variant":[
        "Kilfr\u00f6slunda"
    ],
    "wof:name":"Kilfroslunda",
    "wof:placetype":"locality"
},
  "geometry": {"coordinates":[17.16667,59.43333000000001],"type":"Point"}
}