{
  "type": "Feature",
  "properties": {
    "gn:country":"SE",
    "gn:fcode":"PPL",
    "gn:population":0,
    "iso:country":"SE",
    "name:ceb_x_preferred":[
        "Skruv"
    ],
    "name:eng_x_preferred":[
        "Skruv"
    ],
    "name:fra_x_preferred":[
        "Skruv"
    ],
    "name:ita_x_preferred":[
        "Skruv"
    ],
    "name:nan_x_preferred":[
        "Skruv"
    ],
    "name:nld_x_preferred":[
        "Skruv"
    ],
    "name:nno_x_preferred":[
        "Skruv"
    ],
    "name:nob_x_preferred":[
        "Skruv"
    ],
    "name:sme_x_preferred":[
        "Skruv"
    ],
    "name:swe_x_preferred":[
        "Skruv"
    ],
    "qs_pg:aaroncc":"SE",
    "qs_pg:gn_country":"SE",
    "qs_pg:gn_fcode":"PPL",
    "qs_pg:gn_pop":0,
    "qs_pg:name":"Skruv",
    "qs_pg:name_adm0":"Sverige",
    "qs_pg:name_adm1":"Kronobergs L\u00e4n",
    "qs_pg:photos":38,
    "qs_pg:photos_1k":8,
    "qs_pg:photos_9k":1,
    "qs_pg:photos_9r":2,
    "qs_pg:photos_all":38,
    "qs_pg:photos_sr":2,
    "qs_pg:pop_sr":0,
    "qs_pg:qs_pg_placetype":"locality",
    "qs_pg:qs_pg_placetype_gp":"Town",
    "qs_pg:woe_adm0":23424954,
    "woe:adm0_id":23424954,
    "woe:name_adm0":"Sverige",
    "woe:name_adm1":"Kronobergs L\u00e4n",
    "woe:placetype":"Town",
    "wof:name":"Skruv",
    "wof:placetype":"locality",
    "wof:population":586
},
  "geometry": {"coordinates":[15.36667,56.68333],"type":"Point"}
}