{
  "type": "Feature",
  "properties": {
    "gn:admin1_code":"9.0",
    "gn:admin2_code":"862.0",
    "gn:asciiname":"Karsamala",
    "gn:country_code":"SE",
    "gn:dem":149,
    "gn:feature_class":"P",
    "gn:feature_code":"PPL",
    "gn:name":"Karsam\u00e5la",
    "gn:population":0,
    "gn:timezone":"Europe/Stockholm",
    "iso:country":"SE",
    "wof:name":"Karsamala",
    "wof:placetype":"locality"
},
  "geometry": {"coordinates":[15.45,56.55],"type":"Point"}
}