{
  "type": "Feature",
  "properties": {
    "gn:admin1_code":"12.0",
    "gn:asciiname":"Afors",
    "gn:country_code":"SE",
    "gn:dem":180,
    "gn:feature_class":"P",
    "gn:feature_code":"PPL",
    "gn:name":"\u00c5fors",
    "gn:population":0,
    "gn:timezone":"Europe/Stockholm",
    "iso:country":"SE",
    "wof:name":"Afors",
    "wof:placetype":"locality"
},
  "geometry": {"coordinates":[15.48333,56.75],"type":"Point"}
}