{
  "type": "Feature",
  "properties": {
    "gn:admin1_code":"23.0",
    "gn:admin2_code":"2422.0",
    "gn:asciiname":"Stridsmark",
    "gn:country_code":"SE",
    "gn:dem":345,
    "gn:feature_class":"P",
    "gn:feature_code":"PPL",
    "gn:name":"Stridsmark",
    "gn:population":0,
    "gn:timezone":"Europe/Stockholm",
    "iso:country":"SE",
    "name:swe_x_preferred":[
        "Stridsmark"
    ],
    "wof:name":"Stridsmark",
    "wof:placetype":"locality"
},
  "geometry": {"coordinates":[17.41717,65.52848],"type":"Point"}
}