{
  "type": "Feature",
  "properties": {
    "gn:admin1_code":"7.0",
    "gn:admin2_code":"2303.0",
    "gn:asciiname":"Bjorkvattnet",
    "gn:country_code":"SE",
    "gn:dem":509,
    "gn:feature_class":"P",
    "gn:feature_code":"PPL",
    "gn:name":"Bj\u00f6rkvattnet",
    "gn:population":0,
    "gn:timezone":"Europe/Stockholm",
    "iso:country":"SE",
    "name:nor_x_preferred":[
        "Bj\u00f6rkvattnet"
    ],
    "name:nor_x_variant":[
        "Bj\u00f8rkvattnet"
    ],
    "name:und_x_variant":[
        "Bj\u00f6rkvattnet"
    ],
    "wof:name":"Bjorkvattnet",
    "wof:placetype":"locality"
},
  "geometry": {"coordinates":[16.08333,63.41667],"type":"Point"}
}