{
  "type": "Feature",
  "properties": {
    "gn:gn_country":"SE",
    "gn:gn_fcode":"PPL",
    "gn:gn_pop":230,
    "gn:population":231,
    "iso:country":"SE",
    "name:eng_x_preferred":[
        "L\u00e4by"
    ],
    "name:nan_x_preferred":[
        "L\u00e4by"
    ],
    "name:nld_x_preferred":[
        "L\u00e4by"
    ],
    "name:nno_x_preferred":[
        "L\u00e4by"
    ],
    "name:nob_x_preferred":[
        "L\u00e4by"
    ],
    "name:pol_x_preferred":[
        "L\u00e4by"
    ],
    "name:swe_x_preferred":[
        "L\u00e4by"
    ],
    "qs_pg:aaroncc":"SE",
    "qs_pg:gn_country":"SE",
    "qs_pg:gn_fcode":"PPL",
    "qs_pg:gn_pop":230,
    "qs_pg:name":"L\u00e4by",
    "qs_pg:name_adm0":"Sverige",
    "qs_pg:name_adm1":"Uppsala L\u00e4n",
    "qs_pg:photos":23,
    "qs_pg:photos_1k":5,
    "qs_pg:photos_9k":1,
    "qs_pg:photos_9r":1,
    "qs_pg:photos_all":23,
    "qs_pg:photos_sr":1,
    "qs_pg:pop_sr":2,
    "qs_pg:qs_pg_placetype":"locality",
    "qs_pg:qs_pg_placetype_gp":"Town",
    "qs_pg:woe_adm0":23424954,
    "woe:adm0_id":23424954,
    "woe:name_adm0":"Sverige",
    "woe:name_adm1":"Uppsala L\u00e4n",
    "woe:placetype":"Town",
    "wof:name":"L\u00e4by",
    "wof:placetype":"locality",
    "wof:population":231
},
  "geometry": {"coordinates":[17.55,60.08333],"type":"Point"}
}