{
  "type": "Feature",
  "properties": {
    "gn:admin1_code":"3.0",
    "gn:admin2_code":"2121.0",
    "gn:admin3_code":"212103.0",
    "gn:admin4_code":"2394.0",
    "gn:asciiname":"Storsveden",
    "gn:country_code":"SE",
    "gn:dem":124,
    "gn:feature_class":"P",
    "gn:feature_code":"PPL",
    "gn:name":"Storsveden",
    "gn:population":0,
    "gn:timezone":"Europe/Stockholm",
    "iso:country":"SE",
    "wof:name":"Storsveden",
    "wof:placetype":"locality"
},
  "geometry": {"coordinates":[16.02174,61.34571],"type":"Point"}
}