{
  "type": "Feature",
  "properties": {
    "gn:admin1_code":"28.0",
    "gn:admin2_code":"1463.0",
    "gn:asciiname":"Skepphult",
    "gn:cc2":"SE",
    "gn:country_code":"SE",
    "gn:dem":140,
    "gn:feature_class":"P",
    "gn:feature_code":"PPL",
    "gn:name":"Skepphult",
    "gn:population":0,
    "gn:timezone":"Europe/Stockholm",
    "iso:country":"SE",
    "name:und_x_variant":[
        "Skephult",
        "Skepphult"
    ],
    "wof:name":"Skepphult",
    "wof:placetype":"locality"
},
  "geometry": {"coordinates":[12.86667,57.53333000000001],"type":"Point"}
}