{
  "type": "Feature",
  "properties": {
    "gn:admin1_code":"14.0",
    "gn:admin2_code":"2514.0",
    "gn:asciiname":"Sockentrask",
    "gn:country_code":"SE",
    "gn:dem":143,
    "gn:feature_class":"P",
    "gn:feature_code":"PPL",
    "gn:name":"Sockentr\u00e4sk",
    "gn:population":0,
    "gn:timezone":"Europe/Stockholm",
    "iso:country":"SE",
    "wof:name":"Sockentrask",
    "wof:placetype":"locality"
},
  "geometry": {"coordinates":[23.11667000000001,66.08333],"type":"Point"}
}