{
  "type": "Feature",
  "properties": {
    "gn:admin1_code":"15.0",
    "gn:admin2_code":"1861.0",
    "gn:asciiname":"Gardsjobacken",
    "gn:country_code":"SE",
    "gn:dem":117,
    "gn:feature_class":"P",
    "gn:feature_code":"PPL",
    "gn:name":"G\u00e5rdsj\u00f6backen",
    "gn:population":0,
    "gn:timezone":"Europe/Stockholm",
    "iso:country":"SE",
    "name:nor_x_preferred":[
        "G\u00e5rdsj\u00f6backen"
    ],
    "name:nor_x_variant":[
        "G\u00e5rdsj\u00f8backen"
    ],
    "name:und_x_variant":[
        "G\u00e5rdsj\u00f6backen"
    ],
    "wof:name":"Gardsjobacken",
    "wof:placetype":"locality"
},
  "geometry": {"coordinates":[15.18333,59.05],"type":"Point"}
}