{
  "type": "Feature",
  "properties": {
    "gn:admin1_code":"23.0",
    "gn:admin2_code":"2409.0",
    "gn:asciiname":"Sodra Stortjarn",
    "gn:cc2":"SE",
    "gn:country_code":"SE",
    "gn:dem":176,
    "gn:feature_class":"P",
    "gn:feature_code":"PPL",
    "gn:name":"S\u00f6dra Stortj\u00e4rn",
    "gn:population":0,
    "gn:timezone":"Europe/Stockholm",
    "iso:country":"SE",
    "name:und_x_variant":[
        "Stortj\u00e4rn",
        "S\u00f6dra Stortj\u00e4rn"
    ],
    "wof:name":"Sodra Stortjarn",
    "wof:placetype":"locality"
},
  "geometry": {"coordinates":[20.56667,64.26666999999999],"type":"Point"}
}