{
  "type": "Feature",
  "properties": {
    "gn:admin1_code":"28.0",
    "gn:admin2_code":"1486.0",
    "gn:asciiname":"Mork",
    "gn:country_code":"SE",
    "gn:dem":47,
    "gn:feature_class":"P",
    "gn:feature_code":"PPL",
    "gn:name":"M\u00f6rk",
    "gn:population":0,
    "gn:timezone":"Europe/Stockholm",
    "iso:country":"SE",
    "name:ceb_x_preferred":[
        "Mork"
    ],
    "name:deu_x_preferred":[
        "Mork"
    ],
    "name:nds_x_preferred":[
        "Mork"
    ],
    "name:nor_x_preferred":[
        "M\u00f6rk"
    ],
    "name:nor_x_variant":[
        "M\u00f8rk"
    ],
    "name:und_x_variant":[
        "M\u00f6rk"
    ],
    "wof:name":"Mork",
    "wof:placetype":"locality"
},
  "geometry": {"coordinates":[11.16667,59.01667],"type":"Point"}
}