{
  "type": "Feature",
  "properties": {
    "gn:admin1_code":"14.0",
    "gn:admin2_code":"2518.0",
    "gn:asciiname":"Potila",
    "gn:country_code":"SE",
    "gn:dem":49,
    "gn:feature_class":"P",
    "gn:feature_code":"PPL",
    "gn:name":"Potila",
    "gn:population":0,
    "gn:timezone":"Europe/Stockholm",
    "iso:country":"SE",
    "name:fit_x_preferred":[
        "Potila"
    ],
    "wof:name":"Potila",
    "wof:placetype":"locality"
},
  "geometry": {"coordinates":[23.86288,66.16385],"type":"Point"}
}