{
  "type": "Feature",
  "properties": {
    "gn:admin1_code":"7.0",
    "gn:admin2_code":"2380.0",
    "gn:asciiname":"Norra Rasten",
    "gn:country_code":"SE",
    "gn:dem":360,
    "gn:feature_class":"P",
    "gn:feature_code":"PPL",
    "gn:name":"Norra Rasten",
    "gn:population":0,
    "gn:timezone":"Europe/Stockholm",
    "iso:country":"SE",
    "wof:name":"Norra Rasten",
    "wof:placetype":"locality"
},
  "geometry": {"coordinates":[14.58333,63.15],"type":"Point"}
}