{
  "type": "Feature",
  "properties": {
    "gn:admin1_code":"28.0",
    "gn:admin2_code":"1486.0",
    "gn:asciiname":"Svindalen",
    "gn:country_code":"SE",
    "gn:dem":28,
    "gn:feature_class":"P",
    "gn:feature_code":"PPL",
    "gn:name":"Svindalen",
    "gn:population":0,
    "gn:timezone":"Europe/Stockholm",
    "iso:country":"SE",
    "wof:name":"Svindalen",
    "wof:placetype":"locality"
},
  "geometry": {"coordinates":[11.39167,59.05833000000001],"type":"Point"}
}