{
  "type": "Feature",
  "properties": {
    "gn:country":"SE",
    "gn:fcode":"PPL",
    "gn:population":451,
    "iso:country":"SE",
    "name:fra_x_preferred":[
        "Skottorp"
    ],
    "name:nld_x_preferred":[
        "Skottorp"
    ],
    "name:nno_x_preferred":[
        "Skottorp"
    ],
    "name:nor_x_preferred":[
        "Skottorp"
    ],
    "name:swe_x_preferred":[
        "Skottorp"
    ],
    "qs_pg:aaroncc":"SE",
    "qs_pg:gn_country":"SE",
    "qs_pg:gn_fcode":"PPL",
    "qs_pg:gn_pop":451,
    "qs_pg:name":"Skottorp",
    "qs_pg:photos_9r":0,
    "qs_pg:photos_sr":0,
    "qs_pg:pop_sr":2,
    "qs_pg:qs_pg_placetype":"locality",
    "wof:name":"Skottorp",
    "wof:placetype":"locality",
    "wof:population":451
},
  "geometry": {"coordinates":[15.38333,59.93333],"type":"Point"}
}