{
  "type": "Feature",
  "properties": {
    "gn:admin1_code":"14.0",
    "gn:admin2_code":"2510.0",
    "gn:asciiname":"Kerkejaure",
    "gn:country_code":"SE",
    "gn:dem":382,
    "gn:feature_class":"P",
    "gn:feature_code":"PPL",
    "gn:name":"Kerkejaure",
    "gn:population":0,
    "gn:timezone":"Europe/Stockholm",
    "iso:country":"SE",
    "wof:name":"Kerkejaure",
    "wof:placetype":"locality"
},
  "geometry": {"coordinates":[19.55,66.41667],"type":"Point"}
}