{
  "type": "Feature",
  "properties": {
    "gn:admin1_code":"28.0",
    "gn:admin2_code":"1486.0",
    "gn:asciiname":"Stora Aserod",
    "gn:country_code":"SE",
    "gn:dem":41,
    "gn:feature_class":"P",
    "gn:feature_code":"PPL",
    "gn:name":"Stora \u00c5ser\u00f6d",
    "gn:population":0,
    "gn:timezone":"Europe/Stockholm",
    "iso:country":"SE",
    "name:nor_x_preferred":[
        "Stora \u00c5ser\u00f6d"
    ],
    "name:nor_x_variant":[
        "Stora \u00c5ser\u00f8d"
    ],
    "name:und_x_variant":[
        "Stora \u00c5ser\u00f6d"
    ],
    "wof:name":"Stora Aserod",
    "wof:placetype":"locality"
},
  "geometry": {"coordinates":[11.38333,58.91667],"type":"Point"}
}