{
  "type": "Feature",
  "properties": {
    "gn:admin1_code":"25.0",
    "gn:admin2_code":"1984.0",
    "gn:asciiname":"Ekeby",
    "gn:country_code":"SE",
    "gn:dem":25,
    "gn:feature_class":"P",
    "gn:feature_code":"PPL",
    "gn:name":"Ekeby",
    "gn:population":0,
    "gn:timezone":"Europe/Stockholm",
    "iso:country":"SE",
    "name:ceb_x_preferred":[
        "Ekeby"
    ],
    "name:deu_x_preferred":[
        "Ekeby"
    ],
    "name:fin_x_preferred":[
        "Ekeby"
    ],
    "name:fra_x_preferred":[
        "Ekeby"
    ],
    "name:nld_x_preferred":[
        "Ekeby"
    ],
    "name:swe_x_preferred":[
        "Ekeby"
    ],
    "wof:name":"Ekeby",
    "wof:placetype":"locality"
},
  "geometry": {"coordinates":[15.75,59.45],"type":"Point"}
}