{
  "type": "Feature",
  "properties": {
    "gn:admin1_code":"16.0",
    "gn:admin2_code":"562.0",
    "gn:asciiname":"Solberga",
    "gn:country_code":"SE",
    "gn:dem":93,
    "gn:feature_class":"P",
    "gn:feature_code":"PPL",
    "gn:name":"Solberga",
    "gn:population":0,
    "gn:timezone":"Europe/Stockholm",
    "iso:country":"SE",
    "name:ceb_x_preferred":[
        "Solberga"
    ],
    "name:deu_x_preferred":[
        "Solberga"
    ],
    "name:fin_x_preferred":[
        "Solberga"
    ],
    "name:ita_x_preferred":[
        "Solberga"
    ],
    "name:nld_x_preferred":[
        "Solberga"
    ],
    "name:swe_x_preferred":[
        "Solberga"
    ],
    "wof:name":"Solberga",
    "wof:placetype":"locality"
},
  "geometry": {"coordinates":[15.48333,58.75],"type":"Point"}
}