{
  "type": "Feature",
  "properties": {
    "gn:admin1_code":"23.0",
    "gn:admin2_code":"2480.0",
    "gn:asciiname":"Stromback",
    "gn:country_code":"SE",
    "gn:dem":119,
    "gn:feature_class":"P",
    "gn:feature_code":"PPL",
    "gn:name":"Str\u00f6mb\u00e4ck",
    "gn:population":0,
    "gn:timezone":"Europe/Stockholm",
    "iso:country":"SE",
    "wof:name":"Stromback",
    "wof:placetype":"locality"
},
  "geometry": {"coordinates":[20.33333,64.09999999999999],"type":"Point"}
}