{
  "type": "Feature",
  "properties": {
    "gn:admin1_code":"28.0",
    "gn:admin2_code":"1492.0",
    "gn:asciiname":"Ostra Sjogar",
    "gn:country_code":"SE",
    "gn:dem":52,
    "gn:feature_class":"P",
    "gn:feature_code":"PPL",
    "gn:name":"\u00d6stra Sj\u00f6gar",
    "gn:population":0,
    "gn:timezone":"Europe/Stockholm",
    "iso:country":"SE",
    "name:nor_x_preferred":[
        "\u00d6stra Sj\u00f6gar"
    ],
    "name:nor_x_variant":[
        "\u00d8stra Sj\u00f8gar"
    ],
    "wof:name":"Ostra Sjogar",
    "wof:placetype":"locality"
},
  "geometry": {"coordinates":[12.63333,58.95],"type":"Point"}
}