{
  "type": "Feature",
  "properties": {
    "gn:admin1_code":"23.0",
    "gn:admin2_code":"2481.0",
    "gn:asciiname":"Tuvtrask",
    "gn:country_code":"SE",
    "gn:dem":306,
    "gn:feature_class":"P",
    "gn:feature_code":"PPL",
    "gn:name":"Tuvtr\u00e4sk",
    "gn:population":0,
    "gn:timezone":"Europe/Stockholm",
    "iso:country":"SE",
    "wof:name":"Tuvtrask",
    "wof:placetype":"locality"
},
  "geometry": {"coordinates":[18.53333,64.55],"type":"Point"}
}