{
  "type": "Feature",
  "properties": {
    "gn:admin1_code":"14.0",
    "gn:admin2_code":"2506.0",
    "gn:asciiname":"Rattik",
    "gn:country_code":"SE",
    "gn:dem":427,
    "gn:feature_class":"P",
    "gn:feature_code":"PPL",
    "gn:name":"Rattik",
    "gn:population":0,
    "gn:timezone":"Europe/Stockholm",
    "iso:country":"SE",
    "name:swe_x_preferred":[
        "Rattik"
    ],
    "wof:name":"Rattik",
    "wof:placetype":"locality"
},
  "geometry": {"coordinates":[17.86378999999999,66.06789999999999],"type":"Point"}
}