{
  "type": "Feature",
  "properties": {
    "gn:gn_country":"SE",
    "gn:gn_fcode":"PPL",
    "gn:gn_pop":0,
    "gn:population":366,
    "iso:country":"SE",
    "name:ceb_x_preferred":[
        "Gl\u00f6mminge"
    ],
    "name:dan_x_preferred":[
        "Gl\u00f6mminge"
    ],
    "name:deu_x_preferred":[
        "Gl\u00f6mminge"
    ],
    "name:eng_x_preferred":[
        "Gl\u00f6mminge"
    ],
    "name:fra_x_preferred":[
        "Gl\u00f6mminge"
    ],
    "name:nds_x_preferred":[
        "Gl\u00f6mminge"
    ],
    "name:nld_x_preferred":[
        "Gl\u00f6mminge"
    ],
    "name:nno_x_preferred":[
        "Gl\u00f6mminge"
    ],
    "name:nob_x_preferred":[
        "Gl\u00f6mminge"
    ],
    "name:nor_x_preferred":[
        "Gl\u00f8mminge"
    ],
    "name:nor_x_variant":[
        "Gl\u00f6mminge"
    ],
    "name:swe_x_preferred":[
        "Gl\u00f6mminge"
    ],
    "qs_pg:aaroncc":"SE",
    "qs_pg:gn_country":"SE",
    "qs_pg:gn_fcode":"PPL",
    "qs_pg:gn_pop":0,
    "qs_pg:name":"Gl\u00f6mminge",
    "qs_pg:name_adm0":"Sverige",
    "qs_pg:name_adm1":"Kalmar L\u00e4n",
    "qs_pg:photos":40,
    "qs_pg:photos_1k":8,
    "qs_pg:photos_9k":1,
    "qs_pg:photos_9r":2,
    "qs_pg:photos_all":40,
    "qs_pg:photos_sr":2,
    "qs_pg:pop_sr":0,
    "qs_pg:qs_pg_placetype":"locality",
    "qs_pg:qs_pg_placetype_gp":"Town",
    "qs_pg:woe_adm0":23424954,
    "woe:adm0_id":23424954,
    "woe:name_adm0":"Sverige",
    "woe:name_adm1":"Kalmar L\u00e4n",
    "woe:placetype":"Town",
    "wof:name":"Gl\u00f6mminge",
    "wof:placetype":"locality",
    "wof:population":366
},
  "geometry": {"coordinates":[16.53333,56.71667],"type":"Point"}
}