{
  "type": "Feature",
  "properties": {
    "gn:admin1_code":"28.0",
    "gn:admin2_code":"1452.0",
    "gn:asciiname":"Varred",
    "gn:cc2":"SE",
    "gn:country_code":"SE",
    "gn:dem":169,
    "gn:feature_class":"P",
    "gn:feature_code":"PPL",
    "gn:name":"Varred",
    "gn:population":0,
    "gn:timezone":"Europe/Stockholm",
    "iso:country":"SE",
    "name:und_x_variant":[
        "Warred",
        "Varred"
    ],
    "wof:name":"Varred",
    "wof:placetype":"locality"
},
  "geometry": {"coordinates":[13.26667,57.58333],"type":"Point"}
}