{
  "type": "Feature",
  "properties": {
    "gn:admin1_code":"7.0",
    "gn:admin2_code":"2321.0",
    "gn:asciiname":"Ytterhallen",
    "gn:country_code":"SE",
    "gn:dem":325,
    "gn:feature_class":"P",
    "gn:feature_code":"PPL",
    "gn:name":"Ytterhallen",
    "gn:population":0,
    "gn:timezone":"Europe/Stockholm",
    "iso:country":"SE",
    "wof:name":"Ytterhallen",
    "wof:placetype":"locality"
},
  "geometry": {"coordinates":[14.08333,63.18333000000001],"type":"Point"}
}