{
  "type": "Feature",
  "properties": {
    "gn:admin1_code":"7.0",
    "gn:admin2_code":"2309.0",
    "gn:asciiname":"Rismon",
    "gn:country_code":"SE",
    "gn:dem":460,
    "gn:feature_class":"P",
    "gn:feature_code":"PPL",
    "gn:name":"Rismon",
    "gn:population":0,
    "gn:timezone":"Europe/Stockholm",
    "iso:country":"SE",
    "wof:name":"Rismon",
    "wof:placetype":"locality"
},
  "geometry": {"coordinates":[14.13333,63.61666999999999],"type":"Point"}
}