{
  "type": "Feature",
  "properties": {
    "gn:admin1_code":"9.0",
    "gn:admin2_code":"881.0",
    "gn:asciiname":"Branthult",
    "gn:country_code":"SE",
    "gn:dem":116,
    "gn:feature_class":"P",
    "gn:feature_code":"PPL",
    "gn:name":"Branthult",
    "gn:population":0,
    "gn:timezone":"Europe/Stockholm",
    "iso:country":"SE",
    "wof:name":"Branthult",
    "wof:placetype":"locality"
},
  "geometry": {"coordinates":[15.93333,57.06667],"type":"Point"}
}