{
  "type": "Feature",
  "properties": {
    "gn:admin1_code":"3.0",
    "gn:admin2_code":"2182.0",
    "gn:asciiname":"Langror",
    "gn:country_code":"SE",
    "gn:dem":1,
    "gn:feature_class":"P",
    "gn:feature_code":"PPL",
    "gn:name":"L\u00e5ngr\u00f6r",
    "gn:population":0,
    "gn:timezone":"Europe/Stockholm",
    "iso:country":"SE",
    "name:nor_x_preferred":[
        "L\u00e5ngr\u00f6r"
    ],
    "name:nor_x_variant":[
        "L\u00e5ngr\u00f8r"
    ],
    "wof:name":"Langror",
    "wof:placetype":"locality"
},
  "geometry": {"coordinates":[17.15,61.26667],"type":"Point"}
}