{
  "type": "Feature",
  "properties": {
    "iso:country":"SE",
    "name:swe_x_preferred":[
        "Troll\u00e5sen"
    ],
    "wof:name":"Trollasen",
    "wof:placetype":"neighbourhood"
},
  "geometry": {"coordinates":[11.93634038998715,57.62829031524158],"type":"Point"}
}