{
  "type": "Feature",
  "properties": {
    "gn:gn_country":"SE",
    "gn:gn_fcode":"PPL",
    "gn:gn_pop":0,
    "iso:country":"SE",
    "qs_pg:aaroncc":"SE",
    "qs_pg:gn_country":"SE",
    "qs_pg:gn_fcode":"PPL",
    "qs_pg:gn_pop":0,
    "qs_pg:name":"Bran\u00e4s",
    "qs_pg:name_adm0":"Sverige",
    "qs_pg:name_adm1":"V\u00e4rmlands L\u00e4n",
    "qs_pg:photos":218,
    "qs_pg:photos_1k":44,
    "qs_pg:photos_9k":1,
    "qs_pg:photos_9r":4,
    "qs_pg:photos_all":218,
    "qs_pg:photos_sr":4,
    "qs_pg:pop_sr":0,
    "qs_pg:qs_pg_placetype":"locality",
    "qs_pg:qs_pg_placetype_gp":"Town",
    "qs_pg:woe_adm0":23424954,
    "woe:adm0_id":23424954,
    "woe:name_adm0":"Sverige",
    "woe:name_adm1":"V\u00e4rmlands L\u00e4n",
    "woe:placetype":"Town",
    "wof:name":"Bran\u00e4s",
    "wof:placetype":"locality"
},
  "geometry": {"coordinates":[12.95,60.64972],"type":"Point"}
}