{
  "type": "Feature",
  "properties": {
    "gn:admin1_code":"22.0",
    "gn:admin2_code":"1780.0",
    "gn:asciiname":"Bofasterud",
    "gn:country_code":"SE",
    "gn:dem":95,
    "gn:feature_class":"P",
    "gn:feature_code":"PPL",
    "gn:name":"Bofasterud",
    "gn:population":0,
    "gn:timezone":"Europe/Stockholm",
    "iso:country":"SE",
    "wof:name":"Bofasterud",
    "wof:placetype":"locality"
},
  "geometry": {"coordinates":[13.35,59.41667],"type":"Point"}
}