{
  "type": "Feature",
  "properties": {
    "gn:admin1_code":"28.0",
    "gn:admin2_code":"1444.0",
    "gn:asciiname":"Bragnum",
    "gn:country_code":"SE",
    "gn:dem":71,
    "gn:feature_class":"P",
    "gn:feature_code":"PPL",
    "gn:name":"Bragnum",
    "gn:population":0,
    "gn:timezone":"Europe/Stockholm",
    "iso:country":"SE",
    "wof:name":"Bragnum",
    "wof:placetype":"locality"
},
  "geometry": {"coordinates":[12.53333,58.33333],"type":"Point"}
}