{
  "type": "Feature",
  "properties": {
    "gn:admin1_code":"28.0",
    "gn:admin2_code":"1452.0",
    "gn:asciiname":"Algrena",
    "gn:country_code":"SE",
    "gn:dem":332,
    "gn:feature_class":"P",
    "gn:feature_code":"PPL",
    "gn:name":"Algrena",
    "gn:population":0,
    "gn:timezone":"Europe/Stockholm",
    "iso:country":"SE",
    "wof:name":"Algrena",
    "wof:placetype":"locality"
},
  "geometry": {"coordinates":[13.65,57.63333000000001],"type":"Point"}
}