{
  "type": "Feature",
  "properties": {
    "gn:admin1_code":"18.0",
    "gn:admin2_code":"486.0",
    "gn:asciiname":"Morbytorp",
    "gn:country_code":"SE",
    "gn:dem":19,
    "gn:feature_class":"P",
    "gn:feature_code":"PPL",
    "gn:name":"M\u00f6rbytorp",
    "gn:population":0,
    "gn:timezone":"Europe/Stockholm",
    "iso:country":"SE",
    "name:nor_x_preferred":[
        "M\u00f6rbytorp"
    ],
    "name:nor_x_variant":[
        "M\u00f8rbytorp"
    ],
    "wof:name":"Morbytorp",
    "wof:placetype":"locality"
},
  "geometry": {"coordinates":[17.13332999999999,59.41667],"type":"Point"}
}