{
  "type": "Feature",
  "properties": {
    "gn:admin1_code":"26.0",
    "gn:admin2_code":"120.0",
    "gn:asciiname":"Ostra Ekedal",
    "gn:country_code":"SE",
    "gn:dem":38,
    "gn:feature_class":"P",
    "gn:feature_code":"PPL",
    "gn:name":"\u00d6stra Ekedal",
    "gn:population":0,
    "gn:timezone":"Europe/Stockholm",
    "iso:country":"SE",
    "name:nor_x_preferred":[
        "\u00d6stra Ekedal"
    ],
    "name:nor_x_variant":[
        "\u00d8stra Ekedal"
    ],
    "wof:name":"Ostra Ekedal",
    "wof:placetype":"locality"
},
  "geometry": {"coordinates":[18.36667000000001,59.33333],"type":"Point"}
}