{
  "type": "Feature",
  "properties": {
    "gn:admin1_code":"24",
    "gn:admin2_code":"2281.0",
    "gn:admin3_code":"228108.0",
    "gn:admin4_code":"2505.0",
    "gn:asciiname":"Lilldaelje",
    "gn:country_code":"SE",
    "gn:dem":74,
    "gn:feature_class":"P",
    "gn:feature_code":"PPLL",
    "gn:name":"Lilld\u00e4lje",
    "gn:population":0,
    "gn:timezone":"Europe/Stockholm",
    "iso:country":"SE",
    "wof:name":"Lilldaelje",
    "wof:placetype":"locality"
},
  "geometry": {"coordinates":[17.08601,62.36754000000001],"type":"Point"}
}