{
  "type": "Feature",
  "properties": {
    "gn:admin1_code":"7.0",
    "gn:admin2_code":"2313.0",
    "gn:asciiname":"Jansjo",
    "gn:country_code":"SE",
    "gn:dem":213,
    "gn:feature_class":"P",
    "gn:feature_code":"PPL",
    "gn:name":"Jansj\u00f6",
    "gn:population":0,
    "gn:timezone":"Europe/Stockholm",
    "iso:country":"SE",
    "name:nor_x_preferred":[
        "Jansj\u00f6"
    ],
    "name:nor_x_variant":[
        "Jansj\u00f8"
    ],
    "name:und_x_variant":[
        "Jansj\u00f6"
    ],
    "wof:name":"Jansjo",
    "wof:placetype":"locality"
},
  "geometry": {"coordinates":[16.36667000000001,63.85],"type":"Point"}
}