{
  "type": "Feature",
  "properties": {
    "gn:admin1_code":"21.0",
    "gn:admin2_code":"382.0",
    "gn:asciiname":"Barko",
    "gn:country_code":"SE",
    "gn:dem":10,
    "gn:feature_class":"P",
    "gn:feature_code":"PPL",
    "gn:name":"Bark\u00f6",
    "gn:population":0,
    "gn:timezone":"Europe/Stockholm",
    "iso:country":"SE",
    "name:nor_x_preferred":[
        "Bark\u00f6"
    ],
    "name:nor_x_variant":[
        "Bark\u00f8"
    ],
    "wof:name":"Barko",
    "wof:placetype":"locality"
},
  "geometry": {"coordinates":[18.26667,60.26667],"type":"Point"}
}