{
  "type": "Feature",
  "properties": {
    "gn:admin1_code":"16.0",
    "gn:admin2_code":"580.0",
    "gn:asciiname":"Ubbetorp",
    "gn:country_code":"SE",
    "gn:dem":43,
    "gn:feature_class":"P",
    "gn:feature_code":"PPL",
    "gn:name":"Ubbetorp",
    "gn:population":0,
    "gn:timezone":"Europe/Stockholm",
    "iso:country":"SE",
    "wof:name":"Ubbetorp",
    "wof:placetype":"locality"
},
  "geometry": {"coordinates":[15.76667,58.46666999999999],"type":"Point"}
}