{
  "type": "Feature",
  "properties": {
    "gn:admin1_code":"22.0",
    "gn:admin2_code":"1781.0",
    "gn:asciiname":"Lilla Lerdala",
    "gn:country_code":"SE",
    "gn:dem":54,
    "gn:feature_class":"P",
    "gn:feature_code":"PPL",
    "gn:name":"Lilla Lerdala",
    "gn:population":0,
    "gn:timezone":"Europe/Stockholm",
    "iso:country":"SE",
    "wof:name":"Lilla Lerdala",
    "wof:placetype":"locality"
},
  "geometry": {"coordinates":[14.03333,59.38333000000001],"type":"Point"}
}