{
  "type": "Feature",
  "properties": {
    "gn:admin1_code":"10.0",
    "gn:admin2_code":"2081.0",
    "gn:asciiname":"Esaiegardar",
    "gn:country_code":"SE",
    "gn:dem":144,
    "gn:feature_class":"P",
    "gn:feature_code":"PPL",
    "gn:name":"Esaieg\u00e5rdar",
    "gn:population":0,
    "gn:timezone":"Europe/Stockholm",
    "iso:country":"SE",
    "wof:name":"Esaiegardar",
    "wof:placetype":"locality"
},
  "geometry": {"coordinates":[15.35,60.41667],"type":"Point"}
}