{
  "type": "Feature",
  "properties": {
    "gn:admin1_code":"9.0",
    "gn:admin2_code":"840.0",
    "gn:admin3_code":"84008.0",
    "gn:admin4_code":"869.0",
    "gn:asciiname":"Sodra Mockleby",
    "gn:country_code":"SE",
    "gn:dem":29,
    "gn:feature_class":"P",
    "gn:feature_code":"PPL",
    "gn:name":"S\u00f6dra M\u00f6ckleby",
    "gn:population":0,
    "gn:timezone":"Europe/Stockholm",
    "iso:country":"SE",
    "name:nor_x_preferred":[
        "S\u00f6dra M\u00f6ckleby"
    ],
    "name:nor_x_variant":[
        "S\u00f8dra M\u00f8ckleby"
    ],
    "name:und_x_variant":[
        "S\u00f6dra M\u00f6ckleby"
    ],
    "wof:name":"Sodra Mockleby",
    "wof:placetype":"locality"
},
  "geometry": {"coordinates":[16.41967,56.35588000000001],"type":"Point"}
}