{
  "type": "Feature",
  "properties": {
    "gn:admin1_code":"21.0",
    "gn:admin2_code":"380.0",
    "gn:asciiname":"Arnevi",
    "gn:cc2":"SE",
    "gn:country_code":"SE",
    "gn:dem":46,
    "gn:feature_class":"P",
    "gn:feature_code":"PPL",
    "gn:name":"\u00c4rnevi",
    "gn:population":0,
    "gn:timezone":"Europe/Stockholm",
    "iso:country":"SE",
    "name:und_x_variant":[
        "Ernevi",
        "\u00c4rnevi"
    ],
    "wof:name":"Arnevi",
    "wof:placetype":"locality"
},
  "geometry": {"coordinates":[17.81667000000001,59.85],"type":"Point"}
}