{
  "type": "Feature",
  "properties": {
    "gn:admin1_code":"21.0",
    "gn:admin2_code":"382.0",
    "gn:asciiname":"Sjodal",
    "gn:country_code":"SE",
    "gn:dem":-9999,
    "gn:feature_class":"P",
    "gn:feature_code":"PPL",
    "gn:name":"Sj\u00f6dal",
    "gn:population":0,
    "gn:timezone":"Europe/Stockholm",
    "iso:country":"SE",
    "name:nor_x_preferred":[
        "Sj\u00f6dal"
    ],
    "name:nor_x_variant":[
        "Sj\u00f8dal"
    ],
    "wof:name":"Sjodal",
    "wof:placetype":"locality"
},
  "geometry": {"coordinates":[18.43333,60.25],"type":"Point"}
}