{
  "type": "Feature",
  "properties": {
    "gn:gn_country":"SE",
    "gn:gn_fcode":"PPL",
    "gn:gn_pop":836,
    "gn:population":921,
    "iso:country":"SE",
    "name:bul_x_preferred":[
        "\u0421\u0432\u0430\u0440\u0442\u0435"
    ],
    "name:ceb_x_preferred":[
        "Svarte"
    ],
    "name:deu_x_preferred":[
        "Svarte"
    ],
    "name:eng_x_preferred":[
        "Svarte"
    ],
    "name:fao_x_preferred":[
        "Svarte"
    ],
    "name:fra_x_preferred":[
        "Svarte"
    ],
    "name:ita_x_preferred":[
        "Svarte"
    ],
    "name:nan_x_preferred":[
        "Svarte"
    ],
    "name:nld_x_preferred":[
        "Svarte"
    ],
    "name:nno_x_preferred":[
        "Svarte"
    ],
    "name:nob_x_preferred":[
        "Svarte"
    ],
    "name:por_x_preferred":[
        "Svarte"
    ],
    "name:swe_x_preferred":[
        "Svarte"
    ],
    "qs_pg:aaroncc":"SE",
    "qs_pg:gn_country":"SE",
    "qs_pg:gn_fcode":"PPL",
    "qs_pg:gn_pop":836,
    "qs_pg:name":"Svarte",
    "qs_pg:photos_9r":0,
    "qs_pg:photos_sr":0,
    "qs_pg:pop_sr":2,
    "qs_pg:qs_pg_placetype":"locality",
    "wof:name":"Svarte",
    "wof:placetype":"locality",
    "wof:population":921
},
  "geometry": {"coordinates":[13.71667,55.41667],"type":"Point"}
}