{
  "type": "Feature",
  "properties": {
    "gn:admin1_code":"7.0",
    "gn:admin2_code":"2326.0",
    "gn:asciiname":"Alven",
    "gn:cc2":"SE",
    "gn:country_code":"SE",
    "gn:dem":513,
    "gn:feature_class":"P",
    "gn:feature_code":"PPL",
    "gn:name":"\u00c4lven",
    "gn:population":0,
    "gn:timezone":"Europe/Stockholm",
    "iso:country":"SE",
    "name:und_x_variant":[
        "V\u00e4ster-\u00c4lven",
        "\u00c4lven"
    ],
    "wof:name":"Alven",
    "wof:placetype":"locality"
},
  "geometry": {"coordinates":[14.26667,62.93333000000001],"type":"Point"}
}