{
  "type": "Feature",
  "properties": {
    "gn:admin1_code":"10.0",
    "gn:admin2_code":"2083.0",
    "gn:asciiname":"Vasterby",
    "gn:cc2":"SE",
    "gn:country_code":"SE",
    "gn:dem":98,
    "gn:feature_class":"P",
    "gn:feature_code":"PPL",
    "gn:name":"V\u00e4sterby",
    "gn:population":0,
    "gn:timezone":"Europe/Stockholm",
    "iso:country":"SE",
    "name:und_x_variant":[
        "Vesterbyn",
        "V\u00e4sterby"
    ],
    "wof:name":"Vasterby",
    "wof:placetype":"locality"
},
  "geometry": {"coordinates":[16.13332999999999,60.45],"type":"Point"}
}