{
  "type": "Feature",
  "properties": {
    "gn:admin1_code":"28.0",
    "gn:admin2_code":"1486.0",
    "gn:asciiname":"Holma",
    "gn:country_code":"SE",
    "gn:dem":10,
    "gn:feature_class":"P",
    "gn:feature_code":"PPL",
    "gn:name":"Holma",
    "gn:population":0,
    "gn:timezone":"Europe/Stockholm",
    "iso:country":"SE",
    "name:ita_x_preferred":[
        "Holma"
    ],
    "name:nld_x_preferred":[
        "Holma"
    ],
    "name:vie_x_preferred":[
        "Holma"
    ],
    "wof:name":"Holma",
    "wof:placetype":"locality"
},
  "geometry": {"coordinates":[11.26667,58.83889],"type":"Point"}
}