{
  "type": "Feature",
  "properties": {
    "gn:admin1_code":"28.0",
    "gn:admin2_code":"1435.0",
    "gn:asciiname":"Sodra Rod",
    "gn:country_code":"SE",
    "gn:dem":13,
    "gn:feature_class":"P",
    "gn:feature_code":"PPL",
    "gn:name":"S\u00f6dra R\u00f6d",
    "gn:population":0,
    "gn:timezone":"Europe/Stockholm",
    "iso:country":"SE",
    "name:nor_x_preferred":[
        "S\u00f6dra R\u00f6d"
    ],
    "name:nor_x_variant":[
        "S\u00f8dra R\u00f8d"
    ],
    "name:und_x_variant":[
        "S\u00f6dra R\u00f6d"
    ],
    "wof:name":"Sodra Rod",
    "wof:placetype":"locality"
},
  "geometry": {"coordinates":[11.26667,58.5375],"type":"Point"}
}