{
  "type": "Feature",
  "properties": {
    "gn:country":"SE",
    "gn:fcode":"PPL",
    "gn:population":717,
    "iso:country":"SE",
    "name:ceb_x_preferred":[
        "Fredriksberg"
    ],
    "name:dan_x_preferred":[
        "Fredriksberg"
    ],
    "name:deu_x_preferred":[
        "Fredriksberg"
    ],
    "name:eng_x_preferred":[
        "Fredriksberg"
    ],
    "name:ita_x_preferred":[
        "Fredriksberg"
    ],
    "name:jpn_x_preferred":[
        "\u30d5\u30ec\u30c9\u30ea\u30af\u30b9\u30d9\u30ea\u30fc"
    ],
    "name:nan_x_preferred":[
        "Fredriksberg"
    ],
    "name:nld_x_preferred":[
        "Fredriksberg"
    ],
    "name:nno_x_preferred":[
        "Fredriksberg"
    ],
    "name:nob_x_preferred":[
        "Fredriksberg"
    ],
    "name:pol_x_preferred":[
        "Fredriksberg"
    ],
    "name:por_x_preferred":[
        "Fredriksberg"
    ],
    "name:spa_x_preferred":[
        "Fredriksberg"
    ],
    "name:swe_x_preferred":[
        "Fredriksberg"
    ],
    "qs_pg:aaroncc":"SE",
    "qs_pg:gn_country":"SE",
    "qs_pg:gn_fcode":"PPL",
    "qs_pg:gn_pop":717,
    "qs_pg:name":"Fredriksberg",
    "qs_pg:name_adm0":"Sverige",
    "qs_pg:name_adm1":"Dalarnas L\u00e4n",
    "qs_pg:photos":342,
    "qs_pg:photos_1k":69,
    "qs_pg:photos_9k":2,
    "qs_pg:photos_9r":5,
    "qs_pg:photos_all":342,
    "qs_pg:photos_sr":5,
    "qs_pg:pop_sr":2,
    "qs_pg:qs_pg_placetype":"locality",
    "qs_pg:qs_pg_placetype_gp":"Town",
    "qs_pg:woe_adm0":23424954,
    "woe:adm0_id":23424954,
    "woe:name_adm0":"Sverige",
    "woe:name_adm1":"Dalarnas L\u00e4n",
    "woe:placetype":"Town",
    "wof:name":"Fredriksberg",
    "wof:placetype":"locality",
    "wof:population":717
},
  "geometry": {"coordinates":[14.38333,60.13333],"type":"Point"}
}