{
  "type": "Feature",
  "properties": {
    "iso:country":"SE",
    "wof:name":"Hallstenshagen",
    "wof:placetype":"neighbourhood"
},
  "geometry": {"coordinates":[11.88660111110995,57.64725803288762],"type":"Point"}
}