{
  "type": "Feature",
  "properties": {
    "gn:gn_country":"SE",
    "gn:gn_fcode":"PPL",
    "gn:gn_pop":0,
    "iso:country":"SE",
    "name:ceb_x_preferred":[
        "Rumskulla"
    ],
    "name:dan_x_preferred":[
        "Rumskulla"
    ],
    "name:deu_x_preferred":[
        "Rumskulla"
    ],
    "name:eng_x_preferred":[
        "Rumskulla"
    ],
    "name:fra_x_preferred":[
        "Rumskulla"
    ],
    "name:nds_x_preferred":[
        "Rumskulla"
    ],
    "name:nld_x_preferred":[
        "Rumskulla"
    ],
    "name:nno_x_preferred":[
        "Rumskulla"
    ],
    "name:nob_x_preferred":[
        "Rumskulla"
    ],
    "name:swe_x_preferred":[
        "Rumskulla"
    ],
    "qs_pg:aaroncc":"SE",
    "qs_pg:gn_country":"SE",
    "qs_pg:gn_fcode":"PPL",
    "qs_pg:gn_pop":0,
    "qs_pg:name":"Rumskulla",
    "qs_pg:name_adm0":"Sverige",
    "qs_pg:name_adm1":"Kalmar L\u00e4n",
    "qs_pg:photos":89,
    "qs_pg:photos_1k":18,
    "qs_pg:photos_9k":1,
    "qs_pg:photos_9r":3,
    "qs_pg:photos_all":89,
    "qs_pg:photos_sr":3,
    "qs_pg:pop_sr":0,
    "qs_pg:qs_pg_placetype":"locality",
    "qs_pg:qs_pg_placetype_gp":"Town",
    "qs_pg:woe_adm0":23424954,
    "woe:adm0_id":23424954,
    "woe:name_adm0":"Sverige",
    "woe:name_adm1":"Kalmar L\u00e4n",
    "woe:placetype":"Town",
    "wof:name":"Rumskulla",
    "wof:placetype":"locality"
},
  "geometry": {"coordinates":[15.58333,57.66667],"type":"Point"}
}