{
  "type": "Feature",
  "properties": {
    "gn:admin1_code":"28.0",
    "gn:admin2_code":"1427.0",
    "gn:asciiname":"Vigarna",
    "gn:country_code":"SE",
    "gn:dem":8,
    "gn:feature_class":"P",
    "gn:feature_code":"PPL",
    "gn:name":"Vigarna",
    "gn:population":0,
    "gn:timezone":"Europe/Stockholm",
    "iso:country":"SE",
    "wof:name":"Vigarna",
    "wof:placetype":"locality"
},
  "geometry": {"coordinates":[11.25,58.39583],"type":"Point"}
}