{
  "type": "Feature",
  "properties": {
    "gn:admin1_code":"9.0",
    "gn:asciiname":"Lotebacke",
    "gn:country_code":"SE",
    "gn:dem":4,
    "gn:feature_class":"P",
    "gn:feature_code":"PPL",
    "gn:name":"L\u00f6tebacke",
    "gn:population":0,
    "gn:timezone":"Europe/Stockholm",
    "iso:country":"SE",
    "name:nor_x_preferred":[
        "L\u00f6tebacke"
    ],
    "name:nor_x_variant":[
        "L\u00f8tebacke"
    ],
    "name:und_x_variant":[
        "L\u00f6tebacke"
    ],
    "wof:name":"Lotebacke",
    "wof:placetype":"locality"
},
  "geometry": {"coordinates":[16.56667,57.11666999999999],"type":"Point"}
}