{
  "type": "Feature",
  "properties": {
    "gn:admin1_code":"14.0",
    "gn:admin2_code":"2584.0",
    "gn:asciiname":"Nearva",
    "gn:country_code":"SE",
    "gn:dem":350,
    "gn:feature_class":"P",
    "gn:feature_code":"PPL",
    "gn:name":"Nearv\u00e1",
    "gn:population":0,
    "gn:timezone":"Europe/Stockholm",
    "iso:country":"SE",
    "name:fit_x_preferred":[
        "Mertaj\u00e4rvi"
    ],
    "name:sme_x_preferred":[
        "Nearv\u00e1"
    ],
    "name:und_x_variant":[
        "N\u00e4rv\u00e4"
    ],
    "wof:name":"Nearva",
    "wof:placetype":"locality"
},
  "geometry": {"coordinates":[22.17059,68.35796999999999],"type":"Point"}
}