{
  "type": "Feature",
  "properties": {
    "gn:admin1_code":"9.0",
    "gn:admin2_code":"883.0",
    "gn:asciiname":"Oren",
    "gn:country_code":"SE",
    "gn:dem":43,
    "gn:feature_class":"P",
    "gn:feature_code":"PPL",
    "gn:name":"\u00d6ren",
    "gn:population":0,
    "gn:timezone":"Europe/Stockholm",
    "iso:country":"SE",
    "name:deu_x_preferred":[
        "Oren"
    ],
    "name:ita_x_preferred":[
        "Oren"
    ],
    "name:nor_x_preferred":[
        "\u00d6ren"
    ],
    "name:nor_x_variant":[
        "\u00d8ren"
    ],
    "name:por_x_preferred":[
        "Oren"
    ],
    "name:und_x_variant":[
        "\u00d6ren"
    ],
    "wof:name":"Oren",
    "wof:placetype":"locality"
},
  "geometry": {"coordinates":[16.6425,57.92583000000001],"type":"Point"}
}