{
  "type": "Feature",
  "properties": {
    "gn:admin1_code":"28.0",
    "gn:admin2_code":"1415.0",
    "gn:asciiname":"Kanstorp",
    "gn:cc2":"SE",
    "gn:country_code":"SE",
    "gn:dem":45,
    "gn:feature_class":"P",
    "gn:feature_code":"PPL",
    "gn:name":"K\u00e4nstorp",
    "gn:population":0,
    "gn:timezone":"Europe/Stockholm",
    "iso:country":"SE",
    "name:und_x_variant":[
        "K\u00e4nnestorp",
        "K\u00e4nstorp"
    ],
    "wof:name":"Kanstorp",
    "wof:placetype":"locality"
},
  "geometry": {"coordinates":[11.85,58.03333000000001],"type":"Point"}
}