{
  "type": "Feature",
  "properties": {
    "iso:country":"SE",
    "wof:name":"Toredammen",
    "wof:placetype":"neighbourhood"
},
  "geometry": {"coordinates":[11.87401260379945,57.67872216801497],"type":"Point"}
}