{
  "type": "Feature",
  "properties": {
    "gn:admin1_code":"28.0",
    "gn:admin2_code":"1461.0",
    "gn:asciiname":"Backa",
    "gn:country_code":"SE",
    "gn:dem":76,
    "gn:feature_class":"P",
    "gn:feature_code":"PPL",
    "gn:name":"Backa",
    "gn:population":0,
    "gn:timezone":"Europe/Stockholm",
    "iso:country":"SE",
    "wof:name":"Backa",
    "wof:placetype":"locality"
},
  "geometry": {"coordinates":[12.36667,58.73333],"type":"Point"}
}