{
  "type": "Feature",
  "properties": {
    "iso:country":"SE",
    "name:ita_x_preferred":[
        "\u00d6pir"
    ],
    "name:spa_x_preferred":[
        "\u00d6pir"
    ],
    "name:swe_x_preferred":[
        "Alvsunda",
        "\u00d6pir"
    ],
    "name:swe_x_variant":[
        "\u00c4lvsunda"
    ],
    "qs:gn_adm0_cc":"SE",
    "qs:gn_local":2666238,
    "qs:gn_nam_loc":"Upplands V\u00e4sby, Upplands-V\u00e4sby, Stockholms L\u00e4n, SE",
    "qs:gn_namadm1":"26",
    "qs:local_max":203,
    "qs:local_sum":991,
    "qs:localhoods":13,
    "qs:name":"Alvsunda",
    "qs:name_adm0":"Sverige",
    "qs:name_adm1":"Stockholms L\u00e4n",
    "qs:name_adm2":"Upplands-V\u00e4sby",
    "qs:name_local":"Upplands-V\u00e4sby",
    "qs:photo_max":37,
    "qs:photo_sum":76,
    "qs:placetype":"Suburb",
    "qs:quad_count":12,
    "qs:woe_adm0":23424954,
    "qs:woe_adm1":2347067,
    "qs:woe_adm2":12587483,
    "qs:woe_lau":0,
    "qs:woe_local":908560,
    "qs:woe_ver":"7.10.0",
    "wof:lang":[
        "swe"
    ],
    "wof:name":"Alvsunda",
    "wof:placetype":"neighbourhood"
},
  "geometry": {"coordinates":[17.890206,59.504905],"type":"Point"}
}