{
  "type": "Feature",
  "properties": {
    "gn:admin1_code":"3.0",
    "gn:admin2_code":"2132.0",
    "gn:asciiname":"Sorby",
    "gn:country_code":"SE",
    "gn:dem":74,
    "gn:feature_class":"P",
    "gn:feature_code":"PPL",
    "gn:name":"S\u00f6rby",
    "gn:population":0,
    "gn:timezone":"Europe/Stockholm",
    "iso:country":"SE",
    "name:nor_x_preferred":[
        "S\u00f6rby"
    ],
    "name:nor_x_variant":[
        "S\u00f8rby"
    ],
    "name:und_x_variant":[
        "S\u00f6rby"
    ],
    "wof:name":"Sorby",
    "wof:placetype":"locality"
},
  "geometry": {"coordinates":[17.03333,61.85],"type":"Point"}
}