{
  "type": "Feature",
  "properties": {
    "gn:admin1_code":"2.0",
    "gn:asciiname":"Roan",
    "gn:country_code":"SE",
    "gn:dem":50,
    "gn:feature_class":"P",
    "gn:feature_code":"PPL",
    "gn:name":"R\u00f6an",
    "gn:population":0,
    "gn:timezone":"Europe/Stockholm",
    "iso:country":"SE",
    "name:ceb_x_preferred":[
        "Roan"
    ],
    "name:fra_x_preferred":[
        "Roan"
    ],
    "name:nor_x_preferred":[
        "R\u00f6an"
    ],
    "name:nor_x_variant":[
        "R\u00f8an"
    ],
    "name:und_x_variant":[
        "R\u00f6an"
    ],
    "wof:name":"Roan",
    "wof:placetype":"locality"
},
  "geometry": {"coordinates":[14.56667,56.21666999999999],"type":"Point"}
}