{
  "type": "Feature",
  "properties": {
    "gn:admin1_code":"3.0",
    "gn:admin2_code":"2121.0",
    "gn:asciiname":"Mallangsbo",
    "gn:cc2":"SE",
    "gn:country_code":"SE",
    "gn:dem":216,
    "gn:feature_class":"P",
    "gn:feature_code":"PPL",
    "gn:name":"M\u00e5ll\u00e5ngsbo",
    "gn:population":0,
    "gn:timezone":"Europe/Stockholm",
    "iso:country":"SE",
    "name:und_x_variant":[
        "M\u00e5llongsbo",
        "M\u00e5ll\u00e5ngsbo"
    ],
    "wof:name":"Mallangsbo",
    "wof:placetype":"locality"
},
  "geometry": {"coordinates":[15.85,61.26667],"type":"Point"}
}