{
  "type": "Feature",
  "properties": {
    "gn:admin1_code":"10.0",
    "gn:admin2_code":"2085.0",
    "gn:asciiname":"Kasen",
    "gn:country_code":"SE",
    "gn:dem":187,
    "gn:feature_class":"P",
    "gn:feature_code":"PPL",
    "gn:name":"K\u00e5sen",
    "gn:population":0,
    "gn:timezone":"Europe/Stockholm",
    "iso:country":"SE",
    "wof:name":"Kasen",
    "wof:placetype":"locality"
},
  "geometry": {"coordinates":[15.15,60.08333],"type":"Point"}
}