{
  "type": "Feature",
  "properties": {
    "gn:admin1_code":"9.0",
    "gn:admin2_code":"861.0",
    "gn:asciiname":"Brotorp",
    "gn:country_code":"SE",
    "gn:dem":18,
    "gn:feature_class":"P",
    "gn:feature_code":"PPL",
    "gn:name":"Brotorp",
    "gn:population":0,
    "gn:timezone":"Europe/Stockholm",
    "iso:country":"SE",
    "wof:name":"Brotorp",
    "wof:placetype":"locality"
},
  "geometry": {"coordinates":[16.36667000000001,56.95],"type":"Point"}
}