{
  "type": "Feature",
  "properties": {
    "gn:admin1_code":"15.0",
    "gn:admin2_code":"1861.0",
    "gn:asciiname":"Lybby",
    "gn:country_code":"SE",
    "gn:dem":71,
    "gn:feature_class":"P",
    "gn:feature_code":"PPL",
    "gn:name":"Lybby",
    "gn:population":0,
    "gn:timezone":"Europe/Stockholm",
    "iso:country":"SE",
    "wof:name":"Lybby",
    "wof:placetype":"locality"
},
  "geometry": {"coordinates":[14.93333,59.05],"type":"Point"}
}