{
  "type": "Feature",
  "properties": {
    "gn:admin1_code":"7.0",
    "gn:admin2_code":"2313.0",
    "gn:asciiname":"Rotnaset",
    "gn:country_code":"SE",
    "gn:dem":249,
    "gn:feature_class":"P",
    "gn:feature_code":"PPL",
    "gn:name":"Rotn\u00e4set",
    "gn:population":0,
    "gn:timezone":"Europe/Stockholm",
    "iso:country":"SE",
    "wof:name":"Rotnaset",
    "wof:placetype":"locality"
},
  "geometry": {"coordinates":[15.56667,64.43333],"type":"Point"}
}