{
  "type": "Feature",
  "properties": {
    "gn:admin1_code":"8.0",
    "gn:admin2_code":"680.0",
    "gn:asciiname":"Kviarp",
    "gn:country_code":"SE",
    "gn:dem":257,
    "gn:feature_class":"P",
    "gn:feature_code":"PPL",
    "gn:name":"Kviarp",
    "gn:population":0,
    "gn:timezone":"Europe/Stockholm",
    "iso:country":"SE",
    "wof:name":"Kviarp",
    "wof:placetype":"locality"
},
  "geometry": {"coordinates":[14.46667,57.75],"type":"Point"}
}