{
  "type": "Feature",
  "properties": {
    "gn:admin1_code":"25.0",
    "gn:admin2_code":"1907.0",
    "gn:asciiname":"Nordano",
    "gn:country_code":"SE",
    "gn:dem":97,
    "gn:feature_class":"P",
    "gn:feature_code":"PPL",
    "gn:name":"Nordan\u00f6",
    "gn:population":0,
    "gn:timezone":"Europe/Stockholm",
    "iso:country":"SE",
    "name:nor_x_preferred":[
        "Nordan\u00f6"
    ],
    "name:nor_x_variant":[
        "Nordan\u00f8"
    ],
    "wof:name":"Nordano",
    "wof:placetype":"locality"
},
  "geometry": {"coordinates":[16.06667,59.88333000000001],"type":"Point"}
}