{
  "type": "Feature",
  "properties": {
    "gn:admin1_code":"28.0",
    "gn:admin2_code":"1440.0",
    "gn:asciiname":"Olanda",
    "gn:country_code":"SE",
    "gn:dem":57,
    "gn:feature_class":"P",
    "gn:feature_code":"PPL",
    "gn:name":"\u00d6landa",
    "gn:population":0,
    "gn:timezone":"Europe/Stockholm",
    "iso:country":"SE",
    "name:nor_x_preferred":[
        "\u00d6landa"
    ],
    "name:nor_x_variant":[
        "\u00d8landa"
    ],
    "name:und_x_variant":[
        "\u00d6landa"
    ],
    "wof:name":"Olanda",
    "wof:placetype":"locality"
},
  "geometry": {"coordinates":[12.18333,57.93333000000001],"type":"Point"}
}