{
  "type": "Feature",
  "properties": {
    "gn:admin1_code":"22.0",
    "gn:admin2_code":"1737.0",
    "gn:asciiname":"Backadammen",
    "gn:country_code":"SE",
    "gn:dem":338,
    "gn:feature_class":"P",
    "gn:feature_code":"PPL",
    "gn:name":"Backadammen",
    "gn:population":0,
    "gn:timezone":"Europe/Stockholm",
    "iso:country":"SE",
    "wof:name":"Backadammen",
    "wof:placetype":"locality"
},
  "geometry": {"coordinates":[13.21667,60.56667],"type":"Point"}
}