{
  "type": "Feature",
  "properties": {
    "gn:admin1_code":"9.0",
    "gn:asciiname":"Lilla Marken",
    "gn:country_code":"SE",
    "gn:dem":156,
    "gn:feature_class":"P",
    "gn:feature_code":"PPL",
    "gn:name":"Lilla Marken",
    "gn:population":0,
    "gn:timezone":"Europe/Stockholm",
    "iso:country":"SE",
    "wof:name":"Lilla Marken",
    "wof:placetype":"locality"
},
  "geometry": {"coordinates":[15.96667,57.85],"type":"Point"}
}