{
  "type": "Feature",
  "properties": {
    "gn:admin1_code":"12.0",
    "gn:admin2_code":"764.0",
    "gn:asciiname":"Sodra Vare",
    "gn:country_code":"SE",
    "gn:dem":169,
    "gn:feature_class":"P",
    "gn:feature_code":"PPL",
    "gn:name":"S\u00f6dra Vare",
    "gn:population":0,
    "gn:timezone":"Europe/Stockholm",
    "iso:country":"SE",
    "name:nor_x_preferred":[
        "S\u00f6dra Vare"
    ],
    "name:nor_x_variant":[
        "S\u00f8dra Vare"
    ],
    "name:und_x_variant":[
        "S\u00f6dra Vare"
    ],
    "wof:name":"Sodra Vare",
    "wof:placetype":"locality"
},
  "geometry": {"coordinates":[14.43333,56.81667],"type":"Point"}
}