{
  "type": "Feature",
  "properties": {
    "gn:admin1_code":"9.0",
    "gn:admin2_code":"882.0",
    "gn:asciiname":"Fagerhult",
    "gn:country_code":"SE",
    "gn:dem":80,
    "gn:feature_class":"P",
    "gn:feature_code":"PPL",
    "gn:name":"Fagerhult",
    "gn:population":0,
    "gn:timezone":"Europe/Stockholm",
    "iso:country":"SE",
    "name:ceb_x_preferred":[
        "Fagerhult"
    ],
    "name:fin_x_preferred":[
        "Fagerhult"
    ],
    "name:fra_x_preferred":[
        "Fagerhult"
    ],
    "name:nld_x_preferred":[
        "Fagerhult"
    ],
    "name:swe_x_preferred":[
        "Fagerhult"
    ],
    "wof:name":"Fagerhult",
    "wof:placetype":"locality"
},
  "geometry": {"coordinates":[16.15,57.43333000000001],"type":"Point"}
}