{
  "type": "Feature",
  "properties": {
    "gn:admin1_code":"21.0",
    "gn:admin2_code":"305.0",
    "gn:asciiname":"Kilarne",
    "gn:cc2":"SE",
    "gn:country_code":"SE",
    "gn:dem":16,
    "gn:feature_class":"P",
    "gn:feature_code":"PPL",
    "gn:name":"Kilarne",
    "gn:population":0,
    "gn:timezone":"Europe/Stockholm",
    "iso:country":"SE",
    "name:und_x_variant":[
        "Kilarna",
        "Kilarne"
    ],
    "wof:name":"Kilarne",
    "wof:placetype":"locality"
},
  "geometry": {"coordinates":[17.53333,59.56667],"type":"Point"}
}