{
  "type": "Feature",
  "properties": {
    "gn:admin1_code":"15.0",
    "gn:admin2_code":"1885.0",
    "gn:asciiname":"Bajby",
    "gn:country_code":"SE",
    "gn:dem":38,
    "gn:feature_class":"P",
    "gn:feature_code":"PPL",
    "gn:name":"B\u00e4jby",
    "gn:population":0,
    "gn:timezone":"Europe/Stockholm",
    "iso:country":"SE",
    "wof:name":"Bajby",
    "wof:placetype":"locality"
},
  "geometry": {"coordinates":[15.63333,59.43333000000001],"type":"Point"}
}