{
  "type": "Feature",
  "properties": {
    "gn:admin1_code":"6.0",
    "gn:admin2_code":"1384.0",
    "gn:asciiname":"Buera",
    "gn:country_code":"SE",
    "gn:dem":24,
    "gn:feature_class":"P",
    "gn:feature_code":"PPL",
    "gn:name":"Buera",
    "gn:population":0,
    "gn:timezone":"Europe/Stockholm",
    "iso:country":"SE",
    "wof:name":"Buera",
    "wof:placetype":"locality"
},
  "geometry": {"coordinates":[11.93333,57.45],"type":"Point"}
}