{
  "type": "Feature",
  "properties": {
    "gn:country":"SE",
    "gn:fcode":"PPL",
    "gn:population":218,
    "iso:country":"SE",
    "name:ceb_x_preferred":[
        "Marieby"
    ],
    "name:dan_x_preferred":[
        "Marieby"
    ],
    "name:deu_x_preferred":[
        "Marieby"
    ],
    "name:eng_x_preferred":[
        "Marieby"
    ],
    "name:fas_x_preferred":[
        "\u0645\u0627\u0631\u06cc\u0628\u06cc"
    ],
    "name:fra_x_preferred":[
        "Marieby"
    ],
    "name:gle_x_preferred":[
        "Marieby"
    ],
    "name:ita_x_preferred":[
        "Marieby"
    ],
    "name:lld_x_preferred":[
        "Marieby"
    ],
    "name:nan_x_preferred":[
        "Marieby"
    ],
    "name:nld_x_preferred":[
        "Marieby"
    ],
    "name:nno_x_preferred":[
        "Marieby"
    ],
    "name:nob_x_preferred":[
        "Marieby"
    ],
    "name:pol_x_preferred":[
        "Marieby"
    ],
    "name:swe_x_preferred":[
        "Marieby"
    ],
    "qs_pg:aaroncc":"SE",
    "qs_pg:gn_country":"SE",
    "qs_pg:gn_fcode":"PPL",
    "qs_pg:gn_pop":218,
    "qs_pg:name":"Marieby",
    "qs_pg:photos_9r":0,
    "qs_pg:photos_sr":0,
    "qs_pg:pop_sr":2,
    "qs_pg:qs_pg_placetype":"locality",
    "wof:name":"Marieby",
    "wof:placetype":"locality",
    "wof:population":458
},
  "geometry": {"coordinates":[14.73333,63.11667],"type":"Point"}
}