{
  "type": "Feature",
  "properties": {
    "gn:gn_country":"SE",
    "gn:gn_fcode":"PPL",
    "gn:gn_pop":218,
    "gn:population":458,
    "iso:country":"SE",
    "name:eng_x_preferred":[
        "Marieby"
    ],
    "name:fra_x_preferred":[
        "Marieby"
    ],
    "name:nan_x_preferred":[
        "Marieby"
    ],
    "name:nld_x_preferred":[
        "Marieby"
    ],
    "name:nno_x_preferred":[
        "Marieby"
    ],
    "name:nob_x_preferred":[
        "Marieby"
    ],
    "name:swe_x_preferred":[
        "Marieby"
    ],
    "qs_pg:aaroncc":"SE",
    "qs_pg:gn_country":"SE",
    "qs_pg:gn_fcode":"PPL",
    "qs_pg:gn_pop":218,
    "qs_pg:name":"Marieby",
    "qs_pg:photos_9r":0,
    "qs_pg:photos_sr":0,
    "qs_pg:pop_sr":2,
    "qs_pg:qs_pg_placetype":"locality",
    "wof:name":"Marieby",
    "wof:placetype":"locality",
    "wof:population":458
},
  "geometry": {"coordinates":[14.73333,63.11667],"type":"Point"}
}