{
  "type": "Feature",
  "properties": {
    "gn:admin1_code":"8.0",
    "gn:admin2_code":"662.0",
    "gn:asciiname":"Stalebo",
    "gn:country_code":"SE",
    "gn:dem":161,
    "gn:feature_class":"P",
    "gn:feature_code":"PPL",
    "gn:name":"St\u00e5lebo",
    "gn:population":0,
    "gn:timezone":"Europe/Stockholm",
    "iso:country":"SE",
    "wof:name":"Stalebo",
    "wof:placetype":"locality"
},
  "geometry": {"coordinates":[13.46667,57.16667],"type":"Point"}
}