{
  "type": "Feature",
  "properties": {
    "gn:admin1_code":"23.0",
    "gn:admin2_code":"2417.0",
    "gn:asciiname":"Granstrom",
    "gn:country_code":"SE",
    "gn:dem":269,
    "gn:feature_class":"P",
    "gn:feature_code":"PPL",
    "gn:name":"Granstr\u00f6m",
    "gn:population":0,
    "gn:timezone":"Europe/Stockholm",
    "iso:country":"SE",
    "name:nor_x_preferred":[
        "Granstr\u00f6m"
    ],
    "name:nor_x_variant":[
        "Granstr\u00f8m"
    ],
    "name:und_x_variant":[
        "Granstr\u00f6m"
    ],
    "wof:name":"Granstrom",
    "wof:placetype":"locality"
},
  "geometry": {"coordinates":[19.96667,64.73333000000001],"type":"Point"}
}