{
  "type": "Feature",
  "properties": {
    "gn:admin1_code":"23.0",
    "gn:admin2_code":"2481.0",
    "gn:asciiname":"Svanamyran",
    "gn:country_code":"SE",
    "gn:dem":395,
    "gn:feature_class":"P",
    "gn:feature_code":"PPL",
    "gn:name":"Svanamyran",
    "gn:population":0,
    "gn:timezone":"Europe/Stockholm",
    "iso:country":"SE",
    "wof:name":"Svanamyran",
    "wof:placetype":"locality"
},
  "geometry": {"coordinates":[18.13333,64.56667],"type":"Point"}
}