{
  "type": "Feature",
  "properties": {
    "gn:admin1_code":"7.0",
    "gn:admin2_code":"2309.0",
    "gn:asciiname":"Hogasen",
    "gn:country_code":"SE",
    "gn:dem":397,
    "gn:feature_class":"P",
    "gn:feature_code":"PPL",
    "gn:name":"H\u00f6g\u00e5sen",
    "gn:population":0,
    "gn:timezone":"Europe/Stockholm",
    "iso:country":"SE",
    "name:nor_x_preferred":[
        "H\u00f6g\u00e5sen"
    ],
    "name:nor_x_variant":[
        "H\u00f8g\u00e5sen"
    ],
    "name:und_x_variant":[
        "H\u00f6g\u00e5sen"
    ],
    "wof:name":"Hogasen",
    "wof:placetype":"locality"
},
  "geometry": {"coordinates":[13.85,63.35],"type":"Point"}
}