{
  "type": "Feature",
  "properties": {
    "gn:admin1_code":"22.0",
    "gn:admin2_code":"1782.0",
    "gn:asciiname":"Anggruvorna",
    "gn:cc2":"SE",
    "gn:country_code":"SE",
    "gn:dem":189,
    "gn:feature_class":"P",
    "gn:feature_code":"PPL",
    "gn:name":"\u00c4nggruvorna",
    "gn:population":0,
    "gn:timezone":"Europe/Stockholm",
    "iso:country":"SE",
    "name:und_x_variant":[
        "\u00c4nggruvan",
        "\u00c4nggrufvan",
        "\u00c4nggruvorna"
    ],
    "wof:name":"Anggruvorna",
    "wof:placetype":"locality"
},
  "geometry": {"coordinates":[14.16667,59.75],"type":"Point"}
}