{
  "type": "Feature",
  "properties": {
    "gn:admin1_code":"6.0",
    "gn:admin2_code":"1384.0",
    "gn:admin3_code":"138405.0",
    "gn:admin4_code":"1491.0",
    "gn:asciiname":"Algusered",
    "gn:cc2":"SE",
    "gn:country_code":"SE",
    "gn:dem":19,
    "gn:feature_class":"P",
    "gn:feature_code":"PPL",
    "gn:name":"Algusered",
    "gn:population":0,
    "gn:timezone":"Europe/Stockholm",
    "iso:country":"SE",
    "name:und_x_variant":[
        "Alguserud",
        "Algusered"
    ],
    "wof:name":"Algusered",
    "wof:placetype":"locality"
},
  "geometry": {"coordinates":[11.95471,57.51283000000001],"type":"Point"}
}