{
  "type": "Feature",
  "properties": {
    "gn:admin1_code":"25.0",
    "gn:admin2_code":"1961.0",
    "gn:asciiname":"Svenbyang",
    "gn:country_code":"SE",
    "gn:dem":72,
    "gn:feature_class":"P",
    "gn:feature_code":"PPL",
    "gn:name":"Svenby\u00e4ng",
    "gn:population":0,
    "gn:timezone":"Europe/Stockholm",
    "iso:country":"SE",
    "wof:name":"Svenbyang",
    "wof:placetype":"locality"
},
  "geometry": {"coordinates":[16.13332999999999,59.65],"type":"Point"}
}