{
  "type": "Feature",
  "properties": {
    "gn:admin1_code":"23.0",
    "gn:admin2_code":"2418.0",
    "gn:asciiname":"Adak",
    "gn:cc2":"SE",
    "gn:country_code":"SE",
    "gn:dem":403,
    "gn:feature_class":"P",
    "gn:feature_code":"PPL",
    "gn:name":"Adak",
    "gn:population":0,
    "gn:timezone":"Europe/Stockholm",
    "iso:country":"SE",
    "name:und_x_variant":[
        "Nylund",
        "Asplund",
        "Adak"
    ],
    "wof:name":"Adak",
    "wof:placetype":"locality"
},
  "geometry": {"coordinates":[18.61667000000001,65.34999999999999],"type":"Point"}
}