{
  "type": "Feature",
  "properties": {
    "gn:admin1_code":"27.0",
    "gn:admin2_code":"1266.0",
    "gn:asciiname":"Nunnas",
    "gn:country_code":"SE",
    "gn:dem":53,
    "gn:feature_class":"P",
    "gn:feature_code":"PPL",
    "gn:name":"Nunn\u00e4s",
    "gn:population":0,
    "gn:timezone":"Europe/Stockholm",
    "iso:country":"SE",
    "wof:name":"Nunnas",
    "wof:placetype":"locality"
},
  "geometry": {"coordinates":[13.58333,55.88333000000001],"type":"Point"}
}