{
  "type": "Feature",
  "properties": {
    "gn:admin1_code":"14.0",
    "gn:admin2_code":"2523.0",
    "gn:asciiname":"Palkem",
    "gn:cc2":"SE",
    "gn:country_code":"SE",
    "gn:dem":333,
    "gn:feature_class":"P",
    "gn:feature_code":"PPL",
    "gn:name":"P\u00e5lkem",
    "gn:population":0,
    "gn:timezone":"Europe/Stockholm",
    "iso:country":"SE",
    "name:und_x_variant":[
        "Hvittr\u00e4sk",
        "Vittr\u00e4sk",
        "Polkem",
        "P\u00e5lkem"
    ],
    "wof:name":"Palkem",
    "wof:placetype":"locality"
},
  "geometry": {"coordinates":[21.63333,66.38333],"type":"Point"}
}