{
  "type": "Feature",
  "properties": {
    "iso:country":"SE",
    "wof:name":"Lyckhem",
    "wof:placetype":"neighbourhood"
},
  "geometry": {"coordinates":[11.95888526217049,57.60138158379116],"type":"Point"}
}