{
  "type": "Feature",
  "properties": {
    "gn:admin1_code":"28.0",
    "gn:admin2_code":"1415.0",
    "gn:asciiname":"Kycklingedalen",
    "gn:country_code":"SE",
    "gn:dem":89,
    "gn:feature_class":"P",
    "gn:feature_code":"PPL",
    "gn:name":"Kycklingedalen",
    "gn:population":0,
    "gn:timezone":"Europe/Stockholm",
    "iso:country":"SE",
    "wof:name":"Kycklingedalen",
    "wof:placetype":"locality"
},
  "geometry": {"coordinates":[11.88333,58.11666999999999],"type":"Point"}
}