{
  "type": "Feature",
  "properties": {
    "gn:admin1_code":"14.0",
    "gn:admin2_code":"2523.0",
    "gn:asciiname":"Haukajaurekatan",
    "gn:country_code":"SE",
    "gn:dem":872,
    "gn:feature_class":"P",
    "gn:feature_code":"PPL",
    "gn:name":"Haukajaurek\u00e5tan",
    "gn:population":0,
    "gn:timezone":"Europe/Stockholm",
    "iso:country":"SE",
    "wof:name":"Haukajaurekatan",
    "wof:placetype":"locality"
},
  "geometry": {"coordinates":[17.96667,67.91667],"type":"Point"}
}