{
  "type": "Feature",
  "properties": {
    "gn:admin1_code":"7.0",
    "gn:admin2_code":"2326.0",
    "gn:asciiname":"Vigge",
    "gn:country_code":"SE",
    "gn:dem":350,
    "gn:feature_class":"P",
    "gn:feature_code":"PPL",
    "gn:name":"Vigge",
    "gn:population":0,
    "gn:timezone":"Europe/Stockholm",
    "iso:country":"SE",
    "wof:name":"Vigge",
    "wof:placetype":"locality"
},
  "geometry": {"coordinates":[14.38333,62.85],"type":"Point"}
}