{
  "type": "Feature",
  "properties": {
    "gn:admin1_code":"22.0",
    "gn:admin2_code":"1737.0",
    "gn:asciiname":"Norra Torp",
    "gn:country_code":"SE",
    "gn:dem":150,
    "gn:feature_class":"P",
    "gn:feature_code":"PPL",
    "gn:name":"Norra Torp",
    "gn:population":0,
    "gn:timezone":"Europe/Stockholm",
    "iso:country":"SE",
    "wof:name":"Norra Torp",
    "wof:placetype":"locality"
},
  "geometry": {"coordinates":[13.36667,60.33333],"type":"Point"}
}