{
  "type": "Feature",
  "properties": {
    "gn:admin1_code":"22.0",
    "gn:admin2_code":"1784.0",
    "gn:asciiname":"Holm",
    "gn:country_code":"SE",
    "gn:dem":88,
    "gn:feature_class":"P",
    "gn:feature_code":"PPL",
    "gn:name":"Holm",
    "gn:population":0,
    "gn:timezone":"Europe/Stockholm",
    "iso:country":"SE",
    "name:cat_x_preferred":[
        "Holm"
    ],
    "name:ceb_x_preferred":[
        "Holm"
    ],
    "name:dan_x_preferred":[
        "Holm"
    ],
    "name:deu_x_preferred":[
        "Holm"
    ],
    "name:epo_x_preferred":[
        "Holm"
    ],
    "name:est_x_preferred":[
        "Holm"
    ],
    "name:eus_x_preferred":[
        "Holm"
    ],
    "name:fin_x_preferred":[
        "Holm"
    ],
    "name:fra_x_preferred":[
        "Holm"
    ],
    "name:heb_x_preferred":[
        "\u05d4\u05d5\u05dc\u05dd"
    ],
    "name:hun_x_preferred":[
        "Holm"
    ],
    "name:ita_x_preferred":[
        "Holm"
    ],
    "name:jpn_x_preferred":[
        "\u30db\u30eb\u30e0"
    ],
    "name:lav_x_preferred":[
        "Holms"
    ],
    "name:mkd_x_preferred":[
        "\u0425\u043e\u043b\u043c"
    ],
    "name:nds_x_preferred":[
        "Holm"
    ],
    "name:nld_x_preferred":[
        "Holm"
    ],
    "name:nor_x_preferred":[
        "Holm"
    ],
    "name:pol_x_preferred":[
        "Holm"
    ],
    "name:ron_x_preferred":[
        "Holm"
    ],
    "name:rus_x_preferred":[
        "\u0425\u043e\u043b\u044c\u043c"
    ],
    "name:spa_x_preferred":[
        "Holm"
    ],
    "name:srp_x_preferred":[
        "\u0425\u043e\u043b\u043c"
    ],
    "name:swe_x_preferred":[
        "Holm"
    ],
    "wof:name":"Holm",
    "wof:placetype":"locality"
},
  "geometry": {"coordinates":[12.61667,59.66667],"type":"Point"}
}