{
  "type": "Feature",
  "properties": {
    "gn:admin1_code":"14.0",
    "gn:admin2_code":"2518.0",
    "gn:asciiname":"Armasjarvi",
    "gn:country_code":"SE",
    "gn:dem":84,
    "gn:feature_class":"P",
    "gn:feature_code":"PPL",
    "gn:name":"Armasj\u00e4rvi",
    "gn:population":0,
    "gn:timezone":"Europe/Stockholm",
    "iso:country":"SE",
    "name:fit_x_preferred":[
        "Armasj\u00e4rvi"
    ],
    "wof:name":"Armasjarvi",
    "wof:placetype":"locality"
},
  "geometry": {"coordinates":[23.55024,66.31485000000001],"type":"Point"}
}