{
  "type": "Feature",
  "properties": {
    "gn:admin1_code":"9.0",
    "gn:admin2_code":"882.0",
    "gn:asciiname":"Harnas",
    "gn:country_code":"SE",
    "gn:dem":12,
    "gn:feature_class":"P",
    "gn:feature_code":"PPL",
    "gn:name":"Harn\u00e4s",
    "gn:population":0,
    "gn:timezone":"Europe/Stockholm",
    "iso:country":"SE",
    "wof:name":"Harnas",
    "wof:placetype":"locality"
},
  "geometry": {"coordinates":[16.52472,57.56278],"type":"Point"}
}