{
  "type": "Feature",
  "properties": {
    "gn:admin1_code":"12.0",
    "gn:admin2_code":"764.0",
    "gn:asciiname":"Almesas",
    "gn:country_code":"SE",
    "gn:dem":228,
    "gn:feature_class":"P",
    "gn:feature_code":"PPL",
    "gn:name":"\u00c4lmes\u00e5s",
    "gn:population":0,
    "gn:timezone":"Europe/Stockholm",
    "iso:country":"SE",
    "wof:name":"Almesas",
    "wof:placetype":"locality"
},
  "geometry": {"coordinates":[14.63333,57.03333000000001],"type":"Point"}
}