{
  "type": "Feature",
  "properties": {
    "gn:admin1_code":"15.0",
    "gn:admin2_code":"1880.0",
    "gn:asciiname":"Broby",
    "gn:country_code":"SE",
    "gn:dem":58,
    "gn:feature_class":"P",
    "gn:feature_code":"PPL",
    "gn:name":"Broby",
    "gn:population":0,
    "gn:timezone":"Europe/Stockholm",
    "iso:country":"SE",
    "name:dan_x_preferred":[
        "Broby"
    ],
    "name:fin_x_preferred":[
        "Broby"
    ],
    "name:nld_x_preferred":[
        "Broby"
    ],
    "name:swe_x_preferred":[
        "Broby"
    ],
    "wof:name":"Broby",
    "wof:placetype":"locality"
},
  "geometry": {"coordinates":[15.08333,59.36666999999999],"type":"Point"}
}