{
  "type": "Feature",
  "properties": {
    "gn:admin1_code":"7.0",
    "gn:admin2_code":"2313.0",
    "gn:asciiname":"Storon",
    "gn:country_code":"SE",
    "gn:dem":373,
    "gn:feature_class":"P",
    "gn:feature_code":"PPL",
    "gn:name":"Stor\u00f6n",
    "gn:population":0,
    "gn:timezone":"Europe/Stockholm",
    "iso:country":"SE",
    "name:nor_x_preferred":[
        "Stor\u00f6n"
    ],
    "name:nor_x_variant":[
        "Stor\u00f8n"
    ],
    "name:und_x_variant":[
        "Stor\u00f6n"
    ],
    "wof:name":"Storon",
    "wof:placetype":"locality"
},
  "geometry": {"coordinates":[14.11667,64.61667],"type":"Point"}
}