{
  "type": "Feature",
  "properties": {
    "gn:gn_country":"SE",
    "gn:gn_fcode":"PPL",
    "gn:gn_pop":347,
    "gn:population":347,
    "iso:country":"SE",
    "name:ceb_x_preferred":[
        "Holmsj\u00f6"
    ],
    "name:dan_x_preferred":[
        "Holmsj\u00f6"
    ],
    "name:fra_x_preferred":[
        "Holmsj\u00f6"
    ],
    "name:ita_x_preferred":[
        "Holmsj\u00f6"
    ],
    "name:nld_x_preferred":[
        "Holmsj\u00f6"
    ],
    "name:nor_x_preferred":[
        "Holmsj\u00f8"
    ],
    "name:nor_x_variant":[
        "Holmsj\u00f6"
    ],
    "name:pol_x_preferred":[
        "Holmsj\u00f6"
    ],
    "name:swe_x_preferred":[
        "Holmsj\u00f6"
    ],
    "qs_pg:aaroncc":"SE",
    "qs_pg:gn_country":"SE",
    "qs_pg:gn_fcode":"PPL",
    "qs_pg:gn_pop":347,
    "qs_pg:name":"Holmsj\u00f6",
    "qs_pg:name_adm0":"Sverige",
    "qs_pg:name_adm1":"V\u00e4sterbottens L\u00e4n",
    "qs_pg:photos_9r":0,
    "qs_pg:photos_sr":0,
    "qs_pg:pop_sr":2,
    "qs_pg:qs_pg_placetype":"locality",
    "qs_pg:qs_pg_placetype_gp":"Town",
    "qs_pg:woe_adm0":23424954,
    "woe:adm0_id":23424954,
    "woe:name_adm0":"Sverige",
    "woe:name_adm1":"V\u00e4sterbottens L\u00e4n",
    "woe:placetype":"Town",
    "wof:name":"Holmsj\u00f6",
    "wof:placetype":"locality",
    "wof:population":347
},
  "geometry": {"coordinates":[18.33333,65.26667],"type":"Point"}
}