{
  "type": "Feature",
  "properties": {
    "gn:admin1_code":"24.0",
    "gn:admin2_code":"2280.0",
    "gn:asciiname":"Berge",
    "gn:country_code":"SE",
    "gn:dem":110,
    "gn:feature_class":"P",
    "gn:feature_code":"PPL",
    "gn:name":"Berge",
    "gn:population":0,
    "gn:timezone":"Europe/Stockholm",
    "iso:country":"SE",
    "wof:name":"Berge",
    "wof:placetype":"locality"
},
  "geometry": {"coordinates":[17.85,62.71666999999999],"type":"Point"}
}