{
  "type": "Feature",
  "properties": {
    "gn:country":"SE",
    "gn:fcode":"PPL",
    "gn:population":0,
    "iso:country":"SE",
    "name:dan_x_preferred":[
        "Glommen"
    ],
    "name:deu_x_preferred":[
        "Glommen"
    ],
    "name:eng_x_preferred":[
        "Glommen"
    ],
    "name:fin_x_preferred":[
        "Glommen"
    ],
    "name:fra_x_preferred":[
        "Glommen"
    ],
    "name:gle_x_preferred":[
        "Glommen"
    ],
    "name:ita_x_preferred":[
        "Glommen"
    ],
    "name:lld_x_preferred":[
        "Glommen"
    ],
    "name:nan_x_preferred":[
        "Glommen"
    ],
    "name:nld_x_preferred":[
        "Glommen"
    ],
    "name:nno_x_preferred":[
        "Glommen"
    ],
    "name:nob_x_preferred":[
        "Glommen"
    ],
    "name:pol_x_preferred":[
        "Glommen"
    ],
    "name:swe_x_preferred":[
        "Glommen"
    ],
    "qs_pg:aaroncc":"SE",
    "qs_pg:gn_country":"SE",
    "qs_pg:gn_fcode":"PPL",
    "qs_pg:gn_pop":0,
    "qs_pg:name":"Glommen",
    "qs_pg:name_adm0":"Sverige",
    "qs_pg:name_adm1":"Hallands L\u00e4n",
    "qs_pg:photos":713,
    "qs_pg:photos_1k":144,
    "qs_pg:photos_9k":3,
    "qs_pg:photos_9r":5,
    "qs_pg:photos_all":713,
    "qs_pg:photos_sr":8,
    "qs_pg:pop_sr":0,
    "qs_pg:qs_pg_placetype":"locality",
    "qs_pg:qs_pg_placetype_gp":"Town",
    "qs_pg:woe_adm0":23424954,
    "woe:adm0_id":23424954,
    "woe:name_adm0":"Sverige",
    "woe:name_adm1":"Hallands L\u00e4n",
    "woe:placetype":"Town",
    "wof:name":"Glommen",
    "wof:placetype":"locality",
    "wof:population":1082
},
  "geometry": {"coordinates":[12.35,56.93333],"type":"Point"}
}