{
  "type": "Feature",
  "properties": {
    "gn:admin1_code":"10.0",
    "gn:admin2_code":"2080.0",
    "gn:asciiname":"Blixbo",
    "gn:country_code":"SE",
    "gn:dem":144,
    "gn:feature_class":"P",
    "gn:feature_code":"PPL",
    "gn:name":"Blixbo",
    "gn:population":338,
    "gn:timezone":"Europe/Stockholm",
    "iso:country":"SE",
    "wof:name":"Blixbo",
    "wof:placetype":"locality",
    "wof:population":338
},
  "geometry": {"coordinates":[15.84091,60.63906],"type":"Point"}
}