{
  "type": "Feature",
  "properties": {
    "gn:admin1_code":"5.0",
    "gn:admin2_code":"980.0",
    "gn:asciiname":"Havor",
    "gn:country_code":"SE",
    "gn:dem":17,
    "gn:feature_class":"P",
    "gn:feature_code":"PPL",
    "gn:name":"Havor",
    "gn:population":0,
    "gn:timezone":"Europe/Stockholm",
    "iso:country":"SE",
    "name:und_x_variant":[
        "Hafvor",
        "Havor"
    ],
    "wof:name":"Havor",
    "wof:placetype":"locality"
},
  "geometry": {"coordinates":[18.31572,57.18722],"type":"Point"}
}