{
  "type": "Feature",
  "properties": {
    "gn:admin1_code":"3.0",
    "gn:admin2_code":"2183.0",
    "gn:asciiname":"Lanninge",
    "gn:cc2":"SE",
    "gn:country_code":"SE",
    "gn:dem":39,
    "gn:feature_class":"P",
    "gn:feature_code":"PPL",
    "gn:name":"L\u00e4nninge",
    "gn:population":0,
    "gn:timezone":"Europe/Stockholm",
    "iso:country":"SE",
    "name:und_x_variant":[
        "Lenninge",
        "L\u00e4nninge"
    ],
    "wof:name":"Lanninge",
    "wof:placetype":"locality"
},
  "geometry": {"coordinates":[16.43333,61.31667],"type":"Point"}
}