{
  "type": "Feature",
  "properties": {
    "gn:admin1_code":"16.0",
    "gn:admin2_code":"513.0",
    "gn:admin3_code":"51303.0",
    "gn:admin4_code":"533.0",
    "gn:asciiname":"Berga",
    "gn:country_code":"SE",
    "gn:dem":112,
    "gn:feature_class":"P",
    "gn:feature_code":"PPL",
    "gn:name":"Berga",
    "gn:population":0,
    "gn:timezone":"Europe/Stockholm",
    "iso:country":"SE",
    "wof:name":"Berga",
    "wof:placetype":"locality"
},
  "geometry": {"coordinates":[15.66032,58.06265],"type":"Point"}
}