{
  "type": "Feature",
  "properties": {
    "gn:admin1_code":"24.0",
    "gn:admin2_code":"2282.0",
    "gn:admin3_code":"228201.0",
    "gn:admin4_code":"2475.0",
    "gn:asciiname":"Vaeja",
    "gn:country_code":"SE",
    "gn:dem":1,
    "gn:feature_class":"P",
    "gn:feature_code":"PPL",
    "gn:name":"V\u00e4ja",
    "gn:population":0,
    "gn:timezone":"Europe/Stockholm",
    "iso:country":"SE",
    "name:swe_x_historical":[
        "W\u00e4ija"
    ],
    "name:swe_x_preferred":[
        "V\u00e4ja"
    ],
    "name:swe_x_variant":[
        "W\u00e4ija"
    ],
    "wof:name":"Vaeja",
    "wof:placetype":"locality"
},
  "geometry": {"coordinates":[17.70996,62.9768],"type":"Point"}
}