{
  "type": "Feature",
  "properties": {
    "gn:admin1_code":"14.0",
    "gn:admin2_code":"2513.0",
    "gn:asciiname":"Aspberg",
    "gn:cc2":"SE",
    "gn:country_code":"SE",
    "gn:dem":130,
    "gn:feature_class":"P",
    "gn:feature_code":"PPL",
    "gn:name":"Aspberg",
    "gn:population":0,
    "gn:timezone":"Europe/Stockholm",
    "iso:country":"SE",
    "name:und_x_variant":[
        "Aspberget",
        "Aspberg"
    ],
    "wof:name":"Aspberg",
    "wof:placetype":"locality"
},
  "geometry": {"coordinates":[22.33333,66.78333000000001],"type":"Point"}
}