{
  "type": "Feature",
  "properties": {
    "gn:admin1_code":"10.0",
    "gn:admin2_code":"2061.0",
    "gn:asciiname":"Norsbro",
    "gn:country_code":"SE",
    "gn:dem":114,
    "gn:feature_class":"P",
    "gn:feature_code":"PPL",
    "gn:name":"Norsbro",
    "gn:population":0,
    "gn:timezone":"Europe/Stockholm",
    "iso:country":"SE",
    "wof:name":"Norsbro",
    "wof:placetype":"locality"
},
  "geometry": {"coordinates":[15.25,60.15],"type":"Point"}
}