{
  "type": "Feature",
  "properties": {
    "gn:admin1_code":"12.0",
    "gn:admin2_code":"781.0",
    "gn:asciiname":"Boarp",
    "gn:country_code":"SE",
    "gn:dem":179,
    "gn:feature_class":"P",
    "gn:feature_code":"PPL",
    "gn:name":"Boarp",
    "gn:population":0,
    "gn:timezone":"Europe/Stockholm",
    "iso:country":"SE",
    "wof:name":"Boarp",
    "wof:placetype":"locality"
},
  "geometry": {"coordinates":[13.93333,56.75],"type":"Point"}
}