{
  "type": "Feature",
  "properties": {
    "gn:admin1_code":"21.0",
    "gn:admin2_code":"360.0",
    "gn:asciiname":"Imundbo",
    "gn:country_code":"SE",
    "gn:dem":22,
    "gn:feature_class":"P",
    "gn:feature_code":"PPL",
    "gn:name":"Imundbo",
    "gn:population":0,
    "gn:timezone":"Europe/Stockholm",
    "iso:country":"SE",
    "wof:name":"Imundbo",
    "wof:placetype":"locality"
},
  "geometry": {"coordinates":[17.95,60.36666999999999],"type":"Point"}
}