{
  "type": "Feature",
  "properties": {
    "gn:admin1_code":"15.0",
    "gn:admin2_code":"1884.0",
    "gn:admin3_code":"188404.0",
    "gn:admin4_code":"2254.0",
    "gn:asciiname":"Knutsberg",
    "gn:country_code":"SE",
    "gn:dem":119,
    "gn:feature_class":"P",
    "gn:feature_code":"PPL",
    "gn:name":"Knutsberg",
    "gn:population":0,
    "gn:timezone":"Europe/Stockholm",
    "iso:country":"SE",
    "wof:name":"Knutsberg",
    "wof:placetype":"locality"
},
  "geometry": {"coordinates":[15.01239,59.51238000000001],"type":"Point"}
}