{
  "type": "Feature",
  "properties": {
    "gn:admin1_code":"10.0",
    "gn:admin2_code":"2081.0",
    "gn:asciiname":"Angesgardarna",
    "gn:country_code":"SE",
    "gn:dem":157,
    "gn:feature_class":"P",
    "gn:feature_code":"PPL",
    "gn:name":"\u00c4ngesg\u00e5rdarna",
    "gn:population":0,
    "gn:timezone":"Europe/Stockholm",
    "iso:country":"SE",
    "wof:name":"Angesgardarna",
    "wof:placetype":"locality"
},
  "geometry": {"coordinates":[15.35,60.55],"type":"Point"}
}