{
  "type": "Feature",
  "properties": {
    "gn:admin1_code":"28.0",
    "gn:admin2_code":"1460.0",
    "gn:asciiname":"Svarttjarn",
    "gn:country_code":"SE",
    "gn:dem":116,
    "gn:feature_class":"P",
    "gn:feature_code":"PPL",
    "gn:name":"Svarttj\u00e4rn",
    "gn:population":0,
    "gn:timezone":"Europe/Stockholm",
    "iso:country":"SE",
    "wof:name":"Svarttjarn",
    "wof:placetype":"locality"
},
  "geometry": {"coordinates":[12.25,59.13333000000001],"type":"Point"}
}