{
  "type": "Feature",
  "properties": {
    "gn:admin1_code":"10.0",
    "gn:admin2_code":"2085.0",
    "gn:asciiname":"Gudmundberget",
    "gn:country_code":"SE",
    "gn:dem":310,
    "gn:feature_class":"P",
    "gn:feature_code":"PPL",
    "gn:name":"Gudmundberget",
    "gn:population":0,
    "gn:timezone":"Europe/Stockholm",
    "iso:country":"SE",
    "wof:name":"Gudmundberget",
    "wof:placetype":"locality"
},
  "geometry": {"coordinates":[14.98333,60.08333],"type":"Point"}
}