{
  "type": "Feature",
  "properties": {
    "gn:admin1_code":"28.0",
    "gn:admin2_code":"1444.0",
    "gn:asciiname":"Stromslund",
    "gn:country_code":"SE",
    "gn:dem":68,
    "gn:feature_class":"P",
    "gn:feature_code":"PPL",
    "gn:name":"Str\u00f6mslund",
    "gn:population":0,
    "gn:timezone":"Europe/Stockholm",
    "iso:country":"SE",
    "name:nor_x_preferred":[
        "Str\u00f6mslund"
    ],
    "name:nor_x_variant":[
        "Str\u00f8mslund"
    ],
    "name:und_x_variant":[
        "Str\u00f6mslund"
    ],
    "wof:name":"Stromslund",
    "wof:placetype":"locality"
},
  "geometry": {"coordinates":[12.71667,58.33333],"type":"Point"}
}