{
  "type": "Feature",
  "properties": {
    "gn:admin1_code":"15.0",
    "gn:admin2_code":"1880.0",
    "gn:asciiname":"Norra Klysna",
    "gn:cc2":"SE",
    "gn:country_code":"SE",
    "gn:dem":59,
    "gn:feature_class":"P",
    "gn:feature_code":"PPL",
    "gn:name":"Norra Klysna",
    "gn:population":0,
    "gn:timezone":"Europe/Stockholm",
    "iso:country":"SE",
    "name:und_x_variant":[
        "Klysna",
        "Norra Klysna"
    ],
    "wof:name":"Norra Klysna",
    "wof:placetype":"locality"
},
  "geometry": {"coordinates":[15.23333,59.48333],"type":"Point"}
}