{
  "type": "Feature",
  "properties": {
    "gn:admin1_code":"28.0",
    "gn:admin2_code":"1482.0",
    "gn:asciiname":"Ryr",
    "gn:cc2":"SE",
    "gn:country_code":"SE",
    "gn:dem":11,
    "gn:feature_class":"P",
    "gn:feature_code":"PPL",
    "gn:name":"Ryr",
    "gn:population":0,
    "gn:timezone":"Europe/Stockholm",
    "iso:country":"SE",
    "name:und_x_variant":[
        "Stora Ryr",
        "Ryr"
    ],
    "wof:name":"Ryr",
    "wof:placetype":"locality"
},
  "geometry": {"coordinates":[11.75,57.86666999999999],"type":"Point"}
}