{
  "type": "Feature",
  "properties": {
    "gn:admin1_code":"23.0",
    "gn:admin2_code":"2409.0",
    "gn:asciiname":"Ovre Akulla",
    "gn:cc2":"SE",
    "gn:country_code":"SE",
    "gn:dem":61,
    "gn:feature_class":"P",
    "gn:feature_code":"PPL",
    "gn:name":"\u00d6vre \u00c5kulla",
    "gn:population":0,
    "gn:timezone":"Europe/Stockholm",
    "iso:country":"SE",
    "name:nor_x_preferred":[
        "\u00d6vre \u00c5kulla"
    ],
    "name:nor_x_variant":[
        "\u00d8vre \u00c5kulla"
    ],
    "name:und_x_variant":[
        "\u00d6fvre \u00c5kulla"
    ],
    "wof:name":"Ovre Akulla",
    "wof:placetype":"locality"
},
  "geometry": {"coordinates":[20.71667,64.09999999999999],"type":"Point"}
}