{
  "type": "Feature",
  "properties": {
    "gn:admin1_code":"9.0",
    "gn:admin2_code":"861.0",
    "gn:asciiname":"Algerum",
    "gn:country_code":"SE",
    "gn:dem":11,
    "gn:feature_class":"P",
    "gn:feature_code":"PPL",
    "gn:name":"\u00c4lgerum",
    "gn:population":0,
    "gn:timezone":"Europe/Stockholm",
    "iso:country":"SE",
    "wof:name":"Algerum",
    "wof:placetype":"locality"
},
  "geometry": {"coordinates":[16.41667,57.03333000000001],"type":"Point"}
}