{
  "type": "Feature",
  "properties": {
    "gn:gn_country":"SE",
    "gn:gn_fcode":"PPL",
    "gn:gn_pop":266,
    "gn:population":266,
    "iso:country":"SE",
    "name:dan_x_preferred":[
        "V\u00e4stra Klagstorp"
    ],
    "name:dut_x_preferred":[
        "V\u00e4stra Klagstorp"
    ],
    "name:eng_x_preferred":[
        "V\u00e4stra Klagstorp"
    ],
    "name:fre_x_preferred":[
        "V\u00e4stra Klagstorp"
    ],
    "name:ger_x_preferred":[
        "V\u00e4stra Klagstorp"
    ],
    "name:nan_x_preferred":[
        "V\u00e4stra Klagstorp"
    ],
    "name:nds_x_preferred":[
        "V\u00e4stra Klagstorp"
    ],
    "name:nno_x_preferred":[
        "V\u00e4stra Klagstorp"
    ],
    "name:nob_x_preferred":[
        "V\u00e4stra Klagstorp"
    ],
    "name:swe_x_preferred":[
        "V\u00e4stra Klagstorp"
    ],
    "qs_pg:aaroncc":"SE",
    "qs_pg:gn_country":"SE",
    "qs_pg:gn_fcode":"PPL",
    "qs_pg:gn_pop":266,
    "qs_pg:name":"V\u00e4stra Klagstorp",
    "qs_pg:name_adm0":"Sverige",
    "qs_pg:name_adm1":"Sk\u00e5ne L\u00e4n",
    "qs_pg:photos_9r":0,
    "qs_pg:photos_sr":0,
    "qs_pg:pop_sr":2,
    "qs_pg:qs_pg_placetype":"locality",
    "qs_pg:qs_pg_placetype_gp":"Town",
    "qs_pg:woe_adm0":23424954,
    "woe:adm0_id":23424954,
    "woe:name_adm0":"Sverige",
    "woe:name_adm1":"Sk\u00e5ne L\u00e4n",
    "woe:placetype":"Town",
    "wof:name":"V\u00e4stra Klagstorp",
    "wof:placetype":"locality",
    "wof:population":266
},
  "geometry": {"coordinates":[12.98333,55.53333],"type":"Point"}
}