{
  "type": "Feature",
  "properties": {
    "gn:admin1_code":"14.0",
    "gn:admin2_code":"2505.0",
    "gn:asciiname":"Ostra Granberg",
    "gn:country_code":"SE",
    "gn:dem":356,
    "gn:feature_class":"P",
    "gn:feature_code":"PPL",
    "gn:name":"\u00d6stra Granberg",
    "gn:population":0,
    "gn:timezone":"Europe/Stockholm",
    "iso:country":"SE",
    "name:swe_x_preferred":[
        "\u00d6stra Granberg"
    ],
    "name:und_x_variant":[
        "Granberg"
    ],
    "wof:name":"Ostra Granberg",
    "wof:placetype":"locality"
},
  "geometry": {"coordinates":[20.05817,65.76398],"type":"Point"}
}