{
  "type": "Feature",
  "properties": {
    "gn:admin1_code":"15.0",
    "gn:admin2_code":"1881.0",
    "gn:asciiname":"Gotabro",
    "gn:country_code":"SE",
    "gn:dem":53,
    "gn:feature_class":"P",
    "gn:feature_code":"PPL",
    "gn:name":"G\u00f6tabro",
    "gn:population":0,
    "gn:timezone":"Europe/Stockholm",
    "iso:country":"SE",
    "name:nor_x_preferred":[
        "G\u00f6tabro"
    ],
    "name:nor_x_variant":[
        "G\u00f8tabro"
    ],
    "wof:name":"Gotabro",
    "wof:placetype":"locality"
},
  "geometry": {"coordinates":[14.98333,59.11666999999999],"type":"Point"}
}