{
  "type": "Feature",
  "properties": {
    "gn:admin1_code":"23.0",
    "gn:asciiname":"Ratan",
    "gn:country_code":"SE",
    "gn:dem":-9999,
    "gn:feature_class":"P",
    "gn:feature_code":"PPL",
    "gn:name":"Ratan",
    "gn:population":0,
    "gn:timezone":"Europe/Stockholm",
    "iso:country":"SE",
    "wof:name":"Ratan",
    "wof:placetype":"locality"
},
  "geometry": {"coordinates":[20.88333,63.98333],"type":"Point"}
}