{
  "type": "Feature",
  "properties": {
    "iso:country":"SE",
    "name:eng_x_preferred":[
        "Falk\u00f6ping Airport"
    ],
    "name:jpn_x_preferred":[
        "\u30d5\u30a1\u30eb\u30b7\u30a7\u30fc\u30d4\u30f3\u30b0\u7a7a\u6e2f"
    ],
    "name:msa_x_preferred":[
        "Lapangan Terbang Falkoping"
    ],
    "name:ron_x_preferred":[
        "Aeroportul Falk\u00f6ping"
    ],
    "name:swe_x_preferred":[
        "Falk\u00f6pings flygplats"
    ],
    "oa:elevation_ft":"785",
    "oa:type":"small_airport",
    "woe:hierarchy":{
        "country_id":23424954,
        "county_id":12587382,
        "planet_id":1,
        "state_id":20070562
    },
    "wof:name":"Falk\u00f6ping Flygplats",
    "wof:placetype":"campus"
},
  "geometry": {"coordinates":[13.59166667,58.17527778],"type":"Point"}
}