{
  "type": "Feature",
  "properties": {
    "gn:admin1_code":"18.0",
    "gn:admin2_code":"483.0",
    "gn:asciiname":"Sagmon",
    "gn:country_code":"SE",
    "gn:dem":59,
    "gn:feature_class":"P",
    "gn:feature_code":"PPL",
    "gn:name":"S\u00e5gmon",
    "gn:population":0,
    "gn:timezone":"Europe/Stockholm",
    "iso:country":"SE",
    "wof:name":"Sagmon",
    "wof:placetype":"locality"
},
  "geometry": {"coordinates":[16.26667,59.01667],"type":"Point"}
}