{
  "type": "Feature",
  "properties": {
    "gn:admin1_code":"10.0",
    "gn:admin2_code":"2031.0",
    "gn:asciiname":"Anderasen",
    "gn:country_code":"SE",
    "gn:dem":319,
    "gn:feature_class":"P",
    "gn:feature_code":"PPL",
    "gn:name":"Ander\u00e5sen",
    "gn:population":0,
    "gn:timezone":"Europe/Stockholm",
    "iso:country":"SE",
    "wof:name":"Anderasen",
    "wof:placetype":"locality"
},
  "geometry": {"coordinates":[15.18333,61.03333000000001],"type":"Point"}
}