{
  "type": "Feature",
  "properties": {
    "gn:admin1_code":"28.0",
    "gn:asciiname":"Garvik",
    "gn:country_code":"SE",
    "gn:dem":24,
    "gn:feature_class":"P",
    "gn:feature_code":"PPL",
    "gn:name":"G\u00e5rvik",
    "gn:population":0,
    "gn:timezone":"Europe/Stockholm",
    "iso:country":"SE",
    "wof:name":"Garvik",
    "wof:placetype":"locality"
},
  "geometry": {"coordinates":[11.61667,58.40833000000001],"type":"Point"}
}