{
  "type": "Feature",
  "properties": {
    "gn:admin1_code":"14.0",
    "gn:admin2_code":"2513.0",
    "gn:asciiname":"Kesasjarv",
    "gn:cc2":"SE",
    "gn:country_code":"SE",
    "gn:dem":145,
    "gn:feature_class":"P",
    "gn:feature_code":"PPL",
    "gn:name":"Kesasj\u00e4rv",
    "gn:population":0,
    "gn:timezone":"Europe/Stockholm",
    "iso:country":"SE",
    "name:und_x_variant":[
        "Kesaj\u00e4rv",
        "Kesasj\u00e4rv"
    ],
    "wof:name":"Kesasjarv",
    "wof:placetype":"locality"
},
  "geometry": {"coordinates":[22.36667000000001,66.28333000000001],"type":"Point"}
}