{
  "type": "Feature",
  "properties": {
    "gn:admin1_code":"24.0",
    "gn:admin2_code":"2281.0",
    "gn:admin3_code":"228105.0",
    "gn:admin4_code":"2500.0",
    "gn:asciiname":"Nora",
    "gn:country_code":"SE",
    "gn:dem":157,
    "gn:feature_class":"P",
    "gn:feature_code":"PPL",
    "gn:name":"Nora",
    "gn:population":0,
    "gn:timezone":"Europe/Stockholm",
    "iso:country":"SE",
    "name:ara_x_preferred":[
        "\u0646\u0648\u0631\u0627"
    ],
    "name:ast_x_preferred":[
        "Nora"
    ],
    "name:bul_x_preferred":[
        "\u041d\u043e\u0440\u0430"
    ],
    "name:ceb_x_preferred":[
        "Nora"
    ],
    "name:ces_x_preferred":[
        "Nora"
    ],
    "name:dan_x_preferred":[
        "Nora"
    ],
    "name:deu_x_preferred":[
        "Nora"
    ],
    "name:eus_x_preferred":[
        "Nora"
    ],
    "name:fas_x_preferred":[
        "\u0646\u0648\u0631\u0627"
    ],
    "name:fin_x_preferred":[
        "Nora"
    ],
    "name:fra_x_preferred":[
        "Nora"
    ],
    "name:glg_x_preferred":[
        "Nora"
    ],
    "name:hrv_x_preferred":[
        "Nora"
    ],
    "name:ita_x_preferred":[
        "Nora"
    ],
    "name:lat_x_preferred":[
        "Nora"
    ],
    "name:lav_x_preferred":[
        "Nora"
    ],
    "name:lim_x_preferred":[
        "Nora"
    ],
    "name:msa_x_preferred":[
        "Nora"
    ],
    "name:nld_x_preferred":[
        "Nora"
    ],
    "name:nor_x_preferred":[
        "Nora"
    ],
    "name:pol_x_preferred":[
        "Nora"
    ],
    "name:por_x_preferred":[
        "Nora"
    ],
    "name:ron_x_preferred":[
        "Nora"
    ],
    "name:rus_x_preferred":[
        "\u041d\u043e\u0440\u0430"
    ],
    "name:slk_x_preferred":[
        "Nora"
    ],
    "name:spa_x_preferred":[
        "Nora"
    ],
    "name:srp_x_preferred":[
        "\u041d\u043e\u0440\u0430"
    ],
    "name:swe_x_preferred":[
        "Nora"
    ],
    "name:tur_x_preferred":[
        "Nora"
    ],
    "name:ukr_x_preferred":[
        "\u041d\u043e\u0440\u0430"
    ],
    "name:vol_x_preferred":[
        "Nora"
    ],
    "wof:name":"Nora",
    "wof:placetype":"locality"
},
  "geometry": {"coordinates":[16.93439,62.49498000000001],"type":"Point"}
}