{
  "type": "Feature",
  "properties": {
    "gn:admin1_code":"18.0",
    "gn:admin2_code":"486.0",
    "gn:asciiname":"Barby",
    "gn:country_code":"SE",
    "gn:dem":30,
    "gn:feature_class":"P",
    "gn:feature_code":"PPL",
    "gn:name":"B\u00e4rby",
    "gn:population":0,
    "gn:timezone":"Europe/Stockholm",
    "iso:country":"SE",
    "wof:name":"Barby",
    "wof:placetype":"locality"
},
  "geometry": {"coordinates":[16.83333,59.43333000000001],"type":"Point"}
}