{
  "type": "Feature",
  "properties": {
    "gn:admin1_code":"14.0",
    "gn:admin2_code":"2580.0",
    "gn:asciiname":"Alvikstrask",
    "gn:country_code":"SE",
    "gn:dem":20,
    "gn:feature_class":"P",
    "gn:feature_code":"PPL",
    "gn:name":"Alvikstr\u00e4sk",
    "gn:population":0,
    "gn:timezone":"Europe/Stockholm",
    "iso:country":"SE",
    "wof:name":"Alvikstrask",
    "wof:placetype":"locality"
},
  "geometry": {"coordinates":[21.78333,65.61667],"type":"Point"}
}