{
  "type": "Feature",
  "properties": {
    "gn:admin1_code":"12.0",
    "gn:admin2_code":"763.0",
    "gn:asciiname":"Trehorna",
    "gn:country_code":"SE",
    "gn:dem":153,
    "gn:feature_class":"P",
    "gn:feature_code":"PPL",
    "gn:name":"Treh\u00f6rna",
    "gn:population":0,
    "gn:timezone":"Europe/Stockholm",
    "iso:country":"SE",
    "name:nor_x_preferred":[
        "Treh\u00f6rna"
    ],
    "name:nor_x_variant":[
        "Treh\u00f8rna"
    ],
    "name:und_x_variant":[
        "Treh\u00f6rna"
    ],
    "wof:name":"Trehorna",
    "wof:placetype":"locality"
},
  "geometry": {"coordinates":[14.83333,56.53333000000001],"type":"Point"}
}