{
  "type": "Feature",
  "properties": {
    "iso:country":"SE",
    "name:ast_x_preferred":[
        "Tors\u00f6"
    ],
    "name:bar_x_preferred":[
        "Tors\u00f6"
    ],
    "name:ceb_x_preferred":[
        "Tors\u00f6"
    ],
    "name:dan_x_preferred":[
        "Tors\u00f6"
    ],
    "name:deu_x_preferred":[
        "Tors\u00f6"
    ],
    "name:fra_x_preferred":[
        "Tors\u00f6"
    ],
    "name:ita_x_preferred":[
        "Tors\u00f6"
    ],
    "name:nno_x_preferred":[
        "Tors\u00f6"
    ],
    "name:pol_x_preferred":[
        "Tors\u00f6"
    ],
    "name:por_x_preferred":[
        "Tors\u00f6"
    ],
    "name:spa_x_preferred":[
        "Tors\u00f6"
    ],
    "name:swe_x_preferred":[
        "Tors\u00f6"
    ],
    "name:ukr_x_preferred":[
        "\u0422\u043e\u0440\u0441\u0435"
    ],
    "qs_pg:aaroncc":"SE",
    "qs_pg:name":"Tors\u00f6",
    "qs_pg:name_adm0":"Sverige",
    "qs_pg:name_adm1":"S\u00f6dermanlands L\u00e4n",
    "qs_pg:photos":125,
    "qs_pg:photos_1k":25,
    "qs_pg:photos_9k":1,
    "qs_pg:photos_9r":3,
    "qs_pg:photos_all":125,
    "qs_pg:photos_sr":3,
    "qs_pg:pop_sr":0,
    "qs_pg:qs_pg_placetype":"locality",
    "qs_pg:qs_pg_placetype_gp":"Town",
    "qs_pg:woe_adm0":23424954,
    "woe:adm0_id":23424954,
    "woe:name_adm0":"Sverige",
    "woe:name_adm1":"S\u00f6dermanlands L\u00e4n",
    "woe:placetype":"Town",
    "wof:name":"Tors\u00f6",
    "wof:placetype":"locality"
},
  "geometry": {"coordinates":[17.364792,58.810363],"type":"Point"}
}