{
  "type": "Feature",
  "properties": {
    "gn:admin1_code":"14.0",
    "gn:admin2_code":"2506.0",
    "gn:asciiname":"Norra Bergnas",
    "gn:country_code":"SE",
    "gn:dem":428,
    "gn:feature_class":"P",
    "gn:feature_code":"PPL",
    "gn:name":"Norra Bergn\u00e4s",
    "gn:population":0,
    "gn:timezone":"Europe/Stockholm",
    "iso:country":"SE",
    "name:smj_x_preferred":[
        "Luovvanj\u00e1rgga"
    ],
    "name:und_x_variant":[
        "Bergn\u00e4sviken",
        "Norra Bergn\u00e4s"
    ],
    "wof:name":"Norra Bergnas",
    "wof:placetype":"locality"
},
  "geometry": {"coordinates":[18.22152,66.39374000000001],"type":"Point"}
}