{
  "type": "Feature",
  "properties": {
    "gn:admin1_code":"23.0",
    "gn:admin2_code":"2421.0",
    "gn:asciiname":"Gardsjonas",
    "gn:country_code":"SE",
    "gn:dem":521,
    "gn:feature_class":"P",
    "gn:feature_code":"PPL",
    "gn:name":"Gardsj\u00f6n\u00e4s",
    "gn:population":0,
    "gn:timezone":"Europe/Stockholm",
    "iso:country":"SE",
    "name:nno_x_preferred":[
        "Gardsj\u00f6n\u00e4s"
    ],
    "name:nor_x_preferred":[
        "Gardsj\u00f6n\u00e4s"
    ],
    "name:swe_x_preferred":[
        "Gardsj\u00f6n\u00e4s"
    ],
    "wof:name":"Gardsjonas",
    "wof:placetype":"locality"
},
  "geometry": {"coordinates":[16.43333,65.45],"type":"Point"}
}