{
  "type": "Feature",
  "properties": {
    "gn:admin1_code":"10.0",
    "gn:admin2_code":"2080.0",
    "gn:asciiname":"Kvarntakt",
    "gn:country_code":"SE",
    "gn:dem":132,
    "gn:feature_class":"P",
    "gn:feature_code":"PPL",
    "gn:name":"Kvarnt\u00e4kt",
    "gn:population":0,
    "gn:timezone":"Europe/Stockholm",
    "iso:country":"SE",
    "wof:name":"Kvarntakt",
    "wof:placetype":"locality"
},
  "geometry": {"coordinates":[15.76667,60.71666999999999],"type":"Point"}
}