{
  "type": "Feature",
  "properties": {
    "gn:admin1_code":"21.0",
    "gn:asciiname":"Axsjo",
    "gn:country_code":"SE",
    "gn:dem":86,
    "gn:feature_class":"P",
    "gn:feature_code":"PPL",
    "gn:name":"Axsj\u00f6",
    "gn:population":0,
    "gn:timezone":"Europe/Stockholm",
    "iso:country":"SE",
    "name:nor_x_preferred":[
        "Axsj\u00f6"
    ],
    "name:nor_x_variant":[
        "Axsj\u00f8"
    ],
    "wof:name":"Axsjo",
    "wof:placetype":"locality"
},
  "geometry": {"coordinates":[16.95,59.91667],"type":"Point"}
}