{
  "type": "Feature",
  "properties": {
    "gn:admin1_code":"27.0",
    "gn:admin2_code":"1284.0",
    "gn:asciiname":"Skattekarr",
    "gn:country_code":"SE",
    "gn:dem":19,
    "gn:feature_class":"P",
    "gn:feature_code":"PPL",
    "gn:name":"Sk\u00e4ttek\u00e4rr",
    "gn:population":0,
    "gn:timezone":"Europe/Stockholm",
    "iso:country":"SE",
    "wof:name":"Skattekarr",
    "wof:placetype":"locality"
},
  "geometry": {"coordinates":[12.55,56.25],"type":"Point"}
}