{
  "type": "Feature",
  "properties": {
    "gn:admin1_code":"7.0",
    "gn:admin2_code":"2326.0",
    "gn:asciiname":"Lockasbodarna",
    "gn:country_code":"SE",
    "gn:dem":567,
    "gn:feature_class":"P",
    "gn:feature_code":"PPL",
    "gn:name":"Lock\u00e5sbodarna",
    "gn:population":0,
    "gn:timezone":"Europe/Stockholm",
    "iso:country":"SE",
    "wof:name":"Lockasbodarna",
    "wof:placetype":"locality"
},
  "geometry": {"coordinates":[14.08333,62.95],"type":"Point"}
}