{
  "type": "Feature",
  "properties": {
    "gn:admin1_code":"23.0",
    "gn:admin2_code":"2462.0",
    "gn:asciiname":"Siksjo",
    "gn:country_code":"SE",
    "gn:dem":392,
    "gn:feature_class":"P",
    "gn:feature_code":"PPL",
    "gn:name":"Siksj\u00f6",
    "gn:population":0,
    "gn:timezone":"Europe/Stockholm",
    "iso:country":"SE",
    "name:nor_x_preferred":[
        "Siksj\u00f6"
    ],
    "name:nor_x_variant":[
        "Siksj\u00f8"
    ],
    "name:und_x_variant":[
        "Siksj\u00f6"
    ],
    "wof:name":"Siksjo",
    "wof:placetype":"locality"
},
  "geometry": {"coordinates":[17.11667000000001,64.55],"type":"Point"}
}