{
  "type": "Feature",
  "properties": {
    "gn:admin1_code":"24.0",
    "gn:admin2_code":"2284.0",
    "gn:asciiname":"Hogland",
    "gn:country_code":"SE",
    "gn:dem":100,
    "gn:feature_class":"P",
    "gn:feature_code":"PPL",
    "gn:name":"H\u00f6gland",
    "gn:population":0,
    "gn:timezone":"Europe/Stockholm",
    "iso:country":"SE",
    "name:nor_x_preferred":[
        "H\u00f6gland"
    ],
    "name:nor_x_variant":[
        "H\u00f8gland"
    ],
    "wof:name":"Hogland",
    "wof:placetype":"locality"
},
  "geometry": {"coordinates":[18.73333,63.31667],"type":"Point"}
}