{
  "type": "Feature",
  "properties": {
    "gn:admin1_code":"6.0",
    "gn:admin2_code":"1381.0",
    "gn:asciiname":"Klagstorp",
    "gn:country_code":"SE",
    "gn:dem":31,
    "gn:feature_class":"P",
    "gn:feature_code":"PPL",
    "gn:name":"Kl\u00e4gstorp",
    "gn:population":0,
    "gn:timezone":"Europe/Stockholm",
    "iso:country":"SE",
    "name:ita_x_preferred":[
        "Klagstorp"
    ],
    "name:nld_x_preferred":[
        "Klagstorp"
    ],
    "name:nno_x_preferred":[
        "Klagstorp"
    ],
    "name:nor_x_preferred":[
        "Klagstorp"
    ],
    "name:swe_x_preferred":[
        "Klagstorp"
    ],
    "wof:name":"Klagstorp",
    "wof:placetype":"locality"
},
  "geometry": {"coordinates":[13.06667,56.48333],"type":"Point"}
}