{
  "type": "Feature",
  "properties": {
    "gn:admin1_code":"24.0",
    "gn:admin2_code":"2281.0",
    "gn:admin3_code":"228110.0",
    "gn:admin4_code":"2481.0",
    "gn:asciiname":"Bunsta",
    "gn:country_code":"SE",
    "gn:dem":16,
    "gn:feature_class":"P",
    "gn:feature_code":"PPL",
    "gn:name":"Bunsta",
    "gn:population":0,
    "gn:timezone":"Europe/Stockholm",
    "iso:country":"SE",
    "wof:name":"Bunsta",
    "wof:placetype":"locality"
},
  "geometry": {"coordinates":[17.32613,62.25338000000001],"type":"Point"}
}