{
  "type": "Feature",
  "properties": {
    "gn:admin1_code":"15.0",
    "gn:admin2_code":"1884.0",
    "gn:asciiname":"Skrymtarboda",
    "gn:country_code":"SE",
    "gn:dem":148,
    "gn:feature_class":"P",
    "gn:feature_code":"PPL",
    "gn:name":"Skrymtarboda",
    "gn:population":0,
    "gn:timezone":"Europe/Stockholm",
    "iso:country":"SE",
    "wof:name":"Skrymtarboda",
    "wof:placetype":"locality"
},
  "geometry": {"coordinates":[15.15,59.55],"type":"Point"}
}