{
  "type": "Feature",
  "properties": {
    "gn:admin1_code":"9.0",
    "gn:admin2_code":"884.0",
    "gn:asciiname":"Vanga",
    "gn:country_code":"SE",
    "gn:dem":96,
    "gn:feature_class":"P",
    "gn:feature_code":"PPL",
    "gn:name":"V\u00e5nga",
    "gn:population":0,
    "gn:timezone":"Europe/Stockholm",
    "iso:country":"SE",
    "wof:name":"Vanga",
    "wof:placetype":"locality"
},
  "geometry": {"coordinates":[16.21667,57.56667],"type":"Point"}
}