{
  "type": "Feature",
  "properties": {
    "gn:admin1_code":"9.0",
    "gn:admin2_code":"884.0",
    "gn:asciiname":"Vanga",
    "gn:country_code":"SE",
    "gn:dem":96,
    "gn:feature_class":"P",
    "gn:feature_code":"PPL",
    "gn:name":"V\u00e5nga",
    "gn:population":0,
    "gn:timezone":"Europe/Stockholm",
    "iso:country":"SE",
    "name:bel_x_preferred":[
        "Vangidae"
    ],
    "name:bre_x_preferred":[
        "Vangidae"
    ],
    "name:cat_x_preferred":[
        "Vanga"
    ],
    "name:ceb_x_preferred":[
        "Vangidae"
    ],
    "name:deu_x_preferred":[
        "Vangaw\u00fcrger"
    ],
    "name:epo_x_preferred":[
        "Vangaedoj"
    ],
    "name:est_x_preferred":[
        "Vangalased"
    ],
    "name:fas_x_preferred":[
        "\u0648\u0627\u0646\u06af\u0627"
    ],
    "name:fin_x_preferred":[
        "Vangat"
    ],
    "name:fra_x_preferred":[
        "Vangidae"
    ],
    "name:heb_x_preferred":[
        "\u05d5\u05e0\u05d2\u05d9\u05d9\u05dd"
    ],
    "name:hun_x_preferred":[
        "Vangag\u00e9bicsf\u00e9l\u00e9k"
    ],
    "name:ita_x_preferred":[
        "Vangidae"
    ],
    "name:jpn_x_preferred":[
        "\u30aa\u30aa\u30cf\u30b7\u30e2\u30ba\u79d1"
    ],
    "name:kor_x_preferred":[
        "\ud070\ubd80\ub9ac\ub54c\uae4c\uce58\ub958"
    ],
    "name:mrj_x_preferred":[
        "\u0412\u0430\u043d\u0433\u0430 \u0439\u0438\u0448\u0432\u043b\u04d3"
    ],
    "name:nld_x_preferred":[
        "Vanga's"
    ],
    "name:nno_x_preferred":[
        "Vangaer"
    ],
    "name:nor_x_preferred":[
        "Vangafamilien"
    ],
    "name:pnb_x_preferred":[
        "\u0648\u0627\u0646\u06af\u0627"
    ],
    "name:pol_x_preferred":[
        "Wangowate"
    ],
    "name:por_x_preferred":[
        "Vangidae"
    ],
    "name:rus_x_preferred":[
        "\u0412\u0430\u043d\u0433\u043e\u0432\u044b\u0435"
    ],
    "name:spa_x_preferred":[
        "Vangidae"
    ],
    "name:swa_x_preferred":[
        "Vanga"
    ],
    "name:swe_x_preferred":[
        "Vangor"
    ],
    "name:ukr_x_preferred":[
        "\u0412\u0430\u043d\u0433\u043e\u0432\u0456"
    ],
    "name:vie_x_preferred":[
        "Vangidae"
    ],
    "name:war_x_preferred":[
        "Vangidae"
    ],
    "wof:name":"Vanga",
    "wof:placetype":"locality"
},
  "geometry": {"coordinates":[16.21667,57.56667],"type":"Point"}
}