{
  "type": "Feature",
  "properties": {
    "gn:gn_country":"SE",
    "gn:gn_fcode":"PPL",
    "gn:gn_pop":346,
    "gn:population":346,
    "iso:country":"SE",
    "name:ceb_x_preferred":[
        "Grang\u00e4rde"
    ],
    "name:eng_x_preferred":[
        "Grang\u00e4rde"
    ],
    "name:epo_x_preferred":[
        "Grang\u00e4rde"
    ],
    "name:fas_x_preferred":[
        "\u06af\u0631\u0627\u0646\u200c\u06cc\u0631\u062f"
    ],
    "name:ita_x_preferred":[
        "Grang\u00e4rde"
    ],
    "name:nan_x_preferred":[
        "Grang\u00e4rde"
    ],
    "name:nld_x_preferred":[
        "Grang\u00e4rde"
    ],
    "name:nno_x_preferred":[
        "Grang\u00e4rde"
    ],
    "name:nob_x_preferred":[
        "Grang\u00e4rde"
    ],
    "name:swe_x_preferred":[
        "Grang\u00e4rde"
    ],
    "qs_pg:aaroncc":"SE",
    "qs_pg:gn_country":"SE",
    "qs_pg:gn_fcode":"PPL",
    "qs_pg:gn_pop":346,
    "qs_pg:name":"Grang\u00e4rde",
    "qs_pg:name_adm0":"Sverige",
    "qs_pg:name_adm1":"Dalarnas L\u00e4n",
    "qs_pg:photos":54,
    "qs_pg:photos_1k":11,
    "qs_pg:photos_9k":1,
    "qs_pg:photos_9r":2,
    "qs_pg:photos_all":54,
    "qs_pg:photos_sr":2,
    "qs_pg:pop_sr":2,
    "qs_pg:qs_pg_placetype":"locality",
    "qs_pg:qs_pg_placetype_gp":"Town",
    "qs_pg:woe_adm0":23424954,
    "woe:adm0_id":23424954,
    "woe:name_adm0":"Sverige",
    "woe:name_adm1":"Dalarnas L\u00e4n",
    "woe:placetype":"Town",
    "wof:name":"Grang\u00e4rde",
    "wof:placetype":"locality",
    "wof:population":346
},
  "geometry": {"coordinates":[14.98333,60.26667],"type":"Point"}
}