{
  "type": "Feature",
  "properties": {
    "gn:admin1_code":"23.0",
    "gn:asciiname":"Abosjon",
    "gn:cc2":"SE",
    "gn:country_code":"SE",
    "gn:dem":292,
    "gn:feature_class":"P",
    "gn:feature_code":"PPL",
    "gn:name":"\u00c5bosj\u00f6n",
    "gn:population":0,
    "gn:timezone":"Europe/Stockholm",
    "iso:country":"SE",
    "name:nor_x_preferred":[
        "\u00c5bosj\u00f6n"
    ],
    "name:nor_x_variant":[
        "\u00c5bosj\u00f8n"
    ],
    "name:und_x_variant":[
        "\u00c5bosj\u00f6",
        "\u00c5bosj\u00f6n"
    ],
    "wof:name":"Abosjon",
    "wof:placetype":"locality"
},
  "geometry": {"coordinates":[17.76667,63.75],"type":"Point"}
}