{
  "type": "Feature",
  "properties": {
    "gn:admin1_code":"24.0",
    "gn:admin2_code":"2284.0",
    "gn:asciiname":"Movattnet",
    "gn:country_code":"SE",
    "gn:dem":196,
    "gn:feature_class":"P",
    "gn:feature_code":"PPL",
    "gn:name":"Movattnet",
    "gn:population":0,
    "gn:timezone":"Europe/Stockholm",
    "iso:country":"SE",
    "wof:name":"Movattnet",
    "wof:placetype":"locality"
},
  "geometry": {"coordinates":[18.61667000000001,63.65],"type":"Point"}
}