{
  "type": "Feature",
  "properties": {
    "gn:admin1_code":"12.0",
    "gn:admin2_code":"780.0",
    "gn:asciiname":"Skavenas",
    "gn:country_code":"SE",
    "gn:dem":175,
    "gn:feature_class":"P",
    "gn:feature_code":"PPL",
    "gn:name":"Skaven\u00e4s",
    "gn:population":0,
    "gn:timezone":"Europe/Stockholm",
    "iso:country":"SE",
    "wof:name":"Skavenas",
    "wof:placetype":"locality"
},
  "geometry": {"coordinates":[14.76667,57.05],"type":"Point"}
}