{
  "type": "Feature",
  "properties": {
    "gn:admin1_code":"12.0",
    "gn:admin2_code":"765.0",
    "gn:asciiname":"Langhult",
    "gn:country_code":"SE",
    "gn:dem":166,
    "gn:feature_class":"P",
    "gn:feature_code":"PPL",
    "gn:name":"L\u00e5nghult",
    "gn:population":0,
    "gn:timezone":"Europe/Stockholm",
    "iso:country":"SE",
    "wof:name":"Langhult",
    "wof:placetype":"locality"
},
  "geometry": {"coordinates":[14.43333,56.53333000000001],"type":"Point"}
}