{
  "type": "Feature",
  "properties": {
    "gn:admin1_code":"23.0",
    "gn:admin2_code":"2480.0",
    "gn:asciiname":"Teg",
    "gn:cc2":"SE",
    "gn:country_code":"SE",
    "gn:dem":26,
    "gn:feature_class":"P",
    "gn:feature_code":"PPL",
    "gn:name":"Teg",
    "gn:population":0,
    "gn:timezone":"Europe/Stockholm",
    "iso:country":"SE",
    "name:und_x_variant":[
        "\u00d6sterteg",
        "V\u00e4sterteg"
    ],
    "wof:name":"Teg",
    "wof:placetype":"locality"
},
  "geometry": {"coordinates":[20.24712,63.81955],"type":"Point"}
}