{
  "type": "Feature",
  "properties": {
    "gn:admin1_code":"9.0",
    "gn:admin2_code":"883.0",
    "gn:asciiname":"Rasdal",
    "gn:country_code":"SE",
    "gn:dem":6,
    "gn:feature_class":"P",
    "gn:feature_code":"PPL",
    "gn:name":"R\u00e5sdal",
    "gn:population":0,
    "gn:timezone":"Europe/Stockholm",
    "iso:country":"SE",
    "wof:name":"Rasdal",
    "wof:placetype":"locality"
},
  "geometry": {"coordinates":[16.75278,57.92667],"type":"Point"}
}