{
  "type": "Feature",
  "properties": {
    "gn:admin1_code":"14.0",
    "gn:admin2_code":"2506.0",
    "gn:asciiname":"Grannas",
    "gn:country_code":"SE",
    "gn:dem":405,
    "gn:feature_class":"P",
    "gn:feature_code":"PPL",
    "gn:name":"Grann\u00e4s",
    "gn:population":0,
    "gn:timezone":"Europe/Stockholm",
    "iso:country":"SE",
    "name:swe_x_preferred":[
        "Grann\u00e4s"
    ],
    "wof:name":"Grannas",
    "wof:placetype":"locality"
},
  "geometry": {"coordinates":[18.10279,65.64402],"type":"Point"}
}