{
  "type": "Feature",
  "properties": {
    "gn:country":"SE",
    "gn:fcode":"PPL",
    "gn:population":0,
    "iso:country":"SE",
    "name:dan_x_preferred":[
        "Hartungviken"
    ],
    "name:deu_x_preferred":[
        "Hartungviken"
    ],
    "name:eng_x_preferred":[
        "Hartungviken"
    ],
    "name:fra_x_preferred":[
        "Hartungviken"
    ],
    "name:lld_x_preferred":[
        "Hartungviken"
    ],
    "name:nds_x_preferred":[
        "Hartungviken"
    ],
    "name:nld_x_preferred":[
        "Hartungviken"
    ],
    "name:nno_x_preferred":[
        "Hartungviken"
    ],
    "name:nob_x_preferred":[
        "Hartungviken"
    ],
    "name:pol_x_preferred":[
        "Hartungviken"
    ],
    "name:spa_x_preferred":[
        "Hartungviken"
    ],
    "name:swe_x_preferred":[
        "Hartungviken"
    ],
    "qs_pg:aaroncc":"SE",
    "qs_pg:gn_country":"SE",
    "qs_pg:gn_fcode":"PPL",
    "qs_pg:gn_pop":0,
    "qs_pg:name":"Hartungviken",
    "qs_pg:name_adm0":"Sverige",
    "qs_pg:name_adm1":"V\u00e4sternorrlands L\u00e4n",
    "qs_pg:photos":171,
    "qs_pg:photos_1k":35,
    "qs_pg:photos_9k":1,
    "qs_pg:photos_9r":4,
    "qs_pg:photos_all":171,
    "qs_pg:photos_sr":4,
    "qs_pg:pop_sr":0,
    "qs_pg:qs_pg_placetype":"locality",
    "qs_pg:qs_pg_placetype_gp":"Town",
    "qs_pg:woe_adm0":23424954,
    "woe:adm0_id":23424954,
    "woe:name_adm0":"Sverige",
    "woe:name_adm1":"V\u00e4sternorrlands L\u00e4n",
    "woe:placetype":"Town",
    "wof:name":"Hartungviken",
    "wof:placetype":"locality",
    "wof:population":400
},
  "geometry": {"coordinates":[17.51583,62.39333],"type":"Point"}
}