{
  "type": "Feature",
  "properties": {
    "gn:admin1_code":"27.0",
    "gn:admin2_code":"1282.0",
    "gn:asciiname":"Tofta",
    "gn:country_code":"SE",
    "gn:dem":8,
    "gn:feature_class":"P",
    "gn:feature_code":"PPL",
    "gn:name":"Tofta",
    "gn:population":0,
    "gn:timezone":"Europe/Stockholm",
    "iso:country":"SE",
    "name:ceb_x_preferred":[
        "Tofta"
    ],
    "name:fra_x_preferred":[
        "Tofta"
    ],
    "name:nld_x_preferred":[
        "Tofta"
    ],
    "name:swe_x_preferred":[
        "Tofta"
    ],
    "wof:name":"Tofta",
    "wof:placetype":"locality"
},
  "geometry": {"coordinates":[12.91667,55.86666999999999],"type":"Point"}
}