{
  "type": "Feature",
  "properties": {
    "gn:admin1_code":"23.0",
    "gn:admin2_code":"2417.0",
    "gn:asciiname":"Petiknas",
    "gn:country_code":"SE",
    "gn:dem":226,
    "gn:feature_class":"P",
    "gn:feature_code":"PPL",
    "gn:name":"Petikn\u00e4s",
    "gn:population":0,
    "gn:timezone":"Europe/Stockholm",
    "iso:country":"SE",
    "wof:name":"Petiknas",
    "wof:placetype":"locality"
},
  "geometry": {"coordinates":[20.05,64.93333],"type":"Point"}
}