{
  "type": "Feature",
  "properties": {
    "gn:admin1_code":"28.0",
    "gn:admin2_code":"1460.0",
    "gn:asciiname":"Solsjobodane",
    "gn:country_code":"SE",
    "gn:dem":157,
    "gn:feature_class":"P",
    "gn:feature_code":"PPL",
    "gn:name":"Solsj\u00f6bodane",
    "gn:population":0,
    "gn:timezone":"Europe/Stockholm",
    "iso:country":"SE",
    "name:nor_x_preferred":[
        "Solsj\u00f6bodane"
    ],
    "name:nor_x_variant":[
        "Solsj\u00f8bodane"
    ],
    "name:und_x_variant":[
        "Solsj\u00f6bodane"
    ],
    "wof:name":"Solsjobodane",
    "wof:placetype":"locality"
},
  "geometry": {"coordinates":[12.25,59.08333],"type":"Point"}
}