{
  "type": "Feature",
  "properties": {
    "gn:admin1_code":"16.0",
    "gn:admin2_code":"581.0",
    "gn:asciiname":"Monnerum",
    "gn:country_code":"SE",
    "gn:dem":23,
    "gn:feature_class":"P",
    "gn:feature_code":"PPL",
    "gn:name":"M\u00f6nnerum",
    "gn:population":0,
    "gn:timezone":"Europe/Stockholm",
    "iso:country":"SE",
    "name:nor_x_preferred":[
        "M\u00f6nnerum"
    ],
    "name:nor_x_variant":[
        "M\u00f8nnerum"
    ],
    "wof:name":"Monnerum",
    "wof:placetype":"locality"
},
  "geometry": {"coordinates":[16.76667,58.51667],"type":"Point"}
}