{
  "type": "Feature",
  "properties": {
    "gn:country":"SE",
    "gn:fcode":"PPL",
    "gn:population":333,
    "iso:country":"SE",
    "name:ceb_x_preferred":[
        "Junisk\u00e4ren"
    ],
    "name:dan_x_preferred":[
        "Junisk\u00e4r"
    ],
    "name:deu_x_preferred":[
        "Junisk\u00e4r"
    ],
    "name:eng_x_preferred":[
        "Junisk\u00e4r"
    ],
    "name:fra_x_preferred":[
        "Junisk\u00e4r"
    ],
    "name:gle_x_preferred":[
        "Junisk\u00e4r"
    ],
    "name:ita_x_preferred":[
        "Junisk\u00e4r"
    ],
    "name:lld_x_preferred":[
        "Junisk\u00e4r"
    ],
    "name:nan_x_preferred":[
        "Junisk\u00e4r"
    ],
    "name:nld_x_preferred":[
        "Junisk\u00e4r"
    ],
    "name:nno_x_preferred":[
        "Junisk\u00e4r"
    ],
    "name:nob_x_preferred":[
        "Junisk\u00e4r"
    ],
    "name:swe_x_preferred":[
        "Junisk\u00e4r"
    ],
    "qs_pg:aaroncc":"SE",
    "qs_pg:gn_country":"SE",
    "qs_pg:gn_fcode":"PPL",
    "qs_pg:gn_pop":333,
    "qs_pg:name":"Junisk\u00e4r",
    "qs_pg:name_adm0":"Sverige",
    "qs_pg:name_adm1":"V\u00e4sternorrlands L\u00e4n",
    "qs_pg:photos":52,
    "qs_pg:photos_1k":11,
    "qs_pg:photos_9k":1,
    "qs_pg:photos_9r":2,
    "qs_pg:photos_all":52,
    "qs_pg:photos_sr":2,
    "qs_pg:pop_sr":2,
    "qs_pg:qs_pg_placetype":"locality",
    "qs_pg:qs_pg_placetype_gp":"Town",
    "qs_pg:woe_adm0":23424954,
    "woe:adm0_id":23424954,
    "woe:name_adm0":"Sverige",
    "woe:name_adm1":"V\u00e4sternorrlands L\u00e4n",
    "woe:placetype":"Town",
    "wof:name":"Junisk\u00e4r",
    "wof:placetype":"locality",
    "wof:population":333
},
  "geometry": {"coordinates":[17.46,62.29639],"type":"Point"}
}