{
  "type": "Feature",
  "properties": {
    "gn:admin1_code":"8.0",
    "gn:admin2_code":"662.0",
    "gn:asciiname":"Bjarsved",
    "gn:cc2":"SE",
    "gn:country_code":"SE",
    "gn:dem":210,
    "gn:feature_class":"P",
    "gn:feature_code":"PPL",
    "gn:name":"Bj\u00e4rsved",
    "gn:population":0,
    "gn:timezone":"Europe/Stockholm",
    "iso:country":"SE",
    "name:und_x_variant":[
        "Bjersved",
        "Bj\u00e4rsved"
    ],
    "wof:name":"Bjarsved",
    "wof:placetype":"locality"
},
  "geometry": {"coordinates":[13.61667,57.46666999999999],"type":"Point"}
}