{
  "type": "Feature",
  "properties": {
    "gn:admin1_code":"15.0",
    "gn:admin2_code":"1880.0",
    "gn:asciiname":"Bo",
    "gn:country_code":"SE",
    "gn:dem":66,
    "gn:feature_class":"P",
    "gn:feature_code":"PPL",
    "gn:name":"Bo",
    "gn:population":0,
    "gn:timezone":"Europe/Stockholm",
    "iso:country":"SE",
    "name:dan_x_preferred":[
        "Bo"
    ],
    "name:hye_x_preferred":[
        "\u0532\u0578"
    ],
    "name:lit_x_preferred":[
        "Bo"
    ],
    "wof:name":"Bo",
    "wof:placetype":"locality"
},
  "geometry": {"coordinates":[14.96667,59.13306],"type":"Point"}
}