{
  "type": "Feature",
  "properties": {
    "gn:admin1_code":"22.0",
    "gn:admin2_code":"1783.0",
    "gn:asciiname":"Sodra Gras",
    "gn:cc2":"SE",
    "gn:country_code":"SE",
    "gn:dem":162,
    "gn:feature_class":"P",
    "gn:feature_code":"PPL",
    "gn:name":"S\u00f6dra Gr\u00e4s",
    "gn:population":0,
    "gn:timezone":"Europe/Stockholm",
    "iso:country":"SE",
    "name:und_x_variant":[
        "Gr\u00e4s",
        "S\u00f6dra Gr\u00e4s"
    ],
    "wof:name":"Sodra Gras",
    "wof:placetype":"locality"
},
  "geometry": {"coordinates":[13.75,59.85],"type":"Point"}
}