{
  "type": "Feature",
  "properties": {
    "gn:admin1_code":"23.0",
    "gn:admin2_code":"2480.0",
    "gn:asciiname":"Vaxtholm",
    "gn:country_code":"SE",
    "gn:dem":89,
    "gn:feature_class":"P",
    "gn:feature_code":"PPL",
    "gn:name":"V\u00e4xtholm",
    "gn:population":0,
    "gn:timezone":"Europe/Stockholm",
    "iso:country":"SE",
    "wof:name":"Vaxtholm",
    "wof:placetype":"locality"
},
  "geometry": {"coordinates":[20.38333,64.03333000000001],"type":"Point"}
}