{
  "type": "Feature",
  "properties": {
    "gn:admin1_code":"27.0",
    "gn:admin2_code":"1290.0",
    "gn:asciiname":"Trusserod",
    "gn:country_code":"SE",
    "gn:dem":113,
    "gn:feature_class":"P",
    "gn:feature_code":"PPL",
    "gn:name":"Trusser\u00f6d",
    "gn:population":0,
    "gn:timezone":"Europe/Stockholm",
    "iso:country":"SE",
    "name:nor_x_preferred":[
        "Trusser\u00f6d"
    ],
    "name:nor_x_variant":[
        "Trusser\u00f8d"
    ],
    "name:und_x_variant":[
        "Trusser\u00f6d"
    ],
    "wof:name":"Trusserod",
    "wof:placetype":"locality"
},
  "geometry": {"coordinates":[14.08333,55.78333000000001],"type":"Point"}
}