{
  "type": "Feature",
  "properties": {
    "gn:admin1_code":"22.0",
    "gn:admin2_code":"1785.0",
    "gn:asciiname":"Knostad",
    "gn:country_code":"SE",
    "gn:dem":61,
    "gn:feature_class":"P",
    "gn:feature_code":"PPL",
    "gn:name":"Kn\u00f6stad",
    "gn:population":0,
    "gn:timezone":"Europe/Stockholm",
    "iso:country":"SE",
    "name:nor_x_preferred":[
        "Kn\u00f6stad"
    ],
    "name:nor_x_variant":[
        "Kn\u00f8stad"
    ],
    "name:und_x_variant":[
        "Kn\u00f6stad"
    ],
    "wof:name":"Knostad",
    "wof:placetype":"locality"
},
  "geometry": {"coordinates":[12.81667,59.25],"type":"Point"}
}