{
  "type": "Feature",
  "properties": {
    "gn:admin1_code":"23.0",
    "gn:admin2_code":"2481.0",
    "gn:asciiname":"Arvtrask",
    "gn:country_code":"SE",
    "gn:dem":217,
    "gn:feature_class":"P",
    "gn:feature_code":"PPL",
    "gn:name":"Arvtr\u00e4sk",
    "gn:population":0,
    "gn:timezone":"Europe/Stockholm",
    "iso:country":"SE",
    "wof:name":"Arvtrask",
    "wof:placetype":"locality"
},
  "geometry": {"coordinates":[19.01667,64.58333],"type":"Point"}
}