{
  "type": "Feature",
  "properties": {
    "gn:admin1_code":"10.0",
    "gn:admin2_code":"2083.0",
    "gn:asciiname":"Skommarbo",
    "gn:country_code":"SE",
    "gn:dem":168,
    "gn:feature_class":"P",
    "gn:feature_code":"PPL",
    "gn:name":"Skommarbo",
    "gn:population":0,
    "gn:timezone":"Europe/Stockholm",
    "iso:country":"SE",
    "wof:name":"Skommarbo",
    "wof:placetype":"locality"
},
  "geometry": {"coordinates":[16.16667,60.28333000000001],"type":"Point"}
}