{
  "type": "Feature",
  "properties": {
    "gn:admin1_code":"22.0",
    "gn:admin2_code":"1763.0",
    "gn:asciiname":"Sund",
    "gn:country_code":"SE",
    "gn:dem":152,
    "gn:feature_class":"P",
    "gn:feature_code":"PPL",
    "gn:name":"Sund",
    "gn:population":0,
    "gn:timezone":"Europe/Stockholm",
    "iso:country":"SE",
    "wof:name":"Sund",
    "wof:placetype":"locality"
},
  "geometry": {"coordinates":[13.65,59.73333],"type":"Point"}
}