{
  "type": "Feature",
  "properties": {
    "gn:admin1_code":"7.0",
    "gn:admin2_code":"2309.0",
    "gn:asciiname":"Konsta",
    "gn:country_code":"SE",
    "gn:dem":325,
    "gn:feature_class":"P",
    "gn:feature_code":"PPL",
    "gn:name":"K\u00f6nsta",
    "gn:population":0,
    "gn:timezone":"Europe/Stockholm",
    "iso:country":"SE",
    "name:nor_x_preferred":[
        "K\u00f6nsta"
    ],
    "name:nor_x_variant":[
        "K\u00f8nsta"
    ],
    "wof:name":"Konsta",
    "wof:placetype":"locality"
},
  "geometry": {"coordinates":[14.06667,63.43333000000001],"type":"Point"}
}