{
  "type": "Feature",
  "properties": {
    "gn:admin1_code":"7.0",
    "gn:admin2_code":"2309.0",
    "gn:asciiname":"Osterulvsas",
    "gn:cc2":"SE",
    "gn:country_code":"SE",
    "gn:dem":319,
    "gn:feature_class":"P",
    "gn:feature_code":"PPL",
    "gn:name":"\u00d6sterulvs\u00e5s",
    "gn:population":0,
    "gn:timezone":"Europe/Stockholm",
    "iso:country":"SE",
    "name:nor_x_preferred":[
        "\u00d6sterulvs\u00e5s"
    ],
    "name:nor_x_variant":[
        "\u00d8sterulvs\u00e5s"
    ],
    "name:und_x_variant":[
        "Ulvs\u00e5s",
        "\u00d6stra Ulfs\u00e5s",
        "\u00d6stra Ulvs\u00e5s",
        "\u00d6sterulvs\u00e5s"
    ],
    "wof:name":"Osterulvsas",
    "wof:placetype":"locality"
},
  "geometry": {"coordinates":[14.31667,63.48333],"type":"Point"}
}