{
  "type": "Feature",
  "properties": {
    "gn:admin1_code":"16.0",
    "gn:admin2_code":"512.0",
    "gn:asciiname":"Hertsmalen",
    "gn:cc2":"SE",
    "gn:country_code":"SE",
    "gn:dem":286,
    "gn:feature_class":"P",
    "gn:feature_code":"PPL",
    "gn:name":"Hertsm\u00e5len",
    "gn:population":0,
    "gn:timezone":"Europe/Stockholm",
    "iso:country":"SE",
    "name:und_x_variant":[
        "Harsm\u00e5la",
        "Hertsm\u00e5la",
        "Hertsm\u00e5len"
    ],
    "wof:name":"Hertsmalen",
    "wof:placetype":"locality"
},
  "geometry": {"coordinates":[15.08333,57.91667],"type":"Point"}
}