{
  "type": "Feature",
  "properties": {
    "gn:admin1_code":"22.0",
    "gn:admin2_code":"1730.0",
    "gn:asciiname":"Sjogerval",
    "gn:country_code":"SE",
    "gn:dem":111,
    "gn:feature_class":"P",
    "gn:feature_code":"PPL",
    "gn:name":"Sj\u00f6gerv\u00e5l",
    "gn:population":0,
    "gn:timezone":"Europe/Stockholm",
    "iso:country":"SE",
    "name:nor_x_preferred":[
        "Sj\u00f6gerv\u00e5l"
    ],
    "name:nor_x_variant":[
        "Sj\u00f8gerv\u00e5l"
    ],
    "name:und_x_variant":[
        "Sj\u00f6gerv\u00e5l"
    ],
    "wof:name":"Sjogerval",
    "wof:placetype":"locality"
},
  "geometry": {"coordinates":[12.31667,59.83333],"type":"Point"}
}