{
  "type": "Feature",
  "properties": {
    "gn:admin1_code":"7.0",
    "gn:admin2_code":"2361.0",
    "gn:asciiname":"Stensan",
    "gn:country_code":"SE",
    "gn:dem":277,
    "gn:feature_class":"P",
    "gn:feature_code":"PPL",
    "gn:name":"Stens\u00e5n",
    "gn:population":0,
    "gn:timezone":"Europe/Stockholm",
    "iso:country":"SE",
    "wof:name":"Stensan",
    "wof:placetype":"locality"
},
  "geometry": {"coordinates":[15.16667,62.23333],"type":"Point"}
}