{
  "type": "Feature",
  "properties": {
    "gn:admin1_code":"24.0",
    "gn:admin2_code":"2262.0",
    "gn:admin3_code":"226201.0",
    "gn:admin4_code":"2501.0",
    "gn:asciiname":"Lovudden",
    "gn:country_code":"SE",
    "gn:dem":-9999,
    "gn:feature_class":"P",
    "gn:feature_code":"PPL",
    "gn:name":"L\u00f6vudden",
    "gn:population":0,
    "gn:timezone":"Europe/Stockholm",
    "iso:country":"SE",
    "name:nor_x_preferred":[
        "L\u00f6vudden"
    ],
    "name:nor_x_variant":[
        "L\u00f8vudden"
    ],
    "wof:name":"Lovudden",
    "wof:placetype":"locality"
},
  "geometry": {"coordinates":[17.44629,62.5145],"type":"Point"}
}