{
  "type": "Feature",
  "properties": {
    "gn:admin1_code":"23.0",
    "gn:admin2_code":"2481.0",
    "gn:asciiname":"Ledaberg",
    "gn:country_code":"SE",
    "gn:dem":388,
    "gn:feature_class":"P",
    "gn:feature_code":"PPL",
    "gn:name":"Led\u00e5berg",
    "gn:population":0,
    "gn:timezone":"Europe/Stockholm",
    "iso:country":"SE",
    "wof:name":"Ledaberg",
    "wof:placetype":"locality"
},
  "geometry": {"coordinates":[18.21667,64.53333000000001],"type":"Point"}
}