{
  "type": "Feature",
  "properties": {
    "gn:admin1_code":"22.0",
    "gn:asciiname":"Dalen",
    "gn:country_code":"SE",
    "gn:dem":188,
    "gn:feature_class":"P",
    "gn:feature_code":"PPL",
    "gn:name":"Dalen",
    "gn:population":0,
    "gn:timezone":"Europe/Stockholm",
    "iso:country":"SE",
    "name:ceb_x_preferred":[
        "Dalen"
    ],
    "name:cym_x_preferred":[
        "Dalen"
    ],
    "name:fra_x_preferred":[
        "Dalen"
    ],
    "name:fry_x_preferred":[
        "Dalen"
    ],
    "name:ita_x_preferred":[
        "Dalen"
    ],
    "name:nld_x_preferred":[
        "Dalen"
    ],
    "name:pol_x_preferred":[
        "Dalen"
    ],
    "wof:name":"Dalen",
    "wof:placetype":"locality"
},
  "geometry": {"coordinates":[11.73333,59.55],"type":"Point"}
}