{
  "type": "Feature",
  "properties": {
    "gn:admin1_code":"28.0",
    "gn:asciiname":"Gronvik",
    "gn:country_code":"SE",
    "gn:dem":-9999,
    "gn:feature_class":"P",
    "gn:feature_code":"PPL",
    "gn:name":"Gr\u00f6nvik",
    "gn:population":0,
    "gn:timezone":"Europe/Stockholm",
    "iso:country":"SE",
    "name:nor_x_preferred":[
        "Gr\u00f6nvik"
    ],
    "name:nor_x_variant":[
        "Gr\u00f8nvik"
    ],
    "wof:name":"Gronvik",
    "wof:placetype":"locality"
},
  "geometry": {"coordinates":[11.34167,58.35417],"type":"Point"}
}