{
  "type": "Feature",
  "properties": {
    "gn:admin1_code":"25.0",
    "gn:admin2_code":"1904.0",
    "gn:asciiname":"Rolo",
    "gn:country_code":"SE",
    "gn:dem":79,
    "gn:feature_class":"P",
    "gn:feature_code":"PPL",
    "gn:name":"R\u00f6l\u00f6",
    "gn:population":0,
    "gn:timezone":"Europe/Stockholm",
    "iso:country":"SE",
    "name:deu_x_preferred":[
        "Rolo"
    ],
    "name:fra_x_preferred":[
        "Rolo"
    ],
    "name:nld_x_preferred":[
        "Rolo"
    ],
    "name:nor_x_preferred":[
        "R\u00f6l\u00f6"
    ],
    "name:nor_x_variant":[
        "R\u00f8l\u00f8"
    ],
    "name:tur_x_preferred":[
        "Rolo"
    ],
    "wof:name":"Rolo",
    "wof:placetype":"locality"
},
  "geometry": {"coordinates":[15.93333,59.68333000000001],"type":"Point"}
}