{
  "type": "Feature",
  "properties": {
    "gn:admin1_code":"9.0",
    "gn:admin2_code":"881.0",
    "gn:asciiname":"Hogebo",
    "gn:country_code":"SE",
    "gn:dem":80,
    "gn:feature_class":"P",
    "gn:feature_code":"PPL",
    "gn:name":"H\u00f6gebo",
    "gn:population":0,
    "gn:timezone":"Europe/Stockholm",
    "iso:country":"SE",
    "name:nor_x_preferred":[
        "H\u00f6gebo"
    ],
    "name:nor_x_variant":[
        "H\u00f8gebo"
    ],
    "name:und_x_variant":[
        "H\u00f6gebo"
    ],
    "wof:name":"Hogebo",
    "wof:placetype":"locality"
},
  "geometry": {"coordinates":[15.98333,56.76667],"type":"Point"}
}