{
  "type": "Feature",
  "properties": {
    "gn:admin1_code":"7.0",
    "gn:admin2_code":"2326.0",
    "gn:asciiname":"Aldbodarna",
    "gn:cc2":"SE",
    "gn:country_code":"SE",
    "gn:dem":366,
    "gn:feature_class":"P",
    "gn:feature_code":"PPL",
    "gn:name":"\u00c4ldbodarna",
    "gn:population":0,
    "gn:timezone":"Europe/Stockholm",
    "iso:country":"SE",
    "name:und_x_variant":[
        "\u00c4ldodarna",
        "\u00c4ldbodarna"
    ],
    "wof:name":"Aldbodarna",
    "wof:placetype":"locality"
},
  "geometry": {"coordinates":[14.41667,62.61666999999999],"type":"Point"}
}