{
  "type": "Feature",
  "properties": {
    "gn:admin1_code":"27.0",
    "gn:admin2_code":"1270.0",
    "gn:asciiname":"Listarum",
    "gn:country_code":"SE",
    "gn:dem":89,
    "gn:feature_class":"P",
    "gn:feature_code":"PPL",
    "gn:name":"Listarum",
    "gn:population":0,
    "gn:timezone":"Europe/Stockholm",
    "iso:country":"SE",
    "wof:name":"Listarum",
    "wof:placetype":"locality"
},
  "geometry": {"coordinates":[14.11667,55.58333],"type":"Point"}
}