{
  "type": "Feature",
  "properties": {
    "gn:admin1_code":"24.0",
    "gn:admin2_code":"2280.0",
    "gn:asciiname":"Skjollsta",
    "gn:country_code":"SE",
    "gn:dem":136,
    "gn:feature_class":"P",
    "gn:feature_code":"PPL",
    "gn:name":"Skjollsta",
    "gn:population":0,
    "gn:timezone":"Europe/Stockholm",
    "iso:country":"SE",
    "wof:name":"Skjollsta",
    "wof:placetype":"locality"
},
  "geometry": {"coordinates":[17.68332999999999,62.65],"type":"Point"}
}