{
  "type": "Feature",
  "properties": {
    "gn:admin1_code":"24.0",
    "gn:admin2_code":"2280.0",
    "gn:admin3_code":"228006.0",
    "gn:admin4_code":"2499.0",
    "gn:asciiname":"Bondsjo",
    "gn:cc2":"SE",
    "gn:country_code":"SE",
    "gn:dem":81,
    "gn:feature_class":"P",
    "gn:feature_code":"PPL",
    "gn:name":"Bondsj\u00f6",
    "gn:population":0,
    "gn:timezone":"Europe/Stockholm",
    "iso:country":"SE",
    "name:nor_x_preferred":[
        "Bondsj\u00f6"
    ],
    "name:nor_x_variant":[
        "Bondsj\u00f8"
    ],
    "name:und_x_variant":[
        "Bondsj\u00f6h\u00f6jden",
        "Bondsj\u00f6"
    ],
    "wof:name":"Bondsjo",
    "wof:placetype":"locality"
},
  "geometry": {"coordinates":[17.88332999999999,62.65],"type":"Point"}
}