{
  "type": "Feature",
  "properties": {
    "gn:admin1_code":"16.0",
    "gn:admin2_code":"513.0",
    "gn:asciiname":"Ennesbo",
    "gn:country_code":"SE",
    "gn:dem":189,
    "gn:feature_class":"P",
    "gn:feature_code":"PPL",
    "gn:name":"Ennesbo",
    "gn:population":0,
    "gn:timezone":"Europe/Stockholm",
    "iso:country":"SE",
    "wof:name":"Ennesbo",
    "wof:placetype":"locality"
},
  "geometry": {"coordinates":[15.63333,57.86666999999999],"type":"Point"}
}