{
  "type": "Feature",
  "properties": {
    "gn:admin1_code":"27.0",
    "gn:admin2_code":"1284.0",
    "gn:asciiname":"Vattenmollan",
    "gn:country_code":"SE",
    "gn:dem":12,
    "gn:feature_class":"P",
    "gn:feature_code":"PPL",
    "gn:name":"Vattenm\u00f6llan",
    "gn:population":0,
    "gn:timezone":"Europe/Stockholm",
    "iso:country":"SE",
    "name:nor_x_preferred":[
        "Vattenm\u00f6llan"
    ],
    "name:nor_x_variant":[
        "Vattenm\u00f8llan"
    ],
    "wof:name":"Vattenmollan",
    "wof:placetype":"locality"
},
  "geometry": {"coordinates":[12.51667,56.26667],"type":"Point"}
}