{
  "type": "Feature",
  "properties": {
    "gn:admin1_code":"28.0",
    "gn:admin2_code":"1470.0",
    "gn:asciiname":"Ulvstorp",
    "gn:country_code":"SE",
    "gn:dem":83,
    "gn:feature_class":"P",
    "gn:feature_code":"PPL",
    "gn:name":"Ulvstorp",
    "gn:population":0,
    "gn:timezone":"Europe/Stockholm",
    "iso:country":"SE",
    "wof:name":"Ulvstorp",
    "wof:placetype":"locality"
},
  "geometry": {"coordinates":[12.82259,58.31774],"type":"Point"}
}