{
  "type": "Feature",
  "properties": {
    "gn:admin1_code":"24.0",
    "gn:admin2_code":"2284.0",
    "gn:asciiname":"Vastergensjo",
    "gn:cc2":"SE",
    "gn:country_code":"SE",
    "gn:dem":128,
    "gn:feature_class":"P",
    "gn:feature_code":"PPL",
    "gn:name":"V\u00e4stergensj\u00f6",
    "gn:population":0,
    "gn:timezone":"Europe/Stockholm",
    "iso:country":"SE",
    "name:und_x_variant":[
        "Gensj\u00f6",
        "V\u00e4stra Gensj\u00f6",
        "V\u00e4stergensj\u00f6"
    ],
    "wof:name":"Vastergensjo",
    "wof:placetype":"locality"
},
  "geometry": {"coordinates":[18.03333,63.46666999999999],"type":"Point"}
}