{
  "type": "Feature",
  "properties": {
    "gn:admin1_code":"14.0",
    "gn:admin2_code":"2505.0",
    "gn:asciiname":"Lilla Backnas",
    "gn:country_code":"SE",
    "gn:dem":419,
    "gn:feature_class":"P",
    "gn:feature_code":"PPL",
    "gn:name":"Lilla B\u00e4ckn\u00e4s",
    "gn:population":0,
    "gn:timezone":"Europe/Stockholm",
    "iso:country":"SE",
    "name:swe_x_preferred":[
        "Lilla B\u00e4ckn\u00e4s"
    ],
    "name:und_x_variant":[
        "B\u00e4ckn\u00e4s"
    ],
    "wof:name":"Lilla Backnas",
    "wof:placetype":"locality"
},
  "geometry": {"coordinates":[18.57274,65.64465],"type":"Point"}
}