{
  "type": "Feature",
  "properties": {
    "gn:admin1_code":"15.0",
    "gn:admin2_code":"1860.0",
    "gn:admin3_code":"186004.0",
    "gn:admin4_code":"2259.0",
    "gn:asciiname":"Porla brunn",
    "gn:country_code":"SE",
    "gn:dem":93,
    "gn:feature_class":"P",
    "gn:feature_code":"PPL",
    "gn:name":"Porla brunn",
    "gn:population":0,
    "gn:timezone":"Europe/Stockholm",
    "iso:country":"SE",
    "wof:name":"Porla brunn",
    "wof:placetype":"locality"
},
  "geometry": {"coordinates":[14.6632,59.02803],"type":"Point"}
}