{
  "type": "Feature",
  "properties": {
    "gn:admin1_code":"18.0",
    "gn:admin2_code":"482.0",
    "gn:asciiname":"Malby",
    "gn:country_code":"SE",
    "gn:dem":54,
    "gn:feature_class":"P",
    "gn:feature_code":"PPL",
    "gn:name":"M\u00e4lby",
    "gn:population":0,
    "gn:timezone":"Europe/Stockholm",
    "iso:country":"SE",
    "wof:name":"Malby",
    "wof:placetype":"locality"
},
  "geometry": {"coordinates":[16.71667,59.18333000000001],"type":"Point"}
}