{
  "type": "Feature",
  "properties": {
    "gn:admin1_code":"15.0",
    "gn:admin2_code":"1864.0",
    "gn:asciiname":"Brannbyn",
    "gn:country_code":"SE",
    "gn:dem":319,
    "gn:feature_class":"P",
    "gn:feature_code":"PPL",
    "gn:name":"Br\u00e4nnbyn",
    "gn:population":0,
    "gn:timezone":"Europe/Stockholm",
    "iso:country":"SE",
    "wof:name":"Brannbyn",
    "wof:placetype":"locality"
},
  "geometry": {"coordinates":[15.06667,59.96666999999999],"type":"Point"}
}