{
  "type": "Feature",
  "properties": {
    "gn:admin1_code":"15.0",
    "gn:asciiname":"Svanhult",
    "gn:country_code":"SE",
    "gn:dem":118,
    "gn:feature_class":"P",
    "gn:feature_code":"PPL",
    "gn:name":"Svanhult",
    "gn:population":0,
    "gn:timezone":"Europe/Stockholm",
    "iso:country":"SE",
    "wof:name":"Svanhult",
    "wof:placetype":"locality"
},
  "geometry": {"coordinates":[14.48333,58.71666999999999],"type":"Point"}
}