{
  "type": "Feature",
  "properties": {
    "gn:admin1_code":"10.0",
    "gn:admin2_code":"2029.0",
    "gn:asciiname":"Ovre Boda",
    "gn:cc2":"SE",
    "gn:country_code":"SE",
    "gn:dem":195,
    "gn:feature_class":"P",
    "gn:feature_code":"PPL",
    "gn:name":"\u00d6vre Boda",
    "gn:population":0,
    "gn:timezone":"Europe/Stockholm",
    "iso:country":"SE",
    "name:nor_x_preferred":[
        "\u00d6vre Boda"
    ],
    "name:nor_x_variant":[
        "\u00d8vre Boda"
    ],
    "name:und_x_variant":[
        "\u00d6fvre Boda"
    ],
    "wof:name":"Ovre Boda",
    "wof:placetype":"locality"
},
  "geometry": {"coordinates":[15.03333,60.78333000000001],"type":"Point"}
}