{
  "type": "Feature",
  "properties": {
    "gn:admin1_code":"14.0",
    "gn:admin2_code":"2505.0",
    "gn:asciiname":"Ljusselsstugan",
    "gn:country_code":"SE",
    "gn:dem":357,
    "gn:feature_class":"P",
    "gn:feature_code":"PPL",
    "gn:name":"Ljusselsstugan",
    "gn:population":0,
    "gn:timezone":"Europe/Stockholm",
    "iso:country":"SE",
    "wof:name":"Ljusselsstugan",
    "wof:placetype":"locality"
},
  "geometry": {"coordinates":[19.51667,65.96666999999999],"type":"Point"}
}