{
  "type": "Feature",
  "properties": {
    "gn:admin1_code":"22.0",
    "gn:admin2_code":"1765.0",
    "gn:asciiname":"Toresbyn",
    "gn:country_code":"SE",
    "gn:dem":121,
    "gn:feature_class":"P",
    "gn:feature_code":"PPL",
    "gn:name":"T\u00f6resbyn",
    "gn:population":0,
    "gn:timezone":"Europe/Stockholm",
    "iso:country":"SE",
    "name:nor_x_preferred":[
        "T\u00f6resbyn"
    ],
    "name:nor_x_variant":[
        "T\u00f8resbyn"
    ],
    "wof:name":"Toresbyn",
    "wof:placetype":"locality"
},
  "geometry": {"coordinates":[11.95,59.28333000000001],"type":"Point"}
}