{
  "type": "Feature",
  "properties": {
    "gn:admin1_code":"26.0",
    "gn:admin2_code":"188.0",
    "gn:asciiname":"Sjohagnaden",
    "gn:country_code":"SE",
    "gn:dem":32,
    "gn:feature_class":"P",
    "gn:feature_code":"PPL",
    "gn:name":"Sj\u00f6h\u00e4gnaden",
    "gn:population":0,
    "gn:timezone":"Europe/Stockholm",
    "iso:country":"SE",
    "wof:name":"Sjohagnaden",
    "wof:placetype":"locality"
},
  "geometry": {"coordinates":[18.85,59.76667],"type":"Point"}
}