{
  "type": "Feature",
  "properties": {
    "gn:admin1_code":"25.0",
    "gn:admin2_code":"1907.0",
    "gn:asciiname":"Gammelby",
    "gn:country_code":"SE",
    "gn:dem":90,
    "gn:feature_class":"P",
    "gn:feature_code":"PPL",
    "gn:name":"Gammelby",
    "gn:population":0,
    "gn:timezone":"Europe/Stockholm",
    "iso:country":"SE",
    "name:ceb_x_preferred":[
        "Gammelby"
    ],
    "name:dan_x_preferred":[
        "Gammelby"
    ],
    "name:deu_x_preferred":[
        "Gammelby"
    ],
    "name:epo_x_preferred":[
        "Gammelby"
    ],
    "name:eus_x_preferred":[
        "Gammelby"
    ],
    "name:fas_x_preferred":[
        "\u06af\u0627\u0645\u0644\u0628\u06cc"
    ],
    "name:fra_x_preferred":[
        "Gammelby"
    ],
    "name:hun_x_preferred":[
        "Gammelby"
    ],
    "name:ita_x_preferred":[
        "Gammelby"
    ],
    "name:kaz_x_preferred":[
        "\u0413\u0430\u043c\u043c\u0435\u043b\u044c\u0431\u0438"
    ],
    "name:kir_x_preferred":[
        "\u0413\u0430\u043c\u043c\u0435\u043b\u044c\u0431\u0438"
    ],
    "name:mkd_x_preferred":[
        "\u0413\u0430\u043c\u0435\u043b\u0431\u0438"
    ],
    "name:msa_x_preferred":[
        "Gammelby"
    ],
    "name:nld_x_preferred":[
        "Gammelby"
    ],
    "name:pol_x_preferred":[
        "Gammelby"
    ],
    "name:por_x_preferred":[
        "Gammelby"
    ],
    "name:ron_x_preferred":[
        "Gammelby"
    ],
    "name:rus_x_preferred":[
        "\u0413\u0430\u043c\u043c\u0435\u043b\u044c\u0431\u0438"
    ],
    "name:spa_x_preferred":[
        "Gammelby"
    ],
    "name:srp_x_preferred":[
        "\u0413\u0430\u043c\u0435\u043b\u0431\u0438"
    ],
    "name:tur_x_preferred":[
        "Gammelby"
    ],
    "name:ukr_x_preferred":[
        "\u0413\u0430\u043c\u043c\u0435\u043b\u044c\u0431\u0456"
    ],
    "name:uzb_x_preferred":[
        "Gammelby"
    ],
    "name:vie_x_preferred":[
        "Gammelby"
    ],
    "name:vol_x_preferred":[
        "Gammelby"
    ],
    "name:war_x_preferred":[
        "Gammelby"
    ],
    "name:zho_x_preferred":[
        "\u52a0\u6885\u5c14\u6bd4"
    ],
    "wof:name":"Gammelby",
    "wof:placetype":"locality"
},
  "geometry": {"coordinates":[16.08333,59.86666999999999],"type":"Point"}
}