{
  "type": "Feature",
  "properties": {
    "gn:admin1_code":"24.0",
    "gn:admin2_code":"2281.0",
    "gn:admin3_code":"228101.0",
    "gn:admin4_code":"2497.0",
    "gn:asciiname":"Korsta",
    "gn:country_code":"SE",
    "gn:dem":33,
    "gn:feature_class":"P",
    "gn:feature_code":"PPL",
    "gn:name":"Korsta",
    "gn:population":0,
    "gn:timezone":"Europe/Stockholm",
    "iso:country":"SE",
    "wof:name":"Korsta",
    "wof:placetype":"locality"
},
  "geometry": {"coordinates":[17.37617,62.4072],"type":"Point"}
}