{
  "type": "Feature",
  "properties": {
    "gn:admin1_code":"12.0",
    "gn:admin2_code":"765.0",
    "gn:asciiname":"Kornberga",
    "gn:cc2":"SE",
    "gn:country_code":"SE",
    "gn:dem":134,
    "gn:feature_class":"P",
    "gn:feature_code":"PPL",
    "gn:name":"Kornberga",
    "gn:population":0,
    "gn:timezone":"Europe/Stockholm",
    "iso:country":"SE",
    "name:und_x_variant":[
        "Kronberga",
        "Kornberga"
    ],
    "wof:name":"Kornberga",
    "wof:placetype":"locality"
},
  "geometry": {"coordinates":[13.85,56.46666999999999],"type":"Point"}
}