{
  "type": "Feature",
  "properties": {
    "gn:admin1_code":"23.0",
    "gn:admin2_code":"2481.0",
    "gn:asciiname":"Bergvattnet",
    "gn:country_code":"SE",
    "gn:dem":276,
    "gn:feature_class":"P",
    "gn:feature_code":"PPL",
    "gn:name":"Bergvattnet",
    "gn:population":0,
    "gn:timezone":"Europe/Stockholm",
    "iso:country":"SE",
    "wof:name":"Bergvattnet",
    "wof:placetype":"locality"
},
  "geometry": {"coordinates":[18.25,65.01666999999999],"type":"Point"}
}