{
  "type": "Feature",
  "properties": {
    "gn:admin1_code":"14.0",
    "gn:admin2_code":"2510.0",
    "gn:asciiname":"Kartevarekatorna",
    "gn:country_code":"SE",
    "gn:dem":850,
    "gn:feature_class":"P",
    "gn:feature_code":"PPL",
    "gn:name":"Kartevarek\u00e5torna",
    "gn:population":0,
    "gn:timezone":"Europe/Stockholm",
    "iso:country":"SE",
    "wof:name":"Kartevarekatorna",
    "wof:placetype":"locality"
},
  "geometry": {"coordinates":[17.16667,67.09999999999999],"type":"Point"}
}