{
  "type": "Feature",
  "properties": {
    "gn:admin1_code":"9.0",
    "gn:admin2_code":"840.0",
    "gn:admin3_code":"84008.0",
    "gn:admin4_code":"866.0",
    "gn:asciiname":"Alvlosa",
    "gn:country_code":"SE",
    "gn:dem":42,
    "gn:feature_class":"P",
    "gn:feature_code":"PPL",
    "gn:name":"Alvl\u00f6sa",
    "gn:population":0,
    "gn:timezone":"Europe/Stockholm",
    "iso:country":"SE",
    "name:nor_x_preferred":[
        "Alvl\u00f6sa"
    ],
    "name:nor_x_variant":[
        "Alvl\u00f8sa"
    ],
    "name:und_x_variant":[
        "Alvl\u00f6sa"
    ],
    "wof:name":"Alvlosa",
    "wof:placetype":"locality"
},
  "geometry": {"coordinates":[16.43435,56.42103],"type":"Point"}
}