{
  "type": "Feature",
  "properties": {
    "iso:country":"SE",
    "qs_pg:aaroncc":"SE",
    "qs_pg:name":"Lacko",
    "qs_pg:name_adm0":"Sverige",
    "qs_pg:name_adm1":"V\u00e4stra G\u00f6talands L\u00e4n",
    "qs_pg:photos":375,
    "qs_pg:photos_1k":76,
    "qs_pg:photos_9k":2,
    "qs_pg:photos_9r":5,
    "qs_pg:photos_all":375,
    "qs_pg:photos_sr":6,
    "qs_pg:pop_sr":0,
    "qs_pg:qs_pg_placetype":"locality",
    "qs_pg:qs_pg_placetype_gp":"Town",
    "qs_pg:woe_adm0":23424954,
    "woe:adm0_id":23424954,
    "woe:name_adm0":"Sverige",
    "woe:name_adm1":"V\u00e4stra G\u00f6talands L\u00e4n",
    "woe:placetype":"Town",
    "wof:name":"Lacko",
    "wof:placetype":"locality"
},
  "geometry": {"coordinates":[13.218913,58.675331],"type":"Point"}
}