{
  "type": "Feature",
  "properties": {
    "gn:admin1_code":"24.0",
    "gn:admin2_code":"2283.0",
    "gn:asciiname":"Sanga",
    "gn:country_code":"SE",
    "gn:dem":27,
    "gn:feature_class":"P",
    "gn:feature_code":"PPL",
    "gn:name":"S\u00e5nga",
    "gn:population":0,
    "gn:timezone":"Europe/Stockholm",
    "iso:country":"SE",
    "name:ceb_x_preferred":[
        "Sanga"
    ],
    "name:deu_x_preferred":[
        "Sanga"
    ],
    "name:fra_x_preferred":[
        "Sanga"
    ],
    "name:ita_x_preferred":[
        "Sanga"
    ],
    "name:por_x_preferred":[
        "Sanga"
    ],
    "name:swe_x_preferred":[
        "Sanga"
    ],
    "wof:name":"Sanga",
    "wof:placetype":"locality"
},
  "geometry": {"coordinates":[17.55,63.18333000000001],"type":"Point"}
}