{
  "type": "Feature",
  "properties": {
    "gn:admin1_code":"6.0",
    "gn:admin2_code":"1383.0",
    "gn:asciiname":"Ljungstorp",
    "gn:country_code":"SE",
    "gn:dem":11,
    "gn:feature_class":"P",
    "gn:feature_code":"PPL",
    "gn:name":"Ljungstorp",
    "gn:population":0,
    "gn:timezone":"Europe/Stockholm",
    "iso:country":"SE",
    "wof:name":"Ljungstorp",
    "wof:placetype":"locality"
},
  "geometry": {"coordinates":[12.35,57.11666999999999],"type":"Point"}
}