{
  "type": "Feature",
  "properties": {
    "gn:admin1_code":"9.0",
    "gn:admin2_code":"840.0",
    "gn:admin3_code":"84008.0",
    "gn:admin4_code":"809.0",
    "gn:asciiname":"Torngard",
    "gn:country_code":"SE",
    "gn:dem":10,
    "gn:feature_class":"P",
    "gn:feature_code":"PPL",
    "gn:name":"Torng\u00e5rd",
    "gn:population":0,
    "gn:timezone":"Europe/Stockholm",
    "iso:country":"SE",
    "wof:name":"Torngard",
    "wof:placetype":"locality"
},
  "geometry": {"coordinates":[16.52479,56.33071],"type":"Point"}
}