{
  "type": "Feature",
  "properties": {
    "gn:admin1_code":"28.0",
    "gn:admin2_code":"1494.0",
    "gn:asciiname":"Alvetorp",
    "gn:country_code":"SE",
    "gn:dem":66,
    "gn:feature_class":"P",
    "gn:feature_code":"PPL",
    "gn:name":"Alvetorp",
    "gn:population":0,
    "gn:timezone":"Europe/Stockholm",
    "iso:country":"SE",
    "wof:name":"Alvetorp",
    "wof:placetype":"locality"
},
  "geometry": {"coordinates":[13.11667,58.54971999999999],"type":"Point"}
}