{
  "type": "Feature",
  "properties": {
    "gn:admin1_code":"28.0",
    "gn:admin2_code":"1439.0",
    "gn:asciiname":"Sodra Hillingsater",
    "gn:cc2":"SE",
    "gn:country_code":"SE",
    "gn:dem":106,
    "gn:feature_class":"P",
    "gn:feature_code":"PPL",
    "gn:name":"S\u00f6dra Hillings\u00e4ter",
    "gn:population":0,
    "gn:timezone":"Europe/Stockholm",
    "iso:country":"SE",
    "name:und_x_variant":[
        "Hillings\u00e4ter",
        "S\u00f6dra Hillings\u00e4ter"
    ],
    "wof:name":"Sodra Hillingsater",
    "wof:placetype":"locality"
},
  "geometry": {"coordinates":[11.93333,58.55],"type":"Point"}
}