{
  "type": "Feature",
  "properties": {
    "gn:admin1_code":"27.0",
    "gn:admin2_code":"1214.0",
    "gn:asciiname":"Norra Skravlinge",
    "gn:country_code":"SE",
    "gn:dem":32,
    "gn:feature_class":"P",
    "gn:feature_code":"PPL",
    "gn:name":"Norra Skr\u00e4vlinge",
    "gn:population":0,
    "gn:timezone":"Europe/Stockholm",
    "iso:country":"SE",
    "wof:name":"Norra Skravlinge",
    "wof:placetype":"locality"
},
  "geometry": {"coordinates":[13.08333,55.88333000000001],"type":"Point"}
}