{
  "type": "Feature",
  "properties": {
    "gn:admin1_code":"12.0",
    "gn:admin2_code":"781.0",
    "gn:asciiname":"Issjoa",
    "gn:country_code":"SE",
    "gn:dem":152,
    "gn:feature_class":"P",
    "gn:feature_code":"PPL",
    "gn:name":"Issj\u00f6\u00e5",
    "gn:population":0,
    "gn:timezone":"Europe/Stockholm",
    "iso:country":"SE",
    "name:nor_x_preferred":[
        "Issj\u00f6\u00e5"
    ],
    "name:nor_x_variant":[
        "Issj\u00f8\u00e5"
    ],
    "wof:name":"Issjoa",
    "wof:placetype":"locality"
},
  "geometry": {"coordinates":[13.81667,56.61666999999999],"type":"Point"}
}