{
  "type": "Feature",
  "properties": {
    "gn:admin1_code":"28.0",
    "gn:admin2_code":"1421.0",
    "gn:asciiname":"Trankoket",
    "gn:country_code":"SE",
    "gn:dem":3,
    "gn:feature_class":"P",
    "gn:feature_code":"PPL",
    "gn:name":"Trankoket",
    "gn:population":0,
    "gn:timezone":"Europe/Stockholm",
    "iso:country":"SE",
    "wof:name":"Trankoket",
    "wof:placetype":"locality"
},
  "geometry": {"coordinates":[11.48333,58.21666999999999],"type":"Point"}
}