{
  "type": "Feature",
  "properties": {
    "gn:admin1_code":"3.0",
    "gn:admin2_code":"2183.0",
    "gn:asciiname":"Innantjara",
    "gn:country_code":"SE",
    "gn:dem":41,
    "gn:feature_class":"P",
    "gn:feature_code":"PPL",
    "gn:name":"Innantj\u00e4ra",
    "gn:population":0,
    "gn:timezone":"Europe/Stockholm",
    "iso:country":"SE",
    "wof:name":"Innantjara",
    "wof:placetype":"locality"
},
  "geometry": {"coordinates":[16.61667000000001,61.25],"type":"Point"}
}