{
  "type": "Feature",
  "properties": {
    "gn:admin1_code":"16.0",
    "gn:admin2_code":"513.0",
    "gn:asciiname":"Orsvik",
    "gn:country_code":"SE",
    "gn:dem":146,
    "gn:feature_class":"P",
    "gn:feature_code":"PPL",
    "gn:name":"\u00d6rsvik",
    "gn:population":0,
    "gn:timezone":"Europe/Stockholm",
    "iso:country":"SE",
    "name:nor_x_preferred":[
        "\u00d6rsvik"
    ],
    "name:nor_x_variant":[
        "\u00d8rsvik"
    ],
    "name:und_x_variant":[
        "\u00d6rsvik"
    ],
    "wof:name":"Orsvik",
    "wof:placetype":"locality"
},
  "geometry": {"coordinates":[15.41667,57.98333],"type":"Point"}
}