{
  "type": "Feature",
  "properties": {
    "gn:admin1_code":"2.0",
    "gn:admin2_code":"1060.0",
    "gn:asciiname":"Bengtsboda",
    "gn:country_code":"SE",
    "gn:dem":151,
    "gn:feature_class":"P",
    "gn:feature_code":"PPL",
    "gn:name":"Bengtsboda",
    "gn:population":0,
    "gn:timezone":"Europe/Stockholm",
    "iso:country":"SE",
    "wof:name":"Bengtsboda",
    "wof:placetype":"locality"
},
  "geometry": {"coordinates":[14.58333,56.41667],"type":"Point"}
}