{
  "type": "Feature",
  "properties": {
    "gn:admin1_code":"28.0",
    "gn:admin2_code":"1490.0",
    "gn:asciiname":"AEspered",
    "gn:country_code":"SE",
    "gn:dem":290,
    "gn:feature_class":"P",
    "gn:feature_code":"PPL",
    "gn:name":"\u00c4spered",
    "gn:population":293,
    "gn:timezone":"Europe/Stockholm",
    "iso:country":"SE",
    "name:und_x_variant":[
        "\u00c4spered"
    ],
    "wof:name":"AEspered",
    "wof:placetype":"locality",
    "wof:population":293
},
  "geometry": {"coordinates":[13.181,57.75565],"type":"Point"}
}