{
  "type": "Feature",
  "properties": {
    "gn:admin1_code":"14.0",
    "gn:admin2_code":"2582.0",
    "gn:asciiname":"Forstraskhed",
    "gn:country_code":"SE",
    "gn:dem":114,
    "gn:feature_class":"P",
    "gn:feature_code":"PPL",
    "gn:name":"Forstr\u00e4skhed",
    "gn:population":0,
    "gn:timezone":"Europe/Stockholm",
    "iso:country":"SE",
    "wof:name":"Forstraskhed",
    "wof:placetype":"locality"
},
  "geometry": {"coordinates":[22.01667,66.06667],"type":"Point"}
}