{
  "type": "Feature",
  "properties": {
    "gn:admin1_code":"28.0",
    "gn:admin2_code":"1444.0",
    "gn:asciiname":"Asen",
    "gn:country_code":"SE",
    "gn:dem":50,
    "gn:feature_class":"P",
    "gn:feature_code":"PPL",
    "gn:name":"\u00c5sen",
    "gn:population":0,
    "gn:timezone":"Europe/Stockholm",
    "iso:country":"SE",
    "name:bul_x_preferred":[
        "\u0410\u0441\u0435\u043d"
    ],
    "name:ceb_x_preferred":[
        "Asen"
    ],
    "name:deu_x_preferred":[
        "Asen"
    ],
    "name:fra_x_preferred":[
        "Asen"
    ],
    "name:ita_x_preferred":[
        "Asen"
    ],
    "name:nld_x_preferred":[
        "Asen"
    ],
    "name:swe_x_preferred":[
        "Asen"
    ],
    "name:vie_x_preferred":[
        "Asen"
    ],
    "wof:name":"Asen",
    "wof:placetype":"locality"
},
  "geometry": {"coordinates":[12.66667,58.36666999999999],"type":"Point"}
}