{
  "type": "Feature",
  "properties": {
    "gn:gn_country":"SE",
    "gn:gn_fcode":"PPL",
    "gn:gn_pop":59,
    "gn:population":59,
    "iso:country":"SE",
    "name:dan_x_preferred":[
        "Jockfall"
    ],
    "name:deu_x_preferred":[
        "Jockfall"
    ],
    "name:eng_x_preferred":[
        "Jockfall"
    ],
    "name:fra_x_preferred":[
        "Jockfall"
    ],
    "name:nds_x_preferred":[
        "Jockfall"
    ],
    "name:nld_x_preferred":[
        "Jockfall"
    ],
    "name:nno_x_preferred":[
        "Jockfall"
    ],
    "name:nob_x_preferred":[
        "Jockfall"
    ],
    "name:swe_x_preferred":[
        "Jockfall"
    ],
    "name:unk_x_variant":[
        "Jock"
    ],
    "qs_pg:aaroncc":"SE",
    "qs_pg:gn_country":"SE",
    "qs_pg:gn_fcode":"PPL",
    "qs_pg:gn_pop":59,
    "qs_pg:name":"Jockfall",
    "qs_pg:photos_9r":0,
    "qs_pg:photos_sr":0,
    "qs_pg:pop_sr":1,
    "qs_pg:qs_pg_placetype":"locality",
    "wof:name":"Jockfall",
    "wof:placetype":"locality",
    "wof:population":59
},
  "geometry": {"coordinates":[22.71667,66.65000000000001],"type":"Point"}
}