{
  "type": "Feature",
  "properties": {
    "gn:admin1_code":"26.0",
    "gn:admin2_code":"188.0",
    "gn:asciiname":"Rannilen",
    "gn:country_code":"SE",
    "gn:dem":1,
    "gn:feature_class":"P",
    "gn:feature_code":"PPL",
    "gn:name":"R\u00e4nnilen",
    "gn:population":0,
    "gn:timezone":"Europe/Stockholm",
    "iso:country":"SE",
    "wof:name":"Rannilen",
    "wof:placetype":"locality"
},
  "geometry": {"coordinates":[18.55,60.11666999999999],"type":"Point"}
}