{
  "type": "Feature",
  "properties": {
    "gn:admin1_code":"21.0",
    "gn:asciiname":"Harsback",
    "gn:country_code":"SE",
    "gn:dem":60,
    "gn:feature_class":"P",
    "gn:feature_code":"PPL",
    "gn:name":"H\u00e5rsb\u00e4ck",
    "gn:population":0,
    "gn:timezone":"Europe/Stockholm",
    "iso:country":"SE",
    "name:und_x_variant":[
        "Horsb\u00e4ck",
        "H\u00e5rsb\u00e4ck"
    ],
    "wof:name":"Harsback",
    "wof:placetype":"locality"
},
  "geometry": {"coordinates":[16.91667,59.88333000000001],"type":"Point"}
}