{
  "type": "Feature",
  "properties": {
    "gn:admin1_code":"24.0",
    "gn:admin2_code":"2284.0",
    "gn:asciiname":"Osterfanbyn",
    "gn:cc2":"SE",
    "gn:country_code":"SE",
    "gn:dem":45,
    "gn:feature_class":"P",
    "gn:feature_code":"PPL",
    "gn:name":"\u00d6sterfanbyn",
    "gn:population":0,
    "gn:timezone":"Europe/Stockholm",
    "iso:country":"SE",
    "name:nor_x_preferred":[
        "\u00d6sterfanbyn"
    ],
    "name:nor_x_variant":[
        "\u00d8sterfanbyn"
    ],
    "name:und_x_variant":[
        "\u00d6sterfannbyn",
        "\u00d6sterfanbyn"
    ],
    "wof:name":"Osterfanbyn",
    "wof:placetype":"locality"
},
  "geometry": {"coordinates":[18.13333,63.45],"type":"Point"}
}