{
  "type": "Feature",
  "properties": {
    "gn:admin1_code":"28.0",
    "gn:admin2_code":"1407.0",
    "gn:asciiname":"Klavan",
    "gn:cc2":"SE",
    "gn:country_code":"SE",
    "gn:dem":5,
    "gn:feature_class":"P",
    "gn:feature_code":"PPL",
    "gn:name":"Kl\u00e5van",
    "gn:population":0,
    "gn:timezone":"Europe/Stockholm",
    "iso:country":"SE",
    "name:und_x_variant":[
        "Kl\u00e5va",
        "Kl\u00e5van"
    ],
    "wof:name":"Klavan",
    "wof:placetype":"locality"
},
  "geometry": {"coordinates":[11.64667,57.68306],"type":"Point"}
}