{
  "type": "Feature",
  "properties": {
    "gn:admin1_code":"12.0",
    "gn:admin2_code":"781.0",
    "gn:asciiname":"Bjarseryd",
    "gn:country_code":"SE",
    "gn:dem":169,
    "gn:feature_class":"P",
    "gn:feature_code":"PPL",
    "gn:name":"Bj\u00e4rseryd",
    "gn:population":0,
    "gn:timezone":"Europe/Stockholm",
    "iso:country":"SE",
    "wof:name":"Bjarseryd",
    "wof:placetype":"locality"
},
  "geometry": {"coordinates":[13.46667,56.73333],"type":"Point"}
}