{
  "type": "Feature",
  "properties": {
    "gn:admin1_code":"27.0",
    "gn:admin2_code":"1293.0",
    "gn:asciiname":"Grasabygget",
    "gn:country_code":"SE",
    "gn:dem":131,
    "gn:feature_class":"P",
    "gn:feature_code":"PPL",
    "gn:name":"Gr\u00e4sabygget",
    "gn:population":0,
    "gn:timezone":"Europe/Stockholm",
    "iso:country":"SE",
    "wof:name":"Grasabygget",
    "wof:placetype":"locality"
},
  "geometry": {"coordinates":[13.61667,56.18333000000001],"type":"Point"}
}