{
  "type": "Feature",
  "properties": {
    "gn:admin1_code":"9.0",
    "gn:admin2_code":"885.0",
    "gn:asciiname":"Kallahamn",
    "gn:country_code":"SE",
    "gn:dem":7,
    "gn:feature_class":"P",
    "gn:feature_code":"PPL",
    "gn:name":"K\u00e4llahamn",
    "gn:population":0,
    "gn:timezone":"Europe/Stockholm",
    "iso:country":"SE",
    "wof:name":"Kallahamn",
    "wof:placetype":"locality"
},
  "geometry": {"coordinates":[16.98333,57.11666999999999],"type":"Point"}
}