{
  "type": "Feature",
  "properties": {
    "gn:admin1_code":"27.0",
    "gn:admin2_code":"1292.0",
    "gn:asciiname":"Toarp",
    "gn:country_code":"SE",
    "gn:dem":55,
    "gn:feature_class":"P",
    "gn:feature_code":"PPL",
    "gn:name":"Toarp",
    "gn:population":0,
    "gn:timezone":"Europe/Stockholm",
    "iso:country":"SE",
    "wof:name":"Toarp",
    "wof:placetype":"locality"
},
  "geometry": {"coordinates":[12.95,56.28333000000001],"type":"Point"}
}