{
  "type": "Feature",
  "properties": {
    "gn:admin1_code":"24.0",
    "gn:admin2_code":"2280.0",
    "gn:admin3_code":"228001.0",
    "gn:admin4_code":"2470.0",
    "gn:asciiname":"Vangsta",
    "gn:country_code":"SE",
    "gn:dem":64,
    "gn:feature_class":"P",
    "gn:feature_code":"PPL",
    "gn:name":"Vangsta",
    "gn:population":0,
    "gn:timezone":"Europe/Stockholm",
    "iso:country":"SE",
    "wof:name":"Vangsta",
    "wof:placetype":"locality"
},
  "geometry": {"coordinates":[17.98333,62.61666999999999],"type":"Point"}
}