{
  "type": "Feature",
  "properties": {
    "iso:country":"SE",
    "name:dan_x_preferred":[
        "Finkarby"
    ],
    "name:deu_x_preferred":[
        "Finkarby"
    ],
    "name:eng_x_preferred":[
        "Finkarby"
    ],
    "name:fra_x_preferred":[
        "Finkarby"
    ],
    "name:nan_x_preferred":[
        "Finkarby"
    ],
    "name:nds_x_preferred":[
        "Finkarby"
    ],
    "name:nld_x_preferred":[
        "Finkarby"
    ],
    "name:nno_x_preferred":[
        "Finkarby"
    ],
    "name:nob_x_preferred":[
        "Finkarby"
    ],
    "name:pol_x_preferred":[
        "Finkarby"
    ],
    "name:swe_x_preferred":[
        "Finkarby"
    ],
    "qs_pg:aaroncc":"SE",
    "qs_pg:name":"Finkarby",
    "qs_pg:name_adm0":"Sverige",
    "qs_pg:name_adm1":"Stockholms L\u00e4n",
    "qs_pg:photos":164,
    "qs_pg:photos_1k":33,
    "qs_pg:photos_9k":1,
    "qs_pg:photos_9r":4,
    "qs_pg:photos_all":164,
    "qs_pg:photos_sr":4,
    "qs_pg:pop_sr":0,
    "qs_pg:qs_pg_placetype":"locality",
    "qs_pg:qs_pg_placetype_gp":"Town",
    "qs_pg:woe_adm0":23424954,
    "woe:adm0_id":23424954,
    "woe:name_adm0":"Sverige",
    "woe:name_adm1":"Stockholms L\u00e4n",
    "woe:placetype":"Town",
    "wof:name":"Finkarby",
    "wof:placetype":"locality"
},
  "geometry": {"coordinates":[17.274842,59.203338],"type":"Point"}
}