{
  "type": "Feature",
  "properties": {
    "gn:admin1_code":"10.0",
    "gn:admin2_code":"2081.0",
    "gn:admin3_code":"208102.0",
    "gn:admin4_code":"2378.0",
    "gn:asciiname":"Storsten",
    "gn:country_code":"SE",
    "gn:dem":102,
    "gn:feature_class":"P",
    "gn:feature_code":"PPL",
    "gn:name":"Storsten",
    "gn:population":0,
    "gn:timezone":"Europe/Stockholm",
    "iso:country":"SE",
    "wof:name":"Storsten",
    "wof:placetype":"locality"
},
  "geometry": {"coordinates":[15.54317,60.48535],"type":"Point"}
}