{
  "type": "Feature",
  "properties": {
    "gn:admin1_code":"10.0",
    "gn:admin2_code":"2084.0",
    "gn:asciiname":"Leknas",
    "gn:country_code":"SE",
    "gn:dem":34,
    "gn:feature_class":"P",
    "gn:feature_code":"PPL",
    "gn:name":"Lekn\u00e4s",
    "gn:population":0,
    "gn:timezone":"Europe/Stockholm",
    "iso:country":"SE",
    "wof:name":"Leknas",
    "wof:placetype":"locality"
},
  "geometry": {"coordinates":[16.58333,60.18333000000001],"type":"Point"}
}