{
  "type": "Feature",
  "properties": {
    "gn:admin1_code":"15.0",
    "gn:admin2_code":"1882.0",
    "gn:asciiname":"Bastedalen",
    "gn:country_code":"SE",
    "gn:dem":97,
    "gn:feature_class":"P",
    "gn:feature_code":"PPL",
    "gn:name":"Bastedalen",
    "gn:population":0,
    "gn:timezone":"Europe/Stockholm",
    "iso:country":"SE",
    "wof:name":"Bastedalen",
    "wof:placetype":"locality"
},
  "geometry": {"coordinates":[14.93333,58.78333000000001],"type":"Point"}
}