{
  "type": "Feature",
  "properties": {
    "gn:admin1_code":"12.0",
    "gn:admin2_code":"760.0",
    "gn:asciiname":"Rismala",
    "gn:country_code":"SE",
    "gn:dem":247,
    "gn:feature_class":"P",
    "gn:feature_code":"PPL",
    "gn:name":"Rism\u00e5la",
    "gn:population":0,
    "gn:timezone":"Europe/Stockholm",
    "iso:country":"SE",
    "wof:name":"Rismala",
    "wof:placetype":"locality"
},
  "geometry": {"coordinates":[15.43333,57.08333],"type":"Point"}
}