{
  "type": "Feature",
  "properties": {
    "gn:admin1_code":"12.0",
    "gn:admin2_code":"767.0",
    "gn:asciiname":"Ravaryd",
    "gn:country_code":"SE",
    "gn:dem":121,
    "gn:feature_class":"P",
    "gn:feature_code":"PPL",
    "gn:name":"R\u00e4varyd",
    "gn:population":0,
    "gn:timezone":"Europe/Stockholm",
    "iso:country":"SE",
    "wof:name":"Ravaryd",
    "wof:placetype":"locality"
},
  "geometry": {"coordinates":[13.48333,56.53333000000001],"type":"Point"}
}