{
  "type": "Feature",
  "properties": {
    "iso:country":"SE",
    "name:swe_x_preferred":[
        "Bj\u00f6rlanda"
    ],
    "wof:name":"Bjorlanda",
    "wof:placetype":"neighbourhood"
},
  "geometry": {"coordinates":[11.82212669918389,57.76146208788671],"type":"Point"}
}