{
  "type": "Feature",
  "properties": {
    "gn:admin1_code":"26.0",
    "gn:admin2_code":"191.0",
    "gn:asciiname":"Torsborg",
    "gn:country_code":"SE",
    "gn:dem":52,
    "gn:feature_class":"P",
    "gn:feature_code":"PPL",
    "gn:name":"Torsborg",
    "gn:population":0,
    "gn:timezone":"Europe/Stockholm",
    "iso:country":"SE",
    "wof:name":"Torsborg",
    "wof:placetype":"locality"
},
  "geometry": {"coordinates":[17.64972000000001,59.68306],"type":"Point"}
}