{
  "type": "Feature",
  "properties": {
    "iso:country":"SE",
    "name:eng_x_preferred":[
        "Trolleholm"
    ],
    "name:nld_x_preferred":[
        "Trolleholm"
    ],
    "name:swe_x_preferred":[
        "Trolleholm"
    ],
    "qs_pg:aaroncc":"SE",
    "qs_pg:name":"Trolleholm",
    "qs_pg:name_adm0":"Sverige",
    "qs_pg:name_adm1":"Sk\u00e5ne L\u00e4n",
    "qs_pg:photos":98,
    "qs_pg:photos_1k":20,
    "qs_pg:photos_9k":1,
    "qs_pg:photos_9r":3,
    "qs_pg:photos_all":98,
    "qs_pg:photos_sr":3,
    "qs_pg:pop_sr":0,
    "qs_pg:qs_pg_placetype":"locality",
    "qs_pg:qs_pg_placetype_gp":"Town",
    "qs_pg:woe_adm0":23424954,
    "woe:adm0_id":23424954,
    "woe:name_adm0":"Sverige",
    "woe:name_adm1":"Sk\u00e5ne L\u00e4n",
    "woe:placetype":"Town",
    "wof:name":"Trolleholm",
    "wof:placetype":"locality"
},
  "geometry": {"coordinates":[13.25715,55.908135],"type":"Point"}
}