{
  "type": "Feature",
  "properties": {
    "gn:admin1_code":"27.0",
    "gn:admin2_code":"1287.0",
    "gn:admin3_code":"128721.0",
    "gn:admin4_code":"1294.0",
    "gn:asciiname":"Boste",
    "gn:country_code":"SE",
    "gn:dem":3,
    "gn:feature_class":"P",
    "gn:feature_code":"PPL",
    "gn:name":"B\u00f6ste",
    "gn:population":0,
    "gn:timezone":"Europe/Stockholm",
    "iso:country":"SE",
    "name:nor_x_preferred":[
        "B\u00f6ste"
    ],
    "name:nor_x_variant":[
        "B\u00f8ste"
    ],
    "wof:name":"Boste",
    "wof:placetype":"locality"
},
  "geometry": {"coordinates":[13.31491,55.34364],"type":"Point"}
}