{
  "type": "Feature",
  "properties": {
    "gn:admin1_code":"27.0",
    "gn:admin2_code":"1275.0",
    "gn:asciiname":"Honsholma",
    "gn:country_code":"SE",
    "gn:dem":115,
    "gn:feature_class":"P",
    "gn:feature_code":"PPL",
    "gn:name":"H\u00f6nsholma",
    "gn:population":0,
    "gn:timezone":"Europe/Stockholm",
    "iso:country":"SE",
    "name:nor_x_preferred":[
        "H\u00f6nsholma"
    ],
    "name:nor_x_variant":[
        "H\u00f8nsholma"
    ],
    "name:und_x_variant":[
        "H\u00f6nsholma"
    ],
    "wof:name":"Honsholma",
    "wof:placetype":"locality"
},
  "geometry": {"coordinates":[13.43333,56.15],"type":"Point"}
}