{
  "type": "Feature",
  "properties": {
    "gn:admin1_code":"7.0",
    "gn:admin2_code":"2313.0",
    "gn:asciiname":"Gussvattnet",
    "gn:country_code":"SE",
    "gn:dem":377,
    "gn:feature_class":"P",
    "gn:feature_code":"PPL",
    "gn:name":"Gussvattnet",
    "gn:population":0,
    "gn:timezone":"Europe/Stockholm",
    "iso:country":"SE",
    "wof:name":"Gussvattnet",
    "wof:placetype":"locality"
},
  "geometry": {"coordinates":[14.25,64.46666999999999],"type":"Point"}
}