{
  "type": "Feature",
  "properties": {
    "gn:gn_country":"SE",
    "gn:gn_fcode":"PPL",
    "gn:gn_pop":271,
    "gn:population":265,
    "iso:country":"SE",
    "name:eng_x_preferred":[
        "Rockhammar"
    ],
    "name:nan_x_preferred":[
        "Rockhammar"
    ],
    "name:nld_x_preferred":[
        "Rockhammar"
    ],
    "name:nno_x_preferred":[
        "Rockhammar"
    ],
    "name:nob_x_preferred":[
        "Rockhammar"
    ],
    "name:swe_x_preferred":[
        "Rockhammar"
    ],
    "qs_pg:aaroncc":"SE",
    "qs_pg:gn_country":"SE",
    "qs_pg:gn_fcode":"PPL",
    "qs_pg:gn_pop":271,
    "qs_pg:name":"Rockhammar",
    "qs_pg:name_adm0":"Sverige",
    "qs_pg:name_adm1":"\u00d6rebro L\u00e4n",
    "qs_pg:photos_9k":1,
    "qs_pg:photos_9r":1,
    "qs_pg:photos_all":4,
    "qs_pg:photos_sr":0,
    "qs_pg:pop_sr":2,
    "qs_pg:qs_pg_placetype":"locality",
    "qs_pg:qs_pg_placetype_gp":"Town",
    "qs_pg:woe_adm0":23424954,
    "woe:adm0_id":23424954,
    "woe:name_adm0":"Sverige",
    "woe:name_adm1":"\u00d6rebro L\u00e4n",
    "woe:placetype":"Town",
    "wof:name":"Rockhammar",
    "wof:placetype":"locality",
    "wof:population":265
},
  "geometry": {"coordinates":[15.43333,59.53333],"type":"Point"}
}