{
  "type": "Feature",
  "properties": {
    "gn:admin1_code":"23.0",
    "gn:admin2_code":"2482.0",
    "gn:asciiname":"Ostra Falmark",
    "gn:country_code":"SE",
    "gn:dem":49,
    "gn:feature_class":"P",
    "gn:feature_code":"PPL",
    "gn:name":"\u00d6stra Falmark",
    "gn:population":0,
    "gn:timezone":"Europe/Stockholm",
    "iso:country":"SE",
    "name:nor_x_preferred":[
        "\u00d6stra Falmark"
    ],
    "name:nor_x_variant":[
        "\u00d8stra Falmark"
    ],
    "name:und_x_variant":[
        "\u00d6stra Falmark"
    ],
    "wof:name":"Ostra Falmark",
    "wof:placetype":"locality"
},
  "geometry": {"coordinates":[21.01667,64.63333],"type":"Point"}
}