{
  "type": "Feature",
  "properties": {
    "gn:admin1_code":"9.0",
    "gn:admin2_code":"840.0",
    "gn:admin3_code":"84008.0",
    "gn:admin4_code":"878.0",
    "gn:asciiname":"Lindby",
    "gn:country_code":"SE",
    "gn:dem":9,
    "gn:feature_class":"P",
    "gn:feature_code":"PPL",
    "gn:name":"Lindby",
    "gn:population":0,
    "gn:timezone":"Europe/Stockholm",
    "iso:country":"SE",
    "wof:name":"Lindby",
    "wof:placetype":"locality"
},
  "geometry": {"coordinates":[16.46078,56.27963],"type":"Point"}
}