{
  "type": "Feature",
  "properties": {
    "gn:admin1_code":"28.0",
    "gn:admin2_code":"1421.0",
    "gn:asciiname":"Haga",
    "gn:country_code":"SE",
    "gn:dem":17,
    "gn:feature_class":"P",
    "gn:feature_code":"PPL",
    "gn:name":"Haga",
    "gn:population":0,
    "gn:timezone":"Europe/Stockholm",
    "iso:country":"SE",
    "name:ceb_x_preferred":[
        "Haga"
    ],
    "name:dan_x_preferred":[
        "Haga"
    ],
    "name:deu_x_preferred":[
        "Haga"
    ],
    "name:fin_x_preferred":[
        "Haga"
    ],
    "name:fra_x_preferred":[
        "Haga"
    ],
    "name:nld_x_preferred":[
        "Haga"
    ],
    "name:nno_x_preferred":[
        "Haga"
    ],
    "name:nor_x_preferred":[
        "Haga"
    ],
    "name:por_x_preferred":[
        "Haga"
    ],
    "name:ron_x_preferred":[
        "Haga"
    ],
    "name:rus_x_preferred":[
        "\u0425\u0430\u0433\u0430"
    ],
    "name:swe_x_preferred":[
        "Haga"
    ],
    "wof:name":"Haga",
    "wof:placetype":"locality"
},
  "geometry": {"coordinates":[11.61667,58.1375],"type":"Point"}
}