{
  "type": "Feature",
  "properties": {
    "gn:admin1_code":"28.0",
    "gn:admin2_code":"1463.0",
    "gn:asciiname":"Obranstorp",
    "gn:cc2":"SE",
    "gn:country_code":"SE",
    "gn:dem":213,
    "gn:feature_class":"P",
    "gn:feature_code":"PPL",
    "gn:name":"\u00d6branstorp",
    "gn:population":0,
    "gn:timezone":"Europe/Stockholm",
    "iso:country":"SE",
    "name:nor_x_preferred":[
        "\u00d6branstorp"
    ],
    "name:nor_x_variant":[
        "\u00d8branstorp"
    ],
    "name:und_x_variant":[
        "\u00d6brandstorp"
    ],
    "wof:name":"Obranstorp",
    "wof:placetype":"locality"
},
  "geometry": {"coordinates":[12.86667,57.35],"type":"Point"}
}