{
  "type": "Feature",
  "properties": {
    "gn:admin1_code":"7.0",
    "gn:admin2_code":"2380.0",
    "gn:asciiname":"Nordero",
    "gn:country_code":"SE",
    "gn:dem":294,
    "gn:feature_class":"P",
    "gn:feature_code":"PPL",
    "gn:name":"Norder\u00f6",
    "gn:population":0,
    "gn:timezone":"Europe/Stockholm",
    "iso:country":"SE",
    "name:nor_x_preferred":[
        "Norder\u00f6"
    ],
    "name:nor_x_variant":[
        "Norder\u00f8"
    ],
    "wof:name":"Nordero",
    "wof:placetype":"locality"
},
  "geometry": {"coordinates":[14.36667,63.13333000000001],"type":"Point"}
}