{
  "type": "Feature",
  "properties": {
    "gn:admin1_code":"3.0",
    "gn:admin2_code":"2161.0",
    "gn:asciiname":"Lorang",
    "gn:country_code":"SE",
    "gn:dem":103,
    "gn:feature_class":"P",
    "gn:feature_code":"PPL",
    "gn:name":"L\u00f6r\u00e4ng",
    "gn:population":0,
    "gn:timezone":"Europe/Stockholm",
    "iso:country":"SE",
    "name:deu_x_preferred":[
        "Lorang"
    ],
    "name:ltz_x_preferred":[
        "Lorang"
    ],
    "wof:name":"Lorang",
    "wof:placetype":"locality"
},
  "geometry": {"coordinates":[16.15,61.66667],"type":"Point"}
}