{
  "type": "Feature",
  "properties": {
    "gn:admin1_code":"10.0",
    "gn:admin2_code":"2026.0",
    "gn:asciiname":"Bomsarvet",
    "gn:cc2":"SE",
    "gn:country_code":"SE",
    "gn:dem":201,
    "gn:feature_class":"P",
    "gn:feature_code":"PPL",
    "gn:name":"Bomsarvet",
    "gn:population":0,
    "gn:timezone":"Europe/Stockholm",
    "iso:country":"SE",
    "name:und_x_variant":[
        "Bomsarfvet",
        "Bomsarvet"
    ],
    "wof:name":"Bomsarvet",
    "wof:placetype":"locality"
},
  "geometry": {"coordinates":[15.08333,60.55],"type":"Point"}
}