{
  "type": "Feature",
  "properties": {
    "gn:gn_country":"SE",
    "gn:gn_fcode":"PPLL",
    "gn:gn_pop":77,
    "gn:population":77,
    "iso:country":"SE",
    "name:eng_x_preferred":[
        "Brink"
    ],
    "name:nld_x_preferred":[
        "Brink"
    ],
    "name:swe_x_preferred":[
        "K\u00e4rrhagen och Byrsta kvarn"
    ],
    "qs_pg:aaroncc":"SE",
    "qs_pg:gn_country":"SE",
    "qs_pg:gn_fcode":"PPLL",
    "qs_pg:gn_pop":77,
    "qs_pg:name":"Brink",
    "qs_pg:name_adm0":"Sverige",
    "qs_pg:name_adm1":"Stockholms L\u00e4n",
    "qs_pg:photos":49,
    "qs_pg:photos_1k":10,
    "qs_pg:photos_9k":1,
    "qs_pg:photos_9r":2,
    "qs_pg:photos_all":49,
    "qs_pg:photos_sr":2,
    "qs_pg:pop_sr":1,
    "qs_pg:qs_pg_placetype":"locality",
    "qs_pg:qs_pg_placetype_gp":"Town",
    "qs_pg:woe_adm0":23424954,
    "woe:adm0_id":23424954,
    "woe:name_adm0":"Sverige",
    "woe:name_adm1":"Stockholms L\u00e4n",
    "woe:placetype":"Town",
    "wof:name":"Brink",
    "wof:placetype":"locality",
    "wof:population":77
},
  "geometry": {"coordinates":[17.8055,59.1069],"type":"Point"}
}