{
  "type": "Feature",
  "properties": {
    "gn:admin1_code":"28.0",
    "gn:asciiname":"Asared",
    "gn:country_code":"SE",
    "gn:dem":209,
    "gn:feature_class":"P",
    "gn:feature_code":"PPL",
    "gn:name":"\u00c5sared",
    "gn:population":0,
    "gn:timezone":"Europe/Stockholm",
    "iso:country":"SE",
    "wof:name":"Asared",
    "wof:placetype":"locality"
},
  "geometry": {"coordinates":[14.03333,57.88333000000001],"type":"Point"}
}