{
  "type": "Feature",
  "properties": {
    "gn:admin1_code":"7.0",
    "gn:admin2_code":"2313.0",
    "gn:asciiname":"Hossjoberget",
    "gn:cc2":"SE",
    "gn:country_code":"SE",
    "gn:dem":276,
    "gn:feature_class":"P",
    "gn:feature_code":"PPL",
    "gn:name":"H\u00f6ssj\u00f6berget",
    "gn:population":0,
    "gn:timezone":"Europe/Stockholm",
    "iso:country":"SE",
    "name:nor_x_preferred":[
        "H\u00f6ssj\u00f6berget"
    ],
    "name:nor_x_variant":[
        "H\u00f8ssj\u00f8berget"
    ],
    "name:und_x_variant":[
        "H\u00f6ssj\u00f6n",
        "H\u00f6sj\u00f6berg",
        "H\u00f6ssj\u00f6berget"
    ],
    "wof:name":"Hossjoberget",
    "wof:placetype":"locality"
},
  "geometry": {"coordinates":[15.86667,63.86666999999999],"type":"Point"}
}