{
  "type": "Feature",
  "properties": {
    "gn:admin1_code":"22.0",
    "gn:admin2_code":"1715.0",
    "gn:asciiname":"Nedre Bondestad",
    "gn:cc2":"SE",
    "gn:country_code":"SE",
    "gn:dem":106,
    "gn:feature_class":"P",
    "gn:feature_code":"PPL",
    "gn:name":"Nedre Bondestad",
    "gn:population":0,
    "gn:timezone":"Europe/Stockholm",
    "iso:country":"SE",
    "name:und_x_variant":[
        "Bondestad",
        "Nedre Bondestad"
    ],
    "wof:name":"Nedre Bondestad",
    "wof:placetype":"locality"
},
  "geometry": {"coordinates":[13.28333,59.58333],"type":"Point"}
}