{
  "type": "Feature",
  "properties": {
    "gn:admin1_code":"3.0",
    "gn:admin2_code":"2121.0",
    "gn:asciiname":"Finnstuga",
    "gn:country_code":"SE",
    "gn:dem":229,
    "gn:feature_class":"P",
    "gn:feature_code":"PPL",
    "gn:name":"Finnstuga",
    "gn:population":0,
    "gn:timezone":"Europe/Stockholm",
    "iso:country":"SE",
    "wof:name":"Finnstuga",
    "wof:placetype":"locality"
},
  "geometry": {"coordinates":[15.53333,61.33333],"type":"Point"}
}