{
  "type": "Feature",
  "properties": {
    "gn:admin1_code":"8.0",
    "gn:admin2_code":"680.0",
    "gn:asciiname":"Savdabo",
    "gn:country_code":"SE",
    "gn:dem":281,
    "gn:feature_class":"P",
    "gn:feature_code":"PPL",
    "gn:name":"S\u00e4vdabo",
    "gn:population":0,
    "gn:timezone":"Europe/Stockholm",
    "iso:country":"SE",
    "wof:name":"Savdabo",
    "wof:placetype":"locality"
},
  "geometry": {"coordinates":[13.96667,57.66667],"type":"Point"}
}