{
  "type": "Feature",
  "properties": {
    "gn:admin1_code":"26.0",
    "gn:admin2_code":"188.0",
    "gn:asciiname":"Goringe",
    "gn:country_code":"SE",
    "gn:dem":17,
    "gn:feature_class":"P",
    "gn:feature_code":"PPL",
    "gn:name":"G\u00f6ringe",
    "gn:population":0,
    "gn:timezone":"Europe/Stockholm",
    "iso:country":"SE",
    "name:nor_x_preferred":[
        "G\u00f6ringe"
    ],
    "name:nor_x_variant":[
        "G\u00f8ringe"
    ],
    "wof:name":"Goringe",
    "wof:placetype":"locality"
},
  "geometry": {"coordinates":[18.68333,60.05],"type":"Point"}
}