{
  "type": "Feature",
  "properties": {
    "gn:country":"SE",
    "gn:fcode":"PPL",
    "gn:population":0,
    "iso:country":"SE",
    "name:bul_x_preferred":[
        "\u041a\u0430\u0442\u0445\u0430\u043c\u0430\u0440\u0441\u0432\u0438\u043a"
    ],
    "name:ceb_x_preferred":[
        "Katthammarsvik"
    ],
    "name:dan_x_preferred":[
        "Katthammarsvik"
    ],
    "name:deu_x_preferred":[
        "Katthammarsvik"
    ],
    "name:eng_x_preferred":[
        "Katthammarsvik"
    ],
    "name:fas_x_preferred":[
        "\u06a9\u0627\u062a\u0627\u0645\u0627\u0631\u0634\u0648\u06cc\u06a9"
    ],
    "name:gle_x_preferred":[
        "Katthammarsvik"
    ],
    "name:lld_x_preferred":[
        "Katthammarsvik"
    ],
    "name:nld_x_preferred":[
        "Katthammarsvik"
    ],
    "name:swe_x_preferred":[
        "Katthammarsvik"
    ],
    "qs_pg:aaroncc":"SE",
    "qs_pg:gn_country":"SE",
    "qs_pg:gn_fcode":"PPL",
    "qs_pg:gn_pop":0,
    "qs_pg:name":"Katthammarsvik",
    "qs_pg:name_adm0":"Sverige",
    "qs_pg:name_adm1":"Gotlands L\u00e4n",
    "qs_pg:photos":386,
    "qs_pg:photos_1k":78,
    "qs_pg:photos_9k":2,
    "qs_pg:photos_9r":5,
    "qs_pg:photos_all":386,
    "qs_pg:photos_sr":6,
    "qs_pg:pop_sr":0,
    "qs_pg:qs_pg_placetype":"locality",
    "qs_pg:qs_pg_placetype_gp":"Town",
    "qs_pg:woe_adm0":23424954,
    "woe:adm0_id":23424954,
    "woe:name_adm0":"Sverige",
    "woe:name_adm1":"Gotlands L\u00e4n",
    "woe:placetype":"Town",
    "wof:name":"Katthammarsvik",
    "wof:placetype":"locality"
},
  "geometry": {"coordinates":[18.83333,57.43333],"type":"Point"}
}