{
  "type": "Feature",
  "properties": {
    "gn:admin1_code":"15.0",
    "gn:admin2_code":"1884.0",
    "gn:asciiname":"Hammarby",
    "gn:country_code":"SE",
    "gn:dem":89,
    "gn:feature_class":"P",
    "gn:feature_code":"PPL",
    "gn:name":"Hammarby",
    "gn:population":0,
    "gn:timezone":"Europe/Stockholm",
    "iso:country":"SE",
    "name:ceb_x_preferred":[
        "Hammarby"
    ],
    "name:deu_x_preferred":[
        "Hammarby"
    ],
    "name:fin_x_preferred":[
        "Hammarby"
    ],
    "name:nld_x_preferred":[
        "Hammarby"
    ],
    "name:swe_x_preferred":[
        "Hammarby"
    ],
    "wof:name":"Hammarby",
    "wof:placetype":"locality"
},
  "geometry": {"coordinates":[15.11667,59.53333000000001],"type":"Point"}
}