{
  "type": "Feature",
  "properties": {
    "gn:admin1_code":"24.0",
    "gn:admin2_code":"2281.0",
    "gn:admin3_code":"228109.0",
    "gn:admin4_code":"2451.0",
    "gn:asciiname":"Malstabodarna",
    "gn:country_code":"SE",
    "gn:dem":160,
    "gn:feature_class":"P",
    "gn:feature_code":"PPL",
    "gn:name":"Malstabodarna",
    "gn:population":0,
    "gn:timezone":"Europe/Stockholm",
    "iso:country":"SE",
    "wof:name":"Malstabodarna",
    "wof:placetype":"locality"
},
  "geometry": {"coordinates":[16.98795,62.24176],"type":"Point"}
}