{
  "type": "Feature",
  "properties": {
    "gn:admin1_code":"24.0",
    "gn:admin2_code":"2262.0",
    "gn:admin3_code":"226202.0",
    "gn:admin4_code":"2477.0",
    "gn:asciiname":"Lagfors",
    "gn:country_code":"SE",
    "gn:dem":133,
    "gn:feature_class":"P",
    "gn:feature_code":"PPL",
    "gn:name":"Lagfors",
    "gn:population":0,
    "gn:timezone":"Europe/Stockholm",
    "iso:country":"SE",
    "wof:name":"Lagfors",
    "wof:placetype":"locality"
},
  "geometry": {"coordinates":[17.19738,62.66116],"type":"Point"}
}