{
  "type": "Feature",
  "properties": {
    "gn:gn_country":"SE",
    "gn:gn_fcode":"PPL",
    "gn:gn_pop":609,
    "gn:population":609,
    "iso:country":"SE",
    "name:bul_x_preferred":[
        "\u0422\u0438\u043c\u0441\u0444\u043e\u0440\u0441"
    ],
    "name:dan_x_preferred":[
        "Timsfors"
    ],
    "name:dut_x_preferred":[
        "Timsfors"
    ],
    "name:eng_x_preferred":[
        "Timsfors"
    ],
    "name:fre_x_preferred":[
        "Timsfors"
    ],
    "name:ger_x_preferred":[
        "Timsfors"
    ],
    "name:ita_x_preferred":[
        "Timsfors"
    ],
    "name:nan_x_preferred":[
        "Timsfors"
    ],
    "name:nds_x_preferred":[
        "Timsfors"
    ],
    "name:nno_x_preferred":[
        "Timsfors"
    ],
    "name:nob_x_preferred":[
        "Timsfors"
    ],
    "name:sme_x_preferred":[
        "Timsfors"
    ],
    "name:swe_x_preferred":[
        "Timsfors"
    ],
    "qs_pg:aaroncc":"SE",
    "qs_pg:gn_country":"SE",
    "qs_pg:gn_fcode":"PPL",
    "qs_pg:gn_pop":609,
    "qs_pg:name":"Timsfors",
    "qs_pg:name_adm0":"Sverige",
    "qs_pg:name_adm1":"Kronobergs L\u00e4n",
    "qs_pg:photos_9k":1,
    "qs_pg:photos_9r":1,
    "qs_pg:photos_all":1,
    "qs_pg:photos_sr":0,
    "qs_pg:pop_sr":2,
    "qs_pg:qs_pg_placetype":"locality",
    "qs_pg:qs_pg_placetype_gp":"Town",
    "qs_pg:woe_adm0":23424954,
    "woe:adm0_id":23424954,
    "woe:name_adm0":"Sverige",
    "woe:name_adm1":"Kronobergs L\u00e4n",
    "woe:placetype":"Town",
    "wof:name":"Timsfors",
    "wof:placetype":"locality",
    "wof:population":609
},
  "geometry": {"coordinates":[13.58333,56.48333],"type":"Point"}
}