{
  "type": "Feature",
  "properties": {
    "gn:admin1_code":"18.0",
    "gn:admin2_code":"484.0",
    "gn:asciiname":"Hjalmsater",
    "gn:country_code":"SE",
    "gn:dem":45,
    "gn:feature_class":"P",
    "gn:feature_code":"PPL",
    "gn:name":"Hj\u00e4lms\u00e4ter",
    "gn:population":0,
    "gn:timezone":"Europe/Stockholm",
    "iso:country":"SE",
    "wof:name":"Hjalmsater",
    "wof:placetype":"locality"
},
  "geometry": {"coordinates":[15.91667,59.31667],"type":"Point"}
}