{
  "type": "Feature",
  "properties": {
    "gn:country":"SE",
    "gn:fcode":"PPL",
    "gn:population":0,
    "iso:country":"SE",
    "name:dan_x_preferred":[
        "K\u00e5tilla"
    ],
    "name:deu_x_preferred":[
        "K\u00e5tilla"
    ],
    "name:eng_x_preferred":[
        "K\u00e5tilla"
    ],
    "name:fra_x_preferred":[
        "K\u00e5tilla"
    ],
    "name:gle_x_preferred":[
        "K\u00e5tilla"
    ],
    "name:lld_x_preferred":[
        "K\u00e5tilla"
    ],
    "name:nds_x_preferred":[
        "K\u00e5tilla"
    ],
    "name:nld_x_preferred":[
        "K\u00e5tilla"
    ],
    "name:nno_x_preferred":[
        "K\u00e5tilla"
    ],
    "name:nob_x_preferred":[
        "K\u00e5tilla"
    ],
    "name:swe_x_preferred":[
        "K\u00e5tilla"
    ],
    "qs_pg:aaroncc":"SE",
    "qs_pg:gn_country":"SE",
    "qs_pg:gn_fcode":"PPL",
    "qs_pg:gn_pop":0,
    "qs_pg:name":"K\u00e5tila",
    "qs_pg:name_adm0":"Sverige",
    "qs_pg:name_adm1":"Dalarnas L\u00e4n",
    "qs_pg:photos":5,
    "qs_pg:photos_1k":1,
    "qs_pg:photos_9k":1,
    "qs_pg:photos_9r":1,
    "qs_pg:photos_all":5,
    "qs_pg:photos_sr":1,
    "qs_pg:pop_sr":0,
    "qs_pg:qs_pg_placetype":"locality",
    "qs_pg:qs_pg_placetype_gp":"Town",
    "qs_pg:woe_adm0":23424954,
    "woe:adm0_id":23424954,
    "woe:name_adm0":"Sverige",
    "woe:name_adm1":"Dalarnas L\u00e4n",
    "woe:placetype":"Town",
    "wof:name":"K\u00e5tila",
    "wof:placetype":"locality"
},
  "geometry": {"coordinates":[14.01667,61.21667],"type":"Point"}
}