{
  "type": "Feature",
  "properties": {
    "gn:admin1_code":"2.0",
    "gn:admin2_code":"1082.0",
    "gn:asciiname":"Allestad",
    "gn:country_code":"SE",
    "gn:dem":5,
    "gn:feature_class":"P",
    "gn:feature_code":"PPL",
    "gn:name":"\u00c4llestad",
    "gn:population":0,
    "gn:timezone":"Europe/Stockholm",
    "iso:country":"SE",
    "wof:name":"Allestad",
    "wof:placetype":"locality"
},
  "geometry": {"coordinates":[14.91667,56.16667],"type":"Point"}
}