{
  "type": "Feature",
  "properties": {
    "gn:admin1_code":"26.0",
    "gn:asciiname":"Tjocko",
    "gn:country_code":"SE",
    "gn:dem":12,
    "gn:feature_class":"P",
    "gn:feature_code":"PPL",
    "gn:name":"Tjock\u00f6",
    "gn:population":0,
    "gn:timezone":"Europe/Stockholm",
    "iso:country":"SE",
    "name:nor_x_preferred":[
        "Tjock\u00f6"
    ],
    "name:nor_x_variant":[
        "Tjock\u00f8"
    ],
    "name:und_x_variant":[
        "Tjock\u00f6"
    ],
    "wof:name":"Tjocko",
    "wof:placetype":"locality"
},
  "geometry": {"coordinates":[19.11667000000001,59.75],"type":"Point"}
}