{
  "type": "Feature",
  "properties": {
    "gn:admin1_code":"22.0",
    "gn:admin2_code":"1784.0",
    "gn:asciiname":"Tvarud",
    "gn:country_code":"SE",
    "gn:dem":139,
    "gn:feature_class":"P",
    "gn:feature_code":"PPL",
    "gn:name":"Tv\u00e4rud",
    "gn:population":0,
    "gn:timezone":"Europe/Stockholm",
    "iso:country":"SE",
    "wof:name":"Tvarud",
    "wof:placetype":"locality"
},
  "geometry": {"coordinates":[12.53333,59.88333000000001],"type":"Point"}
}