{
  "type": "Feature",
  "properties": {
    "gn:admin1_code":"6.0",
    "gn:admin2_code":"1382.0",
    "gn:asciiname":"Fare",
    "gn:country_code":"SE",
    "gn:dem":150,
    "gn:feature_class":"P",
    "gn:feature_code":"PPL",
    "gn:name":"Fare",
    "gn:population":0,
    "gn:timezone":"Europe/Stockholm",
    "iso:country":"SE",
    "name:ces_x_preferred":[
        "J\u00edzdn\u00e9"
    ],
    "name:deu_x_preferred":[
        "Pauschaltarif"
    ],
    "name:eus_x_preferred":[
        "Tarifa"
    ],
    "name:fas_x_preferred":[
        "\u06a9\u0631\u0627\u06cc\u0647 \u0633\u0641\u0631"
    ],
    "name:por_x_preferred":[
        "Tarifa"
    ],
    "name:spa_x_preferred":[
        "Tarifa"
    ],
    "wof:name":"Fare",
    "wof:placetype":"locality"
},
  "geometry": {"coordinates":[12.73333,57.18333000000001],"type":"Point"}
}