{
  "type": "Feature",
  "properties": {
    "gn:admin1_code":"15.0",
    "gn:admin2_code":"1880.0",
    "gn:asciiname":"Martenstorp",
    "gn:country_code":"SE",
    "gn:dem":102,
    "gn:feature_class":"P",
    "gn:feature_code":"PPL",
    "gn:name":"M\u00e5rtenstorp",
    "gn:population":0,
    "gn:timezone":"Europe/Stockholm",
    "iso:country":"SE",
    "wof:name":"Martenstorp",
    "wof:placetype":"locality"
},
  "geometry": {"coordinates":[14.88333,59.25],"type":"Point"}
}