{
  "type": "Feature",
  "properties": {
    "gn:admin1_code":"23.0",
    "gn:admin2_code":"2482.0",
    "gn:asciiname":"Ostra Hjaggbole",
    "gn:cc2":"SE",
    "gn:country_code":"SE",
    "gn:dem":68,
    "gn:feature_class":"P",
    "gn:feature_code":"PPL",
    "gn:name":"\u00d6stra Hj\u00e5ggb\u00f6le",
    "gn:population":0,
    "gn:timezone":"Europe/Stockholm",
    "iso:country":"SE",
    "name:nor_x_preferred":[
        "\u00d6stra Hj\u00e5ggb\u00f6le"
    ],
    "name:nor_x_variant":[
        "\u00d8stra Hj\u00e5ggb\u00f8le"
    ],
    "name:und_x_variant":[
        "\u00d6stra Hjoggb\u00f6le"
    ],
    "wof:name":"Ostra Hjaggbole",
    "wof:placetype":"locality"
},
  "geometry": {"coordinates":[20.96667,64.56667],"type":"Point"}
}