{
  "type": "Feature",
  "properties": {
    "gn:admin1_code":"3.0",
    "gn:admin2_code":"2181.0",
    "gn:admin3_code":"218104.0",
    "gn:admin4_code":"2446.0",
    "gn:asciiname":"Akra",
    "gn:country_code":"SE",
    "gn:dem":69,
    "gn:feature_class":"P",
    "gn:feature_code":"PPL",
    "gn:name":"\u00c5kra",
    "gn:population":0,
    "gn:timezone":"Europe/Stockholm",
    "iso:country":"SE",
    "wof:name":"Akra",
    "wof:placetype":"locality"
},
  "geometry": {"coordinates":[16.6645,60.48778000000001],"type":"Point"}
}