{
  "type": "Feature",
  "properties": {
    "gn:admin1_code":"18",
    "gn:admin2_code":"484.0",
    "gn:admin3_code":"48413.0",
    "gn:admin4_code":"394.0",
    "gn:asciiname":"Stora Sundby",
    "gn:country_code":"SE",
    "gn:dem":37,
    "gn:feature_class":"P",
    "gn:feature_code":"PPL",
    "gn:name":"Stora Sundby",
    "gn:population":0,
    "gn:timezone":"Europe/Stockholm",
    "iso:country":"SE",
    "wof:name":"Stora Sundby",
    "wof:placetype":"locality"
},
  "geometry": {"coordinates":[16.12158,59.27231],"type":"Point"}
}