{
  "type": "Feature",
  "properties": {
    "gn:admin1_code":"27.0",
    "gn:admin2_code":"1293.0",
    "gn:asciiname":"Lilla Torsjo",
    "gn:country_code":"SE",
    "gn:dem":97,
    "gn:feature_class":"P",
    "gn:feature_code":"PPL",
    "gn:name":"Lilla Torsj\u00f6",
    "gn:population":0,
    "gn:timezone":"Europe/Stockholm",
    "iso:country":"SE",
    "name:nor_x_preferred":[
        "Lilla Torsj\u00f6"
    ],
    "name:nor_x_variant":[
        "Lilla Torsj\u00f8"
    ],
    "name:und_x_variant":[
        "Lilla Torsj\u00f6"
    ],
    "wof:name":"Lilla Torsjo",
    "wof:placetype":"locality"
},
  "geometry": {"coordinates":[13.55,56.15],"type":"Point"}
}