{
  "type": "Feature",
  "properties": {
    "gn:admin1_code":"27.0",
    "gn:admin2_code":"1293.0",
    "gn:asciiname":"Galthult",
    "gn:country_code":"SE",
    "gn:dem":144,
    "gn:feature_class":"P",
    "gn:feature_code":"PPL",
    "gn:name":"Galthult",
    "gn:population":0,
    "gn:timezone":"Europe/Stockholm",
    "iso:country":"SE",
    "wof:name":"Galthult",
    "wof:placetype":"locality"
},
  "geometry": {"coordinates":[13.51667,56.21666999999999],"type":"Point"}
}