{
  "type": "Feature",
  "properties": {
    "gn:country":"SE",
    "gn:fcode":"PPL",
    "gn:population":0,
    "iso:country":"SE",
    "name:dan_x_preferred":[
        "Forsmark"
    ],
    "name:deu_x_preferred":[
        "Forsmark"
    ],
    "name:eng_x_preferred":[
        "Forsmark"
    ],
    "name:fin_x_preferred":[
        "Forsmark"
    ],
    "name:fra_x_preferred":[
        "Forsmark"
    ],
    "name:ita_x_preferred":[
        "Forsmark"
    ],
    "name:nds_x_preferred":[
        "Forsmark"
    ],
    "name:nld_x_preferred":[
        "Forsmark"
    ],
    "name:nno_x_preferred":[
        "Forsmark"
    ],
    "name:nob_x_preferred":[
        "Forsmark"
    ],
    "name:por_x_preferred":[
        "Forsmark"
    ],
    "name:swe_x_preferred":[
        "Forsmark"
    ],
    "qs_pg:aaroncc":"SE",
    "qs_pg:gn_country":"SE",
    "qs_pg:gn_fcode":"PPL",
    "qs_pg:gn_pop":0,
    "qs_pg:name":"Forsmark",
    "qs_pg:name_adm0":"Sverige",
    "qs_pg:name_adm1":"Uppsala L\u00e4n",
    "qs_pg:photos":95,
    "qs_pg:photos_1k":19,
    "qs_pg:photos_9k":1,
    "qs_pg:photos_9r":3,
    "qs_pg:photos_all":95,
    "qs_pg:photos_sr":3,
    "qs_pg:pop_sr":0,
    "qs_pg:qs_pg_placetype":"locality",
    "qs_pg:qs_pg_placetype_gp":"Town",
    "qs_pg:woe_adm0":23424954,
    "woe:adm0_id":23424954,
    "woe:name_adm0":"Sverige",
    "woe:name_adm1":"Uppsala L\u00e4n",
    "woe:placetype":"Town",
    "wof:name":"Forsmark",
    "wof:placetype":"locality"
},
  "geometry": {"coordinates":[18.15,60.36667],"type":"Point"}
}