{
  "type": "Feature",
  "properties": {
    "gn:admin1_code":"7.0",
    "gn:admin2_code":"2361.0",
    "gn:asciiname":"Backarna",
    "gn:country_code":"SE",
    "gn:dem":603,
    "gn:feature_class":"P",
    "gn:feature_code":"PPL",
    "gn:name":"B\u00e4ckarna",
    "gn:population":0,
    "gn:timezone":"Europe/Stockholm",
    "iso:country":"SE",
    "wof:name":"Backarna",
    "wof:placetype":"locality"
},
  "geometry": {"coordinates":[14.51667,62.25],"type":"Point"}
}