{
  "type": "Feature",
  "properties": {
    "gn:gn_country":"SE",
    "gn:gn_fcode":"PPL",
    "gn:gn_pop":348,
    "gn:population":354,
    "iso:country":"SE",
    "name:dut_x_preferred":[
        "G\u00e5rdsk\u00e4r"
    ],
    "name:eng_x_preferred":[
        "G\u00e5rdsk\u00e4r"
    ],
    "name:ita_x_preferred":[
        "G\u00e5rdsk\u00e4r"
    ],
    "name:nan_x_preferred":[
        "G\u00e5rdsk\u00e4r"
    ],
    "name:nno_x_preferred":[
        "G\u00e5rdsk\u00e4r"
    ],
    "name:nob_x_preferred":[
        "G\u00e5rdsk\u00e4r"
    ],
    "name:por_x_preferred":[
        "G\u00e5rdsk\u00e4r"
    ],
    "name:swe_x_preferred":[
        "G\u00e5rdsk\u00e4r"
    ],
    "name:unk_x_variant":[
        "Berget"
    ],
    "qs_pg:aaroncc":"SE",
    "qs_pg:gn_country":"SE",
    "qs_pg:gn_fcode":"PPL",
    "qs_pg:gn_pop":348,
    "qs_pg:name":"G\u00e5rdsk\u00e4r",
    "qs_pg:name_adm0":"Sverige",
    "qs_pg:name_adm1":"Uppsala L\u00e4n",
    "qs_pg:photos_9k":1,
    "qs_pg:photos_9r":1,
    "qs_pg:photos_all":1,
    "qs_pg:photos_sr":0,
    "qs_pg:pop_sr":2,
    "qs_pg:qs_pg_placetype":"locality",
    "qs_pg:qs_pg_placetype_gp":"Town",
    "qs_pg:woe_adm0":23424954,
    "woe:adm0_id":23424954,
    "woe:name_adm0":"Sverige",
    "woe:name_adm1":"Uppsala L\u00e4n",
    "woe:placetype":"Town",
    "wof:name":"G\u00e5rdsk\u00e4r",
    "wof:placetype":"locality",
    "wof:population":354
},
  "geometry": {"coordinates":[17.58333,60.61667],"type":"Point"}
}