{
  "type": "Feature",
  "properties": {
    "gn:admin1_code":"3.0",
    "gn:admin2_code":"2161.0",
    "gn:asciiname":"Forange",
    "gn:country_code":"SE",
    "gn:dem":121,
    "gn:feature_class":"P",
    "gn:feature_code":"PPL",
    "gn:name":"F\u00f6r\u00e4nge",
    "gn:population":0,
    "gn:timezone":"Europe/Stockholm",
    "iso:country":"SE",
    "wof:name":"Forange",
    "wof:placetype":"locality"
},
  "geometry": {"coordinates":[16.18333,61.68333000000001],"type":"Point"}
}