{
  "type": "Feature",
  "properties": {
    "gn:admin1_code":"18.0",
    "gn:admin2_code":"482.0",
    "gn:asciiname":"Stalboga",
    "gn:cc2":"SE",
    "gn:country_code":"SE",
    "gn:dem":49,
    "gn:feature_class":"P",
    "gn:feature_code":"PPL",
    "gn:name":"St\u00e5lboga",
    "gn:population":0,
    "gn:timezone":"Europe/Stockholm",
    "iso:country":"SE",
    "name:und_x_variant":[
        "St\u00e5lb\u00e5ga",
        "St\u00e5lboga"
    ],
    "wof:name":"Stalboga",
    "wof:placetype":"locality"
},
  "geometry": {"coordinates":[16.81667,59.23333],"type":"Point"}
}