{
  "type": "Feature",
  "properties": {
    "gn:admin1_code":"24.0",
    "gn:admin2_code":"2282.0",
    "gn:asciiname":"Utvik",
    "gn:country_code":"SE",
    "gn:dem":35,
    "gn:feature_class":"P",
    "gn:feature_code":"PPL",
    "gn:name":"Utvik",
    "gn:population":0,
    "gn:timezone":"Europe/Stockholm",
    "iso:country":"SE",
    "name:msa_x_preferred":[
        "Utvik"
    ],
    "name:nld_x_preferred":[
        "Utvik"
    ],
    "name:nno_x_preferred":[
        "Utvik"
    ],
    "name:nor_x_preferred":[
        "Utvik"
    ],
    "name:pol_x_preferred":[
        "Utvik"
    ],
    "name:ron_x_preferred":[
        "Utvik"
    ],
    "wof:name":"Utvik",
    "wof:placetype":"locality"
},
  "geometry": {"coordinates":[18.18333,63.01667],"type":"Point"}
}