{
  "type": "Feature",
  "properties": {
    "iso:country":"SE",
    "name:bul_x_preferred":[
        "\u0428\u044c\u043e\u0431\u0443"
    ],
    "name:ceb_x_preferred":[
        "Sj\u00f6bo"
    ],
    "name:dan_x_preferred":[
        "Sj\u00f6bo"
    ],
    "name:deu_x_preferred":[
        "Sj\u00f6bo"
    ],
    "name:fao_x_preferred":[
        "Sj\u00f6bo"
    ],
    "name:fas_x_preferred":[
        "\u062e\u0627\u0628\u0648"
    ],
    "name:fin_x_preferred":[
        "Sj\u00f6bo"
    ],
    "name:fra_x_preferred":[
        "Sj\u00f6bo"
    ],
    "name:isl_x_preferred":[
        "Sj\u00f6bo"
    ],
    "name:ita_x_preferred":[
        "Sj\u00f6bo"
    ],
    "name:nld_x_preferred":[
        "Sj\u00f6bo"
    ],
    "name:nno_x_preferred":[
        "Sj\u00f6bo"
    ],
    "name:nor_x_preferred":[
        "Sj\u00f8bo"
    ],
    "name:nor_x_variant":[
        "Sj\u00f6bo"
    ],
    "name:pol_x_preferred":[
        "Sj\u00f6bo"
    ],
    "name:ron_x_preferred":[
        "Sj\u00f6bo"
    ],
    "name:swe_x_colloquial":[
        "Sjobo",
        "Sjoebo"
    ],
    "name:swe_x_preferred":[
        "Sj\u00f6bo"
    ],
    "name:unk_x_variant":[
        "Sj\u00f6bo"
    ],
    "qs:gn_adm0_cc":"SE",
    "qs:gn_fcode":"PPLX",
    "qs:gn_local":2720501,
    "qs:gn_nam_loc":"Bor\u00e5s, Bor\u00e5s, V\u00e4stra G\u00f6talands L\u00e4n, SE",
    "qs:gn_namadm1":"28",
    "qs:gn_name":"Sj\u00f6bo",
    "qs:local_max":1005,
    "qs:local_sum":2043,
    "qs:localhoods":3,
    "qs:name":"Sj\u00f6bo",
    "qs:name_adm0":"Sverige",
    "qs:name_adm1":"V\u00e4stra G\u00f6talands L\u00e4n",
    "qs:name_adm2":"Bor\u00e5s",
    "qs:name_local":"Bor\u00e5s",
    "qs:photo_max":167,
    "qs:photo_sum":1005,
    "qs:placetype":"Suburb",
    "qs:quad_count":84,
    "qs:woe_adm0":23424954,
    "qs:woe_adm1":20070562,
    "qs:woe_adm2":12587204,
    "qs:woe_lau":0,
    "qs:woe_local":887229,
    "qs:woe_ver":"7.10.0",
    "wof:lang":[
        "swe"
    ],
    "wof:name":"Sj\u00f6bo",
    "wof:placetype":"neighbourhood"
},
  "geometry": {"coordinates":[12.943901,57.740962],"type":"Point"}
}