{
  "type": "Feature",
  "properties": {
    "gn:admin1_code":"21.0",
    "gn:admin2_code":"382.0",
    "gn:asciiname":"Mysslinge",
    "gn:country_code":"SE",
    "gn:dem":12,
    "gn:feature_class":"P",
    "gn:feature_code":"PPL",
    "gn:name":"Mysslinge",
    "gn:population":0,
    "gn:timezone":"Europe/Stockholm",
    "iso:country":"SE",
    "wof:name":"Mysslinge",
    "wof:placetype":"locality"
},
  "geometry": {"coordinates":[18.08333,60.11666999999999],"type":"Point"}
}