{
  "type": "Feature",
  "properties": {
    "gn:admin1_code":"9.0",
    "gn:admin2_code":"884.0",
    "gn:asciiname":"Falla",
    "gn:country_code":"SE",
    "gn:dem":139,
    "gn:feature_class":"P",
    "gn:feature_code":"PPL",
    "gn:name":"Falla",
    "gn:population":0,
    "gn:timezone":"Europe/Stockholm",
    "iso:country":"SE",
    "wof:name":"Falla",
    "wof:placetype":"locality"
},
  "geometry": {"coordinates":[15.91667,57.61666999999999],"type":"Point"}
}