{
  "type": "Feature",
  "properties": {
    "gn:admin1_code":"9.0",
    "gn:admin2_code":"884.0",
    "gn:asciiname":"Falla",
    "gn:country_code":"SE",
    "gn:dem":139,
    "gn:feature_class":"P",
    "gn:feature_code":"PPL",
    "gn:name":"Falla",
    "gn:population":0,
    "gn:timezone":"Europe/Stockholm",
    "iso:country":"SE",
    "name:arg_x_preferred":[
        "Falla"
    ],
    "name:cat_x_preferred":[
        "Falla"
    ],
    "name:ceb_x_preferred":[
        "Falla"
    ],
    "name:ces_x_preferred":[
        "Falla"
    ],
    "name:deu_x_preferred":[
        "Falla"
    ],
    "name:fin_x_preferred":[
        "Falla"
    ],
    "name:fra_x_preferred":[
        "Falla"
    ],
    "name:ita_x_preferred":[
        "Falla"
    ],
    "name:jpn_x_preferred":[
        "\u30d5\u30a1\u30ea\u30e3"
    ],
    "name:rus_x_preferred":[
        "\u0424\u0430\u043b\u044c\u044f"
    ],
    "name:slv_x_preferred":[
        "Falla"
    ],
    "name:spa_x_preferred":[
        "Falla"
    ],
    "name:swe_x_preferred":[
        "Falla"
    ],
    "wof:name":"Falla",
    "wof:placetype":"locality"
},
  "geometry": {"coordinates":[15.91667,57.61666999999999],"type":"Point"}
}