{
  "type": "Feature",
  "properties": {
    "gn:admin1_code":"12.0",
    "gn:asciiname":"Balshult",
    "gn:country_code":"SE",
    "gn:dem":205,
    "gn:feature_class":"P",
    "gn:feature_code":"PPL",
    "gn:name":"B\u00e4lshult",
    "gn:population":0,
    "gn:timezone":"Europe/Stockholm",
    "iso:country":"SE",
    "wof:name":"Balshult",
    "wof:placetype":"locality"
},
  "geometry": {"coordinates":[15.56667,56.76667],"type":"Point"}
}