{
  "type": "Feature",
  "properties": {
    "gn:admin1_code":"21.0",
    "gn:asciiname":"Langarsbo",
    "gn:country_code":"SE",
    "gn:dem":52,
    "gn:feature_class":"P",
    "gn:feature_code":"PPL",
    "gn:name":"L\u00e5ngarsbo",
    "gn:population":0,
    "gn:timezone":"Europe/Stockholm",
    "iso:country":"SE",
    "wof:name":"Langarsbo",
    "wof:placetype":"locality"
},
  "geometry": {"coordinates":[17.06667,60.16667],"type":"Point"}
}