{
  "type": "Feature",
  "properties": {
    "gn:admin1_code":"7.0",
    "gn:admin2_code":"2380.0",
    "gn:asciiname":"Garde",
    "gn:country_code":"SE",
    "gn:dem":306,
    "gn:feature_class":"P",
    "gn:feature_code":"PPL",
    "gn:name":"G\u00e4rde",
    "gn:population":0,
    "gn:timezone":"Europe/Stockholm",
    "iso:country":"SE",
    "name:ceb_x_preferred":[
        "Garde"
    ],
    "name:ces_x_preferred":[
        "Garde"
    ],
    "name:deu_x_preferred":[
        "Garde"
    ],
    "name:fra_x_preferred":[
        "Garde"
    ],
    "name:ita_x_preferred":[
        "Garde"
    ],
    "name:nld_x_preferred":[
        "Garde"
    ],
    "name:pol_x_preferred":[
        "Garde"
    ],
    "name:rus_x_preferred":[
        "\u0413\u0430\u0440\u0434"
    ],
    "name:scn_x_preferred":[
        "Guardianu"
    ],
    "name:swe_x_preferred":[
        "Garde"
    ],
    "name:ukr_x_preferred":[
        "\u0413\u0430\u0440\u0434"
    ],
    "wof:name":"Garde",
    "wof:placetype":"locality"
},
  "geometry": {"coordinates":[14.43333,63.11666999999999],"type":"Point"}
}