{
  "type": "Feature",
  "properties": {
    "gn:country":"SE",
    "gn:fcode":"PPL",
    "gn:population":205,
    "iso:country":"SE",
    "name:ceb_x_preferred":[
        "\u00d6stmark"
    ],
    "name:dan_x_preferred":[
        "\u00d6stmark"
    ],
    "name:deu_x_preferred":[
        "\u00d6stmark"
    ],
    "name:eng_x_preferred":[
        "\u00d6stmark"
    ],
    "name:fra_x_preferred":[
        "\u00d6stmark"
    ],
    "name:gle_x_preferred":[
        "\u00d6stmark"
    ],
    "name:ita_x_preferred":[
        "\u00d6stmark"
    ],
    "name:lld_x_preferred":[
        "\u00d6stmark"
    ],
    "name:nan_x_preferred":[
        "\u00d6stmark"
    ],
    "name:nds_x_preferred":[
        "\u00d6stmark"
    ],
    "name:nld_x_preferred":[
        "\u00d6stmark"
    ],
    "name:nno_x_preferred":[
        "\u00d6stmark"
    ],
    "name:nob_x_preferred":[
        "\u00d6stmark"
    ],
    "name:nor_x_preferred":[
        "\u00d8stmark"
    ],
    "name:nor_x_variant":[
        "\u00d6stmark"
    ],
    "name:swe_x_preferred":[
        "\u00d6stmark"
    ],
    "name:und_x_variant":[
        "\u00d6stra Marken"
    ],
    "qs_pg:aaroncc":"SE",
    "qs_pg:gn_country":"SE",
    "qs_pg:gn_fcode":"PPL",
    "qs_pg:gn_pop":205,
    "qs_pg:name":"\u00d6stmark",
    "qs_pg:name_adm0":"Sverige",
    "qs_pg:name_adm1":"V\u00e4rmlands L\u00e4n",
    "qs_pg:photos":74,
    "qs_pg:photos_1k":15,
    "qs_pg:photos_9k":1,
    "qs_pg:photos_9r":2,
    "qs_pg:photos_all":74,
    "qs_pg:photos_sr":2,
    "qs_pg:pop_sr":2,
    "qs_pg:qs_pg_placetype":"locality",
    "qs_pg:qs_pg_placetype_gp":"Town",
    "qs_pg:woe_adm0":23424954,
    "woe:adm0_id":23424954,
    "woe:name_adm0":"Sverige",
    "woe:name_adm1":"V\u00e4rmlands L\u00e4n",
    "woe:placetype":"Town",
    "wof:name":"\u00d6stmark",
    "wof:placetype":"locality",
    "wof:population":205
},
  "geometry": {"coordinates":[12.75,60.28333],"type":"Point"}
}