{
  "type": "Feature",
  "properties": {
    "gn:admin1_code":"7.0",
    "gn:admin2_code":"2313.0",
    "gn:asciiname":"Raukasjo",
    "gn:country_code":"SE",
    "gn:dem":630,
    "gn:feature_class":"P",
    "gn:feature_code":"PPL",
    "gn:name":"Raukasj\u00f6",
    "gn:population":0,
    "gn:timezone":"Europe/Stockholm",
    "iso:country":"SE",
    "name:nor_x_preferred":[
        "Raukasj\u00f6"
    ],
    "name:nor_x_variant":[
        "Raukasj\u00f8"
    ],
    "wof:name":"Raukasjo",
    "wof:placetype":"locality"
},
  "geometry": {"coordinates":[14.55,64.93333],"type":"Point"}
}