{
  "type": "Feature",
  "properties": {
    "gn:admin1_code":"24.0",
    "gn:admin2_code":"2281.0",
    "gn:admin3_code":"228109.0",
    "gn:admin4_code":"2451.0",
    "gn:asciiname":"Karlang",
    "gn:country_code":"SE",
    "gn:dem":6,
    "gn:feature_class":"P",
    "gn:feature_code":"PPL",
    "gn:name":"Karl\u00e4ng",
    "gn:population":0,
    "gn:timezone":"Europe/Stockholm",
    "iso:country":"SE",
    "wof:name":"Karlang",
    "wof:placetype":"locality"
},
  "geometry": {"coordinates":[17.04426,62.30764],"type":"Point"}
}