{
  "type": "Feature",
  "properties": {
    "gn:admin1_code":"24.0",
    "gn:admin2_code":"2282.0",
    "gn:asciiname":"Almsjonas",
    "gn:country_code":"SE",
    "gn:dem":163,
    "gn:feature_class":"P",
    "gn:feature_code":"PPL",
    "gn:name":"Almsj\u00f6n\u00e4s",
    "gn:population":0,
    "gn:timezone":"Europe/Stockholm",
    "iso:country":"SE",
    "wof:name":"Almsjonas",
    "wof:placetype":"locality"
},
  "geometry": {"coordinates":[18.01667,63.06667],"type":"Point"}
}