{
  "type": "Feature",
  "properties": {
    "gn:admin1_code":"7.0",
    "gn:admin2_code":"2361.0",
    "gn:asciiname":"Ostvallarna",
    "gn:country_code":"SE",
    "gn:dem":763,
    "gn:feature_class":"P",
    "gn:feature_code":"PPL",
    "gn:name":"\u00d6stvallarna",
    "gn:population":0,
    "gn:timezone":"Europe/Stockholm",
    "iso:country":"SE",
    "name:nor_x_preferred":[
        "\u00d6stvallarna"
    ],
    "name:nor_x_variant":[
        "\u00d8stvallarna"
    ],
    "name:und_x_variant":[
        "\u00d6stvallarna"
    ],
    "wof:name":"Ostvallarna",
    "wof:placetype":"locality"
},
  "geometry": {"coordinates":[13.31667,62.35],"type":"Point"}
}