{
  "type": "Feature",
  "properties": {
    "gn:admin1_code":"2.0",
    "gn:admin2_code":"1082.0",
    "gn:asciiname":"Notabrane",
    "gn:country_code":"SE",
    "gn:dem":57,
    "gn:feature_class":"P",
    "gn:feature_code":"PPL",
    "gn:name":"N\u00f6tabr\u00e5ne",
    "gn:population":0,
    "gn:timezone":"Europe/Stockholm",
    "iso:country":"SE",
    "name:nor_x_preferred":[
        "N\u00f6tabr\u00e5ne"
    ],
    "name:nor_x_variant":[
        "N\u00f8tabr\u00e5ne"
    ],
    "wof:name":"Notabrane",
    "wof:placetype":"locality"
},
  "geometry": {"coordinates":[14.86667,56.23333],"type":"Point"}
}