{
  "type": "Feature",
  "properties": {
    "gn:admin1_code":"18.0",
    "gn:admin2_code":"482.0",
    "gn:asciiname":"Lundby",
    "gn:country_code":"SE",
    "gn:dem":55,
    "gn:feature_class":"P",
    "gn:feature_code":"PPL",
    "gn:name":"Lundby",
    "gn:population":0,
    "gn:timezone":"Europe/Stockholm",
    "iso:country":"SE",
    "name:ceb_x_preferred":[
        "Lundby"
    ],
    "name:dan_x_preferred":[
        "Lundby"
    ],
    "name:deu_x_preferred":[
        "Lundby"
    ],
    "name:nld_x_preferred":[
        "Lundby"
    ],
    "name:swe_x_preferred":[
        "Lundby"
    ],
    "wof:name":"Lundby",
    "wof:placetype":"locality"
},
  "geometry": {"coordinates":[16.71667,59.11666999999999],"type":"Point"}
}