{
  "type": "Feature",
  "properties": {
    "gn:admin1_code":"7.0",
    "gn:admin2_code":"2326.0",
    "gn:asciiname":"Felingen",
    "gn:country_code":"SE",
    "gn:dem":350,
    "gn:feature_class":"P",
    "gn:feature_code":"PPL",
    "gn:name":"Felingen",
    "gn:population":0,
    "gn:timezone":"Europe/Stockholm",
    "iso:country":"SE",
    "wof:name":"Felingen",
    "wof:placetype":"locality"
},
  "geometry": {"coordinates":[14.71667,62.86666999999999],"type":"Point"}
}