{
  "type": "Feature",
  "properties": {
    "gn:admin1_code":"15.0",
    "gn:admin2_code":"1884.0",
    "gn:asciiname":"Timanshyttan",
    "gn:cc2":"SE",
    "gn:country_code":"SE",
    "gn:dem":154,
    "gn:feature_class":"P",
    "gn:feature_code":"PPL",
    "gn:name":"Timanshyttan",
    "gn:population":0,
    "gn:timezone":"Europe/Stockholm",
    "iso:country":"SE",
    "name:und_x_variant":[
        "Timansberg",
        "Timanshyttan"
    ],
    "wof:name":"Timanshyttan",
    "wof:placetype":"locality"
},
  "geometry": {"coordinates":[14.85,59.61666999999999],"type":"Point"}
}