{
  "type": "Feature",
  "properties": {
    "gn:admin1_code":"7.0",
    "gn:admin2_code":"2305.0",
    "gn:asciiname":"Binnaset",
    "gn:country_code":"SE",
    "gn:dem":287,
    "gn:feature_class":"P",
    "gn:feature_code":"PPL",
    "gn:name":"Binn\u00e4set",
    "gn:population":0,
    "gn:timezone":"Europe/Stockholm",
    "iso:country":"SE",
    "wof:name":"Binnaset",
    "wof:placetype":"locality"
},
  "geometry": {"coordinates":[15.31667,62.93333000000001],"type":"Point"}
}