{
  "type": "Feature",
  "properties": {
    "gn:admin1_code":"10.0",
    "gn:admin2_code":"2081.0",
    "gn:asciiname":"Alderbacken",
    "gn:cc2":"SE",
    "gn:country_code":"SE",
    "gn:dem":135,
    "gn:feature_class":"P",
    "gn:feature_code":"PPL",
    "gn:name":"Alderb\u00e4cken",
    "gn:population":0,
    "gn:timezone":"Europe/Stockholm",
    "iso:country":"SE",
    "name:und_x_variant":[
        "Alderb\u00e4ck",
        "Alderb\u00e4cken"
    ],
    "wof:name":"Alderbacken",
    "wof:placetype":"locality"
},
  "geometry": {"coordinates":[15.41667,60.45],"type":"Point"}
}