{
  "type": "Feature",
  "properties": {
    "gn:admin1_code":"8.0",
    "gn:admin2_code":"684.0",
    "gn:asciiname":"Anderstorp",
    "gn:country_code":"SE",
    "gn:dem":207,
    "gn:feature_class":"P",
    "gn:feature_code":"PPL",
    "gn:name":"Anderstorp",
    "gn:population":0,
    "gn:timezone":"Europe/Stockholm",
    "iso:country":"SE",
    "name:ceb_x_preferred":[
        "Anderstorp"
    ],
    "name:deu_x_preferred":[
        "Anderstorp"
    ],
    "name:fin_x_preferred":[
        "Anderstorp"
    ],
    "name:nld_x_preferred":[
        "Anderstorp"
    ],
    "name:nno_x_preferred":[
        "Anderstorp"
    ],
    "name:nor_x_preferred":[
        "Anderstorp"
    ],
    "name:pol_x_preferred":[
        "Anderstorp"
    ],
    "name:por_x_preferred":[
        "Anderstorp"
    ],
    "name:swe_x_preferred":[
        "Anderstorp"
    ],
    "name:zho_x_preferred":[
        "\u5b89\u5fb7\u4ec0\u6258\u666e"
    ],
    "wof:name":"Anderstorp",
    "wof:placetype":"locality"
},
  "geometry": {"coordinates":[14.55,57.28333000000001],"type":"Point"}
}