{
  "type": "Feature",
  "properties": {
    "gn:admin1_code":"8.0",
    "gn:admin2_code":"680.0",
    "gn:asciiname":"Kullen",
    "gn:country_code":"SE",
    "gn:dem":231,
    "gn:feature_class":"P",
    "gn:feature_code":"PPL",
    "gn:name":"Kullen",
    "gn:population":0,
    "gn:timezone":"Europe/Stockholm",
    "iso:country":"SE",
    "wof:name":"Kullen",
    "wof:placetype":"locality"
},
  "geometry": {"coordinates":[13.78333,57.81667],"type":"Point"}
}