{
  "type": "Feature",
  "properties": {
    "gn:admin1_code":"28.0",
    "gn:admin2_code":"1491.0",
    "gn:asciiname":"Hallestorp",
    "gn:country_code":"SE",
    "gn:dem":221,
    "gn:feature_class":"P",
    "gn:feature_code":"PPL",
    "gn:name":"H\u00e5llestorp",
    "gn:population":0,
    "gn:timezone":"Europe/Stockholm",
    "iso:country":"SE",
    "wof:name":"Hallestorp",
    "wof:placetype":"locality"
},
  "geometry": {"coordinates":[13.46667,57.95],"type":"Point"}
}