{
  "type": "Feature",
  "properties": {
    "gn:country":"SE",
    "gn:fcode":"PPL",
    "gn:population":0,
    "iso:country":"SE",
    "name:dan_x_preferred":[
        "M\u00e4larbaden"
    ],
    "name:deu_x_preferred":[
        "M\u00e4larbaden"
    ],
    "name:eng_x_preferred":[
        "M\u00e4larbaden"
    ],
    "name:fra_x_preferred":[
        "M\u00e4larbaden"
    ],
    "name:nds_x_preferred":[
        "M\u00e4larbaden"
    ],
    "name:nld_x_preferred":[
        "M\u00e4larbaden"
    ],
    "name:nno_x_preferred":[
        "M\u00e4larbaden"
    ],
    "name:nob_x_preferred":[
        "M\u00e4larbaden"
    ],
    "name:swe_x_preferred":[
        "M\u00e4larbaden"
    ],
    "qs_pg:aaroncc":"SE",
    "qs_pg:gn_country":"SE",
    "qs_pg:gn_fcode":"PPL",
    "qs_pg:gn_pop":0,
    "qs_pg:name":"M\u00e4larbaden",
    "qs_pg:name_adm0":"Sverige",
    "qs_pg:name_adm1":"S\u00f6dermanlands L\u00e4n",
    "qs_pg:photos":137,
    "qs_pg:photos_1k":28,
    "qs_pg:photos_9k":1,
    "qs_pg:photos_9r":3,
    "qs_pg:photos_all":137,
    "qs_pg:photos_sr":3,
    "qs_pg:pop_sr":0,
    "qs_pg:qs_pg_placetype":"locality",
    "qs_pg:qs_pg_placetype_gp":"Town",
    "qs_pg:woe_adm0":23424954,
    "woe:adm0_id":23424954,
    "woe:name_adm0":"Sverige",
    "woe:name_adm1":"S\u00f6dermanlands L\u00e4n",
    "woe:placetype":"Town",
    "wof:name":"M\u00e4larbaden",
    "wof:placetype":"locality"
},
  "geometry": {"coordinates":[16.43333,59.45],"type":"Point"}
}