{
  "type": "Feature",
  "properties": {
    "gn:admin1_code":"26.0",
    "gn:admin2_code":"117.0",
    "gn:asciiname":"Svartgarn",
    "gn:country_code":"SE",
    "gn:dem":6,
    "gn:feature_class":"P",
    "gn:feature_code":"PPL",
    "gn:name":"Svartgarn",
    "gn:population":0,
    "gn:timezone":"Europe/Stockholm",
    "iso:country":"SE",
    "wof:name":"Svartgarn",
    "wof:placetype":"locality"
},
  "geometry": {"coordinates":[18.28743,59.43569],"type":"Point"}
}