{
  "type": "Feature",
  "properties": {
    "gn:admin1_code":"14.0",
    "gn:admin2_code":"2518.0",
    "gn:asciiname":"Keroniemi",
    "gn:country_code":"SE",
    "gn:dem":141,
    "gn:feature_class":"P",
    "gn:feature_code":"PPL",
    "gn:name":"Keroniemi",
    "gn:population":0,
    "gn:timezone":"Europe/Stockholm",
    "iso:country":"SE",
    "name:fin_x_preferred":[
        "Keroniemi"
    ],
    "wof:name":"Keroniemi",
    "wof:placetype":"locality"
},
  "geometry": {"coordinates":[23.63141,66.65781],"type":"Point"}
}