{
  "type": "Feature",
  "properties": {
    "gn:admin1_code":"26.0",
    "gn:admin2_code":"136.0",
    "gn:asciiname":"Stromslund",
    "gn:cc2":"SE",
    "gn:country_code":"SE",
    "gn:dem":46,
    "gn:feature_class":"P",
    "gn:feature_code":"PPL",
    "gn:name":"Str\u00f6mslund",
    "gn:population":0,
    "gn:timezone":"Europe/Stockholm",
    "iso:country":"SE",
    "name:nor_x_preferred":[
        "Str\u00f6mslund"
    ],
    "name:nor_x_variant":[
        "Str\u00f8mslund"
    ],
    "name:und_x_variant":[
        "Str\u00f6msund"
    ],
    "wof:name":"Stromslund",
    "wof:placetype":"locality"
},
  "geometry": {"coordinates":[18.13306,59.14972],"type":"Point"}
}