{
  "type": "Feature",
  "properties": {
    "gn:admin1_code":"24.0",
    "gn:admin2_code":"2282.0",
    "gn:asciiname":"Dal",
    "gn:country_code":"SE",
    "gn:dem":43,
    "gn:feature_class":"P",
    "gn:feature_code":"PPL",
    "gn:name":"Dal",
    "gn:population":0,
    "gn:timezone":"Europe/Stockholm",
    "iso:country":"SE",
    "name:aze_x_preferred":[
        "Dal"
    ],
    "name:ben_x_preferred":[
        "\u09a1\u09be\u09b2"
    ],
    "name:dan_x_preferred":[
        "Dhal"
    ],
    "name:deu_x_preferred":[
        "Dal"
    ],
    "name:epo_x_preferred":[
        "Dalo"
    ],
    "name:fra_x_preferred":[
        "Dal"
    ],
    "name:guj_x_preferred":[
        "\u0aa6\u0abe\u0ab3"
    ],
    "name:heb_x_preferred":[
        "\u05d3\u05d0\u05dc"
    ],
    "name:hin_x_preferred":[
        "\u0926\u093e\u0932"
    ],
    "name:hye_x_preferred":[
        "\u0534\u0561\u056c"
    ],
    "name:ita_x_preferred":[
        "Dal"
    ],
    "name:jpn_x_preferred":[
        "\u30c0\u30fc\u30eb"
    ],
    "name:kan_x_preferred":[
        "\u0cac\u0cc7\u0cb3\u0cc6"
    ],
    "name:kor_x_preferred":[
        "\ub2ec"
    ],
    "name:lit_x_preferred":[
        "Dal"
    ],
    "name:mal_x_preferred":[
        "\u0d2a\u0d30\u0d3f\u0d2a\u0d4d\u0d2a\u0d41\u0d15\u0d31\u0d3f"
    ],
    "name:nep_x_preferred":[
        "\u0926\u093e\u0932"
    ],
    "name:nld_x_preferred":[
        "Dal"
    ],
    "name:nor_x_preferred":[
        "Dhal"
    ],
    "name:ori_x_preferred":[
        "\u0b21\u0b3e\u0b32\u0b3f"
    ],
    "name:pan_x_preferred":[
        "\u0a26\u0a3e\u0a32"
    ],
    "name:pol_x_preferred":[
        "Dal"
    ],
    "name:por_x_preferred":[
        "Dal"
    ],
    "name:ron_x_preferred":[
        "Dal"
    ],
    "name:rus_x_preferred":[
        "\u0414\u0430\u043b"
    ],
    "name:sat_x_preferred":[
        "\u1c6b\u1c5f\u1c79\u1c5e"
    ],
    "name:sin_x_preferred":[
        "\u0db4\u0dbb\u0dd2\u0db4\u0dca\u0db4\u0dd4"
    ],
    "name:spa_x_preferred":[
        "Dal"
    ],
    "name:swe_x_preferred":[
        "Dal"
    ],
    "name:tam_x_preferred":[
        "\u0baa\u0bb0\u0bc1\u0baa\u0bcd\u0baa\u0bc1"
    ],
    "name:tel_x_preferred":[
        "\u0c2a\u0c2a\u0c4d\u0c2a\u0c41"
    ],
    "name:tha_x_preferred":[
        "\u0e16\u0e31\u0e48\u0e27\u0e14\u0e32\u0e25"
    ],
    "wof:name":"Dal",
    "wof:placetype":"locality"
},
  "geometry": {"coordinates":[17.61667000000001,63.05],"type":"Point"}
}