{
  "type": "Feature",
  "properties": {
    "gn:admin1_code":"25.0",
    "gn:admin2_code":"1980.0",
    "gn:asciiname":"Grytaas",
    "gn:country_code":"SE",
    "gn:dem":52,
    "gn:feature_class":"P",
    "gn:feature_code":"PPL",
    "gn:name":"Gryta\u00e5s",
    "gn:population":0,
    "gn:timezone":"Europe/Stockholm",
    "iso:country":"SE",
    "wof:name":"Grytaas",
    "wof:placetype":"locality"
},
  "geometry": {"coordinates":[16.58333,59.68333000000001],"type":"Point"}
}