{
  "type": "Feature",
  "properties": {
    "gn:admin1_code":"27.0",
    "gn:admin2_code":"1256.0",
    "gn:asciiname":"Ostarod",
    "gn:country_code":"SE",
    "gn:dem":108,
    "gn:feature_class":"P",
    "gn:feature_code":"PPL",
    "gn:name":"\u00d6star\u00f6d",
    "gn:population":0,
    "gn:timezone":"Europe/Stockholm",
    "iso:country":"SE",
    "name:nor_x_preferred":[
        "\u00d6star\u00f6d"
    ],
    "name:nor_x_variant":[
        "\u00d8star\u00f8d"
    ],
    "name:und_x_variant":[
        "\u00d6star\u00f6d"
    ],
    "wof:name":"Ostarod",
    "wof:placetype":"locality"
},
  "geometry": {"coordinates":[14.13333,56.35],"type":"Point"}
}