{
  "type": "Feature",
  "properties": {
    "gn:admin1_code":"28.0",
    "gn:admin2_code":"1463.0",
    "gn:asciiname":"Nodinge",
    "gn:country_code":"SE",
    "gn:dem":39,
    "gn:feature_class":"P",
    "gn:feature_code":"PPL",
    "gn:name":"N\u00f6dinge",
    "gn:population":0,
    "gn:timezone":"Europe/Stockholm",
    "iso:country":"SE",
    "name:nor_x_preferred":[
        "N\u00f6dinge"
    ],
    "name:nor_x_variant":[
        "N\u00f8dinge"
    ],
    "wof:name":"Nodinge",
    "wof:placetype":"locality"
},
  "geometry": {"coordinates":[12.51667,57.48333],"type":"Point"}
}