{
  "type": "Feature",
  "properties": {
    "gn:admin1_code":"24.0",
    "gn:admin2_code":"2283.0",
    "gn:asciiname":"Strand",
    "gn:country_code":"SE",
    "gn:dem":171,
    "gn:feature_class":"P",
    "gn:feature_code":"PPL",
    "gn:name":"Strand",
    "gn:population":0,
    "gn:timezone":"Europe/Stockholm",
    "iso:country":"SE",
    "wof:name":"Strand",
    "wof:placetype":"locality"
},
  "geometry": {"coordinates":[17.06667,63.35],"type":"Point"}
}