{
  "type": "Feature",
  "properties": {
    "gn:admin1_code":"12.0",
    "gn:admin2_code":"763.0",
    "gn:asciiname":"Rossmala",
    "gn:cc2":"SE",
    "gn:country_code":"SE",
    "gn:dem":154,
    "gn:feature_class":"P",
    "gn:feature_code":"PPL",
    "gn:name":"R\u00f6ssm\u00e5la",
    "gn:population":0,
    "gn:timezone":"Europe/Stockholm",
    "iso:country":"SE",
    "name:nor_x_preferred":[
        "R\u00f6ssm\u00e5la"
    ],
    "name:nor_x_variant":[
        "R\u00f8ssm\u00e5la"
    ],
    "name:und_x_variant":[
        "R\u00f6sm\u00e5la",
        "R\u00f6ssm\u00e5la"
    ],
    "wof:name":"Rossmala",
    "wof:placetype":"locality"
},
  "geometry": {"coordinates":[14.85,56.56667],"type":"Point"}
}