{
  "type": "Feature",
  "properties": {
    "gn:admin1_code":"24.0",
    "gn:admin2_code":"2281.0",
    "gn:admin3_code":"228108.0",
    "gn:admin4_code":"2505.0",
    "gn:asciiname":"Skole",
    "gn:country_code":"SE",
    "gn:dem":45,
    "gn:feature_class":"P",
    "gn:feature_code":"PPL",
    "gn:name":"Sk\u00f6le",
    "gn:population":0,
    "gn:timezone":"Europe/Stockholm",
    "iso:country":"SE",
    "name:nor_x_preferred":[
        "Sk\u00f6le"
    ],
    "name:nor_x_variant":[
        "Sk\u00f8le"
    ],
    "name:und_x_variant":[
        "Sk\u00f6le"
    ],
    "wof:name":"Skole",
    "wof:placetype":"locality"
},
  "geometry": {"coordinates":[17.01422,62.34991],"type":"Point"}
}