{
  "type": "Feature",
  "properties": {
    "gn:admin1_code":"24.0",
    "gn:admin2_code":"2281.0",
    "gn:admin3_code":"228108.0",
    "gn:admin4_code":"2505.0",
    "gn:asciiname":"Skole",
    "gn:country_code":"SE",
    "gn:dem":45,
    "gn:feature_class":"P",
    "gn:feature_code":"PPL",
    "gn:name":"Sk\u00f6le",
    "gn:population":0,
    "gn:timezone":"Europe/Stockholm",
    "iso:country":"SE",
    "name:bel_x_preferred":[
        "\u0421\u043a\u043e\u043b\u044d"
    ],
    "name:ceb_x_preferred":[
        "Skole"
    ],
    "name:crh_x_preferred":[
        "Skole"
    ],
    "name:deu_x_preferred":[
        "Skole"
    ],
    "name:fas_x_preferred":[
        "\u0627\u0633\u06a9\u0648\u0644\u0647"
    ],
    "name:fra_x_preferred":[
        "Skole"
    ],
    "name:heb_x_preferred":[
        "\u05e1\u05e7\u05d5\u05dc\u05d4"
    ],
    "name:hsb_x_preferred":[
        "Skole"
    ],
    "name:hye_x_preferred":[
        "\u054d\u056f\u0578\u056c\u0565"
    ],
    "name:ita_x_preferred":[
        "Skole"
    ],
    "name:kat_x_preferred":[
        "\u10e1\u10d9\u10dd\u10da\u10d4"
    ],
    "name:lav_x_preferred":[
        "Skole"
    ],
    "name:nld_x_preferred":[
        "Skole"
    ],
    "name:nor_x_preferred":[
        "Sk\u00f6le"
    ],
    "name:nor_x_variant":[
        "Sk\u00f8le"
    ],
    "name:pol_x_preferred":[
        "Skole"
    ],
    "name:ron_x_preferred":[
        "Skole"
    ],
    "name:rus_x_preferred":[
        "\u0421\u043a\u043e\u043b\u0435"
    ],
    "name:ukr_x_preferred":[
        "\u0421\u043a\u043e\u043b\u0435"
    ],
    "name:und_x_variant":[
        "Sk\u00f6le"
    ],
    "name:vie_x_preferred":[
        "Skole"
    ],
    "name:zho_x_preferred":[
        "\u65af\u79d1\u5217"
    ],
    "wof:name":"Skole",
    "wof:placetype":"locality"
},
  "geometry": {"coordinates":[17.01422,62.34991],"type":"Point"}
}