{
  "type": "Feature",
  "properties": {
    "gn:admin1_code":"9.0",
    "gn:admin2_code":"860.0",
    "gn:asciiname":"Blaxhult",
    "gn:country_code":"SE",
    "gn:dem":139,
    "gn:feature_class":"P",
    "gn:feature_code":"PPL",
    "gn:name":"Blaxhult",
    "gn:population":0,
    "gn:timezone":"Europe/Stockholm",
    "iso:country":"SE",
    "wof:name":"Blaxhult",
    "wof:placetype":"locality"
},
  "geometry": {"coordinates":[16.03333,57.51667],"type":"Point"}
}