{
  "type": "Feature",
  "properties": {
    "gn:admin1_code":"24.0",
    "gn:asciiname":"Norredsta",
    "gn:country_code":"SE",
    "gn:dem":237,
    "gn:feature_class":"P",
    "gn:feature_code":"PPL",
    "gn:name":"Norredsta",
    "gn:population":0,
    "gn:timezone":"Europe/Stockholm",
    "iso:country":"SE",
    "wof:name":"Norredsta",
    "wof:placetype":"locality"
},
  "geometry": {"coordinates":[16.41667,63.71666999999999],"type":"Point"}
}