{
  "type": "Feature",
  "properties": {
    "gn:admin1_code":"27.0",
    "gn:admin2_code":"1285.0",
    "gn:asciiname":"Hogestorp",
    "gn:country_code":"SE",
    "gn:dem":50,
    "gn:feature_class":"P",
    "gn:feature_code":"PPL",
    "gn:name":"H\u00f6gestorp",
    "gn:population":0,
    "gn:timezone":"Europe/Stockholm",
    "iso:country":"SE",
    "name:nor_x_preferred":[
        "H\u00f6gestorp"
    ],
    "name:nor_x_variant":[
        "H\u00f8gestorp"
    ],
    "name:und_x_variant":[
        "H\u00f6gestorp"
    ],
    "wof:name":"Hogestorp",
    "wof:placetype":"locality"
},
  "geometry": {"coordinates":[13.15,55.88333000000001],"type":"Point"}
}