{
  "type": "Feature",
  "properties": {
    "gn:admin1_code":"15.0",
    "gn:admin2_code":"1882.0",
    "gn:asciiname":"Sodra Karra",
    "gn:country_code":"SE",
    "gn:dem":88,
    "gn:feature_class":"P",
    "gn:feature_code":"PPL",
    "gn:name":"S\u00f6dra K\u00e4rra",
    "gn:population":0,
    "gn:timezone":"Europe/Stockholm",
    "iso:country":"SE",
    "wof:name":"Sodra Karra",
    "wof:placetype":"locality"
},
  "geometry": {"coordinates":[14.98333,58.75],"type":"Point"}
}