{
  "type": "Feature",
  "properties": {
    "gn:admin1_code":"28.0",
    "gn:admin2_code":"1484.0",
    "gn:asciiname":"Rinkenas",
    "gn:country_code":"SE",
    "gn:dem":-1,
    "gn:feature_class":"P",
    "gn:feature_code":"PPL",
    "gn:name":"Rinken\u00e4s",
    "gn:population":0,
    "gn:timezone":"Europe/Stockholm",
    "iso:country":"SE",
    "wof:name":"Rinkenas",
    "wof:placetype":"locality"
},
  "geometry": {"coordinates":[11.425,58.275],"type":"Point"}
}