{
  "type": "Feature",
  "properties": {
    "gn:country":"SE",
    "gn:fcode":"PPL",
    "gn:population":0,
    "iso:country":"SE",
    "name:dan_x_preferred":[
        "Kassj\u00f6"
    ],
    "name:deu_x_preferred":[
        "Kassj\u00f6"
    ],
    "name:eng_x_preferred":[
        "Kassj\u00f6"
    ],
    "name:fra_x_preferred":[
        "Kassj\u00f6"
    ],
    "name:gle_x_preferred":[
        "Kassj\u00f6"
    ],
    "name:lld_x_preferred":[
        "Kassj\u00f6"
    ],
    "name:nds_x_preferred":[
        "Kassj\u00f6"
    ],
    "name:nld_x_preferred":[
        "Kassj\u00f6"
    ],
    "name:nno_x_preferred":[
        "Kassj\u00f6"
    ],
    "name:nob_x_preferred":[
        "Kassj\u00f6"
    ],
    "name:nor_x_preferred":[
        "Kassj\u00f8n"
    ],
    "name:nor_x_variant":[
        "Kassj\u00f6n"
    ],
    "name:swe_x_preferred":[
        "Kassj\u00f6"
    ],
    "qs_pg:aaroncc":"SE",
    "qs_pg:gn_country":"SE",
    "qs_pg:gn_fcode":"PPL",
    "qs_pg:gn_pop":0,
    "qs_pg:name":"Kassj\u00f6n",
    "qs_pg:name_adm0":"Sverige",
    "qs_pg:name_adm1":"V\u00e4sterbottens L\u00e4n",
    "qs_pg:photos":46,
    "qs_pg:photos_1k":9,
    "qs_pg:photos_9k":1,
    "qs_pg:photos_9r":2,
    "qs_pg:photos_all":46,
    "qs_pg:photos_sr":2,
    "qs_pg:pop_sr":0,
    "qs_pg:qs_pg_placetype":"locality",
    "qs_pg:qs_pg_placetype_gp":"Town",
    "qs_pg:woe_adm0":23424954,
    "woe:adm0_id":23424954,
    "woe:name_adm0":"Sverige",
    "woe:name_adm1":"V\u00e4sterbottens L\u00e4n",
    "woe:placetype":"Town",
    "wof:name":"Kassj\u00f6n",
    "wof:placetype":"locality"
},
  "geometry": {"coordinates":[19.98333,63.93333],"type":"Point"}
}