{
  "type": "Feature",
  "properties": {
    "gn:admin1_code":"24.0",
    "gn:admin2_code":"2284.0",
    "gn:asciiname":"Bureaborg",
    "gn:country_code":"SE",
    "gn:dem":242,
    "gn:feature_class":"P",
    "gn:feature_code":"PPL",
    "gn:name":"Bure\u00e5borg",
    "gn:population":0,
    "gn:timezone":"Europe/Stockholm",
    "iso:country":"SE",
    "wof:name":"Bureaborg",
    "wof:placetype":"locality"
},
  "geometry": {"coordinates":[17.73333,63.46666999999999],"type":"Point"}
}