{
  "type": "Feature",
  "properties": {
    "gn:admin1_code":"5.0",
    "gn:admin2_code":"980.0",
    "gn:asciiname":"Stora Solbjarge",
    "gn:country_code":"SE",
    "gn:dem":58,
    "gn:feature_class":"P",
    "gn:feature_code":"PPL",
    "gn:name":"Stora Solbj\u00e4rge",
    "gn:population":0,
    "gn:timezone":"Europe/Stockholm",
    "iso:country":"SE",
    "name:und_x_variant":[
        "Stora Solbj\u00e4rge",
        "Stora Solberga"
    ],
    "wof:name":"Stora Solbjarge",
    "wof:placetype":"locality"
},
  "geometry": {"coordinates":[18.26541,57.35791],"type":"Point"}
}