{
  "type": "Feature",
  "properties": {
    "gn:admin1_code":"24.0",
    "gn:admin2_code":"2281.0",
    "gn:admin3_code":"228111.0",
    "gn:admin4_code":"2473.0",
    "gn:asciiname":"Bjallsta",
    "gn:country_code":"SE",
    "gn:dem":106,
    "gn:feature_class":"P",
    "gn:feature_code":"PPL",
    "gn:name":"Bj\u00e4llsta",
    "gn:population":0,
    "gn:timezone":"Europe/Stockholm",
    "iso:country":"SE",
    "wof:name":"Bjallsta",
    "wof:placetype":"locality"
},
  "geometry": {"coordinates":[17.0805,62.58379],"type":"Point"}
}