{
  "type": "Feature",
  "properties": {
    "gn:admin1_code":"28.0",
    "gn:admin2_code":"1472.0",
    "gn:asciiname":"Sprottebo",
    "gn:cc2":"SE",
    "gn:country_code":"SE",
    "gn:dem":115,
    "gn:feature_class":"P",
    "gn:feature_code":"PPL",
    "gn:name":"Sprottebo",
    "gn:population":0,
    "gn:timezone":"Europe/Stockholm",
    "iso:country":"SE",
    "name:und_x_variant":[
        "Spr\u00e5ttebo",
        "Sprottebo"
    ],
    "wof:name":"Sprottebo",
    "wof:placetype":"locality"
},
  "geometry": {"coordinates":[14.15,58.41667],"type":"Point"}
}