{
  "type": "Feature",
  "properties": {
    "gn:admin1_code":"18.0",
    "gn:admin2_code":"488.0",
    "gn:asciiname":"Trosa",
    "gn:country_code":"SE",
    "gn:dem":8,
    "gn:feature_class":"P",
    "gn:feature_code":"PPLA2",
    "gn:name":"Trosa",
    "gn:population":5836,
    "gn:timezone":"Europe/Stockholm",
    "iso:country":"SE",
    "name:ara_x_preferred":[
        "\u062a\u0631\u0648\u0633\u0627"
    ],
    "name:bul_x_preferred":[
        "\u0422\u0440\u0443\u0441\u0430"
    ],
    "name:zho_x_preferred":[
        "\u7279\u9b6f\u85a9"
    ],
    "wof:name":"Trosa",
    "wof:placetype":"locality",
    "wof:population":5836
},
  "geometry": {"coordinates":[17.54812,58.89621],"type":"Point"}
}