{
  "type": "Feature",
  "properties": {
    "gn:admin1_code":"28.0",
    "gn:admin2_code":"1485.0",
    "gn:asciiname":"Logas",
    "gn:country_code":"SE",
    "gn:dem":50,
    "gn:feature_class":"P",
    "gn:feature_code":"PPL",
    "gn:name":"L\u00f6g\u00e5s",
    "gn:population":0,
    "gn:timezone":"Europe/Stockholm",
    "iso:country":"SE",
    "name:nor_x_preferred":[
        "L\u00f6g\u00e5s"
    ],
    "name:nor_x_variant":[
        "L\u00f8g\u00e5s"
    ],
    "wof:name":"Logas",
    "wof:placetype":"locality"
},
  "geometry": {"coordinates":[11.55,58.28333000000001],"type":"Point"}
}