{
  "type": "Feature",
  "properties": {
    "gn:admin1_code":"9.0",
    "gn:asciiname":"Mellanmalmo",
    "gn:country_code":"SE",
    "gn:dem":9,
    "gn:feature_class":"P",
    "gn:feature_code":"PPL",
    "gn:name":"Mellanmalm\u00f6",
    "gn:population":0,
    "gn:timezone":"Europe/Stockholm",
    "iso:country":"SE",
    "name:nor_x_preferred":[
        "Mellanmalm\u00f6"
    ],
    "name:nor_x_variant":[
        "Mellanmalm\u00f8"
    ],
    "wof:name":"Mellanmalmo",
    "wof:placetype":"locality"
},
  "geometry": {"coordinates":[16.7075,57.80416999999999],"type":"Point"}
}