{
  "type": "Feature",
  "properties": {
    "gn:admin1_code":"22.0",
    "gn:admin2_code":"1785.0",
    "gn:asciiname":"Kaled",
    "gn:cc2":"SE",
    "gn:country_code":"SE",
    "gn:dem":122,
    "gn:feature_class":"P",
    "gn:feature_code":"PPL",
    "gn:name":"K\u00e5led",
    "gn:population":0,
    "gn:timezone":"Europe/Stockholm",
    "iso:country":"SE",
    "name:und_x_variant":[
        "K\u00e5l\u00f6",
        "K\u00e5led"
    ],
    "wof:name":"Kaled",
    "wof:placetype":"locality"
},
  "geometry": {"coordinates":[12.58333,59.16667],"type":"Point"}
}