{
  "type": "Feature",
  "properties": {
    "gn:admin1_code":"12.0",
    "gn:admin2_code":"780.0",
    "gn:asciiname":"Gisshult",
    "gn:country_code":"SE",
    "gn:dem":249,
    "gn:feature_class":"P",
    "gn:feature_code":"PPL",
    "gn:name":"Gisshult",
    "gn:population":0,
    "gn:timezone":"Europe/Stockholm",
    "iso:country":"SE",
    "wof:name":"Gisshult",
    "wof:placetype":"locality"
},
  "geometry": {"coordinates":[14.85,57.13333000000001],"type":"Point"}
}