{
  "type": "Feature",
  "properties": {
    "gn:admin1_code":"7.0",
    "gn:admin2_code":"2380.0",
    "gn:asciiname":"Asan",
    "gn:country_code":"SE",
    "gn:dem":390,
    "gn:feature_class":"P",
    "gn:feature_code":"PPL",
    "gn:name":"\u00c5san",
    "gn:population":0,
    "gn:timezone":"Europe/Stockholm",
    "iso:country":"SE",
    "wof:name":"Asan",
    "wof:placetype":"locality"
},
  "geometry": {"coordinates":[14.68333,62.98333],"type":"Point"}
}