{
  "type": "Feature",
  "properties": {
    "gn:admin1_code":"16.0",
    "gn:admin2_code":"509.0",
    "gn:asciiname":"Lilla Aleryd",
    "gn:country_code":"SE",
    "gn:dem":197,
    "gn:feature_class":"P",
    "gn:feature_code":"PPL",
    "gn:name":"Lilla Aleryd",
    "gn:population":0,
    "gn:timezone":"Europe/Stockholm",
    "iso:country":"SE",
    "wof:name":"Lilla Aleryd",
    "wof:placetype":"locality"
},
  "geometry": {"coordinates":[14.68333,58.11666999999999],"type":"Point"}
}