{
  "type": "Feature",
  "properties": {
    "gn:admin1_code":"28.0",
    "gn:admin2_code":"1415.0",
    "gn:asciiname":"Grinstorp",
    "gn:cc2":"SE",
    "gn:country_code":"SE",
    "gn:dem":31,
    "gn:feature_class":"P",
    "gn:feature_code":"PPL",
    "gn:name":"Grinstorp",
    "gn:population":0,
    "gn:timezone":"Europe/Stockholm",
    "iso:country":"SE",
    "name:und_x_variant":[
        "Grindstorp",
        "Grinstorp"
    ],
    "wof:name":"Grinstorp",
    "wof:placetype":"locality"
},
  "geometry": {"coordinates":[11.88333,58.03333000000001],"type":"Point"}
}