{
  "type": "Feature",
  "properties": {
    "gn:admin1_code":"2.0",
    "gn:admin2_code":"1081.0",
    "gn:asciiname":"Hogalund",
    "gn:country_code":"SE",
    "gn:dem":132,
    "gn:feature_class":"P",
    "gn:feature_code":"PPL",
    "gn:name":"H\u00f6galund",
    "gn:population":0,
    "gn:timezone":"Europe/Stockholm",
    "iso:country":"SE",
    "name:nor_x_preferred":[
        "H\u00f6galund"
    ],
    "name:nor_x_variant":[
        "H\u00f8galund"
    ],
    "wof:name":"Hogalund",
    "wof:placetype":"locality"
},
  "geometry": {"coordinates":[15.35,56.46666999999999],"type":"Point"}
}