{
  "type": "Feature",
  "properties": {
    "gn:admin1_code":"27.0",
    "gn:admin2_code":"1257.0",
    "gn:asciiname":"Skanes Varsjo",
    "gn:country_code":"SE",
    "gn:dem":119,
    "gn:feature_class":"P",
    "gn:feature_code":"PPL",
    "gn:name":"Sk\u00e5nes V\u00e4rsj\u00f6",
    "gn:population":0,
    "gn:timezone":"Europe/Stockholm",
    "iso:country":"SE",
    "wof:name":"Skanes Varsjo",
    "wof:placetype":"locality"
},
  "geometry": {"coordinates":[13.43333,56.33333],"type":"Point"}
}