{
  "type": "Feature",
  "properties": {
    "gn:country":"SE",
    "gn:fcode":"PPL",
    "gn:population":847,
    "iso:country":"SE",
    "name:bul_x_preferred":[
        "\u0411\u0435\u0440\u0433\u0432\u0438\u043a"
    ],
    "name:ceb_x_preferred":[
        "Bergvik"
    ],
    "name:dan_x_preferred":[
        "Bergvik"
    ],
    "name:deu_x_preferred":[
        "Bergvik"
    ],
    "name:eng_x_preferred":[
        "Bergvik"
    ],
    "name:fra_x_preferred":[
        "Bergvik"
    ],
    "name:gle_x_preferred":[
        "Bergvik"
    ],
    "name:ita_x_preferred":[
        "Bergvik"
    ],
    "name:lld_x_preferred":[
        "Bergvik"
    ],
    "name:mkd_x_preferred":[
        "\u0411\u0435\u0440\u0433\u0432\u0438\u043a"
    ],
    "name:nan_x_preferred":[
        "Bergvik"
    ],
    "name:nld_x_preferred":[
        "Bergvik"
    ],
    "name:nno_x_preferred":[
        "Bergvik"
    ],
    "name:nob_x_preferred":[
        "Bergvik"
    ],
    "name:pol_x_preferred":[
        "Bergvik"
    ],
    "name:swe_x_preferred":[
        "Bergvik"
    ],
    "qs_pg:aaroncc":"SE",
    "qs_pg:gn_country":"SE",
    "qs_pg:gn_fcode":"PPL",
    "qs_pg:gn_pop":847,
    "qs_pg:name":"Bergvik",
    "qs_pg:name_adm0":"Sverige",
    "qs_pg:name_adm1":"G\u00e4vleborgs L\u00e4n",
    "qs_pg:photos":153,
    "qs_pg:photos_1k":31,
    "qs_pg:photos_9k":1,
    "qs_pg:photos_9r":4,
    "qs_pg:photos_all":153,
    "qs_pg:photos_sr":4,
    "qs_pg:pop_sr":2,
    "qs_pg:qs_pg_placetype":"locality",
    "qs_pg:qs_pg_placetype_gp":"Town",
    "qs_pg:woe_adm0":23424954,
    "woe:adm0_id":23424954,
    "woe:name_adm0":"Sverige",
    "woe:name_adm1":"G\u00e4vleborgs L\u00e4n",
    "woe:placetype":"Town",
    "wof:name":"Bergvik",
    "wof:placetype":"locality",
    "wof:population":719
},
  "geometry": {"coordinates":[16.85,61.26667],"type":"Point"}
}