{
  "type": "Feature",
  "properties": {
    "gn:admin1_code":"28.0",
    "gn:admin2_code":"1439.0",
    "gn:asciiname":"Barby",
    "gn:country_code":"SE",
    "gn:dem":108,
    "gn:feature_class":"P",
    "gn:feature_code":"PPL",
    "gn:name":"B\u00e4rby",
    "gn:population":0,
    "gn:timezone":"Europe/Stockholm",
    "iso:country":"SE",
    "name:ceb_x_preferred":[
        "Barby"
    ],
    "name:ces_x_preferred":[
        "Barby"
    ],
    "name:deu_x_preferred":[
        "Barby"
    ],
    "name:fra_x_preferred":[
        "Barby"
    ],
    "name:ita_x_preferred":[
        "Barby"
    ],
    "name:nds_x_preferred":[
        "Barby"
    ],
    "name:nld_x_preferred":[
        "Barby"
    ],
    "name:pol_x_preferred":[
        "Barby"
    ],
    "name:rus_x_preferred":[
        "\u0411\u0430\u0440\u0431\u0438"
    ],
    "name:scn_x_preferred":[
        "Barby"
    ],
    "name:slk_x_preferred":[
        "Barby"
    ],
    "name:spa_x_preferred":[
        "Barby"
    ],
    "name:swe_x_preferred":[
        "Barby"
    ],
    "name:ukr_x_preferred":[
        "\u0411\u0430\u0440\u0431\u0456"
    ],
    "wof:name":"Barby",
    "wof:placetype":"locality"
},
  "geometry": {"coordinates":[12.03306,58.66667],"type":"Point"}
}