{
  "type": "Feature",
  "properties": {
    "gn:admin1_code":"28.0",
    "gn:admin2_code":"1439.0",
    "gn:asciiname":"Barby",
    "gn:country_code":"SE",
    "gn:dem":108,
    "gn:feature_class":"P",
    "gn:feature_code":"PPL",
    "gn:name":"B\u00e4rby",
    "gn:population":0,
    "gn:timezone":"Europe/Stockholm",
    "iso:country":"SE",
    "wof:name":"Barby",
    "wof:placetype":"locality"
},
  "geometry": {"coordinates":[12.03306,58.66667],"type":"Point"}
}