{
  "type": "Feature",
  "properties": {
    "gn:gn_country":"SE",
    "gn:gn_fcode":"PPL",
    "gn:gn_pop":763,
    "gn:population":763,
    "iso:country":"SE",
    "name:dan_x_preferred":[
        "Sylta"
    ],
    "name:dut_x_preferred":[
        "Sylta"
    ],
    "name:eng_x_preferred":[
        "Sylta"
    ],
    "name:fre_x_preferred":[
        "Sylta"
    ],
    "name:ger_x_preferred":[
        "Sylta"
    ],
    "name:jav_x_preferred":[
        "Sylta"
    ],
    "name:may_x_preferred":[
        "Sylta"
    ],
    "name:nds_x_preferred":[
        "Sylta"
    ],
    "name:nno_x_preferred":[
        "Sylta"
    ],
    "name:nob_x_preferred":[
        "Sylta"
    ],
    "name:swe_x_preferred":[
        "Sylta"
    ],
    "qs_pg:aaroncc":"SE",
    "qs_pg:gn_country":"SE",
    "qs_pg:gn_fcode":"PPL",
    "qs_pg:gn_pop":763,
    "qs_pg:name":"Sylta",
    "qs_pg:photos_9r":0,
    "qs_pg:photos_sr":0,
    "qs_pg:pop_sr":2,
    "qs_pg:qs_pg_placetype":"locality",
    "wof:name":"Sylta",
    "wof:placetype":"locality",
    "wof:population":763
},
  "geometry": {"coordinates":[17.72,59.48],"type":"Point"}
}