{
  "type": "Feature",
  "properties": {
    "gn:admin1_code":"28.0",
    "gn:admin2_code":"1452.0",
    "gn:asciiname":"Grimsastorp",
    "gn:country_code":"SE",
    "gn:dem":262,
    "gn:feature_class":"P",
    "gn:feature_code":"PPL",
    "gn:name":"Grims\u00e5storp",
    "gn:population":0,
    "gn:timezone":"Europe/Stockholm",
    "iso:country":"SE",
    "wof:name":"Grimsastorp",
    "wof:placetype":"locality"
},
  "geometry": {"coordinates":[13.53333,57.46666999999999],"type":"Point"}
}