{
  "type": "Feature",
  "properties": {
    "gn:admin1_code":"26.0",
    "gn:admin2_code":"136.0",
    "gn:asciiname":"Bjoernoe",
    "gn:country_code":"SE",
    "gn:dem":13,
    "gn:feature_class":"P",
    "gn:feature_code":"PPL",
    "gn:name":"Bj\u00f6rn\u00f6",
    "gn:population":0,
    "gn:timezone":"Europe/Stockholm",
    "iso:country":"SE",
    "wof:name":"Bjoernoe",
    "wof:placetype":"locality"
},
  "geometry": {"coordinates":[18.29447,59.1106],"type":"Point"}
}