{
  "type": "Feature",
  "properties": {
    "gn:admin1_code":"28.0",
    "gn:admin2_code":"1482.0",
    "gn:asciiname":"Rod",
    "gn:country_code":"SE",
    "gn:dem":29,
    "gn:feature_class":"P",
    "gn:feature_code":"PPL",
    "gn:name":"R\u00f6d",
    "gn:population":0,
    "gn:timezone":"Europe/Stockholm",
    "iso:country":"SE",
    "name:bos_x_preferred":[
        "Rod"
    ],
    "name:bre_x_preferred":[
        "Rod"
    ],
    "name:bul_x_preferred":[
        "\u0420\u043e\u0434"
    ],
    "name:ceb_x_preferred":[
        "Rod"
    ],
    "name:ces_x_preferred":[
        "Rod"
    ],
    "name:dan_x_preferred":[
        "Rod"
    ],
    "name:deu_x_preferred":[
        "Rod"
    ],
    "name:fra_x_preferred":[
        "Rod"
    ],
    "name:hrv_x_preferred":[
        "Rod"
    ],
    "name:jpn_x_preferred":[
        "\u30ed\u30c3\u30c9"
    ],
    "name:mkd_x_preferred":[
        "\u0420\u043e\u0434"
    ],
    "name:nor_x_preferred":[
        "R\u00f6d"
    ],
    "name:nor_x_variant":[
        "R\u00f8d"
    ],
    "name:pol_x_preferred":[
        "Rod"
    ],
    "name:slk_x_preferred":[
        "Rod"
    ],
    "name:slv_x_preferred":[
        "Rod"
    ],
    "name:spa_x_preferred":[
        "Rod"
    ],
    "name:srp_x_preferred":[
        "\u0420\u043e\u0434"
    ],
    "name:vie_x_preferred":[
        "Rod"
    ],
    "wof:name":"Rod",
    "wof:placetype":"locality"
},
  "geometry": {"coordinates":[11.76667,57.83333],"type":"Point"}
}