{
  "type": "Feature",
  "properties": {
    "gn:admin1_code":"28.0",
    "gn:admin2_code":"1482.0",
    "gn:asciiname":"Rod",
    "gn:country_code":"SE",
    "gn:dem":29,
    "gn:feature_class":"P",
    "gn:feature_code":"PPL",
    "gn:name":"R\u00f6d",
    "gn:population":0,
    "gn:timezone":"Europe/Stockholm",
    "iso:country":"SE",
    "name:nor_x_preferred":[
        "R\u00f6d"
    ],
    "name:nor_x_variant":[
        "R\u00f8d"
    ],
    "name:und_x_variant":[
        "R\u00f6d"
    ],
    "wof:name":"Rod",
    "wof:placetype":"locality"
},
  "geometry": {"coordinates":[11.76667,57.83333],"type":"Point"}
}