{
  "type": "Feature",
  "properties": {
    "gn:admin1_code":"28.0",
    "gn:admin2_code":"1499.0",
    "gn:asciiname":"Marjarp",
    "gn:country_code":"SE",
    "gn:dem":212,
    "gn:feature_class":"P",
    "gn:feature_code":"PPL",
    "gn:name":"Marjarp",
    "gn:population":0,
    "gn:timezone":"Europe/Stockholm",
    "iso:country":"SE",
    "wof:name":"Marjarp",
    "wof:placetype":"locality"
},
  "geometry": {"coordinates":[13.56667,58.18333000000001],"type":"Point"}
}