{
  "type": "Feature",
  "properties": {
    "gn:admin1_code":"26.0",
    "gn:admin2_code":"191.0",
    "gn:asciiname":"Algesta",
    "gn:country_code":"SE",
    "gn:dem":26,
    "gn:feature_class":"P",
    "gn:feature_code":"PPL",
    "gn:name":"\u00c4lgesta",
    "gn:population":0,
    "gn:timezone":"Europe/Stockholm",
    "iso:country":"SE",
    "wof:name":"Algesta",
    "wof:placetype":"locality"
},
  "geometry": {"coordinates":[17.88332999999999,59.65],"type":"Point"}
}