{
  "type": "Feature",
  "properties": {
    "gn:admin1_code":"14.0",
    "gn:admin2_code":"2505.0",
    "gn:asciiname":"Klappen",
    "gn:country_code":"SE",
    "gn:dem":426,
    "gn:feature_class":"P",
    "gn:feature_code":"PPL",
    "gn:name":"Kl\u00e4ppen",
    "gn:population":0,
    "gn:timezone":"Europe/Stockholm",
    "iso:country":"SE",
    "name:swe_x_preferred":[
        "Kl\u00e4ppen"
    ],
    "wof:name":"Klappen",
    "wof:placetype":"locality"
},
  "geometry": {"coordinates":[18.8736,65.59669],"type":"Point"}
}