{
  "type": "Feature",
  "properties": {
    "gn:admin1_code":"23.0",
    "gn:admin2_code":"2481.0",
    "gn:asciiname":"Stenkulla",
    "gn:country_code":"SE",
    "gn:dem":310,
    "gn:feature_class":"P",
    "gn:feature_code":"PPL",
    "gn:name":"Stenkulla",
    "gn:population":0,
    "gn:timezone":"Europe/Stockholm",
    "iso:country":"SE",
    "wof:name":"Stenkulla",
    "wof:placetype":"locality"
},
  "geometry": {"coordinates":[18.35,64.71666999999999],"type":"Point"}
}