{
  "type": "Feature",
  "properties": {
    "gn:admin1_code":"27.0",
    "gn:admin2_code":"1265.0",
    "gn:asciiname":"Grimstofta",
    "gn:country_code":"SE",
    "gn:dem":49,
    "gn:feature_class":"P",
    "gn:feature_code":"PPL",
    "gn:name":"Grimstofta",
    "gn:population":0,
    "gn:timezone":"Europe/Stockholm",
    "iso:country":"SE",
    "wof:name":"Grimstofta",
    "wof:placetype":"locality"
},
  "geometry": {"coordinates":[13.71667,55.63333000000001],"type":"Point"}
}