{
  "type": "Feature",
  "properties": {
    "gn:admin1_code":"16.0",
    "gn:admin2_code":"586.0",
    "gn:admin3_code":"58603.0",
    "gn:admin4_code":"493.0",
    "gn:asciiname":"Skaenninge",
    "gn:country_code":"SE",
    "gn:dem":100,
    "gn:feature_class":"P",
    "gn:feature_code":"PPL",
    "gn:name":"Sk\u00e4nninge",
    "gn:population":3358,
    "gn:timezone":"Europe/Stockholm",
    "iso:country":"SE",
    "name:bul_x_preferred":[
        "\u0428\u0435\u043d\u0438\u043d\u0433\u0435"
    ],
    "name:ceb_x_preferred":[
        "Sk\u00e4nninge"
    ],
    "name:dan_x_preferred":[
        "Sk\u00e4nninge"
    ],
    "name:deu_x_preferred":[
        "Sk\u00e4nninge"
    ],
    "name:fas_x_preferred":[
        "\u06a9\u0648\u0627\u0646\u06cc\u0646\u06af\u0647"
    ],
    "name:fin_x_preferred":[
        "Sk\u00e4nninge"
    ],
    "name:fra_x_preferred":[
        "Sk\u00e4nninge"
    ],
    "name:hrv_x_preferred":[
        "Sk\u00e4nninge"
    ],
    "name:ita_x_preferred":[
        "Sk\u00e4nninge"
    ],
    "name:nld_x_preferred":[
        "Sk\u00e4nninge"
    ],
    "name:nno_x_preferred":[
        "Sk\u00e4nninge"
    ],
    "name:nor_x_preferred":[
        "Sk\u00e4nninge"
    ],
    "name:pol_x_preferred":[
        "Sk\u00e4nninge"
    ],
    "name:por_x_preferred":[
        "Sk\u00e4nninge"
    ],
    "name:ron_x_preferred":[
        "Sk\u00e4nninge"
    ],
    "name:swe_x_preferred":[
        "Sk\u00e4nninge"
    ],
    "name:tur_x_preferred":[
        "Sk\u00e4nninge"
    ],
    "name:vol_x_preferred":[
        "Sk\u00e4nninge"
    ],
    "wof:name":"Skaenninge",
    "wof:placetype":"locality",
    "wof:population":3358
},
  "geometry": {"coordinates":[15.08659,58.39427],"type":"Point"}
}