{
  "type": "Feature",
  "properties": {
    "gn:admin1_code":"22.0",
    "gn:admin2_code":"1782.0",
    "gn:asciiname":"Langskogen",
    "gn:country_code":"SE",
    "gn:dem":249,
    "gn:feature_class":"P",
    "gn:feature_code":"PPL",
    "gn:name":"L\u00e5ngskogen",
    "gn:population":0,
    "gn:timezone":"Europe/Stockholm",
    "iso:country":"SE",
    "wof:name":"Langskogen",
    "wof:placetype":"locality"
},
  "geometry": {"coordinates":[14.25,59.78333000000001],"type":"Point"}
}