{
  "type": "Feature",
  "properties": {
    "gn:admin1_code":"10.0",
    "gn:admin2_code":"2080.0",
    "gn:asciiname":"Bjorsberg",
    "gn:country_code":"SE",
    "gn:dem":255,
    "gn:feature_class":"P",
    "gn:feature_code":"PPL",
    "gn:name":"Bj\u00f6rsberg",
    "gn:population":0,
    "gn:timezone":"Europe/Stockholm",
    "iso:country":"SE",
    "name:nor_x_preferred":[
        "Bj\u00f6rsberg"
    ],
    "name:nor_x_variant":[
        "Bj\u00f8rsberg"
    ],
    "wof:name":"Bjorsberg",
    "wof:placetype":"locality"
},
  "geometry": {"coordinates":[15.46667,60.78333000000001],"type":"Point"}
}