{
  "type": "Feature",
  "properties": {
    "gn:admin1_code":"28.0",
    "gn:admin2_code":"1473.0",
    "gn:asciiname":"Bockersboda",
    "gn:country_code":"SE",
    "gn:dem":72,
    "gn:feature_class":"P",
    "gn:feature_code":"PPL",
    "gn:name":"B\u00f6ckersboda",
    "gn:population":0,
    "gn:timezone":"Europe/Stockholm",
    "iso:country":"SE",
    "name:nor_x_preferred":[
        "B\u00f6ckersboda"
    ],
    "name:nor_x_variant":[
        "B\u00f8ckersboda"
    ],
    "wof:name":"Bockersboda",
    "wof:placetype":"locality"
},
  "geometry": {"coordinates":[14.08333,58.78333000000001],"type":"Point"}
}