{
  "type": "Feature",
  "properties": {
    "gn:admin1_code":"16.0",
    "gn:admin2_code":"563.0",
    "gn:asciiname":"Frodetorp",
    "gn:country_code":"SE",
    "gn:dem":55,
    "gn:feature_class":"P",
    "gn:feature_code":"PPL",
    "gn:name":"Fr\u00f6detorp",
    "gn:population":0,
    "gn:timezone":"Europe/Stockholm",
    "iso:country":"SE",
    "name:nor_x_preferred":[
        "Fr\u00f6detorp"
    ],
    "name:nor_x_variant":[
        "Fr\u00f8detorp"
    ],
    "name:und_x_variant":[
        "Fr\u00f6detorp"
    ],
    "wof:name":"Frodetorp",
    "wof:placetype":"locality"
},
  "geometry": {"coordinates":[16.43306,58.35],"type":"Point"}
}